{
  "type": "Feature",
  "properties": {
    "sfomuseum:placetype": "tweet",
    "twitter:tweet": {
      "created": 1427221379,
      "created_at": "Tue Mar 24 18:22:59 +0000 2015",
      "display_text_range": [
        "0", 
        "124"
      ],
      "entities": {
        "urls": [
          {
            "display_url": "instagram.com/p/0ns-_qxkxO/",
            "expanded_url": "https://instagram.com/p/0ns-_qxkxO/",
            "indices": [
              "101", 
              "124"
            ],
            "url": "https://t.co/uEpCAD6Ptu"
          }
        ]
      },
      "favorite_count": "0",
      "favorited": false,
      "full_text": "Grab some exhibition brochures or a (free!) catalogue or two the next time you stop by the Aviation… https://t.co/uEpCAD6Ptu",
      "id_str": "580434650805473280",
      "lang": "en",
      "possibly_sensitive": false,
      "retweet_count": "0",
      "retweeted": false,
      "source": "\u003ca href=\"http://instagram.com\" rel=\"nofollow\"\u003eInstagram\u003c/a\u003e",
      "truncated": false
    },
    "wof:name": "Twitter message #580434650805473280",
    "wof:placetype": "custom"
  },
  "geometry": {"coordinates":[-122.386166,37.616356],"type":"Point"}
}
