{
  "type": "Feature",
  "properties": {
    "sfomuseum:placetype": "tweet",
    "twitter:tweet": {
      "created": 1331595001,
      "created_at": "Mon Mar 12 23:30:01 +0000 2012",
      "display_text_range": [
        "0", 
        "137"
      ],
      "entities": {
        "hashtags": [
          {
            "indices": [
              "81", 
              "85"
            ],
            "text": "SFO"
          }, 
          {
            "indices": [
              "108", 
              "115"
            ],
            "text": "travel"
          }, 
          {
            "indices": [
              "116", 
              "124"
            ],
            "text": "airport"
          }, 
          {
            "indices": [
              "125", 
              "129"
            ],
            "text": "art"
          }, 
          {
            "indices": [
              "130", 
              "137"
            ],
            "text": "sewing"
          }
        ],
        "urls": [
          {
            "display_url": "ow.ly/9AlRn",
            "expanded_url": "http://ow.ly/9AlRn",
            "indices": [
              "87", 
              "107"
            ],
            "url": "http://t.co/D6WHnVHX"
          }
        ],
        "user_mentions": [
          {
            "id_str": "45217275",
            "indices": [
              "40", 
              "55"
            ],
            "name": "Harriet Baskas",
            "screen_name": "StuckatAirport"
          }
        ]
      },
      "favorite_count": "0",
      "favorited": false,
      "full_text": "We're \"sew\" happy about the exhibit! MT @StuckatAirport: Things are \"sew-sew\" at #SFO. http://t.co/D6WHnVHX #travel #airport #art #sewing",
      "id_str": "179348550591856640",
      "lang": "en",
      "possibly_sensitive": false,
      "retweet_count": "0",
      "retweeted": false,
      "source": "\u003ca href=\"https://about.twitter.com/products/tweetdeck\" rel=\"nofollow\"\u003eTweetDeck\u003c/a\u003e",
      "truncated": false
    },
    "wof:name": "Twitter message #179348550591856640",
    "wof:placetype": "custom"
  },
  "geometry": {"coordinates":[-122.386166,37.616356],"type":"Point"}
}
