{
  "type": "Feature",
  "properties": {
    "sfomuseum:placetype": "tweet",
    "twitter:tweet": {
      "created": 1322594912,
      "created_at": "Tue Nov 29 19:28:32 +0000 2011",
      "display_text_range": [
        "0", 
        "86"
      ],
      "entities": {
        "user_mentions": [
          {
            "id_str": "7301572",
            "indices": [
              "0", 
              "12"
            ],
            "name": "Rob Pegoraro",
            "screen_name": "robpegoraro"
          }
        ]
      },
      "favorite_count": "0",
      "favorited": false,
      "full_text": "@robpegoraro Thanks for noticing! :) We'll have to see if we can get added to the map.",
      "id_str": "141599441571414018",
      "in_reply_to_screen_name": "robpegoraro",
      "in_reply_to_status_id": "141580958347440129",
      "in_reply_to_status_id_str": "141580958347440129",
      "in_reply_to_user_id": "7301572",
      "in_reply_to_user_id_str": "7301572",
      "lang": "en",
      "retweet_count": "0",
      "retweeted": false,
      "source": "\u003ca href=\"http://www.hootsuite.com\" rel=\"nofollow\"\u003eHootsuite\u003c/a\u003e",
      "truncated": false
    },
    "wof:name": "Twitter message #141599441571414018",
    "wof:placetype": "custom"
  },
  "geometry": {"coordinates":[-122.386166,37.616356],"type":"Point"}
}
