{
  "type": "Feature",
  "properties": {
    "date:cessation_lower": "2023-03-17",
    "date:cessation_upper": "2023-03-17",
    "date:inception_lower": "2023-03-17",
    "date:inception_upper": "2023-03-17",
    "sfomuseum:placetype": "tweet",
    "twitter:tweet": {
      "created": 1679011901,
      "created_at": "Fri Mar 17 00:11:41 +0000 2023",
      "display_text_range": [
        "0",
        "221"
      ],
      "edit_info": {
        "initial": {
          "editTweetIds": [
            "1636520645759737856"
          ],
          "editableUntil": "2023-03-17T00:41:41.000Z",
          "editsRemaining": "5",
          "isEditEligible": false
        }
      },
      "entities": {
      },
      "favorite_count": "0",
      "favorited": false,
      "full_text": "📸:\n1. photograph: Western Air Lines, Convair CV-240; 1948\nGift of Barbara A. Dawson\n2000.073.010\n\n2. photograph: San Francisco Airport, Western Air Lines Convair CV-240; c. 1947\nCollection of Justus H. Dobrin\n2013.132.001",
      "id_str": "1636520645759737856",
      "in_reply_to_screen_name": "SFOMuseum",
      "in_reply_to_status_id": "1636520644010741762",
      "in_reply_to_status_id_str": "1636520644010741762",
      "in_reply_to_user_id": "116329337",
      "in_reply_to_user_id_str": "116329337",
      "lang": "en",
      "retweet_count": "0",
      "retweeted": false,
      "source": "\u003ca href=\"https://mobile.twitter.com\" rel=\"nofollow\"\u003eTwitter Web App\u003c/a\u003e",
      "truncated": false
    },
    "wof:name": "📸:\n1. photograph: Western Air Lines, Convair CV-240; 1948\nGift of Barbara A. Dawson\n2000.073.010\n\n2. photograph: San Francisco Airport, Western Air Lines Convair CV-240; c. 1947\nCollection of Justus H. Dobrin\n2013.132.001",
    "wof:placetype": "custom",
    "wof:placetype_alt": [
      "tweet"
    ]
  },
  "geometry": {"coordinates":[-122.386166,37.616356],"type":"Point"}
}
