{
  "type": "Feature",
  "properties": {
    "sfomuseum:placetype": "tweet",
    "twitter:tweet": {
      "created": 1348604782,
      "created_at": "Tue Sep 25 20:26:22 +0000 2012",
      "display_text_range": [
        "0", 
        "140"
      ],
      "entities": {
        "urls": [
          {
            "display_url": "bit.ly/UExpiv",
            "expanded_url": "http://bit.ly/UExpiv",
            "indices": [
              "120", 
              "140"
            ],
            "url": "http://t.co/GwQarWIV"
          }
        ],
        "user_mentions": [
          {
            "id_str": "165127375",
            "indices": [
              "23", 
              "36"
            ],
            "name": "Rebecca J Kaye",
            "screen_name": "rebeccajkaye"
          }, 
          {
            "id_str": "116329337",
            "indices": [
              "83", 
              "93"
            ],
            "name": "SFO Museum",
            "screen_name": "SFOMuseum"
          }
        ]
      },
      "favorite_count": "0",
      "favorited": false,
      "full_text": "Thanks!! Great pix! MT @rebeccajkaye: Great exhibition on mountain bikes at SFO by @SFOMuseum - 'From Repack to Rwanda' http://t.co/GwQarWIV",
      "id_str": "250692745637810177",
      "lang": "en",
      "possibly_sensitive": false,
      "retweet_count": "0",
      "retweeted": false,
      "source": "\u003ca href=\"https://about.twitter.com/products/tweetdeck\" rel=\"nofollow\"\u003eTweetDeck\u003c/a\u003e",
      "truncated": false
    },
    "wof:name": "Twitter message #250692745637810177",
    "wof:placetype": "custom"
  },
  "geometry": {"coordinates":[-122.386166,37.616356],"type":"Point"}
}
