{
  "type": "Feature",
  "properties": {
    "date:cessation_lower": "2012-03-23",
    "date:cessation_upper": "2012-03-23",
    "date:inception_lower": "2012-03-23",
    "date:inception_upper": "2012-03-23",
    "iso:country": "US",
    "sfomuseum:placetype": "tweet",
    "twitter:tweet": {
      "created": 1332542201,
      "created_at": "Fri Mar 23 22:36:41 +0000 2012",
      "display_text_range": [
        "0",
        "112"
      ],
      "entities": {
        "urls": [
          {
            "display_url": "instagr.am/p/IiCodqRkx2/",
            "expanded_url": "http://instagr.am/p/IiCodqRkx2/",
            "indices": [
              "92",
              "112"
            ],
            "url": "http://t.co/eGYJAeZS"
          }
        ]
      },
      "favorite_count": "0",
      "favorited": false,
      "full_text": "Models from The Nut Tree Restaurant \u0026amp; Airfield Model Aircraft Collection, on view in T3 http://t.co/eGYJAeZS",
      "id_str": "183321394308845568",
      "lang": "en",
      "possibly_sensitive": false,
      "retweet_count": "0",
      "retweeted": false,
      "source": "\u003ca href=\"http://instagram.com\" rel=\"nofollow\"\u003eInstagram\u003c/a\u003e",
      "truncated": false
    },
    "wof:name": "Models from The Nut Tree Restaurant \u0026amp; Airfield Model Aircraft Collection, on view in T3 http://t.co/eGYJAeZS",
    "wof:placetype": "custom"
  },
  "geometry": {"coordinates":[-122.386166,37.616356],"type":"Point"}
}
