{
  "type": "Feature",
  "properties": {
    "date:cessation_lower":"2012-06-29",
    "date:cessation_upper":"2012-06-29",
    "date:inception_lower":"2012-06-29",
    "date:inception_upper":"2012-06-29",
    "iso:country":"US",
    "sfomuseum:placetype":"tweet",
    "twitter:tweet":{
        "created":1341001025,
        "created_at":"Fri Jun 29 20:17:05 +0000 2012",
        "display_text_range":[
            "0",
            "135"
        ],
        "entities":{
            "urls":[
                {
                    "display_url":"bit.ly/unL1YG",
                    "expanded_url":"http://bit.ly/unL1YG",
                    "indices":[
                        "115",
                        "135"
                    ],
                    "url":"http://t.co/gCAj6sdA"
                }
            ]
        },
        "favorite_count":"1",
        "favorited":false,
        "full_text":"Almost famous: check out the artwork from students of The Ruth Asawa San Francisco School of the Arts, in Term. 1! http://t.co/gCAj6sdA",
        "id_str":"218800276990210050",
        "lang":"en",
        "possibly_sensitive":false,
        "retweet_count":"3",
        "retweeted":false,
        "source":"<a href=\"https://about.twitter.com/products/tweetdeck\" rel=\"nofollow\">TweetDeck</a>",
        "truncated":false
    },
    "wof:name":"Almost famous: check out the artwork from students of The Ruth Asawa San Francisco School of the Arts, in Term. 1! http://t.co/gCAj6sdA",
    "wof:placetype":"custom"
},
  "geometry": {"coordinates":[-122.386166,37.616356],"type":"Point"}
}