{
  "type": "Feature",
  "properties": {
    "sfomuseum:placetype": "tweet",
    "twitter:tweet": {
      "created": 1343063650,
      "created_at": "Mon Jul 23 17:14:10 +0000 2012",
      "display_text_range": [
        "0", 
        "129"
      ],
      "entities": {
        "hashtags": [
          {
            "indices": [
              "120", 
              "129"
            ],
            "text": "aviation"
          }
        ],
        "user_mentions": [
          {
            "id_str": "2890961",
            "indices": [
              "23", 
              "31"
            ],
            "name": "Gizmodo",
            "screen_name": "Gizmodo"
          }
        ]
      },
      "favorite_count": "0",
      "favorited": false,
      "full_text": "Whoa! Just spotted via @gizmodo: a video from inside a 747's fuel tank. They're SO big that you could walk inside them! #aviation",
      "id_str": "227451550602252289",
      "lang": "en",
      "retweet_count": "0",
      "retweeted": false,
      "source": "\u003ca href=\"https://about.twitter.com/products/tweetdeck\" rel=\"nofollow\"\u003eTweetDeck\u003c/a\u003e",
      "truncated": false
    },
    "wof:name": "Twitter message #227451550602252289",
    "wof:placetype": "custom"
  },
  "geometry": {"coordinates":[-122.386166,37.616356],"type":"Point"}
}
