{
  "type": "Feature",
  "properties": {
    "date:cessation_lower":"2017-01-27",
    "date:cessation_upper":"2017-01-27",
    "date:inception_lower":"2017-01-27",
    "date:inception_upper":"2017-01-27",
    "iso:country":"US",
    "sfomuseum:placetype":"tweet",
    "twitter:tweet":{
        "created":1485554527,
        "created_at":"Fri Jan 27 22:02:07 +0000 2017",
        "display_text_range":[
            "0",
            "93"
        ],
        "entities":{
            "urls":[
                {
                    "display_url":"eventbrite.com/e/sfo-monthly-\u2026",
                    "expanded_url":"https://www.eventbrite.com/e/sfo-monthly-plane-spotter-meet-up-tickets-31492942238?utm-medium=discovery&utm-campaign=social&utm-content=attendeeshare&aff=estw&utm-source=tw&utm-term=listing",
                    "indices":[
                        "58",
                        "81"
                    ],
                    "url":"https://t.co/PZzyECz2Gy"
                }
            ],
            "user_mentions":[
                {
                    "id_str":"16408759",
                    "indices":[
                        "3",
                        "10"
                    ],
                    "name":"San Francisco International Airport (SFO) \u2708\ufe0f",
                    "screen_name":"flySFO"
                },
                {
                    "id_str":"5625972",
                    "indices":[
                        "82",
                        "93"
                    ],
                    "name":"Eventbrite",
                    "screen_name":"eventbrite"
                }
            ]
        },
        "favorite_count":"0",
        "favorited":false,
        "full_text":"RT @flySFO: Check out \"SFO Monthly Plane Spotter Meet-Up\" https://t.co/PZzyECz2Gy @Eventbrite",
        "id_str":"825101608883064833",
        "lang":"en",
        "possibly_sensitive":false,
        "retweet_count":"0",
        "retweeted":false,
        "source":"<a href=\"http://twitter.com\" rel=\"nofollow\">Twitter Web Client</a>",
        "truncated":false
    },
    "wof:name":"RT @flySFO: Check out \"SFO Monthly Plane Spotter Meet-Up\" https://t.co/PZzyECz2Gy @Eventbrite",
    "wof:placetype":"custom"
},
  "geometry": {"coordinates":[-122.386166,37.616356],"type":"Point"}
}