{
  "type": "Feature",
  "properties": {
    "sfomuseum:placetype": "tweet",
    "twitter:tweet": {
      "created": 1379630346,
      "created_at": "Thu Sep 19 22:39:06 +0000 2013",
      "display_text_range": [
        "0", 
        "121"
      ],
      "entities": {
        "urls": [
          {
            "display_url": "instagram.com/p/edXA35xk-v/",
            "expanded_url": "http://instagram.com/p/edXA35xk-v/",
            "indices": [
              "99", 
              "121"
            ],
            "url": "http://t.co/M2sMavhh7g"
          }
        ]
      },
      "favorite_count": "0",
      "favorited": false,
      "full_text": "In the running for 'most irreverent exhibit', our 1992 exhibit Souvenir Neckties featured painted… http://t.co/M2sMavhh7g",
      "id_str": "380823391273771008",
      "lang": "en",
      "possibly_sensitive": false,
      "retweet_count": "0",
      "retweeted": false,
      "source": "\u003ca href=\"http://instagram.com\" rel=\"nofollow\"\u003eInstagram\u003c/a\u003e",
      "truncated": false
    },
    "wof:name": "Twitter message #380823391273771008",
    "wof:placetype": "custom"
  },
  "geometry": {"coordinates":[-122.386166,37.616356],"type":"Point"}
}
