{
  "type": "Feature",
  "properties": {
    "sfomuseum:placetype": "tweet",
    "twitter:tweet": {
      "created": 1463007617,
      "created_at": "Wed May 11 23:00:17 +0000 2016",
      "display_text_range": [
        "0", 
        "140"
      ],
      "entities": {
        "hashtags": [
          {
            "indices": [
              "100", 
              "116"
            ],
            "text": "WomeninAviation"
          }
        ],
        "media": [
          {
            "display_url": "pic.twitter.com/wGOVigSnYq",
            "expanded_url": "https://twitter.com/SFOMuseum/status/730533012010635265/photo/1",
            "id_str": "730533010840367104",
            "indices": [
              "117", 
              "140"
            ],
            "media_url": "http://pbs.twimg.com/media/CiNf5x_WMAAGuUH.jpg",
            "media_url_https": "https://pbs.twimg.com/media/CiNf5x_WMAAGuUH.jpg",
            "sizes": {
              "large": {
                "h": "2000",
                "resize": "fit",
                "w": "1448"
              },
              "medium": {
                "h": "1200",
                "resize": "fit",
                "w": "869"
              },
              "small": {
                "h": "680",
                "resize": "fit",
                "w": "492"
              },
              "thumb": {
                "h": "150",
                "resize": "crop",
                "w": "150"
              }
            },
            "type": "photo",
            "url": "https://t.co/wGOVigSnYq"
          }
        ]
      },
      "extended_entities": {
        "media": [
          {
            "display_url": "pic.twitter.com/wGOVigSnYq",
            "expanded_url": "https://twitter.com/SFOMuseum/status/730533012010635265/photo/1",
            "id_str": "730533010840367104",
            "indices": [
              "117", 
              "140"
            ],
            "media_url": "http://pbs.twimg.com/media/CiNf5x_WMAAGuUH.jpg",
            "media_url_https": "https://pbs.twimg.com/media/CiNf5x_WMAAGuUH.jpg",
            "sizes": {
              "large": {
                "h": "2000",
                "resize": "fit",
                "w": "1448"
              },
              "medium": {
                "h": "1200",
                "resize": "fit",
                "w": "869"
              },
              "small": {
                "h": "680",
                "resize": "fit",
                "w": "492"
              },
              "thumb": {
                "h": "150",
                "resize": "crop",
                "w": "150"
              }
            },
            "type": "photo",
            "url": "https://t.co/wGOVigSnYq"
          }
        ]
      },
      "favorite_count": "1",
      "favorited": false,
      "full_text": "Anne \u0026amp; Charles Lindbergh made headlines around the world with their 1931 Arctic flight to Asia. #WomeninAviation https://t.co/wGOVigSnYq",
      "id_str": "730533012010635265",
      "lang": "en",
      "possibly_sensitive": false,
      "retweet_count": "1",
      "retweeted": false,
      "source": "\u003ca href=\"http://www.hootsuite.com\" rel=\"nofollow\"\u003eHootsuite\u003c/a\u003e",
      "truncated": false
    },
    "wof:name": "Twitter message #730533012010635265",
    "wof:placetype": "custom"
  },
  "geometry": {"coordinates":[-122.386166,37.616356],"type":"Point"}
}
