{
  "type": "Feature",
  "properties": {
    "sfomuseum:placetype": "tweet",
    "twitter:tweet": {
      "created": 1509307225,
      "created_at": "Sun Oct 29 20:00:25 +0000 2017",
      "display_text_range": [
        "0", 
        "164"
      ],
      "entities": {
        "media": [
          {
            "display_url": "pic.twitter.com/Cu3Jqjrnit",
            "expanded_url": "https://twitter.com/SFOMuseum/status/924727641571241985/photo/1",
            "id_str": "924727638752743436",
            "indices": [
              "141", 
              "164"
            ],
            "media_url": "http://pbs.twimg.com/media/DNVK41XX0Aw5h85.jpg",
            "media_url_https": "https://pbs.twimg.com/media/DNVK41XX0Aw5h85.jpg",
            "sizes": {
              "large": {
                "h": "1500",
                "resize": "fit",
                "w": "2000"
              },
              "medium": {
                "h": "900",
                "resize": "fit",
                "w": "1200"
              },
              "small": {
                "h": "510",
                "resize": "fit",
                "w": "680"
              },
              "thumb": {
                "h": "150",
                "resize": "crop",
                "w": "150"
              }
            },
            "type": "photo",
            "url": "https://t.co/Cu3Jqjrnit"
          }
        ],
        "urls": [
          {
            "display_url": "bit.ly/2y8BKpj",
            "expanded_url": "http://bit.ly/2y8BKpj",
            "indices": [
              "117", 
              "140"
            ],
            "url": "https://t.co/jRYSlV4zCq"
          }
        ]
      },
      "extended_entities": {
        "media": [
          {
            "display_url": "pic.twitter.com/Cu3Jqjrnit",
            "expanded_url": "https://twitter.com/SFOMuseum/status/924727641571241985/photo/1",
            "id_str": "924727638752743436",
            "indices": [
              "141", 
              "164"
            ],
            "media_url": "http://pbs.twimg.com/media/DNVK41XX0Aw5h85.jpg",
            "media_url_https": "https://pbs.twimg.com/media/DNVK41XX0Aw5h85.jpg",
            "sizes": {
              "large": {
                "h": "1500",
                "resize": "fit",
                "w": "2000"
              },
              "medium": {
                "h": "900",
                "resize": "fit",
                "w": "1200"
              },
              "small": {
                "h": "510",
                "resize": "fit",
                "w": "680"
              },
              "thumb": {
                "h": "150",
                "resize": "crop",
                "w": "150"
              }
            },
            "type": "photo",
            "url": "https://t.co/Cu3Jqjrnit"
          }
        ]
      },
      "favorite_count": "1",
      "favorited": false,
      "full_text": "See \"Yosemite in Focus\" by the participants of Parks in Focus on display, pre-security, in the arrivals level of T1. https://t.co/jRYSlV4zCq https://t.co/Cu3Jqjrnit",
      "id_str": "924727641571241985",
      "lang": "en",
      "possibly_sensitive": false,
      "retweet_count": "1",
      "retweeted": false,
      "source": "\u003ca href=\"http://www.hootsuite.com\" rel=\"nofollow\"\u003eHootsuite\u003c/a\u003e",
      "truncated": false
    },
    "wof:name": "Twitter message #924727641571241985",
    "wof:placetype": "custom"
  },
  "geometry": {"coordinates":[-122.386166,37.616356],"type":"Point"}
}
