{
  "type": "Feature",
  "properties": {
    "sfomuseum:placetype": "tweet",
    "twitter:tweet": {
      "created": 1351883067,
      "created_at": "Fri Nov 02 19:04:27 +0000 2012",
      "display_text_range": [
        "0", 
        "140"
      ],
      "entities": {
        "hashtags": [
          {
            "indices": [
              "73", 
              "77"
            ],
            "text": "SFO"
          }
        ],
        "urls": [
          {
            "display_url": "fb.me/22aIEmf7s",
            "expanded_url": "http://fb.me/22aIEmf7s",
            "indices": [
              "120", 
              "140"
            ],
            "url": "http://t.co/cvKlAk4D"
          }
        ],
        "user_mentions": [
          {
            "id_str": "18958334",
            "indices": [
              "3", 
              "8"
            ],
            "name": "SF Arts Commission",
            "screen_name": "SFAC"
          }, 
          {
            "id_str": "16536215",
            "indices": [
              "95", 
              "102"
            ],
            "name": "SFMOMA",
            "screen_name": "SFMOMA"
          }
        ]
      },
      "favorite_count": "0",
      "favorited": false,
      "full_text": "RT @SFAC: Civic Art Cllxn painting by Jay DeFeo originally purchased for #SFO hits big time in @SFMOMA retrospective... http://t.co/cvKlAk4D",
      "id_str": "264442866481369088",
      "lang": "en",
      "possibly_sensitive": false,
      "retweet_count": "0",
      "retweeted": false,
      "source": "\u003ca href=\"http://www.hootsuite.com\" rel=\"nofollow\"\u003eHootsuite\u003c/a\u003e",
      "truncated": false
    },
    "wof:name": "Twitter message #264442866481369088",
    "wof:placetype": "custom"
  },
  "geometry": {"coordinates":[-122.386166,37.616356],"type":"Point"}
}
