{
  "type": "Feature",
  "properties": {
    "date:cessation_lower": "2016-07-05",
    "date:cessation_upper": "2016-07-05",
    "date:inception_lower": "2016-07-05",
    "date:inception_upper": "2016-07-05",
    "iso:country": "US",
    "sfomuseum:placetype": "tweet",
    "twitter:tweet": {
      "created": 1467759211,
      "created_at": "Tue Jul 05 22:53:31 +0000 2016",
      "display_text_range": [
        "0",
        "140"
      ],
      "edit_info": {
        "initial": {
          "editTweetIds": [
            "750462642834268160"
          ],
          "editableUntil": "2016-07-05T23:53:31.630Z",
          "editsRemaining": "5",
          "isEditEligible": true
        }
      },
      "entities": {
        "user_mentions": [
          {
            "id_str": "396887508",
            "indices": [
              "3",
              "14"
            ],
            "name": "World Air Photo",
            "screen_name": "planenut27"
          }
        ]
      },
      "favorite_count": "0",
      "favorited": false,
      "full_text": "RT @planenut27: WOMAN IN AVIATION\nAmy Johnson, English aviatrix, the first female pilot to fly alone from Britain to Australia. https://t.c…",
      "id_str": "750462642834268160",
      "lang": "en",
      "retweet_count": "0",
      "retweeted": false,
      "source": "\u003ca href=\"http://www.hootsuite.com\" rel=\"nofollow\"\u003eHootsuite\u003c/a\u003e",
      "truncated": false
    },
    "twitter:user_mentions": [
      "planenut27"
    ],
    "wof:name": "RT @planenut27: WOMAN IN AVIATION\nAmy Johnson, English aviatrix, the first female pilot to fly alone from Britain to Australia. https://t.c…",
    "wof:placetype": "custom",
    "wof:placetype_alt": [
      "tweet"
    ]
  },
  "geometry": {"coordinates":[-122.386166,37.616356],"type":"Point"}
}
