{
  "type": "Feature",
  "properties": {
    "date:cessation_lower": "2013-06-19",
    "date:cessation_upper": "2013-06-19",
    "date:inception_lower": "2013-06-19",
    "date:inception_upper": "2013-06-19",
    "iso:country": "US",
    "sfomuseum:placetype": "tweet",
    "twitter:tweet": {
      "created": 1371668823,
      "created_at": "Wed Jun 19 19:07:03 +0000 2013",
      "display_text_range": [
        "0",
        "140"
      ],
      "entities": {
        "urls": [
          {
            "display_url": "ow.ly/mcbhp",
            "expanded_url": "http://ow.ly/mcbhp",
            "indices": [
              "118",
              "140"
            ],
            "url": "http://t.co/n8e3UgtoXN"
          }
        ]
      },
      "favorite_count": "0",
      "favorited": false,
      "full_text": "In T3, Russell Lee's searing photos for the Farm Security Administration, a New Deal program to assist rural farmers: http://t.co/n8e3UgtoXN",
      "id_str": "347430345467121664",
      "lang": "en",
      "possibly_sensitive": false,
      "retweet_count": "0",
      "retweeted": false,
      "source": "\u003ca href=\"http://www.hootsuite.com\" rel=\"nofollow\"\u003eHootsuite\u003c/a\u003e",
      "truncated": false
    },
    "wof:name": "In T3, Russell Lee's searing photos for the Farm Security Administration, a New Deal program to assist rural farmers: http://t.co/n8e3UgtoXN",
    "wof:placetype": "custom"
  },
  "geometry": {"coordinates":[-122.386166,37.616356],"type":"Point"}
}
