{
  "type": "Feature",
  "properties": {
    "sfomuseum:placetype": "tweet",
    "twitter:tweet": {
      "created": 1332433464,
      "created_at": "Thu Mar 22 16:24:24 +0000 2012",
      "display_text_range": [
        "0", 
        "142"
      ],
      "entities": {
        "urls": [
          {
            "display_url": "bit.ly/GFZnEI",
            "expanded_url": "http://bit.ly/GFZnEI",
            "indices": [
              "122", 
              "142"
            ],
            "url": "http://t.co/y8nEwfJq"
          }
        ]
      },
      "favorite_count": "0",
      "favorited": false,
      "full_text": "\"Toy\" sewing machines introduced girls to sewing \u0026amp; were also marketed as travel-size machines for their moms- clever! http://t.co/y8nEwfJq",
      "id_str": "182865320946577409",
      "lang": "en",
      "possibly_sensitive": false,
      "retweet_count": "0",
      "retweeted": false,
      "source": "\u003ca href=\"https://about.twitter.com/products/tweetdeck\" rel=\"nofollow\"\u003eTweetDeck\u003c/a\u003e",
      "truncated": false
    },
    "wof:name": "Twitter message #182865320946577409",
    "wof:placetype": "custom"
  },
  "geometry": {"coordinates":[-122.386166,37.616356],"type":"Point"}
}
