{
  "type": "Feature",
  "properties": {
    "date:cessation_lower": "2013-11-22",
    "date:cessation_upper": "2013-11-22",
    "date:inception_lower": "2013-11-22",
    "date:inception_upper": "2013-11-22",
    "iso:country": "US",
    "sfomuseum:placetype": "tweet",
    "twitter:hashtags": [
      "sfo"
    ],
    "twitter:tweet": {
      "created": 1385147650,
      "created_at": "Fri Nov 22 19:14:10 +0000 2013",
      "display_text_range": [
        "0",
        "84"
      ],
      "edit_info": {
        "initial": {
          "editTweetIds": [
            "403964641421692928"
          ],
          "editableUntil": "2013-11-22T20:14:10.472Z",
          "editsRemaining": "5",
          "isEditEligible": true
        }
      },
      "entities": {
        "hashtags": [
          {
            "indices": [
              "39",
              "43"
            ],
            "text": "sfo"
          }
        ],
        "urls": [
          {
            "display_url": "instagram.com/p/hALtMihbCK/",
            "expanded_url": "http://instagram.com/p/hALtMihbCK/",
            "indices": [
              "62",
              "84"
            ],
            "url": "http://t.co/PSLVeSdQCc"
          }
        ],
        "user_mentions": [
          {
            "id_str": "242794198",
            "indices": [
              "3",
              "14"
            ],
            "name": "Grecia Lima",
            "screen_name": "GreciaLima"
          }
        ]
      },
      "favorite_count": "0",
      "favorited": false,
      "full_text": "RT @GreciaLima: Really cool exhibit at #sfo of JAPANESE TOYS! http://t.co/PSLVeSdQCc",
      "id_str": "403964641421692928",
      "lang": "en",
      "possibly_sensitive": false,
      "retweet_count": "0",
      "retweeted": false,
      "source": "\u003ca href=\"http://www.hootsuite.com\" rel=\"nofollow\"\u003eHootsuite\u003c/a\u003e",
      "truncated": false
    },
    "twitter:user_mentions": [
      "GreciaLima"
    ],
    "wof:name": "RT @GreciaLima: Really cool exhibit at #sfo of JAPANESE TOYS! http://t.co/PSLVeSdQCc",
    "wof:placetype": "custom"
  },
  "geometry": {"coordinates":[-122.386166,37.616356],"type":"Point"}
}
