{
  "type": "Feature",
  "properties": {
    "date:cessation_lower": "2011-11-04",
    "date:cessation_upper": "2011-11-04",
    "date:inception_lower": "2011-11-04",
    "date:inception_upper": "2011-11-04",
    "iso:country": "US",
    "sfomuseum:placetype": "tweet",
    "twitter:tweet": {
      "created": 1320419625,
      "created_at": "Fri Nov 04 15:13:45 +0000 2011",
      "display_text_range": [
        "0",
        "121"
      ],
      "edit_info": {
        "initial": {
          "editTweetIds": [
            "132475626941722625"
          ],
          "editableUntil": "2011-11-04T15:43:45.398Z",
          "editsRemaining": "5",
          "isEditEligible": true
        }
      },
      "entities": {
        "urls": [
          {
            "display_url": "bit.ly/w08kS3",
            "expanded_url": "http://bit.ly/w08kS3",
            "indices": [
              "101",
              "121"
            ],
            "url": "http://t.co/XIClpDDv"
          }
        ]
      },
      "favorite_count": "0",
      "favorited": false,
      "full_text": "It's official! Moto Bellissima: Italian Motorcycles from the 1950s and 1960s is now on view at SFO.  http://t.co/XIClpDDv",
      "id_str": "132475626941722625",
      "lang": "en",
      "possibly_sensitive": false,
      "retweet_count": "1",
      "retweeted": false,
      "source": "\u003ca href=\"https://about.twitter.com/products/tweetdeck\" rel=\"nofollow\"\u003eTweetDeck\u003c/a\u003e",
      "truncated": false
    },
    "wof:name": "It's official! Moto Bellissima: Italian Motorcycles from the 1950s and 1960s is now on view at SFO.  http://t.co/XIClpDDv",
    "wof:placetype": "custom"
  },
  "geometry": {"coordinates":[-122.386166,37.616356],"type":"Point"}
}
