{
  "type": "Feature",
  "properties": {
    "date:cessation_lower": "2014-10-24",
    "date:cessation_upper": "2014-10-24",
    "date:inception_lower": "2014-10-24",
    "date:inception_upper": "2014-10-24",
    "iso:country": "US",
    "sfomuseum:placetype": "tweet",
    "twitter:hashtags": [
      "StudioGlass"
    ],
    "twitter:tweet": {
      "created": 1414173434,
      "created_at": "Fri Oct 24 17:57:14 +0000 2014",
      "display_text_range": [
        "0",
        "134"
      ],
      "edit_info": {
        "initial": {
          "editTweetIds": [
            "525707601632563202"
          ],
          "editableUntil": "2014-10-24T18:57:14.061Z",
          "editsRemaining": "5",
          "isEditEligible": true
        }
      },
      "entities": {
        "hashtags": [
          {
            "indices": [
              "122",
              "134"
            ],
            "text": "StudioGlass"
          }
        ],
        "urls": [
          {
            "display_url": "ow.ly/DivVM",
            "expanded_url": "http://ow.ly/DivVM",
            "indices": [
              "85",
              "107"
            ],
            "url": "http://t.co/sGraMFCSTB"
          }
        ]
      },
      "favorite_count": "1",
      "favorited": false,
      "full_text": "New exhibit alert! Studio Glass examines four pioneering artists with Bay Area ties: http://t.co/sGraMFCSTB T2, post-TSA. #StudioGlass",
      "id_str": "525707601632563202",
      "lang": "en",
      "possibly_sensitive": false,
      "retweet_count": "2",
      "retweeted": false,
      "source": "\u003ca href=\"http://www.hootsuite.com\" rel=\"nofollow\"\u003eHootsuite\u003c/a\u003e",
      "truncated": false
    },
    "wof:name": "New exhibit alert! Studio Glass examines four pioneering artists with Bay Area ties: http://t.co/sGraMFCSTB T2, post-TSA. #StudioGlass",
    "wof:placetype": "custom"
  },
  "geometry": {"coordinates":[-122.386166,37.616356],"type":"Point"}
}
