{
  "type": "Feature",
  "properties": {
    "sfomuseum:placetype": "tweet",
    "twitter:tweet": {
      "created": 1414173434,
      "created_at": "Fri Oct 24 17:57:14 +0000 2014",
      "display_text_range": [
        "0", 
        "134"
      ],
      "entities": {
        "hashtags": [
          {
            "indices": [
              "122", 
              "134"
            ],
            "text": "StudioGlass"
          }
        ],
        "urls": [
          {
            "display_url": "ow.ly/DivVM",
            "expanded_url": "http://ow.ly/DivVM",
            "indices": [
              "85", 
              "107"
            ],
            "url": "http://t.co/sGraMFCSTB"
          }
        ]
      },
      "favorite_count": "1",
      "favorited": false,
      "full_text": "New exhibit alert! Studio Glass examines four pioneering artists with Bay Area ties: http://t.co/sGraMFCSTB T2, post-TSA. #StudioGlass",
      "id_str": "525707601632563202",
      "lang": "en",
      "possibly_sensitive": false,
      "retweet_count": "2",
      "retweeted": false,
      "source": "\u003ca href=\"http://www.hootsuite.com\" rel=\"nofollow\"\u003eHootsuite\u003c/a\u003e",
      "truncated": false
    },
    "wof:name": "Twitter message #525707601632563202",
    "wof:placetype": "custom"
  },
  "geometry": {"coordinates":[-122.386166,37.616356],"type":"Point"}
}
