{
  "type": "Feature",
  "properties": {
    "sfomuseum:placetype": "tweet",
    "twitter:tweet": {
      "created": 1322523909,
      "created_at": "Mon Nov 28 23:45:09 +0000 2011",
      "display_text_range": [
        "0", 
        "96"
      ],
      "entities": {
        "urls": [
          {
            "display_url": "ow.ly/1BaKSP",
            "expanded_url": "http://ow.ly/1BaKSP",
            "indices": [
              "76", 
              "96"
            ],
            "url": "http://t.co/uE66K7BA"
          }
        ],
        "user_mentions": [
          {
            "id_str": "60981874",
            "indices": [
              "0", 
              "12"
            ],
            "name": "Jim Malcolm",
            "screen_name": "jim_malcolm"
          }
        ]
      },
      "favorite_count": "0",
      "favorited": false,
      "full_text": "@jim_malcolm Great find! You can learn more about Bob Zoell's artwork here: http://t.co/uE66K7BA",
      "id_str": "141301633006059520",
      "in_reply_to_screen_name": "jim_malcolm",
      "in_reply_to_status_id": "140506159395254272",
      "in_reply_to_status_id_str": "140506159395254272",
      "in_reply_to_user_id": "60981874",
      "in_reply_to_user_id_str": "60981874",
      "lang": "en",
      "possibly_sensitive": false,
      "retweet_count": "0",
      "retweeted": false,
      "source": "\u003ca href=\"http://www.hootsuite.com\" rel=\"nofollow\"\u003eHootsuite\u003c/a\u003e",
      "truncated": false
    },
    "wof:name": "Twitter message #141301633006059520",
    "wof:placetype": "custom"
  },
  "geometry": {"coordinates":[-122.386166,37.616356],"type":"Point"}
}
