{
  "type": "Feature",
  "properties": {
    "sfomuseum:placetype": "tweet",
    "twitter:tweet": {
      "created": 1535763275,
      "created_at": "Sat Sep 01 00:54:35 +0000 2018",
      "display_text_range": [
        "0", 
        "307"
      ],
      "entities": {
        "hashtags": [
          {
            "indices": [
              "273", 
              "283"
            ],
            "text": "SFHistory"
          }
        ],
        "media": [
          {
            "display_url": "pic.twitter.com/ObqewPX38D",
            "expanded_url": "https://twitter.com/SFOMuseum/status/1035692360464646145/photo/1",
            "id_str": "1035691178044284929",
            "indices": [
              "284", 
              "307"
            ],
            "media_url": "http://pbs.twimg.com/media/Dl-Do5xV4AE8qfO.jpg",
            "media_url_https": "https://pbs.twimg.com/media/Dl-Do5xV4AE8qfO.jpg",
            "sizes": {
              "large": {
                "h": "1542",
                "resize": "fit",
                "w": "2000"
              },
              "medium": {
                "h": "925",
                "resize": "fit",
                "w": "1200"
              },
              "small": {
                "h": "524",
                "resize": "fit",
                "w": "680"
              },
              "thumb": {
                "h": "150",
                "resize": "crop",
                "w": "150"
              }
            },
            "type": "photo",
            "url": "https://t.co/ObqewPX38D"
          }
        ]
      },
      "extended_entities": {
        "media": [
          {
            "display_url": "pic.twitter.com/ObqewPX38D",
            "expanded_url": "https://twitter.com/SFOMuseum/status/1035692360464646145/photo/1",
            "id_str": "1035691178044284929",
            "indices": [
              "284", 
              "307"
            ],
            "media_url": "http://pbs.twimg.com/media/Dl-Do5xV4AE8qfO.jpg",
            "media_url_https": "https://pbs.twimg.com/media/Dl-Do5xV4AE8qfO.jpg",
            "sizes": {
              "large": {
                "h": "1542",
                "resize": "fit",
                "w": "2000"
              },
              "medium": {
                "h": "925",
                "resize": "fit",
                "w": "1200"
              },
              "small": {
                "h": "524",
                "resize": "fit",
                "w": "680"
              },
              "thumb": {
                "h": "150",
                "resize": "crop",
                "w": "150"
              }
            },
            "type": "photo",
            "url": "https://t.co/ObqewPX38D"
          }
        ]
      },
      "favorite_count": "10",
      "favorited": false,
      "full_text": "Built for the Panama–Pacific International Exposition in 1915, the Palace of Fine Arts is a San Francisco landmark. This photo was taken about 5 years after the Expo \u0026amp; the remnants of the fair buildings are still visible. Have you ever been to the Palace of Fine Arts? #SFHistory https://t.co/ObqewPX38D",
      "id_str": "1035692360464646145",
      "lang": "en",
      "possibly_sensitive": false,
      "retweet_count": "3",
      "retweeted": false,
      "source": "\u003ca href=\"http://twitter.com\" rel=\"nofollow\"\u003eTwitter Web Client\u003c/a\u003e",
      "truncated": false
    },
    "wof:name": "Twitter message #1035692360464646145",
    "wof:placetype": "custom"
  },
  "geometry": {"coordinates":[-122.386166,37.616356],"type":"Point"}
}
