{
  "type": "Feature",
  "properties": {
    "date:cessation_lower": "2019-10-01",
    "date:cessation_upper": "2019-10-01",
    "date:inception_lower": "2019-10-01",
    "date:inception_upper": "2019-10-01",
    "iso:country": "US",
    "sfomuseum:placetype": "tweet",
    "twitter:tweet": {
      "created": 1569968805,
      "created_at": "Tue Oct 01 22:26:45 +0000 2019",
      "display_text_range": [
        "0",
        "148"
      ],
      "edit_info": {
        "initial": {
          "editTweetIds": [
            "1179160752646541312"
          ],
          "editableUntil": "2019-10-01T22:56:45.835Z",
          "editsRemaining": "5",
          "isEditEligible": true
        }
      },
      "entities": {
        "user_mentions": [
          {
            "id_str": "1034573384112168960",
            "indices": [
              "0",
              "16"
            ],
            "name": "Saz",
            "screen_name": "sarahcollins747"
          }
        ]
      },
      "favorite_count": "2",
      "favorited": false,
      "full_text": "@sarahcollins747 Yes, we ship internationally! Please email us at curator@flysfo.com with your mailing address and we can send you a poster. Thanks!",
      "id_str": "1179160752646541312",
      "in_reply_to_screen_name": "sarahcollins747",
      "in_reply_to_status_id": "1179120512804327424",
      "in_reply_to_status_id_str": "1179120512804327424",
      "in_reply_to_user_id": "1034573384112168960",
      "in_reply_to_user_id_str": "1034573384112168960",
      "lang": "en",
      "retweet_count": "0",
      "retweeted": false,
      "source": "\u003ca href=\"https://mobile.twitter.com\" rel=\"nofollow\"\u003eTwitter Web App\u003c/a\u003e",
      "truncated": false
    },
    "wof:name": "@sarahcollins747 Yes, we ship internationally! Please email us at curator@flysfo.com with your mailing address and we can send you a poster. Thanks!",
    "wof:placetype": "custom"
  },
  "geometry": {"coordinates":[-122.386166,37.616356],"type":"Point"}
}
