{
  "type": "Feature",
  "properties": {
    "sfomuseum:placetype": "tweet",
    "twitter:tweet": {
      "created": 1524595807,
      "created_at": "Tue Apr 24 18:50:07 +0000 2018",
      "display_text_range": [
        "0", 
        "166"
      ],
      "entities": {
        "hashtags": [
          {
            "indices": [
              "135", 
              "142"
            ],
            "text": "avgeek"
          }
        ],
        "media": [
          {
            "display_url": "pic.twitter.com/PvZonZUdAL",
            "expanded_url": "https://twitter.com/SFOMuseum/status/988852602732457984/photo/1",
            "id_str": "988852599288975360",
            "indices": [
              "143", 
              "166"
            ],
            "media_url": "http://pbs.twimg.com/media/DbkcMyvXUAA-qIf.jpg",
            "media_url_https": "https://pbs.twimg.com/media/DbkcMyvXUAA-qIf.jpg",
            "sizes": {
              "large": {
                "h": "1912",
                "resize": "fit",
                "w": "2000"
              },
              "medium": {
                "h": "1147",
                "resize": "fit",
                "w": "1200"
              },
              "small": {
                "h": "650",
                "resize": "fit",
                "w": "680"
              },
              "thumb": {
                "h": "150",
                "resize": "crop",
                "w": "150"
              }
            },
            "type": "photo",
            "url": "https://t.co/PvZonZUdAL"
          }
        ]
      },
      "extended_entities": {
        "media": [
          {
            "display_url": "pic.twitter.com/PvZonZUdAL",
            "expanded_url": "https://twitter.com/SFOMuseum/status/988852602732457984/photo/1",
            "id_str": "988852599288975360",
            "indices": [
              "143", 
              "166"
            ],
            "media_url": "http://pbs.twimg.com/media/DbkcMyvXUAA-qIf.jpg",
            "media_url_https": "https://pbs.twimg.com/media/DbkcMyvXUAA-qIf.jpg",
            "sizes": {
              "large": {
                "h": "1912",
                "resize": "fit",
                "w": "2000"
              },
              "medium": {
                "h": "1147",
                "resize": "fit",
                "w": "1200"
              },
              "small": {
                "h": "650",
                "resize": "fit",
                "w": "680"
              },
              "thumb": {
                "h": "150",
                "resize": "crop",
                "w": "150"
              }
            },
            "type": "photo",
            "url": "https://t.co/PvZonZUdAL"
          }
        ]
      },
      "favorite_count": "9",
      "favorited": false,
      "full_text": "The last branded Virgin America flights are scheduled to depart from SFO this evening. What are your favorite Virgin America memories? #avgeek https://t.co/PvZonZUdAL",
      "id_str": "988852602732457984",
      "lang": "en",
      "possibly_sensitive": false,
      "retweet_count": "1",
      "retweeted": false,
      "source": "\u003ca href=\"http://www.hootsuite.com\" rel=\"nofollow\"\u003eHootsuite\u003c/a\u003e",
      "truncated": false
    },
    "wof:name": "Twitter message #988852602732457984",
    "wof:placetype": "custom"
  },
  "geometry": {"coordinates":[-122.386166,37.616356],"type":"Point"}
}
