{
  "type": "Feature",
  "properties": {
    "sfomuseum:placetype": "tweet",
    "twitter:tweet": {
      "created": 1559323231,
      "created_at": "Fri May 31 17:20:31 +0000 2019",
      "display_text_range": [
        "0", 
        "140"
      ],
      "entities": {
        "user_mentions": [
          {
            "id_str": "990953574011203585",
            "indices": [
              "3", 
              "17"
            ],
            "name": "Trans World Airlines",
            "screen_name": "FlyTransWorld"
          }
        ]
      },
      "favorite_count": "0",
      "favorited": false,
      "full_text": "RT @FlyTransWorld: 76 years, thousands and thousands of miles and smiles. Thank you to our wonderful flight attendants who made it all poss…",
      "id_str": "1134509975911378944",
      "lang": "en",
      "retweet_count": "0",
      "retweeted": false,
      "source": "\u003ca href=\"http://twitter.com\" rel=\"nofollow\"\u003eTwitter Web Client\u003c/a\u003e",
      "truncated": false
    },
    "wof:name": "Twitter message #1134509975911378944",
    "wof:placetype": "custom"
  },
  "geometry": {"coordinates":[-122.386166,37.616356],"type":"Point"}
}
