{
  "type": "Feature",
  "properties": {
    "sfomuseum:placetype": "tweet",
    "twitter:tweet": {
      "created": 1437158363,
      "created_at": "Fri Jul 17 18:39:23 +0000 2015",
      "display_text_range": [
        "0", 
        "128"
      ],
      "entities": {
        "hashtags": [
          {
            "indices": [
              "77", 
              "91"
            ],
            "text": "kirksmonsters"
          }
        ],
        "urls": [
          {
            "display_url": "instagram.com/p/5LIxLLopN5/",
            "expanded_url": "https://instagram.com/p/5LIxLLopN5/",
            "indices": [
              "105", 
              "128"
            ],
            "url": "https://t.co/DYjcskBHfD"
          }
        ],
        "user_mentions": [
          {
            "id_str": "7816062",
            "indices": [
              "3", 
              "11"
            ],
            "name": "JD KCET ~clean mix~",
            "screen_name": "jai_dit"
          }
        ]
      },
      "favorite_count": "0",
      "favorited": false,
      "full_text": "RT @jai_dit: Dracula and the Bride of Frankenstein: accomplished guitarists. #kirksmonsters @ SFO Museum https://t.co/DYjcskBHfD",
      "id_str": "622113384868130816",
      "lang": "en",
      "possibly_sensitive": false,
      "retweet_count": "0",
      "retweeted": false,
      "source": "\u003ca href=\"http://twitter.com\" rel=\"nofollow\"\u003eTwitter Web Client\u003c/a\u003e",
      "truncated": false
    },
    "wof:name": "Twitter message #622113384868130816",
    "wof:placetype": "custom"
  },
  "geometry": {"coordinates":[-122.386166,37.616356],"type":"Point"}
}
