{
  "type": "Feature",
  "properties": {
    "date:cessation_lower": "2021-03-03",
    "date:cessation_upper": "2021-03-03",
    "date:inception_lower": "2021-03-03",
    "date:inception_upper": "2021-03-03",
    "sfomuseum:placetype": "tweet",
    "twitter:tweet": {
      "created": 1614802232,
      "created_at": "Wed Mar 03 20:10:32 +0000 2021",
      "display_text_range": [
        "0",
        "183"
      ],
      "edit_info": {
        "initial": {
          "editTweetIds": [
            "1367205773533573122"
          ],
          "editableUntil": "2021-03-03T20:40:32.522Z",
          "editsRemaining": "5",
          "isEditEligible": true
        }
      },
      "entities": {
        "urls": [
          {
            "display_url": "sfomuseum.org/governance",
            "expanded_url": "https://www.sfomuseum.org/governance",
            "indices": [
              "160",
              "183"
            ],
            "url": "https://t.co/Uw1aacfmBJ"
          }
        ],
        "user_mentions": [
          {
            "id_str": "377186587",
            "indices": [
              "0",
              "15"
            ],
            "name": "Devin McCutchen",
            "screen_name": "DevinMcCutchen"
          }
        ]
      },
      "favorite_count": "1",
      "favorited": false,
      "full_text": "@DevinMcCutchen But if you’re interested in how other items would potentially be deaccessioned from our collection, our Collection Management Policy is online: https://t.co/Uw1aacfmBJ",
      "id_str": "1367205773533573122",
      "in_reply_to_screen_name": "SFOMuseum",
      "in_reply_to_status_id": "1367205536781889538",
      "in_reply_to_status_id_str": "1367205536781889538",
      "in_reply_to_user_id": "116329337",
      "in_reply_to_user_id_str": "116329337",
      "lang": "en",
      "possibly_sensitive": false,
      "retweet_count": "0",
      "retweeted": false,
      "source": "\u003ca href=\"https://mobile.twitter.com\" rel=\"nofollow\"\u003eTwitter Web App\u003c/a\u003e",
      "truncated": false
    },
    "wof:name": "@DevinMcCutchen But if you’re interested in how other items would potentially be deaccessioned from our collection, our Collection Management Policy is online: https://t.co/Uw1aacfmBJ",
    "wof:placetype": "custom"
  },
  "geometry": {"coordinates":[-122.386166,37.616356],"type":"Point"}
}
