{
  "type": "Feature",
  "properties": {
    "sfomuseum:placetype": "tweet",
    "twitter:tweet": {
      "created": 1347475827,
      "created_at": "Wed Sep 12 18:50:27 +0000 2012",
      "display_text_range": [
        "0", 
        "129"
      ],
      "entities": {
        "urls": [
          {
            "display_url": "bit.ly/ognemN",
            "expanded_url": "http://bit.ly/ognemN",
            "indices": [
              "109", 
              "129"
            ],
            "url": "http://t.co/Q4k0UVWE"
          }
        ],
        "user_mentions": [
          {
            "id_str": "16408759",
            "indices": [
              "17", 
              "24"
            ],
            "name": "San Francisco International Airport (SFO) ✈️",
            "screen_name": "flySFO"
          }
        ]
      },
      "favorite_count": "0",
      "favorited": false,
      "full_text": "Wherever you are @flySFO, there is always art! Take a look at our map to find out what's around that corner: http://t.co/Q4k0UVWE",
      "id_str": "245957562950889473",
      "lang": "en",
      "possibly_sensitive": false,
      "retweet_count": "1",
      "retweeted": false,
      "source": "\u003ca href=\"https://about.twitter.com/products/tweetdeck\" rel=\"nofollow\"\u003eTweetDeck\u003c/a\u003e",
      "truncated": false
    },
    "wof:name": "Twitter message #245957562950889473",
    "wof:placetype": "custom"
  },
  "geometry": {"coordinates":[-122.386166,37.616356],"type":"Point"}
}
