{
  "type": "Feature",
  "properties": {
    "sfomuseum:placetype": "tweet",
    "twitter:tweet": {
      "created": 1323719102,
      "created_at": "Mon Dec 12 19:45:02 +0000 2011",
      "display_text_range": [
        "0", 
        "112"
      ],
      "entities": {
        "urls": [
          {
            "display_url": "bit.ly/vEIztP",
            "expanded_url": "http://bit.ly/vEIztP",
            "indices": [
              "92", 
              "112"
            ],
            "url": "http://t.co/Si1CRF8B"
          }
        ],
        "user_mentions": [
          {
            "id_str": "284134803",
            "indices": [
              "21", 
              "36"
            ],
            "name": "Brian Thompson",
            "screen_name": "AskACopywriter"
          }
        ]
      },
      "favorite_count": "0",
      "favorited": false,
      "full_text": "Great blog post from @AskACopywriter on our TV exhibit, esp featuring early advertisements: http://t.co/Si1CRF8B",
      "id_str": "146314637892272128",
      "lang": "en",
      "possibly_sensitive": false,
      "retweet_count": "1",
      "retweeted": false,
      "source": "\u003ca href=\"https://about.twitter.com/products/tweetdeck\" rel=\"nofollow\"\u003eTweetDeck\u003c/a\u003e",
      "truncated": false
    },
    "wof:name": "Twitter message #146314637892272128",
    "wof:placetype": "custom"
  },
  "geometry": {"coordinates":[-122.386166,37.616356],"type":"Point"}
}
