{
  "type": "Feature",
  "properties": {
    "sfomuseum:placetype": "tweet",
    "twitter:tweet": {
      "created": 1326483967,
      "created_at": "Fri Jan 13 19:46:07 +0000 2012",
      "display_text_range": [
        "0", 
        "103"
      ],
      "entities": {
        "urls": [
          {
            "display_url": "ow.ly/i/pJj5",
            "expanded_url": "http://ow.ly/i/pJj5",
            "indices": [
              "83", 
              "103"
            ],
            "url": "http://t.co/PrhHnYRP"
          }
        ]
      },
      "favorite_count": "0",
      "favorited": false,
      "full_text": "One of the first \"laptops\": Sony's 1964 Micro TV, advertised as \"Tummy Television\" http://t.co/PrhHnYRP",
      "id_str": "157911319339737088",
      "lang": "en",
      "possibly_sensitive": false,
      "retweet_count": "1",
      "retweeted": false,
      "source": "\u003ca href=\"http://www.hootsuite.com\" rel=\"nofollow\"\u003eHootsuite\u003c/a\u003e",
      "truncated": false
    },
    "wof:name": "Twitter message #157911319339737088",
    "wof:placetype": "custom"
  },
  "geometry": {"coordinates":[-122.386166,37.616356],"type":"Point"}
}
