{
  "type": "Feature",
  "properties": {
    "sfomuseum:placetype": "tweet",
    "twitter:tweet": {
      "created": 1474907122,
      "created_at": "Mon Sep 26 16:25:22 +0000 2016",
      "display_text_range": [
        "0", 
        "154"
      ],
      "entities": {
        "hashtags": [
          {
            "indices": [
              "65", 
              "82"
            ],
            "text": "ArtAndDisability"
          }
        ],
        "media": [
          {
            "display_url": "pic.twitter.com/he6KX5Xdbr",
            "expanded_url": "https://twitter.com/SFOMuseum/status/780443155682525184/photo/1",
            "id_str": "780443152721256448",
            "indices": [
              "131", 
              "154"
            ],
            "media_url": "http://pbs.twimg.com/media/CtSw6ZVWIAASDpc.jpg",
            "media_url_https": "https://pbs.twimg.com/media/CtSw6ZVWIAASDpc.jpg",
            "sizes": {
              "large": {
                "h": "960",
                "resize": "fit",
                "w": "1243"
              },
              "medium": {
                "h": "927",
                "resize": "fit",
                "w": "1200"
              },
              "small": {
                "h": "525",
                "resize": "fit",
                "w": "680"
              },
              "thumb": {
                "h": "150",
                "resize": "crop",
                "w": "150"
              }
            },
            "type": "photo",
            "url": "https://t.co/he6KX5Xdbr"
          }
        ],
        "urls": [
          {
            "display_url": "bit.ly/ArtAndDisabili…",
            "expanded_url": "http://bit.ly/ArtAndDisability",
            "indices": [
              "107", 
              "130"
            ],
            "url": "https://t.co/Zffsk9qy1H"
          }
        ]
      },
      "extended_entities": {
        "media": [
          {
            "display_url": "pic.twitter.com/he6KX5Xdbr",
            "expanded_url": "https://twitter.com/SFOMuseum/status/780443155682525184/photo/1",
            "id_str": "780443152721256448",
            "indices": [
              "131", 
              "154"
            ],
            "media_url": "http://pbs.twimg.com/media/CtSw6ZVWIAASDpc.jpg",
            "media_url_https": "https://pbs.twimg.com/media/CtSw6ZVWIAASDpc.jpg",
            "sizes": {
              "large": {
                "h": "960",
                "resize": "fit",
                "w": "1243"
              },
              "medium": {
                "h": "927",
                "resize": "fit",
                "w": "1200"
              },
              "small": {
                "h": "525",
                "resize": "fit",
                "w": "680"
              },
              "thumb": {
                "h": "150",
                "resize": "crop",
                "w": "150"
              }
            },
            "type": "photo",
            "url": "https://t.co/he6KX5Xdbr"
          }
        ]
      },
      "favorite_count": "2",
      "favorited": false,
      "full_text": "See more art, including Billy White's, in \"Celebrating a Vision: #ArtAndDisability\", post-security, in T3. https://t.co/Zffsk9qy1H https://t.co/he6KX5Xdbr",
      "id_str": "780443155682525184",
      "lang": "en",
      "possibly_sensitive": false,
      "retweet_count": "0",
      "retweeted": false,
      "source": "\u003ca href=\"http://www.hootsuite.com\" rel=\"nofollow\"\u003eHootsuite\u003c/a\u003e",
      "truncated": false
    },
    "wof:name": "Twitter message #780443155682525184",
    "wof:placetype": "custom"
  },
  "geometry": {"coordinates":[-122.386166,37.616356],"type":"Point"}
}
