{
  "type": "Feature",
  "properties": {
    "date:cessation_lower":"2013-01-03",
    "date:cessation_upper":"2013-01-03",
    "date:inception_lower":"2013-01-03",
    "date:inception_upper":"2013-01-03",
    "iso:country":"US",
    "sfomuseum:placetype":"tweet",
    "twitter:tweet":{
        "created":1357242383,
        "created_at":"Thu Jan 03 19:46:23 +0000 2013",
        "display_text_range":[
            "0",
            "131"
        ],
        "entities":{
            "urls":[
                {
                    "display_url":"lockerz.com/s/274310776",
                    "expanded_url":"http://lockerz.com/s/274310776",
                    "indices":[
                        "111",
                        "131"
                    ],
                    "url":"http://t.co/AG4IRfPe"
                }
            ],
            "user_mentions":[
                {
                    "id_str":"1034261",
                    "indices":[
                        "3",
                        "11"
                    ],
                    "name":"Laralyn McWilliams",
                    "screen_name":"Laralyn"
                }
            ]
        },
        "favorite_count":"0",
        "favorited":false,
        "full_text":"RT @Laralyn: Board game exhibit at SFO. Love that the spider and bee are sparring while wearing boxing gloves! http://t.co/AG4IRfPe",
        "id_str":"286921470528061440",
        "lang":"en",
        "possibly_sensitive":false,
        "retweet_count":"0",
        "retweeted":false,
        "source":"<a href=\"http://www.hootsuite.com\" rel=\"nofollow\">Hootsuite</a>",
        "truncated":false
    },
    "wof:name":"RT @Laralyn: Board game exhibit at SFO. Love that the spider and bee are sparring while wearing boxing gloves! http://t.co/AG4IRfPe",
    "wof:placetype":"custom"
},
  "geometry": {"coordinates":[-122.386166,37.616356],"type":"Point"}
}