{
  "type": "Feature",
  "properties": {
    "date:cessation_lower": "2012-08-09",
    "date:cessation_upper": "2012-08-09",
    "date:inception_lower": "2012-08-09",
    "date:inception_upper": "2012-08-09",
    "iso:country": "US",
    "sfomuseum:placetype": "tweet",
    "twitter:tweet": {
      "created": 1344539035,
      "created_at": "Thu Aug 09 19:03:55 +0000 2012",
      "display_text_range": [
        "0",
        "113"
      ],
      "edit_info": {
        "initial": {
          "editTweetIds": [
            "233639765373767680"
          ],
          "editableUntil": "2012-08-09T19:33:55.539Z",
          "editsRemaining": "5",
          "isEditEligible": true
        }
      },
      "entities": {
        "urls": [
          {
            "display_url": "bit.ly/RDH6fC",
            "expanded_url": "http://bit.ly/RDH6fC",
            "indices": [
              "93",
              "113"
            ],
            "url": "http://t.co/CyDx2GfI"
          }
        ],
        "user_mentions": [
          {
            "id_str": "18958334",
            "indices": [
              "28",
              "33"
            ],
            "name": "SF Arts Commission",
            "screen_name": "SFAC"
          }
        ]
      },
      "favorite_count": "0",
      "favorited": false,
      "full_text": "Absolutely incredible!!  RT @SFAC: Art can make possible what you may never have dreamed of. http://t.co/CyDx2GfI",
      "id_str": "233639765373767680",
      "lang": "en",
      "possibly_sensitive": false,
      "retweet_count": "0",
      "retweeted": false,
      "source": "\u003ca href=\"https://about.twitter.com/products/tweetdeck\" rel=\"nofollow\"\u003eTweetDeck\u003c/a\u003e",
      "truncated": false
    },
    "wof:name": "Absolutely incredible!!  RT @SFAC: Art can make possible what you may never have dreamed of. http://t.co/CyDx2GfI",
    "wof:placetype": "custom"
  },
  "geometry": {"coordinates":[-122.386166,37.616356],"type":"Point"}
}
