{
  "type": "Feature",
  "properties": {
    "date:cessation_lower": "2013-04-16",
    "date:cessation_upper": "2013-04-16",
    "date:inception_lower": "2013-04-16",
    "date:inception_upper": "2013-04-16",
    "iso:country": "US",
    "sfomuseum:placetype": "tweet",
    "twitter:tweet": {
      "created": 1366147707,
      "created_at": "Tue Apr 16 21:28:27 +0000 2013",
      "display_text_range": [
        "0",
        "115"
      ],
      "edit_info": {
        "initial": {
          "editTweetIds": [
            "324273103918227457"
          ],
          "editableUntil": "2013-04-16T21:58:27.334Z",
          "editsRemaining": "5",
          "isEditEligible": true
        }
      },
      "entities": {
        "urls": [
          {
            "display_url": "instagram.com/p/YLjOfGxk-H/",
            "expanded_url": "http://instagram.com/p/YLjOfGxk-H/",
            "indices": [
              "93",
              "115"
            ],
            "url": "http://t.co/VVBuHWRdjW"
          }
        ]
      },
      "favorite_count": "0",
      "favorited": false,
      "full_text": "It's quite the race in the Game of Matrimony or Old Maid, a popular board game in the 1880s. http://t.co/VVBuHWRdjW",
      "id_str": "324273103918227457",
      "lang": "en",
      "possibly_sensitive": false,
      "retweet_count": "0",
      "retweeted": false,
      "source": "\u003ca href=\"http://instagram.com\" rel=\"nofollow\"\u003eInstagram\u003c/a\u003e",
      "truncated": false
    },
    "wof:name": "It's quite the race in the Game of Matrimony or Old Maid, a popular board game in the 1880s. http://t.co/VVBuHWRdjW",
    "wof:placetype": "custom"
  },
  "geometry": {"coordinates":[-122.386166,37.616356],"type":"Point"}
}
