{
  "type": "Feature",
  "properties": {
    "date:cessation_lower": "2014-01-23",
    "date:cessation_upper": "2014-01-23",
    "date:inception_lower": "2014-01-23",
    "date:inception_upper": "2014-01-23",
    "iso:country": "US",
    "sfomuseum:placetype": "tweet",
    "twitter:tweet": {
      "created": 1390507153,
      "created_at": "Thu Jan 23 19:59:13 +0000 2014",
      "display_text_range": [
        "0",
        "136"
      ],
      "entities": {
        "hashtags": [
          {
            "indices": [
              "67",
              "76"
            ],
            "text": "aviation"
          },
          {
            "indices": [
              "77",
              "84"
            ],
            "text": "museum"
          },
          {
            "indices": [
              "109",
              "113"
            ],
            "text": "sfo"
          }
        ],
        "urls": [
          {
            "display_url": "tmblr.co/ZjxuDw15CjoQF",
            "expanded_url": "http://tmblr.co/ZjxuDw15CjoQF",
            "indices": [
              "114",
              "136"
            ],
            "url": "http://t.co/PyWa4dOvhJ"
          }
        ],
        "user_mentions": [
          {
            "id_str": "16103807",
            "indices": [
              "13",
              "26"
            ],
            "name": "Emil Petrinic",
            "screen_name": "emilpetrinic"
          }
        ]
      },
      "favorite_count": "0",
      "favorited": false,
      "full_text": "Welcome!! RT @emilpetrinic: Photo: Made it to our destination, the #aviation #museum. This place is amazing. #sfo http://t.co/PyWa4dOvhJ",
      "id_str": "426444024967614464",
      "lang": "en",
      "possibly_sensitive": false,
      "retweet_count": "1",
      "retweeted": false,
      "source": "\u003ca href=\"http://www.hootsuite.com\" rel=\"nofollow\"\u003eHootsuite\u003c/a\u003e",
      "truncated": false
    },
    "wof:name": "Welcome!! RT @emilpetrinic: Photo: Made it to our destination, the #aviation #museum. This place is amazing. #sfo http://t.co/PyWa4dOvhJ",
    "wof:placetype": "custom"
  },
  "geometry": {"coordinates":[-122.386166,37.616356],"type":"Point"}
}
