{
  "type": "Feature",
  "properties": {
    "sfomuseum:placetype": "tweet",
    "twitter:tweet": {
      "created": 1323364201,
      "created_at": "Thu Dec 08 17:10:01 +0000 2011",
      "display_text_range": [
        "0", 
        "66"
      ],
      "entities": {
        "user_mentions": [
          {
            "id_str": "21921560",
            "indices": [
              "27", 
              "38"
            ],
            "name": "SF Symphony",
            "screen_name": "SFSymphony"
          }
        ]
      },
      "favorite_count": "0",
      "favorited": false,
      "full_text": "Happy 100th anniversary to @SFSymphony!! Here's to 100 more years!",
      "id_str": "144826074637930497",
      "lang": "en",
      "retweet_count": "0",
      "retweeted": false,
      "source": "\u003ca href=\"https://about.twitter.com/products/tweetdeck\" rel=\"nofollow\"\u003eTweetDeck\u003c/a\u003e",
      "truncated": false
    },
    "wof:name": "Twitter message #144826074637930497",
    "wof:placetype": "custom"
  },
  "geometry": {"coordinates":[-122.386166,37.616356],"type":"Point"}
}
