{
  "type": "Feature",
  "properties": {
    "sfomuseum:placetype": "tweet",
    "twitter:tweet": {
      "created": 1576547852,
      "created_at": "Tue Dec 17 01:57:32 +0000 2019",
      "display_text_range": [
        "0", 
        "219"
      ],
      "entities": {
        "hashtags": [
          {
            "indices": [
              "78", 
              "89"
            ],
            "text": "BarryMcGee"
          }
        ],
        "media": [
          {
            "display_url": "pic.twitter.com/m5pQqgloct",
            "expanded_url": "https://twitter.com/SFOMuseum/status/1206755272602947584/photo/1",
            "id_str": "1206755265837592576",
            "indices": [
              "196", 
              "219"
            ],
            "media_url": "http://pbs.twimg.com/media/EL9BhUcU8AAx_AG.jpg",
            "media_url_https": "https://pbs.twimg.com/media/EL9BhUcU8AAx_AG.jpg",
            "sizes": {
              "large": {
                "h": "1504",
                "resize": "fit",
                "w": "2000"
              },
              "medium": {
                "h": "902",
                "resize": "fit",
                "w": "1200"
              },
              "small": {
                "h": "511",
                "resize": "fit",
                "w": "680"
              },
              "thumb": {
                "h": "150",
                "resize": "crop",
                "w": "150"
              }
            },
            "type": "photo",
            "url": "https://t.co/m5pQqgloct"
          }
        ]
      },
      "extended_entities": {
        "media": [
          {
            "display_url": "pic.twitter.com/m5pQqgloct",
            "expanded_url": "https://twitter.com/SFOMuseum/status/1206755272602947584/photo/1",
            "id_str": "1206755265837592576",
            "indices": [
              "196", 
              "219"
            ],
            "media_url": "http://pbs.twimg.com/media/EL9BhUcU8AAx_AG.jpg",
            "media_url_https": "https://pbs.twimg.com/media/EL9BhUcU8AAx_AG.jpg",
            "sizes": {
              "large": {
                "h": "1504",
                "resize": "fit",
                "w": "2000"
              },
              "medium": {
                "h": "902",
                "resize": "fit",
                "w": "1200"
              },
              "small": {
                "h": "511",
                "resize": "fit",
                "w": "680"
              },
              "thumb": {
                "h": "150",
                "resize": "crop",
                "w": "150"
              }
            },
            "type": "photo",
            "url": "https://t.co/m5pQqgloct"
          }
        ]
      },
      "favorite_count": "2",
      "favorited": false,
      "full_text": "Echoing the graffiti, skate, surf, and punk traditions in which he is rooted, #BarryMcGee paints the characters he observes on materials he collects from the edges and hidden corners of the city. https://t.co/m5pQqgloct",
      "id_str": "1206755272602947584",
      "in_reply_to_screen_name": "SFOMuseum",
      "in_reply_to_status_id": "1206755261194489858",
      "in_reply_to_status_id_str": "1206755261194489858",
      "in_reply_to_user_id": "116329337",
      "in_reply_to_user_id_str": "116329337",
      "lang": "en",
      "possibly_sensitive": false,
      "retweet_count": "0",
      "retweeted": false,
      "source": "\u003ca href=\"https://mobile.twitter.com\" rel=\"nofollow\"\u003eTwitter Web App\u003c/a\u003e",
      "truncated": false
    },
    "wof:name": "Twitter message #1206755272602947584",
    "wof:placetype": "custom"
  },
  "geometry": {"coordinates":[-122.386166,37.616356],"type":"Point"}
}
