{
  "type": "Feature",
  "properties": {
    "sfomuseum:placetype": "tweet",
    "twitter:tweet": {
      "created": 1450152309,
      "created_at": "Tue Dec 15 04:05:09 +0000 2015",
      "display_text_range": [
        "0", 
        "138"
      ],
      "entities": {
        "hashtags": [
          {
            "indices": [
              "99", 
              "105"
            ],
            "text": "PanAm"
          }
        ],
        "media": [
          {
            "display_url": "pic.twitter.com/6jqJd3UZdn",
            "expanded_url": "https://twitter.com/SFOMuseum/status/676613941078945793/photo/1",
            "id_str": "676613940596576256",
            "indices": [
              "115", 
              "138"
            ],
            "media_url": "http://pbs.twimg.com/media/CWPQy0tWEAAcQwV.jpg",
            "media_url_https": "https://pbs.twimg.com/media/CWPQy0tWEAAcQwV.jpg",
            "sizes": {
              "large": {
                "h": "488",
                "resize": "fit",
                "w": "618"
              },
              "medium": {
                "h": "488",
                "resize": "fit",
                "w": "618"
              },
              "small": {
                "h": "488",
                "resize": "fit",
                "w": "618"
              },
              "thumb": {
                "h": "150",
                "resize": "crop",
                "w": "150"
              }
            },
            "type": "photo",
            "url": "https://t.co/6jqJd3UZdn"
          }
        ]
      },
      "extended_entities": {
        "media": [
          {
            "display_url": "pic.twitter.com/6jqJd3UZdn",
            "expanded_url": "https://twitter.com/SFOMuseum/status/676613941078945793/photo/1",
            "id_str": "676613940596576256",
            "indices": [
              "115", 
              "138"
            ],
            "media_url": "http://pbs.twimg.com/media/CWPQy0tWEAAcQwV.jpg",
            "media_url_https": "https://pbs.twimg.com/media/CWPQy0tWEAAcQwV.jpg",
            "sizes": {
              "large": {
                "h": "488",
                "resize": "fit",
                "w": "618"
              },
              "medium": {
                "h": "488",
                "resize": "fit",
                "w": "618"
              },
              "small": {
                "h": "488",
                "resize": "fit",
                "w": "618"
              },
              "thumb": {
                "h": "150",
                "resize": "crop",
                "w": "150"
              }
            },
            "type": "photo",
            "url": "https://t.co/6jqJd3UZdn"
          }
        ]
      },
      "favorite_count": "3",
      "favorited": false,
      "full_text": "The North Haven passed under an unfinished S.F. Bay Bridge en route to establish Pacific bases for #PanAm in 1935. https://t.co/6jqJd3UZdn",
      "id_str": "676613941078945793",
      "lang": "en",
      "possibly_sensitive": false,
      "retweet_count": "2",
      "retweeted": false,
      "source": "\u003ca href=\"http://www.hootsuite.com\" rel=\"nofollow\"\u003eHootsuite\u003c/a\u003e",
      "truncated": false
    },
    "wof:name": "Twitter message #676613941078945793",
    "wof:placetype": "custom"
  },
  "geometry": {"coordinates":[-122.386166,37.616356],"type":"Point"}
}
