{
  "type": "Feature",
  "properties": {
    "sfomuseum:placetype": "tweet",
    "twitter:tweet": {
      "created": 1317153945,
      "created_at": "Tue Sep 27 20:05:45 +0000 2011",
      "display_text_range": [
        "0", 
        "85"
      ],
      "entities": {
        "user_mentions": [
          {
            "id_str": "17844854",
            "indices": [
              "0", 
              "15"
            ],
            "name": "Asian Art Museum",
            "screen_name": "asianartmuseum"
          }
        ]
      },
      "favorite_count": "0",
      "favorited": false,
      "full_text": "@asianartmuseum Congratulations! We're looking forward to seeing more of the new you!",
      "id_str": "118778371281915904",
      "in_reply_to_screen_name": "asianartmuseum",
      "in_reply_to_status_id": "118776236746096640",
      "in_reply_to_status_id_str": "118776236746096640",
      "in_reply_to_user_id": "17844854",
      "in_reply_to_user_id_str": "17844854",
      "lang": "en",
      "retweet_count": "0",
      "retweeted": false,
      "source": "\u003ca href=\"http://www.hootsuite.com\" rel=\"nofollow\"\u003eHootsuite\u003c/a\u003e",
      "truncated": false
    },
    "wof:name": "Twitter message #118778371281915904",
    "wof:placetype": "custom"
  },
  "geometry": {"coordinates":[-122.386166,37.616356],"type":"Point"}
}
