{
  "type": "Feature",
  "properties": {
    "date:cessation_lower": "2011-09-27",
    "date:cessation_upper": "2011-09-27",
    "date:inception_lower": "2011-09-27",
    "date:inception_upper": "2011-09-27",
    "iso:country": "US",
    "sfomuseum:placetype": "tweet",
    "twitter:tweet": {
      "created": 1317153945,
      "created_at": "Tue Sep 27 20:05:45 +0000 2011",
      "display_text_range": [
        "0",
        "85"
      ],
      "edit_info": {
        "initial": {
          "editTweetIds": [
            "118778371281915904"
          ],
          "editableUntil": "2011-09-27T21:05:45.166Z",
          "editsRemaining": "5",
          "isEditEligible": true
        }
      },
      "entities": {
        "user_mentions": [
          {
            "id_str": "17844854",
            "indices": [
              "0",
              "15"
            ],
            "name": "Asian Art Museum",
            "screen_name": "asianartmuseum"
          }
        ]
      },
      "favorite_count": "0",
      "favorited": false,
      "full_text": "@asianartmuseum Congratulations! We're looking forward to seeing more of the new you!",
      "id_str": "118778371281915904",
      "in_reply_to_screen_name": "asianartmuseum",
      "in_reply_to_status_id": "118776236746096640",
      "in_reply_to_status_id_str": "118776236746096640",
      "in_reply_to_user_id": "17844854",
      "in_reply_to_user_id_str": "17844854",
      "lang": "en",
      "retweet_count": "0",
      "retweeted": false,
      "source": "\u003ca href=\"http://www.hootsuite.com\" rel=\"nofollow\"\u003eHootsuite\u003c/a\u003e",
      "truncated": false
    },
    "twitter:user_mentions": [
      "asianartmuseum"
    ],
    "wof:name": "@asianartmuseum Congratulations! We're looking forward to seeing more of the new you!",
    "wof:placetype": "custom"
  },
  "geometry": {"coordinates":[-122.386166,37.616356],"type":"Point"}
}
