{
  "type": "Feature",
  "properties": {
    "sfomuseum:placetype": "tweet",
    "twitter:tweet": {
      "created": 1384973667,
      "created_at": "Wed Nov 20 18:54:27 +0000 2013",
      "display_text_range": [
        "0", 
        "143"
      ],
      "entities": {
        "hashtags": [
          {
            "indices": [
              "130", 
              "143"
            ],
            "text": "JapaneseToys"
          }
        ],
        "urls": [
          {
            "display_url": "ow.ly/r1lJX",
            "expanded_url": "http://ow.ly/r1lJX",
            "indices": [
              "107", 
              "129"
            ],
            "url": "http://t.co/lWOPCSeDZw"
          }
        ]
      },
      "favorite_count": "0",
      "favorited": false,
      "full_text": "Early tin toys were made w/ rejected cannery tin, but became regarded for their quality \u0026amp; workmanship: http://t.co/lWOPCSeDZw #JapaneseToys",
      "id_str": "403234901878906880",
      "lang": "en",
      "possibly_sensitive": false,
      "retweet_count": "1",
      "retweeted": false,
      "source": "\u003ca href=\"http://www.hootsuite.com\" rel=\"nofollow\"\u003eHootsuite\u003c/a\u003e",
      "truncated": false
    },
    "wof:name": "Twitter message #403234901878906880",
    "wof:placetype": "custom"
  },
  "geometry": {"coordinates":[-122.386166,37.616356],"type":"Point"}
}
