{
  "type": "Feature",
  "properties": {
    "date:cessation_lower": "2022-11-09",
    "date:cessation_upper": "2022-11-09",
    "date:inception_lower": "2022-11-09",
    "date:inception_upper": "2022-11-09",
    "sfomuseum:placetype": "tweet",
    "twitter:tweet": {
      "created": 1668034462,
      "created_at": "Wed Nov 09 22:54:22 +0000 2022",
      "display_text_range": [
        "0",
        "165"
      ],
      "edit_info": {
        "initial": {
          "editTweetIds": [
            "1590477928324005888"
          ],
          "editableUntil": "2022-11-09T23:24:22.000Z",
          "editsRemaining": "5",
          "isEditEligible": false
        }
      },
      "entities": {
      },
      "favorite_count": "0",
      "favorited": false,
      "full_text": "📸 2/3:\nQantas Empire Airways, First Boeing 707 Flight, Honolulu–Sydney airmail flight cover;  August 1, 1959\nSFO Museum, Gift of Mrs. Siusiadh Rasmussen\n2003.013.001",
      "id_str": "1590477928324005888",
      "in_reply_to_screen_name": "SFOMuseum",
      "in_reply_to_status_id": "1590477926491127808",
      "in_reply_to_status_id_str": "1590477926491127808",
      "in_reply_to_user_id": "116329337",
      "in_reply_to_user_id_str": "116329337",
      "lang": "en",
      "retweet_count": "0",
      "retweeted": false,
      "source": "\u003ca href=\"https://mobile.twitter.com\" rel=\"nofollow\"\u003eTwitter Web App\u003c/a\u003e",
      "truncated": false
    },
    "wof:name": "📸 2/3:\nQantas Empire Airways, First Boeing 707 Flight, Honolulu–Sydney airmail flight cover;  August 1, 1959\nSFO Museum, Gift of Mrs. Siusiadh Rasmussen\n2003.013.001",
    "wof:placetype": "custom"
  },
  "geometry": {"coordinates":[-122.386166,37.616356],"type":"Point"}
}
