{
  "type": "Feature",
  "properties": {
    "date:cessation_lower": "2020-04-21",
    "date:cessation_upper": "2020-04-21",
    "date:inception_lower": "2020-04-21",
    "date:inception_upper": "2020-04-21",
    "iso:country": "US",
    "sfomuseum:placetype": "tweet",
    "twitter:tweet": {
      "created": 1587498660,
      "created_at": "Tue Apr 21 19:51:00 +0000 2020",
      "display_text_range": [
        "0",
        "140"
      ],
      "edit_info": {
        "initial": {
          "editTweetIds": [
            "1252686293177266176"
          ],
          "editableUntil": "2020-04-21T20:51:00.736Z",
          "editsRemaining": "5",
          "isEditEligible": true
        }
      },
      "entities": {
        "user_mentions": [
          {
            "id_str": "14848513",
            "indices": [
              "3",
              "15"
            ],
            "name": "National Air and Space Museum",
            "screen_name": "airandspace"
          },
          {
            "id_str": "2332208684",
            "indices": [
              "103",
              "119"
            ],
            "name": "Smithsonian Archives",
            "screen_name": "SmithsonianArch"
          }
        ]
      },
      "favorite_count": "0",
      "favorited": false,
      "full_text": "RT @airandspace: Sending this National Air and Space Museum flag — which flew in space by the way — to @SmithsonianArch because we loved yo…",
      "id_str": "1252686293177266176",
      "lang": "en",
      "retweet_count": "0",
      "retweeted": false,
      "source": "\u003ca href=\"https://mobile.twitter.com\" rel=\"nofollow\"\u003eTwitter Web App\u003c/a\u003e",
      "truncated": false
    },
    "wof:name": "RT @airandspace: Sending this National Air and Space Museum flag — which flew in space by the way — to @SmithsonianArch because we loved yo…",
    "wof:placetype": "custom"
  },
  "geometry": {"coordinates":[-122.386166,37.616356],"type":"Point"}
}
