{
  "type": "Feature",
  "properties": {
    "date:cessation_lower": "2011-10-24",
    "date:cessation_upper": "2011-10-24",
    "date:inception_lower": "2011-10-24",
    "date:inception_upper": "2011-10-24",
    "iso:country": "US",
    "sfomuseum:placetype": "tweet",
    "twitter:tweet": {
      "created": 1319489378,
      "created_at": "Mon Oct 24 20:49:38 +0000 2011",
      "display_text_range": [
        "0",
        "124"
      ],
      "entities": {
        "urls": [
          {
            "display_url": "pic.twitter.com/a3Du8E8V",
            "expanded_url": "https://twitter.com/jaredr/status/127926274143432704/photo/1",
            "indices": [
              "104",
              "124"
            ],
            "url": "http://t.co/a3Du8E8V"
          }
        ],
        "user_mentions": [
          {
            "id_str": "8146732",
            "indices": [
              "3",
              "10"
            ],
            "name": "Jared Rea",
            "screen_name": "jaredr"
          }
        ]
      },
      "favorite_count": "0",
      "favorited": false,
      "full_text": "RT @jaredr: History of pre-cable television exhibit at SFO heavily features The Twilight Zone. Love it. http://t.co/a3Du8E8V",
      "id_str": "128573888371228673",
      "lang": "en",
      "possibly_sensitive": false,
      "retweet_count": "0",
      "retweeted": false,
      "source": "\u003ca href=\"https://about.twitter.com/products/tweetdeck\" rel=\"nofollow\"\u003eTweetDeck\u003c/a\u003e",
      "truncated": false
    },
    "wof:name": "RT @jaredr: History of pre-cable television exhibit at SFO heavily features The Twilight Zone. Love it. http://t.co/a3Du8E8V",
    "wof:placetype": "custom"
  },
  "geometry": {"coordinates":[-122.386166,37.616356],"type":"Point"}
}
