{
  "type": "Feature",
  "properties": {
    "sfomuseum:placetype": "tweet",
    "twitter:tweet": {
      "created": 1465837809,
      "created_at": "Mon Jun 13 17:10:09 +0000 2016",
      "display_text_range": [
        "0", 
        "71"
      ],
      "entities": {
        "user_mentions": [
          {
            "id_str": "23520855",
            "indices": [
              "0", 
              "7"
            ],
            "name": "Nathalie Atkinson",
            "screen_name": "NathAt"
          }
        ]
      },
      "favorite_count": "1",
      "favorited": false,
      "full_text": "@NathAt Thanks so much for stopping by! What was your favorite uniform?",
      "id_str": "742403698052063233",
      "in_reply_to_screen_name": "NathAt",
      "in_reply_to_status_id": "742158111532830720",
      "in_reply_to_status_id_str": "742158111532830720",
      "in_reply_to_user_id": "23520855",
      "in_reply_to_user_id_str": "23520855",
      "lang": "en",
      "retweet_count": "0",
      "retweeted": false,
      "source": "\u003ca href=\"http://twitter.com\" rel=\"nofollow\"\u003eTwitter Web Client\u003c/a\u003e",
      "truncated": false
    },
    "wof:name": "Twitter message #742403698052063233",
    "wof:placetype": "custom"
  },
  "geometry": {"coordinates":[-122.386166,37.616356],"type":"Point"}
}
