{
  "type": "Feature",
  "properties": {
    "sfomuseum:placetype": "tweet",
    "twitter:tweet": {
      "created": 1524604169,
      "created_at": "Tue Apr 24 21:09:29 +0000 2018",
      "display_text_range": [
        "0", 
        "140"
      ],
      "entities": {
        "hashtags": [
          {
            "indices": [
              "83", 
              "98"
            ],
            "text": "myvxexperience"
          }
        ],
        "user_mentions": [
          {
            "id_str": "16321591",
            "indices": [
              "3", 
              "14"
            ],
            "name": "SanDeE✨ Summers",
            "screen_name": "socalgecko"
          }, 
          {
            "id_str": "12101862",
            "indices": [
              "29", 
              "43"
            ],
            "name": "Virgin America",
            "screen_name": "VirginAmerica"
          }
        ]
      },
      "favorite_count": "0",
      "favorited": false,
      "full_text": "RT @socalgecko: My very last @VirginAmerica boarding pass. What an incredible ride #myvxexperience has been. Tonight, get ready to fly. #vx…",
      "id_str": "988887677305962496",
      "lang": "en",
      "retweet_count": "0",
      "retweeted": false,
      "source": "\u003ca href=\"http://twitter.com\" rel=\"nofollow\"\u003eTwitter Web Client\u003c/a\u003e",
      "truncated": false
    },
    "wof:name": "Twitter message #988887677305962496",
    "wof:placetype": "custom"
  },
  "geometry": {"coordinates":[-122.386166,37.616356],"type":"Point"}
}
