{
  "type": "Feature",
  "properties": {
    "date:cessation_lower": "2017-08-14",
    "date:cessation_upper": "2017-08-14",
    "date:inception_lower": "2017-08-14",
    "date:inception_upper": "2017-08-14",
    "iso:country": "US",
    "sfomuseum:placetype": "tweet",
    "twitter:tweet": {
      "created": 1502726645,
      "created_at": "Mon Aug 14 16:04:05 +0000 2017",
      "display_text_range": [
        "0",
        "140"
      ],
      "edit_info": {
        "initial": {
          "editTweetIds": [
            "897126691436244994"
          ],
          "editableUntil": "2017-08-14T16:34:05.703Z",
          "editsRemaining": "5",
          "isEditEligible": true
        }
      },
      "entities": {
        "hashtags": [
          {
            "indices": [
              "28",
              "35"
            ],
            "text": "avgeek"
          }
        ],
        "urls": [
          {
            "display_url": "usat.ly/2hZdMFd",
            "expanded_url": "https://usat.ly/2hZdMFd",
            "indices": [
              "99",
              "122"
            ],
            "url": "https://t.co/1ic610mNcZ"
          }
        ],
        "user_mentions": [
          {
            "id_str": "1167742169366638592",
            "indices": [
              "3",
              "17"
            ],
            "name": "TodayInTheSky",
            "screen_name": "TodayInTheSky"
          }
        ]
      },
      "favorite_count": "0",
      "favorited": false,
      "full_text": "RT @TodayInTheSky: August's #avgeek gallery: 30 cool aviation photos (this one is for 757 lovers!) https://t.co/1ic610mNcZ  (pics: @photoJD…",
      "id_str": "897126691436244994",
      "lang": "en",
      "possibly_sensitive": false,
      "retweet_count": "0",
      "retweeted": false,
      "source": "\u003ca href=\"http://twitter.com\" rel=\"nofollow\"\u003eTwitter Web Client\u003c/a\u003e",
      "truncated": false
    },
    "wof:name": "RT @TodayInTheSky: August's #avgeek gallery: 30 cool aviation photos (this one is for 757 lovers!) https://t.co/1ic610mNcZ  (pics: @photoJD…",
    "wof:placetype": "custom"
  },
  "geometry": {"coordinates":[-122.386166,37.616356],"type":"Point"}
}
