{
  "type": "Feature",
  "properties": {
    "sfomuseum:placetype": "tweet",
    "twitter:tweet": {
      "created": 1344883418,
      "created_at": "Mon Aug 13 18:43:38 +0000 2012",
      "display_text_range": [
        "0", 
        "86"
      ],
      "entities": {
        "hashtags": [
          {
            "indices": [
              "71", 
              "86"
            ],
            "text": "MuseumOlympics"
          }
        ],
        "user_mentions": [
          {
            "id_str": "15907760",
            "indices": [
              "0", 
              "5"
            ],
            "name": "YBCA",
            "screen_name": "ybca"
          }
        ]
      },
      "favorite_count": "0",
      "favorited": false,
      "full_text": "@ybca Who'd have thunk? Thanks for compiling everything \u0026amp; posting! #MuseumOlympics",
      "id_str": "235084212183629824",
      "in_reply_to_screen_name": "ybca",
      "in_reply_to_status_id": "235081274413424640",
      "in_reply_to_status_id_str": "235081274413424640",
      "in_reply_to_user_id": "15907760",
      "in_reply_to_user_id_str": "15907760",
      "lang": "en",
      "retweet_count": "0",
      "retweeted": false,
      "source": "\u003ca href=\"http://twitter.com/download/iphone\" rel=\"nofollow\"\u003eTwitter for iPhone\u003c/a\u003e",
      "truncated": false
    },
    "wof:name": "Twitter message #235084212183629824",
    "wof:placetype": "custom"
  },
  "geometry": {"coordinates":[-122.386166,37.616356],"type":"Point"}
}
