{
  "type": "Feature",
  "properties": {
    "sfomuseum:placetype": "tweet",
    "twitter:tweet": {
      "created": 1321901505,
      "created_at": "Mon Nov 21 18:51:45 +0000 2011",
      "display_text_range": [
        "0", 
        "94"
      ],
      "entities": {
      },
      "favorite_count": "0",
      "favorited": false,
      "full_text": "@NOnionsXPickles Wow! What a great blog post! Thanks so much for bringing it to our attention!",
      "id_str": "138691084065841152",
      "in_reply_to_status_id": "137947116952748032",
      "in_reply_to_status_id_str": "137947116952748032",
      "in_reply_to_user_id": "111443323",
      "in_reply_to_user_id_str": "111443323",
      "lang": "en",
      "retweet_count": "0",
      "retweeted": false,
      "source": "\u003ca href=\"https://about.twitter.com/products/tweetdeck\" rel=\"nofollow\"\u003eTweetDeck\u003c/a\u003e",
      "truncated": false
    },
    "wof:name": "Twitter message #138691084065841152",
    "wof:placetype": "custom"
  },
  "geometry": {"coordinates":[-122.386166,37.616356],"type":"Point"}
}
