{
  "type": "Feature",
  "properties": {
    "date:cessation_lower": "2012-10-31",
    "date:cessation_upper": "2012-10-31",
    "date:inception_lower": "2012-10-31",
    "date:inception_upper": "2012-10-31",
    "iso:country": "US",
    "sfomuseum:placetype": "tweet",
    "twitter:tweet": {
      "created": 1351705292,
      "created_at": "Wed Oct 31 17:41:32 +0000 2012",
      "display_text_range": [
        "0",
        "109"
      ],
      "entities": {
        "urls": [
          {
            "display_url": "instagr.am/p/RblhT1BiXV/",
            "expanded_url": "http://instagr.am/p/RblhT1BiXV/",
            "indices": [
              "89",
              "109"
            ],
            "url": "http://t.co/bqcD6EYF"
          }
        ],
        "user_mentions": [
          {
            "id_str": "251695111",
            "indices": [
              "3",
              "15"
            ],
            "name": "Becky",
            "screen_name": "wreckobecko"
          }
        ]
      },
      "favorite_count": "0",
      "favorited": false,
      "full_text": "RT @wreckobecko: Love the SFO Airport Museum! (did anyone catch their scripophily show?) http://t.co/bqcD6EYF",
      "id_str": "263697226155556865",
      "lang": "en",
      "possibly_sensitive": false,
      "retweet_count": "0",
      "retweeted": false,
      "source": "\u003ca href=\"http://www.hootsuite.com\" rel=\"nofollow\"\u003eHootsuite\u003c/a\u003e",
      "truncated": false
    },
    "wof:name": "RT @wreckobecko: Love the SFO Airport Museum! (did anyone catch their scripophily show?) http://t.co/bqcD6EYF",
    "wof:placetype": "custom"
  },
  "geometry": {"coordinates":[-122.386166,37.616356],"type":"Point"}
}
