{
  "type": "Feature",
  "properties": {
    "date:cessation_lower": "2011-12-02",
    "date:cessation_upper": "2011-12-02",
    "date:inception_lower": "2011-12-02",
    "date:inception_upper": "2011-12-02",
    "iso:country": "US",
    "sfomuseum:placetype": "tweet",
    "twitter:tweet": {
      "created": 1322854209,
      "created_at": "Fri Dec 02 19:30:09 +0000 2011",
      "display_text_range": [
        "0",
        "127"
      ],
      "edit_info": {
        "initial": {
          "editTweetIds": [
            "142687014498729984"
          ],
          "editableUntil": "2011-12-02T20:00:09.910Z",
          "editsRemaining": "5",
          "isEditEligible": true
        }
      },
      "entities": {
        "urls": [
          {
            "display_url": "bit.ly/vdQooO",
            "expanded_url": "http://bit.ly/vdQooO",
            "indices": [
              "107",
              "127"
            ],
            "url": "http://t.co/TnNGt12Z"
          }
        ]
      },
      "favorite_count": "0",
      "favorited": false,
      "full_text": "Automata were important 19th C. drawing-room objects, set in motion for visitor's or children's amusement: http://t.co/TnNGt12Z",
      "id_str": "142687014498729984",
      "lang": "en",
      "possibly_sensitive": false,
      "retweet_count": "0",
      "retweeted": false,
      "source": "\u003ca href=\"https://about.twitter.com/products/tweetdeck\" rel=\"nofollow\"\u003eTweetDeck\u003c/a\u003e",
      "truncated": false
    },
    "wof:name": "Automata were important 19th C. drawing-room objects, set in motion for visitor's or children's amusement: http://t.co/TnNGt12Z",
    "wof:placetype": "custom"
  },
  "geometry": {"coordinates":[-122.386166,37.616356],"type":"Point"}
}
