{
  "type": "Feature",
  "properties": {
    "sfomuseum:placetype": "tweet",
    "twitter:tweet": {
      "created": 1333581660,
      "created_at": "Wed Apr 04 23:21:00 +0000 2012",
      "display_text_range": [
        "0", 
        "133"
      ],
      "entities": {
        "urls": [
          {
            "display_url": "bit.ly/unL1YG",
            "expanded_url": "http://bit.ly/unL1YG",
            "indices": [
              "113", 
              "133"
            ],
            "url": "http://t.co/gCAnE2eu"
          }
        ]
      },
      "favorite_count": "0",
      "favorited": false,
      "full_text": "We have a new Children's Art exhibit in T1, featuring art from junior k-2nd graders at Marin Preparatory School! http://t.co/gCAnE2eu",
      "id_str": "187681205217538049",
      "lang": "en",
      "possibly_sensitive": false,
      "retweet_count": "0",
      "retweeted": false,
      "source": "\u003ca href=\"https://about.twitter.com/products/tweetdeck\" rel=\"nofollow\"\u003eTweetDeck\u003c/a\u003e",
      "truncated": false
    },
    "wof:name": "Twitter message #187681205217538049",
    "wof:placetype": "custom"
  },
  "geometry": {"coordinates":[-122.386166,37.616356],"type":"Point"}
}
