{
  "type": "Feature",
  "properties": {
    "date:cessation_lower": "2014-08-21",
    "date:cessation_upper": "2014-08-21",
    "date:inception_lower": "2014-08-21",
    "date:inception_upper": "2014-08-21",
    "iso:country": "US",
    "sfomuseum:placetype": "tweet",
    "twitter:tweet": {
      "created": 1408656031,
      "created_at": "Thu Aug 21 21:20:31 +0000 2014",
      "display_text_range": [
        "0",
        "120"
      ],
      "edit_info": {
        "initial": {
          "editTweetIds": [
            "502565936071995394"
          ],
          "editableUntil": "2014-08-21T21:50:31.040Z",
          "editsRemaining": "5",
          "isEditEligible": true
        }
      },
      "entities": {
        "hashtags": [
          {
            "indices": [
              "23",
              "31"
            ],
            "text": "Tiffany"
          }
        ],
        "urls": [
          {
            "display_url": "instagram.com/p/r-aZHMxk4z/",
            "expanded_url": "http://instagram.com/p/r-aZHMxk4z/",
            "indices": [
              "98",
              "120"
            ],
            "url": "http://t.co/kgTlJRPf6j"
          }
        ]
      },
      "favorite_count": "1",
      "favorited": false,
      "full_text": "Among the tools of the #Tiffany trade: tweezers, hammers, files, and shards upon shards of glass. http://t.co/kgTlJRPf6j",
      "id_str": "502565936071995394",
      "lang": "en",
      "possibly_sensitive": false,
      "retweet_count": "0",
      "retweeted": false,
      "source": "\u003ca href=\"http://instagram.com\" rel=\"nofollow\"\u003eInstagram\u003c/a\u003e",
      "truncated": false
    },
    "wof:name": "Among the tools of the #Tiffany trade: tweezers, hammers, files, and shards upon shards of glass. http://t.co/kgTlJRPf6j",
    "wof:placetype": "custom"
  },
  "geometry": {"coordinates":[-122.386166,37.616356],"type":"Point"}
}
