{
  "type": "Feature",
  "properties": {
    "sfomuseum:placetype": "tweet",
    "twitter:tweet": {
      "created": 1318269375,
      "created_at": "Mon Oct 10 17:56:15 +0000 2011",
      "display_text_range": [
        "0", 
        "45"
      ],
      "entities": {
        "user_mentions": [
          {
            "id_str": "18609087",
            "indices": [
              "0", 
              "9"
            ],
            "name": "Jason Langone",
            "screen_name": "langonej"
          }
        ]
      },
      "favorite_count": "0",
      "favorited": false,
      "full_text": "@langonej We're glad you enjoyed the exhibit!",
      "id_str": "123456824220450816",
      "in_reply_to_screen_name": "langonej",
      "in_reply_to_status_id": "123256486670512128",
      "in_reply_to_status_id_str": "123256486670512128",
      "in_reply_to_user_id": "18609087",
      "in_reply_to_user_id_str": "18609087",
      "lang": "en",
      "retweet_count": "0",
      "retweeted": false,
      "source": "\u003ca href=\"http://www.hootsuite.com\" rel=\"nofollow\"\u003eHootsuite\u003c/a\u003e",
      "truncated": false
    },
    "wof:name": "Twitter message #123456824220450816",
    "wof:placetype": "custom"
  },
  "geometry": {"coordinates":[-122.386166,37.616356],"type":"Point"}
}
