{
  "type": "Feature",
  "properties": {
    "date:cessation_lower": "2020-05-07",
    "date:cessation_upper": "2020-05-07",
    "date:inception_lower": "2020-05-07",
    "date:inception_upper": "2020-05-07",
    "iso:country": "US",
    "sfomuseum:placetype": "tweet",
    "twitter:hashtags": [
      "SFO"
    ],
    "twitter:tweet": {
      "created": 1588891552,
      "created_at": "Thu May 07 22:45:52 +0000 2020",
      "display_text_range": [
        "0",
        "140"
      ],
      "edit_info": {
        "initial": {
          "editTweetIds": [
            "1258528504779427841"
          ],
          "editableUntil": "2020-05-07T23:45:52.525Z",
          "editsRemaining": "5",
          "isEditEligible": true
        }
      },
      "entities": {
        "hashtags": [
          {
            "indices": [
              "65",
              "69"
            ],
            "text": "SFO"
          }
        ],
        "user_mentions": [
          {
            "id_str": "16408759",
            "indices": [
              "3",
              "10"
            ],
            "name": "San Francisco International Airport (SFO) ✈️",
            "screen_name": "flySFO"
          },
          {
            "id_str": "1139113469418991617",
            "indices": [
              "40",
              "56"
            ],
            "name": "Vietnam Airlines",
            "screen_name": "VietnamAirlines"
          }
        ]
      },
      "favorite_count": "0",
      "favorited": false,
      "full_text": "RT @flySFO: Up close of details on this @VietnamAirlines livery. #SFO is proud to have the very first Vietnam Airlines passenger flight int…",
      "id_str": "1258528504779427841",
      "lang": "en",
      "retweet_count": "0",
      "retweeted": false,
      "source": "\u003ca href=\"https://mobile.twitter.com\" rel=\"nofollow\"\u003eTwitter Web App\u003c/a\u003e",
      "truncated": false
    },
    "twitter:user_mentions": [
      "flySFO",
      "VietnamAirlines"
    ],
    "wof:name": "RT @flySFO: Up close of details on this @VietnamAirlines livery. #SFO is proud to have the very first Vietnam Airlines passenger flight int…",
    "wof:placetype": "custom"
  },
  "geometry": {"coordinates":[-122.386166,37.616356],"type":"Point"}
}
