{
  "type": "Feature",
  "properties": {
    "sfomuseum:placetype": "tweet",
    "twitter:tweet": {
      "created": 1588891552,
      "created_at": "Thu May 07 22:45:52 +0000 2020",
      "display_text_range": [
        "0", 
        "140"
      ],
      "entities": {
        "hashtags": [
          {
            "indices": [
              "65", 
              "69"
            ],
            "text": "SFO"
          }
        ],
        "user_mentions": [
          {
            "id_str": "16408759",
            "indices": [
              "3", 
              "10"
            ],
            "name": "San Francisco International Airport (SFO) ✈️",
            "screen_name": "flySFO"
          }, 
          {
            "id_str": "1139113469418991617",
            "indices": [
              "40", 
              "56"
            ],
            "name": "Vietnam Airlines",
            "screen_name": "VietnamAirlines"
          }
        ]
      },
      "favorite_count": "0",
      "favorited": false,
      "full_text": "RT @flySFO: Up close of details on this @VietnamAirlines livery. #SFO is proud to have the very first Vietnam Airlines passenger flight int…",
      "id_str": "1258528504779427841",
      "lang": "en",
      "retweet_count": "0",
      "retweeted": false,
      "source": "\u003ca href=\"https://mobile.twitter.com\" rel=\"nofollow\"\u003eTwitter Web App\u003c/a\u003e",
      "truncated": false
    },
    "wof:name": "Twitter message #1258528504779427841",
    "wof:placetype": "custom"
  },
  "geometry": {"coordinates":[-122.386166,37.616356],"type":"Point"}
}
