{
  "type": "Feature",
  "properties": {
    "date:cessation_lower":"2016-09-26",
    "date:cessation_upper":"2016-09-26",
    "date:inception_lower":"2016-09-26",
    "date:inception_upper":"2016-09-26",
    "iso:country":"US",
    "sfomuseum:placetype":"tweet",
    "twitter:tweet":{
        "created":1474917050,
        "created_at":"Mon Sep 26 19:10:50 +0000 2016",
        "display_text_range":[
            "0",
            "140"
        ],
        "entities":{
            "hashtags":[
                {
                    "indices":[
                        "42",
                        "49"
                    ],
                    "text":"Boeing"
                }
            ],
            "user_mentions":[
                {
                    "id_str":"22090282",
                    "indices":[
                        "3",
                        "19"
                    ],
                    "name":"Boeing Airplanes",
                    "screen_name":"BoeingAirplanes"
                }
            ]
        },
        "favorite_count":"0",
        "favorited":false,
        "full_text":"RT @BoeingAirplanes: 35 years strong! The #Boeing 767 first flew on this day in 1981. Since then, nearly 70 airlines have taken delivery of\u2026",
        "id_str":"780484795235176448",
        "lang":"en",
        "retweet_count":"0",
        "retweeted":false,
        "source":"<a href=\"http://www.hootsuite.com\" rel=\"nofollow\">Hootsuite</a>",
        "truncated":false
    },
    "wof:name":"RT @BoeingAirplanes: 35 years strong! The #Boeing 767 first flew on this day in 1981. Since then, nearly 70 airlines have taken delivery of\u2026",
    "wof:placetype":"custom"
},
  "geometry": {"coordinates":[-122.386166,37.616356],"type":"Point"}
}