{
  "type": "Feature",
  "properties": {
    "sfomuseum:placetype": "tweet",
    "twitter:tweet": {
      "created": 1317920710,
      "created_at": "Thu Oct 06 17:05:10 +0000 2011",
      "display_text_range": [
        "0", 
        "137"
      ],
      "entities": {
        "hashtags": [
          {
            "indices": [
              "66", 
              "77"
            ],
            "text": "television"
          }, 
          {
            "indices": [
              "89", 
              "93"
            ],
            "text": "SFO"
          }
        ],
        "urls": [
          {
            "display_url": "twitpic.com/6w1ozp",
            "expanded_url": "http://twitpic.com/6w1ozp",
            "indices": [
              "117", 
              "137"
            ],
            "url": "http://t.co/RhbbcEhR"
          }
        ],
        "user_mentions": [
          {
            "id_str": "15288527",
            "indices": [
              "3", 
              "17"
            ],
            "name": "Glenn O'Donnell",
            "screen_name": "glennodonnell"
          }
        ]
      },
      "favorite_count": "0",
      "favorited": false,
      "full_text": "RT @glennodonnell: If you can, take time to check out the vintage #television exhibit at #SFO terminal 3. Very cool! http://t.co/RhbbcEhR",
      "id_str": "121994418575261696",
      "lang": "en",
      "possibly_sensitive": false,
      "retweet_count": "0",
      "retweeted": false,
      "source": "\u003ca href=\"http://www.hootsuite.com\" rel=\"nofollow\"\u003eHootsuite\u003c/a\u003e",
      "truncated": false
    },
    "wof:name": "Twitter message #121994418575261696",
    "wof:placetype": "custom"
  },
  "geometry": {"coordinates":[-122.386166,37.616356],"type":"Point"}
}
