{
  "type": "Feature",
  "properties": {
    "date:cessation_lower": "2016-05-05",
    "date:cessation_upper": "2016-05-05",
    "date:inception_lower": "2016-05-05",
    "date:inception_upper": "2016-05-05",
    "iso:country": "US",
    "sfomuseum:placetype": "tweet",
    "twitter:tweet": {
      "created": 1462479337,
      "created_at": "Thu May 05 20:15:37 +0000 2016",
      "display_text_range": [
        "0",
        "108"
      ],
      "entities": {
        "urls": [
          {
            "display_url": "vox.com/2016/5/2/11520…",
            "expanded_url": "http://www.vox.com/2016/5/2/11520288/pilot-airplane-photos",
            "indices": [
              "85",
              "108"
            ],
            "url": "https://t.co/te8U7Xplxx"
          }
        ],
        "user_mentions": [
          {
            "id_str": "2347049341",
            "indices": [
              "73",
              "83"
            ],
            "name": "Vox",
            "screen_name": "voxdotcom"
          }
        ]
      },
      "favorite_count": "2",
      "favorited": false,
      "full_text": "I fly 747s for a living. Here are the amazing things I see every day via @voxdotcom  https://t.co/te8U7Xplxx",
      "id_str": "728317246133522432",
      "lang": "en",
      "possibly_sensitive": false,
      "retweet_count": "0",
      "retweeted": false,
      "source": "\u003ca href=\"http://twitter.com/download/iphone\" rel=\"nofollow\"\u003eTwitter for iPhone\u003c/a\u003e",
      "truncated": false
    },
    "wof:name": "I fly 747s for a living. Here are the amazing things I see every day via @voxdotcom  https://t.co/te8U7Xplxx",
    "wof:placetype": "custom"
  },
  "geometry": {"coordinates":[-122.386166,37.616356],"type":"Point"}
}
