{
  "type": "Feature",
  "properties": {
    "sfomuseum:placetype": "tweet",
    "twitter:tweet": {
      "created": 1472925662,
      "created_at": "Sat Sep 03 18:01:02 +0000 2016",
      "display_text_range": [
        "0", 
        "125"
      ],
      "entities": {
        "hashtags": [
          {
            "indices": [
              "42", 
              "58"
            ],
            "text": "DeniseTarantino"
          }
        ],
        "media": [
          {
            "display_url": "pic.twitter.com/zWByQ3eLz4",
            "expanded_url": "https://twitter.com/SFOMuseum/status/772132306509262848/photo/1",
            "id_str": "772132301815877632",
            "indices": [
              "102", 
              "125"
            ],
            "media_url": "http://pbs.twimg.com/media/CrcqPNFXEAA9T06.jpg",
            "media_url_https": "https://pbs.twimg.com/media/CrcqPNFXEAA9T06.jpg",
            "sizes": {
              "large": {
                "h": "2000",
                "resize": "fit",
                "w": "2000"
              },
              "medium": {
                "h": "1200",
                "resize": "fit",
                "w": "1200"
              },
              "small": {
                "h": "680",
                "resize": "fit",
                "w": "680"
              },
              "thumb": {
                "h": "150",
                "resize": "crop",
                "w": "150"
              }
            },
            "type": "photo",
            "url": "https://t.co/zWByQ3eLz4"
          }
        ]
      },
      "extended_entities": {
        "media": [
          {
            "display_url": "pic.twitter.com/zWByQ3eLz4",
            "expanded_url": "https://twitter.com/SFOMuseum/status/772132306509262848/photo/1",
            "id_str": "772132301815877632",
            "indices": [
              "102", 
              "125"
            ],
            "media_url": "http://pbs.twimg.com/media/CrcqPNFXEAA9T06.jpg",
            "media_url_https": "https://pbs.twimg.com/media/CrcqPNFXEAA9T06.jpg",
            "sizes": {
              "large": {
                "h": "2000",
                "resize": "fit",
                "w": "2000"
              },
              "medium": {
                "h": "1200",
                "resize": "fit",
                "w": "1200"
              },
              "small": {
                "h": "680",
                "resize": "fit",
                "w": "680"
              },
              "thumb": {
                "h": "150",
                "resize": "crop",
                "w": "150"
              }
            },
            "type": "photo",
            "url": "https://t.co/zWByQ3eLz4"
          }
        ]
      },
      "favorite_count": "1",
      "favorited": false,
      "full_text": "Roadside America features selections from #DeniseTarantino’s travels along the nation’s rural byways. https://t.co/zWByQ3eLz4",
      "id_str": "772132306509262848",
      "lang": "en",
      "possibly_sensitive": false,
      "retweet_count": "0",
      "retweeted": false,
      "source": "\u003ca href=\"http://www.hootsuite.com\" rel=\"nofollow\"\u003eHootsuite\u003c/a\u003e",
      "truncated": false
    },
    "wof:name": "Twitter message #772132306509262848",
    "wof:placetype": "custom"
  },
  "geometry": {"coordinates":[-122.386166,37.616356],"type":"Point"}
}
