{
  "type": "Feature",
  "properties": {
    "date:cessation_lower": "2013-09-09",
    "date:cessation_upper": "2013-09-09",
    "date:inception_lower": "2013-09-09",
    "date:inception_upper": "2013-09-09",
    "iso:country": "US",
    "sfomuseum:placetype": "tweet",
    "twitter:tweet": {
      "created": 1378752589,
      "created_at": "Mon Sep 09 18:49:49 +0000 2013",
      "display_text_range": [
        "0",
        "44"
      ],
      "edit_info": {
        "initial": {
          "editTweetIds": [
            "377141812588445697"
          ],
          "editableUntil": "2013-09-09T19:19:49.734Z",
          "editsRemaining": "5",
          "isEditEligible": true
        }
      },
      "entities": {
        "hashtags": [
          {
            "indices": [
              "28",
              "44"
            ],
            "text": "jamesjetseurope"
          }
        ],
        "user_mentions": [
          {
            "id_str": "41842642",
            "indices": [
              "0",
              "15"
            ],
            "name": "James Mowdy | BSPOKE",
            "screen_name": "JamesJetsOften"
          }
        ]
      },
      "favorite_count": "1",
      "favorited": false,
      "full_text": "@jamesjetsoften Bon voyage! #jamesjetseurope",
      "id_str": "377141812588445697",
      "in_reply_to_screen_name": "JamesJetsOften",
      "in_reply_to_status_id": "377138202143772672",
      "in_reply_to_status_id_str": "377138202143772672",
      "in_reply_to_user_id": "41842642",
      "in_reply_to_user_id_str": "41842642",
      "lang": "fr",
      "retweet_count": "1",
      "retweeted": false,
      "source": "\u003ca href=\"http://www.hootsuite.com\" rel=\"nofollow\"\u003eHootsuite\u003c/a\u003e",
      "truncated": false
    },
    "wof:name": "@jamesjetsoften Bon voyage! #jamesjetseurope",
    "wof:placetype": "custom"
  },
  "geometry": {"coordinates":[-122.386166,37.616356],"type":"Point"}
}
