{
  "type": "Feature",
  "properties": {
    "date:cessation_lower": "2013-10-23",
    "date:cessation_upper": "2013-10-23",
    "date:inception_lower": "2013-10-23",
    "date:inception_upper": "2013-10-23",
    "iso:country": "US",
    "sfomuseum:placetype": "tweet",
    "twitter:tweet": {
      "created": 1382550974,
      "created_at": "Wed Oct 23 17:56:14 +0000 2013",
      "display_text_range": [
        "0",
        "73"
      ],
      "edit_info": {
        "initial": {
          "editTweetIds": [
            "393073393505153024"
          ],
          "editableUntil": "2013-10-23T18:26:14.619Z",
          "editsRemaining": "5",
          "isEditEligible": true
        }
      },
      "entities": {
        "hashtags": [
          {
            "indices": [
              "41",
              "50"
            ],
            "text": "recology"
          }
        ],
        "urls": [
          {
            "display_url": "instagram.com/p/f0a2JPxk74/",
            "expanded_url": "http://instagram.com/p/f0a2JPxk74/",
            "indices": [
              "51",
              "73"
            ],
            "url": "http://t.co/Ieiie5YfzY"
          }
        ]
      },
      "favorite_count": "0",
      "favorited": false,
      "full_text": "How to disassemble a (styrofoam) Hummer. #recology http://t.co/Ieiie5YfzY",
      "id_str": "393073393505153024",
      "lang": "en",
      "possibly_sensitive": false,
      "retweet_count": "0",
      "retweeted": false,
      "source": "\u003ca href=\"http://instagram.com\" rel=\"nofollow\"\u003eInstagram\u003c/a\u003e",
      "truncated": false
    },
    "wof:name": "How to disassemble a (styrofoam) Hummer. #recology http://t.co/Ieiie5YfzY",
    "wof:placetype": "custom"
  },
  "geometry": {"coordinates":[-122.386166,37.616356],"type":"Point"}
}
