{
  "type": "Feature",
  "properties": {
    "sfomuseum:placetype": "tweet",
    "twitter:tweet": {
      "created": 1505322907,
      "created_at": "Wed Sep 13 17:15:07 +0000 2017",
      "display_text_range": [
        "0", 
        "154"
      ],
      "entities": {
        "user_mentions": [
          {
            "id_str": "892435796153815041",
            "indices": [
              "0", 
              "15"
            ],
            "name": "Caroline Clausewitz",
            "screen_name": "CarolineComeOn"
          }
        ]
      },
      "favorite_count": "1",
      "favorited": false,
      "full_text": "@CarolineComeOn Fantastic question! Because SFO Museum is located within the airport terminals, we are able to reach a large, diverse traveling public 1/3",
      "id_str": "908016201049169920",
      "in_reply_to_screen_name": "CarolineComeOn",
      "in_reply_to_status_id": "908006642360504321",
      "in_reply_to_status_id_str": "908006642360504321",
      "in_reply_to_user_id": "892435796153815041",
      "in_reply_to_user_id_str": "892435796153815041",
      "lang": "en",
      "retweet_count": "0",
      "retweeted": false,
      "source": "\u003ca href=\"http://twitter.com\" rel=\"nofollow\"\u003eTwitter Web Client\u003c/a\u003e",
      "truncated": false
    },
    "wof:name": "Twitter message #908016201049169920",
    "wof:placetype": "custom"
  },
  "geometry": {"coordinates":[-122.386166,37.616356],"type":"Point"}
}
