{
  "type": "Feature",
  "properties": {
    "sfomuseum:placetype": "tweet",
    "twitter:tweet": {
      "created": 1485809743,
      "created_at": "Mon Jan 30 20:55:43 +0000 2017",
      "display_text_range": [
        "0", 
        "138"
      ],
      "entities": {
        "hashtags": [
          {
            "indices": [
              "10", 
              "27"
            ],
            "text": "AmericanAirlines"
          }, 
          {
            "indices": [
              "83", 
              "93"
            ],
            "text": "Boeing707"
          }, 
          {
            "indices": [
              "100", 
              "107"
            ],
            "text": "avgeek"
          }, 
          {
            "indices": [
              "108", 
              "114"
            ],
            "text": "1960s"
          }
        ],
        "urls": [
          {
            "display_url": "sfomuseum.tumblr.com/post/156590124…",
            "expanded_url": "http://sfomuseum.tumblr.com/post/156590124396/this-1960-american-airlines-flight-information",
            "indices": [
              "115", 
              "138"
            ],
            "url": "https://t.co/ubgEaRNvH3"
          }
        ]
      },
      "favorite_count": "0",
      "favorited": false,
      "full_text": "This 1960 #AmericanAirlines flight information packet advertises the airline's new #Boeing707 jets. #avgeek #1960s https://t.co/ubgEaRNvH3",
      "id_str": "826172059927539712",
      "lang": "en",
      "possibly_sensitive": false,
      "retweet_count": "1",
      "retweeted": false,
      "source": "\u003ca href=\"http://twitter.com\" rel=\"nofollow\"\u003eTwitter Web Client\u003c/a\u003e",
      "truncated": false
    },
    "wof:name": "Twitter message #826172059927539712",
    "wof:placetype": "custom"
  },
  "geometry": {"coordinates":[-122.386166,37.616356],"type":"Point"}
}
