{
  "type": "Feature",
  "properties": {
    "sfomuseum:placetype": "tweet",
    "twitter:tweet": {
      "created": 1468350838,
      "created_at": "Tue Jul 12 19:13:58 +0000 2016",
      "display_text_range": [
        "0", 
        "140"
      ],
      "entities": {
        "hashtags": [
          {
            "indices": [
              "104", 
              "110"
            ],
            "text": "PaxEx"
          }
        ],
        "urls": [
          {
            "display_url": "paxex.me/29KTPg3",
            "expanded_url": "http://paxex.me/29KTPg3",
            "indices": [
              "80", 
              "103"
            ],
            "url": "https://t.co/QZbSVGziZ4"
          }
        ],
        "user_mentions": [
          {
            "id_str": "4134016317",
            "indices": [
              "3", 
              "19"
            ],
            "name": "Becca A 🏳️‍🌈",
            "screen_name": "RunwayGirlBecca"
          }, 
          {
            "id_str": "17542672",
            "indices": [
              "115", 
              "126"
            ],
            "name": "Runway Girl Network 🏳️‍🌈",
            "screen_name": "RunwayGirl"
          }
        ]
      },
      "favorite_count": "0",
      "favorited": false,
      "full_text": "RT @RunwayGirlBecca: ICYMI: Airbus launches A380-focused flight search engine - https://t.co/QZbSVGziZ4 #PaxEx via @RunwayGirl https://t.co…",
      "id_str": "752944106066833408",
      "lang": "en",
      "possibly_sensitive": false,
      "retweet_count": "0",
      "retweeted": false,
      "source": "\u003ca href=\"http://www.hootsuite.com\" rel=\"nofollow\"\u003eHootsuite\u003c/a\u003e",
      "truncated": false
    },
    "wof:name": "Twitter message #752944106066833408",
    "wof:placetype": "custom"
  },
  "geometry": {"coordinates":[-122.386166,37.616356],"type":"Point"}
}
