{
  "type": "Feature",
  "properties": {
    "date:cessation_lower": "2013-03-28",
    "date:cessation_upper": "2013-03-28",
    "date:inception_lower": "2013-03-28",
    "date:inception_upper": "2013-03-28",
    "iso:country": "US",
    "sfomuseum:placetype": "tweet",
    "twitter:tweet": {
      "created": 1364505853,
      "created_at": "Thu Mar 28 21:24:13 +0000 2013",
      "display_text_range": [
        "0",
        "86"
      ],
      "edit_info": {
        "initial": {
          "editTweetIds": [
            "317386669886152705"
          ],
          "editableUntil": "2013-03-28T22:24:13.517Z",
          "editsRemaining": "5",
          "isEditEligible": true
        }
      },
      "entities": {
        "urls": [
          {
            "display_url": "bit.ly/YJJPtk",
            "expanded_url": "http://bit.ly/YJJPtk",
            "indices": [
              "64",
              "86"
            ],
            "url": "http://t.co/zihWE4ufFQ"
          }
        ]
      },
      "favorite_count": "0",
      "favorited": false,
      "full_text": "Thanks, @annetkentroom! It looks so official in your database!  http://t.co/zihWE4ufFQ",
      "id_str": "317386669886152705",
      "lang": "en",
      "possibly_sensitive": false,
      "retweet_count": "0",
      "retweeted": false,
      "source": "\u003ca href=\"https://about.twitter.com/products/tweetdeck\" rel=\"nofollow\"\u003eTweetDeck\u003c/a\u003e",
      "truncated": false
    },
    "twitter:user_mentions": [
      "annetkentroom"
    ],
    "wof:name": "Thanks, @annetkentroom! It looks so official in your database!  http://t.co/zihWE4ufFQ",
    "wof:placetype": "custom",
    "wof:placetype_alt": [
      "tweet"
    ]
  },
  "geometry": {"coordinates":[-122.386166,37.616356],"type":"Point"}
}
