{
  "type": "Feature",
  "properties": {
    "sfomuseum:placetype": "tweet",
    "twitter:tweet": {
      "created": 1421195351,
      "created_at": "Wed Jan 14 00:29:11 +0000 2015",
      "display_text_range": [
        "0", 
        "124"
      ],
      "entities": {
        "urls": [
          {
            "display_url": "ow.ly/HhgEt",
            "expanded_url": "http://ow.ly/HhgEt",
            "indices": [
              "102", 
              "124"
            ],
            "url": "http://t.co/RcI3opuHH0"
          }
        ]
      },
      "favorite_count": "1",
      "favorited": false,
      "full_text": "David Klein produced numerous iconic 1950s-60s Jet Age posters. His one for San Francisco? Nailed it. http://t.co/RcI3opuHH0",
      "id_str": "555159656625344512",
      "lang": "en",
      "possibly_sensitive": false,
      "retweet_count": "1",
      "retweeted": false,
      "source": "\u003ca href=\"http://www.hootsuite.com\" rel=\"nofollow\"\u003eHootsuite\u003c/a\u003e",
      "truncated": false
    },
    "wof:name": "Twitter message #555159656625344512",
    "wof:placetype": "custom"
  },
  "geometry": {"coordinates":[-122.386166,37.616356],"type":"Point"}
}
