{
  "type": "Feature",
  "properties": {
    "date:cessation_lower": "2023-01-14",
    "date:cessation_upper": "2023-01-14",
    "date:inception_lower": "2023-01-14",
    "date:inception_upper": "2023-01-14",
    "sfomuseum:placetype": "tweet",
    "twitter:tweet": {
      "created": 1673721849,
      "created_at": "Sat Jan 14 18:44:09 +0000 2023",
      "display_text_range": [
        "0",
        "186"
      ],
      "edit_info": {
        "initial": {
          "editTweetIds": [
            "1614332560108097540"
          ],
          "editableUntil": "2023-01-14T19:14:09.000Z",
          "editsRemaining": "5",
          "isEditEligible": false
        }
      },
      "entities": {
      },
      "favorite_count": "0",
      "favorited": false,
      "full_text": "📸 1/2: \n1. photograph: Braniff International, Concorde; 1979\nGift of Marie G. Clark\n2022.089.019\n\n2. photograph: Braniff International, Concorde; 1979\nGift of Marie G. Clark\n2022.089.010",
      "id_str": "1614332560108097540",
      "in_reply_to_screen_name": "SFOMuseum",
      "in_reply_to_status_id": "1614332538843004930",
      "in_reply_to_status_id_str": "1614332538843004930",
      "in_reply_to_user_id": "116329337",
      "in_reply_to_user_id_str": "116329337",
      "lang": "en",
      "retweet_count": "0",
      "retweeted": false,
      "source": "\u003ca href=\"http://twitter.com/download/iphone\" rel=\"nofollow\"\u003eTwitter for iPhone\u003c/a\u003e",
      "truncated": false
    },
    "wof:name": "📸 1/2: \n1. photograph: Braniff International, Concorde; 1979\nGift of Marie G. Clark\n2022.089.019\n\n2. photograph: Braniff International, Concorde; 1979\nGift of Marie G. Clark\n2022.089.010",
    "wof:placetype": "custom",
    "wof:placetype_alt": [
      "tweet"
    ]
  },
  "geometry": {"coordinates":[-122.386166,37.616356],"type":"Point"}
}
