{
  "type": "Feature",
  "properties": {
    "date:cessation_lower": "2014-08-04",
    "date:cessation_upper": "2014-08-04",
    "date:inception_lower": "2014-08-04",
    "date:inception_upper": "2014-08-04",
    "iso:country": "US",
    "sfomuseum:placetype": "tweet",
    "twitter:tweet": {
      "created": 1407174674,
      "created_at": "Mon Aug 04 17:51:14 +0000 2014",
      "display_text_range": [
        "0",
        "124"
      ],
      "edit_info": {
        "initial": {
          "editTweetIds": [
            "496352675047698438"
          ],
          "editableUntil": "2014-08-04T18:51:14.175Z",
          "editsRemaining": "5",
          "isEditEligible": true
        }
      },
      "entities": {
        "urls": [
          {
            "display_url": "instagram.com/p/rSQ7bIxk6N/",
            "expanded_url": "http://instagram.com/p/rSQ7bIxk6N/",
            "indices": [
              "102",
              "124"
            ],
            "url": "http://t.co/Wg0IADv3vp"
          }
        ]
      },
      "favorite_count": "0",
      "favorited": false,
      "full_text": "The primary features of Golden Gate Park's 1015 acres were largely in place by 1904, as seen in this… http://t.co/Wg0IADv3vp",
      "id_str": "496352675047698438",
      "lang": "en",
      "possibly_sensitive": false,
      "retweet_count": "0",
      "retweeted": false,
      "source": "\u003ca href=\"http://instagram.com\" rel=\"nofollow\"\u003eInstagram\u003c/a\u003e",
      "truncated": false
    },
    "wof:name": "The primary features of Golden Gate Park's 1015 acres were largely in place by 1904, as seen in this… http://t.co/Wg0IADv3vp",
    "wof:placetype": "custom"
  },
  "geometry": {"coordinates":[-122.386166,37.616356],"type":"Point"}
}
