{
  "type": "Feature",
  "properties": {
    "date:cessation_lower": "2022-01-13",
    "date:cessation_upper": "2022-01-13",
    "date:inception_lower": "2022-01-13",
    "date:inception_upper": "2022-01-13",
    "sfomuseum:placetype": "tweet",
    "twitter:tweet": {
      "created": 1642106597,
      "created_at": "Thu Jan 13 20:43:17 +0000 2022",
      "display_text_range": [
        "0",
        "134"
      ],
      "edit_info": {
        "initial": {
          "editTweetIds": [
            "1481728580308508678"
          ],
          "editableUntil": "2022-01-13T21:43:17.388Z",
          "editsRemaining": "5",
          "isEditEligible": true
        }
      },
      "entities": {
        "urls": [
          {
            "display_url": "collection.sfomuseum.org/objects/174667…",
            "expanded_url": "https://collection.sfomuseum.org/objects/1746678581/",
            "indices": [
              "111",
              "134"
            ],
            "url": "https://t.co/Bg3g0mQUg7"
          }
        ],
        "user_mentions": [
          {
            "id_str": "127575007",
            "indices": [
              "3",
              "19"
            ],
            "name": "thisisaaronland",
            "screen_name": "thisisaaronland"
          },
          {
            "id_str": "116329337",
            "indices": [
              "38",
              "48"
            ],
            "name": "SFO Museum",
            "screen_name": "SFOMuseum"
          }
        ]
      },
      "favorite_count": "0",
      "favorited": false,
      "full_text": "RT @thisisaaronland: did you know the @sfomuseum aviation collection is full of amazing hats / like this one – https://t.co/Bg3g0mQUg7",
      "id_str": "1481728580308508678",
      "lang": "en",
      "possibly_sensitive": false,
      "retweet_count": "0",
      "retweeted": false,
      "source": "\u003ca href=\"https://mobile.twitter.com\" rel=\"nofollow\"\u003eTwitter Web App\u003c/a\u003e",
      "truncated": false
    },
    "twitter:user_mentions": [
      "thisisaaronland",
      "SFOMuseum"
    ],
    "wof:name": "RT @thisisaaronland: did you know the @sfomuseum aviation collection is full of amazing hats / like this one – https://t.co/Bg3g0mQUg7",
    "wof:placetype": "custom"
  },
  "geometry": {"coordinates":[-122.386166,37.616356],"type":"Point"}
}
