{
  "type": "Feature",
  "properties": {
    "date:cessation_lower": "2022-05-06",
    "date:cessation_upper": "2022-05-06",
    "date:inception_lower": "2022-05-06",
    "date:inception_upper": "2022-05-06",
    "sfomuseum:placetype": "tweet",
    "twitter:tweet": {
      "created": 1651862260,
      "created_at": "Fri May 06 18:37:40 +0000 2022",
      "display_text_range": [
        "0",
        "124"
      ],
      "edit_info": {
        "initial": {
          "editTweetIds": [
            "1522646798430470144"
          ],
          "editableUntil": "2022-05-06T19:07:40.000Z",
          "editsRemaining": "5",
          "isEditEligible": true
        }
      },
      "entities": {
      },
      "favorite_count": "0",
      "favorited": false,
      "full_text": "📸:\nUnited Air Lines, Ellen Church, first stewardess\n1930\nSFO Museum Collection\nGift of United Airlines Archives\n1999.047.311",
      "id_str": "1522646798430470144",
      "in_reply_to_screen_name": "SFOMuseum",
      "in_reply_to_status_id": "1522646797222510592",
      "in_reply_to_status_id_str": "1522646797222510592",
      "in_reply_to_user_id": "116329337",
      "in_reply_to_user_id_str": "116329337",
      "lang": "en",
      "retweet_count": "0",
      "retweeted": false,
      "source": "\u003ca href=\"https://mobile.twitter.com\" rel=\"nofollow\"\u003eTwitter Web App\u003c/a\u003e",
      "truncated": false
    },
    "wof:name": "📸:\nUnited Air Lines, Ellen Church, first stewardess\n1930\nSFO Museum Collection\nGift of United Airlines Archives\n1999.047.311",
    "wof:placetype": "custom"
  },
  "geometry": {"coordinates":[-122.386166,37.616356],"type":"Point"}
}
