{
  "type": "Feature",
  "properties": {
    "date:cessation_lower":"2013-04-08",
    "date:cessation_upper":"2013-04-08",
    "date:inception_lower":"2013-04-08",
    "date:inception_upper":"2013-04-08",
    "iso:country":"US",
    "sfomuseum:placetype":"tweet",
    "twitter:tweet":{
        "created":1365437315,
        "created_at":"Mon Apr 08 16:08:35 +0000 2013",
        "display_text_range":[
            "0",
            "113"
        ],
        "entities":{
            "user_mentions":[
                {
                    "id_str":"1189601",
                    "indices":[
                        "42",
                        "48"
                    ],
                    "name":"Dan Miller",
                    "screen_name":"dnm54"
                }
            ]
        },
        "favorite_count":"0",
        "favorited":false,
        "full_text":"Thanks! Did you have a favorite piece? RT @dnm54: Recycled art display at SFO is very well done. Lots to look at.",
        "id_str":"321293505978855424",
        "lang":"en",
        "retweet_count":"0",
        "retweeted":false,
        "source":"<a href=\"http://www.hootsuite.com\" rel=\"nofollow\">Hootsuite</a>",
        "truncated":false
    },
    "wof:name":"Thanks! Did you have a favorite piece? RT @dnm54: Recycled art display at SFO is very well done. Lots to look at.",
    "wof:placetype":"custom"
},
  "geometry": {"coordinates":[-122.386166,37.616356],"type":"Point"}
}