{
  "type": "Feature",
  "properties": {
    "date:cessation_lower": "2012-07-02",
    "date:cessation_upper": "2012-07-02",
    "date:inception_lower": "2012-07-02",
    "date:inception_upper": "2012-07-02",
    "iso:country": "US",
    "sfomuseum:placetype": "tweet",
    "twitter:tweet": {
      "created": 1341246430,
      "created_at": "Mon Jul 02 16:27:10 +0000 2012",
      "display_text_range": [
        "0",
        "140"
      ],
      "edit_info": {
        "initial": {
          "editTweetIds": [
            "219829578775015425"
          ],
          "editableUntil": "2012-07-02T16:57:10.473Z",
          "editsRemaining": "5",
          "isEditEligible": true
        }
      },
      "entities": {
        "user_mentions": [
          {
            "id_str": "604236115",
            "indices": [
              "3",
              "16"
            ],
            "name": "Alex.Muscat",
            "screen_name": "AlexMooseCat"
          }
        ]
      },
      "favorite_count": "0",
      "favorited": false,
      "full_text": "RT @AlexMooseCat: One of the most awesome Ducati's I've ever seen, and it's in SFO's Italian motorcycle exhibit. Best terminal ever. htt ...",
      "id_str": "219829578775015425",
      "lang": "en",
      "retweet_count": "0",
      "retweeted": false,
      "source": "\u003ca href=\"http://www.hootsuite.com\" rel=\"nofollow\"\u003eHootsuite\u003c/a\u003e",
      "truncated": false
    },
    "wof:name": "RT @AlexMooseCat: One of the most awesome Ducati's I've ever seen, and it's in SFO's Italian motorcycle exhibit. Best terminal ever. htt ...",
    "wof:placetype": "custom"
  },
  "geometry": {"coordinates":[-122.386166,37.616356],"type":"Point"}
}
