{
  "type": "Feature",
  "properties": {
    "sfomuseum:placetype": "tweet",
    "twitter:tweet": {
      "created": 1341246430,
      "created_at": "Mon Jul 02 16:27:10 +0000 2012",
      "display_text_range": [
        "0", 
        "140"
      ],
      "entities": {
        "user_mentions": [
          {
            "id_str": "604236115",
            "indices": [
              "3", 
              "16"
            ],
            "name": "Alex.Muscat",
            "screen_name": "AlexMooseCat"
          }
        ]
      },
      "favorite_count": "0",
      "favorited": false,
      "full_text": "RT @AlexMooseCat: One of the most awesome Ducati's I've ever seen, and it's in SFO's Italian motorcycle exhibit. Best terminal ever. htt ...",
      "id_str": "219829578775015425",
      "lang": "en",
      "retweet_count": "0",
      "retweeted": false,
      "source": "\u003ca href=\"http://www.hootsuite.com\" rel=\"nofollow\"\u003eHootsuite\u003c/a\u003e",
      "truncated": false
    },
    "wof:name": "Twitter message #219829578775015425",
    "wof:placetype": "custom"
  },
  "geometry": {"coordinates":[-122.386166,37.616356],"type":"Point"}
}
