{
  "type": "Feature",
  "properties": {
    "date:cessation_lower": "2014-12-19",
    "date:cessation_upper": "2014-12-19",
    "date:inception_lower": "2014-12-19",
    "date:inception_upper": "2014-12-19",
    "iso:country": "US",
    "sfomuseum:placetype": "tweet",
    "twitter:tweet": {
      "created": 1419028706,
      "created_at": "Fri Dec 19 22:38:26 +0000 2014",
      "display_text_range": [
        "0",
        "118"
      ],
      "edit_info": {
        "initial": {
          "editTweetIds": [
            "546072089732476928"
          ],
          "editableUntil": "2014-12-19T23:08:26.378Z",
          "editsRemaining": "5",
          "isEditEligible": true
        }
      },
      "entities": {
        "hashtags": [
          {
            "indices": [
              "77",
              "86"
            ],
            "text": "aviation"
          },
          {
            "indices": [
              "87",
              "95"
            ],
            "text": "library"
          }
        ],
        "urls": [
          {
            "display_url": "instagram.com/p/wzis1Pxk23/",
            "expanded_url": "http://instagram.com/p/wzis1Pxk23/",
            "indices": [
              "96",
              "118"
            ],
            "url": "http://t.co/QNGjph2Ztu"
          }
        ]
      },
      "favorite_count": "0",
      "favorited": false,
      "full_text": "Need a read? Swing by our library and peruse our over 8,000 book collection! #aviation #library http://t.co/QNGjph2Ztu",
      "id_str": "546072089732476928",
      "lang": "en",
      "possibly_sensitive": false,
      "retweet_count": "0",
      "retweeted": false,
      "source": "\u003ca href=\"http://instagram.com\" rel=\"nofollow\"\u003eInstagram\u003c/a\u003e",
      "truncated": false
    },
    "wof:name": "Need a read? Swing by our library and peruse our over 8,000 book collection! #aviation #library http://t.co/QNGjph2Ztu",
    "wof:placetype": "custom"
  },
  "geometry": {"coordinates":[-122.386166,37.616356],"type":"Point"}
}
