{
  "type": "Feature",
  "properties": {
    "sfomuseum:placetype": "tweet",
    "twitter:tweet": {
      "created": 1515963625,
      "created_at": "Sun Jan 14 21:00:25 +0000 2018",
      "display_text_range": [
        "0", 
        "201"
      ],
      "entities": {
        "hashtags": [
          {
            "indices": [
              "136", 
              "153"
            ],
            "text": "AmericaInColor40"
          }
        ],
        "media": [
          {
            "display_url": "pic.twitter.com/bFsPZezj0U",
            "expanded_url": "https://twitter.com/SFOMuseum/status/952646609539616769/photo/1",
            "id_str": "952646605857083392",
            "indices": [
              "178", 
              "201"
            ],
            "media_url": "http://pbs.twimg.com/media/DTh7CmqX0AA7g6Q.jpg",
            "media_url_https": "https://pbs.twimg.com/media/DTh7CmqX0AA7g6Q.jpg",
            "sizes": {
              "large": {
                "h": "1598",
                "resize": "fit",
                "w": "2000"
              },
              "medium": {
                "h": "959",
                "resize": "fit",
                "w": "1200"
              },
              "small": {
                "h": "543",
                "resize": "fit",
                "w": "680"
              },
              "thumb": {
                "h": "150",
                "resize": "crop",
                "w": "150"
              }
            },
            "type": "photo",
            "url": "https://t.co/bFsPZezj0U"
          }
        ],
        "urls": [
          {
            "display_url": "bit.ly/2CQdypZ",
            "expanded_url": "http://bit.ly/2CQdypZ",
            "indices": [
              "154", 
              "177"
            ],
            "url": "https://t.co/LvqfTBFWoE"
          }
        ]
      },
      "extended_entities": {
        "media": [
          {
            "display_url": "pic.twitter.com/bFsPZezj0U",
            "expanded_url": "https://twitter.com/SFOMuseum/status/952646609539616769/photo/1",
            "id_str": "952646605857083392",
            "indices": [
              "178", 
              "201"
            ],
            "media_url": "http://pbs.twimg.com/media/DTh7CmqX0AA7g6Q.jpg",
            "media_url_https": "https://pbs.twimg.com/media/DTh7CmqX0AA7g6Q.jpg",
            "sizes": {
              "large": {
                "h": "1598",
                "resize": "fit",
                "w": "2000"
              },
              "medium": {
                "h": "959",
                "resize": "fit",
                "w": "1200"
              },
              "small": {
                "h": "543",
                "resize": "fit",
                "w": "680"
              },
              "thumb": {
                "h": "150",
                "resize": "crop",
                "w": "150"
              }
            },
            "type": "photo",
            "url": "https://t.co/bFsPZezj0U"
          }
        ]
      },
      "favorite_count": "2",
      "favorited": false,
      "full_text": "\"America in Color: 1940–1943\" by photographers under the Farm Security Administration (FSA) is on display, pre-security, in Terminal 2. #AmericaInColor40 https://t.co/LvqfTBFWoE https://t.co/bFsPZezj0U",
      "id_str": "952646609539616769",
      "lang": "en",
      "possibly_sensitive": false,
      "retweet_count": "1",
      "retweeted": false,
      "source": "\u003ca href=\"http://www.hootsuite.com\" rel=\"nofollow\"\u003eHootsuite\u003c/a\u003e",
      "truncated": false
    },
    "wof:name": "Twitter message #952646609539616769",
    "wof:placetype": "custom"
  },
  "geometry": {"coordinates":[-122.386166,37.616356],"type":"Point"}
}
