{
  "type": "Feature",
  "properties": {
    "date:cessation_lower": "2021-02-19",
    "date:cessation_upper": "2021-02-19",
    "date:inception_lower": "2021-02-19",
    "date:inception_upper": "2021-02-19",
    "sfomuseum:placetype": "tweet",
    "twitter:tweet": {
      "created": 1613768713,
      "created_at": "Fri Feb 19 21:05:13 +0000 2021",
      "display_text_range": [
        "0",
        "269"
      ],
      "edit_info": {
        "initial": {
          "editTweetIds": [
            "1362870881223991297"
          ],
          "editableUntil": "2021-02-19T21:35:13.657Z",
          "editsRemaining": "5",
          "isEditEligible": true
        }
      },
      "entities": {
      },
      "favorite_count": "0",
      "favorited": false,
      "full_text": "📸:\nphotograph: Eastern Airlines, Boeing 757, 1980s\nGift of William Rys, Jr.\n2019.085.156\n\npostcard: Condor, Boeing 757-200, 1980s\nGift of Thomas G. Dragges\n2915.166.0481\n\npostcard: LTE International Airways, Boeing 757-200, 1980s\nGift of Thomas G. Dragges\n2015.166.0961",
      "id_str": "1362870881223991297",
      "in_reply_to_screen_name": "SFOMuseum",
      "in_reply_to_status_id": "1362870877323370499",
      "in_reply_to_status_id_str": "1362870877323370499",
      "in_reply_to_user_id": "116329337",
      "in_reply_to_user_id_str": "116329337",
      "lang": "en",
      "retweet_count": "0",
      "retweeted": false,
      "source": "\u003ca href=\"https://mobile.twitter.com\" rel=\"nofollow\"\u003eTwitter Web App\u003c/a\u003e",
      "truncated": false
    },
    "wof:name": "📸:\nphotograph: Eastern Airlines, Boeing 757, 1980s\nGift of William Rys, Jr.\n2019.085.156\n\npostcard: Condor, Boeing 757-200, 1980s\nGift of Thomas G. Dragges\n2915.166.0481\n\npostcard: LTE International Airways, Boeing 757-200, 1980s\nGift of Thomas G. Dragges\n2015.166.0961",
    "wof:placetype": "custom"
  },
  "geometry": {"coordinates":[-122.386166,37.616356],"type":"Point"}
}
