{
  "type": "Feature",
  "properties": {
    "date:cessation_lower": "2022-08-18",
    "date:cessation_upper": "2022-08-18",
    "date:inception_lower": "2022-08-18",
    "date:inception_upper": "2022-08-18",
    "sfomuseum:placetype": "tweet",
    "twitter:hashtags": [
      "agardenforgeorge",
      "marcellohutchisontrujillo"
    ],
    "twitter:tweet": {
      "created": 1660847175,
      "created_at": "Thu Aug 18 18:26:15 +0000 2022",
      "display_text_range": [
        "0",
        "280"
      ],
      "edit_info": {
        "initial": {
          "editTweetIds": [
            "1560332263010619393"
          ],
          "editableUntil": "2022-08-18T18:56:15.000Z",
          "editsRemaining": "5",
          "isEditEligible": false
        }
      },
      "entities": {
        "hashtags": [
          {
            "indices": [
              "203",
              "220"
            ],
            "text": "agardenforgeorge"
          },
          {
            "indices": [
              "221",
              "247"
            ],
            "text": "marcellohutchisontrujillo"
          }
        ],
        "urls": [
          {
            "display_url": "bit.ly/VideoArts",
            "expanded_url": "http://bit.ly/VideoArts",
            "indices": [
              "179",
              "202"
            ],
            "url": "https://t.co/s0oA7fUN7a"
          }
        ],
        "user_mentions": [
          {
            "id_str": "2340573404",
            "indices": [
              "249",
              "264"
            ],
            "name": "SF FILM FINALS",
            "screen_name": "sfsufilmfinals"
          },
          {
            "id_str": "384523839",
            "indices": [
              "265",
              "280"
            ],
            "name": "SFSU Cinema Dept.",
            "screen_name": "SFSUCinemaDept"
          }
        ]
      },
      "favorite_count": "0",
      "favorited": false,
      "full_text": "\"See “A Garden for George” by Marcello Hutchison-Trujillo in the Video Arts Gallery, located pre-security in the International Terminal open daily from 7am to 10pm, or online at: https://t.co/s0oA7fUN7a\n#agardenforgeorge #marcellohutchisontrujillo  @sfsufilmfinals @SFSUCinemaDept",
      "id_str": "1560332263010619393",
      "in_reply_to_screen_name": "SFOMuseum",
      "in_reply_to_status_id": "1560332258845675520",
      "in_reply_to_status_id_str": "1560332258845675520",
      "in_reply_to_user_id": "116329337",
      "in_reply_to_user_id_str": "116329337",
      "lang": "en",
      "possibly_sensitive": false,
      "retweet_count": "0",
      "retweeted": false,
      "source": "\u003ca href=\"https://mobile.twitter.com\" rel=\"nofollow\"\u003eTwitter Web App\u003c/a\u003e",
      "truncated": false
    },
    "twitter:user_mentions": [
      "sfsufilmfinals",
      "SFSUCinemaDept"
    ],
    "wof:name": "\"See “A Garden for George” by Marcello Hutchison-Trujillo in the Video Arts Gallery, located pre-security in the International Terminal open daily from 7am to 10pm, or online at: https://t.co/s0oA7fUN7a\n#agardenforgeorge #marcellohutchisontrujillo  @sfsufilmfinals @SFSUCinemaDept",
    "wof:placetype": "custom"
  },
  "geometry": {"coordinates":[-122.386166,37.616356],"type":"Point"}
}
