{
  "type": "Feature",
  "properties": {
    "date:cessation_lower": "2020-12-21",
    "date:cessation_upper": "2020-12-21",
    "date:inception_lower": "2020-12-21",
    "date:inception_upper": "2020-12-21",
    "sfomuseum:placetype": "tweet",
    "twitter:hashtags": [
      "TeamSFO",
      "MaskOnSFO"
    ],
    "twitter:tweet": {
      "created": 1608586300,
      "created_at": "Mon Dec 21 21:31:40 +0000 2020",
      "display_text_range": [
        "0",
        "139"
      ],
      "edit_info": {
        "initial": {
          "editTweetIds": [
            "1341134263798755329"
          ],
          "editableUntil": "2020-12-21T22:31:40.216Z",
          "editsRemaining": "5",
          "isEditEligible": true
        }
      },
      "entities": {
        "hashtags": [
          {
            "indices": [
              "20",
              "28"
            ],
            "text": "TeamSFO"
          },
          {
            "indices": [
              "89",
              "99"
            ],
            "text": "MaskOnSFO"
          }
        ],
        "user_mentions": [
          {
            "id_str": "16408759",
            "indices": [
              "3",
              "10"
            ],
            "name": "San Francisco International Airport (SFO) ✈️",
            "screen_name": "flySFO"
          }
        ]
      },
      "favorite_count": "0",
      "favorited": false,
      "full_text": "RT @flySFO: We know #TeamSFO talents run deep, so when we put the call for help creating #MaskOnSFO, we were thrilled to receive responses…",
      "id_str": "1341134263798755329",
      "lang": "en",
      "retweet_count": "0",
      "retweeted": false,
      "source": "\u003ca href=\"https://mobile.twitter.com\" rel=\"nofollow\"\u003eTwitter Web App\u003c/a\u003e",
      "truncated": false
    },
    "twitter:user_mentions": [
      "flySFO"
    ],
    "wof:name": "RT @flySFO: We know #TeamSFO talents run deep, so when we put the call for help creating #MaskOnSFO, we were thrilled to receive responses…",
    "wof:placetype": "custom",
    "wof:placetype_alt": [
      "tweet"
    ]
  },
  "geometry": {"coordinates":[-122.386166,37.616356],"type":"Point"}
}
