{
  "type": "Feature",
  "properties": {
    "sfomuseum:placetype": "tweet",
    "twitter:tweet": {
      "created": 1536187161,
      "created_at": "Wed Sep 05 22:39:21 +0000 2018",
      "display_text_range": [
        "0", 
        "149"
      ],
      "entities": {
        "urls": [
          {
            "display_url": "twitter.com/CultureThemes/…",
            "expanded_url": "https://twitter.com/CultureThemes/status/1035854899915968514",
            "indices": [
              "126", 
              "149"
            ],
            "url": "https://t.co/YEAuDjF60j"
          }
        ]
      },
      "favorite_count": "1",
      "favorited": false,
      "full_text": "SFO Museum is participating in Ask A Curator next week! What would you like to know about SFO Museum? Stay tuned for answers! https://t.co/YEAuDjF60j",
      "id_str": "1037470266006228992",
      "lang": "en",
      "possibly_sensitive": false,
      "retweet_count": "0",
      "retweeted": false,
      "source": "\u003ca href=\"http://twitter.com\" rel=\"nofollow\"\u003eTwitter Web Client\u003c/a\u003e",
      "truncated": false
    },
    "wof:name": "Twitter message #1037470266006228992",
    "wof:placetype": "custom"
  },
  "geometry": {"coordinates":[-122.386166,37.616356],"type":"Point"}
}
