{
  "type": "Feature",
  "properties": {
    "date:cessation_lower": "2022-10-06",
    "date:cessation_upper": "2022-10-06",
    "date:inception_lower": "2022-10-06",
    "date:inception_upper": "2022-10-06",
    "sfomuseum:placetype": "tweet",
    "twitter:hashtags": [
      "Kapaemahu",
      "hinaleimoanawongkalu",
      "deanhamer",
      "joewilson",
      "VideoArts"
    ],
    "twitter:tweet": {
      "created": 1665079785,
      "created_at": "Thu Oct 06 18:09:45 +0000 2022",
      "display_text_range": [
        "0",
        "283"
      ],
      "edit_info": {
        "initial": {
          "editTweetIds": [
            "1578085114453495809"
          ],
          "editableUntil": "2022-10-06T18:39:45.000Z",
          "editsRemaining": "5",
          "isEditEligible": false
        }
      },
      "entities": {
        "hashtags": [
          {
            "indices": [
              "217",
              "227"
            ],
            "text": "Kapaemahu"
          },
          {
            "indices": [
              "229",
              "250"
            ],
            "text": "hinaleimoanawongkalu"
          },
          {
            "indices": [
              "251",
              "261"
            ],
            "text": "deanhamer"
          },
          {
            "indices": [
              "262",
              "272"
            ],
            "text": "joewilson"
          },
          {
            "indices": [
              "273",
              "283"
            ],
            "text": "VideoArts"
          }
        ],
        "urls": [
          {
            "display_url": "bit.ly/VideoArts",
            "expanded_url": "http://bit.ly/VideoArts",
            "indices": [
              "193",
              "216"
            ],
            "url": "https://t.co/s0oA7fUN7a"
          }
        ]
      },
      "favorite_count": "0",
      "favorited": false,
      "full_text": "See “Kapaemahu” by Hinaleimoana Wong-Kalu, Dean Hamer \u0026amp; Joe Wilson in the Video Arts Gallery, located pre-security in the International Terminal, open daily from 7am to 10pm, or online at: https://t.co/s0oA7fUN7a #Kapaemahu  #hinaleimoanawongkalu #deanhamer #joewilson #VideoArts",
      "id_str": "1578085114453495809",
      "in_reply_to_screen_name": "SFOMuseum",
      "in_reply_to_status_id": "1578085111794257920",
      "in_reply_to_status_id_str": "1578085111794257920",
      "in_reply_to_user_id": "116329337",
      "in_reply_to_user_id_str": "116329337",
      "lang": "en",
      "possibly_sensitive": false,
      "retweet_count": "0",
      "retweeted": false,
      "source": "\u003ca href=\"https://mobile.twitter.com\" rel=\"nofollow\"\u003eTwitter Web App\u003c/a\u003e",
      "truncated": false
    },
    "wof:name": "See “Kapaemahu” by Hinaleimoana Wong-Kalu, Dean Hamer \u0026amp; Joe Wilson in the Video Arts Gallery, located pre-security in the International Terminal, open daily from 7am to 10pm, or online at: https://t.co/s0oA7fUN7a #Kapaemahu  #hinaleimoanawongkalu #deanhamer #joewilson #VideoArts",
    "wof:placetype": "custom"
  },
  "geometry": {"coordinates":[-122.386166,37.616356],"type":"Point"}
}
