{
  "type": "Feature",
  "properties": {
    "sfomuseum:placetype": "tweet",
    "twitter:tweet": {
      "created": 1344029545,
      "created_at": "Fri Aug 03 21:32:25 +0000 2012",
      "display_text_range": [
        "0", 
        "98"
      ],
      "entities": {
        "hashtags": [
          {
            "indices": [
              "0", 
              "15"
            ],
            "text": "MuseumOlympics"
          }, 
          {
            "indices": [
              "66", 
              "77"
            ],
            "text": "MuseumLove"
          }
        ],
        "urls": [
          {
            "display_url": "instagr.am/p/N4ZEWtxk8T/",
            "expanded_url": "http://instagr.am/p/N4ZEWtxk8T/",
            "indices": [
              "78", 
              "98"
            ],
            "url": "http://t.co/Qz5dA7aa"
          }
        ]
      },
      "favorite_count": "0",
      "favorited": false,
      "full_text": "#MuseumOlympics participants, you are the wind beneath our wings! #MuseumLove http://t.co/Qz5dA7aa",
      "id_str": "231502810695471104",
      "lang": "en",
      "possibly_sensitive": false,
      "retweet_count": "1",
      "retweeted": false,
      "source": "\u003ca href=\"http://instagram.com\" rel=\"nofollow\"\u003eInstagram\u003c/a\u003e",
      "truncated": false
    },
    "wof:name": "Twitter message #231502810695471104",
    "wof:placetype": "custom"
  },
  "geometry": {"coordinates":[-122.386166,37.616356],"type":"Point"}
}
