{
  "type": "Feature",
  "properties": {
    "sfomuseum:placetype": "tweet",
    "twitter:tweet": {
      "created": 1431024800,
      "created_at": "Thu May 07 18:53:20 +0000 2015",
      "display_text_range": [
        "0", 
        "121"
      ],
      "entities": {
        "hashtags": [
          {
            "indices": [
              "0", 
              "18"
            ],
            "text": "ThrowbackThursday"
          }
        ],
        "urls": [
          {
            "display_url": "ow.ly/MFcHn",
            "expanded_url": "http://ow.ly/MFcHn",
            "indices": [
              "99", 
              "121"
            ],
            "url": "http://t.co/JJo9LveVPr"
          }
        ],
        "user_mentions": [
          {
            "id_str": "16408759",
            "indices": [
              "43", 
              "50"
            ],
            "name": "San Francisco International Airport (SFO) ✈️",
            "screen_name": "flySFO"
          }
        ]
      },
      "favorite_count": "0",
      "favorited": false,
      "full_text": "#ThrowbackThursday and a Happy Birthday to @flySFO! Mills Field was dedicated on this day in 1927! http://t.co/JJo9LveVPr",
      "id_str": "596387355533156352",
      "lang": "en",
      "possibly_sensitive": false,
      "retweet_count": "0",
      "retweeted": false,
      "source": "\u003ca href=\"http://www.hootsuite.com\" rel=\"nofollow\"\u003eHootsuite\u003c/a\u003e",
      "truncated": false
    },
    "wof:name": "Twitter message #596387355533156352",
    "wof:placetype": "custom"
  },
  "geometry": {"coordinates":[-122.386166,37.616356],"type":"Point"}
}
