{
  "type": "Feature",
  "properties": {
    "date:cessation_lower": "2015-01-27",
    "date:cessation_upper": "2015-01-27",
    "date:inception_lower": "2015-01-27",
    "date:inception_upper": "2015-01-27",
    "iso:country": "US",
    "sfomuseum:placetype": "tweet",
    "twitter:hashtags": [
      "avgeek"
    ],
    "twitter:tweet": {
      "created": 1422401572,
      "created_at": "Tue Jan 27 23:32:52 +0000 2015",
      "display_text_range": [
        "0",
        "142"
      ],
      "edit_info": {
        "initial": {
          "editTweetIds": [
            "560218914781921280"
          ],
          "editableUntil": "2015-01-28T00:32:52.305Z",
          "editsRemaining": "5",
          "isEditEligible": true
        }
      },
      "entities": {
        "hashtags": [
          {
            "indices": [
              "135",
              "142"
            ],
            "text": "avgeek"
          }
        ],
        "urls": [
          {
            "display_url": "ow.ly/I3qWg",
            "expanded_url": "http://ow.ly/I3qWg",
            "indices": [
              "112",
              "134"
            ],
            "url": "http://t.co/TsHRVPH0uo"
          }
        ]
      },
      "favorite_count": "0",
      "favorited": false,
      "full_text": "Czech Airlines celebrated the first jetliner service between Prague \u0026amp; Moscow with a colorful luggage label: http://t.co/TsHRVPH0uo #avgeek",
      "id_str": "560218914781921280",
      "lang": "en",
      "possibly_sensitive": false,
      "retweet_count": "2",
      "retweeted": false,
      "source": "\u003ca href=\"http://www.hootsuite.com\" rel=\"nofollow\"\u003eHootsuite\u003c/a\u003e",
      "truncated": false
    },
    "wof:name": "Czech Airlines celebrated the first jetliner service between Prague \u0026amp; Moscow with a colorful luggage label: http://t.co/TsHRVPH0uo #avgeek",
    "wof:placetype": "custom",
    "wof:placetype_alt": [
      "tweet"
    ]
  },
  "geometry": {"coordinates":[-122.386166,37.616356],"type":"Point"}
}
