{
  "type": "Feature",
  "properties": {
    "sfomuseum:placetype": "tweet",
    "twitter:tweet": {
      "created": 1503714304,
      "created_at": "Sat Aug 26 02:25:04 +0000 2017",
      "display_text_range": [
        "0", 
        "168"
      ],
      "entities": {
        "media": [
          {
            "display_url": "pic.twitter.com/n7T31cG6Te",
            "expanded_url": "https://twitter.com/SFOMuseum/status/901269233698574336/photo/1",
            "id_str": "901269230531760131",
            "indices": [
              "145", 
              "168"
            ],
            "media_url": "http://pbs.twimg.com/media/DIHzlwzV0AMTTnO.jpg",
            "media_url_https": "https://pbs.twimg.com/media/DIHzlwzV0AMTTnO.jpg",
            "sizes": {
              "large": {
                "h": "1333",
                "resize": "fit",
                "w": "2000"
              },
              "medium": {
                "h": "800",
                "resize": "fit",
                "w": "1200"
              },
              "small": {
                "h": "453",
                "resize": "fit",
                "w": "680"
              },
              "thumb": {
                "h": "150",
                "resize": "crop",
                "w": "150"
              }
            },
            "type": "photo",
            "url": "https://t.co/n7T31cG6Te"
          }
        ]
      },
      "extended_entities": {
        "media": [
          {
            "display_url": "pic.twitter.com/n7T31cG6Te",
            "expanded_url": "https://twitter.com/SFOMuseum/status/901269233698574336/photo/1",
            "id_str": "901269230531760131",
            "indices": [
              "145", 
              "168"
            ],
            "media_url": "http://pbs.twimg.com/media/DIHzlwzV0AMTTnO.jpg",
            "media_url_https": "https://pbs.twimg.com/media/DIHzlwzV0AMTTnO.jpg",
            "sizes": {
              "large": {
                "h": "1333",
                "resize": "fit",
                "w": "2000"
              },
              "medium": {
                "h": "800",
                "resize": "fit",
                "w": "1200"
              },
              "small": {
                "h": "453",
                "resize": "fit",
                "w": "680"
              },
              "thumb": {
                "h": "150",
                "resize": "crop",
                "w": "150"
              }
            },
            "type": "photo",
            "url": "https://t.co/n7T31cG6Te"
          }
        ]
      },
      "favorite_count": "2",
      "favorited": false,
      "full_text": "In the past, weavers made items for themselves \u0026amp; for family members. Now they are a means for indigenous women to earn supplementary income. https://t.co/n7T31cG6Te",
      "id_str": "901269233698574336",
      "lang": "en",
      "possibly_sensitive": false,
      "retweet_count": "0",
      "retweeted": false,
      "source": "\u003ca href=\"http://www.hootsuite.com\" rel=\"nofollow\"\u003eHootsuite\u003c/a\u003e",
      "truncated": false
    },
    "wof:name": "Twitter message #901269233698574336",
    "wof:placetype": "custom"
  },
  "geometry": {"coordinates":[-122.386166,37.616356],"type":"Point"}
}
