{
  "type": "Feature",
  "properties": {
    "sfomuseum:placetype": "tweet",
    "twitter:tweet": {
      "created": 1494549910,
      "created_at": "Fri May 12 00:45:10 +0000 2017",
      "display_text_range": [
        "0", 
        "156"
      ],
      "entities": {
        "hashtags": [
          {
            "indices": [
              "17", 
              "24"
            ],
            "text": "Manchu"
          }, 
          {
            "indices": [
              "52", 
              "57"
            ],
            "text": "Qing"
          }, 
          {
            "indices": [
              "117", 
              "132"
            ],
            "text": "ShoesinCulture"
          }
        ],
        "media": [
          {
            "display_url": "pic.twitter.com/ZnWDvK80Ju",
            "expanded_url": "https://twitter.com/SFOMuseum/status/862830978477305859/photo/1",
            "id_str": "862830974601535488",
            "indices": [
              "133", 
              "156"
            ],
            "media_url": "http://pbs.twimg.com/media/C_lkMy5UIAATMEh.jpg",
            "media_url_https": "https://pbs.twimg.com/media/C_lkMy5UIAATMEh.jpg",
            "sizes": {
              "large": {
                "h": "2000",
                "resize": "fit",
                "w": "1849"
              },
              "medium": {
                "h": "1200",
                "resize": "fit",
                "w": "1109"
              },
              "small": {
                "h": "680",
                "resize": "fit",
                "w": "629"
              },
              "thumb": {
                "h": "150",
                "resize": "crop",
                "w": "150"
              }
            },
            "type": "photo",
            "url": "https://t.co/ZnWDvK80Ju"
          }
        ]
      },
      "extended_entities": {
        "media": [
          {
            "display_url": "pic.twitter.com/ZnWDvK80Ju",
            "expanded_url": "https://twitter.com/SFOMuseum/status/862830978477305859/photo/1",
            "id_str": "862830974601535488",
            "indices": [
              "133", 
              "156"
            ],
            "media_url": "http://pbs.twimg.com/media/C_lkMy5UIAATMEh.jpg",
            "media_url_https": "https://pbs.twimg.com/media/C_lkMy5UIAATMEh.jpg",
            "sizes": {
              "large": {
                "h": "2000",
                "resize": "fit",
                "w": "1849"
              },
              "medium": {
                "h": "1200",
                "resize": "fit",
                "w": "1109"
              },
              "small": {
                "h": "680",
                "resize": "fit",
                "w": "629"
              },
              "thumb": {
                "h": "150",
                "resize": "crop",
                "w": "150"
              }
            },
            "type": "photo",
            "url": "https://t.co/ZnWDvK80Ju"
          }
        ]
      },
      "favorite_count": "2",
      "favorited": false,
      "full_text": "The semi-nomadic #Manchu conquerors who founded the #Qing dynasty conveyed their prestige by wearing platform shoes. #ShoesinCulture https://t.co/ZnWDvK80Ju",
      "id_str": "862830978477305859",
      "lang": "en",
      "possibly_sensitive": false,
      "retweet_count": "1",
      "retweeted": false,
      "source": "\u003ca href=\"http://www.hootsuite.com\" rel=\"nofollow\"\u003eHootsuite\u003c/a\u003e",
      "truncated": false
    },
    "wof:name": "Twitter message #862830978477305859",
    "wof:placetype": "custom"
  },
  "geometry": {"coordinates":[-122.386166,37.616356],"type":"Point"}
}
