{
  "type": "Feature",
  "properties": {
    "date:cessation_lower": "2014-11-06",
    "date:cessation_upper": "2014-11-06",
    "date:inception_lower": "2014-11-06",
    "date:inception_upper": "2014-11-06",
    "iso:country": "US",
    "sfomuseum:placetype": "tweet",
    "twitter:tweet": {
      "created": 1415234726,
      "created_at": "Thu Nov 06 00:45:26 +0000 2014",
      "display_text_range": [
        "0",
        "125"
      ],
      "edit_info": {
        "initial": {
          "editTweetIds": [
            "530158985676996609"
          ],
          "editableUntil": "2014-11-06T01:45:26.720Z",
          "editsRemaining": "5",
          "isEditEligible": true
        }
      },
      "entities": {
        "urls": [
          {
            "display_url": "instagram.com/p/vCeQjgRk_t/",
            "expanded_url": "http://instagram.com/p/vCeQjgRk_t/",
            "indices": [
              "103",
              "125"
            ],
            "url": "http://t.co/h2FnTLLDgB"
          }
        ]
      },
      "favorite_count": "0",
      "favorited": false,
      "full_text": "New art alert! Jim Melchert's \"Riven/River\" is on view in the new secure corridor between Terminals 1… http://t.co/h2FnTLLDgB",
      "id_str": "530158985676996609",
      "lang": "en",
      "possibly_sensitive": false,
      "retweet_count": "0",
      "retweeted": false,
      "source": "\u003ca href=\"http://instagram.com\" rel=\"nofollow\"\u003eInstagram\u003c/a\u003e",
      "truncated": false
    },
    "wof:name": "New art alert! Jim Melchert's \"Riven/River\" is on view in the new secure corridor between Terminals 1… http://t.co/h2FnTLLDgB",
    "wof:placetype": "custom",
    "wof:placetype_alt": [
      "tweet"
    ]
  },
  "geometry": {"coordinates":[-122.386166,37.616356],"type":"Point"}
}
