{
  "type": "Feature",
  "properties": {
    "sfomuseum:placetype": "tweet",
    "twitter:tweet": {
      "created": 1415234726,
      "created_at": "Thu Nov 06 00:45:26 +0000 2014",
      "display_text_range": [
        "0", 
        "125"
      ],
      "entities": {
        "urls": [
          {
            "display_url": "instagram.com/p/vCeQjgRk_t/",
            "expanded_url": "http://instagram.com/p/vCeQjgRk_t/",
            "indices": [
              "103", 
              "125"
            ],
            "url": "http://t.co/h2FnTLLDgB"
          }
        ]
      },
      "favorite_count": "0",
      "favorited": false,
      "full_text": "New art alert! Jim Melchert's \"Riven/River\" is on view in the new secure corridor between Terminals 1… http://t.co/h2FnTLLDgB",
      "id_str": "530158985676996609",
      "lang": "en",
      "possibly_sensitive": false,
      "retweet_count": "0",
      "retweeted": false,
      "source": "\u003ca href=\"http://instagram.com\" rel=\"nofollow\"\u003eInstagram\u003c/a\u003e",
      "truncated": false
    },
    "wof:name": "Twitter message #530158985676996609",
    "wof:placetype": "custom"
  },
  "geometry": {"coordinates":[-122.386166,37.616356],"type":"Point"}
}
