{
  "type": "Feature",
  "properties": {
    "sfomuseum:placetype": "tweet",
    "twitter:tweet": {
      "created": 1529715904,
      "created_at": "Sat Jun 23 01:05:04 +0000 2018",
      "display_text_range": [
        "0", 
        "294"
      ],
      "entities": {
        "hashtags": [
          {
            "indices": [
              "257", 
              "270"
            ],
            "text": "IntoTheEther"
          }
        ],
        "media": [
          {
            "display_url": "pic.twitter.com/G44uv9qdYc",
            "expanded_url": "https://twitter.com/SFOMuseum/status/1010327847746056198/photo/1",
            "id_str": "1010327844617113601",
            "indices": [
              "271", 
              "294"
            ],
            "media_url": "http://pbs.twimg.com/media/DgVn0l0W0AEuVtI.jpg",
            "media_url_https": "https://pbs.twimg.com/media/DgVn0l0W0AEuVtI.jpg",
            "sizes": {
              "large": {
                "h": "2000",
                "resize": "fit",
                "w": "1676"
              },
              "medium": {
                "h": "1200",
                "resize": "fit",
                "w": "1006"
              },
              "small": {
                "h": "680",
                "resize": "fit",
                "w": "570"
              },
              "thumb": {
                "h": "150",
                "resize": "crop",
                "w": "150"
              }
            },
            "type": "photo",
            "url": "https://t.co/G44uv9qdYc"
          }
        ]
      },
      "extended_entities": {
        "media": [
          {
            "display_url": "pic.twitter.com/G44uv9qdYc",
            "expanded_url": "https://twitter.com/SFOMuseum/status/1010327847746056198/photo/1",
            "id_str": "1010327844617113601",
            "indices": [
              "271", 
              "294"
            ],
            "media_url": "http://pbs.twimg.com/media/DgVn0l0W0AEuVtI.jpg",
            "media_url_https": "https://pbs.twimg.com/media/DgVn0l0W0AEuVtI.jpg",
            "sizes": {
              "large": {
                "h": "2000",
                "resize": "fit",
                "w": "1676"
              },
              "medium": {
                "h": "1200",
                "resize": "fit",
                "w": "1006"
              },
              "small": {
                "h": "680",
                "resize": "fit",
                "w": "570"
              },
              "thumb": {
                "h": "150",
                "resize": "crop",
                "w": "150"
              }
            },
            "type": "photo",
            "url": "https://t.co/G44uv9qdYc"
          }
        ]
      },
      "favorite_count": "2",
      "favorited": false,
      "full_text": "First created in France during the Age of Enlightenment by brothers Joseph-Michel and Jacques-Étienne Montgolfier between 1782–1783, the hot air balloon’s influence on society and culture, as well as the advancement of technology and science, was profound. #IntoTheEther https://t.co/G44uv9qdYc",
      "id_str": "1010327847746056198",
      "lang": "en",
      "possibly_sensitive": false,
      "retweet_count": "2",
      "retweeted": false,
      "source": "\u003ca href=\"https://www.hootsuite.com\" rel=\"nofollow\"\u003eHootsuite Inc.\u003c/a\u003e",
      "truncated": false
    },
    "wof:name": "Twitter message #1010327847746056198",
    "wof:placetype": "custom"
  },
  "geometry": {"coordinates":[-122.386166,37.616356],"type":"Point"}
}
