{
  "type": "Feature",
  "properties": {
    "sfomuseum:placetype": "tweet",
    "twitter:tweet": {
      "created": 1465326935,
      "created_at": "Tue Jun 07 19:15:35 +0000 2016",
      "display_text_range": [
        "0", 
        "140"
      ],
      "entities": {
        "user_mentions": [
          {
            "id_str": "396887508",
            "indices": [
              "3", 
              "14"
            ],
            "name": "World Air Photo",
            "screen_name": "planenut27"
          }
        ]
      },
      "favorite_count": "0",
      "favorited": false,
      "full_text": "RT @planenut27: Williams Field, a US airfield in Antarctica. It consists of two snow runways and serves McMurdo Station. https://t.co/y57HO…",
      "id_str": "740260937903398913",
      "lang": "en",
      "retweet_count": "0",
      "retweeted": false,
      "source": "\u003ca href=\"http://twitter.com\" rel=\"nofollow\"\u003eTwitter Web Client\u003c/a\u003e",
      "truncated": false
    },
    "wof:name": "Twitter message #740260937903398913",
    "wof:placetype": "custom"
  },
  "geometry": {"coordinates":[-122.386166,37.616356],"type":"Point"}
}
