{
  "type": "Feature",
  "properties": {
    "sfomuseum:placetype": "tweet",
    "twitter:tweet": {
      "created": 1522004421,
      "created_at": "Sun Mar 25 19:00:21 +0000 2018",
      "display_text_range": [
        "0", 
        "196"
      ],
      "entities": {
        "media": [
          {
            "display_url": "pic.twitter.com/5daowaYRxW",
            "expanded_url": "https://twitter.com/SFOMuseum/status/977983545024106496/photo/1",
            "id_str": "977983541333057536",
            "indices": [
              "173", 
              "196"
            ],
            "media_url": "http://pbs.twimg.com/media/DZJ-2WlV4AAqZqH.jpg",
            "media_url_https": "https://pbs.twimg.com/media/DZJ-2WlV4AAqZqH.jpg",
            "sizes": {
              "large": {
                "h": "1208",
                "resize": "fit",
                "w": "2000"
              },
              "medium": {
                "h": "725",
                "resize": "fit",
                "w": "1200"
              },
              "small": {
                "h": "411",
                "resize": "fit",
                "w": "680"
              },
              "thumb": {
                "h": "150",
                "resize": "crop",
                "w": "150"
              }
            },
            "type": "photo",
            "url": "https://t.co/5daowaYRxW"
          }
        ]
      },
      "extended_entities": {
        "media": [
          {
            "display_url": "pic.twitter.com/5daowaYRxW",
            "expanded_url": "https://twitter.com/SFOMuseum/status/977983545024106496/photo/1",
            "id_str": "977983541333057536",
            "indices": [
              "173", 
              "196"
            ],
            "media_url": "http://pbs.twimg.com/media/DZJ-2WlV4AAqZqH.jpg",
            "media_url_https": "https://pbs.twimg.com/media/DZJ-2WlV4AAqZqH.jpg",
            "sizes": {
              "large": {
                "h": "1208",
                "resize": "fit",
                "w": "2000"
              },
              "medium": {
                "h": "725",
                "resize": "fit",
                "w": "1200"
              },
              "small": {
                "h": "411",
                "resize": "fit",
                "w": "680"
              },
              "thumb": {
                "h": "150",
                "resize": "crop",
                "w": "150"
              }
            },
            "type": "photo",
            "url": "https://t.co/5daowaYRxW"
          }
        ]
      },
      "favorite_count": "11",
      "favorited": false,
      "full_text": "In 1954, the City of Miami converted the Dinner Key building into its City Hall, and the Pan American Airways winged-globe logo can still be found on the building's façade. https://t.co/5daowaYRxW",
      "id_str": "977983545024106496",
      "lang": "en",
      "possibly_sensitive": false,
      "retweet_count": "1",
      "retweeted": false,
      "source": "\u003ca href=\"http://www.hootsuite.com\" rel=\"nofollow\"\u003eHootsuite\u003c/a\u003e",
      "truncated": false
    },
    "wof:name": "Twitter message #977983545024106496",
    "wof:placetype": "custom"
  },
  "geometry": {"coordinates":[-122.386166,37.616356],"type":"Point"}
}
