{
  "type": "Feature",
  "properties": {
    "sfomuseum:placetype": "tweet",
    "twitter:tweet": {
      "created": 1509229614,
      "created_at": "Sat Oct 28 22:26:54 +0000 2017",
      "display_text_range": [
        "0", 
        "140"
      ],
      "entities": {
        "hashtags": [
          {
            "indices": [
              "18", 
              "28"
            ],
            "text": "Onthisday"
          }, 
          {
            "indices": [
              "48", 
              "54"
            ],
            "text": "PanAm"
          }
        ],
        "user_mentions": [
          {
            "id_str": "95746689",
            "indices": [
              "3", 
              "16"
            ],
            "name": "panamhistory",
            "screen_name": "panamhistory"
          }
        ]
      },
      "favorite_count": "0",
      "favorited": false,
      "full_text": "RT @panamhistory: #Onthisday October  28, 1927: #PanAm's 1st Daily Round Trip Air Mail Flight from Key West to Havana on a Fokker F-7. Phot…",
      "id_str": "924402119070720000",
      "lang": "en",
      "retweet_count": "0",
      "retweeted": false,
      "source": "\u003ca href=\"http://twitter.com\" rel=\"nofollow\"\u003eTwitter Web Client\u003c/a\u003e",
      "truncated": false
    },
    "wof:name": "Twitter message #924402119070720000",
    "wof:placetype": "custom"
  },
  "geometry": {"coordinates":[-122.386166,37.616356],"type":"Point"}
}
