{
  "type": "Feature",
  "properties": {
    "date:cessation_lower": "2017-09-13",
    "date:cessation_upper": "2017-09-13",
    "date:inception_lower": "2017-09-13",
    "date:inception_upper": "2017-09-13",
    "iso:country": "US",
    "sfomuseum:placetype": "tweet",
    "twitter:tweet": {
      "created": 1505331937,
      "created_at": "Wed Sep 13 19:45:37 +0000 2017",
      "display_text_range": [
        "0",
        "76"
      ],
      "edit_info": {
        "initial": {
          "editTweetIds": [
            "908054078281805824"
          ],
          "editableUntil": "2017-09-13T20:15:37.748Z",
          "editsRemaining": "5",
          "isEditEligible": true
        }
      },
      "entities": {
        "hashtags": [
          {
            "indices": [
              "40",
              "52"
            ],
            "text": "askacurator"
          }
        ],
        "urls": [
          {
            "display_url": "twitter.com/ProfMassa/stat…",
            "expanded_url": "https://twitter.com/ProfMassa/status/908053049947643907",
            "indices": [
              "53",
              "76"
            ],
            "url": "https://t.co/9iA9l2NUzu"
          }
        ],
        "user_mentions": [
          {
            "id_str": "1509947965158404099",
            "indices": [
              "3",
              "15"
            ],
            "name": "Ask a Curator",
            "screen_name": "AskaCurator"
          }
        ]
      },
      "favorite_count": "0",
      "favorited": false,
      "full_text": "RT @AskACurator: Good questions for all #askacurator https://t.co/9iA9l2NUzu",
      "id_str": "908054078281805824",
      "lang": "en",
      "possibly_sensitive": false,
      "retweet_count": "0",
      "retweeted": false,
      "source": "\u003ca href=\"http://twitter.com/download/iphone\" rel=\"nofollow\"\u003eTwitter for iPhone\u003c/a\u003e",
      "truncated": false
    },
    "wof:name": "RT @AskACurator: Good questions for all #askacurator https://t.co/9iA9l2NUzu",
    "wof:placetype": "custom"
  },
  "geometry": {"coordinates":[-122.386166,37.616356],"type":"Point"}
}
