{
  "type": "Feature",
  "properties": {
    "date:cessation_lower": "2014-04-22",
    "date:cessation_upper": "2014-04-22",
    "date:inception_lower": "2014-04-22",
    "date:inception_upper": "2014-04-22",
    "iso:country": "US",
    "sfomuseum:placetype": "tweet",
    "twitter:tweet": {
      "created": 1398124836,
      "created_at": "Tue Apr 22 00:00:36 +0000 2014",
      "display_text_range": [
        "0",
        "112"
      ],
      "edit_info": {
        "initial": {
          "editTweetIds": [
            "458394905828917248"
          ],
          "editableUntil": "2014-04-22T01:00:36.772Z",
          "editsRemaining": "5",
          "isEditEligible": true
        }
      },
      "entities": {
        "urls": [
          {
            "display_url": "instagram.com/p/nBXHr4DM0R/",
            "expanded_url": "http://instagram.com/p/nBXHr4DM0R/",
            "indices": [
              "90",
              "112"
            ],
            "url": "http://t.co/1TPV67brqs"
          }
        ],
        "user_mentions": [
          {
            "id_str": "91417438",
            "indices": [
              "3",
              "12"
            ],
            "name": "Dennis Brown",
            "screen_name": "bagger43"
          },
          {
            "id_str": "116329337",
            "indices": [
              "79",
              "89"
            ],
            "name": "SFO Museum",
            "screen_name": "SFOMuseum"
          }
        ]
      },
      "favorite_count": "0",
      "favorited": false,
      "full_text": "RT @bagger43: Pretty rad vintage Japanese toy showcase at SFO, put together by @sfomuseum http://t.co/1TPV67brqs",
      "id_str": "458394905828917248",
      "lang": "en",
      "possibly_sensitive": false,
      "retweet_count": "0",
      "retweeted": false,
      "source": "\u003ca href=\"http://www.hootsuite.com\" rel=\"nofollow\"\u003eHootsuite\u003c/a\u003e",
      "truncated": false
    },
    "wof:name": "RT @bagger43: Pretty rad vintage Japanese toy showcase at SFO, put together by @sfomuseum http://t.co/1TPV67brqs",
    "wof:placetype": "custom"
  },
  "geometry": {"coordinates":[-122.386166,37.616356],"type":"Point"}
}
