{
  "type": "Feature",
  "properties": {
    "date:cessation_lower": "2018-03-30",
    "date:cessation_upper": "2018-03-30",
    "date:inception_lower": "2018-03-30",
    "date:inception_upper": "2018-03-30",
    "iso:country": "US",
    "sfomuseum:placetype": "tweet",
    "twitter:tweet": {
      "created": 1522440881,
      "created_at": "Fri Mar 30 20:14:41 +0000 2018",
      "display_text_range": [
        "0",
        "88"
      ],
      "edit_info": {
        "initial": {
          "editTweetIds": [
            "979814189655982080"
          ],
          "editableUntil": "2018-03-30T20:44:41.538Z",
          "editsRemaining": "5",
          "isEditEligible": true
        }
      },
      "entities": {
        "urls": [
          {
            "display_url": "wired.trib.al/Tl2FspX",
            "expanded_url": "https://wired.trib.al/Tl2FspX",
            "indices": [
              "65",
              "88"
            ],
            "url": "https://t.co/o88t8WBf3d"
          }
        ],
        "user_mentions": [
          {
            "id_str": "1344951",
            "indices": [
              "3",
              "9"
            ],
            "name": "WIRED",
            "screen_name": "WIRED"
          }
        ]
      },
      "favorite_count": "0",
      "favorited": false,
      "full_text": "RT @WIRED: You don't fold paper planes like this guy—but you can https://t.co/o88t8WBf3d",
      "id_str": "979814189655982080",
      "lang": "en",
      "possibly_sensitive": false,
      "retweet_count": "0",
      "retweeted": false,
      "source": "\u003ca href=\"http://twitter.com\" rel=\"nofollow\"\u003eTwitter Web Client\u003c/a\u003e",
      "truncated": false
    },
    "wof:name": "RT @WIRED: You don't fold paper planes like this guy—but you can https://t.co/o88t8WBf3d",
    "wof:placetype": "custom"
  },
  "geometry": {"coordinates":[-122.386166,37.616356],"type":"Point"}
}
