{
  "type": "Feature",
  "properties": {
    "date:cessation_lower": "2021-10-21",
    "date:cessation_upper": "2021-10-21",
    "date:inception_lower": "2021-10-21",
    "date:inception_upper": "2021-10-21",
    "sfomuseum:placetype": "tweet",
    "twitter:tweet": {
      "created": 1634780178,
      "created_at": "Thu Oct 21 01:36:18 +0000 2021",
      "display_text_range": [
        "0",
        "192"
      ],
      "edit_info": {
        "initial": {
          "editTweetIds": [
            "1450999354307715074"
          ],
          "editableUntil": "2021-10-21T02:36:18.988Z",
          "editsRemaining": "5",
          "isEditEligible": true
        }
      },
      "entities": {
      },
      "favorite_count": "0",
      "favorited": false,
      "full_text": "📸 1/2:\npostcard: Finnair, McDonnell Douglas MD-11; 1990s\nGift of Thomas G. Dragges\n2015.166.0700\n\npostcard: World Airways, McDonnell Douglas MD-11; c. 2000\nGift of Mireille Boyd\n2004.052.022 a",
      "id_str": "1450999354307715074",
      "in_reply_to_screen_name": "SFOMuseum",
      "in_reply_to_status_id": "1450999352562884610",
      "in_reply_to_status_id_str": "1450999352562884610",
      "in_reply_to_user_id": "116329337",
      "in_reply_to_user_id_str": "116329337",
      "lang": "en",
      "retweet_count": "0",
      "retweeted": false,
      "source": "\u003ca href=\"http://twitter.com/download/iphone\" rel=\"nofollow\"\u003eTwitter for iPhone\u003c/a\u003e",
      "truncated": false
    },
    "wof:name": "📸 1/2:\npostcard: Finnair, McDonnell Douglas MD-11; 1990s\nGift of Thomas G. Dragges\n2015.166.0700\n\npostcard: World Airways, McDonnell Douglas MD-11; c. 2000\nGift of Mireille Boyd\n2004.052.022 a",
    "wof:placetype": "custom"
  },
  "geometry": {"coordinates":[-122.386166,37.616356],"type":"Point"}
}
