{
  "type": "Feature",
  "properties": {
    "sfomuseum:placetype": "tweet",
    "twitter:tweet": {
      "created": 1488486628,
      "created_at": "Thu Mar 02 20:30:28 +0000 2017",
      "display_text_range": [
        "0", 
        "140"
      ],
      "entities": {
        "urls": [
          {
            "display_url": "airspacemag.com/daily-planet/g…",
            "expanded_url": "http://www.airspacemag.com/daily-planet/getting-high-skies-180961700/",
            "indices": [
              "111", 
              "134"
            ],
            "url": "https://t.co/bWYp7LPfD7"
          }
        ],
        "user_mentions": [
          {
            "id_str": "171112947",
            "indices": [
              "3", 
              "15"
            ],
            "name": "Air \u0026 Space Magazine",
            "screen_name": "airspacemag"
          }
        ]
      },
      "favorite_count": "0",
      "favorited": false,
      "full_text": "RT @airspacemag: If you wanted a cocktail in-flight in 1950, better hope you weren't passing over a dry state. https://t.co/bWYp7LPfD7 http…",
      "id_str": "837399729189216256",
      "lang": "en",
      "possibly_sensitive": false,
      "retweet_count": "0",
      "retweeted": false,
      "source": "\u003ca href=\"http://twitter.com\" rel=\"nofollow\"\u003eTwitter Web Client\u003c/a\u003e",
      "truncated": false
    },
    "wof:name": "Twitter message #837399729189216256",
    "wof:placetype": "custom"
  },
  "geometry": {"coordinates":[-122.386166,37.616356],"type":"Point"}
}
