{
  "type": "Feature",
  "properties": {
    "date:cessation_lower": "2014-07-07",
    "date:cessation_upper": "2014-07-07",
    "date:inception_lower": "2014-07-07",
    "date:inception_upper": "2014-07-07",
    "iso:country": "US",
    "sfomuseum:placetype": "tweet",
    "twitter:hashtags": [
      "modelplanes",
      "aviation"
    ],
    "twitter:tweet": {
      "created": 1404766648,
      "created_at": "Mon Jul 07 20:57:28 +0000 2014",
      "display_text_range": [
        "0",
        "97"
      ],
      "edit_info": {
        "initial": {
          "editTweetIds": [
            "486252683729178624"
          ],
          "editableUntil": "2014-07-07T21:57:28.596Z",
          "editsRemaining": "5",
          "isEditEligible": true
        }
      },
      "entities": {
        "hashtags": [
          {
            "indices": [
              "52",
              "64"
            ],
            "text": "modelplanes"
          },
          {
            "indices": [
              "65",
              "74"
            ],
            "text": "aviation"
          }
        ],
        "urls": [
          {
            "display_url": "instagram.com/p/qKf-8jxkza/",
            "expanded_url": "http://instagram.com/p/qKf-8jxkza/",
            "indices": [
              "75",
              "97"
            ],
            "url": "http://t.co/A8HwYWCVPE"
          }
        ]
      },
      "favorite_count": "1",
      "favorited": false,
      "full_text": "Jet Age Models - on display in the Aviation Museum! #modelplanes #aviation http://t.co/A8HwYWCVPE",
      "id_str": "486252683729178624",
      "lang": "en",
      "possibly_sensitive": false,
      "retweet_count": "0",
      "retweeted": false,
      "source": "\u003ca href=\"http://instagram.com\" rel=\"nofollow\"\u003eInstagram\u003c/a\u003e",
      "truncated": false
    },
    "wof:name": "Jet Age Models - on display in the Aviation Museum! #modelplanes #aviation http://t.co/A8HwYWCVPE",
    "wof:placetype": "custom"
  },
  "geometry": {"coordinates":[-122.386166,37.616356],"type":"Point"}
}
