{
  "type": "Feature",
  "properties": {
    "sfomuseum:placetype": "tweet",
    "twitter:tweet": {
      "created": 1404766648,
      "created_at": "Mon Jul 07 20:57:28 +0000 2014",
      "display_text_range": [
        "0", 
        "97"
      ],
      "entities": {
        "hashtags": [
          {
            "indices": [
              "52", 
              "64"
            ],
            "text": "modelplanes"
          }, 
          {
            "indices": [
              "65", 
              "74"
            ],
            "text": "aviation"
          }
        ],
        "urls": [
          {
            "display_url": "instagram.com/p/qKf-8jxkza/",
            "expanded_url": "http://instagram.com/p/qKf-8jxkza/",
            "indices": [
              "75", 
              "97"
            ],
            "url": "http://t.co/A8HwYWCVPE"
          }
        ]
      },
      "favorite_count": "1",
      "favorited": false,
      "full_text": "Jet Age Models - on display in the Aviation Museum! #modelplanes #aviation http://t.co/A8HwYWCVPE",
      "id_str": "486252683729178624",
      "lang": "en",
      "possibly_sensitive": false,
      "retweet_count": "0",
      "retweeted": false,
      "source": "\u003ca href=\"http://instagram.com\" rel=\"nofollow\"\u003eInstagram\u003c/a\u003e",
      "truncated": false
    },
    "wof:name": "Twitter message #486252683729178624",
    "wof:placetype": "custom"
  },
  "geometry": {"coordinates":[-122.386166,37.616356],"type":"Point"}
}
