{
  "type": "Feature",
  "properties": {
    "sfomuseum:placetype": "tweet",
    "twitter:tweet": {
      "created": 1370908513,
      "created_at": "Mon Jun 10 23:55:13 +0000 2013",
      "display_text_range": [
        "0", 
        "122"
      ],
      "entities": {
        "urls": [
          {
            "display_url": "instagram.com/p/aZcZ-Qxkwa/",
            "expanded_url": "http://instagram.com/p/aZcZ-Qxkwa/",
            "indices": [
              "100", 
              "122"
            ],
            "url": "http://t.co/YspBSuEftV"
          }
        ]
      },
      "favorite_count": "0",
      "favorited": false,
      "full_text": "A scene of Edinburgh graces a painted windowpane from the dining room of the Clansman, a steamship… http://t.co/YspBSuEftV",
      "id_str": "344241373161074688",
      "lang": "en",
      "possibly_sensitive": false,
      "retweet_count": "0",
      "retweeted": false,
      "source": "\u003ca href=\"http://instagram.com\" rel=\"nofollow\"\u003eInstagram\u003c/a\u003e",
      "truncated": false
    },
    "wof:name": "Twitter message #344241373161074688",
    "wof:placetype": "custom"
  },
  "geometry": {"coordinates":[-122.386166,37.616356],"type":"Point"}
}
