{
  "type": "Feature",
  "properties": {
    "date:cessation_lower": "2013-06-10",
    "date:cessation_upper": "2013-06-10",
    "date:inception_lower": "2013-06-10",
    "date:inception_upper": "2013-06-10",
    "iso:country": "US",
    "sfomuseum:placetype": "tweet",
    "twitter:tweet": {
      "created": 1370908513,
      "created_at": "Mon Jun 10 23:55:13 +0000 2013",
      "display_text_range": [
        "0",
        "122"
      ],
      "edit_info": {
        "initial": {
          "editTweetIds": [
            "344241373161074688"
          ],
          "editableUntil": "2013-06-11T00:25:13.714Z",
          "editsRemaining": "5",
          "isEditEligible": true
        }
      },
      "entities": {
        "urls": [
          {
            "display_url": "instagram.com/p/aZcZ-Qxkwa/",
            "expanded_url": "http://instagram.com/p/aZcZ-Qxkwa/",
            "indices": [
              "100",
              "122"
            ],
            "url": "http://t.co/YspBSuEftV"
          }
        ]
      },
      "favorite_count": "0",
      "favorited": false,
      "full_text": "A scene of Edinburgh graces a painted windowpane from the dining room of the Clansman, a steamship… http://t.co/YspBSuEftV",
      "id_str": "344241373161074688",
      "lang": "en",
      "possibly_sensitive": false,
      "retweet_count": "0",
      "retweeted": false,
      "source": "\u003ca href=\"http://instagram.com\" rel=\"nofollow\"\u003eInstagram\u003c/a\u003e",
      "truncated": false
    },
    "wof:name": "A scene of Edinburgh graces a painted windowpane from the dining room of the Clansman, a steamship… http://t.co/YspBSuEftV",
    "wof:placetype": "custom"
  },
  "geometry": {"coordinates":[-122.386166,37.616356],"type":"Point"}
}
