{
  "type": "Feature",
  "properties": {
    "date:cessation_lower": "2020-11-25",
    "date:cessation_upper": "2020-11-25",
    "date:inception_lower": "2020-11-25",
    "date:inception_upper": "2020-11-25",
    "sfomuseum:placetype": "tweet",
    "twitter:tweet": {
      "created": 1606339879,
      "created_at": "Wed Nov 25 21:31:19 +0000 2020",
      "display_text_range": [
        "0",
        "139"
      ],
      "edit_info": {
        "initial": {
          "editTweetIds": [
            "1331712093133950978"
          ],
          "editableUntil": "2020-11-25T22:01:19.674Z",
          "editsRemaining": "5",
          "isEditEligible": true
        }
      },
      "entities": {
        "user_mentions": [
          {
            "id_str": "14848513",
            "indices": [
              "3",
              "15"
            ],
            "name": "National Air and Space Museum",
            "screen_name": "airandspace"
          }
        ]
      },
      "favorite_count": "0",
      "favorited": false,
      "full_text": "RT @airandspace: The Curtiss JN-4D “Jenny” is almost synonymous with American aviation in the 1920s. Its affordability, ease of operation,…",
      "id_str": "1331712093133950978",
      "lang": "en",
      "retweet_count": "0",
      "retweeted": false,
      "source": "\u003ca href=\"https://www.hootsuite.com\" rel=\"nofollow\"\u003eHootsuite Inc.\u003c/a\u003e",
      "truncated": false
    },
    "wof:name": "RT @airandspace: The Curtiss JN-4D “Jenny” is almost synonymous with American aviation in the 1920s. Its affordability, ease of operation,…",
    "wof:placetype": "custom"
  },
  "geometry": {"coordinates":[-122.386166,37.616356],"type":"Point"}
}
