{
  "type": "Feature",
  "properties": {
    "sfomuseum:placetype": "tweet",
    "twitter:tweet": {
      "created": 1399074606,
      "created_at": "Fri May 02 23:50:06 +0000 2014",
      "display_text_range": [
        "0", 
        "112"
      ],
      "entities": {
        "hashtags": [
          {
            "indices": [
              "105", 
              "112"
            ],
            "text": "avgeek"
          }
        ],
        "urls": [
          {
            "display_url": "ow.ly/wqNvc",
            "expanded_url": "http://ow.ly/wqNvc",
            "indices": [
              "82", 
              "104"
            ],
            "url": "http://t.co/v5Z5JY5zPY"
          }
        ]
      },
      "favorite_count": "2",
      "favorited": false,
      "full_text": "Mexicana de Aviación S.A.'s luggage label from the mid-1930s is fit to be framed! http://t.co/v5Z5JY5zPY #avgeek",
      "id_str": "462378527598600193",
      "lang": "es",
      "possibly_sensitive": false,
      "retweet_count": "2",
      "retweeted": false,
      "source": "\u003ca href=\"http://www.hootsuite.com\" rel=\"nofollow\"\u003eHootsuite\u003c/a\u003e",
      "truncated": false
    },
    "wof:name": "Twitter message #462378527598600193",
    "wof:placetype": "custom"
  },
  "geometry": {"coordinates":[-122.386166,37.616356],"type":"Point"}
}
