{
  "type": "Feature",
  "properties": {
    "date:cessation_lower": "2011-10-05",
    "date:cessation_upper": "2011-10-05",
    "date:inception_lower": "2011-10-05",
    "date:inception_upper": "2011-10-05",
    "iso:country": "US",
    "sfomuseum:placetype": "tweet",
    "twitter:tweet": {
      "created": 1317842102,
      "created_at": "Wed Oct 05 19:15:02 +0000 2011",
      "display_text_range": [
        "0",
        "135"
      ],
      "edit_info": {
        "initial": {
          "editTweetIds": [
            "121664713548513280"
          ],
          "editableUntil": "2011-10-05T19:45:02.788Z",
          "editsRemaining": "5",
          "isEditEligible": true
        }
      },
      "entities": {
        "user_mentions": [
          {
            "id_str": "37270635",
            "indices": [
              "11",
              "21"
            ],
            "name": "linda_her",
            "screen_name": "linda_her"
          }
        ]
      },
      "favorite_count": "0",
      "favorited": false,
      "full_text": "Thanks! RT @linda_her: SFO has one of the best displays I have seen. TVs throughout its history, everything from TV dinners to betamax.",
      "id_str": "121664713548513280",
      "lang": "en",
      "retweet_count": "0",
      "retweeted": false,
      "source": "\u003ca href=\"http://www.hootsuite.com\" rel=\"nofollow\"\u003eHootsuite\u003c/a\u003e",
      "truncated": false
    },
    "wof:name": "Thanks! RT @linda_her: SFO has one of the best displays I have seen. TVs throughout its history, everything from TV dinners to betamax.",
    "wof:placetype": "custom"
  },
  "geometry": {"coordinates":[-122.386166,37.616356],"type":"Point"}
}
