{
  "type": "Feature",
  "properties": {
    "sfomuseum:placetype": "tweet",
    "twitter:tweet": {
      "created": 1437523251,
      "created_at": "Wed Jul 22 00:00:51 +0000 2015",
      "display_text_range": [
        "0", 
        "70"
      ],
      "entities": {
        "hashtags": [
          {
            "indices": [
              "56", 
              "70"
            ],
            "text": "TravelTuesday"
          }
        ]
      },
      "favorite_count": "1",
      "favorited": false,
      "full_text": "Where would you go on this gloriously sunny day at SFO? #TravelTuesday",
      "id_str": "623643834308800512",
      "lang": "en",
      "retweet_count": "0",
      "retweeted": false,
      "source": "\u003ca href=\"http://www.hootsuite.com\" rel=\"nofollow\"\u003eHootsuite\u003c/a\u003e",
      "truncated": false
    },
    "wof:name": "Twitter message #623643834308800512",
    "wof:placetype": "custom"
  },
  "geometry": {"coordinates":[-122.386166,37.616356],"type":"Point"}
}
