{
  "type": "Feature",
  "properties": {
    "date:cessation_lower":"2015-07-21",
    "date:cessation_upper":"2015-07-21",
    "date:inception_lower":"2015-07-21",
    "date:inception_upper":"2015-07-21",
    "iso:country":"US",
    "sfomuseum:placetype":"tweet",
    "twitter:tweet":{
        "created":1437523251,
        "created_at":"Wed Jul 22 00:00:51 +0000 2015",
        "display_text_range":[
            "0",
            "70"
        ],
        "entities":{
            "hashtags":[
                {
                    "indices":[
                        "56",
                        "70"
                    ],
                    "text":"TravelTuesday"
                }
            ]
        },
        "favorite_count":"1",
        "favorited":false,
        "full_text":"Where would you go on this gloriously sunny day at SFO? #TravelTuesday",
        "id_str":"623643834308800512",
        "lang":"en",
        "retweet_count":"0",
        "retweeted":false,
        "source":"<a href=\"http://www.hootsuite.com\" rel=\"nofollow\">Hootsuite</a>",
        "truncated":false
    },
    "wof:name":"Where would you go on this gloriously sunny day at SFO? #TravelTuesday",
    "wof:placetype":"custom"
},
  "geometry": {"coordinates":[-122.386166,37.616356],"type":"Point"}
}