{
  "type": "Feature",
  "properties": {
    "date:cessation_lower":"2014-03-18",
    "date:cessation_upper":"2014-03-18",
    "date:inception_lower":"2014-03-18",
    "date:inception_upper":"2014-03-18",
    "iso:country":"US",
    "sfomuseum:placetype":"tweet",
    "twitter:tweet":{
        "created":1395164150,
        "created_at":"Tue Mar 18 17:35:50 +0000 2014",
        "display_text_range":[
            "0",
            "134"
        ],
        "entities":{
            "urls":[
                {
                    "display_url":"ow.ly/uIuA1",
                    "expanded_url":"http://ow.ly/uIuA1",
                    "indices":[
                        "44",
                        "66"
                    ],
                    "url":"http://t.co/anf4n69KFr"
                },
                {
                    "display_url":"ow.ly/uIuDG",
                    "expanded_url":"http://ow.ly/uIuDG",
                    "indices":[
                        "112",
                        "134"
                    ],
                    "url":"http://t.co/QVmZ637rqD"
                }
            ]
        },
        "favorite_count":"0",
        "favorited":false,
        "full_text":"After 45 years, Goodyear has a new airship! http://t.co/anf4n69KFr Learn more about dirigibles via our exhibit: http://t.co/QVmZ637rqD",
        "id_str":"445976886083342336",
        "lang":"en",
        "possibly_sensitive":false,
        "retweet_count":"0",
        "retweeted":false,
        "source":"<a href=\"http://www.hootsuite.com\" rel=\"nofollow\">Hootsuite</a>",
        "truncated":false
    },
    "wof:name":"After 45 years, Goodyear has a new airship! http://t.co/anf4n69KFr Learn more about dirigibles via our exhibit: http://t.co/QVmZ637rqD",
    "wof:placetype":"custom"
},
  "geometry": {"coordinates":[-122.386166,37.616356],"type":"Point"}
}