{
  "type": "Feature",
  "properties": {
    "sfomuseum:placetype": "tweet",
    "twitter:tweet": {
      "created": 1499475616,
      "created_at": "Sat Jul 08 01:00:16 +0000 2017",
      "display_text_range": [
        "0", 
        "164"
      ],
      "entities": {
        "hashtags": [
          {
            "indices": [
              "126", 
              "140"
            ],
            "text": "thetypewriter"
          }
        ],
        "media": [
          {
            "display_url": "pic.twitter.com/RZ8weh5Lqy",
            "expanded_url": "https://twitter.com/SFOMuseum/status/883490888726532096/photo/1",
            "id_str": "883490884880302080",
            "indices": [
              "141", 
              "164"
            ],
            "media_url": "http://pbs.twimg.com/media/DELKR2OWAAAphv1.jpg",
            "media_url_https": "https://pbs.twimg.com/media/DELKR2OWAAAphv1.jpg",
            "sizes": {
              "large": {
                "h": "1267",
                "resize": "fit",
                "w": "2000"
              },
              "medium": {
                "h": "760",
                "resize": "fit",
                "w": "1200"
              },
              "small": {
                "h": "431",
                "resize": "fit",
                "w": "680"
              },
              "thumb": {
                "h": "150",
                "resize": "crop",
                "w": "150"
              }
            },
            "type": "photo",
            "url": "https://t.co/RZ8weh5Lqy"
          }
        ]
      },
      "extended_entities": {
        "media": [
          {
            "display_url": "pic.twitter.com/RZ8weh5Lqy",
            "expanded_url": "https://twitter.com/SFOMuseum/status/883490888726532096/photo/1",
            "id_str": "883490884880302080",
            "indices": [
              "141", 
              "164"
            ],
            "media_url": "http://pbs.twimg.com/media/DELKR2OWAAAphv1.jpg",
            "media_url_https": "https://pbs.twimg.com/media/DELKR2OWAAAphv1.jpg",
            "sizes": {
              "large": {
                "h": "1267",
                "resize": "fit",
                "w": "2000"
              },
              "medium": {
                "h": "760",
                "resize": "fit",
                "w": "1200"
              },
              "small": {
                "h": "431",
                "resize": "fit",
                "w": "680"
              },
              "thumb": {
                "h": "150",
                "resize": "crop",
                "w": "150"
              }
            },
            "type": "photo",
            "url": "https://t.co/RZ8weh5Lqy"
          }
        ]
      },
      "favorite_count": "9",
      "favorited": false,
      "full_text": "For the 1915 Panama-Pacific International Exposition, Underwood produced a giant working typewriter, 1728x the original size. #thetypewriter https://t.co/RZ8weh5Lqy",
      "id_str": "883490888726532096",
      "lang": "en",
      "possibly_sensitive": false,
      "retweet_count": "4",
      "retweeted": false,
      "source": "\u003ca href=\"http://www.hootsuite.com\" rel=\"nofollow\"\u003eHootsuite\u003c/a\u003e",
      "truncated": false
    },
    "wof:name": "Twitter message #883490888726532096",
    "wof:placetype": "custom"
  },
  "geometry": {"coordinates":[-122.386166,37.616356],"type":"Point"}
}
