{
  "type": "Feature",
  "properties": {
    "date:cessation_lower": "2022-06-07",
    "date:cessation_upper": "2022-06-07",
    "date:inception_lower": "2022-06-07",
    "date:inception_upper": "2022-06-07",
    "sfomuseum:placetype": "tweet",
    "twitter:tweet": {
      "created": 1654628172,
      "created_at": "Tue Jun 07 18:56:12 +0000 2022",
      "display_text_range": [
        "0",
        "139"
      ],
      "edit_info": {
        "initial": {
          "editTweetIds": [
            "1534247873847517184"
          ],
          "editableUntil": "2022-06-07T19:26:12.729Z",
          "editsRemaining": "5",
          "isEditEligible": false
        }
      },
      "entities": {
        "user_mentions": [
          {
            "id_str": "127575007",
            "indices": [
              "3",
              "19"
            ],
            "name": "thisisaaronland",
            "screen_name": "thisisaaronland"
          },
          {
            "id_str": "116329337",
            "indices": [
              "58",
              "68"
            ],
            "name": "SFO Museum",
            "screen_name": "SFOMuseum"
          }
        ]
      },
      "favorite_count": "0",
      "favorited": false,
      "full_text": "RT @thisisaaronland: did you know that as of this morning @sfomuseum has published open data records for over 6 million flights in and out…",
      "id_str": "1534247873847517184",
      "lang": "en",
      "retweet_count": "0",
      "retweeted": false,
      "source": "\u003ca href=\"https://mobile.twitter.com\" rel=\"nofollow\"\u003eTwitter Web App\u003c/a\u003e",
      "truncated": false
    },
    "twitter:user_mentions": [
      "thisisaaronland",
      "SFOMuseum"
    ],
    "wof:name": "RT @thisisaaronland: did you know that as of this morning @sfomuseum has published open data records for over 6 million flights in and out…",
    "wof:placetype": "custom"
  },
  "geometry": {"coordinates":[-122.386166,37.616356],"type":"Point"}
}
