{
  "type": "Feature",
  "properties": {
    "sfomuseum:placetype": "tweet",
    "twitter:tweet": {
      "created": 1469234438,
      "created_at": "Sat Jul 23 00:40:38 +0000 2016",
      "display_text_range": [
        "0", 
        "144"
      ],
      "entities": {
        "hashtags": [
          {
            "indices": [
              "104", 
              "120"
            ],
            "text": "FashionInFlight"
          }
        ],
        "media": [
          {
            "display_url": "pic.twitter.com/ACXMe4nxGp",
            "expanded_url": "https://twitter.com/SFOMuseum/status/756650193588588544/photo/1",
            "id_str": "756634476709490688",
            "indices": [
              "121", 
              "144"
            ],
            "media_url": "http://pbs.twimg.com/media/CoAbDDkVMAAoXGq.jpg",
            "media_url_https": "https://pbs.twimg.com/media/CoAbDDkVMAAoXGq.jpg",
            "sizes": {
              "large": {
                "h": "2000",
                "resize": "fit",
                "w": "1333"
              },
              "medium": {
                "h": "1200",
                "resize": "fit",
                "w": "800"
              },
              "small": {
                "h": "680",
                "resize": "fit",
                "w": "453"
              },
              "thumb": {
                "h": "150",
                "resize": "crop",
                "w": "150"
              }
            },
            "type": "photo",
            "url": "https://t.co/ACXMe4nxGp"
          }
        ]
      },
      "extended_entities": {
        "media": [
          {
            "display_url": "pic.twitter.com/ACXMe4nxGp",
            "expanded_url": "https://twitter.com/SFOMuseum/status/756650193588588544/photo/1",
            "id_str": "756634476709490688",
            "indices": [
              "121", 
              "144"
            ],
            "media_url": "http://pbs.twimg.com/media/CoAbDDkVMAAoXGq.jpg",
            "media_url_https": "https://pbs.twimg.com/media/CoAbDDkVMAAoXGq.jpg",
            "sizes": {
              "large": {
                "h": "2000",
                "resize": "fit",
                "w": "1333"
              },
              "medium": {
                "h": "1200",
                "resize": "fit",
                "w": "800"
              },
              "small": {
                "h": "680",
                "resize": "fit",
                "w": "453"
              },
              "thumb": {
                "h": "150",
                "resize": "crop",
                "w": "150"
              }
            },
            "type": "photo",
            "url": "https://t.co/ACXMe4nxGp"
          }
        ]
      },
      "favorite_count": "2",
      "favorited": false,
      "full_text": "The 1970 Continental uniform was designed to project the airline’s identity \u0026amp; a sporty casual look. #FashionInFlight https://t.co/ACXMe4nxGp",
      "id_str": "756650193588588544",
      "lang": "en",
      "possibly_sensitive": false,
      "retweet_count": "1",
      "retweeted": false,
      "source": "\u003ca href=\"http://dashboard.twitter.com\" rel=\"nofollow\"\u003eTwitter Dashboard for iPhone\u003c/a\u003e",
      "truncated": false
    },
    "wof:name": "Twitter message #756650193588588544",
    "wof:placetype": "custom"
  },
  "geometry": {"coordinates":[-122.386166,37.616356],"type":"Point"}
}
