{
  "type": "Feature",
  "properties": {
    "sfomuseum:placetype": "tweet",
    "twitter:tweet": {
      "created": 1396632795,
      "created_at": "Fri Apr 04 17:33:15 +0000 2014",
      "display_text_range": [
        "0", 
        "122"
      ],
      "entities": {
        "hashtags": [
          {
            "indices": [
              "95", 
              "99"
            ],
            "text": "SFO"
          }
        ],
        "urls": [
          {
            "display_url": "vine.co/v/MiAVVxU6xH5",
            "expanded_url": "http://vine.co/v/MiAVVxU6xH5",
            "indices": [
              "100", 
              "122"
            ],
            "url": "http://t.co/u0OeyB8sP5"
          }
        ],
        "user_mentions": [
          {
            "id_str": "6782762",
            "indices": [
              "70", 
              "74"
            ],
            "name": "Ali Alexander 🟧 ⭐️⭐️⭐️",
            "screen_name": "ali"
          }
        ]
      },
      "favorite_count": "0",
      "favorited": false,
      "full_text": "By Eric Staller, the genius behind the bubbleboat and lightmobile. RT @ali: Pretty cool art at #SFO http://t.co/u0OeyB8sP5",
      "id_str": "452136832390922240",
      "lang": "en",
      "possibly_sensitive": false,
      "retweet_count": "1",
      "retweeted": false,
      "source": "\u003ca href=\"http://www.hootsuite.com\" rel=\"nofollow\"\u003eHootsuite\u003c/a\u003e",
      "truncated": false
    },
    "wof:name": "Twitter message #452136832390922240",
    "wof:placetype": "custom"
  },
  "geometry": {"coordinates":[-122.386166,37.616356],"type":"Point"}
}
