{
  "type": "Feature",
  "properties": {
    "sfomuseum:placetype": "tweet",
    "twitter:tweet": {
      "created": 1420758020,
      "created_at": "Thu Jan 08 23:00:20 +0000 2015",
      "display_text_range": [
        "0", 
        "123"
      ],
      "entities": {
        "urls": [
          {
            "display_url": "instagram.com/p/xnFGqMRkwU/",
            "expanded_url": "http://instagram.com/p/xnFGqMRkwU/",
            "indices": [
              "101", 
              "123"
            ],
            "url": "http://t.co/5rRB4DVybA"
          }
        ]
      },
      "favorite_count": "0",
      "favorited": false,
      "full_text": "Installation is underway in the International Terminal for our newest exhibit, Egyptian Revival: An… http://t.co/5rRB4DVybA",
      "id_str": "553325356904878081",
      "lang": "en",
      "possibly_sensitive": false,
      "retweet_count": "0",
      "retweeted": false,
      "source": "\u003ca href=\"http://instagram.com\" rel=\"nofollow\"\u003eInstagram\u003c/a\u003e",
      "truncated": false
    },
    "wof:name": "Twitter message #553325356904878081",
    "wof:placetype": "custom"
  },
  "geometry": {"coordinates":[-122.386166,37.616356],"type":"Point"}
}
