{
  "type": "Feature",
  "properties": {
    "sfomuseum:placetype": "tweet",
    "twitter:tweet": {
      "created": 1360692748,
      "created_at": "Tue Feb 12 18:12:28 +0000 2013",
      "display_text_range": [
        "0", 
        "140"
      ],
      "entities": {
        "urls": [
          {
            "display_url": "bit.ly/WH0dYk",
            "expanded_url": "http://bit.ly/WH0dYk",
            "indices": [
              "120", 
              "140"
            ],
            "url": "http://t.co/Gb0R6sUw"
          }
        ],
        "user_mentions": [
          {
            "id_str": "10716292",
            "indices": [
              "76", 
              "90"
            ],
            "name": "Exploratorium",
            "screen_name": "exploratorium"
          }
        ]
      },
      "favorite_count": "0",
      "favorited": false,
      "full_text": "We have new photo exhibits! Passengers in T1 can check out the evolution of @exploratorium! Not traveling? View online: http://t.co/Gb0R6sUw",
      "id_str": "301393347879264256",
      "lang": "en",
      "possibly_sensitive": false,
      "retweet_count": "1",
      "retweeted": false,
      "source": "\u003ca href=\"https://about.twitter.com/products/tweetdeck\" rel=\"nofollow\"\u003eTweetDeck\u003c/a\u003e",
      "truncated": false
    },
    "wof:name": "Twitter message #301393347879264256",
    "wof:placetype": "custom"
  },
  "geometry": {"coordinates":[-122.386166,37.616356],"type":"Point"}
}
