{
  "type": "Feature",
  "properties": {
    "sfomuseum:placetype": "tweet",
    "twitter:tweet": {
      "created": 1330969945,
      "created_at": "Mon Mar 05 17:52:25 +0000 2012",
      "display_text_range": [
        "0", 
        "138"
      ],
      "entities": {
        "hashtags": [
          {
            "indices": [
              "76", 
              "80"
            ],
            "text": "SFO"
          }, 
          {
            "indices": [
              "103", 
              "107"
            ],
            "text": "BOS"
          }
        ],
        "urls": [
          {
            "display_url": "bit.ly/n4Gq9Y",
            "expanded_url": "http://bit.ly/n4Gq9Y",
            "indices": [
              "41", 
              "61"
            ],
            "url": "http://t.co/rTKJxGjC"
          }
        ],
        "user_mentions": [
          {
            "id_str": "237133730",
            "indices": [
              "65", 
              "74"
            ],
            "name": "Ryan Ma",
            "screen_name": "ryanlyma"
          }
        ]
      },
      "favorite_count": "0",
      "favorited": false,
      "full_text": "And its own museum? And free audio tour? http://t.co/rTKJxGjC :) @ryanlyma: #SFO T2 is soo artsy. Wish #BOS had an art commission as well.",
      "id_str": "176726876658728960",
      "lang": "en",
      "possibly_sensitive": false,
      "retweet_count": "0",
      "retweeted": false,
      "source": "\u003ca href=\"https://about.twitter.com/products/tweetdeck\" rel=\"nofollow\"\u003eTweetDeck\u003c/a\u003e",
      "truncated": false
    },
    "wof:name": "Twitter message #176726876658728960",
    "wof:placetype": "custom"
  },
  "geometry": {"coordinates":[-122.386166,37.616356],"type":"Point"}
}
