{
  "type": "Feature",
  "properties": {
    "sfomuseum:placetype": "tweet",
    "twitter:tweet": {
      "created": 1400101365,
      "created_at": "Wed May 14 21:02:45 +0000 2014",
      "display_text_range": [
        "0", 
        "120"
      ],
      "entities": {
        "urls": [
          {
            "display_url": "instagram.com/p/n_cawkxkyO/",
            "expanded_url": "http://instagram.com/p/n_cawkxkyO/",
            "indices": [
              "98", 
              "120"
            ],
            "url": "http://t.co/ur8XGJk955"
          }
        ]
      },
      "favorite_count": "0",
      "favorited": false,
      "full_text": "'Translated Vases' by Korean artist Yeesookyung anchor Dual Natures in Ceramics, currently being… http://t.co/ur8XGJk955",
      "id_str": "466685067821981696",
      "lang": "en",
      "possibly_sensitive": false,
      "retweet_count": "0",
      "retweeted": false,
      "source": "\u003ca href=\"http://instagram.com\" rel=\"nofollow\"\u003eInstagram\u003c/a\u003e",
      "truncated": false
    },
    "wof:name": "Twitter message #466685067821981696",
    "wof:placetype": "custom"
  },
  "geometry": {"coordinates":[-122.386166,37.616356],"type":"Point"}
}
