{
  "type": "Feature",
  "properties": {
    "sfomuseum:placetype": "tweet",
    "twitter:tweet": {
      "created": 1355862340,
      "created_at": "Tue Dec 18 20:25:40 +0000 2012",
      "display_text_range": [
        "0", 
        "144"
      ],
      "entities": {
        "urls": [
          {
            "display_url": "bit.ly/Y4G64S",
            "expanded_url": "http://bit.ly/Y4G64S",
            "indices": [
              "124", 
              "144"
            ],
            "url": "http://t.co/UwZXBdVm"
          }
        ]
      },
      "favorite_count": "0",
      "favorited": false,
      "full_text": "In Fiji, headrests of high-ranking people can acquire strong powers \u0026amp; may not be used by anyone other than their owner. http://t.co/UwZXBdVm",
      "id_str": "281133150229372928",
      "lang": "en",
      "possibly_sensitive": false,
      "retweet_count": "1",
      "retweeted": false,
      "source": "\u003ca href=\"https://about.twitter.com/products/tweetdeck\" rel=\"nofollow\"\u003eTweetDeck\u003c/a\u003e",
      "truncated": false
    },
    "wof:name": "Twitter message #281133150229372928",
    "wof:placetype": "custom"
  },
  "geometry": {"coordinates":[-122.386166,37.616356],"type":"Point"}
}
