{
  "type": "Feature",
  "properties": {
    "date:cessation_lower": "2024-02-09",
    "date:cessation_upper": "2024-02-09",
    "date:inception_lower": "2024-02-09",
    "date:inception_upper": "2024-02-09",
    "sfomuseum:placetype": "tweet",
    "twitter:tweet": {
      "created": 1707442038,
      "created_at": "Fri Feb 09 01:27:18 +0000 2024",
      "display_text_range": [
        "0",
        "110"
      ],
      "edit_info": {
        "initial": {
          "editTweetIds": [
            "1755765280364773618"
          ],
          "editableUntil": "2024-02-09T02:27:18.000Z",
          "editsRemaining": "5",
          "isEditEligible": false
        }
      },
      "entities": {
        "hashtags": [
          {
            "indices": [
              "100",
              "110"
            ],
            "text": "52Posters"
          }
        ],
        "urls": [
          {
            "display_url": "collection.sfomuseum.org/objects/177943…",
            "expanded_url": "https://collection.sfomuseum.org/objects/1779436261/",
            "indices": [
              "74",
              "97"
            ],
            "url": "https://t.co/P2WRQRudYu"
          }
        ]
      },
      "favorite_count": "1",
      "favorited": false,
      "full_text": "poster: Japan Air Lines, Japan; 1980s\nGift of Japan Airlines\n2015.030.045\nhttps://t.co/P2WRQRudYu\n \n#52Posters",
      "id_str": "1755765280364773618",
      "in_reply_to_screen_name": "SFOMuseum",
      "in_reply_to_status_id": "1755765278158573630",
      "in_reply_to_status_id_str": "1755765278158573630",
      "in_reply_to_user_id": "116329337",
      "in_reply_to_user_id_str": "116329337",
      "lang": "en",
      "possibly_sensitive": false,
      "retweet_count": "0",
      "retweeted": false,
      "source": "\u003ca href=\"https://mobile.twitter.com\" rel=\"nofollow\"\u003eTwitter Web App\u003c/a\u003e",
      "truncated": false
    },
    "wof:name": "poster: Japan Air Lines, Japan; 1980s\nGift of Japan Airlines\n2015.030.045\nhttps://t.co/P2WRQRudYu\n \n#52Posters",
    "wof:placetype": "custom",
    "wof:placetype_alt": [
      "tweet"
    ]
  },
  "geometry": {"coordinates":[-122.386166,37.616356],"type":"Point"}
}
