{
  "type": "Feature",
  "properties": {
    "sfomuseum:placetype": "tweet",
    "twitter:tweet": {
      "created": 1368465737,
      "created_at": "Mon May 13 17:22:17 +0000 2013",
      "display_text_range": [
        "0", 
        "118"
      ],
      "entities": {
        "urls": [
          {
            "display_url": "ow.ly/kYUYH",
            "expanded_url": "http://ow.ly/kYUYH",
            "indices": [
              "96", 
              "118"
            ],
            "url": "http://t.co/xWw85WuDpr"
          }
        ]
      },
      "favorite_count": "0",
      "favorited": false,
      "full_text": "Richard Branson as an AirAsia flight attendant. Now that would be a uniform for the collection. http://t.co/xWw85WuDpr",
      "id_str": "333995628889784321",
      "lang": "en",
      "possibly_sensitive": false,
      "retweet_count": "0",
      "retweeted": false,
      "source": "\u003ca href=\"http://www.hootsuite.com\" rel=\"nofollow\"\u003eHootsuite\u003c/a\u003e",
      "truncated": false
    },
    "wof:name": "Twitter message #333995628889784321",
    "wof:placetype": "custom"
  },
  "geometry": {"coordinates":[-122.386166,37.616356],"type":"Point"}
}
