{
  "type": "Feature",
  "properties": {
    "sfomuseum:placetype": "tweet",
    "twitter:tweet": {
      "created": 1452140618,
      "created_at": "Thu Jan 07 04:23:38 +0000 2016",
      "display_text_range": [
        "0", 
        "136"
      ],
      "entities": {
        "media": [
          {
            "display_url": "pic.twitter.com/AcUBFesCCY",
            "expanded_url": "https://twitter.com/SFOMuseum/status/684953516012482560/photo/1",
            "id_str": "684953501076553728",
            "indices": [
              "113", 
              "136"
            ],
            "media_url": "http://pbs.twimg.com/media/CYFxlIdUAAAr8ez.jpg",
            "media_url_https": "https://pbs.twimg.com/media/CYFxlIdUAAAr8ez.jpg",
            "sizes": {
              "large": {
                "h": "682",
                "resize": "fit",
                "w": "1024"
              },
              "medium": {
                "h": "682",
                "resize": "fit",
                "w": "1024"
              },
              "small": {
                "h": "453",
                "resize": "fit",
                "w": "680"
              },
              "thumb": {
                "h": "150",
                "resize": "crop",
                "w": "150"
              }
            },
            "type": "photo",
            "url": "https://t.co/AcUBFesCCY"
          }
        ]
      },
      "extended_entities": {
        "media": [
          {
            "display_url": "pic.twitter.com/AcUBFesCCY",
            "expanded_url": "https://twitter.com/SFOMuseum/status/684953516012482560/photo/1",
            "id_str": "684953501076553728",
            "indices": [
              "113", 
              "136"
            ],
            "media_url": "http://pbs.twimg.com/media/CYFxlIdUAAAr8ez.jpg",
            "media_url_https": "https://pbs.twimg.com/media/CYFxlIdUAAAr8ez.jpg",
            "sizes": {
              "large": {
                "h": "682",
                "resize": "fit",
                "w": "1024"
              },
              "medium": {
                "h": "682",
                "resize": "fit",
                "w": "1024"
              },
              "small": {
                "h": "453",
                "resize": "fit",
                "w": "680"
              },
              "thumb": {
                "h": "150",
                "resize": "crop",
                "w": "150"
              }
            },
            "type": "photo",
            "url": "https://t.co/AcUBFesCCY"
          }
        ]
      },
      "favorite_count": "1",
      "favorited": false,
      "full_text": "Conquest of Space by Rufino Tamayo was the first sculpture by Tamayo to be permanently placed outside of Mexico. https://t.co/AcUBFesCCY",
      "id_str": "684953516012482560",
      "lang": "en",
      "possibly_sensitive": false,
      "retweet_count": "0",
      "retweeted": false,
      "source": "\u003ca href=\"http://twitter.com/download/iphone\" rel=\"nofollow\"\u003eTwitter for iPhone\u003c/a\u003e",
      "truncated": false
    },
    "wof:name": "Twitter message #684953516012482560",
    "wof:placetype": "custom"
  },
  "geometry": {"coordinates":[-122.386166,37.616356],"type":"Point"}
}
