{
  "type": "Feature",
  "properties": {
    "sfomuseum:placetype": "tweet",
    "twitter:tweet": {
      "created": 1470252013,
      "created_at": "Wed Aug 03 19:20:13 +0000 2016",
      "display_text_range": [
        "0", 
        "123"
      ],
      "entities": {
        "hashtags": [
          {
            "indices": [
              "85", 
              "99"
            ],
            "text": "ArtNouveauSFO"
          }
        ],
        "media": [
          {
            "display_url": "pic.twitter.com/QgfKkdw9U4",
            "expanded_url": "https://twitter.com/SFOMuseum/status/760918210065694720/photo/1",
            "id_str": "760918206416556032",
            "indices": [
              "100", 
              "123"
            ],
            "media_url": "http://pbs.twimg.com/media/Co9TE8SWEAALjfz.jpg",
            "media_url_https": "https://pbs.twimg.com/media/Co9TE8SWEAALjfz.jpg",
            "sizes": {
              "large": {
                "h": "2000",
                "resize": "fit",
                "w": "1600"
              },
              "medium": {
                "h": "1200",
                "resize": "fit",
                "w": "960"
              },
              "small": {
                "h": "680",
                "resize": "fit",
                "w": "544"
              },
              "thumb": {
                "h": "150",
                "resize": "crop",
                "w": "150"
              }
            },
            "type": "photo",
            "url": "https://t.co/QgfKkdw9U4"
          }
        ]
      },
      "extended_entities": {
        "media": [
          {
            "display_url": "pic.twitter.com/QgfKkdw9U4",
            "expanded_url": "https://twitter.com/SFOMuseum/status/760918210065694720/photo/1",
            "id_str": "760918206416556032",
            "indices": [
              "100", 
              "123"
            ],
            "media_url": "http://pbs.twimg.com/media/Co9TE8SWEAALjfz.jpg",
            "media_url_https": "https://pbs.twimg.com/media/Co9TE8SWEAALjfz.jpg",
            "sizes": {
              "large": {
                "h": "2000",
                "resize": "fit",
                "w": "1600"
              },
              "medium": {
                "h": "1200",
                "resize": "fit",
                "w": "960"
              },
              "small": {
                "h": "680",
                "resize": "fit",
                "w": "544"
              },
              "thumb": {
                "h": "150",
                "resize": "crop",
                "w": "150"
              }
            },
            "type": "photo",
            "url": "https://t.co/QgfKkdw9U4"
          }
        ]
      },
      "favorite_count": "3",
      "favorited": false,
      "full_text": "The Vienna Workshops intended to bring good design and craft into all areas of life. #ArtNouveauSFO https://t.co/QgfKkdw9U4",
      "id_str": "760918210065694720",
      "lang": "en",
      "possibly_sensitive": false,
      "retweet_count": "1",
      "retweeted": false,
      "source": "\u003ca href=\"http://www.hootsuite.com\" rel=\"nofollow\"\u003eHootsuite\u003c/a\u003e",
      "truncated": false
    },
    "wof:name": "Twitter message #760918210065694720",
    "wof:placetype": "custom"
  },
  "geometry": {"coordinates":[-122.386166,37.616356],"type":"Point"}
}
