{
  "type": "Feature",
  "properties": {
    "sfomuseum:placetype": "tweet",
    "twitter:tweet": {
      "created": 1512765012,
      "created_at": "Fri Dec 08 20:30:12 +0000 2017",
      "display_text_range": [
        "0", 
        "259"
      ],
      "entities": {
        "hashtags": [
          {
            "indices": [
              "103", 
              "117"
            ],
            "text": "Constellation"
          }, 
          {
            "indices": [
              "216", 
              "235"
            ],
            "text": "AviationEvolutions"
          }
        ],
        "media": [
          {
            "display_url": "pic.twitter.com/QW4M2Tcyrh",
            "expanded_url": "https://twitter.com/SFOMuseum/status/939230651936583680/photo/1",
            "id_str": "939230648572743680",
            "indices": [
              "236", 
              "259"
            ],
            "media_url": "http://pbs.twimg.com/media/DQjRTHJWkAAxddG.jpg",
            "media_url_https": "https://pbs.twimg.com/media/DQjRTHJWkAAxddG.jpg",
            "sizes": {
              "large": {
                "h": "1293",
                "resize": "fit",
                "w": "2000"
              },
              "medium": {
                "h": "776",
                "resize": "fit",
                "w": "1200"
              },
              "small": {
                "h": "440",
                "resize": "fit",
                "w": "680"
              },
              "thumb": {
                "h": "150",
                "resize": "crop",
                "w": "150"
              }
            },
            "type": "photo",
            "url": "https://t.co/QW4M2Tcyrh"
          }
        ]
      },
      "extended_entities": {
        "media": [
          {
            "display_url": "pic.twitter.com/QW4M2Tcyrh",
            "expanded_url": "https://twitter.com/SFOMuseum/status/939230651936583680/photo/1",
            "id_str": "939230648572743680",
            "indices": [
              "236", 
              "259"
            ],
            "media_url": "http://pbs.twimg.com/media/DQjRTHJWkAAxddG.jpg",
            "media_url_https": "https://pbs.twimg.com/media/DQjRTHJWkAAxddG.jpg",
            "sizes": {
              "large": {
                "h": "1293",
                "resize": "fit",
                "w": "2000"
              },
              "medium": {
                "h": "776",
                "resize": "fit",
                "w": "1200"
              },
              "small": {
                "h": "440",
                "resize": "fit",
                "w": "680"
              },
              "thumb": {
                "h": "150",
                "resize": "crop",
                "w": "150"
              }
            },
            "type": "photo",
            "url": "https://t.co/QW4M2Tcyrh"
          }
        ]
      },
      "favorite_count": "9",
      "favorited": false,
      "full_text": "Operated on domestic routes, as well as transatlantic routes between Europe and North America, the 049 #Constellation played a major role in advancing long-range commercial aviation during the immediate postwar era. #AviationEvolutions https://t.co/QW4M2Tcyrh",
      "id_str": "939230651936583680",
      "lang": "en",
      "possibly_sensitive": false,
      "retweet_count": "1",
      "retweeted": false,
      "source": "\u003ca href=\"http://www.hootsuite.com\" rel=\"nofollow\"\u003eHootsuite\u003c/a\u003e",
      "truncated": false
    },
    "wof:name": "Twitter message #939230651936583680",
    "wof:placetype": "custom"
  },
  "geometry": {"coordinates":[-122.386166,37.616356],"type":"Point"}
}
