{
  "type": "Feature",
  "properties": {
    "sfomuseum:placetype": "tweet",
    "twitter:tweet": {
      "created": 1331326075,
      "created_at": "Fri Mar 09 20:47:55 +0000 2012",
      "display_text_range": [
        "0", 
        "107"
      ],
      "entities": {
        "urls": [
          {
            "display_url": "instagr.am/p/H9zC-Gxkzu/",
            "expanded_url": "http://instagr.am/p/H9zC-Gxkzu/",
            "indices": [
              "87", 
              "107"
            ],
            "url": "http://t.co/UkVorQlK"
          }
        ]
      },
      "favorite_count": "1",
      "favorited": false,
      "full_text": "Installation in progress! Threading the Needle: Sewing in the Machine Age, Terminal 3  http://t.co/UkVorQlK",
      "id_str": "178220593240489984",
      "lang": "en",
      "possibly_sensitive": false,
      "retweet_count": "0",
      "retweeted": false,
      "source": "\u003ca href=\"http://instagram.com\" rel=\"nofollow\"\u003eInstagram\u003c/a\u003e",
      "truncated": false
    },
    "wof:name": "Twitter message #178220593240489984",
    "wof:placetype": "custom"
  },
  "geometry": {"coordinates":[-122.386166,37.616356],"type":"Point"}
}
