{
  "type": "Feature",
  "properties": {
    "date:cessation_lower": "2013-01-25",
    "date:cessation_upper": "2013-01-25",
    "date:inception_lower": "2013-01-25",
    "date:inception_upper": "2013-01-25",
    "iso:country": "US",
    "sfomuseum:placetype": "tweet",
    "twitter:tweet": {
      "created": 1359149180,
      "created_at": "Fri Jan 25 21:26:20 +0000 2013",
      "display_text_range": [
        "0",
        "141"
      ],
      "edit_info": {
        "initial": {
          "editTweetIds": [
            "294919155453407232"
          ],
          "editableUntil": "2013-01-25T22:26:20.650Z",
          "editsRemaining": "5",
          "isEditEligible": true
        }
      },
      "entities": {
        "urls": [
          {
            "display_url": "bit.ly/WZceUH",
            "expanded_url": "http://bit.ly/WZceUH",
            "indices": [
              "63",
              "83"
            ],
            "url": "http://t.co/WfFj0e8V"
          },
          {
            "display_url": "bit.ly/Vvxirt",
            "expanded_url": "http://bit.ly/Vvxirt",
            "indices": [
              "121",
              "141"
            ],
            "url": "http://t.co/WgsyVL4O"
          }
        ],
        "user_mentions": [
          {
            "id_str": "18958334",
            "indices": [
              "38",
              "43"
            ],
            "name": "SF Arts Commission",
            "screen_name": "SFAC"
          }
        ]
      },
      "favorite_count": "0",
      "favorited": false,
      "full_text": "Great feature on the art in T-2 \u0026amp; @SFAC! Thanks @kalwnews! http://t.co/WfFj0e8V  Got more time? Take the audio tour: http://t.co/WgsyVL4O",
      "id_str": "294919155453407232",
      "lang": "en",
      "possibly_sensitive": false,
      "retweet_count": "2",
      "retweeted": false,
      "source": "\u003ca href=\"https://about.twitter.com/products/tweetdeck\" rel=\"nofollow\"\u003eTweetDeck\u003c/a\u003e",
      "truncated": false
    },
    "twitter:user_mentions": [
      "SFAC"
    ],
    "wof:name": "Great feature on the art in T-2 \u0026amp; @SFAC! Thanks @kalwnews! http://t.co/WfFj0e8V  Got more time? Take the audio tour: http://t.co/WgsyVL4O",
    "wof:placetype": "custom"
  },
  "geometry": {"coordinates":[-122.386166,37.616356],"type":"Point"}
}
