{
  "type": "Feature",
  "properties": {
    "sfomuseum:placetype": "tweet",
    "twitter:tweet": {
      "created": 1366996669,
      "created_at": "Fri Apr 26 17:17:49 +0000 2013",
      "display_text_range": [
        "0", 
        "135"
      ],
      "entities": {
        "hashtags": [
          {
            "indices": [
              "105", 
              "112"
            ],
            "text": "avgeek"
          }
        ],
        "media": [
          {
            "display_url": "pic.twitter.com/rp6W5ouNlN",
            "expanded_url": "https://twitter.com/SFOMuseum/status/327833906760011776/photo/1",
            "id_str": "327833906764206080",
            "indices": [
              "113", 
              "135"
            ],
            "media_url": "http://pbs.twimg.com/media/BIyzM4YCUAAot0r.jpg",
            "media_url_https": "https://pbs.twimg.com/media/BIyzM4YCUAAot0r.jpg",
            "sizes": {
              "large": {
                "h": "645",
                "resize": "fit",
                "w": "1000"
              },
              "medium": {
                "h": "645",
                "resize": "fit",
                "w": "1000"
              },
              "small": {
                "h": "439",
                "resize": "fit",
                "w": "680"
              },
              "thumb": {
                "h": "150",
                "resize": "crop",
                "w": "150"
              }
            },
            "type": "photo",
            "url": "http://t.co/rp6W5ouNlN"
          }
        ],
        "user_mentions": [
          {
            "id_str": "18332190",
            "indices": [
              "65", 
              "81"
            ],
            "name": "British Airways",
            "screen_name": "British_Airways"
          }
        ]
      },
      "extended_entities": {
        "media": [
          {
            "display_url": "pic.twitter.com/rp6W5ouNlN",
            "expanded_url": "https://twitter.com/SFOMuseum/status/327833906760011776/photo/1",
            "id_str": "327833906764206080",
            "indices": [
              "113", 
              "135"
            ],
            "media_url": "http://pbs.twimg.com/media/BIyzM4YCUAAot0r.jpg",
            "media_url_https": "https://pbs.twimg.com/media/BIyzM4YCUAAot0r.jpg",
            "sizes": {
              "large": {
                "h": "645",
                "resize": "fit",
                "w": "1000"
              },
              "medium": {
                "h": "645",
                "resize": "fit",
                "w": "1000"
              },
              "small": {
                "h": "439",
                "resize": "fit",
                "w": "680"
              },
              "thumb": {
                "h": "150",
                "resize": "crop",
                "w": "150"
              }
            },
            "type": "photo",
            "url": "http://t.co/rp6W5ouNlN"
          }
        ]
      },
      "favorite_count": "0",
      "favorited": false,
      "full_text": "3 days left for Interiors Revealed! Here: 1:50 scale, late 1940s @British_Airways Handley Page Hermes 4. #avgeek http://t.co/rp6W5ouNlN",
      "id_str": "327833906760011776",
      "lang": "en",
      "possibly_sensitive": false,
      "retweet_count": "1",
      "retweeted": false,
      "source": "\u003ca href=\"https://about.twitter.com/products/tweetdeck\" rel=\"nofollow\"\u003eTweetDeck\u003c/a\u003e",
      "truncated": false
    },
    "wof:name": "Twitter message #327833906760011776",
    "wof:placetype": "custom"
  },
  "geometry": {"coordinates":[-122.386166,37.616356],"type":"Point"}
}
