{
  "type": "Feature",
  "properties": {
    "date:cessation_lower":"2013-04-04",
    "date:cessation_upper":"2013-04-04",
    "date:inception_lower":"2013-04-04",
    "date:inception_upper":"2013-04-04",
    "iso:country":"US",
    "sfomuseum:placetype":"tweet",
    "twitter:tweet":{
        "created":1365094222,
        "created_at":"Thu Apr 04 16:50:22 +0000 2013",
        "display_text_range":[
            "0",
            "138"
        ],
        "entities":{
            "urls":[
                {
                    "display_url":"ow.ly/1UBbSR",
                    "expanded_url":"http://ow.ly/1UBbSR",
                    "indices":[
                        "103",
                        "125"
                    ],
                    "url":"http://t.co/6SlpTH5a3R"
                }
            ]
        },
        "favorite_count":"0",
        "favorited":false,
        "full_text":"Introduced to photography while in the Vietnam War, Robert B. Taylor captures rural California beauty: http://t.co/6SlpTH5a3R Post-TSA, T3",
        "id_str":"319854468088877056",
        "lang":"en",
        "possibly_sensitive":false,
        "retweet_count":"0",
        "retweeted":false,
        "source":"<a href=\"http://twitter.com/#!/download/ipad\" rel=\"nofollow\">Twitter for iPad</a>",
        "truncated":false
    },
    "wof:name":"Introduced to photography while in the Vietnam War, Robert B. Taylor captures rural California beauty: http://t.co/6SlpTH5a3R Post-TSA, T3",
    "wof:placetype":"custom"
},
  "geometry": {"coordinates":[-122.386166,37.616356],"type":"Point"}
}