{
  "type": "Feature",
  "properties": {
    "date:cessation_lower": "2015-03-30",
    "date:cessation_upper": "2015-03-30",
    "date:inception_lower": "2015-03-30",
    "date:inception_upper": "2015-03-30",
    "iso:country": "US",
    "sfomuseum:placetype": "tweet",
    "twitter:tweet": {
      "created": 1427758001,
      "created_at": "Mon Mar 30 23:26:41 +0000 2015",
      "display_text_range": [
        "0",
        "122"
      ],
      "edit_info": {
        "initial": {
          "editTweetIds": [
            "582685408519159808"
          ],
          "editableUntil": "2015-03-30T23:56:41.819Z",
          "editsRemaining": "5",
          "isEditEligible": true
        }
      },
      "entities": {
        "urls": [
          {
            "display_url": "instagram.com/p/03sgpxxk_a/",
            "expanded_url": "https://instagram.com/p/03sgpxxk_a/",
            "indices": [
              "99",
              "122"
            ],
            "url": "https://t.co/XjwvZvEXtF"
          }
        ]
      },
      "favorite_count": "0",
      "favorited": false,
      "full_text": "Gone With The Wind, which remains one of the most popular and commercially successful movies ever… https://t.co/XjwvZvEXtF",
      "id_str": "582685408519159808",
      "lang": "en",
      "possibly_sensitive": false,
      "retweet_count": "0",
      "retweeted": false,
      "source": "\u003ca href=\"http://instagram.com\" rel=\"nofollow\"\u003eInstagram\u003c/a\u003e",
      "truncated": false
    },
    "wof:name": "Gone With The Wind, which remains one of the most popular and commercially successful movies ever… https://t.co/XjwvZvEXtF",
    "wof:placetype": "custom"
  },
  "geometry": {"coordinates":[-122.386166,37.616356],"type":"Point"}
}
