{
  "type": "Feature",
  "properties": {
    "date:cessation_lower":"2014-04-21",
    "date:cessation_upper":"2014-04-21",
    "date:inception_lower":"2014-04-21",
    "date:inception_upper":"2014-04-21",
    "iso:country":"US",
    "sfomuseum:placetype":"tweet",
    "twitter:tweet":{
        "created":1398098643,
        "created_at":"Mon Apr 21 16:44:03 +0000 2014",
        "display_text_range":[
            "0",
            "139"
        ],
        "entities":{
            "hashtags":[
                {
                    "indices":[
                        "46",
                        "58"
                    ],
                    "text":"GnomeArthur"
                },
                {
                    "indices":[
                        "81",
                        "85"
                    ],
                    "text":"SFO"
                }
            ],
            "urls":[
                {
                    "display_url":"instagram.com/p/nDqPFuRlgz/",
                    "expanded_url":"http://instagram.com/p/nDqPFuRlgz/",
                    "indices":[
                        "117",
                        "139"
                    ],
                    "url":"http://t.co/qZIKXggrhs"
                }
            ],
            "user_mentions":[
                {
                    "id_str":"340588087",
                    "indices":[
                        "3",
                        "16"
                    ],
                    "name":"Harley Chadly",
                    "screen_name":"HarleyChadly"
                }
            ]
        },
        "favorite_count":"0",
        "favorited":false,
        "full_text":"RT @HarleyChadly: Japanese toy exhibit and my #GnomeArthur wants to play.  Hello #SFO @ San Francisco International\u2026 http://t.co/qZIKXggrhs",
        "id_str":"458285044365139968",
        "lang":"en",
        "possibly_sensitive":false,
        "retweet_count":"0",
        "retweeted":false,
        "source":"<a href=\"http://www.hootsuite.com\" rel=\"nofollow\">Hootsuite</a>",
        "truncated":false
    },
    "wof:name":"RT @HarleyChadly: Japanese toy exhibit and my #GnomeArthur wants to play.  Hello #SFO @ San Francisco International\u2026 http://t.co/qZIKXggrhs",
    "wof:placetype":"custom"
},
  "geometry": {"coordinates":[-122.386166,37.616356],"type":"Point"}
}