{
  "type": "Feature",
  "properties": {
    "date:cessation_lower": "2012-02-03",
    "date:cessation_upper": "2012-02-03",
    "date:inception_lower": "2012-02-03",
    "date:inception_upper": "2012-02-03",
    "iso:country": "US",
    "sfomuseum:placetype": "tweet",
    "twitter:tweet": {
      "created": 1328288520,
      "created_at": "Fri Feb 03 17:02:00 +0000 2012",
      "display_text_range": [
        "0",
        "127"
      ],
      "edit_info": {
        "initial": {
          "editTweetIds": [
            "165480166057984001"
          ],
          "editableUntil": "2012-02-03T18:02:00.718Z",
          "editsRemaining": "5",
          "isEditEligible": true
        }
      },
      "entities": {
        "user_mentions": [
          {
            "id_str": "14194497",
            "indices": [
              "22",
              "33"
            ],
            "name": "Lola",
            "screen_name": "runlolarun"
          },
          {
            "id_str": "929435545586909184",
            "indices": [
              "35",
              "50"
            ],
            "name": "Daniella",
            "screen_name": "Daniella__Rose"
          }
        ]
      },
      "favorite_count": "0",
      "favorited": false,
      "full_text": "Word! And thanks!! RT @runlolarun: @Daniella__Rose SFO is also an AAM accredited museum... wish all airports were that awesome!",
      "id_str": "165480166057984001",
      "lang": "en",
      "retweet_count": "0",
      "retweeted": false,
      "source": "\u003ca href=\"https://about.twitter.com/products/tweetdeck\" rel=\"nofollow\"\u003eTweetDeck\u003c/a\u003e",
      "truncated": false
    },
    "twitter:user_mentions": [
      "runlolarun",
      "Daniella__Rose"
    ],
    "wof:name": "Word! And thanks!! RT @runlolarun: @Daniella__Rose SFO is also an AAM accredited museum... wish all airports were that awesome!",
    "wof:placetype": "custom"
  },
  "geometry": {"coordinates":[-122.386166,37.616356],"type":"Point"}
}
