{
  "type": "Feature",
  "properties": {
    "sfomuseum:placetype": "tweet",
    "twitter:tweet": {
      "created": 1328551766,
      "created_at": "Mon Feb 06 18:09:26 +0000 2012",
      "display_text_range": [
        "0", 
        "109"
      ],
      "entities": {
        "urls": [
          {
            "display_url": "ow.ly/1FH4Du",
            "expanded_url": "http://ow.ly/1FH4Du",
            "indices": [
              "89", 
              "109"
            ],
            "url": "http://t.co/8TVC8XOP"
          }
        ]
      },
      "favorite_count": "0",
      "favorited": false,
      "full_text": "1951's Tennyson was one (\u0026 one of the last) in a series of \"Giant Circle\" tvs by Zenith: http://t.co/8TVC8XOP",
      "id_str": "166584300307886080",
      "lang": "en",
      "possibly_sensitive": false,
      "retweet_count": "1",
      "retweeted": false,
      "source": "\u003ca href=\"http://www.hootsuite.com\" rel=\"nofollow\"\u003eHootsuite\u003c/a\u003e",
      "truncated": false
    },
    "wof:name": "Twitter message #166584300307886080",
    "wof:placetype": "custom"
  },
  "geometry": {"coordinates":[-122.386166,37.616356],"type":"Point"}
}
