{
  "type": "Feature",
  "properties": {
    "sfomuseum:placetype": "tweet",
    "twitter:tweet": {
      "created": 1521068243,
      "created_at": "Wed Mar 14 22:57:23 +0000 2018",
      "display_text_range": [
        "0", 
        "185"
      ],
      "entities": {
        "user_mentions": [
          {
            "id_str": "121594946",
            "indices": [
              "0", 
              "15"
            ],
            "name": "Howard Slutsken",
            "screen_name": "HowardSlutsken"
          }
        ]
      },
      "favorite_count": "1",
      "favorited": false,
      "full_text": "@HowardSlutsken Fantastic! The Aviation Museum and Library is located pre-security in the International Terminal and is open daily from 10am to 4:30pm. We hope you enjoy the exhibition!",
      "id_str": "974056926899130368",
      "in_reply_to_screen_name": "HowardSlutsken",
      "in_reply_to_status_id": "974043786027266049",
      "in_reply_to_status_id_str": "974043786027266049",
      "in_reply_to_user_id": "121594946",
      "in_reply_to_user_id_str": "121594946",
      "lang": "en",
      "retweet_count": "0",
      "retweeted": false,
      "source": "\u003ca href=\"http://twitter.com\" rel=\"nofollow\"\u003eTwitter Web Client\u003c/a\u003e",
      "truncated": false
    },
    "wof:name": "Twitter message #974056926899130368",
    "wof:placetype": "custom"
  },
  "geometry": {"coordinates":[-122.386166,37.616356],"type":"Point"}
}
