{
  "type": "Feature",
  "properties": {
    "date:cessation_lower": "2012-06-25",
    "date:cessation_upper": "2012-06-25",
    "date:inception_lower": "2012-06-25",
    "date:inception_upper": "2012-06-25",
    "iso:country": "US",
    "sfomuseum:placetype": "tweet",
    "twitter:tweet": {
      "created": 1340642462,
      "created_at": "Mon Jun 25 16:41:02 +0000 2012",
      "display_text_range": [
        "0",
        "87"
      ],
      "edit_info": {
        "initial": {
          "editTweetIds": [
            "217296354400149505"
          ],
          "editableUntil": "2012-06-25T17:11:02.717Z",
          "editsRemaining": "5",
          "isEditEligible": true
        }
      },
      "entities": {
        "user_mentions": [
          {
            "id_str": "520060880",
            "indices": [
              "0",
              "13"
            ],
            "name": "Brian Adams @🏡",
            "screen_name": "BrianAdamsPR"
          }
        ]
      },
      "favorite_count": "0",
      "favorited": false,
      "full_text": "@BrianAdamsPR Thanks for checking out Moto Bellissima! We hope you enjoyed the exhibit!",
      "id_str": "217296354400149505",
      "in_reply_to_screen_name": "BrianAdamsPR",
      "in_reply_to_status_id": "216351853363994624",
      "in_reply_to_status_id_str": "216351853363994624",
      "in_reply_to_user_id": "520060880",
      "in_reply_to_user_id_str": "520060880",
      "lang": "en",
      "retweet_count": "0",
      "retweeted": false,
      "source": "\u003ca href=\"https://about.twitter.com/products/tweetdeck\" rel=\"nofollow\"\u003eTweetDeck\u003c/a\u003e",
      "truncated": false
    },
    "wof:name": "@BrianAdamsPR Thanks for checking out Moto Bellissima! We hope you enjoyed the exhibit!",
    "wof:placetype": "custom"
  },
  "geometry": {"coordinates":[-122.386166,37.616356],"type":"Point"}
}
