{
  "type": "Feature",
  "properties": {
    "date:cessation_lower": "2016-06-17",
    "date:cessation_upper": "2016-06-17",
    "date:inception_lower": "2016-06-17",
    "date:inception_upper": "2016-06-17",
    "iso:country": "US",
    "sfomuseum:placetype": "tweet",
    "twitter:tweet": {
      "created": 1466201476,
      "created_at": "Fri Jun 17 22:11:16 +0000 2016",
      "display_text_range": [
        "0",
        "140"
      ],
      "edit_info": {
        "initial": {
          "editTweetIds": [
            "743929027371491328"
          ],
          "editableUntil": "2016-06-17T22:41:16.315Z",
          "editsRemaining": "5",
          "isEditEligible": true
        }
      },
      "entities": {
        "user_mentions": [
          {
            "id_str": "95746689",
            "indices": [
              "3",
              "16"
            ],
            "name": "panamhistory",
            "screen_name": "panamhistory"
          }
        ]
      },
      "favorite_count": "0",
      "favorited": false,
      "full_text": "RT @panamhistory: Clipper America the L-049 Constellation NC86520 took off from LaGuardia Field with a crowd of 4,000 spectators on... http…",
      "id_str": "743929027371491328",
      "lang": "en",
      "retweet_count": "0",
      "retweeted": false,
      "source": "\u003ca href=\"http://twitter.com\" rel=\"nofollow\"\u003eTwitter Web Client\u003c/a\u003e",
      "truncated": false
    },
    "wof:name": "RT @panamhistory: Clipper America the L-049 Constellation NC86520 took off from LaGuardia Field with a crowd of 4,000 spectators on... http…",
    "wof:placetype": "custom"
  },
  "geometry": {"coordinates":[-122.386166,37.616356],"type":"Point"}
}
