{
  "type": "Feature",
  "properties": {
    "date:cessation_lower": "2014-09-25",
    "date:cessation_upper": "2014-09-25",
    "date:inception_lower": "2014-09-25",
    "date:inception_upper": "2014-09-25",
    "iso:country": "US",
    "sfomuseum:placetype": "tweet",
    "twitter:tweet": {
      "created": 1411682061,
      "created_at": "Thu Sep 25 21:54:21 +0000 2014",
      "display_text_range": [
        "0",
        "144"
      ],
      "edit_info": {
        "initial": {
          "editTweetIds": [
            "515258029609324544"
          ],
          "editableUntil": "2014-09-25T22:24:21.947Z",
          "editsRemaining": "5",
          "isEditEligible": true
        }
      },
      "entities": {
        "hashtags": [
          {
            "indices": [
              "137",
              "144"
            ],
            "text": "avgeek"
          }
        ],
        "urls": [
          {
            "display_url": "ow.ly/BWHQQ",
            "expanded_url": "http://ow.ly/BWHQQ",
            "indices": [
              "114",
              "136"
            ],
            "url": "http://t.co/QURxhM0Jtq"
          }
        ]
      },
      "favorite_count": "0",
      "favorited": false,
      "full_text": "Crews used to circulate hand-written reports to passengers, alerting them to details like altitude \u0026amp; scenery: http://t.co/QURxhM0Jtq #avgeek",
      "id_str": "515258029609324544",
      "lang": "en",
      "possibly_sensitive": false,
      "retweet_count": "0",
      "retweeted": false,
      "source": "\u003ca href=\"http://www.hootsuite.com\" rel=\"nofollow\"\u003eHootsuite\u003c/a\u003e",
      "truncated": false
    },
    "wof:name": "Crews used to circulate hand-written reports to passengers, alerting them to details like altitude \u0026amp; scenery: http://t.co/QURxhM0Jtq #avgeek",
    "wof:placetype": "custom"
  },
  "geometry": {"coordinates":[-122.386166,37.616356],"type":"Point"}
}
