{
  "type": "Feature",
  "properties": {
    "sfomuseum:placetype": "tweet",
    "twitter:tweet": {
      "created": 1510276806,
      "created_at": "Fri Nov 10 01:20:06 +0000 2017",
      "display_text_range": [
        "0", 
        "160"
      ],
      "entities": {
        "hashtags": [
          {
            "indices": [
              "109", 
              "125"
            ],
            "text": "AmericanFolkArt"
          }, 
          {
            "indices": [
              "126", 
              "136"
            ],
            "text": "sneakpeek"
          }
        ],
        "media": [
          {
            "display_url": "pic.twitter.com/07RzMRUDja",
            "expanded_url": "https://twitter.com/SFOMuseum/status/928794361961295873/photo/1",
            "id_str": "928794358987542533",
            "indices": [
              "137", 
              "160"
            ],
            "media_url": "http://pbs.twimg.com/media/DOO9jGzW0AUIYJH.jpg",
            "media_url_https": "https://pbs.twimg.com/media/DOO9jGzW0AUIYJH.jpg",
            "sizes": {
              "large": {
                "h": "1500",
                "resize": "fit",
                "w": "2000"
              },
              "medium": {
                "h": "900",
                "resize": "fit",
                "w": "1200"
              },
              "small": {
                "h": "510",
                "resize": "fit",
                "w": "680"
              },
              "thumb": {
                "h": "150",
                "resize": "crop",
                "w": "150"
              }
            },
            "type": "photo",
            "url": "https://t.co/07RzMRUDja"
          }
        ]
      },
      "extended_entities": {
        "media": [
          {
            "display_url": "pic.twitter.com/07RzMRUDja",
            "expanded_url": "https://twitter.com/SFOMuseum/status/928794361961295873/photo/1",
            "id_str": "928794358987542533",
            "indices": [
              "137", 
              "160"
            ],
            "media_url": "http://pbs.twimg.com/media/DOO9jGzW0AUIYJH.jpg",
            "media_url_https": "https://pbs.twimg.com/media/DOO9jGzW0AUIYJH.jpg",
            "sizes": {
              "large": {
                "h": "1500",
                "resize": "fit",
                "w": "2000"
              },
              "medium": {
                "h": "900",
                "resize": "fit",
                "w": "1200"
              },
              "small": {
                "h": "510",
                "resize": "fit",
                "w": "680"
              },
              "thumb": {
                "h": "150",
                "resize": "crop",
                "w": "150"
              }
            },
            "type": "photo",
            "url": "https://t.co/07RzMRUDja"
          }
        ]
      },
      "favorite_count": "3",
      "favorited": false,
      "full_text": "Completed exhibition furniture and mounts wait to be packed and moved to the terminals for our next exhibit, #AmericanFolkArt #sneakpeek https://t.co/07RzMRUDja",
      "id_str": "928794361961295873",
      "lang": "en",
      "possibly_sensitive": false,
      "retweet_count": "0",
      "retweeted": false,
      "source": "\u003ca href=\"http://www.hootsuite.com\" rel=\"nofollow\"\u003eHootsuite\u003c/a\u003e",
      "truncated": false
    },
    "wof:name": "Twitter message #928794361961295873",
    "wof:placetype": "custom"
  },
  "geometry": {"coordinates":[-122.386166,37.616356],"type":"Point"}
}
