{
  "type": "Feature",
  "properties": {
    "sfomuseum:placetype": "tweet",
    "twitter:tweet": {
      "created": 1320436983,
      "created_at": "Fri Nov 04 20:03:03 +0000 2011",
      "display_text_range": [
        "0", 
        "115"
      ],
      "entities": {
        "urls": [
          {
            "display_url": "ht.ly/7jqAo",
            "expanded_url": "http://ht.ly/7jqAo",
            "indices": [
              "95", 
              "115"
            ],
            "url": "http://t.co/r55X1bf5"
          }
        ],
        "user_mentions": [
          {
            "id_str": "16536215",
            "indices": [
              "23", 
              "30"
            ],
            "name": "SFMOMA",
            "screen_name": "SFMOMA"
          }
        ]
      },
      "favorite_count": "0",
      "favorited": false,
      "full_text": "RT @7x7Magazine: 3 new @SFMOMA exhibits start tomorrow \u0026 they are NOT to be missed! Here's why http://t.co/r55X1bf5",
      "id_str": "132548431989325824",
      "lang": "en",
      "possibly_sensitive": false,
      "retweet_count": "0",
      "retweeted": false,
      "source": "\u003ca href=\"https://about.twitter.com/products/tweetdeck\" rel=\"nofollow\"\u003eTweetDeck\u003c/a\u003e",
      "truncated": false
    },
    "wof:name": "Twitter message #132548431989325824",
    "wof:placetype": "custom"
  },
  "geometry": {"coordinates":[-122.386166,37.616356],"type":"Point"}
}
