{
  "type": "Feature",
  "properties": {
    "sfomuseum:placetype": "tweet",
    "twitter:tweet": {
      "created": 1390325538,
      "created_at": "Tue Jan 21 17:32:18 +0000 2014",
      "display_text_range": [
        "0", 
        "101"
      ],
      "entities": {
        "hashtags": [
          {
            "indices": [
              "62", 
              "73"
            ],
            "text": "airportart"
          }, 
          {
            "indices": [
              "74", 
              "78"
            ],
            "text": "sfo"
          }
        ],
        "urls": [
          {
            "display_url": "instagram.com/p/jZvGnJStb7/",
            "expanded_url": "http://instagram.com/p/jZvGnJStb7/",
            "indices": [
              "79", 
              "101"
            ],
            "url": "http://t.co/PKam711I87"
          }
        ],
        "user_mentions": [
          {
            "id_str": "46889163",
            "indices": [
              "3", 
              "14"
            ],
            "name": "Daniel Spiess",
            "screen_name": "dan_spiess"
          }
        ]
      },
      "favorite_count": "0",
      "favorited": false,
      "full_text": "RT @dan_spiess: The Japanese toy exhibit at SFO is fantastic. #airportart #sfo http://t.co/PKam711I87",
      "id_str": "425682277516210176",
      "lang": "en",
      "possibly_sensitive": false,
      "retweet_count": "0",
      "retweeted": false,
      "source": "\u003ca href=\"http://www.hootsuite.com\" rel=\"nofollow\"\u003eHootsuite\u003c/a\u003e",
      "truncated": false
    },
    "wof:name": "Twitter message #425682277516210176",
    "wof:placetype": "custom"
  },
  "geometry": {"coordinates":[-122.386166,37.616356],"type":"Point"}
}
