{
  "type": "Feature",
  "properties": {
    "date:cessation_lower": "2012-06-18",
    "date:cessation_upper": "2012-06-18",
    "date:inception_lower": "2012-06-18",
    "date:inception_upper": "2012-06-18",
    "iso:country": "US",
    "sfomuseum:placetype": "tweet",
    "twitter:tweet": {
      "created": 1340053800,
      "created_at": "Mon Jun 18 21:10:00 +0000 2012",
      "display_text_range": [
        "0",
        "80"
      ],
      "edit_info": {
        "initial": {
          "editTweetIds": [
            "214827326314258433"
          ],
          "editableUntil": "2012-06-18T22:10:00.549Z",
          "editsRemaining": "5",
          "isEditEligible": true
        }
      },
      "entities": {
        "user_mentions": [
          {
            "id_str": "62348231",
            "indices": [
              "0",
              "10"
            ],
            "name": "Christine Tsai",
            "screen_name": "maigochan"
          }
        ]
      },
      "favorite_count": "0",
      "favorited": false,
      "full_text": "@maigochan Thanks for checking out Threading the Needle! We hope you enjoyed it!",
      "id_str": "214827326314258433",
      "in_reply_to_screen_name": "maigochan",
      "in_reply_to_status_id": "214609975731961856",
      "in_reply_to_status_id_str": "214609975731961856",
      "in_reply_to_user_id": "62348231",
      "in_reply_to_user_id_str": "62348231",
      "lang": "en",
      "retweet_count": "0",
      "retweeted": false,
      "source": "\u003ca href=\"https://about.twitter.com/products/tweetdeck\" rel=\"nofollow\"\u003eTweetDeck\u003c/a\u003e",
      "truncated": false
    },
    "twitter:user_mentions": [
      "maigochan"
    ],
    "wof:name": "@maigochan Thanks for checking out Threading the Needle! We hope you enjoyed it!",
    "wof:placetype": "custom",
    "wof:placetype_alt": [
      "tweet"
    ]
  },
  "geometry": {"coordinates":[-122.386166,37.616356],"type":"Point"}
}
