{
  "type": "Feature",
  "properties": {
    "sfomuseum:placetype": "tweet",
    "twitter:tweet": {
      "created": 1340053800,
      "created_at": "Mon Jun 18 21:10:00 +0000 2012",
      "display_text_range": [
        "0", 
        "80"
      ],
      "entities": {
        "user_mentions": [
          {
            "id_str": "62348231",
            "indices": [
              "0", 
              "10"
            ],
            "name": "Christine Tsai",
            "screen_name": "maigochan"
          }
        ]
      },
      "favorite_count": "0",
      "favorited": false,
      "full_text": "@maigochan Thanks for checking out Threading the Needle! We hope you enjoyed it!",
      "id_str": "214827326314258433",
      "in_reply_to_screen_name": "maigochan",
      "in_reply_to_status_id": "214609975731961856",
      "in_reply_to_status_id_str": "214609975731961856",
      "in_reply_to_user_id": "62348231",
      "in_reply_to_user_id_str": "62348231",
      "lang": "en",
      "retweet_count": "0",
      "retweeted": false,
      "source": "\u003ca href=\"https://about.twitter.com/products/tweetdeck\" rel=\"nofollow\"\u003eTweetDeck\u003c/a\u003e",
      "truncated": false
    },
    "wof:name": "Twitter message #214827326314258433",
    "wof:placetype": "custom"
  },
  "geometry": {"coordinates":[-122.386166,37.616356],"type":"Point"}
}
