{
  "type": "Feature",
  "properties": {
    "date:cessation_lower": "2021-05-05",
    "date:cessation_upper": "2021-05-05",
    "date:inception_lower": "2021-05-05",
    "date:inception_upper": "2021-05-05",
    "sfomuseum:placetype": "tweet",
    "twitter:tweet": {
      "created": 1620255079,
      "created_at": "Wed May 05 22:51:19 +0000 2021",
      "display_text_range": [
        "0",
        "232"
      ],
      "edit_info": {
        "initial": {
          "editTweetIds": [
            "1390076671051538437"
          ],
          "editableUntil": "2021-05-05T23:21:19.411Z",
          "editsRemaining": "5",
          "isEditEligible": true
        }
      },
      "entities": {
      },
      "favorite_count": "4",
      "favorited": false,
      "full_text": "📸:\nphoto: Hughes H-4 Hercules; 1947\nGift of Frank A. Norick\n2009.015.002\n\nmodel airplane: Hughes H-4 Hercules; 2002\nMade by and gift of Jim Lund\n2014.153.018 a e\n\nphoto: Hughes H-4 Hercules; 1947\nGift of Frank A. Norick\n2009.015.003",
      "id_str": "1390076671051538437",
      "in_reply_to_screen_name": "SFOMuseum",
      "in_reply_to_status_id": "1390076667389890561",
      "in_reply_to_status_id_str": "1390076667389890561",
      "in_reply_to_user_id": "116329337",
      "in_reply_to_user_id_str": "116329337",
      "lang": "en",
      "retweet_count": "0",
      "retweeted": false,
      "source": "\u003ca href=\"https://mobile.twitter.com\" rel=\"nofollow\"\u003eTwitter Web App\u003c/a\u003e",
      "truncated": false
    },
    "wof:name": "📸:\nphoto: Hughes H-4 Hercules; 1947\nGift of Frank A. Norick\n2009.015.002\n\nmodel airplane: Hughes H-4 Hercules; 2002\nMade by and gift of Jim Lund\n2014.153.018 a e\n\nphoto: Hughes H-4 Hercules; 1947\nGift of Frank A. Norick\n2009.015.003",
    "wof:placetype": "custom"
  },
  "geometry": {"coordinates":[-122.386166,37.616356],"type":"Point"}
}
