{
  "type": "Feature",
  "properties": {
    "sfomuseum:placetype": "tweet",
    "twitter:tweet": {
      "created": 1517533315,
      "created_at": "Fri Feb 02 01:01:55 +0000 2018",
      "display_text_range": [
        "0", 
        "197"
      ],
      "entities": {
        "hashtags": [
          {
            "indices": [
              "157", 
              "161"
            ],
            "text": "TBT"
          }, 
          {
            "indices": [
              "162", 
              "173"
            ],
            "text": "SFOHistory"
          }
        ],
        "media": [
          {
            "display_url": "pic.twitter.com/DECoHGRzdu",
            "expanded_url": "https://twitter.com/SFOMuseum/status/959230364274380803/photo/1",
            "id_str": "959230360885309441",
            "indices": [
              "174", 
              "197"
            ],
            "media_url": "http://pbs.twimg.com/media/DU_e7lZWsAEM8bB.jpg",
            "media_url_https": "https://pbs.twimg.com/media/DU_e7lZWsAEM8bB.jpg",
            "sizes": {
              "large": {
                "h": "1600",
                "resize": "fit",
                "w": "2000"
              },
              "medium": {
                "h": "960",
                "resize": "fit",
                "w": "1200"
              },
              "small": {
                "h": "544",
                "resize": "fit",
                "w": "680"
              },
              "thumb": {
                "h": "150",
                "resize": "crop",
                "w": "150"
              }
            },
            "type": "photo",
            "url": "https://t.co/DECoHGRzdu"
          }
        ]
      },
      "extended_entities": {
        "media": [
          {
            "display_url": "pic.twitter.com/DECoHGRzdu",
            "expanded_url": "https://twitter.com/SFOMuseum/status/959230364274380803/photo/1",
            "id_str": "959230360885309441",
            "indices": [
              "174", 
              "197"
            ],
            "media_url": "http://pbs.twimg.com/media/DU_e7lZWsAEM8bB.jpg",
            "media_url_https": "https://pbs.twimg.com/media/DU_e7lZWsAEM8bB.jpg",
            "sizes": {
              "large": {
                "h": "1600",
                "resize": "fit",
                "w": "2000"
              },
              "medium": {
                "h": "960",
                "resize": "fit",
                "w": "1200"
              },
              "small": {
                "h": "544",
                "resize": "fit",
                "w": "680"
              },
              "thumb": {
                "h": "150",
                "resize": "crop",
                "w": "150"
              }
            },
            "type": "photo",
            "url": "https://t.co/DECoHGRzdu"
          }
        ]
      },
      "favorite_count": "13",
      "favorited": false,
      "full_text": "Flight attendants from multiple airlines wave at the thousands of visitors below, part of the dedication ceremony for the Central Terminal (now T2) in 1954. #TBT #SFOHistory https://t.co/DECoHGRzdu",
      "id_str": "959230364274380803",
      "lang": "en",
      "possibly_sensitive": false,
      "retweet_count": "5",
      "retweeted": false,
      "source": "\u003ca href=\"http://www.hootsuite.com\" rel=\"nofollow\"\u003eHootsuite\u003c/a\u003e",
      "truncated": false
    },
    "wof:name": "Twitter message #959230364274380803",
    "wof:placetype": "custom"
  },
  "geometry": {"coordinates":[-122.386166,37.616356],"type":"Point"}
}
