{
  "type": "Feature",
  "properties": {
    "sfomuseum:placetype": "tweet",
    "twitter:tweet": {
      "created": 1509128706,
      "created_at": "Fri Oct 27 18:25:06 +0000 2017",
      "display_text_range": [
        "0", 
        "164"
      ],
      "entities": {
        "hashtags": [
          {
            "indices": [
              "122", 
              "140"
            ],
            "text": "empoweringthreads"
          }
        ],
        "media": [
          {
            "display_url": "pic.twitter.com/kkm7vxbz5Z",
            "expanded_url": "https://twitter.com/SFOMuseum/status/923978880242929665/photo/1",
            "id_str": "923978876275118081",
            "indices": [
              "141", 
              "164"
            ],
            "media_url": "http://pbs.twimg.com/media/DNKh5HxX0AEJ1kK.jpg",
            "media_url_https": "https://pbs.twimg.com/media/DNKh5HxX0AEJ1kK.jpg",
            "sizes": {
              "large": {
                "h": "1473",
                "resize": "fit",
                "w": "2000"
              },
              "medium": {
                "h": "884",
                "resize": "fit",
                "w": "1200"
              },
              "small": {
                "h": "501",
                "resize": "fit",
                "w": "680"
              },
              "thumb": {
                "h": "150",
                "resize": "crop",
                "w": "150"
              }
            },
            "type": "photo",
            "url": "https://t.co/kkm7vxbz5Z"
          }
        ]
      },
      "extended_entities": {
        "media": [
          {
            "display_url": "pic.twitter.com/kkm7vxbz5Z",
            "expanded_url": "https://twitter.com/SFOMuseum/status/923978880242929665/photo/1",
            "id_str": "923978876275118081",
            "indices": [
              "141", 
              "164"
            ],
            "media_url": "http://pbs.twimg.com/media/DNKh5HxX0AEJ1kK.jpg",
            "media_url_https": "https://pbs.twimg.com/media/DNKh5HxX0AEJ1kK.jpg",
            "sizes": {
              "large": {
                "h": "1473",
                "resize": "fit",
                "w": "2000"
              },
              "medium": {
                "h": "884",
                "resize": "fit",
                "w": "1200"
              },
              "small": {
                "h": "501",
                "resize": "fit",
                "w": "680"
              },
              "thumb": {
                "h": "150",
                "resize": "crop",
                "w": "150"
              }
            },
            "type": "photo",
            "url": "https://t.co/kkm7vxbz5Z"
          }
        ]
      },
      "favorite_count": "2",
      "favorited": false,
      "full_text": "“In the past the weaving process was very arduous. We cannot compare the work of our grandmothers with work we do today.” #empoweringthreads https://t.co/kkm7vxbz5Z",
      "id_str": "923978880242929665",
      "lang": "en",
      "possibly_sensitive": false,
      "retweet_count": "0",
      "retweeted": false,
      "source": "\u003ca href=\"http://www.hootsuite.com\" rel=\"nofollow\"\u003eHootsuite\u003c/a\u003e",
      "truncated": false
    },
    "wof:name": "Twitter message #923978880242929665",
    "wof:placetype": "custom"
  },
  "geometry": {"coordinates":[-122.386166,37.616356],"type":"Point"}
}
