{
  "type": "Feature",
  "properties": {
    "sfomuseum:placetype": "tweet",
    "twitter:tweet": {
      "created": 1544060704,
      "created_at": "Thu Dec 06 01:45:04 +0000 2018",
      "display_text_range": [
        "0", 
        "214"
      ],
      "entities": {
        "hashtags": [
          {
            "indices": [
              "113", 
              "121"
            ],
            "text": "uniform"
          }, 
          {
            "indices": [
              "183", 
              "190"
            ],
            "text": "avgeek"
          }
        ],
        "media": [
          {
            "display_url": "pic.twitter.com/QgcwSchHM8",
            "expanded_url": "https://twitter.com/SFOMuseum/status/1070494298217607168/photo/1",
            "id_str": "1070494295382208512",
            "indices": [
              "191", 
              "214"
            ],
            "media_url": "http://pbs.twimg.com/media/Dtso49JWsAAkZDe.jpg",
            "media_url_https": "https://pbs.twimg.com/media/Dtso49JWsAAkZDe.jpg",
            "sizes": {
              "large": {
                "h": "2000",
                "resize": "fit",
                "w": "1579"
              },
              "medium": {
                "h": "1200",
                "resize": "fit",
                "w": "947"
              },
              "small": {
                "h": "680",
                "resize": "fit",
                "w": "537"
              },
              "thumb": {
                "h": "150",
                "resize": "crop",
                "w": "150"
              }
            },
            "type": "photo",
            "url": "https://t.co/QgcwSchHM8"
          }
        ]
      },
      "extended_entities": {
        "media": [
          {
            "display_url": "pic.twitter.com/QgcwSchHM8",
            "expanded_url": "https://twitter.com/SFOMuseum/status/1070494298217607168/photo/1",
            "id_str": "1070494295382208512",
            "indices": [
              "191", 
              "214"
            ],
            "media_url": "http://pbs.twimg.com/media/Dtso49JWsAAkZDe.jpg",
            "media_url_https": "https://pbs.twimg.com/media/Dtso49JWsAAkZDe.jpg",
            "sizes": {
              "large": {
                "h": "2000",
                "resize": "fit",
                "w": "1579"
              },
              "medium": {
                "h": "1200",
                "resize": "fit",
                "w": "947"
              },
              "small": {
                "h": "680",
                "resize": "fit",
                "w": "537"
              },
              "thumb": {
                "h": "150",
                "resize": "crop",
                "w": "150"
              }
            },
            "type": "photo",
            "url": "https://t.co/QgcwSchHM8"
          }
        ]
      },
      "favorite_count": "7",
      "favorited": false,
      "full_text": "Dubbed “The Uniform for the Superjet Era,” and created for the new wide-body jet service, this 1971 Pan American #uniform marked a new direction in the airline's approach to fashion. #avgeek https://t.co/QgcwSchHM8",
      "id_str": "1070494298217607168",
      "lang": "en",
      "possibly_sensitive": false,
      "retweet_count": "2",
      "retweeted": false,
      "source": "\u003ca href=\"https://www.hootsuite.com\" rel=\"nofollow\"\u003eHootsuite Inc.\u003c/a\u003e",
      "truncated": false
    },
    "wof:name": "Twitter message #1070494298217607168",
    "wof:placetype": "custom"
  },
  "geometry": {"coordinates":[-122.386166,37.616356],"type":"Point"}
}
