{
  "type": "Feature",
  "properties": {
    "sfomuseum:placetype": "tweet",
    "twitter:tweet": {
      "created": 1541446138,
      "created_at": "Mon Nov 05 19:28:58 +0000 2018",
      "display_text_range": [
        "0", 
        "123"
      ],
      "entities": {
        "hashtags": [
          {
            "indices": [
              "20", 
              "34"
            ],
            "text": "RichardBarnes"
          }
        ],
        "urls": [
          {
            "display_url": "flysfo.com/museum/exhibit…",
            "expanded_url": "https://www.flysfo.com/museum/exhibitions/richard-barnes-murmur",
            "indices": [
              "100", 
              "123"
            ],
            "url": "https://t.co/U4xRqu1AfL"
          }
        ],
        "user_mentions": [
          {
            "id_str": "2680117375",
            "indices": [
              "0", 
              "7"
            ],
            "name": "liuche",
            "screen_name": "fliume"
          }
        ]
      },
      "favorite_count": "1",
      "favorited": false,
      "full_text": "@fliume \"Murmur\" by #RichardBarnes on display, pre-security, on the departures level of Terminal 3. https://t.co/U4xRqu1AfL",
      "id_str": "1059528016416530432",
      "in_reply_to_screen_name": "fliume",
      "in_reply_to_status_id": "1059174899590152193",
      "in_reply_to_status_id_str": "1059174899590152193",
      "in_reply_to_user_id": "2680117375",
      "in_reply_to_user_id_str": "2680117375",
      "lang": "en",
      "possibly_sensitive": false,
      "retweet_count": "0",
      "retweeted": false,
      "source": "\u003ca href=\"http://twitter.com\" rel=\"nofollow\"\u003eTwitter Web Client\u003c/a\u003e",
      "truncated": false
    },
    "wof:name": "Twitter message #1059528016416530432",
    "wof:placetype": "custom"
  },
  "geometry": {"coordinates":[-122.386166,37.616356],"type":"Point"}
}
