{
  "type": "Feature",
  "properties": {
    "date:cessation_lower": "2013-01-14",
    "date:cessation_upper": "2013-01-14",
    "date:inception_lower": "2013-01-14",
    "date:inception_upper": "2013-01-14",
    "iso:country": "US",
    "sfomuseum:placetype": "tweet",
    "twitter:tweet": {
      "created": 1358188398,
      "created_at": "Mon Jan 14 18:33:18 +0000 2013",
      "display_text_range": [
        "0",
        "36"
      ],
      "entities": {
        "user_mentions": [
          {
            "id_str": "32597513",
            "indices": [
              "0",
              "11"
            ],
            "name": "sonofabike",
            "screen_name": "sonofabike"
          }
        ]
      },
      "favorite_count": "0",
      "favorited": false,
      "full_text": "@sonofabike Our absolute pleasure :)",
      "id_str": "290889341453099009",
      "in_reply_to_screen_name": "sonofabike",
      "in_reply_to_status_id": "290889159323824130",
      "in_reply_to_status_id_str": "290889159323824130",
      "in_reply_to_user_id": "32597513",
      "in_reply_to_user_id_str": "32597513",
      "lang": "en",
      "retweet_count": "0",
      "retweeted": false,
      "source": "\u003ca href=\"https://about.twitter.com/products/tweetdeck\" rel=\"nofollow\"\u003eTweetDeck\u003c/a\u003e",
      "truncated": false
    },
    "wof:name": "@sonofabike Our absolute pleasure :)",
    "wof:placetype": "custom"
  },
  "geometry": {"coordinates":[-122.386166,37.616356],"type":"Point"}
}
