{
  "type": "Feature",
  "properties": {
    "sfomuseum:placetype": "tweet",
    "twitter:tweet": {
      "created": 1460578512,
      "created_at": "Wed Apr 13 20:15:12 +0000 2016",
      "display_text_range": [
        "0", 
        "136"
      ],
      "entities": {
        "hashtags": [
          {
            "indices": [
              "39", 
              "56"
            ],
            "text": "ArtAndDisability"
          }
        ],
        "media": [
          {
            "display_url": "pic.twitter.com/NwCvVAsinv",
            "expanded_url": "https://twitter.com/SFOMuseum/status/720344606332682241/photo/1",
            "id_str": "720344605028388864",
            "indices": [
              "113", 
              "136"
            ],
            "media_url": "http://pbs.twimg.com/media/Cf8tmgqWEAAh6PZ.jpg",
            "media_url_https": "https://pbs.twimg.com/media/Cf8tmgqWEAAh6PZ.jpg",
            "sizes": {
              "large": {
                "h": "1000",
                "resize": "fit",
                "w": "2000"
              },
              "medium": {
                "h": "600",
                "resize": "fit",
                "w": "1200"
              },
              "small": {
                "h": "340",
                "resize": "fit",
                "w": "680"
              },
              "thumb": {
                "h": "150",
                "resize": "crop",
                "w": "150"
              }
            },
            "type": "photo",
            "url": "https://t.co/NwCvVAsinv"
          }
        ],
        "urls": [
          {
            "display_url": "ow.ly/10Ddzb",
            "expanded_url": "http://ow.ly/10Ddzb",
            "indices": [
              "89", 
              "112"
            ],
            "url": "https://t.co/0aLRJGkxqa"
          }
        ]
      },
      "extended_entities": {
        "media": [
          {
            "display_url": "pic.twitter.com/NwCvVAsinv",
            "expanded_url": "https://twitter.com/SFOMuseum/status/720344606332682241/photo/1",
            "id_str": "720344605028388864",
            "indices": [
              "113", 
              "136"
            ],
            "media_url": "http://pbs.twimg.com/media/Cf8tmgqWEAAh6PZ.jpg",
            "media_url_https": "https://pbs.twimg.com/media/Cf8tmgqWEAAh6PZ.jpg",
            "sizes": {
              "large": {
                "h": "1000",
                "resize": "fit",
                "w": "2000"
              },
              "medium": {
                "h": "600",
                "resize": "fit",
                "w": "1200"
              },
              "small": {
                "h": "340",
                "resize": "fit",
                "w": "680"
              },
              "thumb": {
                "h": "150",
                "resize": "crop",
                "w": "150"
              }
            },
            "type": "photo",
            "url": "https://t.co/NwCvVAsinv"
          }
        ]
      },
      "favorite_count": "0",
      "favorited": false,
      "full_text": "See more art in “Celebrating a Vision: #ArtAndDisability”, post-security, in Terminal 3. https://t.co/0aLRJGkxqa https://t.co/NwCvVAsinv",
      "id_str": "720344606332682241",
      "lang": "en",
      "possibly_sensitive": false,
      "retweet_count": "0",
      "retweeted": false,
      "source": "\u003ca href=\"http://www.hootsuite.com\" rel=\"nofollow\"\u003eHootsuite\u003c/a\u003e",
      "truncated": false
    },
    "wof:name": "Twitter message #720344606332682241",
    "wof:placetype": "custom"
  },
  "geometry": {"coordinates":[-122.386166,37.616356],"type":"Point"}
}
