{
  "type": "Feature",
  "properties": {
    "sfomuseum:placetype": "tweet",
    "twitter:tweet": {
      "created": 1378857241,
      "created_at": "Tue Sep 10 23:54:01 +0000 2013",
      "display_text_range": [
        "0", 
        "73"
      ],
      "entities": {
        "user_mentions": [
          {
            "id_str": "14678484",
            "indices": [
              "0", 
              "12"
            ],
            "name": "Mike Collett",
            "screen_name": "mikecollett"
          }
        ]
      },
      "favorite_count": "0",
      "favorited": false,
      "full_text": "@mikecollett Thanks for the kind words and for checking out our exhibits!",
      "id_str": "377580754953580544",
      "in_reply_to_screen_name": "mikecollett",
      "in_reply_to_status_id": "377577141581258752",
      "in_reply_to_status_id_str": "377577141581258752",
      "in_reply_to_user_id": "14678484",
      "in_reply_to_user_id_str": "14678484",
      "lang": "en",
      "retweet_count": "0",
      "retweeted": false,
      "source": "\u003ca href=\"http://www.hootsuite.com\" rel=\"nofollow\"\u003eHootsuite\u003c/a\u003e",
      "truncated": false
    },
    "wof:name": "Twitter message #377580754953580544",
    "wof:placetype": "custom"
  },
  "geometry": {"coordinates":[-122.386166,37.616356],"type":"Point"}
}
