{
  "type": "Feature",
  "properties": {
    "date:cessation_lower": "2017-12-18",
    "date:cessation_upper": "2017-12-18",
    "date:inception_lower": "2017-12-18",
    "date:inception_upper": "2017-12-18",
    "iso:country": "US",
    "sfomuseum:placetype": "tweet",
    "twitter:tweet": {
      "created": 1513629884,
      "created_at": "Mon Dec 18 20:44:44 +0000 2017",
      "display_text_range": [
        "0",
        "140"
      ],
      "edit_info": {
        "initial": {
          "editTweetIds": [
            "942858191246782464"
          ],
          "editableUntil": "2017-12-18T21:14:44.908Z",
          "editsRemaining": "5",
          "isEditEligible": true
        }
      },
      "entities": {
        "user_mentions": [
          {
            "id_str": "1282791681616748547",
            "indices": [
              "3",
              "13"
            ],
            "name": "James E Russell",
            "screen_name": "e_russell"
          }
        ]
      },
      "favorite_count": "0",
      "favorited": false,
      "full_text": "RT @e_russell: Delta debuted its first 747, a -100, on flights from Atlanta to Los Angeles via Dallas on 25OCT70. It's map: https://t.co/zL…",
      "id_str": "942858191246782464",
      "lang": "en",
      "retweet_count": "0",
      "retweeted": false,
      "source": "\u003ca href=\"http://twitter.com\" rel=\"nofollow\"\u003eTwitter Web Client\u003c/a\u003e",
      "truncated": false
    },
    "wof:name": "RT @e_russell: Delta debuted its first 747, a -100, on flights from Atlanta to Los Angeles via Dallas on 25OCT70. It's map: https://t.co/zL…",
    "wof:placetype": "custom"
  },
  "geometry": {"coordinates":[-122.386166,37.616356],"type":"Point"}
}
