{
  "type": "Feature",
  "properties": {
    "sfomuseum:placetype": "tweet",
    "twitter:tweet": {
      "created": 1452573608,
      "created_at": "Tue Jan 12 04:40:08 +0000 2016",
      "display_text_range": [
        "0", 
        "128"
      ],
      "entities": {
        "hashtags": [
          {
            "indices": [
              "89", 
              "104"
            ],
            "text": "TheNationsGame"
          }
        ],
        "media": [
          {
            "display_url": "pic.twitter.com/Cdo2ce33hO",
            "expanded_url": "https://twitter.com/SFOMuseum/status/686769606531350528/photo/1",
            "id_str": "686769606296473600",
            "indices": [
              "105", 
              "128"
            ],
            "media_url": "http://pbs.twimg.com/media/CYflUXnWEAABZVC.jpg",
            "media_url_https": "https://pbs.twimg.com/media/CYflUXnWEAABZVC.jpg",
            "sizes": {
              "large": {
                "h": "480",
                "resize": "fit",
                "w": "312"
              },
              "medium": {
                "h": "480",
                "resize": "fit",
                "w": "312"
              },
              "small": {
                "h": "480",
                "resize": "fit",
                "w": "312"
              },
              "thumb": {
                "h": "150",
                "resize": "crop",
                "w": "150"
              }
            },
            "type": "photo",
            "url": "https://t.co/Cdo2ce33hO"
          }
        ],
        "user_mentions": [
          {
            "id_str": "43403778",
            "indices": [
              "7", 
              "13"
            ],
            "name": "San Francisco 49ers",
            "screen_name": "49ers"
          }
        ]
      },
      "extended_entities": {
        "media": [
          {
            "display_url": "pic.twitter.com/Cdo2ce33hO",
            "expanded_url": "https://twitter.com/SFOMuseum/status/686769606531350528/photo/1",
            "id_str": "686769606296473600",
            "indices": [
              "105", 
              "128"
            ],
            "media_url": "http://pbs.twimg.com/media/CYflUXnWEAABZVC.jpg",
            "media_url_https": "https://pbs.twimg.com/media/CYflUXnWEAABZVC.jpg",
            "sizes": {
              "large": {
                "h": "480",
                "resize": "fit",
                "w": "312"
              },
              "medium": {
                "h": "480",
                "resize": "fit",
                "w": "312"
              },
              "small": {
                "h": "480",
                "resize": "fit",
                "w": "312"
              },
              "thumb": {
                "h": "150",
                "resize": "crop",
                "w": "150"
              }
            },
            "type": "photo",
            "url": "https://t.co/Cdo2ce33hO"
          }
        ]
      },
      "favorite_count": "1",
      "favorited": false,
      "full_text": "Former @49ers Jerry Rice still holds the record for career receiving touchdowns, at 197. #TheNationsGame https://t.co/Cdo2ce33hO",
      "id_str": "686769606531350528",
      "lang": "en",
      "possibly_sensitive": false,
      "retweet_count": "0",
      "retweeted": false,
      "source": "\u003ca href=\"http://www.hootsuite.com\" rel=\"nofollow\"\u003eHootsuite\u003c/a\u003e",
      "truncated": false
    },
    "wof:name": "Twitter message #686769606531350528",
    "wof:placetype": "custom"
  },
  "geometry": {"coordinates":[-122.386166,37.616356],"type":"Point"}
}
