{
  "type": "Feature",
  "properties": {
    "date:cessation_lower": "2014-01-15",
    "date:cessation_upper": "2014-01-15",
    "date:inception_lower": "2014-01-15",
    "date:inception_upper": "2014-01-15",
    "iso:country": "US",
    "sfomuseum:placetype": "tweet",
    "twitter:tweet": {
      "created": 1389809195,
      "created_at": "Wed Jan 15 18:06:35 +0000 2014",
      "display_text_range": [
        "0",
        "52"
      ],
      "edit_info": {
        "initial": {
          "editTweetIds": [
            "423516577452281857"
          ],
          "editableUntil": "2014-01-15T19:06:35.279Z",
          "editsRemaining": "5",
          "isEditEligible": true
        }
      },
      "entities": {
        "user_mentions": [
          {
            "id_str": "70466017",
            "indices": [
              "0",
              "11"
            ],
            "name": "Tony Banthutham",
            "screen_name": "TonyCatoga"
          }
        ]
      },
      "favorite_count": "0",
      "favorited": false,
      "full_text": "@TonyCatoga Cool pic!  Glad you enjoyed our exhibit!",
      "id_str": "423516577452281857",
      "in_reply_to_screen_name": "TonyCatoga",
      "in_reply_to_status_id": "423514633748492288",
      "in_reply_to_status_id_str": "423514633748492288",
      "in_reply_to_user_id": "70466017",
      "in_reply_to_user_id_str": "70466017",
      "lang": "en",
      "retweet_count": "0",
      "retweeted": false,
      "source": "\u003ca href=\"http://www.hootsuite.com\" rel=\"nofollow\"\u003eHootsuite\u003c/a\u003e",
      "truncated": false
    },
    "twitter:user_mentions": [
      "TonyCatoga"
    ],
    "wof:name": "@TonyCatoga Cool pic!  Glad you enjoyed our exhibit!",
    "wof:placetype": "custom"
  },
  "geometry": {"coordinates":[-122.386166,37.616356],"type":"Point"}
}
