{
  "type": "Feature",
  "properties": {
    "sfomuseum:placetype": "tweet",
    "twitter:tweet": {
      "created": 1601056000,
      "created_at": "Fri Sep 25 17:46:40 +0000 2020",
      "display_text_range": [
        "0", 
        "140"
      ],
      "entities": {
        "user_mentions": [
          {
            "id_str": "2369668423",
            "indices": [
              "3", 
              "17"
            ],
            "name": "Frederic Jung",
            "screen_name": "Frederic_Jung"
          }, 
          {
            "id_str": "16408759",
            "indices": [
              "55", 
              "62"
            ],
            "name": "San Francisco International Airport (SFO) ✈️",
            "screen_name": "flySFO"
          }
        ]
      },
      "favorite_count": "0",
      "favorited": false,
      "full_text": "RT @Frederic_Jung: France is never far away : while at @flySFO, make sure to check out the wonderful exhibit of Zuber 19th century handcraf…",
      "id_str": "1309549897562030080",
      "lang": "en",
      "retweet_count": "0",
      "retweeted": false,
      "source": "\u003ca href=\"https://mobile.twitter.com\" rel=\"nofollow\"\u003eTwitter Web App\u003c/a\u003e",
      "truncated": false
    },
    "wof:name": "Twitter message #1309549897562030080",
    "wof:placetype": "custom"
  },
  "geometry": {"coordinates":[-122.386166,37.616356],"type":"Point"}
}
