{
  "type": "Feature",
  "properties": {
    "date:cessation_lower": "2023-05-08",
    "date:cessation_upper": "2023-05-08",
    "date:inception_lower": "2023-05-08",
    "date:inception_upper": "2023-05-08",
    "sfomuseum:placetype": "tweet",
    "twitter:tweet": {
      "created": 1683587410,
      "created_at": "Mon May 08 23:10:10 +0000 2023",
      "display_text_range": [
        "0",
        "221"
      ],
      "edit_info": {
        "initial": {
          "editTweetIds": [
            "1655711719006818304"
          ],
          "editableUntil": "2023-05-08T23:40:10.000Z",
          "editsRemaining": "5",
          "isEditEligible": false
        }
      },
      "entities": {
        "urls": [
          {
            "display_url": "bit.ly/MillsFieldSFO",
            "expanded_url": "https://bit.ly/MillsFieldSFO",
            "indices": [
              "91",
              "114"
            ],
            "url": "https://t.co/aL3GtInqlj"
          }
        ]
      },
      "favorite_count": "1",
      "favorited": false,
      "full_text": "“Mills Field and the San Francisco Airport” is on display in the SkyTerrace and online at: https://t.co/aL3GtInqlj \n\nThe SkyTerrace is located pre-security in Terminal 2 and is open from Friday to Monday from 10am to 6pm.",
      "id_str": "1655711719006818304",
      "in_reply_to_screen_name": "SFOMuseum",
      "in_reply_to_status_id": "1655711717400379394",
      "in_reply_to_status_id_str": "1655711717400379394",
      "in_reply_to_user_id": "116329337",
      "in_reply_to_user_id_str": "116329337",
      "lang": "en",
      "possibly_sensitive": false,
      "retweet_count": "0",
      "retweeted": false,
      "source": "\u003ca href=\"https://mobile.twitter.com\" rel=\"nofollow\"\u003eTwitter Web App\u003c/a\u003e",
      "truncated": false
    },
    "wof:name": "“Mills Field and the San Francisco Airport” is on display in the SkyTerrace and online at: https://t.co/aL3GtInqlj \n\nThe SkyTerrace is located pre-security in Terminal 2 and is open from Friday to Monday from 10am to 6pm.",
    "wof:placetype": "custom"
  },
  "geometry": {"coordinates":[-122.386166,37.616356],"type":"Point"}
}
