{
  "type": "Feature",
  "properties": {
    "date:cessation_lower": "2018-02-14",
    "date:cessation_upper": "2018-02-14",
    "date:inception_lower": "2018-02-14",
    "date:inception_upper": "2018-02-14",
    "iso:country": "US",
    "sfomuseum:placetype": "tweet",
    "twitter:tweet": {
      "created": 1518630351,
      "created_at": "Wed Feb 14 17:45:51 +0000 2018",
      "display_text_range": [
        "0",
        "95"
      ],
      "edit_info": {
        "initial": {
          "editTweetIds": [
            "963831668485345283"
          ],
          "editableUntil": "2018-02-14T18:45:51.550Z",
          "editsRemaining": "5",
          "isEditEligible": true
        }
      },
      "entities": {
        "urls": [
          {
            "display_url": "twitter.com/SFOMuseum/stat…",
            "expanded_url": "https://twitter.com/SFOMuseum/status/698945238510006272",
            "indices": [
              "72",
              "95"
            ],
            "url": "https://t.co/x4fI5ewyqm"
          }
        ],
        "user_mentions": [
          {
            "id_str": "95746689",
            "indices": [
              "3",
              "16"
            ],
            "name": "panamhistory",
            "screen_name": "panamhistory"
          },
          {
            "id_str": "116329337",
            "indices": [
              "61",
              "71"
            ],
            "name": "SFO Museum",
            "screen_name": "SFOMuseum"
          }
        ]
      },
      "favorite_count": "0",
      "favorited": false,
      "full_text": "RT @panamhistory: Happy Valentines Day! Wonderful image from @SFOMuseum https://t.co/x4fI5ewyqm",
      "id_str": "963831668485345283",
      "lang": "en",
      "possibly_sensitive": false,
      "retweet_count": "0",
      "retweeted": false,
      "source": "\u003ca href=\"http://www.hootsuite.com\" rel=\"nofollow\"\u003eHootsuite\u003c/a\u003e",
      "truncated": false
    },
    "twitter:user_mentions": [
      "panamhistory",
      "SFOMuseum"
    ],
    "wof:name": "RT @panamhistory: Happy Valentines Day! Wonderful image from @SFOMuseum https://t.co/x4fI5ewyqm",
    "wof:placetype": "custom"
  },
  "geometry": {"coordinates":[-122.386166,37.616356],"type":"Point"}
}
