{
  "type": "Feature",
  "properties": {
    "sfomuseum:placetype": "tweet",
    "twitter:tweet": {
      "created": 1334247371,
      "created_at": "Thu Apr 12 16:16:11 +0000 2012",
      "display_text_range": [
        "0", 
        "140"
      ],
      "entities": {
        "urls": [
          {
            "display_url": "instagr.am/p/JTYuAIOxYV/",
            "expanded_url": "http://instagr.am/p/JTYuAIOxYV/",
            "indices": [
              "120", 
              "140"
            ],
            "url": "http://t.co/liGj89aG"
          }
        ],
        "user_mentions": [
          {
            "id_str": "71186978",
            "indices": [
              "98", 
              "110"
            ],
            "name": "Ryan De La Hoz",
            "screen_name": "ryandelahoz"
          }
        ]
      },
      "favorite_count": "0",
      "favorited": false,
      "full_text": "Great pic- Marc Katano's \"Torso\" \u0026 Seiji Kunishima's \"Stacking Stones\" (which weighs 14 tons!) RT @ryandelahoz: SFO Art http://t.co/liGj89aG",
      "id_str": "190473397342441472",
      "lang": "en",
      "possibly_sensitive": false,
      "retweet_count": "0",
      "retweeted": false,
      "source": "\u003ca href=\"https://about.twitter.com/products/tweetdeck\" rel=\"nofollow\"\u003eTweetDeck\u003c/a\u003e",
      "truncated": false
    },
    "wof:name": "Twitter message #190473397342441472",
    "wof:placetype": "custom"
  },
  "geometry": {"coordinates":[-122.386166,37.616356],"type":"Point"}
}
