{
  "type": "Feature",
  "properties": {
    "sfomuseum:placetype": "tweet",
    "twitter:tweet": {
      "created": 1478552842,
      "created_at": "Mon Nov 07 21:07:22 +0000 2016",
      "display_text_range": [
        "0", 
        "144"
      ],
      "entities": {
        "user_mentions": [
          {
            "id_str": "69211886",
            "indices": [
              "3", 
              "19"
            ],
            "name": "Ramón Markus Kadi",
            "screen_name": "ramonmarkuskadi"
          }
        ]
      },
      "favorite_count": "0",
      "favorited": false,
      "full_text": "RT @ramonmarkuskadi: Don't forget to pick up the well designed exhibit brochures (past \u0026amp; present) and to find a poster within each brochure…",
      "id_str": "795734413493440512",
      "lang": "en",
      "retweet_count": "0",
      "retweeted": false,
      "source": "\u003ca href=\"http://twitter.com\" rel=\"nofollow\"\u003eTwitter Web Client\u003c/a\u003e",
      "truncated": false
    },
    "wof:name": "Twitter message #795734413493440512",
    "wof:placetype": "custom"
  },
  "geometry": {"coordinates":[-122.386166,37.616356],"type":"Point"}
}
