{
  "type": "Feature",
  "properties": {
    "date:cessation_lower": "2012-02-23",
    "date:cessation_upper": "2012-02-23",
    "date:inception_lower": "2012-02-23",
    "date:inception_upper": "2012-02-23",
    "iso:country": "US",
    "sfomuseum:placetype": "tweet",
    "twitter:tweet": {
      "created": 1330016265,
      "created_at": "Thu Feb 23 16:57:45 +0000 2012",
      "display_text_range": [
        "0",
        "84"
      ],
      "edit_info": {
        "initial": {
          "editTweetIds": [
            "172726854959112192"
          ],
          "editableUntil": "2012-02-23T17:57:45.989Z",
          "editsRemaining": "5",
          "isEditEligible": true
        }
      },
      "entities": {
        "user_mentions": [
          {
            "id_str": "150802319",
            "indices": [
              "0",
              "11"
            ],
            "name": "superchunk",
            "screen_name": "superchunk"
          }
        ]
      },
      "favorite_count": "0",
      "favorited": false,
      "full_text": "@superchunk Nice photo! Thanks for checking out our exhibit, Revolutions per Minute!",
      "id_str": "172726854959112192",
      "in_reply_to_screen_name": "superchunk",
      "in_reply_to_status_id": "172483016231362562",
      "in_reply_to_status_id_str": "172483016231362562",
      "in_reply_to_user_id": "150802319",
      "in_reply_to_user_id_str": "150802319",
      "lang": "en",
      "retweet_count": "0",
      "retweeted": false,
      "source": "\u003ca href=\"https://about.twitter.com/products/tweetdeck\" rel=\"nofollow\"\u003eTweetDeck\u003c/a\u003e",
      "truncated": false
    },
    "twitter:user_mentions": [
      "superchunk"
    ],
    "wof:name": "@superchunk Nice photo! Thanks for checking out our exhibit, Revolutions per Minute!",
    "wof:placetype": "custom",
    "wof:placetype_alt": [
      "tweet"
    ]
  },
  "geometry": {"coordinates":[-122.386166,37.616356],"type":"Point"}
}
