{
  "type": "Feature",
  "properties": {
    "date:cessation_lower":"2011-12-02",
    "date:cessation_upper":"2011-12-02",
    "date:inception_lower":"2011-12-02",
    "date:inception_upper":"2011-12-02",
    "iso:country":"US",
    "sfomuseum:placetype":"tweet",
    "twitter:tweet":{
        "created":1322883321,
        "created_at":"Sat Dec 03 03:35:21 +0000 2011",
        "display_text_range":[
            "0",
            "103"
        ],
        "entities":{
            "urls":[
                {
                    "display_url":"ow.ly/i/mDer",
                    "expanded_url":"http://ow.ly/i/mDer",
                    "indices":[
                        "83",
                        "103"
                    ],
                    "url":"http://t.co/c23riUPP"
                }
            ],
            "user_mentions":[
                {
                    "id_str":"21543254",
                    "indices":[
                        "62",
                        "70"
                    ],
                    "name":"DJ Q*BERT",
                    "screen_name":"DJQbert"
                }
            ]
        },
        "favorite_count":"0",
        "favorited":false,
        "full_text":"Airplanes aren't the only thing up in the air here! Swag from @DJQbert goes flying http://t.co/c23riUPP",
        "id_str":"142809116807675904",
        "lang":"en",
        "possibly_sensitive":false,
        "retweet_count":"1",
        "retweeted":false,
        "source":"<a href=\"http://www.hootsuite.com\" rel=\"nofollow\">Hootsuite</a>",
        "truncated":false
    },
    "wof:name":"Airplanes aren't the only thing up in the air here! Swag from @DJQbert goes flying http://t.co/c23riUPP",
    "wof:placetype":"custom"
},
  "geometry": {"coordinates":[-122.386166,37.616356],"type":"Point"}
}