{
  "type": "Feature",
  "properties": {
    "sfomuseum:placetype": "tweet",
    "twitter:tweet": {
      "created": 1453346705,
      "created_at": "Thu Jan 21 03:25:05 +0000 2016",
      "display_text_range": [
        "0", 
        "140"
      ],
      "entities": {
        "hashtags": [
          {
            "indices": [
              "107", 
              "116"
            ],
            "text": "PondFarm"
          }
        ],
        "media": [
          {
            "display_url": "pic.twitter.com/wphAe67uUk",
            "expanded_url": "https://twitter.com/SFOMuseum/status/690012208726687745/photo/1",
            "id_str": "690012206981890048",
            "indices": [
              "117", 
              "140"
            ],
            "media_url": "http://pbs.twimg.com/media/CZNqckfWwAA5RAF.jpg",
            "media_url_https": "https://pbs.twimg.com/media/CZNqckfWwAA5RAF.jpg",
            "sizes": {
              "large": {
                "h": "1508",
                "resize": "fit",
                "w": "2048"
              },
              "medium": {
                "h": "884",
                "resize": "fit",
                "w": "1200"
              },
              "small": {
                "h": "501",
                "resize": "fit",
                "w": "680"
              },
              "thumb": {
                "h": "150",
                "resize": "crop",
                "w": "150"
              }
            },
            "type": "photo",
            "url": "https://t.co/wphAe67uUk"
          }
        ],
        "urls": [
          {
            "display_url": "ow.ly/Xleq4",
            "expanded_url": "http://ow.ly/Xleq4",
            "indices": [
              "83", 
              "106"
            ],
            "url": "https://t.co/aKh7PUbYhZ"
          }
        ]
      },
      "extended_entities": {
        "media": [
          {
            "display_url": "pic.twitter.com/wphAe67uUk",
            "expanded_url": "https://twitter.com/SFOMuseum/status/690012208726687745/photo/1",
            "id_str": "690012206981890048",
            "indices": [
              "117", 
              "140"
            ],
            "media_url": "http://pbs.twimg.com/media/CZNqckfWwAA5RAF.jpg",
            "media_url_https": "https://pbs.twimg.com/media/CZNqckfWwAA5RAF.jpg",
            "sizes": {
              "large": {
                "h": "1508",
                "resize": "fit",
                "w": "2048"
              },
              "medium": {
                "h": "884",
                "resize": "fit",
                "w": "1200"
              },
              "small": {
                "h": "501",
                "resize": "fit",
                "w": "680"
              },
              "thumb": {
                "h": "150",
                "resize": "crop",
                "w": "150"
              }
            },
            "type": "photo",
            "url": "https://t.co/wphAe67uUk"
          }
        ]
      },
      "favorite_count": "0",
      "favorited": false,
      "full_text": "Learn about Marguerite Wildenhain’s life in \"A Potter's Life\" postsecurity in T2   https://t.co/aKh7PUbYhZ #PondFarm https://t.co/wphAe67uUk",
      "id_str": "690012208726687745",
      "lang": "en",
      "possibly_sensitive": false,
      "retweet_count": "0",
      "retweeted": false,
      "source": "\u003ca href=\"http://www.hootsuite.com\" rel=\"nofollow\"\u003eHootsuite\u003c/a\u003e",
      "truncated": false
    },
    "wof:name": "Twitter message #690012208726687745",
    "wof:placetype": "custom"
  },
  "geometry": {"coordinates":[-122.386166,37.616356],"type":"Point"}
}
