{
  "type": "Feature",
  "properties": {
    "date:cessation_lower": "2014-12-30",
    "date:cessation_upper": "2014-12-30",
    "date:inception_lower": "2014-12-30",
    "date:inception_upper": "2014-12-30",
    "iso:country": "US",
    "sfomuseum:placetype": "tweet",
    "twitter:tweet": {
      "created": 1419960311,
      "created_at": "Tue Dec 30 17:25:11 +0000 2014",
      "display_text_range": [
        "0",
        "132"
      ],
      "edit_info": {
        "initial": {
          "editTweetIds": [
            "549979525485182976"
          ],
          "editableUntil": "2014-12-30T17:55:11.658Z",
          "editsRemaining": "5",
          "isEditEligible": true
        }
      },
      "entities": {
        "user_mentions": [
          {
            "id_str": "1598411",
            "indices": [
              "0",
              "16"
            ],
            "name": "Todd Lappin",
            "screen_name": "TelstarLogistic"
          },
          {
            "id_str": "16408759",
            "indices": [
              "103",
              "110"
            ],
            "name": "San Francisco International Airport (SFO) ✈️",
            "screen_name": "flySFO"
          }
        ]
      },
      "favorite_count": "3",
      "favorited": false,
      "full_text": "@telstarlogistic *Love* the factoid about 36 million annual passengers for all US airlines! Last year, @flySFO alone had 44 million.",
      "id_str": "549979525485182976",
      "in_reply_to_screen_name": "TelstarLogistic",
      "in_reply_to_status_id": "549792578527170560",
      "in_reply_to_status_id_str": "549792578527170560",
      "in_reply_to_user_id": "1598411",
      "in_reply_to_user_id_str": "1598411",
      "lang": "en",
      "retweet_count": "3",
      "retweeted": false,
      "source": "\u003ca href=\"http://www.hootsuite.com\" rel=\"nofollow\"\u003eHootsuite\u003c/a\u003e",
      "truncated": false
    },
    "wof:name": "@telstarlogistic *Love* the factoid about 36 million annual passengers for all US airlines! Last year, @flySFO alone had 44 million.",
    "wof:placetype": "custom"
  },
  "geometry": {"coordinates":[-122.386166,37.616356],"type":"Point"}
}
