{
  "type": "Feature",
  "properties": {
    "sfomuseum:placetype": "tweet",
    "twitter:tweet": {
      "created": 1444790111,
      "created_at": "Wed Oct 14 02:35:11 +0000 2015",
      "display_text_range": [
        "0", 
        "136"
      ],
      "entities": {
        "hashtags": [
          {
            "indices": [
              "99", 
              "113"
            ],
            "text": "KirksMonsters"
          }
        ],
        "media": [
          {
            "display_url": "pic.twitter.com/ZfUp9DmFYK",
            "expanded_url": "https://twitter.com/SFOMuseum/status/654123252512636930/photo/1",
            "id_str": "654123251933806593",
            "indices": [
              "114", 
              "136"
            ],
            "media_url": "http://pbs.twimg.com/media/CRPpocbWgAE7yjo.jpg",
            "media_url_https": "https://pbs.twimg.com/media/CRPpocbWgAE7yjo.jpg",
            "sizes": {
              "large": {
                "h": "1387",
                "resize": "fit",
                "w": "2048"
              },
              "medium": {
                "h": "813",
                "resize": "fit",
                "w": "1200"
              },
              "small": {
                "h": "461",
                "resize": "fit",
                "w": "680"
              },
              "thumb": {
                "h": "150",
                "resize": "crop",
                "w": "150"
              }
            },
            "type": "photo",
            "url": "http://t.co/ZfUp9DmFYK"
          }
        ]
      },
      "extended_entities": {
        "media": [
          {
            "display_url": "pic.twitter.com/ZfUp9DmFYK",
            "expanded_url": "https://twitter.com/SFOMuseum/status/654123252512636930/photo/1",
            "id_str": "654123251933806593",
            "indices": [
              "114", 
              "136"
            ],
            "media_url": "http://pbs.twimg.com/media/CRPpocbWgAE7yjo.jpg",
            "media_url_https": "https://pbs.twimg.com/media/CRPpocbWgAE7yjo.jpg",
            "sizes": {
              "large": {
                "h": "1387",
                "resize": "fit",
                "w": "2048"
              },
              "medium": {
                "h": "813",
                "resize": "fit",
                "w": "1200"
              },
              "small": {
                "h": "461",
                "resize": "fit",
                "w": "680"
              },
              "thumb": {
                "h": "150",
                "resize": "crop",
                "w": "150"
              }
            },
            "type": "photo",
            "url": "http://t.co/ZfUp9DmFYK"
          }
        ]
      },
      "favorite_count": "3",
      "favorited": false,
      "full_text": "One of Boris Karloff's most famous roles included Frankenstein’s Monster in 'Frankenstein' (1931). #KirksMonsters http://t.co/ZfUp9DmFYK",
      "id_str": "654123252512636930",
      "lang": "en",
      "possibly_sensitive": false,
      "retweet_count": "1",
      "retweeted": false,
      "source": "\u003ca href=\"http://www.hootsuite.com\" rel=\"nofollow\"\u003eHootsuite\u003c/a\u003e",
      "truncated": false
    },
    "wof:name": "Twitter message #654123252512636930",
    "wof:placetype": "custom"
  },
  "geometry": {"coordinates":[-122.386166,37.616356],"type":"Point"}
}
