{
  "type": "Feature",
  "properties": {
    "sfomuseum:placetype": "tweet",
    "twitter:tweet": {
      "created": 1374772027,
      "created_at": "Thu Jul 25 17:07:07 +0000 2013",
      "display_text_range": [
        "0", 
        "122"
      ],
      "entities": {
        "hashtags": [
          {
            "indices": [
              "27", 
              "36"
            ],
            "text": "Ultraman"
          }
        ],
        "urls": [
          {
            "display_url": "instagram.com/p/cMk2pwRk-C/",
            "expanded_url": "http://instagram.com/p/cMk2pwRk-C/",
            "indices": [
              "100", 
              "122"
            ],
            "url": "http://t.co/hgbQD7gbE3"
          }
        ]
      },
      "favorite_count": "0",
      "favorited": false,
      "full_text": "Rawr! Large, rare Red King #Ultraman monster is checking in for pre-exhibition condition reporting. http://t.co/hgbQD7gbE3",
      "id_str": "360446126345822209",
      "lang": "en",
      "possibly_sensitive": false,
      "retweet_count": "0",
      "retweeted": false,
      "source": "\u003ca href=\"http://instagram.com\" rel=\"nofollow\"\u003eInstagram\u003c/a\u003e",
      "truncated": false
    },
    "wof:name": "Twitter message #360446126345822209",
    "wof:placetype": "custom"
  },
  "geometry": {"coordinates":[-122.386166,37.616356],"type":"Point"}
}
