{
  "type": "Feature",
  "properties": {
    "sfomuseum:placetype": "tweet",
    "twitter:tweet": {
      "created": 1542136452,
      "created_at": "Tue Nov 13 19:14:12 +0000 2018",
      "display_text_range": [
        "0", 
        "53"
      ],
      "entities": {
        "hashtags": [
          {
            "indices": [
              "20", 
              "29"
            ],
            "text": "caticons"
          }
        ],
        "urls": [
          {
            "display_url": "twitter.com/tunneIsnakes/s…",
            "expanded_url": "https://twitter.com/tunneIsnakes/status/1061381946486358016",
            "indices": [
              "30", 
              "53"
            ],
            "url": "https://t.co/ORh4f7MhuN"
          }
        ]
      },
      "favorite_count": "3",
      "favorited": false,
      "full_text": "😹 😹 😹 @Caticonsbook #caticons https://t.co/ORh4f7MhuN",
      "id_str": "1062423401468284928",
      "lang": "und",
      "possibly_sensitive": false,
      "retweet_count": "0",
      "retweeted": false,
      "source": "\u003ca href=\"http://twitter.com\" rel=\"nofollow\"\u003eTwitter Web Client\u003c/a\u003e",
      "truncated": false
    },
    "wof:name": "Twitter message #1062423401468284928",
    "wof:placetype": "custom"
  },
  "geometry": {"coordinates":[-122.386166,37.616356],"type":"Point"}
}
