{
  "type": "Feature",
  "properties": {
    "sfomuseum:placetype": "tweet",
    "twitter:tweet": {
      "created": 1487033705,
      "created_at": "Tue Feb 14 00:55:05 +0000 2017",
      "display_text_range": [
        "0", 
        "161"
      ],
      "entities": {
        "hashtags": [
          {
            "indices": [
              "124", 
              "137"
            ],
            "text": "PrintToPlate"
          }
        ],
        "media": [
          {
            "display_url": "pic.twitter.com/l2jzpBsxb8",
            "expanded_url": "https://twitter.com/SFOMuseum/status/831305727922823169/photo/1",
            "id_str": "831305724483555328",
            "indices": [
              "138", 
              "161"
            ],
            "media_url": "http://pbs.twimg.com/media/C4lkJueXUAAX5p7.jpg",
            "media_url_https": "https://pbs.twimg.com/media/C4lkJueXUAAX5p7.jpg",
            "sizes": {
              "large": {
                "h": "1473",
                "resize": "fit",
                "w": "2000"
              },
              "medium": {
                "h": "884",
                "resize": "fit",
                "w": "1200"
              },
              "small": {
                "h": "501",
                "resize": "fit",
                "w": "680"
              },
              "thumb": {
                "h": "150",
                "resize": "crop",
                "w": "150"
              }
            },
            "type": "photo",
            "url": "https://t.co/l2jzpBsxb8"
          }
        ]
      },
      "extended_entities": {
        "media": [
          {
            "display_url": "pic.twitter.com/l2jzpBsxb8",
            "expanded_url": "https://twitter.com/SFOMuseum/status/831305727922823169/photo/1",
            "id_str": "831305724483555328",
            "indices": [
              "138", 
              "161"
            ],
            "media_url": "http://pbs.twimg.com/media/C4lkJueXUAAX5p7.jpg",
            "media_url_https": "https://pbs.twimg.com/media/C4lkJueXUAAX5p7.jpg",
            "sizes": {
              "large": {
                "h": "1473",
                "resize": "fit",
                "w": "2000"
              },
              "medium": {
                "h": "884",
                "resize": "fit",
                "w": "1200"
              },
              "small": {
                "h": "501",
                "resize": "fit",
                "w": "680"
              },
              "thumb": {
                "h": "150",
                "resize": "crop",
                "w": "150"
              }
            },
            "type": "photo",
            "url": "https://t.co/l2jzpBsxb8"
          }
        ]
      },
      "favorite_count": "0",
      "favorited": false,
      "full_text": "Luigi Mayer created the illustration on this soup tureen from his travels through the Ottoman Empire between 1776 and 1794. #PrintToPlate https://t.co/l2jzpBsxb8",
      "id_str": "831305727922823169",
      "lang": "en",
      "possibly_sensitive": false,
      "retweet_count": "0",
      "retweeted": false,
      "source": "\u003ca href=\"http://www.hootsuite.com\" rel=\"nofollow\"\u003eHootsuite\u003c/a\u003e",
      "truncated": false
    },
    "wof:name": "Twitter message #831305727922823169",
    "wof:placetype": "custom"
  },
  "geometry": {"coordinates":[-122.386166,37.616356],"type":"Point"}
}
