{
  "type": "Feature",
  "properties": {
    "sfomuseum:placetype": "tweet",
    "twitter:tweet": {
      "created": 1577821205,
      "created_at": "Tue Dec 31 19:40:05 +0000 2019",
      "display_text_range": [
        "0", 
        "199"
      ],
      "entities": {
        "hashtags": [
          {
            "indices": [
              "161", 
              "175"
            ],
            "text": "1950sConsumer"
          }
        ],
        "media": [
          {
            "display_url": "pic.twitter.com/y5AZjx31Ju",
            "expanded_url": "https://twitter.com/SFOMuseum/status/1212096102784290817/photo/1",
            "id_str": "1212096099755986945",
            "indices": [
              "176", 
              "199"
            ],
            "media_url": "http://pbs.twimg.com/media/ENI6-xOXkAEl5AB.jpg",
            "media_url_https": "https://pbs.twimg.com/media/ENI6-xOXkAEl5AB.jpg",
            "sizes": {
              "large": {
                "h": "960",
                "resize": "fit",
                "w": "1440"
              },
              "medium": {
                "h": "800",
                "resize": "fit",
                "w": "1200"
              },
              "small": {
                "h": "453",
                "resize": "fit",
                "w": "680"
              },
              "thumb": {
                "h": "150",
                "resize": "crop",
                "w": "150"
              }
            },
            "type": "photo",
            "url": "https://t.co/y5AZjx31Ju"
          }
        ],
        "urls": [
          {
            "display_url": "bit.ly/1950sConsumer",
            "expanded_url": "http://bit.ly/1950sConsumer",
            "indices": [
              "137", 
              "160"
            ],
            "url": "https://t.co/A9goh7obtY"
          }
        ]
      },
      "extended_entities": {
        "media": [
          {
            "display_url": "pic.twitter.com/y5AZjx31Ju",
            "expanded_url": "https://twitter.com/SFOMuseum/status/1212096102784290817/photo/1",
            "id_str": "1212096099755986945",
            "indices": [
              "176", 
              "199"
            ],
            "media_url": "http://pbs.twimg.com/media/ENI6-xOXkAEl5AB.jpg",
            "media_url_https": "https://pbs.twimg.com/media/ENI6-xOXkAEl5AB.jpg",
            "sizes": {
              "large": {
                "h": "960",
                "resize": "fit",
                "w": "1440"
              },
              "medium": {
                "h": "800",
                "resize": "fit",
                "w": "1200"
              },
              "small": {
                "h": "453",
                "resize": "fit",
                "w": "680"
              },
              "thumb": {
                "h": "150",
                "resize": "crop",
                "w": "150"
              }
            },
            "type": "photo",
            "url": "https://t.co/y5AZjx31Ju"
          }
        ]
      },
      "favorite_count": "6",
      "favorited": false,
      "full_text": "\"The Modern Consumer: Products and Style\" is on display, post-security, in Terminal 3. Catch it before it closes at the end of the week. https://t.co/A9goh7obtY #1950sConsumer https://t.co/y5AZjx31Ju",
      "id_str": "1212096102784290817",
      "lang": "en",
      "possibly_sensitive": false,
      "retweet_count": "1",
      "retweeted": false,
      "source": "\u003ca href=\"https://www.hootsuite.com\" rel=\"nofollow\"\u003eHootsuite Inc.\u003c/a\u003e",
      "truncated": false
    },
    "wof:name": "Twitter message #1212096102784290817",
    "wof:placetype": "custom"
  },
  "geometry": {"coordinates":[-122.386166,37.616356],"type":"Point"}
}
