{
  "type": "Feature",
  "properties": {
    "sfomuseum:placetype": "tweet",
    "twitter:tweet": {
      "created": 1520193622,
      "created_at": "Sun Mar 04 20:00:22 +0000 2018",
      "display_text_range": [
        "0", 
        "248"
      ],
      "entities": {
        "hashtags": [
          {
            "indices": [
              "173", 
              "185"
            ],
            "text": "AntoineBruy"
          }
        ],
        "media": [
          {
            "display_url": "pic.twitter.com/zoYWvIJnvL",
            "expanded_url": "https://twitter.com/SFOMuseum/status/970388501261881349/photo/1",
            "id_str": "970388497390424064",
            "indices": [
              "225", 
              "248"
            ],
            "media_url": "http://pbs.twimg.com/media/DXeDMnEU0AAD7e-.jpg",
            "media_url_https": "https://pbs.twimg.com/media/DXeDMnEU0AAD7e-.jpg",
            "sizes": {
              "large": {
                "h": "2000",
                "resize": "fit",
                "w": "2000"
              },
              "medium": {
                "h": "1200",
                "resize": "fit",
                "w": "1200"
              },
              "small": {
                "h": "680",
                "resize": "fit",
                "w": "680"
              },
              "thumb": {
                "h": "150",
                "resize": "crop",
                "w": "150"
              }
            },
            "type": "photo",
            "url": "https://t.co/zoYWvIJnvL"
          }
        ]
      },
      "extended_entities": {
        "media": [
          {
            "display_url": "pic.twitter.com/zoYWvIJnvL",
            "expanded_url": "https://twitter.com/SFOMuseum/status/970388501261881349/photo/1",
            "id_str": "970388497390424064",
            "indices": [
              "225", 
              "248"
            ],
            "media_url": "http://pbs.twimg.com/media/DXeDMnEU0AAD7e-.jpg",
            "media_url_https": "https://pbs.twimg.com/media/DXeDMnEU0AAD7e-.jpg",
            "sizes": {
              "large": {
                "h": "2000",
                "resize": "fit",
                "w": "2000"
              },
              "medium": {
                "h": "1200",
                "resize": "fit",
                "w": "1200"
              },
              "small": {
                "h": "680",
                "resize": "fit",
                "w": "680"
              },
              "thumb": {
                "h": "150",
                "resize": "crop",
                "w": "150"
              }
            },
            "type": "photo",
            "url": "https://t.co/zoYWvIJnvL"
          }
        ]
      },
      "favorite_count": "1",
      "favorited": false,
      "full_text": "Using the World Wide Opportunities on Organic Farms (WWOOF) network to locate individuals and communities practicing subsistence farming and using renewable energy sources, #AntoineBruy visited people living in remote areas. https://t.co/zoYWvIJnvL",
      "id_str": "970388501261881349",
      "lang": "en",
      "possibly_sensitive": false,
      "retweet_count": "1",
      "retweeted": false,
      "source": "\u003ca href=\"http://www.hootsuite.com\" rel=\"nofollow\"\u003eHootsuite\u003c/a\u003e",
      "truncated": false
    },
    "wof:name": "Twitter message #970388501261881349",
    "wof:placetype": "custom"
  },
  "geometry": {"coordinates":[-122.386166,37.616356],"type":"Point"}
}
