{
  "type": "Feature",
  "properties": {
    "date:cessation_lower": "2012-05-25",
    "date:cessation_upper": "2012-05-25",
    "date:inception_lower": "2012-05-25",
    "date:inception_upper": "2012-05-25",
    "iso:country": "US",
    "sfomuseum:placetype": "tweet",
    "twitter:tweet": {
      "created": 1337979654,
      "created_at": "Fri May 25 21:00:54 +0000 2012",
      "display_text_range": [
        "0",
        "137"
      ],
      "entities": {
        "urls": [
          {
            "display_url": "n.pr/K6nTz5",
            "expanded_url": "http://n.pr/K6nTz5",
            "indices": [
              "74",
              "94"
            ],
            "url": "http://t.co/dwoUhMtX"
          }
        ]
      },
      "favorite_count": "0",
      "favorited": false,
      "full_text": "Exciting re: 1st commercial spacecraft docking w/the Int'l Space Station! http://t.co/dwoUhMtX What will the next 100yrs of flight offer?",
      "id_str": "206127728074825729",
      "lang": "en",
      "possibly_sensitive": false,
      "retweet_count": "2",
      "retweeted": false,
      "source": "\u003ca href=\"https://about.twitter.com/products/tweetdeck\" rel=\"nofollow\"\u003eTweetDeck\u003c/a\u003e",
      "truncated": false
    },
    "wof:name": "Exciting re: 1st commercial spacecraft docking w/the Int'l Space Station! http://t.co/dwoUhMtX What will the next 100yrs of flight offer?",
    "wof:placetype": "custom"
  },
  "geometry": {"coordinates":[-122.386166,37.616356],"type":"Point"}
}
