{
  "type": "Feature",
  "properties": {
    "sfomuseum:placetype": "tweet",
    "twitter:tweet": {
      "created": 1491859894,
      "created_at": "Mon Apr 10 21:31:34 +0000 2017",
      "display_text_range": [
        "0", 
        "140"
      ],
      "entities": {
        "user_mentions": [
          {
            "id_str": "24016767",
            "indices": [
              "3", 
              "18"
            ],
            "name": "USA TODAY Travel",
            "screen_name": "usatodaytravel"
          }
        ]
      },
      "favorite_count": "0",
      "favorited": false,
      "full_text": "RT @usatodaytravel: Born in 1967: Boeing's workhorse 737, the world's most popular passenger plane, hits half century mark https://t.co/zFA…",
      "id_str": "851548232534675456",
      "lang": "en",
      "retweet_count": "0",
      "retweeted": false,
      "source": "\u003ca href=\"http://www.hootsuite.com\" rel=\"nofollow\"\u003eHootsuite\u003c/a\u003e",
      "truncated": false
    },
    "wof:name": "Twitter message #851548232534675456",
    "wof:placetype": "custom"
  },
  "geometry": {"coordinates":[-122.386166,37.616356],"type":"Point"}
}
