{
  "type": "Feature",
  "properties": {
    "date:cessation_lower": "2012-03-13",
    "date:cessation_upper": "2012-03-13",
    "date:inception_lower": "2012-03-13",
    "date:inception_upper": "2012-03-13",
    "iso:country": "US",
    "sfomuseum:placetype": "tweet",
    "twitter:tweet": {
      "created": 1331675120,
      "created_at": "Tue Mar 13 21:45:20 +0000 2012",
      "display_text_range": [
        "0",
        "136"
      ],
      "edit_info": {
        "initial": {
          "editTweetIds": [
            "179684596726759425"
          ],
          "editableUntil": "2012-03-13T22:15:20.895Z",
          "editsRemaining": "5",
          "isEditEligible": true
        }
      },
      "entities": {
        "urls": [
          {
            "display_url": "bit.ly/A5z1wv",
            "expanded_url": "http://bit.ly/A5z1wv",
            "indices": [
              "116",
              "136"
            ],
            "url": "http://t.co/wcxycS3s"
          }
        ]
      },
      "favorite_count": "0",
      "favorited": false,
      "full_text": "It's tea time! In the 1930s, United Air Lines used lightweight Bakelite serving ware for their \"Mainline\" services. http://t.co/wcxycS3s",
      "id_str": "179684596726759425",
      "lang": "en",
      "possibly_sensitive": false,
      "retweet_count": "0",
      "retweeted": false,
      "source": "\u003ca href=\"https://about.twitter.com/products/tweetdeck\" rel=\"nofollow\"\u003eTweetDeck\u003c/a\u003e",
      "truncated": false
    },
    "wof:name": "It's tea time! In the 1930s, United Air Lines used lightweight Bakelite serving ware for their \"Mainline\" services. http://t.co/wcxycS3s",
    "wof:placetype": "custom"
  },
  "geometry": {"coordinates":[-122.386166,37.616356],"type":"Point"}
}
