{
  "type": "Feature",
  "properties": {
    "date:cessation_lower": "2021-11-01",
    "date:cessation_upper": "2021-11-01",
    "date:inception_lower": "2021-11-01",
    "date:inception_upper": "2021-11-01",
    "sfomuseum:placetype": "tweet",
    "twitter:tweet": {
      "created": 1635789269,
      "created_at": "Mon Nov 01 17:54:29 +0000 2021",
      "display_text_range": [
        "0",
        "140"
      ],
      "edit_info": {
        "initial": {
          "editTweetIds": [
            "1455231787039268871"
          ],
          "editableUntil": "2021-11-01T18:24:29.586Z",
          "editsRemaining": "5",
          "isEditEligible": true
        }
      },
      "entities": {
        "user_mentions": [
          {
            "id_str": "160946337",
            "indices": [
              "3",
              "11"
            ],
            "name": "The FAA ✈️",
            "screen_name": "FAANews"
          }
        ]
      },
      "favorite_count": "0",
      "favorited": false,
      "full_text": "RT @FAANews: It’s National Aviation History Month! We honor all of the unforgettable figures in history who surpassed limits and contribute…",
      "id_str": "1455231787039268871",
      "lang": "en",
      "retweet_count": "0",
      "retweeted": false,
      "source": "\u003ca href=\"https://mobile.twitter.com\" rel=\"nofollow\"\u003eTwitter Web App\u003c/a\u003e",
      "truncated": false
    },
    "wof:name": "RT @FAANews: It’s National Aviation History Month! We honor all of the unforgettable figures in history who surpassed limits and contribute…",
    "wof:placetype": "custom"
  },
  "geometry": {"coordinates":[-122.386166,37.616356],"type":"Point"}
}
