{
  "type": "Feature",
  "properties": {
    "sfomuseum:placetype": "tweet",
    "twitter:tweet": {
      "created": 1401462368,
      "created_at": "Fri May 30 15:06:08 +0000 2014",
      "display_text_range": [
        "0", 
        "138"
      ],
      "entities": {
        "urls": [
          {
            "display_url": "lat.ms/1k9TJN5",
            "expanded_url": "http://lat.ms/1k9TJN5",
            "indices": [
              "116", 
              "138"
            ],
            "url": "http://t.co/JWOHxCFEpo"
          }
        ],
        "user_mentions": [
          {
            "id_str": "16664681",
            "indices": [
              "3", 
              "11"
            ],
            "name": "Los Angeles Times",
            "screen_name": "latimes"
          }
        ]
      },
      "favorite_count": "0",
      "favorited": false,
      "full_text": "RT @latimes: An exhibit at the SFO Museum lets you get a sense of what airline travel was like back when it was fun http://t.co/JWOHxCFEpo",
      "id_str": "472393528027648000",
      "lang": "en",
      "possibly_sensitive": false,
      "retweet_count": "0",
      "retweeted": false,
      "source": "\u003ca href=\"http://www.hootsuite.com\" rel=\"nofollow\"\u003eHootsuite\u003c/a\u003e",
      "truncated": false
    },
    "wof:name": "Twitter message #472393528027648000",
    "wof:placetype": "custom"
  },
  "geometry": {"coordinates":[-122.386166,37.616356],"type":"Point"}
}
