{
  "type": "Feature",
  "properties": {
    "sfomuseum:placetype": "tweet",
    "twitter:tweet": {
      "created": 1410219907,
      "created_at": "Mon Sep 08 23:45:07 +0000 2014",
      "display_text_range": [
        "0", 
        "140"
      ],
      "entities": {
        "hashtags": [
          {
            "indices": [
              "69", 
              "74"
            ],
            "text": "CNAC"
          }, 
          {
            "indices": [
              "133", 
              "140"
            ],
            "text": "avgeek"
          }
        ],
        "urls": [
          {
            "display_url": "ow.ly/Bg4sH",
            "expanded_url": "http://ow.ly/Bg4sH",
            "indices": [
              "110", 
              "132"
            ],
            "url": "http://t.co/kht7m00KAA"
          }
        ],
        "user_mentions": [
          {
            "id_str": "43368063",
            "indices": [
              "97", 
              "108"
            ],
            "name": "Dan Catchpole 📰",
            "screen_name": "dcatchpole"
          }
        ]
      },
      "favorite_count": "0",
      "favorited": false,
      "full_text": "We helped reunite a 99 yr old former pilot with the DC-3 he flew for #CNAC in the '40s! Story by @dcatchpole: http://t.co/kht7m00KAA #avgeek",
      "id_str": "509125310143795200",
      "lang": "en",
      "possibly_sensitive": false,
      "retweet_count": "2",
      "retweeted": false,
      "source": "\u003ca href=\"http://www.hootsuite.com\" rel=\"nofollow\"\u003eHootsuite\u003c/a\u003e",
      "truncated": false
    },
    "wof:name": "Twitter message #509125310143795200",
    "wof:placetype": "custom"
  },
  "geometry": {"coordinates":[-122.386166,37.616356],"type":"Point"}
}
