{
  "type": "Feature",
  "properties": {
    "date:cessation_lower": "2017-12-07",
    "date:cessation_upper": "2017-12-07",
    "date:inception_lower": "2017-12-07",
    "date:inception_upper": "2017-12-07",
    "iso:country": "US",
    "sfomuseum:placetype": "tweet",
    "twitter:tweet": {
      "created": 1512691011,
      "created_at": "Thu Dec 07 23:56:51 +0000 2017",
      "display_text_range": [
        "0",
        "127"
      ],
      "edit_info": {
        "initial": {
          "editTweetIds": [
            "938920272622735361"
          ],
          "editableUntil": "2017-12-08T00:26:51.945Z",
          "editsRemaining": "5",
          "isEditEligible": true
        }
      },
      "entities": {
        "hashtags": [
          {
            "indices": [
              "102",
              "112"
            ],
            "text": "museumjob"
          },
          {
            "indices": [
              "113",
              "127"
            ],
            "text": "graphicdesign"
          }
        ],
        "urls": [
          {
            "display_url": "ow.ly/sO0430h5vQv",
            "expanded_url": "http://ow.ly/sO0430h5vQv",
            "indices": [
              "78",
              "101"
            ],
            "url": "https://t.co/uu9eiiJ2Jj"
          }
        ]
      },
      "favorite_count": "0",
      "favorited": false,
      "full_text": "We're hiring! Check out our listing for a part-time graphic design assistant: https://t.co/uu9eiiJ2Jj #museumjob #graphicdesign",
      "id_str": "938920272622735361",
      "lang": "en",
      "possibly_sensitive": false,
      "retweet_count": "1",
      "retweeted": false,
      "source": "\u003ca href=\"http://www.hootsuite.com\" rel=\"nofollow\"\u003eHootsuite\u003c/a\u003e",
      "truncated": false
    },
    "wof:name": "We're hiring! Check out our listing for a part-time graphic design assistant: https://t.co/uu9eiiJ2Jj #museumjob #graphicdesign",
    "wof:placetype": "custom"
  },
  "geometry": {"coordinates":[-122.386166,37.616356],"type":"Point"}
}
