{
  "type": "Feature",
  "properties": {
    "date:cessation_lower":"2014-01-07",
    "date:cessation_upper":"2014-01-07",
    "date:inception_lower":"2014-01-07",
    "date:inception_upper":"2014-01-07",
    "iso:country":"US",
    "sfomuseum:placetype":"tweet",
    "twitter:tweet":{
        "created":1389138801,
        "created_at":"Tue Jan 07 23:53:21 +0000 2014",
        "display_text_range":[
            "0",
            "52"
        ],
        "entities":{
            "user_mentions":[
                {
                    "id_str":"22073290",
                    "indices":[
                        "0",
                        "11"
                    ],
                    "name":"Robert Friedman",
                    "screen_name":"rfpresents"
                }
            ]
        },
        "favorite_count":"0",
        "favorited":false,
        "full_text":"@rfpresents Thanks! Glad you enjoy the exhibitions!!",
        "id_str":"420704743267516416",
        "in_reply_to_screen_name":"rfpresents",
        "in_reply_to_status_id":"420674508886794241",
        "in_reply_to_status_id_str":"420674508886794241",
        "in_reply_to_user_id":"22073290",
        "in_reply_to_user_id_str":"22073290",
        "lang":"en",
        "retweet_count":"0",
        "retweeted":false,
        "source":"<a href=\"http://www.hootsuite.com\" rel=\"nofollow\">Hootsuite</a>",
        "truncated":false
    },
    "wof:name":"@rfpresents Thanks! Glad you enjoy the exhibitions!!",
    "wof:placetype":"custom"
},
  "geometry": {"coordinates":[-122.386166,37.616356],"type":"Point"}
}