{
  "type": "Feature",
  "properties": {
    "sfomuseum:placetype": "tweet",
    "twitter:tweet": {
      "created": 1441416615,
      "created_at": "Sat Sep 05 01:30:15 +0000 2015",
      "display_text_range": [
        "0", 
        "137"
      ],
      "entities": {
        "media": [
          {
            "display_url": "pic.twitter.com/BUq40FPhQ0",
            "expanded_url": "https://twitter.com/SFOMuseum/status/639973787451170816/photo/1",
            "id_str": "639973786830303233",
            "indices": [
              "115", 
              "137"
            ],
            "media_url": "http://pbs.twimg.com/media/COGkxLWU8AE2qNt.jpg",
            "media_url_https": "https://pbs.twimg.com/media/COGkxLWU8AE2qNt.jpg",
            "sizes": {
              "large": {
                "h": "1054",
                "resize": "fit",
                "w": "1641"
              },
              "medium": {
                "h": "771",
                "resize": "fit",
                "w": "1200"
              },
              "small": {
                "h": "437",
                "resize": "fit",
                "w": "680"
              },
              "thumb": {
                "h": "150",
                "resize": "crop",
                "w": "150"
              }
            },
            "type": "photo",
            "url": "http://t.co/BUq40FPhQ0"
          }
        ],
        "urls": [
          {
            "display_url": "miami.curbed.com/archives/2015/…",
            "expanded_url": "http://miami.curbed.com/archives/2015/09/02/miami-science-museum-pan-am-globe.php",
            "indices": [
              "92", 
              "114"
            ],
            "url": "http://t.co/4q19mOjRmC"
          }
        ]
      },
      "extended_entities": {
        "media": [
          {
            "display_url": "pic.twitter.com/BUq40FPhQ0",
            "expanded_url": "https://twitter.com/SFOMuseum/status/639973787451170816/photo/1",
            "id_str": "639973786830303233",
            "indices": [
              "115", 
              "137"
            ],
            "media_url": "http://pbs.twimg.com/media/COGkxLWU8AE2qNt.jpg",
            "media_url_https": "https://pbs.twimg.com/media/COGkxLWU8AE2qNt.jpg",
            "sizes": {
              "large": {
                "h": "1054",
                "resize": "fit",
                "w": "1641"
              },
              "medium": {
                "h": "771",
                "resize": "fit",
                "w": "1200"
              },
              "small": {
                "h": "437",
                "resize": "fit",
                "w": "680"
              },
              "thumb": {
                "h": "150",
                "resize": "crop",
                "w": "150"
              }
            },
            "type": "photo",
            "url": "http://t.co/BUq40FPhQ0"
          }
        ]
      },
      "favorite_count": "0",
      "favorited": false,
      "full_text": "The painted globe originally housed in Pan Am's Marine Air Terminal in FL needs a new home. http://t.co/4q19mOjRmC http://t.co/BUq40FPhQ0",
      "id_str": "639973787451170816",
      "lang": "en",
      "possibly_sensitive": false,
      "retweet_count": "0",
      "retweeted": false,
      "source": "\u003ca href=\"http://www.hootsuite.com\" rel=\"nofollow\"\u003eHootsuite\u003c/a\u003e",
      "truncated": false
    },
    "wof:name": "Twitter message #639973787451170816",
    "wof:placetype": "custom"
  },
  "geometry": {"coordinates":[-122.386166,37.616356],"type":"Point"}
}
