{
  "type": "Feature",
  "properties": {
    "date:cessation_lower": "2014-06-17",
    "date:cessation_upper": "2014-06-17",
    "date:inception_lower": "2014-06-17",
    "date:inception_upper": "2014-06-17",
    "iso:country": "US",
    "sfomuseum:placetype": "tweet",
    "twitter:hashtags": [
      "avgeek"
    ],
    "twitter:tweet": {
      "created": 1403047863,
      "created_at": "Tue Jun 17 23:31:03 +0000 2014",
      "display_text_range": [
        "0",
        "122"
      ],
      "edit_info": {
        "initial": {
          "editTweetIds": [
            "479043576815693824"
          ],
          "editableUntil": "2014-06-18T00:31:03.569Z",
          "editsRemaining": "5",
          "isEditEligible": true
        }
      },
      "entities": {
        "hashtags": [
          {
            "indices": [
              "115",
              "122"
            ],
            "text": "avgeek"
          }
        ],
        "urls": [
          {
            "display_url": "ow.ly/y9IaJ",
            "expanded_url": "http://ow.ly/y9IaJ",
            "indices": [
              "92",
              "114"
            ],
            "url": "http://t.co/RqxgZ0R02c"
          }
        ]
      },
      "favorite_count": "0",
      "favorited": false,
      "full_text": "With the increase in air travel in the 1950s, airlines' call centers were kept *very* busy: http://t.co/RqxgZ0R02c #avgeek",
      "id_str": "479043576815693824",
      "lang": "en",
      "possibly_sensitive": false,
      "retweet_count": "1",
      "retweeted": false,
      "source": "\u003ca href=\"http://www.hootsuite.com\" rel=\"nofollow\"\u003eHootsuite\u003c/a\u003e",
      "truncated": false
    },
    "wof:name": "With the increase in air travel in the 1950s, airlines' call centers were kept *very* busy: http://t.co/RqxgZ0R02c #avgeek",
    "wof:placetype": "custom"
  },
  "geometry": {"coordinates":[-122.386166,37.616356],"type":"Point"}
}
