{
  "type": "Feature",
  "properties": {
    "date:cessation_lower": "2013-05-30",
    "date:cessation_upper": "2013-05-30",
    "date:inception_lower": "2013-05-30",
    "date:inception_upper": "2013-05-30",
    "iso:country": "US",
    "sfomuseum:placetype": "tweet",
    "twitter:tweet": {
      "created": 1369949522,
      "created_at": "Thu May 30 21:32:02 +0000 2013",
      "display_text_range": [
        "0",
        "123"
      ],
      "edit_info": {
        "initial": {
          "editTweetIds": [
            "340219071641559042"
          ],
          "editableUntil": "2013-05-30T22:32:02.301Z",
          "editsRemaining": "5",
          "isEditEligible": true
        }
      },
      "entities": {
        "urls": [
          {
            "display_url": "instagram.com/p/Z83NeORkyZ/",
            "expanded_url": "http://instagram.com/p/Z83NeORkyZ/",
            "indices": [
              "101",
              "123"
            ],
            "url": "http://t.co/MX3v9VQh4a"
          }
        ]
      },
      "favorite_count": "0",
      "favorited": false,
      "full_text": "The Shakers pioneered the industry of selling seeds in packets, and even invented machinery to cut,… http://t.co/MX3v9VQh4a",
      "id_str": "340219071641559042",
      "lang": "en",
      "possibly_sensitive": false,
      "retweet_count": "0",
      "retweeted": false,
      "source": "\u003ca href=\"http://instagram.com\" rel=\"nofollow\"\u003eInstagram\u003c/a\u003e",
      "truncated": false
    },
    "wof:name": "The Shakers pioneered the industry of selling seeds in packets, and even invented machinery to cut,… http://t.co/MX3v9VQh4a",
    "wof:placetype": "custom"
  },
  "geometry": {"coordinates":[-122.386166,37.616356],"type":"Point"}
}
