{
  "type": "Feature",
  "properties": {
    "date:cessation_lower": "2012-10-17",
    "date:cessation_upper": "2012-10-17",
    "date:inception_lower": "2012-10-17",
    "date:inception_upper": "2012-10-17",
    "iso:country": "US",
    "sfomuseum:placetype": "tweet",
    "twitter:tweet": {
      "created": 1350495240,
      "created_at": "Wed Oct 17 17:34:00 +0000 2012",
      "display_text_range": [
        "0",
        "99"
      ],
      "entities": {
        "hashtags": [
          {
            "indices": [
              "86",
              "99"
            ],
            "text": "SFOfieldtrip"
          }
        ],
        "user_mentions": [
          {
            "id_str": "16321591",
            "indices": [
              "19",
              "30"
            ],
            "name": "UC Santa Barbara Kruger",
            "screen_name": "socalgecko"
          }
        ]
      },
      "favorite_count": "0",
      "favorited": false,
      "full_text": "Woot! Welcome!! RT @socalgecko: On the ground at SFO! Let the museum adventure begin. #SFOfieldtrip",
      "id_str": "258621899825885184",
      "lang": "en",
      "retweet_count": "0",
      "retweeted": false,
      "source": "\u003ca href=\"http://www.hootsuite.com\" rel=\"nofollow\"\u003eHootsuite\u003c/a\u003e",
      "truncated": false
    },
    "wof:name": "Woot! Welcome!! RT @socalgecko: On the ground at SFO! Let the museum adventure begin. #SFOfieldtrip",
    "wof:placetype": "custom"
  },
  "geometry": {"coordinates":[-122.386166,37.616356],"type":"Point"}
}
