{
  "type": "Feature",
  "properties": {
    "sfomuseum:placetype": "tweet",
    "twitter:tweet": {
      "created": 1483985699,
      "created_at": "Mon Jan 09 18:14:59 +0000 2017",
      "display_text_range": [
        "0", 
        "140"
      ],
      "entities": {
        "user_mentions": [
          {
            "id_str": "50753411",
            "indices": [
              "3", 
              "15"
            ],
            "name": "Luke Timmerman",
            "screen_name": "ldtimmerman"
          }
        ]
      },
      "favorite_count": "0",
      "favorited": false,
      "full_text": "RT @ldtimmerman: Fashion in Flight exhibit at SFO. That plastic helmet thing in the center may be appropriate this week. https://t.co/oNgnN…",
      "id_str": "818521466497105921",
      "lang": "en",
      "retweet_count": "0",
      "retweeted": false,
      "source": "\u003ca href=\"http://www.hootsuite.com\" rel=\"nofollow\"\u003eHootsuite\u003c/a\u003e",
      "truncated": false
    },
    "wof:name": "Twitter message #818521466497105921",
    "wof:placetype": "custom"
  },
  "geometry": {"coordinates":[-122.386166,37.616356],"type":"Point"}
}
