{
  "type": "Feature",
  "properties": {
    "date:cessation_lower": "2024-07-24",
    "date:cessation_upper": "2024-07-24",
    "date:inception_lower": "2024-07-24",
    "date:inception_upper": "2024-07-24",
    "sfomuseum:placetype": "tweet",
    "twitter:tweet": {
      "created": 1721865599,
      "created_at": "Wed Jul 24 23:59:59 +0000 2024",
      "display_text_range": [
        "0",
        "122"
      ],
      "edit_info": {
        "initial": {
          "editTweetIds": [
            "1816262080166781443"
          ],
          "editableUntil": "2024-07-25T00:59:59.000Z",
          "editsRemaining": "5",
          "isEditEligible": false
        }
      },
      "entities": {
        "urls": [
          {
            "display_url": "bit.ly/3Y2YAtd",
            "expanded_url": "https://bit.ly/3Y2YAtd",
            "indices": [
              "99",
              "122"
            ],
            "url": "https://t.co/iza4xdR4qk"
          }
        ]
      },
      "favorite_count": "0",
      "favorited": false,
      "full_text": "📸:\nposter: Braniff International, Douglas DC-8-62; c. 1974\nGift of Thomas G. Dragges\n2015.109.020\n\nhttps://t.co/iza4xdR4qk",
      "id_str": "1816262080166781443",
      "in_reply_to_screen_name": "SFOMuseum",
      "in_reply_to_status_id": "1816262078052852191",
      "in_reply_to_status_id_str": "1816262078052852191",
      "in_reply_to_user_id": "116329337",
      "in_reply_to_user_id_str": "116329337",
      "lang": "en",
      "possibly_sensitive": false,
      "retweet_count": "0",
      "retweeted": false,
      "source": "\u003ca href=\"https://mobile.twitter.com\" rel=\"nofollow\"\u003eTwitter Web App\u003c/a\u003e",
      "truncated": false
    },
    "wof:name": "📸:\nposter: Braniff International, Douglas DC-8-62; c. 1974\nGift of Thomas G. Dragges\n2015.109.020\n\nhttps://t.co/iza4xdR4qk",
    "wof:placetype": "custom"
  },
  "geometry": {"coordinates":[-122.386166,37.616356],"type":"Point"}
}
