{
  "type": "Feature",
  "properties": {
    "date:cessation_lower": "2011-12-21",
    "date:cessation_upper": "2011-12-21",
    "date:inception_lower": "2011-12-21",
    "date:inception_upper": "2011-12-21",
    "iso:country": "US",
    "sfomuseum:placetype": "tweet",
    "twitter:tweet": {
      "created": 1324506345,
      "created_at": "Wed Dec 21 22:25:45 +0000 2011",
      "display_text_range": [
        "0",
        "89"
      ],
      "edit_info": {
        "initial": {
          "editTweetIds": [
            "149616574578425856"
          ],
          "editableUntil": "2011-12-21T23:25:45.778Z",
          "editsRemaining": "5",
          "isEditEligible": true
        }
      },
      "entities": {
        "user_mentions": [
          {
            "id_str": "69638529",
            "indices": [
              "0",
              "12"
            ],
            "name": "Lady Fred",
            "screen_name": "theladyfred"
          }
        ]
      },
      "favorite_count": "0",
      "favorited": false,
      "full_text": "@TheLadyFred Awesome!! That is exactly what we like to hear! Thank you \u0026 happy holidays!!",
      "id_str": "149616574578425856",
      "in_reply_to_screen_name": "theladyfred",
      "in_reply_to_status_id": "149612546108829696",
      "in_reply_to_status_id_str": "149612546108829696",
      "in_reply_to_user_id": "69638529",
      "in_reply_to_user_id_str": "69638529",
      "lang": "en",
      "retweet_count": "0",
      "retweeted": false,
      "source": "\u003ca href=\"https://about.twitter.com/products/tweetdeck\" rel=\"nofollow\"\u003eTweetDeck\u003c/a\u003e",
      "truncated": false
    },
    "wof:name": "@TheLadyFred Awesome!! That is exactly what we like to hear! Thank you \u0026 happy holidays!!",
    "wof:placetype": "custom"
  },
  "geometry": {"coordinates":[-122.386166,37.616356],"type":"Point"}
}
