{
  "type": "Feature",
  "properties": {
    "date:cessation_lower": "2023-10-26",
    "date:cessation_upper": "2023-10-26",
    "date:inception_lower": "2023-10-26",
    "date:inception_upper": "2023-10-26",
    "sfomuseum:placetype": "tweet",
    "twitter:tweet": {
      "created": 1698362446,
      "created_at": "Thu Oct 26 23:20:46 +0000 2023",
      "display_text_range": [
        "0",
        "255"
      ],
      "edit_info": {
        "initial": {
          "editTweetIds": [
            "1717682712033812977"
          ],
          "editableUntil": "2023-10-27T00:20:46.000Z",
          "editsRemaining": "5",
          "isEditEligible": false
        }
      },
      "entities": {
        "hashtags": [
          {
            "indices": [
              "242",
              "255"
            ],
            "text": "VideoArtsSFO"
          }
        ],
        "urls": [
          {
            "display_url": "bit.ly/VideoArts",
            "expanded_url": "http://bit.ly/VideoArts",
            "indices": [
              "218",
              "241"
            ],
            "url": "https://t.co/s0oA7gcWli"
          }
        ]
      },
      "favorite_count": "1",
      "favorited": false,
      "full_text": "See “Experiment” by Zoé Berton-Bojko, Susana Covo Perez, Guillaume Heessler, Yann Kacprzak, and Margot Wirath in the Video Arts Gallery, located pre-security in the International Terminal, open daily from 8am to 10pm. https://t.co/s0oA7gcWli #VideoArtsSFO",
      "id_str": "1717682712033812977",
      "in_reply_to_screen_name": "SFOMuseum",
      "in_reply_to_status_id": "1717682710075121851",
      "in_reply_to_status_id_str": "1717682710075121851",
      "in_reply_to_user_id": "116329337",
      "in_reply_to_user_id_str": "116329337",
      "lang": "en",
      "possibly_sensitive": false,
      "retweet_count": "1",
      "retweeted": false,
      "source": "\u003ca href=\"https://mobile.twitter.com\" rel=\"nofollow\"\u003eTwitter Web App\u003c/a\u003e",
      "truncated": false
    },
    "wof:name": "See “Experiment” by Zoé Berton-Bojko, Susana Covo Perez, Guillaume Heessler, Yann Kacprzak, and Margot Wirath in the Video Arts Gallery, located pre-security in the International Terminal, open daily from 8am to 10pm. https://t.co/s0oA7gcWli #VideoArtsSFO",
    "wof:placetype": "custom",
    "wof:placetype_alt": [
      "tweet"
    ]
  },
  "geometry": {"coordinates":[-122.386166,37.616356],"type":"Point"}
}
