{
  "type": "Feature",
  "properties": {
    "date:cessation_lower": "2014-05-01",
    "date:cessation_upper": "2014-05-01",
    "date:inception_lower": "2014-05-01",
    "date:inception_upper": "2014-05-01",
    "iso:country": "US",
    "sfomuseum:placetype": "tweet",
    "twitter:tweet": {
      "created": 1398978724,
      "created_at": "Thu May 01 21:12:04 +0000 2014",
      "display_text_range": [
        "0",
        "134"
      ],
      "edit_info": {
        "initial": {
          "editTweetIds": [
            "461976372135870465"
          ],
          "editableUntil": "2014-05-01T21:42:04.880Z",
          "editsRemaining": "5",
          "isEditEligible": true
        }
      },
      "entities": {
        "user_mentions": [
          {
            "id_str": "1598411",
            "indices": [
              "0",
              "16"
            ],
            "name": "Todd Lappin",
            "screen_name": "TelstarLogistic"
          },
          {
            "id_str": "34006429",
            "indices": [
              "17",
              "32"
            ],
            "name": "Collectors Weekly",
            "screen_name": "collectorswkly"
          }
        ]
      },
      "favorite_count": "1",
      "favorited": false,
      "full_text": "@TelstarLogistic @collectorswkly We're coveting those jackets something fierce! That could be a fun exhibit, come to think about it...",
      "id_str": "461976372135870465",
      "in_reply_to_screen_name": "TelstarLogistic",
      "in_reply_to_status_id": "461973602561040385",
      "in_reply_to_status_id_str": "461973602561040385",
      "in_reply_to_user_id": "1598411",
      "in_reply_to_user_id_str": "1598411",
      "lang": "en",
      "retweet_count": "0",
      "retweeted": false,
      "source": "\u003ca href=\"http://www.hootsuite.com\" rel=\"nofollow\"\u003eHootsuite\u003c/a\u003e",
      "truncated": false
    },
    "wof:name": "@TelstarLogistic @collectorswkly We're coveting those jackets something fierce! That could be a fun exhibit, come to think about it...",
    "wof:placetype": "custom"
  },
  "geometry": {"coordinates":[-122.386166,37.616356],"type":"Point"}
}
