{
  "type": "Feature",
  "properties": {
    "sfomuseum:placetype": "tweet",
    "twitter:tweet": {
      "created": 1415143556,
      "created_at": "Tue Nov 04 23:25:56 +0000 2014",
      "display_text_range": [
        "0", 
        "126"
      ],
      "entities": {
        "urls": [
          {
            "display_url": "instagram.com/p/u_wXYJxkw3/",
            "expanded_url": "http://instagram.com/p/u_wXYJxkw3/",
            "indices": [
              "104", 
              "126"
            ],
            "url": "http://t.co/CPrc1U0eSP"
          }
        ]
      },
      "favorite_count": "1",
      "favorited": false,
      "full_text": "\"As an artist, I have immersed myself in understanding our cultural heritage...Therefore, I have great… http://t.co/CPrc1U0eSP",
      "id_str": "529776590805143552",
      "lang": "en",
      "possibly_sensitive": false,
      "retweet_count": "0",
      "retweeted": false,
      "source": "\u003ca href=\"http://instagram.com\" rel=\"nofollow\"\u003eInstagram\u003c/a\u003e",
      "truncated": false
    },
    "wof:name": "Twitter message #529776590805143552",
    "wof:placetype": "custom"
  },
  "geometry": {"coordinates":[-122.386166,37.616356],"type":"Point"}
}
