{
  "type": "Feature",
  "properties": {
    "date:cessation_lower": "2013-12-10",
    "date:cessation_upper": "2013-12-10",
    "date:inception_lower": "2013-12-10",
    "date:inception_upper": "2013-12-10",
    "iso:country": "US",
    "sfomuseum:placetype": "tweet",
    "twitter:tweet": {
      "created": 1386704012,
      "created_at": "Tue Dec 10 19:33:32 +0000 2013",
      "display_text_range": [
        "0",
        "124"
      ],
      "edit_info": {
        "initial": {
          "editTweetIds": [
            "410492495651688448"
          ],
          "editableUntil": "2013-12-10T20:33:32.202Z",
          "editsRemaining": "5",
          "isEditEligible": true
        }
      },
      "entities": {
        "urls": [
          {
            "display_url": "instagram.com/p/hwLcEKxk1T/",
            "expanded_url": "http://instagram.com/p/hwLcEKxk1T/",
            "indices": [
              "102",
              "124"
            ],
            "url": "http://t.co/lbKUpylTFg"
          }
        ]
      },
      "favorite_count": "0",
      "favorited": false,
      "full_text": "When snails, a delicacy, are found in the Luzon Cordillera, they are scooped up by the plaited sieve… http://t.co/lbKUpylTFg",
      "id_str": "410492495651688448",
      "lang": "en",
      "possibly_sensitive": false,
      "retweet_count": "0",
      "retweeted": false,
      "source": "\u003ca href=\"http://instagram.com\" rel=\"nofollow\"\u003eInstagram\u003c/a\u003e",
      "truncated": false
    },
    "wof:name": "When snails, a delicacy, are found in the Luzon Cordillera, they are scooped up by the plaited sieve… http://t.co/lbKUpylTFg",
    "wof:placetype": "custom"
  },
  "geometry": {"coordinates":[-122.386166,37.616356],"type":"Point"}
}
