{
  "type": "Feature",
  "properties": {
    "date:cessation_lower": "2017-03-20",
    "date:cessation_upper": "2017-03-20",
    "date:inception_lower": "2017-03-20",
    "date:inception_upper": "2017-03-20",
    "iso:country": "US",
    "sfomuseum:placetype": "tweet",
    "twitter:tweet": {
      "created": 1490039061,
      "created_at": "Mon Mar 20 19:44:21 +0000 2017",
      "display_text_range": [
        "0",
        "140"
      ],
      "edit_info": {
        "initial": {
          "editTweetIds": [
            "843911106934460416"
          ],
          "editableUntil": "2017-03-20T20:14:21.660Z",
          "editsRemaining": "5",
          "isEditEligible": true
        }
      },
      "entities": {
        "urls": [
          {
            "display_url": "usat.ly/2maUBKy",
            "expanded_url": "http://usat.ly/2maUBKy",
            "indices": [
              "106",
              "129"
            ],
            "url": "https://t.co/6FB9LkikYL"
          }
        ],
        "user_mentions": [
          {
            "id_str": "24016767",
            "indices": [
              "3",
              "18"
            ],
            "name": "USA TODAY Travel",
            "screen_name": "usatodaytravel"
          },
          {
            "id_str": "161768953",
            "indices": [
              "130",
              "140"
            ],
            "name": "Bart Jansen",
            "screen_name": "ganjansen"
          }
        ]
      },
      "favorite_count": "0",
      "favorited": false,
      "full_text": "RT @usatodaytravel: U.S. airlines broke passenger records in 2016, topping 800 million for the first time https://t.co/6FB9LkikYL @ganjansen",
      "id_str": "843911106934460416",
      "lang": "en",
      "possibly_sensitive": false,
      "retweet_count": "0",
      "retweeted": false,
      "source": "\u003ca href=\"http://twitter.com\" rel=\"nofollow\"\u003eTwitter Web Client\u003c/a\u003e",
      "truncated": false
    },
    "wof:name": "RT @usatodaytravel: U.S. airlines broke passenger records in 2016, topping 800 million for the first time https://t.co/6FB9LkikYL @ganjansen",
    "wof:placetype": "custom"
  },
  "geometry": {"coordinates":[-122.386166,37.616356],"type":"Point"}
}
