{
  "type": "Feature",
  "properties": {
    "date:cessation_lower": "2022-04-16",
    "date:cessation_upper": "2022-04-16",
    "date:inception_lower": "2022-04-16",
    "date:inception_upper": "2022-04-16",
    "sfomuseum:placetype": "tweet",
    "twitter:tweet": {
      "created": 1650071439,
      "created_at": "Sat Apr 16 01:10:39 +0000 2022",
      "display_text_range": [
        "0",
        "156"
      ],
      "edit_info": {
        "initial": {
          "editTweetIds": [
            "1515135551078207488"
          ],
          "editableUntil": "2022-04-16T01:40:39.891Z",
          "editsRemaining": "5",
          "isEditEligible": true
        }
      },
      "entities": {
        "urls": [
          {
            "display_url": "bit.ly/3uMigTh",
            "expanded_url": "https://bit.ly/3uMigTh",
            "indices": [
              "133",
              "156"
            ],
            "url": "https://t.co/YRTMfRnsPn"
          }
        ]
      },
      "favorite_count": "0",
      "favorited": false,
      "full_text": "📸 1/3:\nphotograph: American Airways, Fairchild Pilgrim 100-A; c. 1931\nTransfer from San Francisco International Airport\n2008.128.001\nhttps://t.co/YRTMfRnsPn",
      "id_str": "1515135551078207488",
      "in_reply_to_screen_name": "SFOMuseum",
      "in_reply_to_status_id": "1515113095068323840",
      "in_reply_to_status_id_str": "1515113095068323840",
      "in_reply_to_user_id": "116329337",
      "in_reply_to_user_id_str": "116329337",
      "lang": "en",
      "possibly_sensitive": false,
      "retweet_count": "0",
      "retweeted": false,
      "source": "\u003ca href=\"https://mobile.twitter.com\" rel=\"nofollow\"\u003eTwitter Web App\u003c/a\u003e",
      "truncated": false
    },
    "wof:name": "📸 1/3:\nphotograph: American Airways, Fairchild Pilgrim 100-A; c. 1931\nTransfer from San Francisco International Airport\n2008.128.001\nhttps://t.co/YRTMfRnsPn",
    "wof:placetype": "custom"
  },
  "geometry": {"coordinates":[-122.386166,37.616356],"type":"Point"}
}
