{
  "type": "Feature",
  "properties": {
    "date:cessation_lower": "2013-03-08",
    "date:cessation_upper": "2013-03-08",
    "date:inception_lower": "2013-03-08",
    "date:inception_upper": "2013-03-08",
    "iso:country": "US",
    "sfomuseum:placetype": "tweet",
    "twitter:tweet": {
      "created": 1362771527,
      "created_at": "Fri Mar 08 19:38:47 +0000 2013",
      "display_text_range": [
        "0",
        "131"
      ],
      "edit_info": {
        "initial": {
          "editTweetIds": [
            "310112377364426752"
          ],
          "editableUntil": "2013-03-08T20:08:47.030Z",
          "editsRemaining": "5",
          "isEditEligible": true
        }
      },
      "entities": {
        "urls": [
          {
            "display_url": "500px.com/photo/4751280",
            "expanded_url": "http://500px.com/photo/4751280",
            "indices": [
              "109",
              "131"
            ],
            "url": "http://t.co/TSmJFlLGsm"
          }
        ],
        "user_mentions": [
          {
            "id_str": "31288364",
            "indices": [
              "28",
              "39"
            ],
            "name": "Rich Cruse Photo",
            "screen_name": "CrusePhoto"
          },
          {
            "id_str": "18958334",
            "indices": [
              "43",
              "48"
            ],
            "name": "SF Arts Commission",
            "screen_name": "SFAC"
          }
        ]
      },
      "favorite_count": "0",
      "favorited": false,
      "full_text": "Art of art: gorgeous pic by @CrusePhoto of @SFAC's sculpture by Fred Eversley (a former aerospace engineer)! http://t.co/TSmJFlLGsm",
      "id_str": "310112377364426752",
      "lang": "en",
      "possibly_sensitive": false,
      "retweet_count": "0",
      "retweeted": false,
      "source": "\u003ca href=\"https://about.twitter.com/products/tweetdeck\" rel=\"nofollow\"\u003eTweetDeck\u003c/a\u003e",
      "truncated": false
    },
    "wof:name": "Art of art: gorgeous pic by @CrusePhoto of @SFAC's sculpture by Fred Eversley (a former aerospace engineer)! http://t.co/TSmJFlLGsm",
    "wof:placetype": "custom"
  },
  "geometry": {"coordinates":[-122.386166,37.616356],"type":"Point"}
}
