{
  "type": "Feature",
  "properties": {
    "date:cessation_lower": "2024-09-18",
    "date:cessation_upper": "2024-09-18",
    "date:inception_lower": "2024-09-18",
    "date:inception_upper": "2024-09-18",
    "sfomuseum:placetype": "tweet",
    "twitter:tweet": {
      "created": 1726702994,
      "created_at": "Wed Sep 18 23:43:14 +0000 2024",
      "display_text_range": [
        "0",
        "252"
      ],
      "edit_info": {
        "initial": {
          "editTweetIds": [
            "1836551588279914942"
          ],
          "editableUntil": "2024-09-19T00:43:14.000Z",
          "editsRemaining": "5",
          "isEditEligible": false
        }
      },
      "entities": {
      },
      "favorite_count": "2",
      "favorited": false,
      "full_text": "📸:\n3. Qantas Empire Airways Australia travel poster  c. 1956\nHarry Rogers\nGift of Thomas G. Dragges\n2015.109.067\nR2024.0601.012\n\n4. Qantas Empire Airways Britain travel poster  c. 1956\nHarry Rogers\nGift of Thomas G. Dragges\n2015.109.068\nR2024.0601.0133",
      "id_str": "1836551588279914942",
      "in_reply_to_screen_name": "SFOMuseum",
      "in_reply_to_status_id": "1836551587214635485",
      "in_reply_to_status_id_str": "1836551587214635485",
      "in_reply_to_user_id": "116329337",
      "in_reply_to_user_id_str": "116329337",
      "lang": "en",
      "retweet_count": "0",
      "retweeted": false,
      "source": "\u003ca href=\"https://mobile.twitter.com\" rel=\"nofollow\"\u003eTwitter Web App\u003c/a\u003e",
      "truncated": false
    },
    "wof:name": "📸:\n3. Qantas Empire Airways Australia travel poster  c. 1956\nHarry Rogers\nGift of Thomas G. Dragges\n2015.109.067\nR2024.0601.012\n\n4. Qantas Empire Airways Britain travel poster  c. 1956\nHarry Rogers\nGift of Thomas G. Dragges\n2015.109.068\nR2024.0601.0133",
    "wof:placetype": "custom"
  },
  "geometry": {"coordinates":[-122.386166,37.616356],"type":"Point"}
}
