{
  "type": "Feature",
  "properties": {
    "sfomuseum:placetype": "tweet",
    "twitter:tweet": {
      "created": 1528158606,
      "created_at": "Tue Jun 05 00:30:06 +0000 2018",
      "display_text_range": [
        "0", 
        "190"
      ],
      "entities": {
        "hashtags": [
          {
            "indices": [
              "75", 
              "82"
            ],
            "text": "Boeing"
          }, 
          {
            "indices": [
              "147", 
              "166"
            ],
            "text": "AviationEvolutions"
          }
        ],
        "media": [
          {
            "display_url": "pic.twitter.com/AFEliHOWoR",
            "expanded_url": "https://twitter.com/SFOMuseum/status/1003796065282347009/photo/1",
            "id_str": "1003796063025709058",
            "indices": [
              "167", 
              "190"
            ],
            "media_url": "http://pbs.twimg.com/media/De4zM3OVQAIKSCE.jpg",
            "media_url_https": "https://pbs.twimg.com/media/De4zM3OVQAIKSCE.jpg",
            "sizes": {
              "large": {
                "h": "1591",
                "resize": "fit",
                "w": "2000"
              },
              "medium": {
                "h": "955",
                "resize": "fit",
                "w": "1200"
              },
              "small": {
                "h": "541",
                "resize": "fit",
                "w": "680"
              },
              "thumb": {
                "h": "150",
                "resize": "crop",
                "w": "150"
              }
            },
            "type": "photo",
            "url": "https://t.co/AFEliHOWoR"
          }
        ]
      },
      "extended_entities": {
        "media": [
          {
            "display_url": "pic.twitter.com/AFEliHOWoR",
            "expanded_url": "https://twitter.com/SFOMuseum/status/1003796065282347009/photo/1",
            "id_str": "1003796063025709058",
            "indices": [
              "167", 
              "190"
            ],
            "media_url": "http://pbs.twimg.com/media/De4zM3OVQAIKSCE.jpg",
            "media_url_https": "https://pbs.twimg.com/media/De4zM3OVQAIKSCE.jpg",
            "sizes": {
              "large": {
                "h": "1591",
                "resize": "fit",
                "w": "2000"
              },
              "medium": {
                "h": "955",
                "resize": "fit",
                "w": "1200"
              },
              "small": {
                "h": "541",
                "resize": "fit",
                "w": "680"
              },
              "thumb": {
                "h": "150",
                "resize": "crop",
                "w": "150"
              }
            },
            "type": "photo",
            "url": "https://t.co/AFEliHOWoR"
          }
        ]
      },
      "favorite_count": "8",
      "favorited": false,
      "full_text": "Often referred to as the first modern airliner, the all-metal, twin-engine #Boeing Model 247 was a revolutionary airliner when introduced in 1933. #AviationEvolutions https://t.co/AFEliHOWoR",
      "id_str": "1003796065282347009",
      "lang": "en",
      "possibly_sensitive": false,
      "retweet_count": "1",
      "retweeted": false,
      "source": "\u003ca href=\"https://www.hootsuite.com\" rel=\"nofollow\"\u003eHootsuite Inc.\u003c/a\u003e",
      "truncated": false
    },
    "wof:name": "Twitter message #1003796065282347009",
    "wof:placetype": "custom"
  },
  "geometry": {"coordinates":[-122.386166,37.616356],"type":"Point"}
}
