{
  "type": "Feature",
  "properties": {
    "date:cessation_lower": "2012-04-02",
    "date:cessation_upper": "2012-04-02",
    "date:inception_lower": "2012-04-02",
    "date:inception_upper": "2012-04-02",
    "iso:country": "US",
    "sfomuseum:placetype": "tweet",
    "twitter:tweet": {
      "created": 1333397583,
      "created_at": "Mon Apr 02 20:13:03 +0000 2012",
      "display_text_range": [
        "0",
        "138"
      ],
      "edit_info": {
        "initial": {
          "editTweetIds": [
            "186909127694491649"
          ],
          "editableUntil": "2012-04-02T20:43:03.303Z",
          "editsRemaining": "5",
          "isEditEligible": true
        }
      },
      "entities": {
        "urls": [
          {
            "display_url": "bit.ly/HPnS04",
            "expanded_url": "http://bit.ly/HPnS04",
            "indices": [
              "103",
              "123"
            ],
            "url": "http://t.co/g4ZYfwF8"
          }
        ]
      },
      "favorite_count": "0",
      "favorited": false,
      "full_text": "Chemical engineering training came in handy for Nathalie Krebs in perfecting Saxbo's exquisite glazes: http://t.co/g4ZYfwF8 On view in T2!",
      "id_str": "186909127694491649",
      "lang": "en",
      "possibly_sensitive": false,
      "retweet_count": "0",
      "retweeted": false,
      "source": "\u003ca href=\"https://about.twitter.com/products/tweetdeck\" rel=\"nofollow\"\u003eTweetDeck\u003c/a\u003e",
      "truncated": false
    },
    "wof:name": "Chemical engineering training came in handy for Nathalie Krebs in perfecting Saxbo's exquisite glazes: http://t.co/g4ZYfwF8 On view in T2!",
    "wof:placetype": "custom"
  },
  "geometry": {"coordinates":[-122.386166,37.616356],"type":"Point"}
}
