{
  "type": "Feature",
  "properties": {
    "sfomuseum:placetype": "tweet",
    "twitter:tweet": {
      "created": 1480386005,
      "created_at": "Tue Nov 29 02:20:05 +0000 2016",
      "display_text_range": [
        "0", 
        "133"
      ],
      "entities": {
        "hashtags": [
          {
            "indices": [
              "78", 
              "95"
            ],
            "text": "ArtAndDisability"
          }
        ],
        "urls": [
          {
            "display_url": "youtube.com/watch?v=bHIfea…",
            "expanded_url": "https://www.youtube.com/watch?v=bHIfeaDzq1g",
            "indices": [
              "110", 
              "133"
            ],
            "url": "https://t.co/lXHDkA24RO"
          }
        ]
      },
      "favorite_count": "0",
      "favorited": false,
      "full_text": "Richmond, California's @NIAD_Art Center is featured in \"Celebrating a Vision: #ArtAndDisability\". Learn more: https://t.co/lXHDkA24RO",
      "id_str": "803423256162209792",
      "lang": "en",
      "possibly_sensitive": false,
      "retweet_count": "0",
      "retweeted": false,
      "source": "\u003ca href=\"http://www.hootsuite.com\" rel=\"nofollow\"\u003eHootsuite\u003c/a\u003e",
      "truncated": false
    },
    "wof:name": "Twitter message #803423256162209792",
    "wof:placetype": "custom"
  },
  "geometry": {"coordinates":[-122.386166,37.616356],"type":"Point"}
}
