{
  "type": "Feature",
  "properties": {
    "sfomuseum:placetype": "tweet",
    "twitter:tweet": {
      "created": 1363018879,
      "created_at": "Mon Mar 11 16:21:19 +0000 2013",
      "display_text_range": [
        "0", 
        "118"
      ],
      "entities": {
        "urls": [
          {
            "display_url": "bit.ly/ZfzdO6",
            "expanded_url": "http://bit.ly/ZfzdO6",
            "indices": [
              "96", 
              "118"
            ],
            "url": "http://t.co/LjpiX9jIFX"
          }
        ],
        "user_mentions": [
          {
            "id_str": "16562949",
            "indices": [
              "0", 
              "4"
            ],
            "name": "7x7",
            "screen_name": "7x7"
          }
        ]
      },
      "favorite_count": "0",
      "favorited": false,
      "full_text": "@7x7 The link to the Shaker furniture article doesn't work (but thank you for featuring it!) RE http://t.co/LjpiX9jIFX",
      "id_str": "311149850165133312",
      "in_reply_to_screen_name": "7x7",
      "in_reply_to_user_id": "16562949",
      "in_reply_to_user_id_str": "16562949",
      "lang": "en",
      "possibly_sensitive": false,
      "retweet_count": "0",
      "retweeted": false,
      "source": "\u003ca href=\"https://about.twitter.com/products/tweetdeck\" rel=\"nofollow\"\u003eTweetDeck\u003c/a\u003e",
      "truncated": false
    },
    "wof:name": "Twitter message #311149850165133312",
    "wof:placetype": "custom"
  },
  "geometry": {"coordinates":[-122.386166,37.616356],"type":"Point"}
}
