{
  "type": "Feature",
  "properties": {
    "date:cessation_lower":"2012-06-12",
    "date:cessation_upper":"2012-06-12",
    "date:inception_lower":"2012-06-12",
    "date:inception_upper":"2012-06-12",
    "iso:country":"US",
    "sfomuseum:placetype":"tweet",
    "twitter:tweet":{
        "created":1339533374,
        "created_at":"Tue Jun 12 20:36:14 +0000 2012",
        "display_text_range":[
            "0",
            "139"
        ],
        "entities":{
            "urls":[
                {
                    "display_url":"instagr.am/p/LyUnBcAqRo/",
                    "expanded_url":"http://instagr.am/p/LyUnBcAqRo/",
                    "indices":[
                        "119",
                        "139"
                    ],
                    "url":"http://t.co/9Zh3Tz63"
                }
            ],
            "user_mentions":[
                {
                    "id_str":"24911525",
                    "indices":[
                        "12",
                        "21"
                    ],
                    "name":"randy dodson",
                    "screen_name":"rwdodson"
                }
            ]
        },
        "favorite_count":"0",
        "favorited":false,
        "full_text":"Thanks!! MT @rwdodson: SFO Museum is awesome!!! Next time you're in the SFO Int'l Term, take the time to check it out! http://t.co/9Zh3Tz63",
        "id_str":"212644501494300672",
        "lang":"en",
        "possibly_sensitive":false,
        "retweet_count":"0",
        "retweeted":false,
        "source":"<a href=\"http://www.hootsuite.com\" rel=\"nofollow\">Hootsuite</a>",
        "truncated":false
    },
    "wof:name":"Thanks!! MT @rwdodson: SFO Museum is awesome!!! Next time you're in the SFO Int'l Term, take the time to check it out! http://t.co/9Zh3Tz63",
    "wof:placetype":"custom"
},
  "geometry": {"coordinates":[-122.386166,37.616356],"type":"Point"}
}