{
  "type": "Feature",
  "properties": {
    "sfomuseum:placetype": "tweet",
    "twitter:tweet": {
      "created": 1400087489,
      "created_at": "Wed May 14 17:11:29 +0000 2014",
      "display_text_range": [
        "0", 
        "132"
      ],
      "entities": {
        "hashtags": [
          {
            "indices": [
              "120", 
              "132"
            ],
            "text": "DualNatures"
          }
        ],
        "urls": [
          {
            "display_url": "ow.ly/wQsU2",
            "expanded_url": "http://ow.ly/wQsU2",
            "indices": [
              "97", 
              "119"
            ],
            "url": "http://t.co/1eSZ0GCQiW"
          }
        ]
      },
      "favorite_count": "0",
      "favorited": false,
      "full_text": "Installation is underway for our newest exhibit, Dual Natures in Ceramics! Sneak an online peek: http://t.co/1eSZ0GCQiW #DualNatures",
      "id_str": "466626870017261568",
      "lang": "en",
      "possibly_sensitive": false,
      "retweet_count": "0",
      "retweeted": false,
      "source": "\u003ca href=\"http://www.hootsuite.com\" rel=\"nofollow\"\u003eHootsuite\u003c/a\u003e",
      "truncated": false
    },
    "wof:name": "Twitter message #466626870017261568",
    "wof:placetype": "custom"
  },
  "geometry": {"coordinates":[-122.386166,37.616356],"type":"Point"}
}
