{
  "type": "Feature",
  "properties": {
    "date:cessation_lower": "2014-07-03",
    "date:cessation_upper": "2014-07-03",
    "date:inception_lower": "2014-07-03",
    "date:inception_upper": "2014-07-03",
    "iso:country": "US",
    "sfomuseum:placetype": "tweet",
    "twitter:tweet": {
      "created": 1404423606,
      "created_at": "Thu Jul 03 21:40:06 +0000 2014",
      "display_text_range": [
        "0", 
        "125"
      ],
      "entities": {
        "hashtags": [
          {
            "indices": [
              "91", 
              "101"
            ],
            "text": "4thofJuly"
          }
        ],
        "urls": [
          {
            "display_url": "instagram.com/p/qARrsHxk_1/",
            "expanded_url": "http://instagram.com/p/qARrsHxk_1/",
            "indices": [
              "103", 
              "125"
            ],
            "url": "http://t.co/D9OTG2q642"
          }
        ]
      },
      "favorite_count": "0",
      "favorited": false,
      "full_text": "\"Arrangement in Red, White, and Blue,\" an exhibit in 2002, is picture perfect for both the #4thofJuly… http://t.co/D9OTG2q642",
      "id_str": "484813860205895681",
      "lang": "en",
      "possibly_sensitive": false,
      "retweet_count": "1",
      "retweeted": false,
      "source": "\u003ca href=\"http://instagram.com\" rel=\"nofollow\"\u003eInstagram\u003c/a\u003e",
      "truncated": false
    },
    "wof:name": "\"Arrangement in Red, White, and Blue,\" an exhibit in 2002, is picture perfect for both the #4thofJuly… http://t.co/D9OTG2q642",
    "wof:placetype": "custom"
  },
  "geometry": {"coordinates":[-122.386166,37.616356],"type":"Point"}
}
