{
  "type": "Feature",
  "properties": {
    "sfomuseum:placetype": "tweet",
    "twitter:tweet": {
      "created": 1565825104,
      "created_at": "Wed Aug 14 23:25:04 +0000 2019",
      "display_text_range": [
        "0", 
        "295"
      ],
      "entities": {
        "hashtags": [
          {
            "indices": [
              "0", 
              "10"
            ],
            "text": "OnThisDay"
          }, 
          {
            "indices": [
              "264", 
              "271"
            ],
            "text": "avgeek"
          }
        ],
        "media": [
          {
            "display_url": "pic.twitter.com/l11U5JXID3",
            "expanded_url": "https://twitter.com/SFOMuseum/status/1161780809046646786/photo/1",
            "id_str": "1161780807243112448",
            "indices": [
              "272", 
              "295"
            ],
            "media_url": "http://pbs.twimg.com/media/EB95fSKXoAAullW.jpg",
            "media_url_https": "https://pbs.twimg.com/media/EB95fSKXoAAullW.jpg",
            "sizes": {
              "large": {
                "h": "1356",
                "resize": "fit",
                "w": "2000"
              },
              "medium": {
                "h": "814",
                "resize": "fit",
                "w": "1200"
              },
              "small": {
                "h": "461",
                "resize": "fit",
                "w": "680"
              },
              "thumb": {
                "h": "150",
                "resize": "crop",
                "w": "150"
              }
            },
            "type": "photo",
            "url": "https://t.co/l11U5JXID3"
          }
        ]
      },
      "extended_entities": {
        "media": [
          {
            "display_url": "pic.twitter.com/l11U5JXID3",
            "expanded_url": "https://twitter.com/SFOMuseum/status/1161780809046646786/photo/1",
            "id_str": "1161780807243112448",
            "indices": [
              "272", 
              "295"
            ],
            "media_url": "http://pbs.twimg.com/media/EB95fSKXoAAullW.jpg",
            "media_url_https": "https://pbs.twimg.com/media/EB95fSKXoAAullW.jpg",
            "sizes": {
              "large": {
                "h": "1356",
                "resize": "fit",
                "w": "2000"
              },
              "medium": {
                "h": "814",
                "resize": "fit",
                "w": "1200"
              },
              "small": {
                "h": "461",
                "resize": "fit",
                "w": "680"
              },
              "thumb": {
                "h": "150",
                "resize": "crop",
                "w": "150"
              }
            },
            "type": "photo",
            "url": "https://t.co/l11U5JXID3"
          }
        ]
      },
      "favorite_count": "43",
      "favorited": false,
      "full_text": "#OnThisDay in 1971, the first Douglas DC-10 service started at San Francisco International Airport (SFO). United’s McDonnell Douglas DC-10 was the first of the three-engine, or tri-jet, wide-body airliners to arrive at SFO. Have you ever flown on a Douglas DC-10? #avgeek https://t.co/l11U5JXID3",
      "id_str": "1161780809046646786",
      "lang": "en",
      "possibly_sensitive": false,
      "retweet_count": "11",
      "retweeted": false,
      "source": "\u003ca href=\"https://www.hootsuite.com\" rel=\"nofollow\"\u003eHootsuite Inc.\u003c/a\u003e",
      "truncated": false
    },
    "wof:name": "Twitter message #1161780809046646786",
    "wof:placetype": "custom"
  },
  "geometry": {"coordinates":[-122.386166,37.616356],"type":"Point"}
}
