{
  "type": "Feature",
  "properties": {
    "date:cessation_lower": "2022-10-26",
    "date:cessation_upper": "2022-10-26",
    "date:inception_lower": "2022-10-26",
    "date:inception_upper": "2022-10-26",
    "sfomuseum:placetype": "tweet",
    "twitter:tweet": {
      "created": 1666743898,
      "created_at": "Wed Oct 26 00:24:58 +0000 2022",
      "display_text_range": [
        "0",
        "79"
      ],
      "edit_info": {
        "initial": {
          "editTweetIds": [
            "1585064912682115073"
          ],
          "editableUntil": "2022-10-26T00:54:58.000Z",
          "editsRemaining": "5",
          "isEditEligible": false
        }
      },
      "entities": {
        "urls": [
          {
            "display_url": "bit.ly/3F20GOc",
            "expanded_url": "https://bit.ly/3F20GOc",
            "indices": [
              "56",
              "79"
            ],
            "url": "https://t.co/oOlmCBkhcx"
          }
        ]
      },
      "favorite_count": "0",
      "favorited": false,
      "full_text": "SkyTerrace is open Friday to Monday from 10 am to 6 pm. https://t.co/oOlmCBkhcx",
      "id_str": "1585064912682115073",
      "in_reply_to_screen_name": "SFOMuseum",
      "in_reply_to_status_id": "1585064907099484161",
      "in_reply_to_status_id_str": "1585064907099484161",
      "in_reply_to_user_id": "116329337",
      "in_reply_to_user_id_str": "116329337",
      "lang": "en",
      "possibly_sensitive": false,
      "retweet_count": "0",
      "retweeted": false,
      "source": "\u003ca href=\"https://mobile.twitter.com\" rel=\"nofollow\"\u003eTwitter Web App\u003c/a\u003e",
      "truncated": false
    },
    "wof:name": "SkyTerrace is open Friday to Monday from 10 am to 6 pm. https://t.co/oOlmCBkhcx",
    "wof:placetype": "custom"
  },
  "geometry": {"coordinates":[-122.386166,37.616356],"type":"Point"}
}
