{
  "type": "Feature",
  "properties": {
    "date:cessation_lower": "2018-09-28",
    "date:cessation_upper": "2018-09-28",
    "date:inception_lower": "2018-09-28",
    "date:inception_upper": "2018-09-28",
    "iso:country": "US",
    "sfomuseum:placetype": "tweet",
    "twitter:tweet": {
      "created": 1538150138,
      "created_at": "Fri Sep 28 15:55:38 +0000 2018",
      "display_text_range": [
        "0",
        "149"
      ],
      "edit_info": {
        "initial": {
          "editTweetIds": [
            "1045703588461260801"
          ],
          "editableUntil": "2018-09-28T16:55:38.379Z",
          "editsRemaining": "5",
          "isEditEligible": true
        }
      },
      "entities": {
        "user_mentions": [
          {
            "id_str": "1276389743861866496",
            "indices": [
              "0",
              "6"
            ],
            "name": "Himat",
            "screen_name": "himat"
          },
          {
            "id_str": "3126752787",
            "indices": [
              "8",
              "17"
            ],
            "name": "Dr Ron",
            "screen_name": "GbhvfRon"
          },
          {
            "id_str": "707304543323750400",
            "indices": [
              "19",
              "34"
            ],
            "name": "PacificBlue",
            "screen_name": "DavidWinckoski"
          },
          {
            "id_str": "14612710",
            "indices": [
              "36",
              "46"
            ],
            "name": "ED PARSONS",
            "screen_name": "edparsons"
          }
        ]
      },
      "favorite_count": "3",
      "favorited": false,
      "full_text": "@himat  @GbhvfRon  @DavidWinckoski  @edparsons Whoops! We had a mix up of photo folder. This is indeed a Vickers Viscount. Thanks for your keen eyes!",
      "id_str": "1045703588461260801",
      "in_reply_to_screen_name": "SFOMuseum",
      "in_reply_to_status_id": "1045487026575953920",
      "in_reply_to_status_id_str": "1045487026575953920",
      "in_reply_to_user_id": "116329337",
      "in_reply_to_user_id_str": "116329337",
      "lang": "en",
      "retweet_count": "0",
      "retweeted": false,
      "source": "\u003ca href=\"http://twitter.com\" rel=\"nofollow\"\u003eTwitter Web Client\u003c/a\u003e",
      "truncated": false
    },
    "twitter:user_mentions": [
      "himat",
      "GbhvfRon",
      "DavidWinckoski",
      "edparsons"
    ],
    "wof:name": "@himat  @GbhvfRon  @DavidWinckoski  @edparsons Whoops! We had a mix up of photo folder. This is indeed a Vickers Viscount. Thanks for your keen eyes!",
    "wof:placetype": "custom"
  },
  "geometry": {"coordinates":[-122.386166,37.616356],"type":"Point"}
}
