{
  "type": "Feature",
  "properties": {
    "sfomuseum:placetype": "tweet",
    "twitter:tweet": {
      "created": 1325284461,
      "created_at": "Fri Dec 30 22:34:21 +0000 2011",
      "display_text_range": [
        "0", 
        "110"
      ],
      "entities": {
        "user_mentions": [
          {
            "id_str": "14628872",
            "indices": [
              "0", 
              "11"
            ],
            "name": "Camille Hearst",
            "screen_name": "camillionz"
          }
        ]
      },
      "favorite_count": "0",
      "favorited": false,
      "full_text": "@camillionz So happy to hear that you enjoyed \"Revolutions per Minute\"! We hope you have a wonderful New Year!",
      "id_str": "152880228132339712",
      "in_reply_to_screen_name": "camillionz",
      "in_reply_to_status_id": "152859051070464001",
      "in_reply_to_status_id_str": "152859051070464001",
      "in_reply_to_user_id": "14628872",
      "in_reply_to_user_id_str": "14628872",
      "lang": "en",
      "retweet_count": "0",
      "retweeted": false,
      "source": "\u003ca href=\"https://about.twitter.com/products/tweetdeck\" rel=\"nofollow\"\u003eTweetDeck\u003c/a\u003e",
      "truncated": false
    },
    "wof:name": "Twitter message #152880228132339712",
    "wof:placetype": "custom"
  },
  "geometry": {"coordinates":[-122.386166,37.616356],"type":"Point"}
}
