{
  "type": "Feature",
  "properties": {
    "date:cessation_lower": "2013-09-27",
    "date:cessation_upper": "2013-09-27",
    "date:inception_lower": "2013-09-27",
    "date:inception_upper": "2013-09-27",
    "iso:country": "US",
    "sfomuseum:placetype": "tweet",
    "twitter:tweet": {
      "created": 1380240379,
      "created_at": "Fri Sep 27 00:06:19 +0000 2013",
      "display_text_range": [
        "0",
        "140"
      ],
      "edit_info": {
        "initial": {
          "editTweetIds": [
            "383382056744783872"
          ],
          "editableUntil": "2013-09-27T00:36:19.879Z",
          "editsRemaining": "5",
          "isEditEligible": true
        }
      },
      "entities": {
        "hashtags": [
          {
            "indices": [
              "126",
              "132"
            ],
            "text": "PanAm"
          },
          {
            "indices": [
              "133",
              "140"
            ],
            "text": "avgeek"
          }
        ],
        "urls": [
          {
            "display_url": "ow.ly/pfX6s",
            "expanded_url": "http://ow.ly/pfX6s",
            "indices": [
              "103",
              "125"
            ],
            "url": "http://t.co/8x4paRFlvD"
          }
        ]
      },
      "favorite_count": "0",
      "favorited": false,
      "full_text": "So cool to see depictions of fashionable folks in 1934 boarding their plane...that is docked on water! http://t.co/8x4paRFlvD #PanAm #avgeek",
      "id_str": "383382056744783872",
      "lang": "en",
      "possibly_sensitive": false,
      "retweet_count": "1",
      "retweeted": false,
      "source": "\u003ca href=\"http://www.hootsuite.com\" rel=\"nofollow\"\u003eHootsuite\u003c/a\u003e",
      "truncated": false
    },
    "wof:name": "So cool to see depictions of fashionable folks in 1934 boarding their plane...that is docked on water! http://t.co/8x4paRFlvD #PanAm #avgeek",
    "wof:placetype": "custom"
  },
  "geometry": {"coordinates":[-122.386166,37.616356],"type":"Point"}
}
