{
  "type": "Feature",
  "properties": {
    "date:cessation_lower": "2011-11-22",
    "date:cessation_upper": "2011-11-22",
    "date:inception_lower": "2011-11-22",
    "date:inception_upper": "2011-11-22",
    "iso:country": "US",
    "sfomuseum:placetype": "tweet",
    "twitter:tweet": {
      "created": 1322003556,
      "created_at": "Tue Nov 22 23:12:36 +0000 2011",
      "display_text_range": [
        "0",
        "129"
      ],
      "edit_info": {
        "initial": {
          "editTweetIds": [
            "139119116647792641"
          ],
          "editableUntil": "2011-11-23T00:12:36.774Z",
          "editsRemaining": "5",
          "isEditEligible": true
        }
      },
      "entities": {
        "user_mentions": [
          {
            "id_str": "231887259",
            "indices": [
              "3",
              "14"
            ],
            "name": "Thud Rumble",
            "screen_name": "ThudRumble"
          },
          {
            "id_str": "17659635",
            "indices": [
              "74",
              "85"
            ],
            "name": "Fran Boogie",
            "screen_name": "FranBoogie"
          },
          {
            "id_str": "231887259",
            "indices": [
              "86",
              "97"
            ],
            "name": "Thud Rumble",
            "screen_name": "ThudRumble"
          },
          {
            "id_str": "21543254",
            "indices": [
              "98",
              "106"
            ],
            "name": "DJ Q*BERT 👾 Invisibl Skratch Piklz",
            "screen_name": "DJQbert"
          },
          {
            "id_str": "116329337",
            "indices": [
              "107",
              "117"
            ],
            "name": "SFO Museum",
            "screen_name": "SFOMuseum"
          }
        ]
      },
      "favorite_count": "0",
      "favorited": false,
      "full_text": "RT @ThudRumble: Bring the kidz, we'll be giving away free stuff! . . . RT @FranBoogie @ThudRumble @DJQbert @SFOMuseum - all ages?",
      "id_str": "139119116647792641",
      "lang": "en",
      "retweet_count": "0",
      "retweeted": false,
      "source": "\u003ca href=\"http://twitter.com/download/iphone\" rel=\"nofollow\"\u003eTwitter for iPhone\u003c/a\u003e",
      "truncated": false
    },
    "twitter:user_mentions": [
      "ThudRumble",
      "FranBoogie",
      "DJQbert",
      "SFOMuseum"
    ],
    "wof:name": "RT @ThudRumble: Bring the kidz, we'll be giving away free stuff! . . . RT @FranBoogie @ThudRumble @DJQbert @SFOMuseum - all ages?",
    "wof:placetype": "custom",
    "wof:placetype_alt": [
      "tweet"
    ]
  },
  "geometry": {"coordinates":[-122.386166,37.616356],"type":"Point"}
}
