{
  "type": "Feature",
  "properties": {
    "date:cessation_lower": "2016-12-07",
    "date:cessation_upper": "2016-12-07",
    "date:inception_lower": "2016-12-07",
    "date:inception_upper": "2016-12-07",
    "iso:country": "US",
    "sfomuseum:placetype": "tweet",
    "twitter:hashtags": [
      "AnselAdams"
    ],
    "twitter:tweet": {
      "created": 1481139853,
      "created_at": "Wed Dec 07 19:44:13 +0000 2016",
      "display_text_range": [
        "0",
        "164"
      ],
      "edit_info": {
        "initial": {
          "editTweetIds": [
            "806585122669543424"
          ],
          "editableUntil": "2016-12-07T20:44:13.528Z",
          "editsRemaining": "5",
          "isEditEligible": true
        }
      },
      "entities": {
        "hashtags": [
          {
            "indices": [
              "97",
              "108"
            ],
            "text": "AnselAdams"
          }
        ],
        "urls": [
          {
            "display_url": "bit.ly/2deWdM0",
            "expanded_url": "http://bit.ly/2deWdM0",
            "indices": [
              "117",
              "140"
            ],
            "url": "https://t.co/IfEVwnUNWX"
          },
          {
            "display_url": "twitter.com/KQED/status/80…",
            "expanded_url": "https://twitter.com/KQED/status/806566372184649728",
            "indices": [
              "141",
              "164"
            ],
            "url": "https://t.co/vjIVaTxJS1"
          }
        ]
      },
      "favorite_count": "1",
      "favorited": false,
      "full_text": "Aiko Yoshinaga was sent to Manzanar War Relocation Center during WWII. See photos of Manzanar by #AnselAdams, in T2. https://t.co/IfEVwnUNWX https://t.co/vjIVaTxJS1",
      "id_str": "806585122669543424",
      "lang": "en",
      "possibly_sensitive": false,
      "retweet_count": "0",
      "retweeted": false,
      "source": "\u003ca href=\"http://twitter.com\" rel=\"nofollow\"\u003eTwitter Web Client\u003c/a\u003e",
      "truncated": false
    },
    "wof:name": "Aiko Yoshinaga was sent to Manzanar War Relocation Center during WWII. See photos of Manzanar by #AnselAdams, in T2. https://t.co/IfEVwnUNWX https://t.co/vjIVaTxJS1",
    "wof:placetype": "custom",
    "wof:placetype_alt": [
      "tweet"
    ]
  },
  "geometry": {"coordinates":[-122.386166,37.616356],"type":"Point"}
}
