{
  "type": "Feature",
  "properties": {
    "sfomuseum:placetype": "tweet",
    "twitter:tweet": {
      "created": 1345840622,
      "created_at": "Fri Aug 24 20:37:02 +0000 2012",
      "display_text_range": [
        "0", 
        "132"
      ],
      "entities": {
        "urls": [
          {
            "display_url": "youtu.be/HC3vQnVeaLc",
            "expanded_url": "http://youtu.be/HC3vQnVeaLc",
            "indices": [
              "54", 
              "74"
            ],
            "url": "http://t.co/2kUsi733"
          }, 
          {
            "display_url": "instagr.am/p/OuWuXQkiMJ/",
            "expanded_url": "http://instagr.am/p/OuWuXQkiMJ/",
            "indices": [
              "112", 
              "132"
            ],
            "url": "http://t.co/eHcA1YZU"
          }
        ],
        "user_mentions": [
          {
            "id_str": "14308635",
            "indices": [
              "78", 
              "92"
            ],
            "name": "Victor Gaxiola",
            "screen_name": "VictorGaxiola"
          }
        ]
      },
      "favorite_count": "1",
      "favorited": false,
      "full_text": "Video of the artist, Kendall Buster, at installation: http://t.co/2kUsi733 RT @VictorGaxiola: Airport Art @ SFO http://t.co/eHcA1YZU",
      "id_str": "239099015151624192",
      "lang": "en",
      "possibly_sensitive": false,
      "retweet_count": "1",
      "retweeted": false,
      "source": "\u003ca href=\"https://about.twitter.com/products/tweetdeck\" rel=\"nofollow\"\u003eTweetDeck\u003c/a\u003e",
      "truncated": false
    },
    "wof:name": "Twitter message #239099015151624192",
    "wof:placetype": "custom"
  },
  "geometry": {"coordinates":[-122.386166,37.616356],"type":"Point"}
}
