{
  "type": "Feature",
  "properties": {
    "sfomuseum:placetype": "tweet",
    "twitter:tweet": {
      "created": 1321910940,
      "created_at": "Mon Nov 21 21:29:00 +0000 2011",
      "display_text_range": [
        "0", 
        "73"
      ],
      "entities": {
        "user_mentions": [
          {
            "id_str": "176504938",
            "indices": [
              "0", 
              "9"
            ],
            "name": "W O R K G R O U P",
            "screen_name": "WKGPCREW"
          }
        ]
      },
      "favorite_count": "0",
      "favorited": false,
      "full_text": "@WKGPCREW Thank you!! I'll be sure to pass the praise along to our staff!",
      "id_str": "138730653905715201",
      "in_reply_to_screen_name": "WKGPCREW",
      "in_reply_to_status_id": "138714764544196609",
      "in_reply_to_status_id_str": "138714764544196609",
      "in_reply_to_user_id": "176504938",
      "in_reply_to_user_id_str": "176504938",
      "lang": "en",
      "retweet_count": "0",
      "retweeted": false,
      "source": "\u003ca href=\"https://about.twitter.com/products/tweetdeck\" rel=\"nofollow\"\u003eTweetDeck\u003c/a\u003e",
      "truncated": false
    },
    "wof:name": "Twitter message #138730653905715201",
    "wof:placetype": "custom"
  },
  "geometry": {"coordinates":[-122.386166,37.616356],"type":"Point"}
}
