{
  "type": "Feature",
  "properties": {
    "sfomuseum:placetype": "tweet",
    "twitter:tweet": {
      "created": 1332346921,
      "created_at": "Wed Mar 21 16:22:01 +0000 2012",
      "display_text_range": [
        "0", 
        "125"
      ],
      "entities": {
      },
      "favorite_count": "1",
      "favorited": false,
      "full_text": "The 1st major rock-n-roll concert, The Moondog Coronation Ball, radical in its racially diverse lineup, was held OTD in 1952.",
      "id_str": "182502332217573377",
      "lang": "en",
      "retweet_count": "0",
      "retweeted": false,
      "source": "\u003ca href=\"https://about.twitter.com/products/tweetdeck\" rel=\"nofollow\"\u003eTweetDeck\u003c/a\u003e",
      "truncated": false
    },
    "wof:name": "Twitter message #182502332217573377",
    "wof:placetype": "custom"
  },
  "geometry": {"coordinates":[-122.386166,37.616356],"type":"Point"}
}
