{
  "type": "Feature",
  "properties": {
    "sfomuseum:placetype": "tweet",
    "twitter:tweet": {
      "created": 1350075579,
      "created_at": "Fri Oct 12 20:59:39 +0000 2012",
      "display_text_range": [
        "0", 
        "130"
      ],
      "entities": {
        "urls": [
          {
            "display_url": "ow.ly/ereGN",
            "expanded_url": "http://ow.ly/ereGN",
            "indices": [
              "110", 
              "130"
            ],
            "url": "http://t.co/7RtlSWaY"
          }
        ]
      },
      "favorite_count": "0",
      "favorited": false,
      "full_text": "Berndt Friberg's expert craftsmanship in wheel throwing \u0026amp; glazing won him many awards through his career: http://t.co/7RtlSWaY",
      "id_str": "256861715239673857",
      "lang": "en",
      "possibly_sensitive": false,
      "retweet_count": "1",
      "retweeted": false,
      "source": "\u003ca href=\"http://www.hootsuite.com\" rel=\"nofollow\"\u003eHootsuite\u003c/a\u003e",
      "truncated": false
    },
    "wof:name": "Twitter message #256861715239673857",
    "wof:placetype": "custom"
  },
  "geometry": {"coordinates":[-122.386166,37.616356],"type":"Point"}
}
