{
  "type": "Feature",
  "properties": {
    "sfomuseum:placetype": "tweet",
    "twitter:tweet": {
      "created": 1521231206,
      "created_at": "Fri Mar 16 20:13:26 +0000 2018",
      "display_text_range": [
        "0", 
        "139"
      ],
      "entities": {
        "user_mentions": [
          {
            "id_str": "40113236",
            "indices": [
              "3", 
              "19"
            ],
            "name": "Airline Reporter",
            "screen_name": "AirlineReporter"
          }, 
          {
            "id_str": "22090282",
            "indices": [
              "62", 
              "78"
            ],
            "name": "Boeing Airplanes",
            "screen_name": "BoeingAirplanes"
          }
        ]
      },
      "favorite_count": "0",
      "favorited": false,
      "full_text": "RT @AirlineReporter: It was a rare and lovely sunny day for a @BoeingAirplanes first flight. The 737 Max 7 is the smallest Boeing airplane…",
      "id_str": "974740444453126145",
      "lang": "en",
      "retweet_count": "0",
      "retweeted": false,
      "source": "\u003ca href=\"http://twitter.com\" rel=\"nofollow\"\u003eTwitter Web Client\u003c/a\u003e",
      "truncated": false
    },
    "wof:name": "Twitter message #974740444453126145",
    "wof:placetype": "custom"
  },
  "geometry": {"coordinates":[-122.386166,37.616356],"type":"Point"}
}
