{
  "type": "Feature",
  "properties": {
    "sfomuseum:placetype": "tweet",
    "twitter:tweet": {
      "created": 1380054202,
      "created_at": "Tue Sep 24 20:23:22 +0000 2013",
      "display_text_range": [
        "0", 
        "124"
      ],
      "entities": {
        "urls": [
          {
            "display_url": "instagram.com/p/ep_Ng_xk85/",
            "expanded_url": "http://instagram.com/p/ep_Ng_xk85/",
            "indices": [
              "102", 
              "124"
            ],
            "url": "http://t.co/I381KByHVf"
          }
        ]
      },
      "favorite_count": "0",
      "favorited": false,
      "full_text": "Half models of ships in shadowboxes were crafted by sailors both at sea and on shore, and were often… http://t.co/I381KByHVf",
      "id_str": "382601173909639169",
      "lang": "en",
      "possibly_sensitive": false,
      "retweet_count": "1",
      "retweeted": false,
      "source": "\u003ca href=\"http://instagram.com\" rel=\"nofollow\"\u003eInstagram\u003c/a\u003e",
      "truncated": false
    },
    "wof:name": "Twitter message #382601173909639169",
    "wof:placetype": "custom"
  },
  "geometry": {"coordinates":[-122.386166,37.616356],"type":"Point"}
}
