{
  "type": "Feature",
  "properties": {
    "sfomuseum:placetype": "tweet",
    "twitter:tweet": {
      "created": 1544385636,
      "created_at": "Sun Dec 09 20:00:36 +0000 2018",
      "display_text_range": [
        "0", 
        "264"
      ],
      "entities": {
        "hashtags": [
          {
            "indices": [
              "0", 
              "13"
            ],
            "text": "RhodaKellogg"
          }
        ],
        "media": [
          {
            "display_url": "pic.twitter.com/ttT5FKxPTS",
            "expanded_url": "https://twitter.com/SFOMuseum/status/1071857161981046784/photo/1",
            "id_str": "1071857159577788417",
            "indices": [
              "241", 
              "264"
            ],
            "media_url": "http://pbs.twimg.com/media/DuAAaF6X4AEuVJX.jpg",
            "media_url_https": "https://pbs.twimg.com/media/DuAAaF6X4AEuVJX.jpg",
            "sizes": {
              "large": {
                "h": "1415",
                "resize": "fit",
                "w": "2000"
              },
              "medium": {
                "h": "849",
                "resize": "fit",
                "w": "1200"
              },
              "small": {
                "h": "481",
                "resize": "fit",
                "w": "680"
              },
              "thumb": {
                "h": "150",
                "resize": "crop",
                "w": "150"
              }
            },
            "type": "photo",
            "url": "https://t.co/ttT5FKxPTS"
          }
        ]
      },
      "extended_entities": {
        "media": [
          {
            "display_url": "pic.twitter.com/ttT5FKxPTS",
            "expanded_url": "https://twitter.com/SFOMuseum/status/1071857161981046784/photo/1",
            "id_str": "1071857159577788417",
            "indices": [
              "241", 
              "264"
            ],
            "media_url": "http://pbs.twimg.com/media/DuAAaF6X4AEuVJX.jpg",
            "media_url_https": "https://pbs.twimg.com/media/DuAAaF6X4AEuVJX.jpg",
            "sizes": {
              "large": {
                "h": "1415",
                "resize": "fit",
                "w": "2000"
              },
              "medium": {
                "h": "849",
                "resize": "fit",
                "w": "1200"
              },
              "small": {
                "h": "481",
                "resize": "fit",
                "w": "680"
              },
              "thumb": {
                "h": "150",
                "resize": "crop",
                "w": "150"
              }
            },
            "type": "photo",
            "url": "https://t.co/ttT5FKxPTS"
          }
        ]
      },
      "favorite_count": "0",
      "favorited": false,
      "full_text": "#RhodaKellogg amassed an extensive and wide-ranging collection of children’s art—numbering over half a million pieces—through travels in thirty countries around the world and through her work with children at the Phoebe A. Hearst Preschool. https://t.co/ttT5FKxPTS",
      "id_str": "1071857161981046784",
      "lang": "en",
      "possibly_sensitive": false,
      "retweet_count": "0",
      "retweeted": false,
      "source": "\u003ca href=\"https://www.hootsuite.com\" rel=\"nofollow\"\u003eHootsuite Inc.\u003c/a\u003e",
      "truncated": false
    },
    "wof:name": "Twitter message #1071857161981046784",
    "wof:placetype": "custom"
  },
  "geometry": {"coordinates":[-122.386166,37.616356],"type":"Point"}
}
