{
  "type": "Feature",
  "properties": {
    "sfomuseum:placetype": "tweet",
    "twitter:tweet": {
      "created": 1520190021,
      "created_at": "Sun Mar 04 19:00:21 +0000 2018",
      "display_text_range": [
        "0", 
        "172"
      ],
      "entities": {
        "hashtags": [
          {
            "indices": [
              "23", 
              "35"
            ],
            "text": "AntoineBruy"
          }
        ],
        "media": [
          {
            "display_url": "pic.twitter.com/hB2oiqMPAi",
            "expanded_url": "https://twitter.com/SFOMuseum/status/970373396491067392/photo/1",
            "id_str": "970373392787533825",
            "indices": [
              "149", 
              "172"
            ],
            "media_url": "http://pbs.twimg.com/media/DXd1daCXcAEb2Gl.jpg",
            "media_url_https": "https://pbs.twimg.com/media/DXd1daCXcAEb2Gl.jpg",
            "sizes": {
              "large": {
                "h": "2000",
                "resize": "fit",
                "w": "2000"
              },
              "medium": {
                "h": "1200",
                "resize": "fit",
                "w": "1200"
              },
              "small": {
                "h": "680",
                "resize": "fit",
                "w": "680"
              },
              "thumb": {
                "h": "150",
                "resize": "crop",
                "w": "150"
              }
            },
            "type": "photo",
            "url": "https://t.co/hB2oiqMPAi"
          }
        ]
      },
      "extended_entities": {
        "media": [
          {
            "display_url": "pic.twitter.com/hB2oiqMPAi",
            "expanded_url": "https://twitter.com/SFOMuseum/status/970373396491067392/photo/1",
            "id_str": "970373392787533825",
            "indices": [
              "149", 
              "172"
            ],
            "media_url": "http://pbs.twimg.com/media/DXd1daCXcAEb2Gl.jpg",
            "media_url_https": "https://pbs.twimg.com/media/DXd1daCXcAEb2Gl.jpg",
            "sizes": {
              "large": {
                "h": "2000",
                "resize": "fit",
                "w": "2000"
              },
              "medium": {
                "h": "1200",
                "resize": "fit",
                "w": "1200"
              },
              "small": {
                "h": "680",
                "resize": "fit",
                "w": "680"
              },
              "thumb": {
                "h": "150",
                "resize": "crop",
                "w": "150"
              }
            },
            "type": "photo",
            "url": "https://t.co/hB2oiqMPAi"
          }
        ]
      },
      "favorite_count": "1",
      "favorited": false,
      "full_text": "Between 2010 and 2015, #AntoineBruy traveled throughout Europe and the United States in search of city folk who have embraced an off-grid lifestyle. https://t.co/hB2oiqMPAi",
      "id_str": "970373396491067392",
      "lang": "en",
      "possibly_sensitive": false,
      "retweet_count": "0",
      "retweeted": false,
      "source": "\u003ca href=\"http://www.hootsuite.com\" rel=\"nofollow\"\u003eHootsuite\u003c/a\u003e",
      "truncated": false
    },
    "wof:name": "Twitter message #970373396491067392",
    "wof:placetype": "custom"
  },
  "geometry": {"coordinates":[-122.386166,37.616356],"type":"Point"}
}
