{
  "type": "Feature",
  "properties": {
    "sfomuseum:placetype": "tweet",
    "twitter:tweet": {
      "created": 1383930456,
      "created_at": "Fri Nov 08 17:07:36 +0000 2013",
      "display_text_range": [
        "0", 
        "128"
      ],
      "entities": {
        "urls": [
          {
            "display_url": "ow.ly/qD4Mu",
            "expanded_url": "http://ow.ly/qD4Mu",
            "indices": [
              "106", 
              "128"
            ],
            "url": "http://t.co/QUOEEsytoM"
          }
        ],
        "user_mentions": [
          {
            "id_str": "16408759",
            "indices": [
              "1", 
              "8"
            ],
            "name": "San Francisco International Airport (SFO) ✈️",
            "screen_name": "flySFO"
          }
        ]
      },
      "favorite_count": "1",
      "favorited": false,
      "full_text": ".@flySFO is on the charts! Help them climb higher: vote in USA Today's survey for best art at an airport! http://t.co/QUOEEsytoM",
      "id_str": "398859360551837696",
      "lang": "en",
      "possibly_sensitive": false,
      "retweet_count": "2",
      "retweeted": false,
      "source": "\u003ca href=\"http://www.hootsuite.com\" rel=\"nofollow\"\u003eHootsuite\u003c/a\u003e",
      "truncated": false
    },
    "wof:name": "Twitter message #398859360551837696",
    "wof:placetype": "custom"
  },
  "geometry": {"coordinates":[-122.386166,37.616356],"type":"Point"}
}
