{
  "type": "Feature",
  "properties": {
    "sfomuseum:placetype": "tweet",
    "twitter:tweet": {
      "created": 1490556306,
      "created_at": "Sun Mar 26 19:25:06 +0000 2017",
      "display_text_range": [
        "0", 
        "164"
      ],
      "entities": {
        "hashtags": [
          {
            "indices": [
              "49", 
              "63"
            ],
            "text": "PamelaGentile"
          }
        ],
        "media": [
          {
            "display_url": "pic.twitter.com/FINfIz7EWV",
            "expanded_url": "https://twitter.com/SFOMuseum/status/846080590684270592/photo/1",
            "id_str": "846080588301979648",
            "indices": [
              "141", 
              "164"
            ],
            "media_url": "http://pbs.twimg.com/media/C73hz_UX0AAw3aJ.jpg",
            "media_url_https": "https://pbs.twimg.com/media/C73hz_UX0AAw3aJ.jpg",
            "sizes": {
              "large": {
                "h": "1333",
                "resize": "fit",
                "w": "2000"
              },
              "medium": {
                "h": "800",
                "resize": "fit",
                "w": "1200"
              },
              "small": {
                "h": "453",
                "resize": "fit",
                "w": "680"
              },
              "thumb": {
                "h": "150",
                "resize": "crop",
                "w": "150"
              }
            },
            "type": "photo",
            "url": "https://t.co/FINfIz7EWV"
          }
        ],
        "urls": [
          {
            "display_url": "bit.ly/2nBCfyE",
            "expanded_url": "http://bit.ly/2nBCfyE",
            "indices": [
              "117", 
              "140"
            ],
            "url": "https://t.co/FmEEdiZ4xf"
          }
        ]
      },
      "extended_entities": {
        "media": [
          {
            "display_url": "pic.twitter.com/FINfIz7EWV",
            "expanded_url": "https://twitter.com/SFOMuseum/status/846080590684270592/photo/1",
            "id_str": "846080588301979648",
            "indices": [
              "141", 
              "164"
            ],
            "media_url": "http://pbs.twimg.com/media/C73hz_UX0AAw3aJ.jpg",
            "media_url_https": "https://pbs.twimg.com/media/C73hz_UX0AAw3aJ.jpg",
            "sizes": {
              "large": {
                "h": "1333",
                "resize": "fit",
                "w": "2000"
              },
              "medium": {
                "h": "800",
                "resize": "fit",
                "w": "1200"
              },
              "small": {
                "h": "453",
                "resize": "fit",
                "w": "680"
              },
              "thumb": {
                "h": "150",
                "resize": "crop",
                "w": "150"
              }
            },
            "type": "photo",
            "url": "https://t.co/FINfIz7EWV"
          }
        ]
      },
      "favorite_count": "0",
      "favorited": false,
      "full_text": "See \"Atmosphere: Portrait of a Film Festival\" by #PamelaGentile, pre-security, on the departures level of Terminal 2 https://t.co/FmEEdiZ4xf https://t.co/FINfIz7EWV",
      "id_str": "846080590684270592",
      "lang": "en",
      "possibly_sensitive": false,
      "retweet_count": "0",
      "retweeted": false,
      "source": "\u003ca href=\"http://www.hootsuite.com\" rel=\"nofollow\"\u003eHootsuite\u003c/a\u003e",
      "truncated": false
    },
    "wof:name": "Twitter message #846080590684270592",
    "wof:placetype": "custom"
  },
  "geometry": {"coordinates":[-122.386166,37.616356],"type":"Point"}
}
