{
  "type": "Feature",
  "properties": {
    "date:cessation_lower": "2022-01-05",
    "date:cessation_upper": "2022-01-05",
    "date:inception_lower": "2022-01-05",
    "date:inception_upper": "2022-01-05",
    "sfomuseum:placetype": "tweet",
    "twitter:hashtags": [
      "StonewareStories"
    ],
    "twitter:tweet": {
      "created": 1641351027,
      "created_at": "Wed Jan 05 02:50:27 +0000 2022",
      "display_text_range": [
        "0",
        "141"
      ],
      "edit_info": {
        "initial": {
          "editTweetIds": [
            "1478559489271812098"
          ],
          "editableUntil": "2022-01-05T03:50:27.206Z",
          "editsRemaining": "5",
          "isEditEligible": true
        }
      },
      "entities": {
        "hashtags": [
          {
            "indices": [
              "124",
              "141"
            ],
            "text": "StonewareStories"
          }
        ]
      },
      "favorite_count": "0",
      "favorited": false,
      "full_text": "\"A very large jar which has four handles \npack it full of fresh meat—then light candles\"\nDave (c. 1800–70s) \nApril 12, 1858 #StonewareStories",
      "id_str": "1478559489271812098",
      "lang": "en",
      "retweet_count": "0",
      "retweeted": false,
      "source": "\u003ca href=\"https://mobile.twitter.com\" rel=\"nofollow\"\u003eTwitter Web App\u003c/a\u003e",
      "truncated": false
    },
    "wof:name": "\"A very large jar which has four handles \npack it full of fresh meat—then light candles\"\nDave (c. 1800–70s) \nApril 12, 1858 #StonewareStories",
    "wof:placetype": "custom",
    "wof:placetype_alt": [
      "tweet"
    ]
  },
  "geometry": {"coordinates":[-122.386166,37.616356],"type":"Point"}
}
