{
  "type": "Feature",
  "properties": {
    "date:cessation_lower": "2015-11-11",
    "date:cessation_upper": "2015-11-11",
    "date:inception_lower": "2015-11-11",
    "date:inception_upper": "2015-11-11",
    "iso:country": "US",
    "sfomuseum:placetype": "tweet",
    "twitter:tweet": {
      "created": 1447205708,
      "created_at": "Wed Nov 11 01:35:08 +0000 2015",
      "display_text_range": [
        "0",
        "136"
      ],
      "edit_info": {
        "initial": {
          "editTweetIds": [
            "664255002165293060"
          ],
          "editableUntil": "2015-11-11T02:05:08.434Z",
          "editsRemaining": "5",
          "isEditEligible": true
        }
      },
      "entities": {
        "urls": [
          {
            "display_url": "ow.ly/UuQGV",
            "expanded_url": "http://ow.ly/UuQGV",
            "indices": [
              "113",
              "136"
            ],
            "url": "https://t.co/10PiDldjz1"
          }
        ]
      },
      "favorite_count": "0",
      "favorited": false,
      "full_text": "The Aviation Museum and Library will be closed for Veterans Day, but all other exhibitions are open. Learn more: https://t.co/10PiDldjz1",
      "id_str": "664255002165293060",
      "lang": "en",
      "possibly_sensitive": false,
      "retweet_count": "0",
      "retweeted": false,
      "source": "\u003ca href=\"http://www.hootsuite.com\" rel=\"nofollow\"\u003eHootsuite\u003c/a\u003e",
      "truncated": false
    },
    "wof:name": "The Aviation Museum and Library will be closed for Veterans Day, but all other exhibitions are open. Learn more: https://t.co/10PiDldjz1",
    "wof:placetype": "custom"
  },
  "geometry": {"coordinates":[-122.386166,37.616356],"type":"Point"}
}
