{
  "type": "Feature",
  "properties": {
    "sfomuseum:placetype": "tweet",
    "twitter:tweet": {
      "created": 1502155206,
      "created_at": "Tue Aug 08 01:20:06 +0000 2017",
      "display_text_range": [
        "0", 
        "159"
      ],
      "entities": {
        "media": [
          {
            "display_url": "pic.twitter.com/HpYxzD5SDy",
            "expanded_url": "https://twitter.com/SFOMuseum/status/894729901739200513/photo/1",
            "id_str": "894729898438348801",
            "indices": [
              "136", 
              "159"
            ],
            "media_url": "http://pbs.twimg.com/media/DGq4GiZW0AEVDdi.jpg",
            "media_url_https": "https://pbs.twimg.com/media/DGq4GiZW0AEVDdi.jpg",
            "sizes": {
              "large": {
                "h": "2000",
                "resize": "fit",
                "w": "1562"
              },
              "medium": {
                "h": "1200",
                "resize": "fit",
                "w": "937"
              },
              "small": {
                "h": "680",
                "resize": "fit",
                "w": "531"
              },
              "thumb": {
                "h": "150",
                "resize": "crop",
                "w": "150"
              }
            },
            "type": "photo",
            "url": "https://t.co/HpYxzD5SDy"
          }
        ]
      },
      "extended_entities": {
        "media": [
          {
            "display_url": "pic.twitter.com/HpYxzD5SDy",
            "expanded_url": "https://twitter.com/SFOMuseum/status/894729901739200513/photo/1",
            "id_str": "894729898438348801",
            "indices": [
              "136", 
              "159"
            ],
            "media_url": "http://pbs.twimg.com/media/DGq4GiZW0AEVDdi.jpg",
            "media_url_https": "https://pbs.twimg.com/media/DGq4GiZW0AEVDdi.jpg",
            "sizes": {
              "large": {
                "h": "2000",
                "resize": "fit",
                "w": "1562"
              },
              "medium": {
                "h": "1200",
                "resize": "fit",
                "w": "937"
              },
              "small": {
                "h": "680",
                "resize": "fit",
                "w": "531"
              },
              "thumb": {
                "h": "150",
                "resize": "crop",
                "w": "150"
              }
            },
            "type": "photo",
            "url": "https://t.co/HpYxzD5SDy"
          }
        ]
      },
      "favorite_count": "13",
      "favorited": false,
      "full_text": "\"Wherever in the world you want to go...the world's largest fleet of over-ocean Jets is at your service...the Pan Am Jet Clipper Fleet\" https://t.co/HpYxzD5SDy",
      "id_str": "894729901739200513",
      "lang": "en",
      "possibly_sensitive": false,
      "retweet_count": "8",
      "retweeted": false,
      "source": "\u003ca href=\"http://www.hootsuite.com\" rel=\"nofollow\"\u003eHootsuite\u003c/a\u003e",
      "truncated": false
    },
    "wof:name": "Twitter message #894729901739200513",
    "wof:placetype": "custom"
  },
  "geometry": {"coordinates":[-122.386166,37.616356],"type":"Point"}
}
