{
  "type": "Feature",
  "properties": {
    "sfomuseum:placetype": "tweet",
    "twitter:tweet": {
      "created": 1534010447,
      "created_at": "Sat Aug 11 18:00:47 +0000 2018",
      "display_text_range": [
        "0", 
        "210"
      ],
      "entities": {
        "hashtags": [
          {
            "indices": [
              "50", 
              "62"
            ],
            "text": "LewisDesoto"
          }, 
          {
            "indices": [
              "175", 
              "186"
            ],
            "text": "airportart"
          }
        ],
        "media": [
          {
            "display_url": "pic.twitter.com/eT6sOISXcp",
            "expanded_url": "https://twitter.com/SFOMuseum/status/1028340464540377089/photo/1",
            "id_str": "1028340462199791616",
            "indices": [
              "187", 
              "210"
            ],
            "media_url": "http://pbs.twimg.com/media/DkVmM7WUYAAYupP.jpg",
            "media_url_https": "https://pbs.twimg.com/media/DkVmM7WUYAAYupP.jpg",
            "sizes": {
              "large": {
                "h": "2048",
                "resize": "fit",
                "w": "1530"
              },
              "medium": {
                "h": "1200",
                "resize": "fit",
                "w": "896"
              },
              "small": {
                "h": "680",
                "resize": "fit",
                "w": "508"
              },
              "thumb": {
                "h": "150",
                "resize": "crop",
                "w": "150"
              }
            },
            "type": "photo",
            "url": "https://t.co/eT6sOISXcp"
          }
        ]
      },
      "extended_entities": {
        "media": [
          {
            "display_url": "pic.twitter.com/eT6sOISXcp",
            "expanded_url": "https://twitter.com/SFOMuseum/status/1028340464540377089/photo/1",
            "id_str": "1028340462199791616",
            "indices": [
              "187", 
              "210"
            ],
            "media_url": "http://pbs.twimg.com/media/DkVmM7WUYAAYupP.jpg",
            "media_url_https": "https://pbs.twimg.com/media/DkVmM7WUYAAYupP.jpg",
            "sizes": {
              "large": {
                "h": "2048",
                "resize": "fit",
                "w": "1530"
              },
              "medium": {
                "h": "1200",
                "resize": "fit",
                "w": "896"
              },
              "small": {
                "h": "680",
                "resize": "fit",
                "w": "508"
              },
              "thumb": {
                "h": "150",
                "resize": "crop",
                "w": "150"
              }
            },
            "type": "photo",
            "url": "https://t.co/eT6sOISXcp"
          }
        ]
      },
      "favorite_count": "2",
      "favorited": false,
      "full_text": "\"Shining Paths: San Francisco's Sister Cities\" by #LewisDesoto in its entirety consists of 16 light projections that celebrate San Francisco’s Sister Cities around the world. #airportart https://t.co/eT6sOISXcp",
      "id_str": "1028340464540377089",
      "lang": "en",
      "possibly_sensitive": false,
      "retweet_count": "0",
      "retweeted": false,
      "source": "\u003ca href=\"https://www.hootsuite.com\" rel=\"nofollow\"\u003eHootsuite Inc.\u003c/a\u003e",
      "truncated": false
    },
    "wof:name": "Twitter message #1028340464540377089",
    "wof:placetype": "custom"
  },
  "geometry": {"coordinates":[-122.386166,37.616356],"type":"Point"}
}
