{
  "type": "Feature",
  "properties": {
    "date:cessation_lower": "2021-10-09",
    "date:cessation_upper": "2021-10-09",
    "date:inception_lower": "2021-10-09",
    "date:inception_upper": "2021-10-09",
    "sfomuseum:placetype": "tweet",
    "twitter:tweet": {
      "created": 1633739738,
      "created_at": "Sat Oct 09 00:35:38 +0000 2021",
      "display_text_range": [
        "0",
        "235"
      ],
      "edit_info": {
        "initial": {
          "editTweetIds": [
            "1446635429311094787"
          ],
          "editableUntil": "2021-10-09T01:05:38.191Z",
          "editsRemaining": "5",
          "isEditEligible": true
        }
      },
      "entities": {
        "hashtags": [
          {
            "indices": [
              "203",
              "224"
            ],
            "text": "victorianpaperedwall"
          },
          {
            "indices": [
              "225",
              "235"
            ],
            "text": "wallpaper"
          }
        ],
        "user_mentions": [
          {
            "id_str": "760308751",
            "indices": [
              "61",
              "75"
            ],
            "name": "Bradbury \u0026 Bradbury",
            "screen_name": "BradburyWalls"
          }
        ]
      },
      "favorite_count": "3",
      "favorited": false,
      "full_text": "Special thank you to Bradbury \u0026amp; Bradbury Art Wallpapers (@BradburyWalls) for making this exhibition possible; and to wallpaper hanger Heidi Wright Mead, C. P. for leading the wallpaper installation. #victorianpaperedwall #wallpaper",
      "id_str": "1446635429311094787",
      "in_reply_to_screen_name": "SFOMuseum",
      "in_reply_to_status_id": "1446635424902832128",
      "in_reply_to_status_id_str": "1446635424902832128",
      "in_reply_to_user_id": "116329337",
      "in_reply_to_user_id_str": "116329337",
      "lang": "en",
      "retweet_count": "0",
      "retweeted": false,
      "source": "\u003ca href=\"https://mobile.twitter.com\" rel=\"nofollow\"\u003eTwitter Web App\u003c/a\u003e",
      "truncated": false
    },
    "wof:name": "Special thank you to Bradbury \u0026amp; Bradbury Art Wallpapers (@BradburyWalls) for making this exhibition possible; and to wallpaper hanger Heidi Wright Mead, C. P. for leading the wallpaper installation. #victorianpaperedwall #wallpaper",
    "wof:placetype": "custom"
  },
  "geometry": {"coordinates":[-122.386166,37.616356],"type":"Point"}
}
