{
  "type": "Feature",
  "properties": {
    "date:cessation_lower": "2015-02-10",
    "date:cessation_upper": "2015-02-10",
    "date:inception_lower": "2015-02-10",
    "date:inception_upper": "2015-02-10",
    "iso:country": "US",
    "sfomuseum:placetype": "tweet",
    "twitter:tweet": {
      "created": 1423608848,
      "created_at": "Tue Feb 10 22:54:08 +0000 2015",
      "display_text_range": [
        "0",
        "124"
      ],
      "edit_info": {
        "initial": {
          "editTweetIds": [
            "565282597421715458"
          ],
          "editableUntil": "2015-02-10T23:24:08.325Z",
          "editsRemaining": "5",
          "isEditEligible": true
        }
      },
      "entities": {
        "urls": [
          {
            "display_url": "instagram.com/p/y8CoMkxk9l/",
            "expanded_url": "http://instagram.com/p/y8CoMkxk9l/",
            "indices": [
              "102",
              "124"
            ],
            "url": "http://t.co/RdKaHdGFKS"
          }
        ]
      },
      "favorite_count": "0",
      "favorited": false,
      "full_text": "Founded in 1920, Qantas (an acronym for Queensland and Northern Territory Aerial Services) is one of… http://t.co/RdKaHdGFKS",
      "id_str": "565282597421715458",
      "lang": "en",
      "possibly_sensitive": false,
      "retweet_count": "1",
      "retweeted": false,
      "source": "\u003ca href=\"http://instagram.com\" rel=\"nofollow\"\u003eInstagram\u003c/a\u003e",
      "truncated": false
    },
    "wof:name": "Founded in 1920, Qantas (an acronym for Queensland and Northern Territory Aerial Services) is one of… http://t.co/RdKaHdGFKS",
    "wof:placetype": "custom"
  },
  "geometry": {"coordinates":[-122.386166,37.616356],"type":"Point"}
}
