{
  "type": "Feature",
  "properties": {
    "sfomuseum:placetype": "tweet",
    "twitter:tweet": {
      "created": 1511214608,
      "created_at": "Mon Nov 20 21:50:08 +0000 2017",
      "display_text_range": [
        "0", 
        "170"
      ],
      "entities": {
        "hashtags": [
          {
            "indices": [
              "103", 
              "110"
            ],
            "text": "United"
          }, 
          {
            "indices": [
              "126", 
              "138"
            ],
            "text": "TheMainline"
          }, 
          {
            "indices": [
              "139", 
              "146"
            ],
            "text": "Hawaii"
          }
        ],
        "media": [
          {
            "display_url": "pic.twitter.com/o2VqOLueHf",
            "expanded_url": "https://twitter.com/SFOMuseum/status/932727786061647872/photo/1",
            "id_str": "932727781938614273",
            "indices": [
              "147", 
              "170"
            ],
            "media_url": "http://pbs.twimg.com/media/DPG2-dKW0AE8_FP.jpg",
            "media_url_https": "https://pbs.twimg.com/media/DPG2-dKW0AE8_FP.jpg",
            "sizes": {
              "large": {
                "h": "2000",
                "resize": "fit",
                "w": "915"
              },
              "medium": {
                "h": "1200",
                "resize": "fit",
                "w": "549"
              },
              "small": {
                "h": "680",
                "resize": "fit",
                "w": "311"
              },
              "thumb": {
                "h": "150",
                "resize": "crop",
                "w": "150"
              }
            },
            "type": "photo",
            "url": "https://t.co/o2VqOLueHf"
          }
        ]
      },
      "extended_entities": {
        "media": [
          {
            "display_url": "pic.twitter.com/o2VqOLueHf",
            "expanded_url": "https://twitter.com/SFOMuseum/status/932727786061647872/photo/1",
            "id_str": "932727781938614273",
            "indices": [
              "147", 
              "170"
            ],
            "media_url": "http://pbs.twimg.com/media/DPG2-dKW0AE8_FP.jpg",
            "media_url_https": "https://pbs.twimg.com/media/DPG2-dKW0AE8_FP.jpg",
            "sizes": {
              "large": {
                "h": "2000",
                "resize": "fit",
                "w": "915"
              },
              "medium": {
                "h": "1200",
                "resize": "fit",
                "w": "549"
              },
              "small": {
                "h": "680",
                "resize": "fit",
                "w": "311"
              },
              "thumb": {
                "h": "150",
                "resize": "crop",
                "w": "150"
              }
            },
            "type": "photo",
            "url": "https://t.co/o2VqOLueHf"
          }
        ]
      },
      "favorite_count": "5",
      "favorited": false,
      "full_text": "In an effort to promote the Islands, the Hawaiian Junior Chamber of Commerce organized Aloha Week with #United’s sponsorship. #TheMainline #Hawaii https://t.co/o2VqOLueHf",
      "id_str": "932727786061647872",
      "lang": "en",
      "possibly_sensitive": false,
      "retweet_count": "0",
      "retweeted": false,
      "source": "\u003ca href=\"http://www.hootsuite.com\" rel=\"nofollow\"\u003eHootsuite\u003c/a\u003e",
      "truncated": false
    },
    "wof:name": "Twitter message #932727786061647872",
    "wof:placetype": "custom"
  },
  "geometry": {"coordinates":[-122.386166,37.616356],"type":"Point"}
}
