{
  "type": "Feature",
  "properties": {
    "date:cessation_lower": "2012-12-12",
    "date:cessation_upper": "2012-12-12",
    "date:inception_lower": "2012-12-12",
    "date:inception_upper": "2012-12-12",
    "iso:country": "US",
    "sfomuseum:placetype": "tweet",
    "twitter:tweet": {
      "created": 1355339855,
      "created_at": "Wed Dec 12 19:17:35 +0000 2012",
      "display_text_range": [
        "0",
        "128"
      ],
      "edit_info": {
        "initial": {
          "editTweetIds": [
            "278941688217608192"
          ],
          "editableUntil": "2012-12-12T20:17:35.614Z",
          "editsRemaining": "5",
          "isEditEligible": true
        }
      },
      "entities": {
        "urls": [
          {
            "display_url": "bit.ly/ZgEo3F",
            "expanded_url": "http://bit.ly/ZgEo3F",
            "indices": [
              "108",
              "128"
            ],
            "url": "http://t.co/a04CSZaO"
          }
        ],
        "user_mentions": [
          {
            "id_str": "116329337",
            "indices": [
              "96",
              "106"
            ],
            "name": "SFO Museum",
            "screen_name": "SFOMuseum"
          }
        ]
      },
      "favorite_count": "0",
      "favorited": false,
      "full_text": "Get them started young... RT @ReidCarlberg: The money Game of Junior Executive -- on display at @sfomuseum. http://t.co/a04CSZaO",
      "id_str": "278941688217608192",
      "lang": "en",
      "possibly_sensitive": false,
      "retweet_count": "0",
      "retweeted": false,
      "source": "\u003ca href=\"https://about.twitter.com/products/tweetdeck\" rel=\"nofollow\"\u003eTweetDeck\u003c/a\u003e",
      "truncated": false
    },
    "twitter:user_mentions": [
      "SFOMuseum"
    ],
    "wof:name": "Get them started young... RT @ReidCarlberg: The money Game of Junior Executive -- on display at @sfomuseum. http://t.co/a04CSZaO",
    "wof:placetype": "custom",
    "wof:placetype_alt": [
      "tweet"
    ]
  },
  "geometry": {"coordinates":[-122.386166,37.616356],"type":"Point"}
}
