{
  "type": "Feature",
  "properties": {
    "date:cessation_lower": "2013-07-02",
    "date:cessation_upper": "2013-07-02",
    "date:inception_lower": "2013-07-02",
    "date:inception_upper": "2013-07-02",
    "iso:country": "US",
    "sfomuseum:placetype": "tweet",
    "twitter:hashtags": [
      "Aviation"
    ],
    "twitter:tweet": {
      "created": 1372806433,
      "created_at": "Tue Jul 02 23:07:13 +0000 2013",
      "display_text_range": [
        "0",
        "115"
      ],
      "edit_info": {
        "initial": {
          "editTweetIds": [
            "352201827741212674"
          ],
          "editableUntil": "2013-07-03T00:07:13.984Z",
          "editsRemaining": "5",
          "isEditEligible": true
        }
      },
      "entities": {
        "hashtags": [
          {
            "indices": [
              "76",
              "85"
            ],
            "text": "Aviation"
          }
        ],
        "urls": [
          {
            "display_url": "instagram.com/p/bSAVs-RkyH/",
            "expanded_url": "http://instagram.com/p/bSAVs-RkyH/",
            "indices": [
              "93",
              "115"
            ],
            "url": "http://t.co/5MBTl5CHAW"
          }
        ],
        "user_mentions": [
          {
            "id_str": "260907612",
            "indices": [
              "19",
              "26"
            ],
            "name": "United Airlines",
            "screen_name": "united"
          }
        ]
      },
      "favorite_count": "0",
      "favorited": false,
      "full_text": "Two very different @united uniforms from the mid/late 1960s, on view in our #Aviation Museum http://t.co/5MBTl5CHAW",
      "id_str": "352201827741212674",
      "lang": "en",
      "possibly_sensitive": false,
      "retweet_count": "1",
      "retweeted": false,
      "source": "\u003ca href=\"http://instagram.com\" rel=\"nofollow\"\u003eInstagram\u003c/a\u003e",
      "truncated": false
    },
    "twitter:user_mentions": [
      "united"
    ],
    "wof:name": "Two very different @united uniforms from the mid/late 1960s, on view in our #Aviation Museum http://t.co/5MBTl5CHAW",
    "wof:placetype": "custom",
    "wof:placetype_alt": [
      "tweet"
    ]
  },
  "geometry": {"coordinates":[-122.386166,37.616356],"type":"Point"}
}
