{
  "type": "Feature",
  "properties": {
    "date:cessation_lower": "2021-01-07",
    "date:cessation_upper": "2021-01-07",
    "date:inception_lower": "2021-01-07",
    "date:inception_upper": "2021-01-07",
    "sfomuseum:placetype": "tweet",
    "twitter:tweet": {
      "created": 1610047080,
      "created_at": "Thu Jan 07 19:18:00 +0000 2021",
      "display_text_range": [
        "0",
        "247"
      ],
      "entities": {
        "hashtags": [
          {
            "indices": [
              "0",
              "9"
            ],
            "text": "LinkWray"
          },
          {
            "indices": [
              "213",
              "230"
            ],
            "text": "InstrumentalSurf"
          },
          {
            "indices": [
              "232",
              "247"
            ],
            "text": "MuseumFromHome"
          }
        ],
        "urls": [
          {
            "display_url": "youtube.com/watch?v=46-4aw…",
            "expanded_url": "https://www.youtube.com/watch?v=46-4awkUZP8",
            "indices": [
              "189",
              "212"
            ],
            "url": "https://t.co/RyoEsQmsfa"
          }
        ]
      },
      "favorite_count": "0",
      "favorited": false,
      "full_text": "#LinkWray recalled, “I’ve got bad eyes and I can’t hear real good so I had to play loud ‘cause I couldn’t play clean…The only reason I was doing instrumentals was because I couldn’t sing.” https://t.co/RyoEsQmsfa #InstrumentalSurf  #MuseumFromHome",
      "id_str": "1347261219439259648",
      "lang": "en",
      "possibly_sensitive": false,
      "retweet_count": "0",
      "retweeted": false,
      "source": "\u003ca href=\"https://mobile.twitter.com\" rel=\"nofollow\"\u003eTwitter Web App\u003c/a\u003e",
      "truncated": false
    },
    "wof:name": "#LinkWray recalled, “I’ve got bad eyes and I can’t hear real good so I had to play loud ‘cause I couldn’t play clean…The only reason I was doing instrumentals was because I couldn’t sing.” https://t.co/RyoEsQmsfa #InstrumentalSurf  #MuseumFromHome",
    "wof:placetype": "custom"
  },
  "geometry": {"coordinates":[-122.386166,37.616356],"type":"Point"}
}
