{
  "type": "Feature",
  "properties": {
    "date:cessation_lower": "2012-10-24",
    "date:cessation_upper": "2012-10-24",
    "date:inception_lower": "2012-10-24",
    "date:inception_upper": "2012-10-24",
    "iso:country": "US",
    "sfomuseum:placetype": "tweet",
    "twitter:tweet": {
      "created": 1351112735,
      "created_at": "Wed Oct 24 21:05:35 +0000 2012",
      "display_text_range": [
        "0",
        "76"
      ],
      "edit_info": {
        "initial": {
          "editTweetIds": [
            "261211861662453760"
          ],
          "editableUntil": "2012-10-24T21:35:35.559Z",
          "editsRemaining": "5",
          "isEditEligible": true
        }
      },
      "entities": {
        "user_mentions": [
          {
            "id_str": "15206288",
            "indices": [
              "0",
              "14"
            ],
            "name": "Philip Pell",
            "screen_name": "EdmontonPearl"
          },
          {
            "id_str": "35177073",
            "indices": [
              "15",
              "24"
            ],
            "name": "Vanessa Blaylock",
            "screen_name": "vaneeesa"
          }
        ]
      },
      "favorite_count": "0",
      "favorited": false,
      "full_text": "@EdmontonPearl @vaneeesa Cool! We'd love to take a field trip \u0026amp; visit :)",
      "id_str": "261211861662453760",
      "in_reply_to_screen_name": "EdmontonPearl",
      "in_reply_to_user_id": "15206288",
      "in_reply_to_user_id_str": "15206288",
      "lang": "en",
      "retweet_count": "0",
      "retweeted": false,
      "source": "\u003ca href=\"https://about.twitter.com/products/tweetdeck\" rel=\"nofollow\"\u003eTweetDeck\u003c/a\u003e",
      "truncated": false
    },
    "wof:name": "@EdmontonPearl @vaneeesa Cool! We'd love to take a field trip \u0026amp; visit :)",
    "wof:placetype": "custom"
  },
  "geometry": {"coordinates":[-122.386166,37.616356],"type":"Point"}
}
