{
  "type": "Feature",
  "properties": {
    "date:cessation_lower": "2023-03-21",
    "date:cessation_upper": "2023-03-21",
    "date:inception_lower": "2023-03-21",
    "date:inception_upper": "2023-03-21",
    "sfomuseum:placetype": "tweet",
    "twitter:tweet": {
      "created": 1679358336,
      "created_at": "Tue Mar 21 00:25:36 +0000 2023",
      "display_text_range": [
        "0",
        "210"
      ],
      "edit_info": {
        "initial": {
          "editTweetIds": [
            "1637973696878116865"
          ],
          "editableUntil": "2023-03-21T00:55:36.000Z",
          "editsRemaining": "5",
          "isEditEligible": false
        }
      },
      "entities": {
        "urls": [
          {
            "display_url": "bit.ly/3l9LjhF",
            "expanded_url": "http://bit.ly/3l9LjhF",
            "indices": [
              "187",
              "210"
            ],
            "url": "https://t.co/C2E7YsvXLf"
          }
        ]
      },
      "favorite_count": "1",
      "favorited": false,
      "full_text": "📸:\nphotograph: Pan American Airways, Zoe Dell Lantis Nutter, Treasure Island, San Francisco; c. 1939 (reproduced 1993)\nTransferred from the Pan American World Airways Archive\n1993.11.34\n\nhttps://t.co/C2E7YsvXLf",
      "id_str": "1637973696878116865",
      "in_reply_to_screen_name": "SFOMuseum",
      "in_reply_to_status_id": "1637973693518483458",
      "in_reply_to_status_id_str": "1637973693518483458",
      "in_reply_to_user_id": "116329337",
      "in_reply_to_user_id_str": "116329337",
      "lang": "en",
      "possibly_sensitive": false,
      "retweet_count": "0",
      "retweeted": false,
      "source": "\u003ca href=\"https://mobile.twitter.com\" rel=\"nofollow\"\u003eTwitter Web App\u003c/a\u003e",
      "truncated": false
    },
    "wof:name": "📸:\nphotograph: Pan American Airways, Zoe Dell Lantis Nutter, Treasure Island, San Francisco; c. 1939 (reproduced 1993)\nTransferred from the Pan American World Airways Archive\n1993.11.34\n\nhttps://t.co/C2E7YsvXLf",
    "wof:placetype": "custom",
    "wof:placetype_alt": [
      "tweet"
    ]
  },
  "geometry": {"coordinates":[-122.386166,37.616356],"type":"Point"}
}
