{
  "type": "Feature",
  "properties": {
    "sfomuseum:placetype": "tweet",
    "twitter:tweet": {
      "created": 1456539323,
      "created_at": "Sat Feb 27 02:15:23 +0000 2016",
      "display_text_range": [
        "0", 
        "138"
      ],
      "entities": {
        "media": [
          {
            "display_url": "pic.twitter.com/PC9X7F1C9J",
            "expanded_url": "https://twitter.com/SFOMuseum/status/703403020948783105/photo/1",
            "id_str": "703403019426095104",
            "indices": [
              "115", 
              "138"
            ],
            "media_url": "http://pbs.twimg.com/media/CcL9UcLUYAADKkb.jpg",
            "media_url_https": "https://pbs.twimg.com/media/CcL9UcLUYAADKkb.jpg",
            "sizes": {
              "large": {
                "h": "2048",
                "resize": "fit",
                "w": "1658"
              },
              "medium": {
                "h": "1200",
                "resize": "fit",
                "w": "972"
              },
              "small": {
                "h": "680",
                "resize": "fit",
                "w": "551"
              },
              "thumb": {
                "h": "150",
                "resize": "crop",
                "w": "150"
              }
            },
            "type": "photo",
            "url": "https://t.co/PC9X7F1C9J"
          }
        ]
      },
      "extended_entities": {
        "media": [
          {
            "display_url": "pic.twitter.com/PC9X7F1C9J",
            "expanded_url": "https://twitter.com/SFOMuseum/status/703403020948783105/photo/1",
            "id_str": "703403019426095104",
            "indices": [
              "115", 
              "138"
            ],
            "media_url": "http://pbs.twimg.com/media/CcL9UcLUYAADKkb.jpg",
            "media_url_https": "https://pbs.twimg.com/media/CcL9UcLUYAADKkb.jpg",
            "sizes": {
              "large": {
                "h": "2048",
                "resize": "fit",
                "w": "1658"
              },
              "medium": {
                "h": "1200",
                "resize": "fit",
                "w": "972"
              },
              "small": {
                "h": "680",
                "resize": "fit",
                "w": "551"
              },
              "thumb": {
                "h": "150",
                "resize": "crop",
                "w": "150"
              }
            },
            "type": "photo",
            "url": "https://t.co/PC9X7F1C9J"
          }
        ]
      },
      "favorite_count": "0",
      "favorited": false,
      "full_text": "In the 1940s Airlite Syracuse China claimed to be the lightest, thinnest China mass produced for commercial usage. https://t.co/PC9X7F1C9J",
      "id_str": "703403020948783105",
      "lang": "en",
      "possibly_sensitive": false,
      "retweet_count": "0",
      "retweeted": false,
      "source": "\u003ca href=\"http://www.hootsuite.com\" rel=\"nofollow\"\u003eHootsuite\u003c/a\u003e",
      "truncated": false
    },
    "wof:name": "Twitter message #703403020948783105",
    "wof:placetype": "custom"
  },
  "geometry": {"coordinates":[-122.386166,37.616356],"type":"Point"}
}
