{
  "type": "Feature",
  "properties": {
    "date:cessation_lower": "2012-02-24",
    "date:cessation_upper": "2012-02-24",
    "date:inception_lower": "2012-02-24",
    "date:inception_upper": "2012-02-24",
    "iso:country": "US",
    "sfomuseum:placetype": "tweet",
    "twitter:tweet": {
      "created": 1330114831,
      "created_at": "Fri Feb 24 20:20:31 +0000 2012",
      "display_text_range": [
        "0",
        "133"
      ],
      "edit_info": {
        "initial": {
          "editTweetIds": [
            "173140268650991617"
          ],
          "editableUntil": "2012-02-24T20:50:31.494Z",
          "editsRemaining": "5",
          "isEditEligible": true
        }
      },
      "entities": {
        "urls": [
          {
            "display_url": "yfrog.com/h23r4rtj",
            "expanded_url": "http://yfrog.com/h23r4rtj",
            "indices": [
              "113",
              "133"
            ],
            "url": "http://t.co/p9UyGOPA"
          }
        ]
      },
      "favorite_count": "0",
      "favorited": false,
      "full_text": "Moto Morini's 50cc Corsarino's 4-stroke engine set it apart from 2-stroke \"screamers\" that lead the 50cc market. http://t.co/p9UyGOPA",
      "id_str": "173140268650991617",
      "lang": "en",
      "possibly_sensitive": false,
      "retweet_count": "2",
      "retweeted": false,
      "source": "\u003ca href=\"https://about.twitter.com/products/tweetdeck\" rel=\"nofollow\"\u003eTweetDeck\u003c/a\u003e",
      "truncated": false
    },
    "wof:name": "Moto Morini's 50cc Corsarino's 4-stroke engine set it apart from 2-stroke \"screamers\" that lead the 50cc market. http://t.co/p9UyGOPA",
    "wof:placetype": "custom"
  },
  "geometry": {"coordinates":[-122.386166,37.616356],"type":"Point"}
}
