{
  "type": "Feature",
  "properties": {
    "date:cessation_lower": "2019-10-02",
    "date:cessation_upper": "2019-10-02",
    "date:inception_lower": "2019-10-02",
    "date:inception_upper": "2019-10-02",
    "iso:country": "US",
    "sfomuseum:placetype": "tweet",
    "twitter:hashtags": [
      "SanFrancisco"
    ],
    "twitter:tweet": {
      "created": 1570036376,
      "created_at": "Wed Oct 02 17:12:56 +0000 2019",
      "display_text_range": [
        "0",
        "140"
      ],
      "edit_info": {
        "initial": {
          "editTweetIds": [
            "1179444165635035136"
          ],
          "editableUntil": "2019-10-02T18:12:56.757Z",
          "editsRemaining": "5",
          "isEditEligible": true
        }
      },
      "entities": {
        "hashtags": [
          {
            "indices": [
              "101",
              "114"
            ],
            "text": "SanFrancisco"
          }
        ],
        "user_mentions": [
          {
            "id_str": "16408759",
            "indices": [
              "3",
              "10"
            ],
            "name": "San Francisco International Airport (SFO) ✈️",
            "screen_name": "flySFO"
          },
          {
            "id_str": "101743223",
            "indices": [
              "33",
              "42"
            ],
            "name": "Alitalia",
            "screen_name": "Alitalia"
          }
        ]
      },
      "favorite_count": "0",
      "favorited": false,
      "full_text": "RT @flySFO: Welcome Alitalia! RT @Alitalia: We’re excited to announce the launch of our new route to #SanFrancisco 🎉🥳\nCan’t wait to land @f…",
      "id_str": "1179444165635035136",
      "lang": "en",
      "retweet_count": "0",
      "retweeted": false,
      "source": "\u003ca href=\"https://mobile.twitter.com\" rel=\"nofollow\"\u003eTwitter Web App\u003c/a\u003e",
      "truncated": false
    },
    "twitter:user_mentions": [
      "flySFO",
      "Alitalia"
    ],
    "wof:name": "RT @flySFO: Welcome Alitalia! RT @Alitalia: We’re excited to announce the launch of our new route to #SanFrancisco 🎉🥳\nCan’t wait to land @f…",
    "wof:placetype": "custom",
    "wof:placetype_alt": [
      "tweet"
    ]
  },
  "geometry": {"coordinates":[-122.386166,37.616356],"type":"Point"}
}
