{
  "type": "Feature",
  "properties": {
    "sfomuseum:placetype": "tweet",
    "twitter:tweet": {
      "created": 1495411510,
      "created_at": "Mon May 22 00:05:10 +0000 2017",
      "display_text_range": [
        "0", 
        "161"
      ],
      "entities": {
        "hashtags": [
          {
            "indices": [
              "0", 
              "10"
            ],
            "text": "Onthisday"
          }, 
          {
            "indices": [
              "28", 
              "38"
            ],
            "text": "Lindbergh"
          }
        ],
        "media": [
          {
            "display_url": "pic.twitter.com/mbxEWEYoyd",
            "expanded_url": "https://twitter.com/SFOMuseum/status/866444788882690048/photo/1",
            "id_str": "866444785690714112",
            "indices": [
              "138", 
              "161"
            ],
            "media_url": "http://pbs.twimg.com/media/DAY68SSVoAAOWMh.jpg",
            "media_url_https": "https://pbs.twimg.com/media/DAY68SSVoAAOWMh.jpg",
            "sizes": {
              "large": {
                "h": "2000",
                "resize": "fit",
                "w": "1544"
              },
              "medium": {
                "h": "1200",
                "resize": "fit",
                "w": "926"
              },
              "small": {
                "h": "680",
                "resize": "fit",
                "w": "525"
              },
              "thumb": {
                "h": "150",
                "resize": "crop",
                "w": "150"
              }
            },
            "type": "photo",
            "url": "https://t.co/mbxEWEYoyd"
          }
        ]
      },
      "extended_entities": {
        "media": [
          {
            "display_url": "pic.twitter.com/mbxEWEYoyd",
            "expanded_url": "https://twitter.com/SFOMuseum/status/866444788882690048/photo/1",
            "id_str": "866444785690714112",
            "indices": [
              "138", 
              "161"
            ],
            "media_url": "http://pbs.twimg.com/media/DAY68SSVoAAOWMh.jpg",
            "media_url_https": "https://pbs.twimg.com/media/DAY68SSVoAAOWMh.jpg",
            "sizes": {
              "large": {
                "h": "2000",
                "resize": "fit",
                "w": "1544"
              },
              "medium": {
                "h": "1200",
                "resize": "fit",
                "w": "926"
              },
              "small": {
                "h": "680",
                "resize": "fit",
                "w": "525"
              },
              "thumb": {
                "h": "150",
                "resize": "crop",
                "w": "150"
              }
            },
            "type": "photo",
            "url": "https://t.co/mbxEWEYoyd"
          }
        ]
      },
      "favorite_count": "14",
      "favorited": false,
      "full_text": "#Onthisday in 1927, Charles #Lindbergh landed in Paris completing the first successful solo crossing of the Atlantic Ocean from New York. https://t.co/mbxEWEYoyd",
      "id_str": "866444788882690048",
      "lang": "en",
      "possibly_sensitive": false,
      "retweet_count": "8",
      "retweeted": false,
      "source": "\u003ca href=\"http://www.hootsuite.com\" rel=\"nofollow\"\u003eHootsuite\u003c/a\u003e",
      "truncated": false
    },
    "wof:name": "Twitter message #866444788882690048",
    "wof:placetype": "custom"
  },
  "geometry": {"coordinates":[-122.386166,37.616356],"type":"Point"}
}
