{
  "type": "Feature",
  "properties": {
    "sfomuseum:placetype": "tweet",
    "twitter:tweet": {
      "created": 1445570427,
      "created_at": "Fri Oct 23 03:20:27 +0000 2015",
      "display_text_range": [
        "0", 
        "115"
      ],
      "entities": {
        "hashtags": [
          {
            "indices": [
              "73", 
              "91"
            ],
            "text": "ThrowbackThursday"
          }
        ],
        "urls": [
          {
            "display_url": "ow.ly/TB8Qo",
            "expanded_url": "http://ow.ly/TB8Qo",
            "indices": [
              "92", 
              "115"
            ],
            "url": "https://t.co/wuGTPPYRZk"
          }
        ]
      },
      "favorite_count": "0",
      "favorited": false,
      "full_text": "Wow! Check out this vintage footage of San Francisco Airport circa 1937! #ThrowbackThursday https://t.co/wuGTPPYRZk",
      "id_str": "657396138513932288",
      "lang": "en",
      "possibly_sensitive": false,
      "retweet_count": "0",
      "retweeted": false,
      "source": "\u003ca href=\"http://www.hootsuite.com\" rel=\"nofollow\"\u003eHootsuite\u003c/a\u003e",
      "truncated": false
    },
    "wof:name": "Twitter message #657396138513932288",
    "wof:placetype": "custom"
  },
  "geometry": {"coordinates":[-122.386166,37.616356],"type":"Point"}
}
