{
  "type": "Feature",
  "properties": {
    "date:cessation_lower": "2024-10-17",
    "date:cessation_upper": "2024-10-17",
    "date:inception_lower": "2024-10-17",
    "date:inception_upper": "2024-10-17",
    "sfomuseum:placetype": "tweet",
    "twitter:hashtags": [
      "HaitianMetal"
    ],
    "twitter:tweet": {
      "created": 1729123669,
      "created_at": "Thu Oct 17 00:07:49 +0000 2024",
      "display_text_range": [
        "0",
        "196"
      ],
      "edit_info": {
        "initial": {
          "editTweetIds": [
            "1846704633974227312"
          ],
          "editableUntil": "2024-10-17T01:07:49.000Z",
          "editsRemaining": "5",
          "isEditEligible": false
        }
      },
      "entities": {
        "hashtags": [
          {
            "indices": [
              "183",
              "196"
            ],
            "text": "HaitianMetal"
          }
        ],
        "urls": [
          {
            "display_url": "bit.ly/HaitianMetal",
            "expanded_url": "https://bit.ly/HaitianMetal",
            "indices": [
              "158",
              "181"
            ],
            "url": "https://t.co/Y9uksywLGy"
          }
        ]
      },
      "favorite_count": "0",
      "favorited": false,
      "full_text": "“The Enduring Spirit of Haitian Metal Sculpture” is on display, pre-security, in the Mayor Edwin M. Lee International Terminal Departures Hall and online at: https://t.co/Y9uksywLGy\n\n#HaitianMetal",
      "id_str": "1846704633974227312",
      "in_reply_to_screen_name": "SFOMuseum",
      "in_reply_to_status_id": "1846704630950252688",
      "in_reply_to_status_id_str": "1846704630950252688",
      "in_reply_to_user_id": "116329337",
      "in_reply_to_user_id_str": "116329337",
      "lang": "en",
      "possibly_sensitive": false,
      "retweet_count": "0",
      "retweeted": false,
      "source": "\u003ca href=\"https://mobile.twitter.com\" rel=\"nofollow\"\u003eTwitter Web App\u003c/a\u003e",
      "truncated": false
    },
    "wof:name": "“The Enduring Spirit of Haitian Metal Sculpture” is on display, pre-security, in the Mayor Edwin M. Lee International Terminal Departures Hall and online at: https://t.co/Y9uksywLGy\n\n#HaitianMetal",
    "wof:placetype": "custom"
  },
  "geometry": {"coordinates":[-122.386166,37.616356],"type":"Point"}
}
