{
  "type": "Feature",
  "properties": {
    "sfomuseum:placetype": "tweet",
    "twitter:tweet": {
      "created": 1325269321,
      "created_at": "Fri Dec 30 18:22:01 +0000 2011",
      "display_text_range": [
        "0", 
        "129"
      ],
      "entities": {
        "urls": [
          {
            "display_url": "yfrog.com/oe5lxbwj",
            "expanded_url": "http://yfrog.com/oe5lxbwj",
            "indices": [
              "109", 
              "129"
            ],
            "url": "http://t.co/hXoupwBm"
          }
        ]
      },
      "favorite_count": "0",
      "favorited": false,
      "full_text": "Happy (Jack) Lord's day! The man who would be forever known as Steve McGarrett was born on this day in 1920. http://t.co/hXoupwBm",
      "id_str": "152816727825186816",
      "lang": "en",
      "possibly_sensitive": false,
      "retweet_count": "0",
      "retweeted": false,
      "source": "\u003ca href=\"https://about.twitter.com/products/tweetdeck\" rel=\"nofollow\"\u003eTweetDeck\u003c/a\u003e",
      "truncated": false
    },
    "wof:name": "Twitter message #152816727825186816",
    "wof:placetype": "custom"
  },
  "geometry": {"coordinates":[-122.386166,37.616356],"type":"Point"}
}
