{
  "type": "Feature",
  "properties": {
    "date:cessation_lower": "2016-06-06",
    "date:cessation_upper": "2016-06-06",
    "date:inception_lower": "2016-06-06",
    "date:inception_upper": "2016-06-06",
    "iso:country": "US",
    "sfomuseum:placetype": "tweet",
    "twitter:tweet": {
      "created": 1465248356,
      "created_at": "Mon Jun 06 21:25:56 +0000 2016",
      "display_text_range": [
        "0",
        "139"
      ],
      "entities": {
        "user_mentions": [
          {
            "id_str": "16408759",
            "indices": [
              "3",
              "10"
            ],
            "name": "San Francisco International Airport (SFO) ✈️😷",
            "screen_name": "flySFO"
          },
          {
            "id_str": "399388492",
            "indices": [
              "25",
              "33"
            ],
            "name": "WOW air",
            "screen_name": "wow_air"
          }
        ]
      },
      "favorite_count": "0",
      "favorited": false,
      "full_text": "RT @flySFO: Did you know @wow_air is starting nonstop service to Reykjavik, Iceland, on June 9?!  This flight operates 5 days-a-week on an…",
      "id_str": "739931352234090496",
      "lang": "en",
      "retweet_count": "0",
      "retweeted": false,
      "source": "\u003ca href=\"http://www.hootsuite.com\" rel=\"nofollow\"\u003eHootsuite\u003c/a\u003e",
      "truncated": false
    },
    "wof:name": "RT @flySFO: Did you know @wow_air is starting nonstop service to Reykjavik, Iceland, on June 9?!  This flight operates 5 days-a-week on an…",
    "wof:placetype": "custom"
  },
  "geometry": {"coordinates":[-122.386166,37.616356],"type":"Point"}
}
