{
  "type": "Feature",
  "properties": {
    "sfomuseum:placetype": "tweet",
    "twitter:tweet": {
      "created": 1432079121,
      "created_at": "Tue May 19 23:45:21 +0000 2015",
      "display_text_range": [
        "0", 
        "123"
      ],
      "entities": {
        "urls": [
          {
            "display_url": "instagram.com/p/24eY73Rk7h/",
            "expanded_url": "https://instagram.com/p/24eY73Rk7h/",
            "indices": [
              "100", 
              "123"
            ],
            "url": "https://t.co/kX5yyOiXP4"
          }
        ]
      },
      "favorite_count": "1",
      "favorited": false,
      "full_text": "Scarabs are one of the most popular and easily recognizable motifs from ancient Egypt and as such,… https://t.co/kX5yyOiXP4",
      "id_str": "600809497058222080",
      "lang": "en",
      "possibly_sensitive": false,
      "retweet_count": "1",
      "retweeted": false,
      "source": "\u003ca href=\"http://instagram.com\" rel=\"nofollow\"\u003eInstagram\u003c/a\u003e",
      "truncated": false
    },
    "wof:name": "Twitter message #600809497058222080",
    "wof:placetype": "custom"
  },
  "geometry": {"coordinates":[-122.386166,37.616356],"type":"Point"}
}
