{
  "type": "Feature",
  "properties": {
    "date:cessation_lower": "2020-12-21",
    "date:cessation_upper": "2020-12-21",
    "date:inception_lower": "2020-12-21",
    "date:inception_upper": "2020-12-21",
    "sfomuseum:placetype": "tweet",
    "twitter:tweet": {
      "created": 1608574648,
      "created_at": "Mon Dec 21 18:17:28 +0000 2020",
      "display_text_range": [
        "0",
        "221"
      ],
      "entities": {
        "user_mentions": [
          {
            "id_str": "1032837920602767360",
            "indices": [
              "0",
              "13"
            ],
            "name": "Adventure Animal",
            "screen_name": "AdventureNML"
          }
        ]
      },
      "favorite_count": "3",
      "favorited": false,
      "full_text": "@AdventureNML Wow, what an interesting inquiry. This is in Downtown San Francisco? Do you mind emailing us at curator@flysfo.com and I can forward it to our aviation curators who will have more insight? Thank you so much!",
      "id_str": "1341085393127571459",
      "in_reply_to_screen_name": "AdventureNML",
      "in_reply_to_status_id": "1340573445831204865",
      "in_reply_to_status_id_str": "1340573445831204865",
      "in_reply_to_user_id": "1032837920602767360",
      "in_reply_to_user_id_str": "1032837920602767360",
      "lang": "en",
      "retweet_count": "0",
      "retweeted": false,
      "source": "\u003ca href=\"https://mobile.twitter.com\" rel=\"nofollow\"\u003eTwitter Web App\u003c/a\u003e",
      "truncated": false
    },
    "wof:name": "@AdventureNML Wow, what an interesting inquiry. This is in Downtown San Francisco? Do you mind emailing us at curator@flysfo.com and I can forward it to our aviation curators who will have more insight? Thank you so much!",
    "wof:placetype": "custom"
  },
  "geometry": {"coordinates":[-122.386166,37.616356],"type":"Point"}
}
