{
  "type": "Feature",
  "properties": {
    "date:cessation_lower": "2021-12-07",
    "date:cessation_upper": "2021-12-07",
    "date:inception_lower": "2021-12-07",
    "date:inception_upper": "2021-12-07",
    "sfomuseum:placetype": "tweet",
    "twitter:tweet": {
      "created": 1638902238,
      "created_at": "Tue Dec 07 18:37:18 +0000 2021",
      "display_text_range": [
        "0",
        "140"
      ],
      "edit_info": {
        "initial": {
          "editTweetIds": [
            "1468288523836936194"
          ],
          "editableUntil": "2021-12-07T19:07:18.221Z",
          "editsRemaining": "5",
          "isEditEligible": true
        }
      },
      "entities": {
        "hashtags": [
          {
            "indices": [
              "18",
              "28"
            ],
            "text": "OnThisDay"
          }
        ],
        "user_mentions": [
          {
            "id_str": "95746689",
            "indices": [
              "3",
              "16"
            ],
            "name": "panamhistory",
            "screen_name": "panamhistory"
          }
        ]
      },
      "favorite_count": "0",
      "favorited": false,
      "full_text": "RT @panamhistory: #OnThisDay, December 7, 1941 when America went to war: Pan Am Capt. Bob Ford's astounding B-314 flight around the globe i…",
      "id_str": "1468288523836936194",
      "lang": "en",
      "retweet_count": "0",
      "retweeted": false,
      "source": "\u003ca href=\"https://mobile.twitter.com\" rel=\"nofollow\"\u003eTwitter Web App\u003c/a\u003e",
      "truncated": false
    },
    "wof:name": "RT @panamhistory: #OnThisDay, December 7, 1941 when America went to war: Pan Am Capt. Bob Ford's astounding B-314 flight around the globe i…",
    "wof:placetype": "custom"
  },
  "geometry": {"coordinates":[-122.386166,37.616356],"type":"Point"}
}
