{
  "type": "Feature",
  "properties": {
    "sfomuseum:placetype": "tweet",
    "twitter:tweet": {
      "created": 1517886605,
      "created_at": "Tue Feb 06 03:10:05 +0000 2018",
      "display_text_range": [
        "0", 
        "202"
      ],
      "entities": {
        "hashtags": [
          {
            "indices": [
              "162", 
              "178"
            ],
            "text": "AmericanFolkArt"
          }
        ],
        "media": [
          {
            "display_url": "pic.twitter.com/d8R8kmqYC2",
            "expanded_url": "https://twitter.com/SFOMuseum/status/960712169670234112/photo/1",
            "id_str": "960712166683955200",
            "indices": [
              "179", 
              "202"
            ],
            "media_url": "http://pbs.twimg.com/media/DVUioCKX0AAQ7VQ.jpg",
            "media_url_https": "https://pbs.twimg.com/media/DVUioCKX0AAQ7VQ.jpg",
            "sizes": {
              "large": {
                "h": "1462",
                "resize": "fit",
                "w": "2000"
              },
              "medium": {
                "h": "877",
                "resize": "fit",
                "w": "1200"
              },
              "small": {
                "h": "497",
                "resize": "fit",
                "w": "680"
              },
              "thumb": {
                "h": "150",
                "resize": "crop",
                "w": "150"
              }
            },
            "type": "photo",
            "url": "https://t.co/d8R8kmqYC2"
          }
        ]
      },
      "extended_entities": {
        "media": [
          {
            "display_url": "pic.twitter.com/d8R8kmqYC2",
            "expanded_url": "https://twitter.com/SFOMuseum/status/960712169670234112/photo/1",
            "id_str": "960712166683955200",
            "indices": [
              "179", 
              "202"
            ],
            "media_url": "http://pbs.twimg.com/media/DVUioCKX0AAQ7VQ.jpg",
            "media_url_https": "https://pbs.twimg.com/media/DVUioCKX0AAQ7VQ.jpg",
            "sizes": {
              "large": {
                "h": "1462",
                "resize": "fit",
                "w": "2000"
              },
              "medium": {
                "h": "877",
                "resize": "fit",
                "w": "1200"
              },
              "small": {
                "h": "497",
                "resize": "fit",
                "w": "680"
              },
              "thumb": {
                "h": "150",
                "resize": "crop",
                "w": "150"
              }
            },
            "type": "photo",
            "url": "https://t.co/d8R8kmqYC2"
          }
        ]
      },
      "favorite_count": "2",
      "favorited": false,
      "full_text": "Members also decorated lodges with emblematic pieces, such as plaques and mirrors. The all-seeing eye is a common symbol to the Independent Order of Odd Fellows. #AmericanFolkArt https://t.co/d8R8kmqYC2",
      "id_str": "960712169670234112",
      "lang": "en",
      "possibly_sensitive": false,
      "retweet_count": "0",
      "retweeted": false,
      "source": "\u003ca href=\"http://www.hootsuite.com\" rel=\"nofollow\"\u003eHootsuite\u003c/a\u003e",
      "truncated": false
    },
    "wof:name": "Twitter message #960712169670234112",
    "wof:placetype": "custom"
  },
  "geometry": {"coordinates":[-122.386166,37.616356],"type":"Point"}
}
