{
  "type": "Feature",
  "properties": {
    "sfomuseum:placetype": "tweet",
    "twitter:tweet": {
      "created": 1493582452,
      "created_at": "Sun Apr 30 20:00:52 +0000 2017",
      "display_text_range": [
        "0", 
        "149"
      ],
      "entities": {
        "hashtags": [
          {
            "indices": [
              "45", 
              "55"
            ],
            "text": "onthisday"
          }, 
          {
            "indices": [
              "101", 
              "108"
            ],
            "text": "avgeek"
          }, 
          {
            "indices": [
              "109", 
              "125"
            ],
            "text": "aviationhistory"
          }
        ],
        "media": [
          {
            "display_url": "pic.twitter.com/uW8BSsS17r",
            "expanded_url": "https://twitter.com/SFOMuseum/status/858773165882966017/photo/1",
            "id_str": "858773161399246848",
            "indices": [
              "126", 
              "149"
            ],
            "media_url": "http://pbs.twimg.com/media/C-r5o-vXYAAA7u8.jpg",
            "media_url_https": "https://pbs.twimg.com/media/C-r5o-vXYAAA7u8.jpg",
            "sizes": {
              "large": {
                "h": "1343",
                "resize": "fit",
                "w": "2000"
              },
              "medium": {
                "h": "806",
                "resize": "fit",
                "w": "1200"
              },
              "small": {
                "h": "457",
                "resize": "fit",
                "w": "680"
              },
              "thumb": {
                "h": "150",
                "resize": "crop",
                "w": "150"
              }
            },
            "type": "photo",
            "url": "https://t.co/uW8BSsS17r"
          }
        ]
      },
      "extended_entities": {
        "media": [
          {
            "display_url": "pic.twitter.com/uW8BSsS17r",
            "expanded_url": "https://twitter.com/SFOMuseum/status/858773165882966017/photo/1",
            "id_str": "858773161399246848",
            "indices": [
              "126", 
              "149"
            ],
            "media_url": "http://pbs.twimg.com/media/C-r5o-vXYAAA7u8.jpg",
            "media_url_https": "https://pbs.twimg.com/media/C-r5o-vXYAAA7u8.jpg",
            "sizes": {
              "large": {
                "h": "1343",
                "resize": "fit",
                "w": "2000"
              },
              "medium": {
                "h": "806",
                "resize": "fit",
                "w": "1200"
              },
              "small": {
                "h": "457",
                "resize": "fit",
                "w": "680"
              },
              "thumb": {
                "h": "150",
                "resize": "crop",
                "w": "150"
              }
            },
            "type": "photo",
            "url": "https://t.co/uW8BSsS17r"
          }
        ]
      },
      "favorite_count": "12",
      "favorited": false,
      "full_text": "People Express Airlines commenced operations #onthisday in 1981. Did you ever fly on People Express? #avgeek #aviationhistory https://t.co/uW8BSsS17r",
      "id_str": "858773165882966017",
      "lang": "en",
      "possibly_sensitive": false,
      "retweet_count": "9",
      "retweeted": false,
      "source": "\u003ca href=\"http://www.hootsuite.com\" rel=\"nofollow\"\u003eHootsuite\u003c/a\u003e",
      "truncated": false
    },
    "wof:name": "Twitter message #858773165882966017",
    "wof:placetype": "custom"
  },
  "geometry": {"coordinates":[-122.386166,37.616356],"type":"Point"}
}
