{
  "type": "Feature",
  "properties": {
    "sfomuseum:placetype": "tweet",
    "twitter:tweet": {
      "created": 1375205568,
      "created_at": "Tue Jul 30 17:32:48 +0000 2013",
      "display_text_range": [
        "0", 
        "138"
      ],
      "entities": {
        "hashtags": [
          {
            "indices": [
              "131", 
              "138"
            ],
            "text": "avgeek"
          }
        ],
        "urls": [
          {
            "display_url": "ow.ly/i/2Kk37",
            "expanded_url": "http://ow.ly/i/2Kk37",
            "indices": [
              "108", 
              "130"
            ],
            "url": "http://t.co/SqjbIm7RXJ"
          }
        ]
      },
      "favorite_count": "0",
      "favorited": false,
      "full_text": "A 1937 brochure from ENTA, Costa Rica's 1st natl airline, include an image of the country's famous oxcarts: http://t.co/SqjbIm7RXJ #avgeek",
      "id_str": "362264528026742785",
      "lang": "en",
      "possibly_sensitive": false,
      "retweet_count": "0",
      "retweeted": false,
      "source": "\u003ca href=\"http://www.hootsuite.com\" rel=\"nofollow\"\u003eHootsuite\u003c/a\u003e",
      "truncated": false
    },
    "wof:name": "Twitter message #362264528026742785",
    "wof:placetype": "custom"
  },
  "geometry": {"coordinates":[-122.386166,37.616356],"type":"Point"}
}
