{
  "type": "Feature",
  "properties": {
    "sfomuseum:placetype": "tweet",
    "twitter:tweet": {
      "created": 1471450633,
      "created_at": "Wed Aug 17 16:17:13 +0000 2016",
      "display_text_range": [
        "0", 
        "140"
      ],
      "entities": {
        "hashtags": [
          {
            "indices": [
              "33", 
              "46"
            ],
            "text": "Transferware"
          }, 
          {
            "indices": [
              "86", 
              "93"
            ],
            "text": "LoveIt"
          }
        ],
        "urls": [
          {
            "display_url": "bit.ly/ATTW081716",
            "expanded_url": "http://bit.ly/ATTW081716",
            "indices": [
              "95", 
              "118"
            ],
            "url": "https://t.co/7QcXdhxboO"
          }
        ],
        "user_mentions": [
          {
            "id_str": "21404656",
            "indices": [
              "3", 
              "17"
            ],
            "name": "Antique Trader",
            "screen_name": "AntiqueTrader"
          }, 
          {
            "id_str": "16408759",
            "indices": [
              "58", 
              "65"
            ],
            "name": "San Francisco International Airport (SFO) ✈️",
            "screen_name": "flySFO"
          }
        ]
      },
      "favorite_count": "0",
      "favorited": false,
      "full_text": "RT @AntiqueTrader: Totally cool! #Transferware exhibit at @flySFO Museum and online — #LoveIt. https://t.co/7QcXdhxboO https://t.co/YOpbWJV…",
      "id_str": "765945587099369472",
      "lang": "en",
      "possibly_sensitive": false,
      "retweet_count": "0",
      "retweeted": false,
      "source": "\u003ca href=\"http://twitter.com\" rel=\"nofollow\"\u003eTwitter Web Client\u003c/a\u003e",
      "truncated": false
    },
    "wof:name": "Twitter message #765945587099369472",
    "wof:placetype": "custom"
  },
  "geometry": {"coordinates":[-122.386166,37.616356],"type":"Point"}
}
