{
  "type": "Feature",
  "properties": {
    "sfomuseum:placetype": "tweet",
    "twitter:tweet": {
      "created": 1446607850,
      "created_at": "Wed Nov 04 03:30:50 +0000 2015",
      "display_text_range": [
        "0", 
        "117"
      ],
      "entities": {
        "hashtags": [
          {
            "indices": [
              "79", 
              "93"
            ],
            "text": "TravelTuesday"
          }
        ],
        "media": [
          {
            "display_url": "pic.twitter.com/cNS4DQW99X",
            "expanded_url": "https://twitter.com/SFOMuseum/status/661747402399948800/photo/1",
            "id_str": "661747401724563456",
            "indices": [
              "94", 
              "117"
            ],
            "media_url": "http://pbs.twimg.com/media/CS7_wXrUkAAqs15.jpg",
            "media_url_https": "https://pbs.twimg.com/media/CS7_wXrUkAAqs15.jpg",
            "sizes": {
              "large": {
                "h": "1039",
                "resize": "fit",
                "w": "2048"
              },
              "medium": {
                "h": "609",
                "resize": "fit",
                "w": "1200"
              },
              "small": {
                "h": "345",
                "resize": "fit",
                "w": "680"
              },
              "thumb": {
                "h": "150",
                "resize": "crop",
                "w": "150"
              }
            },
            "type": "photo",
            "url": "https://t.co/cNS4DQW99X"
          }
        ]
      },
      "extended_entities": {
        "media": [
          {
            "display_url": "pic.twitter.com/cNS4DQW99X",
            "expanded_url": "https://twitter.com/SFOMuseum/status/661747402399948800/photo/1",
            "id_str": "661747401724563456",
            "indices": [
              "94", 
              "117"
            ],
            "media_url": "http://pbs.twimg.com/media/CS7_wXrUkAAqs15.jpg",
            "media_url_https": "https://pbs.twimg.com/media/CS7_wXrUkAAqs15.jpg",
            "sizes": {
              "large": {
                "h": "1039",
                "resize": "fit",
                "w": "2048"
              },
              "medium": {
                "h": "609",
                "resize": "fit",
                "w": "1200"
              },
              "small": {
                "h": "345",
                "resize": "fit",
                "w": "680"
              },
              "thumb": {
                "h": "150",
                "resize": "crop",
                "w": "150"
              }
            },
            "type": "photo",
            "url": "https://t.co/cNS4DQW99X"
          }
        ]
      },
      "favorite_count": "0",
      "favorited": false,
      "full_text": "Korean Air’s first flight from Seoul to San Francisco was on October 29, 1994. #TravelTuesday https://t.co/cNS4DQW99X",
      "id_str": "661747402399948800",
      "lang": "en",
      "possibly_sensitive": false,
      "retweet_count": "0",
      "retweeted": false,
      "source": "\u003ca href=\"http://www.hootsuite.com\" rel=\"nofollow\"\u003eHootsuite\u003c/a\u003e",
      "truncated": false
    },
    "wof:name": "Twitter message #661747402399948800",
    "wof:placetype": "custom"
  },
  "geometry": {"coordinates":[-122.386166,37.616356],"type":"Point"}
}
