{
  "type": "Feature",
  "properties": {
    "sfomuseum:placetype": "tweet",
    "twitter:tweet": {
      "created": 1444256726,
      "created_at": "Wed Oct 07 22:25:26 +0000 2015",
      "display_text_range": [
        "0", 
        "139"
      ],
      "entities": {
        "media": [
          {
            "display_url": "pic.twitter.com/ItY3HIUWVG",
            "expanded_url": "https://twitter.com/SFOMuseum/status/651886076009820160/photo/1",
            "id_str": "651886075384868865",
            "indices": [
              "117", 
              "139"
            ],
            "media_url": "http://pbs.twimg.com/media/CQv27oVWsAE1Phd.jpg",
            "media_url_https": "https://pbs.twimg.com/media/CQv27oVWsAE1Phd.jpg",
            "sizes": {
              "large": {
                "h": "480",
                "resize": "fit",
                "w": "640"
              },
              "medium": {
                "h": "480",
                "resize": "fit",
                "w": "640"
              },
              "small": {
                "h": "480",
                "resize": "fit",
                "w": "640"
              },
              "thumb": {
                "h": "150",
                "resize": "crop",
                "w": "150"
              }
            },
            "type": "photo",
            "url": "http://t.co/ItY3HIUWVG"
          }
        ]
      },
      "extended_entities": {
        "media": [
          {
            "display_url": "pic.twitter.com/ItY3HIUWVG",
            "expanded_url": "https://twitter.com/SFOMuseum/status/651886076009820160/photo/1",
            "id_str": "651886075384868865",
            "indices": [
              "117", 
              "139"
            ],
            "media_url": "http://pbs.twimg.com/media/CQv27oVWsAE1Phd.jpg",
            "media_url_https": "https://pbs.twimg.com/media/CQv27oVWsAE1Phd.jpg",
            "sizes": {
              "large": {
                "h": "480",
                "resize": "fit",
                "w": "640"
              },
              "medium": {
                "h": "480",
                "resize": "fit",
                "w": "640"
              },
              "small": {
                "h": "480",
                "resize": "fit",
                "w": "640"
              },
              "thumb": {
                "h": "150",
                "resize": "crop",
                "w": "150"
              }
            },
            "type": "photo",
            "url": "http://t.co/ItY3HIUWVG"
          }
        ]
      },
      "favorite_count": "2",
      "favorited": false,
      "full_text": "In Riven/River, artist Jim Melchert breaks and reassembles tiles to create a complex pattern of cracks and fissures. http://t.co/ItY3HIUWVG",
      "id_str": "651886076009820160",
      "lang": "en",
      "possibly_sensitive": false,
      "retweet_count": "2",
      "retweeted": false,
      "source": "\u003ca href=\"http://www.hootsuite.com\" rel=\"nofollow\"\u003eHootsuite\u003c/a\u003e",
      "truncated": false
    },
    "wof:name": "Twitter message #651886076009820160",
    "wof:placetype": "custom"
  },
  "geometry": {"coordinates":[-122.386166,37.616356],"type":"Point"}
}
