{
  "type": "Feature",
  "properties": {
    "sfomuseum:placetype": "tweet",
    "twitter:tweet": {
      "created": 1509412507,
      "created_at": "Tue Oct 31 01:15:07 +0000 2017",
      "display_text_range": [
        "0", 
        "157"
      ],
      "entities": {
        "hashtags": [
          {
            "indices": [
              "0", 
              "10"
            ],
            "text": "Onthisday"
          }, 
          {
            "indices": [
              "88", 
              "100"
            ],
            "text": "OrsenWelles"
          }
        ],
        "media": [
          {
            "display_url": "pic.twitter.com/TeIv7fP0yh",
            "expanded_url": "https://twitter.com/SFOMuseum/status/925169228713472000/photo/1",
            "id_str": "925169224854667264",
            "indices": [
              "134", 
              "157"
            ],
            "media_url": "http://pbs.twimg.com/media/DNbcghyWAAAhFdE.jpg",
            "media_url_https": "https://pbs.twimg.com/media/DNbcghyWAAAhFdE.jpg",
            "sizes": {
              "large": {
                "h": "2000",
                "resize": "fit",
                "w": "1555"
              },
              "medium": {
                "h": "1200",
                "resize": "fit",
                "w": "933"
              },
              "small": {
                "h": "680",
                "resize": "fit",
                "w": "529"
              },
              "thumb": {
                "h": "150",
                "resize": "crop",
                "w": "150"
              }
            },
            "type": "photo",
            "url": "https://t.co/TeIv7fP0yh"
          }
        ]
      },
      "extended_entities": {
        "media": [
          {
            "display_url": "pic.twitter.com/TeIv7fP0yh",
            "expanded_url": "https://twitter.com/SFOMuseum/status/925169228713472000/photo/1",
            "id_str": "925169224854667264",
            "indices": [
              "134", 
              "157"
            ],
            "media_url": "http://pbs.twimg.com/media/DNbcghyWAAAhFdE.jpg",
            "media_url_https": "https://pbs.twimg.com/media/DNbcghyWAAAhFdE.jpg",
            "sizes": {
              "large": {
                "h": "2000",
                "resize": "fit",
                "w": "1555"
              },
              "medium": {
                "h": "1200",
                "resize": "fit",
                "w": "933"
              },
              "small": {
                "h": "680",
                "resize": "fit",
                "w": "529"
              },
              "thumb": {
                "h": "150",
                "resize": "crop",
                "w": "150"
              }
            },
            "type": "photo",
            "url": "https://t.co/TeIv7fP0yh"
          }
        ]
      },
      "favorite_count": "12",
      "favorited": false,
      "full_text": "#Onthisday in 1938, radio listeners across America were driven into a state of panic by #OrsenWelles' reading of “War of the Worlds.” https://t.co/TeIv7fP0yh",
      "id_str": "925169228713472000",
      "lang": "en",
      "possibly_sensitive": false,
      "retweet_count": "5",
      "retweeted": false,
      "source": "\u003ca href=\"http://www.hootsuite.com\" rel=\"nofollow\"\u003eHootsuite\u003c/a\u003e",
      "truncated": false
    },
    "wof:name": "Twitter message #925169228713472000",
    "wof:placetype": "custom"
  },
  "geometry": {"coordinates":[-122.386166,37.616356],"type":"Point"}
}
