{
  "type": "Feature",
  "properties": {
    "date:cessation_lower": "2023-04-04",
    "date:cessation_upper": "2023-04-04",
    "date:inception_lower": "2023-04-04",
    "date:inception_upper": "2023-04-04",
    "sfomuseum:placetype": "tweet",
    "twitter:tweet": {
      "created": 1680567001,
      "created_at": "Tue Apr 04 00:10:01 +0000 2023",
      "display_text_range": [
        "0",
        "137"
      ],
      "edit_info": {
        "initial": {
          "editTweetIds": [
            "1643043208803520513"
          ],
          "editableUntil": "2023-04-04T00:40:01.000Z",
          "editsRemaining": "5",
          "isEditEligible": false
        }
      },
      "entities": {
        "urls": [
          {
            "display_url": "bit.ly/3MeAztw",
            "expanded_url": "http://bit.ly/3MeAztw",
            "indices": [
              "114",
              "137"
            ],
            "url": "https://t.co/PIs3gzJNGc"
          }
        ]
      },
      "favorite_count": "6",
      "favorited": false,
      "full_text": "📸:\nfloor globe: Pan American World Airways; c. 1939\nTransfer from San Francisco International Airport\n1996.16.04\n\nhttps://t.co/PIs3gzJNGc",
      "id_str": "1643043208803520513",
      "in_reply_to_screen_name": "SFOMuseum",
      "in_reply_to_status_id": "1643043203749404672",
      "in_reply_to_status_id_str": "1643043203749404672",
      "in_reply_to_user_id": "116329337",
      "in_reply_to_user_id_str": "116329337",
      "lang": "en",
      "possibly_sensitive": false,
      "retweet_count": "3",
      "retweeted": false,
      "source": "\u003ca href=\"https://mobile.twitter.com\" rel=\"nofollow\"\u003eTwitter Web App\u003c/a\u003e",
      "truncated": false
    },
    "wof:name": "📸:\nfloor globe: Pan American World Airways; c. 1939\nTransfer from San Francisco International Airport\n1996.16.04\n\nhttps://t.co/PIs3gzJNGc",
    "wof:placetype": "custom",
    "wof:placetype_alt": [
      "tweet"
    ]
  },
  "geometry": {"coordinates":[-122.386166,37.616356],"type":"Point"}
}
