{
  "type": "Feature",
  "properties": {
    "sfomuseum:placetype": "tweet",
    "twitter:tweet": {
      "created": 1349455286,
      "created_at": "Fri Oct 05 16:41:26 +0000 2012",
      "display_text_range": [
        "0", 
        "136"
      ],
      "entities": {
        "urls": [
          {
            "display_url": "bit.ly/vwaZyS",
            "expanded_url": "http://bit.ly/vwaZyS",
            "indices": [
              "116", 
              "136"
            ],
            "url": "http://t.co/oZmdQbfS"
          }
        ],
        "user_mentions": [
          {
            "id_str": "292927415",
            "indices": [
              "0", 
              "15"
            ],
            "name": "Ancient History Encyclopedia",
            "screen_name": "ahencyclopedia"
          }, 
          {
            "id_str": "17844854",
            "indices": [
              "53", 
              "68"
            ],
            "name": "Asian Art Museum",
            "screen_name": "asianartmuseum"
          }
        ]
      },
      "favorite_count": "1",
      "favorited": false,
      "full_text": "@ahencyclopedia Thanks! We're thrilled to be showing @AsianArtMuseum's lovely sculptures. You might like this, too: http://t.co/oZmdQbfS",
      "id_str": "254260015278456832",
      "in_reply_to_screen_name": "ahencyclopedia",
      "in_reply_to_status_id": "254257512604368896",
      "in_reply_to_status_id_str": "254257512604368896",
      "in_reply_to_user_id": "292927415",
      "in_reply_to_user_id_str": "292927415",
      "lang": "en",
      "possibly_sensitive": false,
      "retweet_count": "0",
      "retweeted": false,
      "source": "\u003ca href=\"https://about.twitter.com/products/tweetdeck\" rel=\"nofollow\"\u003eTweetDeck\u003c/a\u003e",
      "truncated": false
    },
    "wof:name": "Twitter message #254260015278456832",
    "wof:placetype": "custom"
  },
  "geometry": {"coordinates":[-122.386166,37.616356],"type":"Point"}
}
