{
  "type": "Feature",
  "properties": {
    "date:cessation_lower": "2011-11-16",
    "date:cessation_upper": "2011-11-16",
    "date:inception_lower": "2011-11-16",
    "date:inception_upper": "2011-11-16",
    "iso:country": "US",
    "sfomuseum:placetype": "tweet",
    "twitter:tweet": {
      "created": 1321469702,
      "created_at": "Wed Nov 16 18:55:02 +0000 2011",
      "display_text_range": [
        "0",
        "137"
      ],
      "edit_info": {
        "initial": {
          "editTweetIds": [
            "136879970659217409"
          ],
          "editableUntil": "2011-11-16T19:25:02.769Z",
          "editsRemaining": "5",
          "isEditEligible": true
        }
      },
      "entities": {
        "urls": [
          {
            "display_url": "bit.ly/hRujQw",
            "expanded_url": "http://bit.ly/hRujQw",
            "indices": [
              "117",
              "137"
            ],
            "url": "http://t.co/BziMdRtD"
          }
        ]
      },
      "favorite_count": "0",
      "favorited": false,
      "full_text": "Italian mfgrs rebuilt decimated facilities post-WW2 \u0026 w/in 5 yrs, 220 companies showed at the Milan Motorcycle Expo: http://t.co/BziMdRtD",
      "id_str": "136879970659217409",
      "lang": "en",
      "possibly_sensitive": false,
      "retweet_count": "0",
      "retweeted": false,
      "source": "\u003ca href=\"https://about.twitter.com/products/tweetdeck\" rel=\"nofollow\"\u003eTweetDeck\u003c/a\u003e",
      "truncated": false
    },
    "wof:name": "Italian mfgrs rebuilt decimated facilities post-WW2 \u0026 w/in 5 yrs, 220 companies showed at the Milan Motorcycle Expo: http://t.co/BziMdRtD",
    "wof:placetype": "custom"
  },
  "geometry": {"coordinates":[-122.386166,37.616356],"type":"Point"}
}
