{
  "type": "Feature",
  "properties": {
    "date:cessation_lower": "2015-03-06",
    "date:cessation_upper": "2015-03-06",
    "date:inception_lower": "2015-03-06",
    "date:inception_upper": "2015-03-06",
    "iso:country": "US",
    "sfomuseum:placetype": "tweet",
    "twitter:tweet": {
      "created": 1425603346,
      "created_at": "Fri Mar 06 00:55:46 +0000 2015",
      "display_text_range": [
        "0",
        "102"
      ],
      "edit_info": {
        "initial": {
          "editTweetIds": [
            "573648129234440193"
          ],
          "editableUntil": "2015-03-06T01:25:46.533Z",
          "editsRemaining": "5",
          "isEditEligible": true
        }
      },
      "entities": {
        "hashtags": [
          {
            "indices": [
              "0",
              "18"
            ],
            "text": "ThrowbackThursday"
          }
        ],
        "urls": [
          {
            "display_url": "ow.ly/JZDq5",
            "expanded_url": "http://ow.ly/JZDq5",
            "indices": [
              "80",
              "102"
            ],
            "url": "http://t.co/HjEZBPac6K"
          }
        ]
      },
      "favorite_count": "1",
      "favorited": false,
      "full_text": "#ThrowbackThursday with an aerial photograph of Sausalito almost 100 years ago: http://t.co/HjEZBPac6K",
      "id_str": "573648129234440193",
      "lang": "en",
      "possibly_sensitive": false,
      "retweet_count": "0",
      "retweeted": false,
      "source": "\u003ca href=\"http://www.hootsuite.com\" rel=\"nofollow\"\u003eHootsuite\u003c/a\u003e",
      "truncated": false
    },
    "wof:name": "#ThrowbackThursday with an aerial photograph of Sausalito almost 100 years ago: http://t.co/HjEZBPac6K",
    "wof:placetype": "custom"
  },
  "geometry": {"coordinates":[-122.386166,37.616356],"type":"Point"}
}
