{
  "type": "Feature",
  "properties": {
    "date:cessation_lower": "2021-09-07",
    "date:cessation_upper": "2021-09-07",
    "date:inception_lower": "2021-09-07",
    "date:inception_upper": "2021-09-07",
    "sfomuseum:placetype": "tweet",
    "twitter:hashtags": [
      "COVID19"
    ],
    "twitter:tweet": {
      "created": 1631055761,
      "created_at": "Tue Sep 07 23:02:41 +0000 2021",
      "display_text_range": [
        "0",
        "140"
      ],
      "edit_info": {
        "initial": {
          "editTweetIds": [
            "1435378014880026635"
          ],
          "editableUntil": "2021-09-08T00:02:41.438Z",
          "editsRemaining": "5",
          "isEditEligible": true
        }
      },
      "entities": {
        "hashtags": [
          {
            "indices": [
              "79",
              "87"
            ],
            "text": "COVID19"
          }
        ],
        "user_mentions": [
          {
            "id_str": "16408759",
            "indices": [
              "3",
              "10"
            ],
            "name": "San Francisco International Airport (SFO) ✈️",
            "screen_name": "flySFO"
          }
        ]
      },
      "favorite_count": "0",
      "favorited": false,
      "full_text": "RT @flySFO: UPDATE! 🥳The SFO Medical Clinic has now administered over 2⃣0⃣0⃣0⃣ #COVID19 vaccine doses! From Azerbaijan to Vietnam, people f…",
      "id_str": "1435378014880026635",
      "lang": "en",
      "retweet_count": "0",
      "retweeted": false,
      "source": "\u003ca href=\"https://mobile.twitter.com\" rel=\"nofollow\"\u003eTwitter Web App\u003c/a\u003e",
      "truncated": false
    },
    "twitter:user_mentions": [
      "flySFO"
    ],
    "wof:name": "RT @flySFO: UPDATE! 🥳The SFO Medical Clinic has now administered over 2⃣0⃣0⃣0⃣ #COVID19 vaccine doses! From Azerbaijan to Vietnam, people f…",
    "wof:placetype": "custom",
    "wof:placetype_alt": [
      "tweet"
    ]
  },
  "geometry": {"coordinates":[-122.386166,37.616356],"type":"Point"}
}
