{
  "type": "Feature",
  "properties": {
    "sfomuseum:placetype": "tweet",
    "twitter:tweet": {
      "created": 1575485076,
      "created_at": "Wed Dec 04 18:44:36 +0000 2019",
      "display_text_range": [
        "0", 
        "291"
      ],
      "entities": {
        "urls": [
          {
            "display_url": "bit.ly/2RihFFl",
            "expanded_url": "http://bit.ly/2RihFFl",
            "indices": [
              "103", 
              "126"
            ],
            "url": "https://t.co/1ETuuNBjeX"
          }, 
          {
            "display_url": "bit.ly/VideoArtsSFO",
            "expanded_url": "http://bit.ly/VideoArtsSFO",
            "indices": [
              "249", 
              "272"
            ],
            "url": "https://t.co/DxTr0Su0zZ"
          }
        ],
        "user_mentions": [
          {
            "id_str": "177475572",
            "indices": [
              "0", 
              "12"
            ],
            "name": "DJ Alex Reyes #StayHomeSaveLives",
            "screen_name": "djalexreyes"
          }
        ]
      },
      "favorite_count": "1",
      "favorited": false,
      "full_text": "@djalexreyes Hi! You can watch the short films featured in our video arts program on our YouTube page (https://t.co/1ETuuNBjeX) or in-person, pre-security, in the Main Hall of the International Terminal. Please see our website for more information. https://t.co/DxTr0Su0zZ Thanks for asking!",
      "id_str": "1202297667478413312",
      "in_reply_to_screen_name": "djalexreyes",
      "in_reply_to_status_id": "1202285712768303104",
      "in_reply_to_status_id_str": "1202285712768303104",
      "in_reply_to_user_id": "177475572",
      "in_reply_to_user_id_str": "177475572",
      "lang": "en",
      "possibly_sensitive": false,
      "retweet_count": "1",
      "retweeted": false,
      "source": "\u003ca href=\"https://mobile.twitter.com\" rel=\"nofollow\"\u003eTwitter Web App\u003c/a\u003e",
      "truncated": false
    },
    "wof:name": "Twitter message #1202297667478413312",
    "wof:placetype": "custom"
  },
  "geometry": {"coordinates":[-122.386166,37.616356],"type":"Point"}
}
