{
  "type": "Feature",
  "properties": {
    "date:cessation_lower": "2020-03-25",
    "date:cessation_upper": "2020-03-25",
    "date:inception_lower": "2020-03-25",
    "date:inception_upper": "2020-03-25",
    "iso:country": "US",
    "sfomuseum:placetype": "tweet",
    "twitter:tweet": {
      "created": 1585105108,
      "created_at": "Wed Mar 25 02:58:28 +0000 2020",
      "display_text_range": [
        "0",
        "178"
      ],
      "edit_info": {
        "initial": {
          "editTweetIds": [
            "1242647008038383616"
          ],
          "editableUntil": "2020-03-25T03:28:28.638Z",
          "editsRemaining": "5",
          "isEditEligible": true
        }
      },
      "entities": {
        "user_mentions": [
          {
            "id_str": "2890591",
            "indices": [
              "0",
              "2"
            ],
            "name": "gene x",
            "screen_name": "x"
          },
          {
            "id_str": "18958334",
            "indices": [
              "90",
              "95"
            ],
            "name": "SF Arts Commission",
            "screen_name": "SFAC"
          }
        ]
      },
      "favorite_count": "1",
      "favorited": false,
      "full_text": "@x Hi! This piece of art is part of the airports permanent art collection, curated by the @SFAC. It will be on permanent display in the Harvey Milk Terminal 1. Thanks for asking!",
      "id_str": "1242647008038383616",
      "in_reply_to_screen_name": "x",
      "in_reply_to_status_id": "1242642391883870209",
      "in_reply_to_status_id_str": "1242642391883870209",
      "in_reply_to_user_id": "2890591",
      "in_reply_to_user_id_str": "2890591",
      "lang": "en",
      "retweet_count": "1",
      "retweeted": false,
      "source": "\u003ca href=\"https://mobile.twitter.com\" rel=\"nofollow\"\u003eTwitter Web App\u003c/a\u003e",
      "truncated": false
    },
    "wof:name": "@x Hi! This piece of art is part of the airports permanent art collection, curated by the @SFAC. It will be on permanent display in the Harvey Milk Terminal 1. Thanks for asking!",
    "wof:placetype": "custom"
  },
  "geometry": {"coordinates":[-122.386166,37.616356],"type":"Point"}
}
