{
  "type": "Feature",
  "properties": {
    "date:cessation_lower": "2022-07-08",
    "date:cessation_upper": "2022-07-08",
    "date:inception_lower": "2022-07-08",
    "date:inception_upper": "2022-07-08",
    "sfomuseum:placetype": "tweet",
    "twitter:tweet": {
      "created": 1657241804,
      "created_at": "Fri Jul 08 00:56:44 +0000 2022",
      "display_text_range": [
        "0",
        "231"
      ],
      "edit_info": {
        "initial": {
          "editTweetIds": [
            "1545210241343582208"
          ],
          "editableUntil": "2022-07-08T01:26:44.000Z",
          "editsRemaining": "5",
          "isEditEligible": false
        }
      },
      "entities": {
      },
      "favorite_count": "0",
      "favorited": false,
      "full_text": "📸 2/3:\npostcard: Douglas DC-3, Ozark Air Lines, Lambert St. Louis Municipal Airport; c. 1950\nGift of Thomas G. Dragges\n2015.166.1179\n\npostcard: Ozark Air Lines, McDonnell Douglas DC-9-34; 1980s\nGift of William Rys, Jr.\n2019.085.089",
      "id_str": "1545210241343582208",
      "in_reply_to_screen_name": "SFOMuseum",
      "in_reply_to_status_id": "1545210239158366208",
      "in_reply_to_status_id_str": "1545210239158366208",
      "in_reply_to_user_id": "116329337",
      "in_reply_to_user_id_str": "116329337",
      "lang": "en",
      "retweet_count": "0",
      "retweeted": false,
      "source": "\u003ca href=\"https://mobile.twitter.com\" rel=\"nofollow\"\u003eTwitter Web App\u003c/a\u003e",
      "truncated": false
    },
    "wof:name": "📸 2/3:\npostcard: Douglas DC-3, Ozark Air Lines, Lambert St. Louis Municipal Airport; c. 1950\nGift of Thomas G. Dragges\n2015.166.1179\n\npostcard: Ozark Air Lines, McDonnell Douglas DC-9-34; 1980s\nGift of William Rys, Jr.\n2019.085.089",
    "wof:placetype": "custom",
    "wof:placetype_alt": [
      "tweet"
    ]
  },
  "geometry": {"coordinates":[-122.386166,37.616356],"type":"Point"}
}
