{
  "type": "Feature",
  "properties": {
    "sfomuseum:placetype": "tweet",
    "twitter:tweet": {
      "created": 1519957205,
      "created_at": "Fri Mar 02 02:20:05 +0000 2018",
      "display_text_range": [
        "0", 
        "252"
      ],
      "entities": {
        "hashtags": [
          {
            "indices": [
              "212", 
              "228"
            ],
            "text": "AmericanFolkArt"
          }
        ],
        "media": [
          {
            "display_url": "pic.twitter.com/0z1BU0ZEfN",
            "expanded_url": "https://twitter.com/SFOMuseum/status/969396896128172032/photo/1",
            "id_str": "969396893628452864",
            "indices": [
              "229", 
              "252"
            ],
            "media_url": "http://pbs.twimg.com/media/DXP9VrMXUAAYaqj.jpg",
            "media_url_https": "https://pbs.twimg.com/media/DXP9VrMXUAAYaqj.jpg",
            "sizes": {
              "large": {
                "h": "1473",
                "resize": "fit",
                "w": "2000"
              },
              "medium": {
                "h": "884",
                "resize": "fit",
                "w": "1200"
              },
              "small": {
                "h": "501",
                "resize": "fit",
                "w": "680"
              },
              "thumb": {
                "h": "150",
                "resize": "crop",
                "w": "150"
              }
            },
            "type": "photo",
            "url": "https://t.co/0z1BU0ZEfN"
          }
        ]
      },
      "extended_entities": {
        "media": [
          {
            "display_url": "pic.twitter.com/0z1BU0ZEfN",
            "expanded_url": "https://twitter.com/SFOMuseum/status/969396896128172032/photo/1",
            "id_str": "969396893628452864",
            "indices": [
              "229", 
              "252"
            ],
            "media_url": "http://pbs.twimg.com/media/DXP9VrMXUAAYaqj.jpg",
            "media_url_https": "https://pbs.twimg.com/media/DXP9VrMXUAAYaqj.jpg",
            "sizes": {
              "large": {
                "h": "1473",
                "resize": "fit",
                "w": "2000"
              },
              "medium": {
                "h": "884",
                "resize": "fit",
                "w": "1200"
              },
              "small": {
                "h": "501",
                "resize": "fit",
                "w": "680"
              },
              "thumb": {
                "h": "150",
                "resize": "crop",
                "w": "150"
              }
            },
            "type": "photo",
            "url": "https://t.co/0z1BU0ZEfN"
          }
        ]
      },
      "favorite_count": "3",
      "favorited": false,
      "full_text": "From coast to coast, various regions of North America developed distinctive types of decoys. Carvers made some decoys to appear sleeping, preening, or with their heads tucked low into their bodies as if resting. #AmericanFolkArt https://t.co/0z1BU0ZEfN",
      "id_str": "969396896128172032",
      "lang": "en",
      "possibly_sensitive": false,
      "retweet_count": "1",
      "retweeted": false,
      "source": "\u003ca href=\"http://www.hootsuite.com\" rel=\"nofollow\"\u003eHootsuite\u003c/a\u003e",
      "truncated": false
    },
    "wof:name": "Twitter message #969396896128172032",
    "wof:placetype": "custom"
  },
  "geometry": {"coordinates":[-122.386166,37.616356],"type":"Point"}
}
