{
  "type": "Feature",
  "properties": {
    "date:cessation_lower": "2021-04-03",
    "date:cessation_upper": "2021-04-03",
    "date:inception_lower": "2021-04-03",
    "date:inception_upper": "2021-04-03",
    "sfomuseum:placetype": "tweet",
    "twitter:tweet": {
      "created": 1617408620,
      "created_at": "Sat Apr 03 00:10:20 +0000 2021",
      "display_text_range": [
        "0",
        "240"
      ],
      "edit_info": {
        "initial": {
          "editTweetIds": [
            "1378137759114620929"
          ],
          "editableUntil": "2021-04-03T00:40:20.991Z",
          "editsRemaining": "5",
          "isEditEligible": true
        }
      },
      "entities": {
      },
      "favorite_count": "2",
      "favorited": false,
      "full_text": "📸:\nHarley-Davidson Model 6; 1910\nHarley-Davidson Motor Company\nMilwaukee, Wisconsin\nCourtesy of Dave Scoffone\nL2020.2301.003\n\nWomen on Harley-Davidson motorcycles in McPherson, Kansas; c. 1910\nCourtesy of Pat and Cris Simmons\nR2020.2304.004",
      "id_str": "1378137759114620929",
      "in_reply_to_screen_name": "SFOMuseum",
      "in_reply_to_status_id": "1378137753351639042",
      "in_reply_to_status_id_str": "1378137753351639042",
      "in_reply_to_user_id": "116329337",
      "in_reply_to_user_id_str": "116329337",
      "lang": "en",
      "retweet_count": "0",
      "retweeted": false,
      "source": "\u003ca href=\"https://mobile.twitter.com\" rel=\"nofollow\"\u003eTwitter Web App\u003c/a\u003e",
      "truncated": false
    },
    "wof:name": "📸:\nHarley-Davidson Model 6; 1910\nHarley-Davidson Motor Company\nMilwaukee, Wisconsin\nCourtesy of Dave Scoffone\nL2020.2301.003\n\nWomen on Harley-Davidson motorcycles in McPherson, Kansas; c. 1910\nCourtesy of Pat and Cris Simmons\nR2020.2304.004",
    "wof:placetype": "custom"
  },
  "geometry": {"coordinates":[-122.386166,37.616356],"type":"Point"}
}
