{
  "type": "Feature",
  "properties": {
    "date:cessation_lower": "2015-06-17",
    "date:cessation_upper": "2015-06-17",
    "date:inception_lower": "2015-06-17",
    "date:inception_upper": "2015-06-17",
    "iso:country": "US",
    "sfomuseum:placetype": "tweet",
    "twitter:tweet": {
      "created": 1434583442,
      "created_at": "Wed Jun 17 23:24:02 +0000 2015",
      "display_text_range": [
        "0",
        "117"
      ],
      "entities": {
        "urls": [
          {
            "display_url": "instagram.com/p/4DHAQKxk0p/",
            "expanded_url": "https://instagram.com/p/4DHAQKxk0p/",
            "indices": [
              "94",
              "117"
            ],
            "url": "https://t.co/rdqEQKke00"
          }
        ]
      },
      "favorite_count": "0",
      "favorited": false,
      "full_text": "Tiaras!! Crowns! The tiara on the left was worn by Miss California, the center crown by Dame… https://t.co/rdqEQKke00",
      "id_str": "611313383636381696",
      "lang": "en",
      "possibly_sensitive": false,
      "retweet_count": "0",
      "retweeted": false,
      "source": "\u003ca href=\"http://instagram.com\" rel=\"nofollow\"\u003eInstagram\u003c/a\u003e",
      "truncated": false
    },
    "wof:name": "Tiaras!! Crowns! The tiara on the left was worn by Miss California, the center crown by Dame… https://t.co/rdqEQKke00",
    "wof:placetype": "custom"
  },
  "geometry": {"coordinates":[-122.386166,37.616356],"type":"Point"}
}
