{
  "type": "Feature",
  "properties": {
    "sfomuseum:placetype": "tweet",
    "twitter:tweet": {
      "created": 1372702746,
      "created_at": "Mon Jul 01 18:19:06 +0000 2013",
      "display_text_range": [
        "0", 
        "120"
      ],
      "entities": {
        "hashtags": [
          {
            "indices": [
              "62", 
              "71"
            ],
            "text": "Plastics"
          }
        ],
        "urls": [
          {
            "display_url": "ow.ly/mywnX",
            "expanded_url": "http://ow.ly/mywnX",
            "indices": [
              "73", 
              "95"
            ],
            "url": "http://t.co/CtgM87SLit"
          }, 
          {
            "display_url": "ow.ly/mywpO",
            "expanded_url": "http://ow.ly/mywpO",
            "indices": [
              "98", 
              "120"
            ],
            "url": "http://t.co/hJ2oOhXkj8"
          }
        ],
        "user_mentions": [
          {
            "id_str": "17799674",
            "indices": [
              "18", 
              "28"
            ],
            "name": "Karl Heine",
            "screen_name": "karlheine"
          }
        ]
      },
      "favorite_count": "0",
      "favorited": false,
      "full_text": "Two great pics by @karlheine from our newest exhibit, Classic #Plastics! http://t.co/CtgM87SLit   http://t.co/hJ2oOhXkj8",
      "id_str": "351766930035716096",
      "lang": "en",
      "possibly_sensitive": false,
      "retweet_count": "0",
      "retweeted": false,
      "source": "\u003ca href=\"http://www.hootsuite.com\" rel=\"nofollow\"\u003eHootsuite\u003c/a\u003e",
      "truncated": false
    },
    "wof:name": "Twitter message #351766930035716096",
    "wof:placetype": "custom"
  },
  "geometry": {"coordinates":[-122.386166,37.616356],"type":"Point"}
}
