{
  "type": "Feature",
  "properties": {
    "date:cessation_lower": "2011-12-03",
    "date:cessation_upper": "2011-12-03",
    "date:inception_lower": "2011-12-03",
    "date:inception_upper": "2011-12-03",
    "iso:country": "US",
    "sfomuseum:placetype": "tweet",
    "twitter:tweet": {
      "created": 1322882878,
      "created_at": "Sat Dec 03 03:27:58 +0000 2011",
      "display_text_range": [
        "0",
        "109"
      ],
      "edit_info": {
        "initial": {
          "editTweetIds": [
            "142807259494359040"
          ],
          "editableUntil": "2011-12-03T03:57:58.551Z",
          "editsRemaining": "5",
          "isEditEligible": true
        }
      },
      "entities": {
        "urls": [
          {
            "display_url": "twitpic.com/7nefp2",
            "expanded_url": "http://twitpic.com/7nefp2",
            "indices": [
              "89",
              "109"
            ],
            "url": "http://t.co/AnavaUhm"
          }
        ],
        "user_mentions": [
          {
            "id_str": "44420775",
            "indices": [
              "3",
              "17"
            ],
            "name": "Anne Espiritu",
            "screen_name": "Anne_Espiritu"
          },
          {
            "id_str": "21543254",
            "indices": [
              "33",
              "41"
            ],
            "name": "DJ Q*BERT Thud Rumble/Invisibl Skratch Piklz",
            "screen_name": "DJQbert"
          },
          {
            "id_str": "772368",
            "indices": [
              "79",
              "87"
            ],
            "name": "Monster",
            "screen_name": "Monster"
          }
        ]
      },
      "favorite_count": "0",
      "favorited": false,
      "full_text": "RT @Anne_Espiritu: Loyal fans of @djqbert! Fingers faster than speed of light. @monster  http://t.co/AnavaUhm",
      "id_str": "142807259494359040",
      "lang": "en",
      "possibly_sensitive": false,
      "retweet_count": "0",
      "retweeted": false,
      "source": "\u003ca href=\"http://www.hootsuite.com\" rel=\"nofollow\"\u003eHootsuite\u003c/a\u003e",
      "truncated": false
    },
    "wof:name": "RT @Anne_Espiritu: Loyal fans of @djqbert! Fingers faster than speed of light. @monster  http://t.co/AnavaUhm",
    "wof:placetype": "custom"
  },
  "geometry": {"coordinates":[-122.386166,37.616356],"type":"Point"}
}
