{
  "type": "Feature",
  "properties": {
    "date:cessation_lower": "2012-10-29",
    "date:cessation_upper": "2012-10-29",
    "date:inception_lower": "2012-10-29",
    "date:inception_upper": "2012-10-29",
    "iso:country": "US",
    "sfomuseum:placetype": "tweet",
    "twitter:tweet": {
      "created": 1351534655,
      "created_at": "Mon Oct 29 18:17:35 +0000 2012",
      "display_text_range": [
        "0",
        "119"
      ],
      "edit_info": {
        "initial": {
          "editTweetIds": [
            "262981522536157186"
          ],
          "editableUntil": "2012-10-29T19:17:35.590Z",
          "editsRemaining": "5",
          "isEditEligible": true
        }
      },
      "entities": {
        "urls": [
          {
            "display_url": "bit.ly/T75Bmw",
            "expanded_url": "http://bit.ly/T75Bmw",
            "indices": [
              "85",
              "105"
            ],
            "url": "http://t.co/jbEeMpn8"
          }
        ],
        "user_mentions": [
          {
            "id_str": "82998214",
            "indices": [
              "0",
              "8"
            ],
            "name": "Mallory Burda",
            "screen_name": "malburd"
          },
          {
            "id_str": "28169211",
            "indices": [
              "9",
              "22"
            ],
            "name": "Jesse Thomas",
            "screen_name": "jessemthomas"
          },
          {
            "id_str": "28454994",
            "indices": [
              "47",
              "62"
            ],
            "name": "Specialized Bicycles",
            "screen_name": "iamspecialized"
          }
        ]
      },
      "favorite_count": "0",
      "favorited": false,
      "full_text": "@malburd @jessemthomas There is indeed a great @iamspecialized bike on display here! http://t.co/jbEeMpn8 Come visit :)",
      "id_str": "262981522536157186",
      "in_reply_to_screen_name": "malburd",
      "in_reply_to_status_id": "262978243089551360",
      "in_reply_to_status_id_str": "262978243089551360",
      "in_reply_to_user_id": "82998214",
      "in_reply_to_user_id_str": "82998214",
      "lang": "en",
      "possibly_sensitive": false,
      "retweet_count": "1",
      "retweeted": false,
      "source": "\u003ca href=\"https://about.twitter.com/products/tweetdeck\" rel=\"nofollow\"\u003eTweetDeck\u003c/a\u003e",
      "truncated": false
    },
    "twitter:user_mentions": [
      "malburd",
      "jessemthomas",
      "iamspecialized"
    ],
    "wof:name": "@malburd @jessemthomas There is indeed a great @iamspecialized bike on display here! http://t.co/jbEeMpn8 Come visit :)",
    "wof:placetype": "custom"
  },
  "geometry": {"coordinates":[-122.386166,37.616356],"type":"Point"}
}
