{
  "type": "Feature",
  "properties": {
    "sfomuseum:placetype": "tweet",
    "twitter:tweet": {
      "created": 1444157739,
      "created_at": "Tue Oct 06 18:55:39 +0000 2015",
      "display_text_range": [
        "0", 
        "138"
      ],
      "entities": {
        "hashtags": [
          {
            "indices": [
              "101", 
              "115"
            ],
            "text": "MingeiFolkArt"
          }
        ],
        "media": [
          {
            "display_url": "pic.twitter.com/REmoYu8ItJ",
            "expanded_url": "https://twitter.com/SFOMuseum/status/651470892724318208/photo/1",
            "id_str": "651470892262780928",
            "indices": [
              "116", 
              "138"
            ],
            "media_url": "http://pbs.twimg.com/media/CQp9UyrUcAATukL.jpg",
            "media_url_https": "https://pbs.twimg.com/media/CQp9UyrUcAATukL.jpg",
            "sizes": {
              "large": {
                "h": "774",
                "resize": "fit",
                "w": "774"
              },
              "medium": {
                "h": "774",
                "resize": "fit",
                "w": "774"
              },
              "small": {
                "h": "680",
                "resize": "fit",
                "w": "680"
              },
              "thumb": {
                "h": "150",
                "resize": "crop",
                "w": "150"
              }
            },
            "type": "photo",
            "url": "http://t.co/REmoYu8ItJ"
          }
        ]
      },
      "extended_entities": {
        "media": [
          {
            "display_url": "pic.twitter.com/REmoYu8ItJ",
            "expanded_url": "https://twitter.com/SFOMuseum/status/651470892724318208/photo/1",
            "id_str": "651470892262780928",
            "indices": [
              "116", 
              "138"
            ],
            "media_url": "http://pbs.twimg.com/media/CQp9UyrUcAATukL.jpg",
            "media_url_https": "https://pbs.twimg.com/media/CQp9UyrUcAATukL.jpg",
            "sizes": {
              "large": {
                "h": "774",
                "resize": "fit",
                "w": "774"
              },
              "medium": {
                "h": "774",
                "resize": "fit",
                "w": "774"
              },
              "small": {
                "h": "680",
                "resize": "fit",
                "w": "680"
              },
              "thumb": {
                "h": "150",
                "resize": "crop",
                "w": "150"
              }
            },
            "type": "photo",
            "url": "http://t.co/REmoYu8ItJ"
          }
        ]
      },
      "favorite_count": "2",
      "favorited": false,
      "full_text": "Kokeshi, one of the most beloved folk dolls in Japan, stem from a tradition that dates to the 1800s. #MingeiFolkArt http://t.co/REmoYu8ItJ",
      "id_str": "651470892724318208",
      "lang": "en",
      "possibly_sensitive": false,
      "retweet_count": "0",
      "retweeted": false,
      "source": "\u003ca href=\"http://www.hootsuite.com\" rel=\"nofollow\"\u003eHootsuite\u003c/a\u003e",
      "truncated": false
    },
    "wof:name": "Twitter message #651470892724318208",
    "wof:placetype": "custom"
  },
  "geometry": {"coordinates":[-122.386166,37.616356],"type":"Point"}
}
