{
  "type": "Feature",
  "properties": {
    "sfomuseum:placetype": "tweet",
    "twitter:tweet": {
      "created": 1397686261,
      "created_at": "Wed Apr 16 22:11:01 +0000 2014",
      "display_text_range": [
        "0", 
        "140"
      ],
      "entities": {
        "user_mentions": [
          {
            "id_str": "735926484376817664",
            "indices": [
              "3", 
              "16"
            ],
            "name": "Bex",
            "screen_name": "greenblanket"
          }
        ]
      },
      "favorite_count": "0",
      "favorited": false,
      "full_text": "RT @greenblanket: Really loving this Japanese Toys exhibit at the San Francisco Airport, thanks to the SFO. Robots and AstroMan and vintage…",
      "id_str": "456555388641345537",
      "lang": "en",
      "retweet_count": "0",
      "retweeted": false,
      "source": "\u003ca href=\"http://www.hootsuite.com\" rel=\"nofollow\"\u003eHootsuite\u003c/a\u003e",
      "truncated": false
    },
    "wof:name": "Twitter message #456555388641345537",
    "wof:placetype": "custom"
  },
  "geometry": {"coordinates":[-122.386166,37.616356],"type":"Point"}
}
