{
  "type": "Feature",
  "properties": {
    "date:cessation_lower": "2012-05-02",
    "date:cessation_upper": "2012-05-02",
    "date:inception_lower": "2012-05-02",
    "date:inception_upper": "2012-05-02",
    "iso:country": "US",
    "sfomuseum:placetype": "tweet",
    "twitter:tweet": {
      "created": 1335990737,
      "created_at": "Wed May 02 20:32:17 +0000 2012",
      "display_text_range": [
        "0",
        "140"
      ],
      "edit_info": {
        "initial": {
          "editTweetIds": [
            "197785606636580864"
          ],
          "editableUntil": "2012-05-02T21:02:17.958Z",
          "editsRemaining": "5",
          "isEditEligible": true
        }
      },
      "entities": {
        "urls": [
          {
            "display_url": "bit.ly/rQtc5r",
            "expanded_url": "http://bit.ly/rQtc5r",
            "indices": [
              "120",
              "140"
            ],
            "url": "http://t.co/ebc5G61m"
          }
        ]
      },
      "favorite_count": "0",
      "favorited": false,
      "full_text": "It's the last day for T1 pssngrs to enjoy Heather Meader-McCausland's photos of N. Alaska's landscape thru the seasons: http://t.co/ebc5G61m",
      "id_str": "197785606636580864",
      "lang": "en",
      "possibly_sensitive": false,
      "retweet_count": "1",
      "retweeted": false,
      "source": "\u003ca href=\"https://about.twitter.com/products/tweetdeck\" rel=\"nofollow\"\u003eTweetDeck\u003c/a\u003e",
      "truncated": false
    },
    "wof:name": "It's the last day for T1 pssngrs to enjoy Heather Meader-McCausland's photos of N. Alaska's landscape thru the seasons: http://t.co/ebc5G61m",
    "wof:placetype": "custom"
  },
  "geometry": {"coordinates":[-122.386166,37.616356],"type":"Point"}
}
