{
  "type": "Feature",
  "properties": {
    "sfomuseum:placetype": "tweet",
    "twitter:tweet": {
      "created": 1439493234,
      "created_at": "Thu Aug 13 19:13:54 +0000 2015",
      "display_text_range": [
        "0", 
        "140"
      ],
      "entities": {
        "urls": [
          {
            "display_url": "bizj.us/1isouq",
            "expanded_url": "http://bizj.us/1isouq",
            "indices": [
              "96", 
              "118"
            ],
            "url": "http://t.co/WuyAEe7Pdh"
          }
        ],
        "user_mentions": [
          {
            "id_str": "19560636",
            "indices": [
              "3", 
              "19"
            ],
            "name": "San Francisco Business Times",
            "screen_name": "SFBusinessTimes"
          }, 
          {
            "id_str": "16408759",
            "indices": [
              "33", 
              "40"
            ],
            "name": "San Francisco International Airport (SFO) ✈️",
            "screen_name": "flySFO"
          }
        ]
      },
      "favorite_count": "0",
      "favorited": false,
      "full_text": "RT @SFBusinessTimes: Look Inside @flySFO new $70M air-traffic control tower that's coming soon  http://t.co/WuyAEe7Pdh http://t.co/wRWQRRZL…",
      "id_str": "631906542715953152",
      "lang": "en",
      "possibly_sensitive": false,
      "retweet_count": "0",
      "retweeted": false,
      "source": "\u003ca href=\"http://www.hootsuite.com\" rel=\"nofollow\"\u003eHootsuite\u003c/a\u003e",
      "truncated": false
    },
    "wof:name": "Twitter message #631906542715953152",
    "wof:placetype": "custom"
  },
  "geometry": {"coordinates":[-122.386166,37.616356],"type":"Point"}
}
