{
  "type": "Feature",
  "properties": {
    "date:cessation_lower": "2023-03-17",
    "date:cessation_upper": "2023-03-17",
    "date:inception_lower": "2023-03-17",
    "date:inception_upper": "2023-03-17",
    "sfomuseum:placetype": "tweet",
    "twitter:tweet": {
      "created": 1679087051,
      "created_at": "Fri Mar 17 21:04:11 +0000 2023",
      "display_text_range": [
        "0",
        "140"
      ],
      "edit_info": {
        "initial": {
          "editTweetIds": [
            "1636835847407554560"
          ],
          "editableUntil": "2023-03-17T21:34:11.618Z",
          "editsRemaining": "5",
          "isEditEligible": false
        }
      },
      "entities": {
        "user_mentions": [
          {
            "id_str": "116329337",
            "indices": [
              "3",
              "13"
            ],
            "name": "SFO Museum",
            "screen_name": "SFOMuseum"
          },
          {
            "id_str": "183320631",
            "indices": [
              "123",
              "131"
            ],
            "name": "San Francisco Opera",
            "screen_name": "SFOpera"
          }
        ]
      },
      "favorite_count": "0",
      "favorited": false,
      "full_text": "RT @SFOMuseum: Want to see “San Francisco Opera: A Centennial Celebration” but don’t have a flight tickets? SFO Museum and @SFOpera are off…",
      "id_str": "1636835847407554560",
      "lang": "en",
      "retweet_count": "0",
      "retweeted": false,
      "source": "\u003ca href=\"https://mobile.twitter.com\" rel=\"nofollow\"\u003eTwitter Web App\u003c/a\u003e",
      "truncated": false
    },
    "wof:name": "RT @SFOMuseum: Want to see “San Francisco Opera: A Centennial Celebration” but don’t have a flight tickets? SFO Museum and @SFOpera are off…",
    "wof:placetype": "custom"
  },
  "geometry": {"coordinates":[-122.386166,37.616356],"type":"Point"}
}
