{
  "type": "Feature",
  "properties": {
    "date:cessation_lower": "2012-10-26",
    "date:cessation_upper": "2012-10-26",
    "date:inception_lower": "2012-10-26",
    "date:inception_upper": "2012-10-26",
    "iso:country": "US",
    "sfomuseum:placetype": "tweet",
    "twitter:tweet": {
      "created": 1351275550,
      "created_at": "Fri Oct 26 18:19:10 +0000 2012",
      "display_text_range": [
        "0",
        "48"
      ],
      "edit_info": {
        "initial": {
          "editTweetIds": [
            "261894757540847616"
          ],
          "editableUntil": "2012-10-26T19:19:10.624Z",
          "editsRemaining": "5",
          "isEditEligible": true
        }
      },
      "entities": {
        "user_mentions": [
          {
            "id_str": "190311360",
            "indices": [
              "0",
              "14"
            ],
            "name": "Father Geek",
            "screen_name": "thefathergeek"
          }
        ]
      },
      "favorite_count": "0",
      "favorited": false,
      "full_text": "@thefathergeek Done! ...but we're always free :)",
      "id_str": "261894757540847616",
      "in_reply_to_screen_name": "thefathergeek",
      "in_reply_to_status_id": "261894558168780800",
      "in_reply_to_status_id_str": "261894558168780800",
      "in_reply_to_user_id": "190311360",
      "in_reply_to_user_id_str": "190311360",
      "lang": "en",
      "retweet_count": "0",
      "retweeted": false,
      "source": "\u003ca href=\"https://about.twitter.com/products/tweetdeck\" rel=\"nofollow\"\u003eTweetDeck\u003c/a\u003e",
      "truncated": false
    },
    "twitter:user_mentions": [
      "thefathergeek"
    ],
    "wof:name": "@thefathergeek Done! ...but we're always free :)",
    "wof:placetype": "custom"
  },
  "geometry": {"coordinates":[-122.386166,37.616356],"type":"Point"}
}
