{
  "type": "Feature",
  "properties": {
    "date:cessation_lower": "2024-01-31",
    "date:cessation_upper": "2024-01-31",
    "date:inception_lower": "2024-01-31",
    "date:inception_upper": "2024-01-31",
    "sfomuseum:placetype": "tweet",
    "twitter:tweet": {
      "created": 1706663936,
      "created_at": "Wed Jan 31 01:18:56 +0000 2024",
      "display_text_range": [
        "0",
        "94"
      ],
      "edit_info": {
        "initial": {
          "editTweetIds": [
            "1752501686273532377"
          ],
          "editableUntil": "2024-01-31T02:18:56.000Z",
          "editsRemaining": "5",
          "isEditEligible": false
        }
      },
      "entities": {
        "urls": [
          {
            "display_url": "collection.sfomuseum.org/objects/174683…",
            "expanded_url": "https://collection.sfomuseum.org/objects/1746836673/",
            "indices": [
              "71",
              "94"
            ],
            "url": "https://t.co/3EmRF7Td6W"
          }
        ]
      },
      "favorite_count": "3",
      "favorited": false,
      "full_text": "📸:\nposter: Air California; 1970s\nGift of David Winckoski\n2011.195.154\n\nhttps://t.co/3EmRF7Td6W",
      "id_str": "1752501686273532377",
      "in_reply_to_screen_name": "SFOMuseum",
      "in_reply_to_status_id": "1752501684100858048",
      "in_reply_to_status_id_str": "1752501684100858048",
      "in_reply_to_user_id": "116329337",
      "in_reply_to_user_id_str": "116329337",
      "lang": "en",
      "possibly_sensitive": false,
      "retweet_count": "1",
      "retweeted": false,
      "source": "\u003ca href=\"https://mobile.twitter.com\" rel=\"nofollow\"\u003eTwitter Web App\u003c/a\u003e",
      "truncated": false
    },
    "wof:name": "📸:\nposter: Air California; 1970s\nGift of David Winckoski\n2011.195.154\n\nhttps://t.co/3EmRF7Td6W",
    "wof:placetype": "custom",
    "wof:placetype_alt": [
      "tweet"
    ]
  },
  "geometry": {"coordinates":[-122.386166,37.616356],"type":"Point"}
}
