{
  "type": "Feature",
  "properties": {
    "sfomuseum:placetype": "tweet",
    "twitter:tweet": {
      "created": 1441899395,
      "created_at": "Thu Sep 10 15:36:35 +0000 2015",
      "display_text_range": [
        "0", 
        "140"
      ],
      "entities": {
        "user_mentions": [
          {
            "id_str": "278263517",
            "indices": [
              "3", 
              "12"
            ],
            "name": "Jeff Wasserstrom",
            "screen_name": "jwassers"
          }, 
          {
            "id_str": "207851376",
            "indices": [
              "113", 
              "129"
            ],
            "name": "Shanghai Lit Fest",
            "screen_name": "litfestshanghai"
          }
        ]
      },
      "favorite_count": "0",
      "favorited": false,
      "full_text": "RT @jwassers: SFO has Art Deco exhibit up now, with attention to Asia; good fit w/Shanghai nov Art Deco congress @litfestshanghai http://t.…",
      "id_str": "641998712328355840",
      "lang": "en",
      "retweet_count": "0",
      "retweeted": false,
      "source": "\u003ca href=\"http://www.hootsuite.com\" rel=\"nofollow\"\u003eHootsuite\u003c/a\u003e",
      "truncated": false
    },
    "wof:name": "Twitter message #641998712328355840",
    "wof:placetype": "custom"
  },
  "geometry": {"coordinates":[-122.386166,37.616356],"type":"Point"}
}
