{
  "type": "Feature",
  "properties": {
    "date:cessation_lower":"2014-05-01",
    "date:cessation_upper":"2014-05-01",
    "date:inception_lower":"2014-05-01",
    "date:inception_upper":"2014-05-01",
    "iso:country":"US",
    "sfomuseum:placetype":"tweet",
    "twitter:tweet":{
        "created":1398977058,
        "created_at":"Thu May 01 20:44:18 +0000 2014",
        "display_text_range":[
            "0",
            "80"
        ],
        "entities":{
            "urls":[
                {
                    "display_url":"ow.ly/wnYqA",
                    "expanded_url":"http://ow.ly/wnYqA",
                    "indices":[
                        "58",
                        "80"
                    ],
                    "url":"http://t.co/HAGymWsmk6"
                }
            ],
            "user_mentions":[
                {
                    "id_str":"16408759",
                    "indices":[
                        "49",
                        "56"
                    ],
                    "name":"San Francisco International Airport (SFO) \u2708\ufe0f",
                    "screen_name":"flySFO"
                }
            ]
        },
        "favorite_count":"0",
        "favorited":false,
        "full_text":"How warm is it today? This is what it feels like @flySFO: http://t.co/HAGymWsmk6",
        "id_str":"461969382760267776",
        "lang":"en",
        "possibly_sensitive":false,
        "retweet_count":"0",
        "retweeted":false,
        "source":"<a href=\"http://www.hootsuite.com\" rel=\"nofollow\">Hootsuite</a>",
        "truncated":false
    },
    "wof:name":"How warm is it today? This is what it feels like @flySFO: http://t.co/HAGymWsmk6",
    "wof:placetype":"custom"
},
  "geometry": {"coordinates":[-122.386166,37.616356],"type":"Point"}
}