{
  "type": "Feature",
  "properties": {
    "date:cessation_lower": "2023-04-28",
    "date:cessation_upper": "2023-04-28",
    "date:inception_lower": "2023-04-28",
    "date:inception_upper": "2023-04-28",
    "sfomuseum:placetype": "tweet",
    "twitter:tweet": {
      "created": 1682641938,
      "created_at": "Fri Apr 28 00:32:18 +0000 2023",
      "display_text_range": [
        "0",
        "272"
      ],
      "edit_info": {
        "initial": {
          "editTweetIds": [
            "1651746124259287040"
          ],
          "editableUntil": "2023-04-28T01:02:18.000Z",
          "editsRemaining": "5",
          "isEditEligible": false
        }
      },
      "entities": {
        "urls": [
          {
            "display_url": "bit.ly/41XsFcE",
            "expanded_url": "https://bit.ly/41XsFcE",
            "indices": [
              "101",
              "124"
            ],
            "url": "https://t.co/4dR8k66CG9"
          },
          {
            "display_url": "bit.ly/3LgaZSt",
            "expanded_url": "https://bit.ly/3LgaZSt",
            "indices": [
              "249",
              "272"
            ],
            "url": "https://t.co/ytAOpT8XmC"
          }
        ]
      },
      "favorite_count": "0",
      "favorited": false,
      "full_text": "📸:\nposter: Airbus A380; 2007\nTransfer from San Francisco International Airport\n2007.093.007.001-.002\nhttps://t.co/4dR8k66CG9\n\nmodel airplane: Emirates Airline, Airbus A380-800; 2014\nTransfer from San Francisco International Airport\n2014.167.042 a b\nhttps://t.co/ytAOpT8XmC",
      "id_str": "1651746124259287040",
      "in_reply_to_screen_name": "SFOMuseum",
      "in_reply_to_status_id": "1651746121394589698",
      "in_reply_to_status_id_str": "1651746121394589698",
      "in_reply_to_user_id": "116329337",
      "in_reply_to_user_id_str": "116329337",
      "lang": "en",
      "possibly_sensitive": false,
      "retweet_count": "0",
      "retweeted": false,
      "source": "\u003ca href=\"https://mobile.twitter.com\" rel=\"nofollow\"\u003eTwitter Web App\u003c/a\u003e",
      "truncated": false
    },
    "wof:name": "📸:\nposter: Airbus A380; 2007\nTransfer from San Francisco International Airport\n2007.093.007.001-.002\nhttps://t.co/4dR8k66CG9\n\nmodel airplane: Emirates Airline, Airbus A380-800; 2014\nTransfer from San Francisco International Airport\n2014.167.042 a b\nhttps://t.co/ytAOpT8XmC",
    "wof:placetype": "custom"
  },
  "geometry": {"coordinates":[-122.386166,37.616356],"type":"Point"}
}
