{
  "type": "Feature",
  "properties": {
    "sfomuseum:placetype": "tweet",
    "twitter:tweet": {
      "created": 1347304564,
      "created_at": "Mon Sep 10 19:16:04 +0000 2012",
      "display_text_range": [
        "0", 
        "103"
      ],
      "entities": {
        "urls": [
          {
            "display_url": "instagr.am/p/PZ8_88Rk3L/",
            "expanded_url": "http://instagr.am/p/PZ8_88Rk3L/",
            "indices": [
              "83", 
              "103"
            ],
            "url": "http://t.co/YuO7gVwT"
          }
        ]
      },
      "favorite_count": "0",
      "favorited": false,
      "full_text": "Lella Vignetti's necklace for San Lorenzo has roots in 17th century Dutch fashion  http://t.co/YuO7gVwT",
      "id_str": "245239232740876288",
      "lang": "en",
      "possibly_sensitive": false,
      "retweet_count": "0",
      "retweeted": false,
      "source": "\u003ca href=\"http://instagram.com\" rel=\"nofollow\"\u003eInstagram\u003c/a\u003e",
      "truncated": false
    },
    "wof:name": "Twitter message #245239232740876288",
    "wof:placetype": "custom"
  },
  "geometry": {"coordinates":[-122.386166,37.616356],"type":"Point"}
}
