{
  "type": "Feature",
  "properties": {
    "sfomuseum:placetype": "tweet",
    "twitter:tweet": {
      "created": 1499394608,
      "created_at": "Fri Jul 07 02:30:08 +0000 2017",
      "display_text_range": [
        "0", 
        "161"
      ],
      "entities": {
        "hashtags": [
          {
            "indices": [
              "17", 
              "31"
            ],
            "text": "artsandcrafts"
          }
        ],
        "media": [
          {
            "display_url": "pic.twitter.com/k9oV5Z1mmT",
            "expanded_url": "https://twitter.com/SFOMuseum/status/883151113121402880/photo/1",
            "id_str": "883151109317173249",
            "indices": [
              "138", 
              "161"
            ],
            "media_url": "http://pbs.twimg.com/media/DEGVQTnXoAEfU8f.jpg",
            "media_url_https": "https://pbs.twimg.com/media/DEGVQTnXoAEfU8f.jpg",
            "sizes": {
              "large": {
                "h": "2000",
                "resize": "fit",
                "w": "1600"
              },
              "medium": {
                "h": "1200",
                "resize": "fit",
                "w": "960"
              },
              "small": {
                "h": "680",
                "resize": "fit",
                "w": "544"
              },
              "thumb": {
                "h": "150",
                "resize": "crop",
                "w": "150"
              }
            },
            "type": "photo",
            "url": "https://t.co/k9oV5Z1mmT"
          }
        ],
        "urls": [
          {
            "display_url": "bit.ly/SFOArtsandCraf…",
            "expanded_url": "http://bit.ly/SFOArtsandCrafts",
            "indices": [
              "114", 
              "137"
            ],
            "url": "https://t.co/beGCVuzpTr"
          }
        ]
      },
      "extended_entities": {
        "media": [
          {
            "display_url": "pic.twitter.com/k9oV5Z1mmT",
            "expanded_url": "https://twitter.com/SFOMuseum/status/883151113121402880/photo/1",
            "id_str": "883151109317173249",
            "indices": [
              "138", 
              "161"
            ],
            "media_url": "http://pbs.twimg.com/media/DEGVQTnXoAEfU8f.jpg",
            "media_url_https": "https://pbs.twimg.com/media/DEGVQTnXoAEfU8f.jpg",
            "sizes": {
              "large": {
                "h": "2000",
                "resize": "fit",
                "w": "1600"
              },
              "medium": {
                "h": "1200",
                "resize": "fit",
                "w": "960"
              },
              "small": {
                "h": "680",
                "resize": "fit",
                "w": "544"
              },
              "thumb": {
                "h": "150",
                "resize": "crop",
                "w": "150"
              }
            },
            "type": "photo",
            "url": "https://t.co/k9oV5Z1mmT"
          }
        ]
      },
      "favorite_count": "2",
      "favorited": false,
      "full_text": "Learn more about #artsandcrafts in \"At Home with Arts and Crafts\" on display, pre-security, in the Intl Terminal. https://t.co/beGCVuzpTr https://t.co/k9oV5Z1mmT",
      "id_str": "883151113121402880",
      "lang": "en",
      "possibly_sensitive": false,
      "retweet_count": "0",
      "retweeted": false,
      "source": "\u003ca href=\"http://www.hootsuite.com\" rel=\"nofollow\"\u003eHootsuite\u003c/a\u003e",
      "truncated": false
    },
    "wof:name": "Twitter message #883151113121402880",
    "wof:placetype": "custom"
  },
  "geometry": {"coordinates":[-122.386166,37.616356],"type":"Point"}
}
