{
  "type": "Feature",
  "properties": {
    "sfomuseum:placetype": "tweet",
    "twitter:tweet": {
      "created": 1322599030,
      "created_at": "Tue Nov 29 20:37:10 +0000 2011",
      "display_text_range": [
        "0", 
        "115"
      ],
      "entities": {
        "user_mentions": [
          {
            "id_str": "7301572",
            "indices": [
              "0", 
              "12"
            ],
            "name": "Rob Pegoraro",
            "screen_name": "robpegoraro"
          }
        ]
      },
      "favorite_count": "0",
      "favorited": false,
      "full_text": "@robpegoraro Oh yeah, please do! There are also non-aviation exhibits pre-TSA in the IT; plenty to keep you busy :)",
      "id_str": "141616715086831616",
      "in_reply_to_screen_name": "robpegoraro",
      "in_reply_to_status_id": "141610558930681856",
      "in_reply_to_status_id_str": "141610558930681856",
      "in_reply_to_user_id": "7301572",
      "in_reply_to_user_id_str": "7301572",
      "lang": "en",
      "retweet_count": "0",
      "retweeted": false,
      "source": "\u003ca href=\"http://twitter.com/download/iphone\" rel=\"nofollow\"\u003eTwitter for iPhone\u003c/a\u003e",
      "truncated": false
    },
    "wof:name": "Twitter message #141616715086831616",
    "wof:placetype": "custom"
  },
  "geometry": {"coordinates":[-122.386166,37.616356],"type":"Point"}
}
