{
  "type": "Feature",
  "properties": {
    "sfomuseum:placetype": "tweet",
    "twitter:tweet": {
      "created": 1327433087,
      "created_at": "Tue Jan 24 19:24:47 +0000 2012",
      "display_text_range": [
        "0", 
        "104"
      ],
      "entities": {
        "user_mentions": [
          {
            "id_str": "115147038",
            "indices": [
              "0", 
              "10"
            ],
            "name": "Blair",
            "screen_name": "CraftChat"
          }
        ]
      },
      "favorite_count": "0",
      "favorited": false,
      "full_text": "@CraftChat Our total pleasure! So glad you enjoyed our TV exhibit \u0026 we look forward to seeing you again!",
      "id_str": "161892217609396225",
      "in_reply_to_screen_name": "CraftChat",
      "in_reply_to_status_id": "161888590064926720",
      "in_reply_to_status_id_str": "161888590064926720",
      "in_reply_to_user_id": "115147038",
      "in_reply_to_user_id_str": "115147038",
      "lang": "en",
      "retweet_count": "0",
      "retweeted": false,
      "source": "\u003ca href=\"http://www.hootsuite.com\" rel=\"nofollow\"\u003eHootsuite\u003c/a\u003e",
      "truncated": false
    },
    "wof:name": "Twitter message #161892217609396225",
    "wof:placetype": "custom"
  },
  "geometry": {"coordinates":[-122.386166,37.616356],"type":"Point"}
}
