{
  "type": "Feature",
  "properties": {
    "date:cessation_lower": "2017-07-20",
    "date:cessation_upper": "2017-07-20",
    "date:inception_lower": "2017-07-20",
    "date:inception_upper": "2017-07-20",
    "iso:country": "US",
    "sfomuseum:placetype": "tweet",
    "twitter:tweet": {
      "created": 1500581706,
      "created_at": "Thu Jul 20 20:15:06 +0000 2017",
      "display_text_range": [
        "0",
        "140"
      ],
      "entities": {
        "hashtags": [
          {
            "indices": [
              "12",
              "16"
            ],
            "text": "tbt"
          },
          {
            "indices": [
              "130",
              "134"
            ],
            "text": "sfo"
          }
        ],
        "user_mentions": [
          {
            "id_str": "16408759",
            "indices": [
              "3",
              "10"
            ],
            "name": "San Francisco International Airport (SFO) ✈️😷",
            "screen_name": "flySFO"
          }
        ]
      },
      "favorite_count": "0",
      "favorited": false,
      "full_text": "RT @flySFO: #tbt The first graded airstrip was 4,950 feet long and surfaced in rolled rock fill covered with two inches of earth. #sfo http…",
      "id_str": "888130166232305664",
      "lang": "en",
      "retweet_count": "0",
      "retweeted": false,
      "source": "\u003ca href=\"http://twitter.com/download/iphone\" rel=\"nofollow\"\u003eTwitter for iPhone\u003c/a\u003e",
      "truncated": false
    },
    "wof:name": "RT @flySFO: #tbt The first graded airstrip was 4,950 feet long and surfaced in rolled rock fill covered with two inches of earth. #sfo http…",
    "wof:placetype": "custom"
  },
  "geometry": {"coordinates":[-122.386166,37.616356],"type":"Point"}
}
