{
  "type": "Feature",
  "properties": {
    "sfomuseum:placetype": "tweet",
    "twitter:tweet": {
      "created": 1339090257,
      "created_at": "Thu Jun 07 17:30:57 +0000 2012",
      "display_text_range": [
        "0", 
        "132"
      ],
      "entities": {
        "urls": [
          {
            "display_url": "ow.ly/bqun6",
            "expanded_url": "http://ow.ly/bqun6",
            "indices": [
              "112", 
              "132"
            ],
            "url": "http://t.co/bycolrHg"
          }
        ]
      },
      "favorite_count": "0",
      "favorited": false,
      "full_text": "Among the microscopes on view in the Int'l Term is this beautiful one of ivory \u0026amp; mahogany from 1660s Italy: http://t.co/bycolrHg",
      "id_str": "210785933577035777",
      "lang": "en",
      "possibly_sensitive": false,
      "retweet_count": "1",
      "retweeted": false,
      "source": "\u003ca href=\"http://www.hootsuite.com\" rel=\"nofollow\"\u003eHootsuite\u003c/a\u003e",
      "truncated": false
    },
    "wof:name": "Twitter message #210785933577035777",
    "wof:placetype": "custom"
  },
  "geometry": {"coordinates":[-122.386166,37.616356],"type":"Point"}
}
