{
  "type": "Feature",
  "properties": {
    "sfomuseum:placetype": "tweet",
    "twitter:tweet": {
      "created": 1325189097,
      "created_at": "Thu Dec 29 20:04:57 +0000 2011",
      "display_text_range": [
        "0", 
        "111"
      ],
      "entities": {
        "urls": [
          {
            "display_url": "yfrog.com/ock2bizj",
            "expanded_url": "http://yfrog.com/ock2bizj",
            "indices": [
              "91", 
              "111"
            ],
            "url": "http://t.co/BDTinjtF"
          }
        ]
      },
      "favorite_count": "0",
      "favorited": false,
      "full_text": "Happy birthday to Mary Tyler Moore! May you continue to turn the world on with your smile! http://t.co/BDTinjtF",
      "id_str": "152480242630524928",
      "lang": "en",
      "possibly_sensitive": false,
      "retweet_count": "0",
      "retweeted": false,
      "source": "\u003ca href=\"https://about.twitter.com/products/tweetdeck\" rel=\"nofollow\"\u003eTweetDeck\u003c/a\u003e",
      "truncated": false
    },
    "wof:name": "Twitter message #152480242630524928",
    "wof:placetype": "custom"
  },
  "geometry": {"coordinates":[-122.386166,37.616356],"type":"Point"}
}
