{
  "type": "Feature",
  "properties": {
    "date:cessation_lower": "2015-07-30",
    "date:cessation_upper": "2015-07-30",
    "date:inception_lower": "2015-07-30",
    "date:inception_upper": "2015-07-30",
    "iso:country": "US",
    "sfomuseum:placetype": "tweet",
    "twitter:tweet": {
      "created": 1438296079,
      "created_at": "Thu Jul 30 22:41:19 +0000 2015",
      "display_text_range": [
        "0",
        "137"
      ],
      "edit_info": {
        "initial": {
          "editTweetIds": [
            "626885311394529280"
          ],
          "editableUntil": "2015-07-30T23:11:19.859Z",
          "editsRemaining": "5",
          "isEditEligible": true
        }
      },
      "entities": {
        "urls": [
          {
            "display_url": "amyellingson.com/blog/2015/7/29…",
            "expanded_url": "http://www.amyellingson.com/blog/2015/7/29/sfo-mural-reveal",
            "indices": [
              "109",
              "131"
            ],
            "url": "http://t.co/bMaJtypDDz"
          }
        ],
        "user_mentions": [
          {
            "id_str": "18958334",
            "indices": [
              "132",
              "137"
            ],
            "name": "SF Arts Commission",
            "screen_name": "SFAC"
          }
        ]
      },
      "favorite_count": "2",
      "favorited": false,
      "full_text": "Amy Ellingson's Untitled opened last week in Terminal 2. Check out her blog about installing her art at SFO! http://t.co/bMaJtypDDz @SFAC",
      "id_str": "626885311394529280",
      "lang": "en",
      "possibly_sensitive": false,
      "retweet_count": "0",
      "retweeted": false,
      "source": "\u003ca href=\"http://twitter.com\" rel=\"nofollow\"\u003eTwitter Web Client\u003c/a\u003e",
      "truncated": false
    },
    "wof:name": "Amy Ellingson's Untitled opened last week in Terminal 2. Check out her blog about installing her art at SFO! http://t.co/bMaJtypDDz @SFAC",
    "wof:placetype": "custom"
  },
  "geometry": {"coordinates":[-122.386166,37.616356],"type":"Point"}
}
