{
  "type": "Feature",
  "properties": {
    "date:cessation_lower": "2012-05-04",
    "date:cessation_upper": "2012-05-04",
    "date:inception_lower": "2012-05-04",
    "date:inception_upper": "2012-05-04",
    "iso:country": "US",
    "sfomuseum:placetype": "tweet",
    "twitter:tweet": {
      "created": 1336149100,
      "created_at": "Fri May 04 16:31:40 +0000 2012",
      "display_text_range": [
        "0",
        "139"
      ],
      "edit_info": {
        "initial": {
          "editTweetIds": [
            "198449828672450560"
          ],
          "editableUntil": "2012-05-04T17:01:40.832Z",
          "editsRemaining": "5",
          "isEditEligible": true
        }
      },
      "entities": {
      },
      "favorite_count": "0",
      "favorited": false,
      "full_text": "'Young Lady's Friend' excerpt (from 1837): A woman who does not know how to sew is as deficient in her education as a man who cannot write.",
      "id_str": "198449828672450560",
      "lang": "en",
      "retweet_count": "0",
      "retweeted": false,
      "source": "\u003ca href=\"https://about.twitter.com/products/tweetdeck\" rel=\"nofollow\"\u003eTweetDeck\u003c/a\u003e",
      "truncated": false
    },
    "wof:name": "'Young Lady's Friend' excerpt (from 1837): A woman who does not know how to sew is as deficient in her education as a man who cannot write.",
    "wof:placetype": "custom"
  },
  "geometry": {"coordinates":[-122.386166,37.616356],"type":"Point"}
}
