{
  "type": "Feature",
  "properties": {
    "date:cessation_lower": "2012-02-07",
    "date:cessation_upper": "2012-02-07",
    "date:inception_lower": "2012-02-07",
    "date:inception_upper": "2012-02-07",
    "iso:country": "US",
    "sfomuseum:placetype": "tweet",
    "twitter:tweet": {
      "created": 1328573374,
      "created_at": "Tue Feb 07 00:09:34 +0000 2012",
      "display_text_range": [
        "0",
        "138"
      ],
      "edit_info": {
        "initial": {
          "editTweetIds": [
            "166674931231375360"
          ],
          "editableUntil": "2012-02-07T00:39:34.933Z",
          "editsRemaining": "5",
          "isEditEligible": true
        }
      },
      "entities": {
        "urls": [
          {
            "display_url": "ow.ly/1FIdUL",
            "expanded_url": "http://ow.ly/1FIdUL",
            "indices": [
              "118",
              "138"
            ],
            "url": "http://t.co/gvW7d4Xn"
          }
        ]
      },
      "favorite_count": "0",
      "favorited": false,
      "full_text": "Like a 1920s version of a tape AND cd playing boombox, this phonograph can play both lateral- \u0026 vertical-cut records: http://t.co/gvW7d4Xn",
      "id_str": "166674931231375360",
      "lang": "en",
      "possibly_sensitive": false,
      "retweet_count": "0",
      "retweeted": false,
      "source": "\u003ca href=\"http://www.hootsuite.com\" rel=\"nofollow\"\u003eHootsuite\u003c/a\u003e",
      "truncated": false
    },
    "wof:name": "Like a 1920s version of a tape AND cd playing boombox, this phonograph can play both lateral- \u0026 vertical-cut records: http://t.co/gvW7d4Xn",
    "wof:placetype": "custom"
  },
  "geometry": {"coordinates":[-122.386166,37.616356],"type":"Point"}
}
