{
  "type": "Feature",
  "properties": {
    "sfomuseum:placetype": "tweet",
    "twitter:tweet": {
      "created": 1317668535,
      "created_at": "Mon Oct 03 19:02:15 +0000 2011",
      "display_text_range": [
        "0", 
        "138"
      ],
      "entities": {
        "urls": [
          {
            "display_url": "tumblr.com/xcu51ojasb",
            "expanded_url": "http://tumblr.com/xcu51ojasb",
            "indices": [
              "118", 
              "138"
            ],
            "url": "http://t.co/OG6pL19M"
          }
        ]
      },
      "favorite_count": "0",
      "favorited": false,
      "full_text": "Endorsed! RT @endorsedornot: Endorsed: Television - TV in the Antenna Age - Exhibit at SFO T3 - worth taking a look - http://t.co/OG6pL19M",
      "id_str": "120936718181474304",
      "lang": "en",
      "possibly_sensitive": false,
      "retweet_count": "0",
      "retweeted": false,
      "source": "\u003ca href=\"http://www.hootsuite.com\" rel=\"nofollow\"\u003eHootsuite\u003c/a\u003e",
      "truncated": false
    },
    "wof:name": "Twitter message #120936718181474304",
    "wof:placetype": "custom"
  },
  "geometry": {"coordinates":[-122.386166,37.616356],"type":"Point"}
}
