{
  "type": "Feature",
  "properties": {
    "date:cessation_lower": "2014-10-07",
    "date:cessation_upper": "2014-10-07",
    "date:inception_lower": "2014-10-07",
    "date:inception_upper": "2014-10-07",
    "iso:country": "US",
    "sfomuseum:placetype": "tweet",
    "twitter:tweet": {
      "created": 1412712875,
      "created_at": "Tue Oct 07 20:14:35 +0000 2014",
      "display_text_range": [
        "0",
        "124"
      ],
      "entities": {
        "urls": [
          {
            "display_url": "instagram.com/p/t3OqabIQCu/",
            "expanded_url": "http://instagram.com/p/t3OqabIQCu/",
            "indices": [
              "102",
              "124"
            ],
            "url": "http://t.co/oRNvITZGkI"
          }
        ],
        "user_mentions": [
          {
            "id_str": "567344863",
            "indices": [
              "3",
              "12"
            ],
            "name": "Grace Stuart",
            "screen_name": "GraceStu"
          }
        ]
      },
      "favorite_count": "0",
      "favorited": false,
      "full_text": "RT @GraceStu: Wow, there's a museum in the terminal. Fun! @ San Francisco International Airport (SFO) http://t.co/oRNvITZGkI",
      "id_str": "519581573541154816",
      "lang": "en",
      "possibly_sensitive": false,
      "retweet_count": "0",
      "retweeted": false,
      "source": "\u003ca href=\"http://www.hootsuite.com\" rel=\"nofollow\"\u003eHootsuite\u003c/a\u003e",
      "truncated": false
    },
    "wof:name": "RT @GraceStu: Wow, there's a museum in the terminal. Fun! @ San Francisco International Airport (SFO) http://t.co/oRNvITZGkI",
    "wof:placetype": "custom",
    "wof:placetype_alt": [
      "tweet"
    ]
  },
  "geometry": {"coordinates":[-122.386166,37.616356],"type":"Point"}
}
