{
  "type": "Feature",
  "properties": {
    "sfomuseum:placetype": "tweet",
    "twitter:tweet": {
      "created": 1321643166,
      "created_at": "Fri Nov 18 19:06:06 +0000 2011",
      "display_text_range": [
        "0", 
        "127"
      ],
      "entities": {
        "urls": [
          {
            "display_url": "yfrog.com/gz7knezrj",
            "expanded_url": "http://yfrog.com/gz7knezrj",
            "indices": [
              "107", 
              "127"
            ],
            "url": "http://t.co/MKNyd3TQ"
          }
        ]
      },
      "favorite_count": "0",
      "favorited": false,
      "full_text": "How many of you had this Andy Warhol-designed album (one of many he did) of The Velvet Underground \u0026 Nico? http://t.co/MKNyd3TQ",
      "id_str": "137607530703618049",
      "lang": "en",
      "possibly_sensitive": false,
      "retweet_count": "0",
      "retweeted": false,
      "source": "\u003ca href=\"https://about.twitter.com/products/tweetdeck\" rel=\"nofollow\"\u003eTweetDeck\u003c/a\u003e",
      "truncated": false
    },
    "wof:name": "Twitter message #137607530703618049",
    "wof:placetype": "custom"
  },
  "geometry": {"coordinates":[-122.386166,37.616356],"type":"Point"}
}
