{
  "type": "Feature",
  "properties": {
    "sfomuseum:placetype": "tweet",
    "twitter:tweet": {
      "created": 1321985883,
      "created_at": "Tue Nov 22 18:18:03 +0000 2011",
      "display_text_range": [
        "0", 
        "134"
      ],
      "entities": {
      },
      "favorite_count": "0",
      "favorited": false,
      "full_text": "HA! A curator recounted buying \"Sgt. Pepper's Lonely Hearts Club Band\"  and coming home to discover he'd bought The Bee Gee's version!",
      "id_str": "139044988964192256",
      "lang": "en",
      "retweet_count": "0",
      "retweeted": false,
      "source": "\u003ca href=\"https://about.twitter.com/products/tweetdeck\" rel=\"nofollow\"\u003eTweetDeck\u003c/a\u003e",
      "truncated": false
    },
    "wof:name": "Twitter message #139044988964192256",
    "wof:placetype": "custom"
  },
  "geometry": {"coordinates":[-122.386166,37.616356],"type":"Point"}
}
