{
  "type": "Feature",
  "properties": {
    "date:cessation_lower": "2011-11-22",
    "date:cessation_upper": "2011-11-22",
    "date:inception_lower": "2011-11-22",
    "date:inception_upper": "2011-11-22",
    "iso:country": "US",
    "sfomuseum:placetype": "tweet",
    "twitter:tweet": {
      "created": 1321985883,
      "created_at": "Tue Nov 22 18:18:03 +0000 2011",
      "display_text_range": [
        "0",
        "134"
      ],
      "edit_info": {
        "initial": {
          "editTweetIds": [
            "139044988964192256"
          ],
          "editableUntil": "2011-11-22T18:48:03.357Z",
          "editsRemaining": "5",
          "isEditEligible": true
        }
      },
      "entities": {
      },
      "favorite_count": "0",
      "favorited": false,
      "full_text": "HA! A curator recounted buying \"Sgt. Pepper's Lonely Hearts Club Band\"  and coming home to discover he'd bought The Bee Gee's version!",
      "id_str": "139044988964192256",
      "lang": "en",
      "retweet_count": "0",
      "retweeted": false,
      "source": "\u003ca href=\"https://about.twitter.com/products/tweetdeck\" rel=\"nofollow\"\u003eTweetDeck\u003c/a\u003e",
      "truncated": false
    },
    "wof:name": "HA! A curator recounted buying \"Sgt. Pepper's Lonely Hearts Club Band\"  and coming home to discover he'd bought The Bee Gee's version!",
    "wof:placetype": "custom"
  },
  "geometry": {"coordinates":[-122.386166,37.616356],"type":"Point"}
}
