{
  "type": "Feature",
  "properties": {
    "date:cessation_lower": "2011-11-22",
    "date:cessation_upper": "2011-11-22",
    "date:inception_lower": "2011-11-22",
    "date:inception_upper": "2011-11-22",
    "iso:country": "US",
    "sfomuseum:placetype": "tweet",
    "twitter:tweet": {
      "created": 1322005314,
      "created_at": "Tue Nov 22 23:41:54 +0000 2011",
      "display_text_range": [
        "0",
        "64"
      ],
      "edit_info": {
        "initial": {
          "editTweetIds": [
            "139126487327580160"
          ],
          "editableUntil": "2011-11-23T00:11:54.081Z",
          "editsRemaining": "5",
          "isEditEligible": true
        }
      },
      "entities": {
        "user_mentions": [
          {
            "id_str": "19071963",
            "indices": [
              "0",
              "11"
            ],
            "name": "Reza Malekzadeh",
            "screen_name": "malekzadeh"
          }
        ]
      },
      "favorite_count": "0",
      "favorited": false,
      "full_text": "@malekzadeh Nice photo! Thanks for checking out Moto Bellissima!",
      "id_str": "139126487327580160",
      "in_reply_to_screen_name": "malekzadeh",
      "in_reply_to_status_id": "139095871311716352",
      "in_reply_to_status_id_str": "139095871311716352",
      "in_reply_to_user_id": "19071963",
      "in_reply_to_user_id_str": "19071963",
      "lang": "en",
      "retweet_count": "1",
      "retweeted": false,
      "source": "\u003ca href=\"http://www.hootsuite.com\" rel=\"nofollow\"\u003eHootsuite\u003c/a\u003e",
      "truncated": false
    },
    "wof:name": "@malekzadeh Nice photo! Thanks for checking out Moto Bellissima!",
    "wof:placetype": "custom"
  },
  "geometry": {"coordinates":[-122.386166,37.616356],"type":"Point"}
}
