{
  "type": "Feature",
  "properties": {
    "date:cessation_lower": "2021-05-08",
    "date:cessation_upper": "2021-05-08",
    "date:inception_lower": "2021-05-08",
    "date:inception_upper": "2021-05-08",
    "sfomuseum:placetype": "tweet",
    "twitter:tweet": {
      "created": 1620432509,
      "created_at": "Sat May 08 00:08:29 +0000 2021",
      "display_text_range": [
        "0",
        "99"
      ],
      "entities": {
      },
      "favorite_count": "4",
      "favorited": false,
      "full_text": "📸:\nMills Field Municipal Airport of San Francisco; May 7, 1927\nTransfer\n2011.032.0005, .0006, .0008",
      "id_str": "1390820864753471491",
      "in_reply_to_screen_name": "SFOMuseum",
      "in_reply_to_status_id": "1390820861683265536",
      "in_reply_to_status_id_str": "1390820861683265536",
      "in_reply_to_user_id": "116329337",
      "in_reply_to_user_id_str": "116329337",
      "lang": "en",
      "retweet_count": "0",
      "retweeted": false,
      "source": "\u003ca href=\"https://mobile.twitter.com\" rel=\"nofollow\"\u003eTwitter Web App\u003c/a\u003e",
      "truncated": false
    },
    "wof:name": "📸:\nMills Field Municipal Airport of San Francisco; May 7, 1927\nTransfer\n2011.032.0005, .0006, .0008",
    "wof:placetype": "custom"
  },
  "geometry": {"coordinates":[-122.386166,37.616356],"type":"Point"}
}
