{
  "type": "Feature",
  "properties": {
    "date:cessation_lower": "2023-10-24",
    "date:cessation_upper": "2023-10-24",
    "date:inception_lower": "2023-10-24",
    "date:inception_upper": "2023-10-24",
    "sfomuseum:placetype": "tweet",
    "twitter:tweet": {
      "created": 1698190101,
      "created_at": "Tue Oct 24 23:28:21 +0000 2023",
      "display_text_range": [
        "0",
        "267"
      ],
      "edit_info": {
        "initial": {
          "editTweetIds": [
            "1716959847105835383"
          ],
          "editableUntil": "2023-10-25T00:28:21.000Z",
          "editsRemaining": "5",
          "isEditEligible": false
        }
      },
      "entities": {
      },
      "favorite_count": "2",
      "favorited": false,
      "full_text": "📸:\n1. program: San Francisco Airport, Dedication of Airport Administration and Airline Terminal Building; 1937\nGift of John R. Barker\n2002.005.029\n\n2. negative: San Francisco Airport, aerial; early 1950s\nTransfer from San Francisco International Airport\n2011.032.0180",
      "id_str": "1716959847105835383",
      "in_reply_to_screen_name": "SFOMuseum",
      "in_reply_to_status_id": "1716959663403798966",
      "in_reply_to_status_id_str": "1716959663403798966",
      "in_reply_to_user_id": "116329337",
      "in_reply_to_user_id_str": "116329337",
      "lang": "en",
      "retweet_count": "0",
      "retweeted": false,
      "source": "\u003ca href=\"https://mobile.twitter.com\" rel=\"nofollow\"\u003eTwitter Web App\u003c/a\u003e",
      "truncated": false
    },
    "wof:name": "📸:\n1. program: San Francisco Airport, Dedication of Airport Administration and Airline Terminal Building; 1937\nGift of John R. Barker\n2002.005.029\n\n2. negative: San Francisco Airport, aerial; early 1950s\nTransfer from San Francisco International Airport\n2011.032.0180",
    "wof:placetype": "custom"
  },
  "geometry": {"coordinates":[-122.386166,37.616356],"type":"Point"}
}
