{
  "type": "Feature",
  "properties": {
    "sfomuseum:placetype": "tweet",
    "twitter:tweet": {
      "created": 1478658306,
      "created_at": "Wed Nov 09 02:25:06 +0000 2016",
      "display_text_range": [
        "0", 
        "162"
      ],
      "entities": {
        "hashtags": [
          {
            "indices": [
              "0", 
              "10"
            ],
            "text": "OnThisDay"
          }, 
          {
            "indices": [
              "30", 
              "36"
            ],
            "text": "PanAm"
          }, 
          {
            "indices": [
              "124", 
              "138"
            ],
            "text": "TravelTuesday"
          }
        ],
        "media": [
          {
            "display_url": "pic.twitter.com/FzsbJDETUU",
            "expanded_url": "https://twitter.com/SFOMuseum/status/796176760597544961/photo/1",
            "id_str": "796176755539247106",
            "indices": [
              "139", 
              "162"
            ],
            "media_url": "http://pbs.twimg.com/media/CwyWinRXAAIn0j0.jpg",
            "media_url_https": "https://pbs.twimg.com/media/CwyWinRXAAIn0j0.jpg",
            "sizes": {
              "large": {
                "h": "1154",
                "resize": "fit",
                "w": "2000"
              },
              "medium": {
                "h": "692",
                "resize": "fit",
                "w": "1200"
              },
              "small": {
                "h": "392",
                "resize": "fit",
                "w": "680"
              },
              "thumb": {
                "h": "150",
                "resize": "crop",
                "w": "150"
              }
            },
            "type": "photo",
            "url": "https://t.co/FzsbJDETUU"
          }
        ]
      },
      "extended_entities": {
        "media": [
          {
            "display_url": "pic.twitter.com/FzsbJDETUU",
            "expanded_url": "https://twitter.com/SFOMuseum/status/796176760597544961/photo/1",
            "id_str": "796176755539247106",
            "indices": [
              "139", 
              "162"
            ],
            "media_url": "http://pbs.twimg.com/media/CwyWinRXAAIn0j0.jpg",
            "media_url_https": "https://pbs.twimg.com/media/CwyWinRXAAIn0j0.jpg",
            "sizes": {
              "large": {
                "h": "1154",
                "resize": "fit",
                "w": "2000"
              },
              "medium": {
                "h": "692",
                "resize": "fit",
                "w": "1200"
              },
              "small": {
                "h": "392",
                "resize": "fit",
                "w": "680"
              },
              "thumb": {
                "h": "150",
                "resize": "crop",
                "w": "150"
              }
            },
            "type": "photo",
            "url": "https://t.co/FzsbJDETUU"
          }
        ]
      },
      "favorite_count": "7",
      "favorited": false,
      "full_text": "#OnThisDay in 1948, the first #PanAm airmail service to Barcelona, Spain departed from NY. Have you ever been to Barcelona? #TravelTuesday https://t.co/FzsbJDETUU",
      "id_str": "796176760597544961",
      "lang": "en",
      "possibly_sensitive": false,
      "retweet_count": "1",
      "retweeted": false,
      "source": "\u003ca href=\"http://www.hootsuite.com\" rel=\"nofollow\"\u003eHootsuite\u003c/a\u003e",
      "truncated": false
    },
    "wof:name": "Twitter message #796176760597544961",
    "wof:placetype": "custom"
  },
  "geometry": {"coordinates":[-122.386166,37.616356],"type":"Point"}
}
