{
  "type": "Feature",
  "properties": {
    "date:cessation_lower": "2021-03-03",
    "date:cessation_upper": "2021-03-03",
    "date:inception_lower": "2021-03-03",
    "date:inception_upper": "2021-03-03",
    "sfomuseum:placetype": "tweet",
    "twitter:tweet": {
      "created": 1614802176,
      "created_at": "Wed Mar 03 20:09:36 +0000 2021",
      "display_text_range": [
        "0",
        "207"
      ],
      "edit_info": {
        "initial": {
          "editTweetIds": [
            "1367205536781889538"
          ],
          "editableUntil": "2021-03-03T21:09:36.076Z",
          "editsRemaining": "5",
          "isEditEligible": true
        }
      },
      "entities": {
      },
      "favorite_count": "0",
      "favorited": false,
      "full_text": "@DevinMcCutchen It was never a part of our collection - it belonged to the Airport. Our collections scope doesn’t allow for *actual* planes. While we’re sad to see it go, we’re sure it will find a good home.",
      "id_str": "1367205536781889538",
      "in_reply_to_status_id": "1367203028986523649",
      "in_reply_to_status_id_str": "1367203028986523649",
      "in_reply_to_user_id": "377186587",
      "in_reply_to_user_id_str": "377186587",
      "lang": "en",
      "retweet_count": "0",
      "retweeted": false,
      "source": "\u003ca href=\"https://mobile.twitter.com\" rel=\"nofollow\"\u003eTwitter Web App\u003c/a\u003e",
      "truncated": false
    },
    "wof:name": "@DevinMcCutchen It was never a part of our collection - it belonged to the Airport. Our collections scope doesn’t allow for *actual* planes. While we’re sad to see it go, we’re sure it will find a good home.",
    "wof:placetype": "custom",
    "wof:placetype_alt": [
      "tweet"
    ]
  },
  "geometry": {"coordinates":[-122.386166,37.616356],"type":"Point"}
}
