{
  "type": "Feature",
  "properties": {
    "sfomuseum:placetype": "tweet",
    "twitter:tweet": {
      "created": 1383067714,
      "created_at": "Tue Oct 29 17:28:34 +0000 2013",
      "display_text_range": [
        "0", 
        "139"
      ],
      "entities": {
        "hashtags": [
          {
            "indices": [
              "130", 
              "139"
            ],
            "text": "maritime"
          }
        ],
        "urls": [
          {
            "display_url": "ow.ly/qi9pW",
            "expanded_url": "http://ow.ly/qi9pW",
            "indices": [
              "107", 
              "129"
            ],
            "url": "http://t.co/5CIYqlSWM4"
          }
        ]
      },
      "favorite_count": "0",
      "favorited": false,
      "full_text": "Sign of the times: an 1815 law requiring the display of ship names resulted in some beautiful name boards: http://t.co/5CIYqlSWM4 #maritime",
      "id_str": "395240758539988992",
      "lang": "en",
      "possibly_sensitive": false,
      "retweet_count": "0",
      "retweeted": false,
      "source": "\u003ca href=\"http://www.hootsuite.com\" rel=\"nofollow\"\u003eHootsuite\u003c/a\u003e",
      "truncated": false
    },
    "wof:name": "Twitter message #395240758539988992",
    "wof:placetype": "custom"
  },
  "geometry": {"coordinates":[-122.386166,37.616356],"type":"Point"}
}
