{
  "type": "Feature",
  "properties": {
    "sfomuseum:placetype": "tweet",
    "twitter:tweet": {
      "created": 1327344387,
      "created_at": "Mon Jan 23 18:46:27 +0000 2012",
      "display_text_range": [
        "0", 
        "129"
      ],
      "entities": {
        "urls": [
          {
            "display_url": "ow.ly/1EDMKf",
            "expanded_url": "http://ow.ly/1EDMKf",
            "indices": [
              "91", 
              "111"
            ],
            "url": "http://t.co/DticctHV"
          }
        ],
        "user_mentions": [
          {
            "id_str": "264326860",
            "indices": [
              "4", 
              "16"
            ],
            "name": "Babes At The Museum",
            "screen_name": "museumbabes"
          }
        ]
      },
      "favorite_count": "0",
      "favorited": false,
      "full_text": "Hey @museumbabes! We're the only full museum, but many airports have exhibit programs. See http://t.co/DticctHV for a short list.",
      "id_str": "161520185507987457",
      "in_reply_to_screen_name": "museumbabes",
      "in_reply_to_status_id": "161513896811839488",
      "in_reply_to_status_id_str": "161513896811839488",
      "in_reply_to_user_id": "264326860",
      "in_reply_to_user_id_str": "264326860",
      "lang": "en",
      "possibly_sensitive": false,
      "retweet_count": "0",
      "retweeted": false,
      "source": "\u003ca href=\"http://www.hootsuite.com\" rel=\"nofollow\"\u003eHootsuite\u003c/a\u003e",
      "truncated": false
    },
    "wof:name": "Twitter message #161520185507987457",
    "wof:placetype": "custom"
  },
  "geometry": {"coordinates":[-122.386166,37.616356],"type":"Point"}
}
