{
  "type": "Feature",
  "properties": {
    "date:cessation_lower": "2016-08-03",
    "date:cessation_upper": "2016-08-03",
    "date:inception_lower": "2016-08-03",
    "date:inception_upper": "2016-08-03",
    "iso:country": "US",
    "sfomuseum:placetype": "tweet",
    "twitter:tweet": {
      "created": 1470255612,
      "created_at": "Wed Aug 03 20:20:12 +0000 2016",
      "display_text_range": [
        "0",
        "138"
      ],
      "edit_info": {
        "initial": {
          "editTweetIds": [
            "760933307752259587"
          ],
          "editableUntil": "2016-08-03T20:50:12.682Z",
          "editsRemaining": "5",
          "isEditEligible": true
        }
      },
      "entities": {
        "hashtags": [
          {
            "indices": [
              "124",
              "138"
            ],
            "text": "ArtNouveauSFO"
          }
        ],
        "urls": [
          {
            "display_url": "bit.ly/ArtNouveauSFO",
            "expanded_url": "http://bit.ly/ArtNouveauSFO",
            "indices": [
              "100",
              "123"
            ],
            "url": "https://t.co/xopkABn31u"
          }
        ]
      },
      "favorite_count": "1",
      "favorited": false,
      "full_text": "See more Art Nouveau in \"The Allure of Art Nouveau\" on display, pre-security, in the Intl Terminal. https://t.co/xopkABn31u #ArtNouveauSFO",
      "id_str": "760933307752259587",
      "lang": "en",
      "possibly_sensitive": false,
      "retweet_count": "0",
      "retweeted": false,
      "source": "\u003ca href=\"http://www.hootsuite.com\" rel=\"nofollow\"\u003eHootsuite\u003c/a\u003e",
      "truncated": false
    },
    "wof:name": "See more Art Nouveau in \"The Allure of Art Nouveau\" on display, pre-security, in the Intl Terminal. https://t.co/xopkABn31u #ArtNouveauSFO",
    "wof:placetype": "custom"
  },
  "geometry": {"coordinates":[-122.386166,37.616356],"type":"Point"}
}
