{
  "type": "Feature",
  "properties": {
    "date:cessation_lower": "2020-10-28",
    "date:cessation_upper": "2020-10-28",
    "date:inception_lower": "2020-10-28",
    "date:inception_upper": "2020-10-28",
    "sfomuseum:placetype": "tweet",
    "twitter:tweet": {
      "created": 1603911034,
      "created_at": "Wed Oct 28 18:50:34 +0000 2020",
      "display_text_range": [
        "0",
        "139"
      ],
      "edit_info": {
        "initial": {
          "editTweetIds": [
            "1321524778256064513"
          ],
          "editableUntil": "2020-10-28T19:50:34.536Z",
          "editsRemaining": "5",
          "isEditEligible": true
        }
      },
      "entities": {
        "hashtags": [
          {
            "indices": [
              "121",
              "127"
            ],
            "text": "An124"
          },
          {
            "indices": [
              "128",
              "135"
            ],
            "text": "AvGeek"
          }
        ],
        "user_mentions": [
          {
            "id_str": "16408759",
            "indices": [
              "3",
              "10"
            ],
            "name": "San Francisco International Airport (SFO) ✈️",
            "screen_name": "flySFO"
          }
        ]
      },
      "favorite_count": "0",
      "favorited": false,
      "full_text": "RT @flySFO: 🛫 It's not every day that we see an these at SFO, although we've had quite a few visit the Airport recently! #An124 #AvGeek\n\n🎥…",
      "id_str": "1321524778256064513",
      "lang": "en",
      "retweet_count": "0",
      "retweeted": false,
      "source": "\u003ca href=\"https://mobile.twitter.com\" rel=\"nofollow\"\u003eTwitter Web App\u003c/a\u003e",
      "truncated": false
    },
    "wof:name": "RT @flySFO: 🛫 It's not every day that we see an these at SFO, although we've had quite a few visit the Airport recently! #An124 #AvGeek\n\n🎥…",
    "wof:placetype": "custom"
  },
  "geometry": {"coordinates":[-122.386166,37.616356],"type":"Point"}
}
