{
  "type": "Feature",
  "properties": {
    "sfomuseum:placetype": "tweet",
    "twitter:tweet": {
      "created": 1344034162,
      "created_at": "Fri Aug 03 22:49:22 +0000 2012",
      "display_text_range": [
        "0", 
        "102"
      ],
      "entities": {
        "hashtags": [
          {
            "indices": [
              "87", 
              "102"
            ],
            "text": "MuseumOlympics"
          }
        ],
        "urls": [
          {
            "display_url": "bit.ly/N4bAoG",
            "expanded_url": "http://bit.ly/N4bAoG",
            "indices": [
              "66", 
              "86"
            ],
            "url": "http://t.co/u90jLY8r"
          }
        ]
      },
      "favorite_count": "0",
      "favorited": false,
      "full_text": "Ooooh, rare double event qualifier for dressage \u0026amp; water polo: http://t.co/u90jLY8r #MuseumOlympics",
      "id_str": "231522173204979712",
      "lang": "en",
      "possibly_sensitive": false,
      "retweet_count": "1",
      "retweeted": false,
      "source": "\u003ca href=\"https://about.twitter.com/products/tweetdeck\" rel=\"nofollow\"\u003eTweetDeck\u003c/a\u003e",
      "truncated": false
    },
    "wof:name": "Twitter message #231522173204979712",
    "wof:placetype": "custom"
  },
  "geometry": {"coordinates":[-122.386166,37.616356],"type":"Point"}
}
