{
  "type": "Feature",
  "properties": {
    "date:cessation_lower": "2022-01-25",
    "date:cessation_upper": "2022-01-25",
    "date:inception_lower": "2022-01-25",
    "date:inception_upper": "2022-01-25",
    "sfomuseum:placetype": "tweet",
    "twitter:tweet": {
      "created": 1643145688,
      "created_at": "Tue Jan 25 21:21:28 +0000 2022",
      "display_text_range": [
        "0",
        "139"
      ],
      "edit_info": {
        "initial": {
          "editTweetIds": [
            "1486086842369785856"
          ],
          "editableUntil": "2022-01-25T21:51:28.036Z",
          "editsRemaining": "5",
          "isEditEligible": true
        }
      },
      "entities": {
        "user_mentions": [
          {
            "id_str": "14848513",
            "indices": [
              "3",
              "15"
            ],
            "name": "National Air and Space Museum",
            "screen_name": "airandspace"
          }
        ]
      },
      "favorite_count": "0",
      "favorited": false,
      "full_text": "RT @airandspace: Did you know that Amelia Earhart and Eleanor Roosevelt were friends? On a spring evening in 1933, Amelia Earhart took the…",
      "id_str": "1486086842369785856",
      "lang": "en",
      "retweet_count": "0",
      "retweeted": false,
      "source": "\u003ca href=\"https://mobile.twitter.com\" rel=\"nofollow\"\u003eTwitter Web App\u003c/a\u003e",
      "truncated": false
    },
    "wof:name": "RT @airandspace: Did you know that Amelia Earhart and Eleanor Roosevelt were friends? On a spring evening in 1933, Amelia Earhart took the…",
    "wof:placetype": "custom"
  },
  "geometry": {"coordinates":[-122.386166,37.616356],"type":"Point"}
}
