{
  "type": "Feature",
  "properties": {
    "sfomuseum:placetype": "tweet",
    "twitter:tweet": {
      "created": 1460396275,
      "created_at": "Mon Apr 11 17:37:55 +0000 2016",
      "display_text_range": [
        "0", 
        "108"
      ],
      "entities": {
        "urls": [
          {
            "display_url": "fb.me/5PKduCUFj",
            "expanded_url": "http://fb.me/5PKduCUFj",
            "indices": [
              "85", 
              "108"
            ],
            "url": "https://t.co/hDKFSow0av"
          }
        ],
        "user_mentions": [
          {
            "id_str": "95746689",
            "indices": [
              "3", 
              "16"
            ],
            "name": "panamhistory",
            "screen_name": "panamhistory"
          }
        ]
      },
      "favorite_count": "0",
      "favorited": false,
      "full_text": "RT @panamhistory: Looking ahead to future trends for inflight experiences in 1945... https://t.co/hDKFSow0av",
      "id_str": "719580251529981953",
      "lang": "en",
      "possibly_sensitive": false,
      "retweet_count": "0",
      "retweeted": false,
      "source": "\u003ca href=\"http://twitter.com\" rel=\"nofollow\"\u003eTwitter Web Client\u003c/a\u003e",
      "truncated": false
    },
    "wof:name": "Twitter message #719580251529981953",
    "wof:placetype": "custom"
  },
  "geometry": {"coordinates":[-122.386166,37.616356],"type":"Point"}
}
