{
  "type": "Feature",
  "properties": {
    "date:cessation_lower": "2022-08-02",
    "date:cessation_upper": "2022-08-02",
    "date:inception_lower": "2022-08-02",
    "date:inception_upper": "2022-08-02",
    "sfomuseum:placetype": "tweet",
    "twitter:tweet": {
      "created": 1659452401,
      "created_at": "Tue Aug 02 15:00:01 +0000 2022",
      "display_text_range": [
        "0",
        "185"
      ],
      "edit_info": {
        "initial": {
          "editTweetIds": [
            "1554482153961844736"
          ],
          "editableUntil": "2022-08-02T15:30:01.000Z",
          "editsRemaining": "5",
          "isEditEligible": true
        }
      },
      "entities": {
        "urls": [
          {
            "display_url": "SFOMuseum.org",
            "expanded_url": "http://www.SFOMuseum.org",
            "indices": [
              "162",
              "185"
            ],
            "url": "https://t.co/6kBaiGiHxZ"
          }
        ]
      },
      "favorite_count": "0",
      "favorited": false,
      "full_text": "The Aviation Museum \u0026amp; Library will close today at 1:00pm for a private event. All other exhibitions are open. For more information, please visit our website: https://t.co/6kBaiGiHxZ",
      "id_str": "1554482153961844736",
      "lang": "en",
      "possibly_sensitive": false,
      "retweet_count": "0",
      "retweeted": false,
      "source": "\u003ca href=\"https://mobile.twitter.com\" rel=\"nofollow\"\u003eTwitter Web App\u003c/a\u003e",
      "truncated": false
    },
    "wof:name": "The Aviation Museum \u0026amp; Library will close today at 1:00pm for a private event. All other exhibitions are open. For more information, please visit our website: https://t.co/6kBaiGiHxZ",
    "wof:placetype": "custom"
  },
  "geometry": {"coordinates":[-122.386166,37.616356],"type":"Point"}
}
