{
  "type": "Feature",
  "properties": {
    "sfomuseum:placetype": "tweet",
    "twitter:tweet": {
      "created": 1324658595,
      "created_at": "Fri Dec 23 16:43:15 +0000 2011",
      "display_text_range": [
        "0", 
        "94"
      ],
      "entities": {
        "urls": [
          {
            "display_url": "path.com/p/35Txzz",
            "expanded_url": "http://path.com/p/35Txzz",
            "indices": [
              "74", 
              "94"
            ],
            "url": "http://t.co/0L1Py6Cp"
          }
        ],
        "user_mentions": [
          {
            "id_str": "1836981",
            "indices": [
              "3", 
              "8"
            ],
            "name": "Travis Cole",
            "screen_name": "kelp"
          }
        ]
      },
      "favorite_count": "0",
      "favorited": false,
      "full_text": "RT @kelp: SFO Terminal 3 has a pretty cool display of TV history. [pic] — http://t.co/0L1Py6Cp",
      "id_str": "150255154753568768",
      "lang": "en",
      "possibly_sensitive": false,
      "retweet_count": "0",
      "retweeted": false,
      "source": "\u003ca href=\"http://www.hootsuite.com\" rel=\"nofollow\"\u003eHootsuite\u003c/a\u003e",
      "truncated": false
    },
    "wof:name": "Twitter message #150255154753568768",
    "wof:placetype": "custom"
  },
  "geometry": {"coordinates":[-122.386166,37.616356],"type":"Point"}
}
