{
  "type": "Feature",
  "properties": {
    "date:cessation_lower": "2012-08-24",
    "date:cessation_upper": "2012-08-24",
    "date:inception_lower": "2012-08-24",
    "date:inception_upper": "2012-08-24",
    "iso:country": "US",
    "sfomuseum:placetype": "tweet",
    "twitter:hashtags": [
      "aviation",
      "art"
    ],
    "twitter:tweet": {
      "created": 1345849889,
      "created_at": "Fri Aug 24 23:11:29 +0000 2012",
      "display_text_range": [
        "0",
        "144"
      ],
      "edit_info": {
        "initial": {
          "editTweetIds": [
            "239137885889118209"
          ],
          "editableUntil": "2012-08-25T00:11:29.620Z",
          "editsRemaining": "5",
          "isEditEligible": true
        }
      },
      "entities": {
        "hashtags": [
          {
            "indices": [
              "105",
              "114"
            ],
            "text": "aviation"
          },
          {
            "indices": [
              "128",
              "132"
            ],
            "text": "art"
          }
        ],
        "user_mentions": [
          {
            "id_str": "260907612",
            "indices": [
              "31",
              "38"
            ],
            "name": "United Airlines",
            "screen_name": "united"
          }
        ]
      },
      "favorite_count": "0",
      "favorited": false,
      "full_text": "22 exhibits, to be exact :) MT @united: So many great guesses to our question. SFO is the airport w/ the #aviation museum \u0026amp; #art exhibition.",
      "id_str": "239137885889118209",
      "lang": "en",
      "retweet_count": "1",
      "retweeted": false,
      "source": "\u003ca href=\"https://about.twitter.com/products/tweetdeck\" rel=\"nofollow\"\u003eTweetDeck\u003c/a\u003e",
      "truncated": false
    },
    "twitter:user_mentions": [
      "united"
    ],
    "wof:name": "22 exhibits, to be exact :) MT @united: So many great guesses to our question. SFO is the airport w/ the #aviation museum \u0026amp; #art exhibition.",
    "wof:placetype": "custom",
    "wof:placetype_alt": [
      "tweet"
    ]
  },
  "geometry": {"coordinates":[-122.386166,37.616356],"type":"Point"}
}
