{
  "type": "Feature",
  "properties": {
    "sfomuseum:placetype": "tweet",
    "twitter:tweet": {
      "created": 1485490205,
      "created_at": "Fri Jan 27 04:10:05 +0000 2017",
      "display_text_range": [
        "0", 
        "126"
      ],
      "entities": {
        "hashtags": [
          {
            "indices": [
              "5", 
              "19"
            ],
            "text": "GamesofChance"
          }
        ],
        "urls": [
          {
            "display_url": "bit.ly/GamesofChance",
            "expanded_url": "http://bit.ly/GamesofChance",
            "indices": [
              "103", 
              "126"
            ],
            "url": "https://t.co/SGiUJdGr06"
          }
        ]
      },
      "favorite_count": "0",
      "favorited": false,
      "full_text": "See \"#GamesofChance: Gambling Devices of the Mechanical Age\" on display, post-security, in Terminal 3. https://t.co/SGiUJdGr06",
      "id_str": "824831821062012929",
      "lang": "en",
      "possibly_sensitive": false,
      "retweet_count": "0",
      "retweeted": false,
      "source": "\u003ca href=\"http://www.hootsuite.com\" rel=\"nofollow\"\u003eHootsuite\u003c/a\u003e",
      "truncated": false
    },
    "wof:name": "Twitter message #824831821062012929",
    "wof:placetype": "custom"
  },
  "geometry": {"coordinates":[-122.386166,37.616356],"type":"Point"}
}
