{
  "type": "Feature",
  "properties": {
    "date:cessation_lower": "2019-01-08",
    "date:cessation_upper": "2019-01-08",
    "date:inception_lower": "2019-01-08",
    "date:inception_upper": "2019-01-08",
    "iso:country": "US",
    "sfomuseum:placetype": "tweet",
    "twitter:tweet": {
      "created": 1546969642,
      "created_at": "Tue Jan 08 17:47:22 +0000 2019",
      "display_text_range": [
        "0",
        "139"
      ],
      "edit_info": {
        "initial": {
          "editTweetIds": [
            "1082695271656509440"
          ],
          "editableUntil": "2019-01-08T18:47:22.925Z",
          "editsRemaining": "5",
          "isEditEligible": true
        }
      },
      "entities": {
        "user_mentions": [
          {
            "id_str": "16408759",
            "indices": [
              "3",
              "10"
            ],
            "name": "San Francisco International Airport (SFO) ✈️",
            "screen_name": "flySFO"
          }
        ]
      },
      "favorite_count": "0",
      "favorited": false,
      "full_text": "RT @flySFO: There's still time left to enter! Enter for a chance to win one of two prizes a GoPro Hero 7, or our Grand Prize of a $200 SFO…",
      "id_str": "1082695271656509440",
      "lang": "en",
      "retweet_count": "0",
      "retweeted": false,
      "source": "\u003ca href=\"http://twitter.com\" rel=\"nofollow\"\u003eTwitter Web Client\u003c/a\u003e",
      "truncated": false
    },
    "twitter:user_mentions": [
      "flySFO"
    ],
    "wof:name": "RT @flySFO: There's still time left to enter! Enter for a chance to win one of two prizes a GoPro Hero 7, or our Grand Prize of a $200 SFO…",
    "wof:placetype": "custom"
  },
  "geometry": {"coordinates":[-122.386166,37.616356],"type":"Point"}
}
