{
  "type": "Feature",
  "properties": {
    "sfomuseum:placetype": "tweet",
    "twitter:tweet": {
      "created": 1546969642,
      "created_at": "Tue Jan 08 17:47:22 +0000 2019",
      "display_text_range": [
        "0", 
        "139"
      ],
      "entities": {
        "user_mentions": [
          {
            "id_str": "16408759",
            "indices": [
              "3", 
              "10"
            ],
            "name": "San Francisco International Airport (SFO) ✈️",
            "screen_name": "flySFO"
          }
        ]
      },
      "favorite_count": "0",
      "favorited": false,
      "full_text": "RT @flySFO: There's still time left to enter! Enter for a chance to win one of two prizes a GoPro Hero 7, or our Grand Prize of a $200 SFO…",
      "id_str": "1082695271656509440",
      "lang": "en",
      "retweet_count": "0",
      "retweeted": false,
      "source": "\u003ca href=\"http://twitter.com\" rel=\"nofollow\"\u003eTwitter Web Client\u003c/a\u003e",
      "truncated": false
    },
    "wof:name": "Twitter message #1082695271656509440",
    "wof:placetype": "custom"
  },
  "geometry": {"coordinates":[-122.386166,37.616356],"type":"Point"}
}
