{
  "type": "Feature",
  "properties": {
    "date:cessation_lower": "2016-07-27",
    "date:cessation_upper": "2016-07-27",
    "date:inception_lower": "2016-07-27",
    "date:inception_upper": "2016-07-27",
    "sfomuseum:placetype": "tweet",
    "twitter:tweet": {
      "created": 1469660963,
      "created_at": "Wed Jul 27 23:09:23 +0000 2016",
      "display_text_range": [
        "0",
        "140"
      ],
      "edit_info": {
        "initial": {
          "editTweetIds": [
            "758439168586506240"
          ],
          "editableUntil": "2016-07-28T00:09:23.566Z",
          "editsRemaining": "5",
          "isEditEligible": true
        }
      },
      "entities": {
        "user_mentions": [
          {
            "id_str": "25579926",
            "indices": [
              "3",
              "11"
            ],
            "name": "🛫Kathryn Creedy🛫",
            "screen_name": "kcreedy"
          },
          {
            "id_str": "15867443",
            "indices": [
              "76",
              "80"
            ],
            "name": "EAA",
            "screen_name": "EAA"
          },
          {
            "id_str": "6707812",
            "indices": [
              "119",
              "128"
            ],
            "name": "Aero-News Network",
            "screen_name": "AeroNews"
          }
        ]
      },
      "favorite_count": "0",
      "favorited": false,
      "full_text": "RT @kcreedy: How cool is this? Estimated 1000 women joined for WomenVenture @EAA. Photog:Erin Brueggen. WASPs in front @AeroNews https://t.…",
      "id_str": "758439168586506240",
      "lang": "en",
      "retweet_count": "0",
      "retweeted": false,
      "source": "\u003ca href=\"http://www.hootsuite.com\" rel=\"nofollow\"\u003eHootsuite\u003c/a\u003e",
      "truncated": false
    },
    "twitter:user_mentions": [
      "kcreedy",
      "EAA",
      "AeroNews"
    ],
    "wof:name": "RT @kcreedy: How cool is this? Estimated 1000 women joined for WomenVenture @EAA. Photog:Erin Brueggen. WASPs in front @AeroNews https://t.…",
    "wof:placetype": "custom"
  },
  "geometry": {"coordinates":[-122.386166,37.616356],"type":"Point"}
}
