{
  "type": "Feature",
  "properties": {
    "date:cessation_lower":"2017-03-08",
    "date:cessation_upper":"2017-03-08",
    "date:inception_lower":"2017-03-08",
    "date:inception_upper":"2017-03-08",
    "iso:country":"US",
    "sfomuseum:placetype":"tweet",
    "twitter:tweet":{
        "created":1489002832,
        "created_at":"Wed Mar 08 19:53:52 +0000 2017",
        "display_text_range":[
            "0",
            "140"
        ],
        "entities":{
            "hashtags":[
                {
                    "indices":[
                        "114",
                        "133"
                    ],
                    "text":"WomensHistoryMonth"
                }
            ],
            "user_mentions":[
                {
                    "id_str":"160946337",
                    "indices":[
                        "3",
                        "11"
                    ],
                    "name":"The FAA \u2708\ufe0f",
                    "screen_name":"FAANews"
                }
            ]
        },
        "favorite_count":"0",
        "favorited":false,
        "full_text":"RT @FAANews: Today we honor aviator Amelia Earhart who was the first woman to fly solo across the Atlantic Ocean. #WomensHistoryMonth https\u2026",
        "id_str":"839564847226331136",
        "lang":"en",
        "retweet_count":"0",
        "retweeted":false,
        "source":"<a href=\"http://twitter.com\" rel=\"nofollow\">Twitter Web Client</a>",
        "truncated":false
    },
    "wof:name":"RT @FAANews: Today we honor aviator Amelia Earhart who was the first woman to fly solo across the Atlantic Ocean. #WomensHistoryMonth https\u2026",
    "wof:placetype":"custom"
},
  "geometry": {"coordinates":[-122.386166,37.616356],"type":"Point"}
}