{
  "type": "Feature",
  "properties": {
    "date:cessation_lower":"2016-07-07",
    "date:cessation_upper":"2016-07-07",
    "date:inception_lower":"2016-07-07",
    "date:inception_upper":"2016-07-07",
    "iso:country":"US",
    "sfomuseum:placetype":"tweet",
    "twitter:tweet":{
        "created":1467910994,
        "created_at":"Thu Jul 07 17:03:14 +0000 2016",
        "display_text_range":[
            "0",
            "61"
        ],
        "entities":{
            "hashtags":[
                {
                    "indices":[
                        "33",
                        "37"
                    ],
                    "text":"SFO"
                }
            ],
            "urls":[
                {
                    "display_url":"twitter.com/cjmcginnis/sta\u2026",
                    "expanded_url":"https://twitter.com/cjmcginnis/status/751091399357968384",
                    "indices":[
                        "38",
                        "61"
                    ],
                    "url":"https://t.co/3f1AnfppLx"
                }
            ],
            "user_mentions":[
                {
                    "id_str":"16408759",
                    "indices":[
                        "25",
                        "32"
                    ],
                    "name":"San Francisco International Airport (SFO) \u2708\ufe0f",
                    "screen_name":"flySFO"
                }
            ]
        },
        "favorite_count":"3",
        "favorited":false,
        "full_text":"Thanks for featuring us! @flySFO #SFO https://t.co/3f1AnfppLx",
        "id_str":"751099264323821570",
        "lang":"en",
        "possibly_sensitive":false,
        "retweet_count":"1",
        "retweeted":false,
        "source":"<a href=\"http://twitter.com\" rel=\"nofollow\">Twitter Web Client</a>",
        "truncated":false
    },
    "wof:name":"Thanks for featuring us! @flySFO #SFO https://t.co/3f1AnfppLx",
    "wof:placetype":"custom"
},
  "geometry": {"coordinates":[-122.386166,37.616356],"type":"Point"}
}