{
  "type": "Feature",
  "properties": {
    "sfomuseum:placetype": "tweet",
    "twitter:tweet": {
      "created": 1350683511,
      "created_at": "Fri Oct 19 21:51:51 +0000 2012",
      "display_text_range": [
        "0", 
        "144"
      ],
      "entities": {
        "hashtags": [
          {
            "indices": [
              "46", 
              "52"
            ],
            "text": "pratx"
          }, 
          {
            "indices": [
              "88", 
              "98"
            ],
            "text": "SFOmuseum"
          }, 
          {
            "indices": [
              "99", 
              "112"
            ],
            "text": "FormFunction"
          }
        ],
        "urls": [
          {
            "display_url": "bit.ly/VdsYau",
            "expanded_url": "http://bit.ly/VdsYau",
            "indices": [
              "124", 
              "144"
            ],
            "url": "http://t.co/puE6fLYd"
          }
        ],
        "user_mentions": [
          {
            "id_str": "76868796",
            "indices": [
              "38", 
              "44"
            ],
            "name": "Prateesh Satsangi",
            "screen_name": "Pratx"
          }
        ]
      },
      "favorite_count": "0",
      "favorited": false,
      "full_text": "Thanks! We're glad you enjoyed it! RT @Pratx: #pratx Beautiful exhibition @ SFO airport #SFOmuseum #FormFunction\u0026amp;Beauty http://t.co/puE6fLYd",
      "id_str": "259411564195627009",
      "lang": "en",
      "possibly_sensitive": false,
      "retweet_count": "0",
      "retweeted": false,
      "source": "\u003ca href=\"https://about.twitter.com/products/tweetdeck\" rel=\"nofollow\"\u003eTweetDeck\u003c/a\u003e",
      "truncated": false
    },
    "wof:name": "Twitter message #259411564195627009",
    "wof:placetype": "custom"
  },
  "geometry": {"coordinates":[-122.386166,37.616356],"type":"Point"}
}
