{
  "type": "Feature",
  "properties": {
    "sfomuseum:placetype": "tweet",
    "twitter:tweet": {
      "created": 1438977681,
      "created_at": "Fri Aug 07 20:01:21 +0000 2015",
      "display_text_range": [
        "0", 
        "130"
      ],
      "entities": {
        "hashtags": [
          {
            "indices": [
              "93", 
              "107"
            ],
            "text": "MingeiFolkArt"
          }
        ],
        "media": [
          {
            "display_url": "pic.twitter.com/la5kQa6BcQ",
            "expanded_url": "https://twitter.com/SFOMuseum/status/629744156471115777/photo/1",
            "id_str": "629744155837767680",
            "indices": [
              "108", 
              "130"
            ],
            "media_url": "http://pbs.twimg.com/media/CL1M-SQWoAA5roz.jpg",
            "media_url_https": "https://pbs.twimg.com/media/CL1M-SQWoAA5roz.jpg",
            "sizes": {
              "large": {
                "h": "2048",
                "resize": "fit",
                "w": "1536"
              },
              "medium": {
                "h": "1200",
                "resize": "fit",
                "w": "900"
              },
              "small": {
                "h": "680",
                "resize": "fit",
                "w": "510"
              },
              "thumb": {
                "h": "150",
                "resize": "crop",
                "w": "150"
              }
            },
            "type": "photo",
            "url": "http://t.co/la5kQa6BcQ"
          }
        ]
      },
      "extended_entities": {
        "media": [
          {
            "display_url": "pic.twitter.com/la5kQa6BcQ",
            "expanded_url": "https://twitter.com/SFOMuseum/status/629744156471115777/photo/1",
            "id_str": "629744155837767680",
            "indices": [
              "108", 
              "130"
            ],
            "media_url": "http://pbs.twimg.com/media/CL1M-SQWoAA5roz.jpg",
            "media_url_https": "https://pbs.twimg.com/media/CL1M-SQWoAA5roz.jpg",
            "sizes": {
              "large": {
                "h": "2048",
                "resize": "fit",
                "w": "1536"
              },
              "medium": {
                "h": "1200",
                "resize": "fit",
                "w": "900"
              },
              "small": {
                "h": "680",
                "resize": "fit",
                "w": "510"
              },
              "thumb": {
                "h": "150",
                "resize": "crop",
                "w": "150"
              }
            },
            "type": "photo",
            "url": "http://t.co/la5kQa6BcQ"
          }
        ]
      },
      "favorite_count": "0",
      "favorited": false,
      "full_text": "This intricate basket has a very intricate mount which takes a steady patient hand to mount. #MingeiFolkArt http://t.co/la5kQa6BcQ",
      "id_str": "629744156471115777",
      "lang": "en",
      "possibly_sensitive": false,
      "retweet_count": "1",
      "retweeted": false,
      "source": "\u003ca href=\"http://www.hootsuite.com\" rel=\"nofollow\"\u003eHootsuite\u003c/a\u003e",
      "truncated": false
    },
    "wof:name": "Twitter message #629744156471115777",
    "wof:placetype": "custom"
  },
  "geometry": {"coordinates":[-122.386166,37.616356],"type":"Point"}
}
