{
  "type": "Feature",
  "properties": {
    "date:cessation_lower": "2022-05-05",
    "date:cessation_upper": "2022-05-05",
    "date:inception_lower": "2022-05-05",
    "date:inception_upper": "2022-05-05",
    "sfomuseum:placetype": "tweet",
    "twitter:tweet": {
      "created": 1651794308,
      "created_at": "Thu May 05 23:45:08 +0000 2022",
      "display_text_range": [
        "0",
        "274"
      ],
      "edit_info": {
        "initial": {
          "editTweetIds": [
            "1522361784463593472"
          ],
          "editableUntil": "2022-05-06T00:15:08.000Z",
          "editsRemaining": "5",
          "isEditEligible": true
        }
      },
      "entities": {
      },
      "favorite_count": "0",
      "favorited": false,
      "full_text": "📸 1/2:\npostcard: Eastern Air Transport; 1930s\nGift of Captain Jon Simmonds\n2015.057.348\n\npostcard: Eastern Air Lines; Early 1950s \nGift of Thomas G. Dragges\n2014.095.060\n\npocket calendar: Eastern Air Lines, Douglas DC-8B, 1961; 1961\nGift of Captain Jon Simmonds\n2015.057.529",
      "id_str": "1522361784463593472",
      "in_reply_to_screen_name": "SFOMuseum",
      "in_reply_to_status_id": "1522361782332911616",
      "in_reply_to_status_id_str": "1522361782332911616",
      "in_reply_to_user_id": "116329337",
      "in_reply_to_user_id_str": "116329337",
      "lang": "en",
      "retweet_count": "0",
      "retweeted": false,
      "source": "\u003ca href=\"https://mobile.twitter.com\" rel=\"nofollow\"\u003eTwitter Web App\u003c/a\u003e",
      "truncated": false
    },
    "wof:name": "📸 1/2:\npostcard: Eastern Air Transport; 1930s\nGift of Captain Jon Simmonds\n2015.057.348\n\npostcard: Eastern Air Lines; Early 1950s \nGift of Thomas G. Dragges\n2014.095.060\n\npocket calendar: Eastern Air Lines, Douglas DC-8B, 1961; 1961\nGift of Captain Jon Simmonds\n2015.057.529",
    "wof:placetype": "custom"
  },
  "geometry": {"coordinates":[-122.386166,37.616356],"type":"Point"}
}
