{
  "type": "Feature",
  "properties": {
    "sfomuseum:placetype": "tweet",
    "twitter:tweet": {
      "created": 1465576868,
      "created_at": "Fri Jun 10 16:41:08 +0000 2016",
      "display_text_range": [
        "0", 
        "140"
      ],
      "entities": {
        "hashtags": [
          {
            "indices": [
              "32", 
              "39"
            ],
            "text": "wowair"
          }
        ],
        "user_mentions": [
          {
            "id_str": "399388492",
            "indices": [
              "3", 
              "11"
            ],
            "name": "WOW air",
            "screen_name": "wow_air"
          }, 
          {
            "id_str": "16408759",
            "indices": [
              "100", 
              "107"
            ],
            "name": "San Francisco International Airport (SFO) ✈️",
            "screen_name": "flySFO"
          }
        ]
      },
      "favorite_count": "0",
      "favorited": false,
      "full_text": "RT @wow_air: Here you can see a #wowair Airbus A330 landing at San Francisco International Airport (@flySFO) for the first time! https://t.…",
      "id_str": "741309231412973568",
      "lang": "en",
      "retweet_count": "0",
      "retweeted": false,
      "source": "\u003ca href=\"http://www.hootsuite.com\" rel=\"nofollow\"\u003eHootsuite\u003c/a\u003e",
      "truncated": false
    },
    "wof:name": "Twitter message #741309231412973568",
    "wof:placetype": "custom"
  },
  "geometry": {"coordinates":[-122.386166,37.616356],"type":"Point"}
}
