{
  "type": "Feature",
  "properties": {
    "date:cessation_lower": "2021-02-09",
    "date:cessation_upper": "2021-02-09",
    "date:inception_lower": "2021-02-09",
    "date:inception_upper": "2021-02-09",
    "sfomuseum:placetype": "tweet",
    "twitter:tweet": {
      "created": 1612899756,
      "created_at": "Tue Feb 09 19:42:36 +0000 2021",
      "display_text_range": [
        "0",
        "276"
      ],
      "entities": {
        "user_mentions": [
          {
            "id_str": "16408759",
            "indices": [
              "144",
              "151"
            ],
            "name": "San Francisco International Airport (SFO) ✈️😷",
            "screen_name": "flySFO"
          },
          {
            "id_str": "16408759",
            "indices": [
              "225",
              "232"
            ],
            "name": "San Francisco International Airport (SFO) ✈️😷",
            "screen_name": "flySFO"
          }
        ]
      },
      "favorite_count": "3",
      "favorited": false,
      "full_text": "📸:\nAirmail flight cover: Boeing 727 first flight\nFeb. 9, 1963\nGift of the Captain John B. Russell Family\n2012.149.2210\n\nSlide: TWA, Boeing 727, @flySFO\n1980s\nGift of Nadine McKinney\n2016.136.009\n\nphotograph: JAL, Boeing 727, @flySFO\n1966\nGift of Thomas G. Dragges\n2015.165.115",
      "id_str": "1359226210220351491",
      "in_reply_to_screen_name": "SFOMuseum",
      "in_reply_to_status_id": "1359226208118919168",
      "in_reply_to_status_id_str": "1359226208118919168",
      "in_reply_to_user_id": "116329337",
      "in_reply_to_user_id_str": "116329337",
      "lang": "en",
      "retweet_count": "2",
      "retweeted": false,
      "source": "\u003ca href=\"https://mobile.twitter.com\" rel=\"nofollow\"\u003eTwitter Web App\u003c/a\u003e",
      "truncated": false
    },
    "wof:name": "📸:\nAirmail flight cover: Boeing 727 first flight\nFeb. 9, 1963\nGift of the Captain John B. Russell Family\n2012.149.2210\n\nSlide: TWA, Boeing 727, @flySFO\n1980s\nGift of Nadine McKinney\n2016.136.009\n\nphotograph: JAL, Boeing 727, @flySFO\n1966\nGift of Thomas G. Dragges\n2015.165.115",
    "wof:placetype": "custom"
  },
  "geometry": {"coordinates":[-122.386166,37.616356],"type":"Point"}
}
