{
  "type": "Feature",
  "properties": {
    "date:cessation_lower": "2023-03-16",
    "date:cessation_upper": "2023-03-16",
    "date:inception_lower": "2023-03-16",
    "date:inception_upper": "2023-03-16",
    "sfomuseum:placetype": "tweet",
    "twitter:hashtags": [
      "VideoArts",
      "VideoArtsSFO",
      "WomensHistoryMonth"
    ],
    "twitter:tweet": {
      "created": 1678991182,
      "created_at": "Thu Mar 16 18:26:22 +0000 2023",
      "display_text_range": [
        "0",
        "275"
      ],
      "edit_info": {
        "initial": {
          "editTweetIds": [
            "1636433744340086784"
          ],
          "editableUntil": "2023-03-16T18:56:22.000Z",
          "editsRemaining": "5",
          "isEditEligible": false
        }
      },
      "entities": {
        "hashtags": [
          {
            "indices": [
              "211",
              "221"
            ],
            "text": "VideoArts"
          },
          {
            "indices": [
              "222",
              "235"
            ],
            "text": "VideoArtsSFO"
          },
          {
            "indices": [
              "236",
              "255"
            ],
            "text": "WomensHistoryMonth"
          }
        ],
        "urls": [
          {
            "display_url": "bit.ly/VideoArts",
            "expanded_url": "http://bit.ly/VideoArts",
            "indices": [
              "187",
              "210"
            ],
            "url": "https://t.co/s0oA7gcWli"
          }
        ],
        "user_mentions": [
          {
            "id_str": "907661573967060992",
            "indices": [
              "256",
              "266"
            ],
            "name": "alisha liu",
            "screen_name": "softgoats"
          },
          {
            "id_str": "66428805",
            "indices": [
              "267",
              "275"
            ],
            "name": "CalArts",
            "screen_name": "CalArts"
          }
        ]
      },
      "favorite_count": "1",
      "favorited": false,
      "full_text": "See “Everything Must Go” by Alisha Liu in the Video Arts Gallery, located pre-security in the International Terminal, open daily from 7am to 10pm. Learn more about this month’s films at: https://t.co/s0oA7gcWli\n#VideoArts #VideoArtsSFO #WomensHistoryMonth @softgoats @CalArts",
      "id_str": "1636433744340086784",
      "in_reply_to_screen_name": "SFOMuseum",
      "in_reply_to_status_id": "1636433743123734530",
      "in_reply_to_status_id_str": "1636433743123734530",
      "in_reply_to_user_id": "116329337",
      "in_reply_to_user_id_str": "116329337",
      "lang": "en",
      "possibly_sensitive": false,
      "retweet_count": "0",
      "retweeted": false,
      "source": "\u003ca href=\"https://mobile.twitter.com\" rel=\"nofollow\"\u003eTwitter Web App\u003c/a\u003e",
      "truncated": false
    },
    "twitter:user_mentions": [
      "softgoats",
      "CalArts"
    ],
    "wof:name": "See “Everything Must Go” by Alisha Liu in the Video Arts Gallery, located pre-security in the International Terminal, open daily from 7am to 10pm. Learn more about this month’s films at: https://t.co/s0oA7gcWli\n#VideoArts #VideoArtsSFO #WomensHistoryMonth @softgoats @CalArts",
    "wof:placetype": "custom"
  },
  "geometry": {"coordinates":[-122.386166,37.616356],"type":"Point"}
}
