{
  "type": "Feature",
  "properties": {
    "date:cessation_lower": "2015-10-05",
    "date:cessation_upper": "2015-10-05",
    "date:inception_lower": "2015-10-05",
    "date:inception_upper": "2015-10-05",
    "iso:country": "US",
    "sfomuseum:placetype": "tweet",
    "twitter:hashtags": [
      "Periscope",
      "TheNationsGame"
    ],
    "twitter:tweet": {
      "created": 1444016082,
      "created_at": "Mon Oct 05 03:34:42 +0000 2015",
      "display_text_range": [
        "0",
        "135"
      ],
      "edit_info": {
        "initial": {
          "editTweetIds": [
            "650876742291230720"
          ],
          "editableUntil": "2015-10-05T04:34:42.724Z",
          "editsRemaining": "5",
          "isEditEligible": true
        }
      },
      "entities": {
        "hashtags": [
          {
            "indices": [
              "38",
              "48"
            ],
            "text": "Periscope"
          },
          {
            "indices": [
              "66",
              "81"
            ],
            "text": "TheNationsGame"
          }
        ],
        "urls": [
          {
            "display_url": "pscp.tv/w/aOHmjzI4NzY4…",
            "expanded_url": "https://www.pscp.tv/w/aOHmjzI4NzY4NTl8MXJteFBaVk5xUG5HTnqIpP8X6jB1rbfeLQmqKJoYLUECQ6T8oLn104Knguwg",
            "indices": [
              "112",
              "135"
            ],
            "url": "https://t.co/aaqjl61CUc"
          }
        ],
        "user_mentions": [
          {
            "id_str": "-1",
            "indices": [
              "3",
              "19"
            ],
            "screen_name": "PeriscopeSummit"
          },
          {
            "id_str": "23632910",
            "indices": [
              "50",
              "65"
            ],
            "name": "Pro Football Hall of Fame",
            "screen_name": "ProFootballHOF"
          },
          {
            "id_str": "16408759",
            "indices": [
              "93",
              "100"
            ],
            "name": "San Francisco International Airport (SFO) ✈️",
            "screen_name": "flySFO"
          },
          {
            "id_str": "116329337",
            "indices": [
              "101",
              "111"
            ],
            "name": "SFO Museum",
            "screen_name": "SFOMuseum"
          }
        ]
      },
      "favorite_count": "0",
      "favorited": false,
      "full_text": "RT @PeriscopeSummit: Watching LIVE on #Periscope: @profootballhof #TheNationsGame exhibit at @flysfo @sfomuseum https://t.co/aaqjl61CUc",
      "id_str": "650876742291230720",
      "lang": "en",
      "possibly_sensitive": false,
      "retweet_count": "0",
      "retweeted": false,
      "source": "\u003ca href=\"http://twitter.com/download/iphone\" rel=\"nofollow\"\u003eTwitter for iPhone\u003c/a\u003e",
      "truncated": false
    },
    "twitter:user_mentions": [
      "SFOMuseum",
      "PeriscopeSummit",
      "ProFootballHOF",
      "flySFO"
    ],
    "wof:name": "RT @PeriscopeSummit: Watching LIVE on #Periscope: @profootballhof #TheNationsGame exhibit at @flysfo @sfomuseum https://t.co/aaqjl61CUc",
    "wof:placetype": "custom"
  },
  "geometry": {"coordinates":[-122.386166,37.616356],"type":"Point"}
}
