{
  "type": "Feature",
  "properties": {
    "date:cessation_lower": "2014-11-21",
    "date:cessation_upper": "2014-11-21",
    "date:inception_lower": "2014-11-21",
    "date:inception_upper": "2014-11-21",
    "iso:country": "US",
    "sfomuseum:placetype": "tweet",
    "twitter:hashtags": [
      "PanAm",
      "TWA"
    ],
    "twitter:tweet": {
      "created": 1416594238,
      "created_at": "Fri Nov 21 18:23:58 +0000 2014",
      "display_text_range": [
        "0",
        "134"
      ],
      "edit_info": {
        "initial": {
          "editTweetIds": [
            "535861193240768512"
          ],
          "editableUntil": "2014-11-21T19:23:58.945Z",
          "editsRemaining": "5",
          "isEditEligible": true
        }
      },
      "entities": {
        "hashtags": [
          {
            "indices": [
              "123",
              "129"
            ],
            "text": "PanAm"
          },
          {
            "indices": [
              "130",
              "134"
            ],
            "text": "TWA"
          }
        ],
        "urls": [
          {
            "display_url": "ow.ly/EGfZM",
            "expanded_url": "http://ow.ly/EGfZM",
            "indices": [
              "77",
              "99"
            ],
            "url": "http://t.co/5cdapmn6TG"
          }
        ],
        "user_mentions": [
          {
            "id_str": "1598411",
            "indices": [
              "105",
              "121"
            ],
            "name": "Todd Lappin",
            "screen_name": "TelstarLogistic"
          }
        ]
      },
      "favorite_count": "1",
      "favorited": false,
      "full_text": "Towering over Union Square in 1965 were some pretty fantastic airline signs: http://t.co/5cdapmn6TG (via @TelstarLogistic) #PanAm #TWA",
      "id_str": "535861193240768512",
      "lang": "en",
      "possibly_sensitive": false,
      "retweet_count": "0",
      "retweeted": false,
      "source": "\u003ca href=\"http://www.hootsuite.com\" rel=\"nofollow\"\u003eHootsuite\u003c/a\u003e",
      "truncated": false
    },
    "twitter:user_mentions": [
      "TelstarLogistic"
    ],
    "wof:name": "Towering over Union Square in 1965 were some pretty fantastic airline signs: http://t.co/5cdapmn6TG (via @TelstarLogistic) #PanAm #TWA",
    "wof:placetype": "custom"
  },
  "geometry": {"coordinates":[-122.386166,37.616356],"type":"Point"}
}
