{
  "type": "Feature",
  "properties": {
    "sfomuseum:placetype": "tweet",
    "twitter:tweet": {
      "created": 1416594238,
      "created_at": "Fri Nov 21 18:23:58 +0000 2014",
      "display_text_range": [
        "0", 
        "134"
      ],
      "entities": {
        "hashtags": [
          {
            "indices": [
              "123", 
              "129"
            ],
            "text": "PanAm"
          }, 
          {
            "indices": [
              "130", 
              "134"
            ],
            "text": "TWA"
          }
        ],
        "urls": [
          {
            "display_url": "ow.ly/EGfZM",
            "expanded_url": "http://ow.ly/EGfZM",
            "indices": [
              "77", 
              "99"
            ],
            "url": "http://t.co/5cdapmn6TG"
          }
        ],
        "user_mentions": [
          {
            "id_str": "1598411",
            "indices": [
              "105", 
              "121"
            ],
            "name": "Todd Lappin",
            "screen_name": "TelstarLogistic"
          }
        ]
      },
      "favorite_count": "1",
      "favorited": false,
      "full_text": "Towering over Union Square in 1965 were some pretty fantastic airline signs: http://t.co/5cdapmn6TG (via @TelstarLogistic) #PanAm #TWA",
      "id_str": "535861193240768512",
      "lang": "en",
      "possibly_sensitive": false,
      "retweet_count": "0",
      "retweeted": false,
      "source": "\u003ca href=\"http://www.hootsuite.com\" rel=\"nofollow\"\u003eHootsuite\u003c/a\u003e",
      "truncated": false
    },
    "wof:name": "Twitter message #535861193240768512",
    "wof:placetype": "custom"
  },
  "geometry": {"coordinates":[-122.386166,37.616356],"type":"Point"}
}
