{
  "type": "Feature",
  "properties": {
    "sfomuseum:placetype": "tweet",
    "twitter:tweet": {
      "created": 1431383373,
      "created_at": "Mon May 11 22:29:33 +0000 2015",
      "display_text_range": [
        "0", 
        "125"
      ],
      "entities": {
        "urls": [
          {
            "display_url": "instagram.com/p/2jvWxcxk34/",
            "expanded_url": "https://instagram.com/p/2jvWxcxk34/",
            "indices": [
              "102", 
              "125"
            ],
            "url": "https://t.co/BgpSmIBnBh"
          }
        ]
      },
      "favorite_count": "0",
      "favorited": false,
      "full_text": "The octagonal Liao Dynasty pagoda of Jinzhou is decorated with over one hundred painted panels, many… https://t.co/BgpSmIBnBh",
      "id_str": "597891318535344129",
      "lang": "en",
      "possibly_sensitive": false,
      "retweet_count": "1",
      "retweeted": false,
      "source": "\u003ca href=\"http://instagram.com\" rel=\"nofollow\"\u003eInstagram\u003c/a\u003e",
      "truncated": false
    },
    "wof:name": "Twitter message #597891318535344129",
    "wof:placetype": "custom"
  },
  "geometry": {"coordinates":[-122.386166,37.616356],"type":"Point"}
}
