{
  "type": "Feature",
  "properties": {
    "date:cessation_lower": "2021-11-10",
    "date:cessation_upper": "2021-11-10",
    "date:inception_lower": "2021-11-10",
    "date:inception_upper": "2021-11-10",
    "sfomuseum:placetype": "tweet",
    "twitter:hashtags": [
      "NativeAmericanHeritageMonth"
    ],
    "twitter:tweet": {
      "created": 1636570041,
      "created_at": "Wed Nov 10 18:47:21 +0000 2021",
      "display_text_range": [
        "0",
        "144"
      ],
      "edit_info": {
        "initial": {
          "editTweetIds": [
            "1458506579783733248"
          ],
          "editableUntil": "2021-11-10T19:47:21.019Z",
          "editsRemaining": "5",
          "isEditEligible": true
        }
      },
      "entities": {
        "hashtags": [
          {
            "indices": [
              "24",
              "52"
            ],
            "text": "NativeAmericanHeritageMonth"
          }
        ],
        "user_mentions": [
          {
            "id_str": "16408759",
            "indices": [
              "3",
              "10"
            ],
            "name": "San Francisco International Airport (SFO) ✈️",
            "screen_name": "flySFO"
          }
        ]
      },
      "favorite_count": "0",
      "favorited": false,
      "full_text": "RT @flySFO: November is #NativeAmericanHeritageMonth, which honors and celebrates the rich histories, vibrant cultures, resilience \u0026amp; divers…",
      "id_str": "1458506579783733248",
      "lang": "en",
      "retweet_count": "0",
      "retweeted": false,
      "source": "\u003ca href=\"http://twitter.com/download/iphone\" rel=\"nofollow\"\u003eTwitter for iPhone\u003c/a\u003e",
      "truncated": false
    },
    "twitter:user_mentions": [
      "flySFO"
    ],
    "wof:name": "RT @flySFO: November is #NativeAmericanHeritageMonth, which honors and celebrates the rich histories, vibrant cultures, resilience \u0026amp; divers…",
    "wof:placetype": "custom"
  },
  "geometry": {"coordinates":[-122.386166,37.616356],"type":"Point"}
}
