{
  "type": "Feature",
  "properties": {
    "date:cessation_lower": "2013-11-15",
    "date:cessation_upper": "2013-11-15",
    "date:inception_lower": "2013-11-15",
    "date:inception_upper": "2013-11-15",
    "iso:country": "US",
    "sfomuseum:placetype": "tweet",
    "twitter:tweet": {
      "created": 1384550934,
      "created_at": "Fri Nov 15 21:28:54 +0000 2013",
      "display_text_range": [
        "0",
        "125"
      ],
      "edit_info": {
        "initial": {
          "editTweetIds": [
            "401461834433462272"
          ],
          "editableUntil": "2013-11-15T22:28:54.786Z",
          "editsRemaining": "5",
          "isEditEligible": true
        }
      },
      "entities": {
        "urls": [
          {
            "display_url": "instagram.com/p/gwA4WrRk7j/",
            "expanded_url": "http://instagram.com/p/gwA4WrRk7j/",
            "indices": [
              "103",
              "125"
            ],
            "url": "http://t.co/ZHVlnUtIen"
          }
        ]
      },
      "favorite_count": "0",
      "favorited": false,
      "full_text": "A model of the Graf Zeppelin is prepped for its close up before it's installed in the Aviation Museum… http://t.co/ZHVlnUtIen",
      "id_str": "401461834433462272",
      "lang": "en",
      "possibly_sensitive": false,
      "retweet_count": "0",
      "retweeted": false,
      "source": "\u003ca href=\"http://instagram.com\" rel=\"nofollow\"\u003eInstagram\u003c/a\u003e",
      "truncated": false
    },
    "wof:name": "A model of the Graf Zeppelin is prepped for its close up before it's installed in the Aviation Museum… http://t.co/ZHVlnUtIen",
    "wof:placetype": "custom",
    "wof:placetype_alt": [
      "tweet"
    ]
  },
  "geometry": {"coordinates":[-122.386166,37.616356],"type":"Point"}
}
