{
  "type": "Feature",
  "properties": {
    "sfomuseum:placetype": "tweet",
    "twitter:tweet": {
      "created": 1391817917,
      "created_at": "Sat Feb 08 00:05:17 +0000 2014",
      "display_text_range": [
        "0", 
        "133"
      ],
      "entities": {
        "hashtags": [
          {
            "indices": [
              "118", 
              "133"
            ],
            "text": "LighterThanAir"
          }
        ],
        "urls": [
          {
            "display_url": "ow.ly/tphye",
            "expanded_url": "http://ow.ly/tphye",
            "indices": [
              "95", 
              "117"
            ],
            "url": "http://t.co/tSpDndnkAc"
          }
        ]
      },
      "favorite_count": "0",
      "favorited": false,
      "full_text": "Do you know the link between blimps and the America's Cup? Read about it on our Facebook page! http://t.co/tSpDndnkAc #LighterThanAir",
      "id_str": "431941769190977536",
      "lang": "en",
      "possibly_sensitive": false,
      "retweet_count": "0",
      "retweeted": false,
      "source": "\u003ca href=\"http://www.hootsuite.com\" rel=\"nofollow\"\u003eHootsuite\u003c/a\u003e",
      "truncated": false
    },
    "wof:name": "Twitter message #431941769190977536",
    "wof:placetype": "custom"
  },
  "geometry": {"coordinates":[-122.386166,37.616356],"type":"Point"}
}
