{
  "type": "Feature",
  "properties": {
    "sfomuseum:placetype": "tweet",
    "twitter:tweet": {
      "created": 1553879901,
      "created_at": "Fri Mar 29 17:18:21 +0000 2019",
      "display_text_range": [
        "0", 
        "140"
      ],
      "entities": {
        "user_mentions": [
          {
            "id_str": "35028425",
            "indices": [
              "3", 
              "12"
            ],
            "name": "Pan Am",
            "screen_name": "FlyPanAm"
          }
        ]
      },
      "favorite_count": "0",
      "favorited": false,
      "full_text": "RT @FlyPanAm: Clipper Flying Cloud, a Boeing 307 Stratoliner after arriving in Bogota, Colombia on its inaugural flight from Miami. https:/…",
      "id_str": "1111678997270679552",
      "lang": "en",
      "retweet_count": "0",
      "retweeted": false,
      "source": "\u003ca href=\"http://twitter.com\" rel=\"nofollow\"\u003eTwitter Web Client\u003c/a\u003e",
      "truncated": false
    },
    "wof:name": "Twitter message #1111678997270679552",
    "wof:placetype": "custom"
  },
  "geometry": {"coordinates":[-122.386166,37.616356],"type":"Point"}
}
