{
  "type": "Feature",
  "properties": {
    "sfomuseum:placetype": "tweet",
    "twitter:tweet": {
      "created": 1551031244,
      "created_at": "Sun Feb 24 18:00:44 +0000 2019",
      "display_text_range": [
        "0", 
        "301"
      ],
      "entities": {
        "hashtags": [
          {
            "indices": [
              "20", 
              "28"
            ],
            "text": "Peralta"
          }, 
          {
            "indices": [
              "266", 
              "277"
            ],
            "text": "studentart"
          }
        ],
        "media": [
          {
            "display_url": "pic.twitter.com/PyI5Gv7FPa",
            "expanded_url": "https://twitter.com/SFOMuseum/status/1099730861422010369/photo/1",
            "id_str": "1099730858645377024",
            "indices": [
              "278", 
              "301"
            ],
            "media_url": "http://pbs.twimg.com/media/D0MHY6oX0AAmr4p.jpg",
            "media_url_https": "https://pbs.twimg.com/media/D0MHY6oX0AAmr4p.jpg",
            "sizes": {
              "large": {
                "h": "1604",
                "resize": "fit",
                "w": "2000"
              },
              "medium": {
                "h": "962",
                "resize": "fit",
                "w": "1200"
              },
              "small": {
                "h": "545",
                "resize": "fit",
                "w": "680"
              },
              "thumb": {
                "h": "150",
                "resize": "crop",
                "w": "150"
              }
            },
            "type": "photo",
            "url": "https://t.co/PyI5Gv7FPa"
          }
        ]
      },
      "extended_entities": {
        "media": [
          {
            "display_url": "pic.twitter.com/PyI5Gv7FPa",
            "expanded_url": "https://twitter.com/SFOMuseum/status/1099730861422010369/photo/1",
            "id_str": "1099730858645377024",
            "indices": [
              "278", 
              "301"
            ],
            "media_url": "http://pbs.twimg.com/media/D0MHY6oX0AAmr4p.jpg",
            "media_url_https": "https://pbs.twimg.com/media/D0MHY6oX0AAmr4p.jpg",
            "sizes": {
              "large": {
                "h": "1604",
                "resize": "fit",
                "w": "2000"
              },
              "medium": {
                "h": "962",
                "resize": "fit",
                "w": "1200"
              },
              "small": {
                "h": "545",
                "resize": "fit",
                "w": "680"
              },
              "thumb": {
                "h": "150",
                "resize": "crop",
                "w": "150"
              }
            },
            "type": "photo",
            "url": "https://t.co/PyI5Gv7FPa"
          }
        ]
      },
      "favorite_count": "3",
      "favorited": false,
      "full_text": "Located in Oakland, #Peralta Elementary School uses art to enhance every aspect of student learning. The school’s leadership recognizes that art education is a vital element in the quest to acquire skills, knowledge, and appreciation for our rich and diverse world. #studentart https://t.co/PyI5Gv7FPa",
      "id_str": "1099730861422010369",
      "lang": "en",
      "possibly_sensitive": false,
      "retweet_count": "0",
      "retweeted": false,
      "source": "\u003ca href=\"https://www.hootsuite.com\" rel=\"nofollow\"\u003eHootsuite Inc.\u003c/a\u003e",
      "truncated": false
    },
    "wof:name": "Twitter message #1099730861422010369",
    "wof:placetype": "custom"
  },
  "geometry": {"coordinates":[-122.386166,37.616356],"type":"Point"}
}
