{
  "type": "Feature",
  "properties": {
    "date:cessation_lower": "2015-09-16",
    "date:cessation_upper": "2015-09-16",
    "date:inception_lower": "2015-09-16",
    "date:inception_upper": "2015-09-16",
    "iso:country": "US",
    "sfomuseum:placetype": "tweet",
    "twitter:tweet": {
      "created": 1442428920,
      "created_at": "Wed Sep 16 18:42:00 +0000 2015",
      "display_text_range": [
        "0",
        "140"
      ],
      "entities": {
        "hashtags": [
          {
            "indices": [
              "122",
              "134"
            ],
            "text": "AskACurator"
          }
        ],
        "urls": [
          {
            "display_url": "ow.ly/SiLgx",
            "expanded_url": "http://ow.ly/SiLgx",
            "indices": [
              "99",
              "121"
            ],
            "url": "http://t.co/NciwJBBj60"
          }
        ],
        "user_mentions": [
          {
            "id_str": "14848513",
            "indices": [
              "3",
              "15"
            ],
            "name": "National Air and Space Museum",
            "screen_name": "airandspace"
          },
          {
            "id_str": "29154355",
            "indices": [
              "18",
              "28"
            ],
            "name": "Gedsudski 🏴‍☠️",
            "screen_name": "Gedsudski"
          }
        ]
      },
      "favorite_count": "0",
      "favorited": false,
      "full_text": "RT @airandspace: .@Gedsudski Tom Crouch, Senior Curator in Aeronautics rec's the 1903 Wright Flyer http://t.co/NciwJBBj60 #AskACurator http…",
      "id_str": "644219702915502080",
      "lang": "en",
      "possibly_sensitive": false,
      "retweet_count": "0",
      "retweeted": false,
      "source": "\u003ca href=\"http://www.hootsuite.com\" rel=\"nofollow\"\u003eHootsuite\u003c/a\u003e",
      "truncated": false
    },
    "wof:name": "RT @airandspace: .@Gedsudski Tom Crouch, Senior Curator in Aeronautics rec's the 1903 Wright Flyer http://t.co/NciwJBBj60 #AskACurator http…",
    "wof:placetype": "custom"
  },
  "geometry": {"coordinates":[-122.386166,37.616356],"type":"Point"}
}
