{
  "type": "Feature",
  "properties": {
    "date:cessation_lower": "2012-01-23",
    "date:cessation_upper": "2012-01-23",
    "date:inception_lower": "2012-01-23",
    "date:inception_upper": "2012-01-23",
    "iso:country": "US",
    "sfomuseum:placetype": "tweet",
    "twitter:tweet": {
      "created": 1327339510,
      "created_at": "Mon Jan 23 17:25:10 +0000 2012",
      "display_text_range": [
        "0",
        "99"
      ],
      "edit_info": {
        "initial": {
          "editTweetIds": [
            "161499729161760769"
          ],
          "editableUntil": "2012-01-23T18:25:10.609Z",
          "editsRemaining": "5",
          "isEditEligible": true
        }
      },
      "entities": {
        "user_mentions": [
          {
            "id_str": "1477789280177033218",
            "indices": [
              "0",
              "13"
            ],
            "name": "Jake",
            "screen_name": "Jakethefurst"
          }
        ]
      },
      "favorite_count": "0",
      "favorited": false,
      "full_text": "@jakethefurst We're so glad that you enjoyed our exhibit on television! Thanks for checking it out!",
      "id_str": "161499729161760769",
      "in_reply_to_screen_name": "furst",
      "in_reply_to_status_id": "161322029688176640",
      "in_reply_to_status_id_str": "161322029688176640",
      "in_reply_to_user_id": "23095315",
      "in_reply_to_user_id_str": "23095315",
      "lang": "en",
      "retweet_count": "0",
      "retweeted": false,
      "source": "\u003ca href=\"http://www.hootsuite.com\" rel=\"nofollow\"\u003eHootsuite\u003c/a\u003e",
      "truncated": false
    },
    "twitter:user_mentions": [
      "Jakethefurst"
    ],
    "wof:name": "@jakethefurst We're so glad that you enjoyed our exhibit on television! Thanks for checking it out!",
    "wof:placetype": "custom"
  },
  "geometry": {"coordinates":[-122.386166,37.616356],"type":"Point"}
}
