{
  "type": "Feature",
  "properties": {
    "date:cessation_lower": "2014-12-10",
    "date:cessation_upper": "2014-12-10",
    "date:inception_lower": "2014-12-10",
    "date:inception_upper": "2014-12-10",
    "iso:country": "US",
    "sfomuseum:placetype": "tweet",
    "twitter:tweet": {
      "created": 1418243218,
      "created_at": "Wed Dec 10 20:26:58 +0000 2014",
      "display_text_range": [
        "0",
        "114"
      ],
      "edit_info": {
        "initial": {
          "editTweetIds": [
            "542777514607656960"
          ],
          "editableUntil": "2014-12-10T20:56:58.458Z",
          "editsRemaining": "5",
          "isEditEligible": true
        }
      },
      "entities": {
        "hashtags": [
          {
            "indices": [
              "76",
              "90"
            ],
            "text": "WhenArtRocked"
          }
        ],
        "urls": [
          {
            "display_url": "instagram.com/p/wcIgDsxkyB/",
            "expanded_url": "http://instagram.com/p/wcIgDsxkyB/",
            "indices": [
              "92",
              "114"
            ],
            "url": "http://t.co/javSQTo8Mv"
          }
        ]
      },
      "favorite_count": "0",
      "favorited": false,
      "full_text": "Big Brother and the Holding Company, tearing up the International Terminal! #WhenArtRocked… http://t.co/javSQTo8Mv",
      "id_str": "542777514607656960",
      "lang": "en",
      "possibly_sensitive": false,
      "retweet_count": "0",
      "retweeted": false,
      "source": "\u003ca href=\"http://instagram.com\" rel=\"nofollow\"\u003eInstagram\u003c/a\u003e",
      "truncated": false
    },
    "wof:name": "Big Brother and the Holding Company, tearing up the International Terminal! #WhenArtRocked… http://t.co/javSQTo8Mv",
    "wof:placetype": "custom"
  },
  "geometry": {"coordinates":[-122.386166,37.616356],"type":"Point"}
}
