{
  "type": "Feature",
  "properties": {
    "date:cessation_lower": "2016-10-31",
    "date:cessation_upper": "2016-10-31",
    "date:inception_lower": "2016-10-31",
    "date:inception_upper": "2016-10-31",
    "iso:country": "US",
    "sfomuseum:placetype": "tweet",
    "twitter:tweet": {
      "created": 1477948635,
      "created_at": "Mon Oct 31 21:17:15 +0000 2016",
      "display_text_range": [
        "0",
        "137"
      ],
      "edit_info": {
        "initial": {
          "editTweetIds": [
            "793200186084380672"
          ],
          "editableUntil": "2016-10-31T21:47:15.966Z",
          "editsRemaining": "5",
          "isEditEligible": true
        }
      },
      "entities": {
        "hashtags": [
          {
            "indices": [
              "45",
              "61"
            ],
            "text": "FashionInFlight"
          }
        ],
        "user_mentions": [
          {
            "id_str": "45780894",
            "indices": [
              "0",
              "6"
            ],
            "name": "Clarissa Cooper (She/Her)",
            "screen_name": "Ryzhy"
          }
        ]
      },
      "favorite_count": "1",
      "favorited": false,
      "full_text": "@Ryzhy We're so glad to hear you enjoyed our #FashionInFlight exhibition! Thank you for sharing this fantastic photo of your grandmother!",
      "id_str": "793200186084380672",
      "in_reply_to_screen_name": "Ryzhy",
      "in_reply_to_status_id": "793170525354729472",
      "in_reply_to_status_id_str": "793170525354729472",
      "in_reply_to_user_id": "45780894",
      "in_reply_to_user_id_str": "45780894",
      "lang": "en",
      "retweet_count": "0",
      "retweeted": false,
      "source": "\u003ca href=\"http://twitter.com\" rel=\"nofollow\"\u003eTwitter Web Client\u003c/a\u003e",
      "truncated": false
    },
    "wof:name": "@Ryzhy We're so glad to hear you enjoyed our #FashionInFlight exhibition! Thank you for sharing this fantastic photo of your grandmother!",
    "wof:placetype": "custom"
  },
  "geometry": {"coordinates":[-122.386166,37.616356],"type":"Point"}
}
