{
  "type": "Feature",
  "properties": {
    "sfomuseum:placetype": "tweet",
    "twitter:tweet": {
      "created": 1594677254,
      "created_at": "Mon Jul 13 21:54:14 +0000 2020",
      "display_text_range": [
        "0", 
        "144"
      ],
      "entities": {
        "hashtags": [
          {
            "indices": [
              "53", 
              "68"
            ],
            "text": "GoldenGatePark"
          }
        ],
        "user_mentions": [
          {
            "id_str": "16408759",
            "indices": [
              "3", 
              "10"
            ],
            "name": "San Francisco International Airport (SFO) ✈️",
            "screen_name": "flySFO"
          }, 
          {
            "id_str": "30090529",
            "indices": [
              "90", 
              "100"
            ],
            "name": "SF Rec and Park",
            "screen_name": "RecParkSF"
          }, 
          {
            "id_str": "41639579",
            "indices": [
              "101", 
              "117"
            ],
            "name": "SF Parks Alliance",
            "screen_name": "SFParksAlliance"
          }, 
          {
            "id_str": "23100755",
            "indices": [
              "124", 
              "140"
            ],
            "name": "SF Public Library",
            "screen_name": "SFPublicLibrary"
          }
        ]
      },
      "favorite_count": "0",
      "favorited": false,
      "full_text": "RT @flySFO: This year marks the 150th anniversary of #GoldenGatePark. In partnership with @RecParkSF @SFParksAlliance \u0026amp; @SFPublicLibrary, t…",
      "id_str": "1282795499653787649",
      "lang": "en",
      "retweet_count": "0",
      "retweeted": false,
      "source": "\u003ca href=\"https://mobile.twitter.com\" rel=\"nofollow\"\u003eTwitter Web App\u003c/a\u003e",
      "truncated": false
    },
    "wof:name": "Twitter message #1282795499653787649",
    "wof:placetype": "custom"
  },
  "geometry": {"coordinates":[-122.386166,37.616356],"type":"Point"}
}
