{
  "type": "Feature",
  "properties": {
    "sfomuseum:placetype": "tweet",
    "twitter:tweet": {
      "created": 1452903916,
      "created_at": "Sat Jan 16 00:25:16 +0000 2016",
      "display_text_range": [
        "0", 
        "134"
      ],
      "entities": {
        "hashtags": [
          {
            "indices": [
              "104", 
              "110"
            ],
            "text": "PanAm"
          }
        ],
        "media": [
          {
            "display_url": "pic.twitter.com/6DjmLtC5zf",
            "expanded_url": "https://twitter.com/SFOMuseum/status/688155020588482561/photo/1",
            "id_str": "688155020001280000",
            "indices": [
              "111", 
              "134"
            ],
            "media_url": "http://pbs.twimg.com/media/CYzRWD2UAAAYE1m.jpg",
            "media_url_https": "https://pbs.twimg.com/media/CYzRWD2UAAAYE1m.jpg",
            "sizes": {
              "large": {
                "h": "429",
                "resize": "fit",
                "w": "618"
              },
              "medium": {
                "h": "429",
                "resize": "fit",
                "w": "618"
              },
              "small": {
                "h": "429",
                "resize": "fit",
                "w": "618"
              },
              "thumb": {
                "h": "150",
                "resize": "crop",
                "w": "150"
              }
            },
            "type": "photo",
            "url": "https://t.co/6DjmLtC5zf"
          }
        ]
      },
      "extended_entities": {
        "media": [
          {
            "display_url": "pic.twitter.com/6DjmLtC5zf",
            "expanded_url": "https://twitter.com/SFOMuseum/status/688155020588482561/photo/1",
            "id_str": "688155020001280000",
            "indices": [
              "111", 
              "134"
            ],
            "media_url": "http://pbs.twimg.com/media/CYzRWD2UAAAYE1m.jpg",
            "media_url_https": "https://pbs.twimg.com/media/CYzRWD2UAAAYE1m.jpg",
            "sizes": {
              "large": {
                "h": "429",
                "resize": "fit",
                "w": "618"
              },
              "medium": {
                "h": "429",
                "resize": "fit",
                "w": "618"
              },
              "small": {
                "h": "429",
                "resize": "fit",
                "w": "618"
              },
              "thumb": {
                "h": "150",
                "resize": "crop",
                "w": "150"
              }
            },
            "type": "photo",
            "url": "https://t.co/6DjmLtC5zf"
          }
        ]
      },
      "favorite_count": "4",
      "favorited": false,
      "full_text": "The Pan American base on Treasure Island included the administration building and a maintenance hangar. #PanAm https://t.co/6DjmLtC5zf",
      "id_str": "688155020588482561",
      "lang": "en",
      "possibly_sensitive": false,
      "retweet_count": "3",
      "retweeted": false,
      "source": "\u003ca href=\"http://www.hootsuite.com\" rel=\"nofollow\"\u003eHootsuite\u003c/a\u003e",
      "truncated": false
    },
    "wof:name": "Twitter message #688155020588482561",
    "wof:placetype": "custom"
  },
  "geometry": {"coordinates":[-122.386166,37.616356],"type":"Point"}
}
