{
  "type": "Feature",
  "properties": {
    "sfomuseum:placetype": "tweet",
    "twitter:tweet": {
      "created": 1359674875,
      "created_at": "Thu Jan 31 23:27:55 +0000 2013",
      "display_text_range": [
        "0", 
        "127"
      ],
      "entities": {
        "urls": [
          {
            "display_url": "bit.ly/U4wN7F",
            "expanded_url": "http://bit.ly/U4wN7F",
            "indices": [
              "107", 
              "127"
            ],
            "url": "http://t.co/YMsFC4cE"
          }
        ],
        "user_mentions": [
          {
            "id_str": "278230029",
            "indices": [
              "22", 
              "38"
            ],
            "name": "Millbrae Library",
            "screen_name": "MillbraeLibrary"
          }
        ]
      },
      "favorite_count": "0",
      "favorited": false,
      "full_text": "So super awesome!! RT @MillbraeLibrary: Super Bowl XLVII: San Francisco librarian vs Baltimore librarian - http://t.co/YMsFC4cE",
      "id_str": "297124079687856128",
      "lang": "es",
      "possibly_sensitive": false,
      "retweet_count": "0",
      "retweeted": false,
      "source": "\u003ca href=\"https://about.twitter.com/products/tweetdeck\" rel=\"nofollow\"\u003eTweetDeck\u003c/a\u003e",
      "truncated": false
    },
    "wof:name": "Twitter message #297124079687856128",
    "wof:placetype": "custom"
  },
  "geometry": {"coordinates":[-122.386166,37.616356],"type":"Point"}
}
