{
  "type": "Feature",
  "properties": {
    "sfomuseum:placetype": "tweet",
    "twitter:tweet": {
      "created": 1570740189,
      "created_at": "Thu Oct 10 20:43:09 +0000 2019",
      "display_text_range": [
        "0", 
        "60"
      ],
      "entities": {
        "user_mentions": [
          {
            "id_str": "1498538449",
            "indices": [
              "0", 
              "10"
            ],
            "name": "John Flett",
            "screen_name": "uk_johnnz"
          }
        ]
      },
      "favorite_count": "1",
      "favorited": false,
      "full_text": "@uk_johnnz Wow 48 hours! What a journey! Thanks for sharing!",
      "id_str": "1182396171471294464",
      "in_reply_to_screen_name": "uk_johnnz",
      "in_reply_to_status_id": "1182224012589568001",
      "in_reply_to_status_id_str": "1182224012589568001",
      "in_reply_to_user_id": "1498538449",
      "in_reply_to_user_id_str": "1498538449",
      "lang": "en",
      "retweet_count": "0",
      "retweeted": false,
      "source": "\u003ca href=\"https://mobile.twitter.com\" rel=\"nofollow\"\u003eTwitter Web App\u003c/a\u003e",
      "truncated": false
    },
    "wof:name": "Twitter message #1182396171471294464",
    "wof:placetype": "custom"
  },
  "geometry": {"coordinates":[-122.386166,37.616356],"type":"Point"}
}
