{
  "type": "Feature",
  "properties": {
    "sfomuseum:placetype": "tweet",
    "twitter:tweet": {
      "created": 1326387720,
      "created_at": "Thu Jan 12 17:02:00 +0000 2012",
      "display_text_range": [
        "0", 
        "88"
      ],
      "entities": {
        "user_mentions": [
          {
            "id_str": "863391",
            "indices": [
              "0", 
              "2"
            ],
            "name": "Naoki  Hiroshima",
            "screen_name": "N"
          }
        ]
      },
      "favorite_count": "0",
      "favorited": false,
      "full_text": "@N Thanks for much for checking out (\u0026 documenting) our exhibit! We hope you enjoyed it!",
      "id_str": "157507631974592513",
      "in_reply_to_screen_name": "N",
      "in_reply_to_user_id": "863391",
      "in_reply_to_user_id_str": "863391",
      "lang": "en",
      "retweet_count": "0",
      "retweeted": false,
      "source": "\u003ca href=\"https://about.twitter.com/products/tweetdeck\" rel=\"nofollow\"\u003eTweetDeck\u003c/a\u003e",
      "truncated": false
    },
    "wof:name": "Twitter message #157507631974592513",
    "wof:placetype": "custom"
  },
  "geometry": {"coordinates":[-122.386166,37.616356],"type":"Point"}
}
