{
  "type": "Feature",
  "properties": {
    "date:cessation_lower": "2016-05-11",
    "date:cessation_upper": "2016-05-11",
    "date:inception_lower": "2016-05-11",
    "date:inception_upper": "2016-05-11",
    "iso:country": "US",
    "sfomuseum:placetype": "tweet",
    "twitter:tweet": {
      "created": 1462986938,
      "created_at": "Wed May 11 17:15:38 +0000 2016",
      "display_text_range": [
        "0",
        "140"
      ],
      "edit_info": {
        "initial": {
          "editTweetIds": [
            "730446277138223105"
          ],
          "editableUntil": "2016-05-11T17:45:38.162Z",
          "editsRemaining": "5",
          "isEditEligible": true
        }
      },
      "entities": {
        "hashtags": [
          {
            "indices": [
              "19",
              "23"
            ],
            "text": "HBD"
          },
          {
            "indices": [
              "53",
              "57"
            ],
            "text": "OTD"
          },
          {
            "indices": [
              "121",
              "135"
            ],
            "text": "womenshistory"
          }
        ],
        "user_mentions": [
          {
            "id_str": "37666708",
            "indices": [
              "3",
              "17"
            ],
            "name": "National Women's History Museum",
            "screen_name": "womenshistory"
          }
        ]
      },
      "favorite_count": "0",
      "favorited": false,
      "full_text": "RT @womenshistory: #HBD to pilot Harriet Quimby born #OTD in 1875 1st American woman to become a licensed airplane pilot #womenshistory htt…",
      "id_str": "730446277138223105",
      "lang": "en",
      "retweet_count": "0",
      "retweeted": false,
      "source": "\u003ca href=\"http://twitter.com\" rel=\"nofollow\"\u003eTwitter Web Client\u003c/a\u003e",
      "truncated": false
    },
    "wof:name": "RT @womenshistory: #HBD to pilot Harriet Quimby born #OTD in 1875 1st American woman to become a licensed airplane pilot #womenshistory htt…",
    "wof:placetype": "custom"
  },
  "geometry": {"coordinates":[-122.386166,37.616356],"type":"Point"}
}
