{
  "type": "Feature",
  "properties": {
    "sfomuseum:placetype": "tweet",
    "twitter:tweet": {
      "created": 1461349883,
      "created_at": "Fri Apr 22 18:31:23 +0000 2016",
      "display_text_range": [
        "0", 
        "140"
      ],
      "entities": {
        "hashtags": [
          {
            "indices": [
              "108", 
              "117"
            ],
            "text": "EarthDay"
          }
        ],
        "user_mentions": [
          {
            "id_str": "181608016",
            "indices": [
              "3", 
              "15"
            ],
            "name": "airlineguys",
            "screen_name": "airlineguys"
          }
        ]
      },
      "favorite_count": "0",
      "favorited": false,
      "full_text": "RT @airlineguys: Apron, messenger bag, or computer case perhaps? \"Up-cycled\" products made from life vests. #EarthDay https://t.co/WeGsH1F3…",
      "id_str": "723579970715574272",
      "lang": "en",
      "retweet_count": "0",
      "retweeted": false,
      "source": "\u003ca href=\"http://www.hootsuite.com\" rel=\"nofollow\"\u003eHootsuite\u003c/a\u003e",
      "truncated": false
    },
    "wof:name": "Twitter message #723579970715574272",
    "wof:placetype": "custom"
  },
  "geometry": {"coordinates":[-122.386166,37.616356],"type":"Point"}
}
