{
  "type": "Feature",
  "properties": {
    "sfomuseum:placetype": "tweet",
    "twitter:tweet": {
      "created": 1318358410,
      "created_at": "Tue Oct 11 18:40:10 +0000 2011",
      "display_text_range": [
        "0", 
        "136"
      ],
      "entities": {
        "urls": [
          {
            "display_url": "mypict.me/mbH2g",
            "expanded_url": "http://mypict.me/mbH2g",
            "indices": [
              "116", 
              "136"
            ],
            "url": "http://t.co/uLe6rZy9"
          }
        ],
        "user_mentions": [
          {
            "id_str": "26314960",
            "indices": [
              "3", 
              "14"
            ],
            "name": "DJ AMEN",
            "screen_name": "djamen3000"
          }
        ]
      },
      "favorite_count": "0",
      "favorited": false,
      "full_text": "RT @djamen3000: The vinyl exhibit in the new Terminal 2 at SFO is pretty dope. Check it out next time your in here. http://t.co/uLe6rZy9",
      "id_str": "123830266576896002",
      "lang": "en",
      "possibly_sensitive": false,
      "retweet_count": "1",
      "retweeted": false,
      "source": "\u003ca href=\"http://www.hootsuite.com\" rel=\"nofollow\"\u003eHootsuite\u003c/a\u003e",
      "truncated": false
    },
    "wof:name": "Twitter message #123830266576896002",
    "wof:placetype": "custom"
  },
  "geometry": {"coordinates":[-122.386166,37.616356],"type":"Point"}
}
