{
  "type": "Feature",
  "properties": {
    "date:cessation_lower":"2015-04-28",
    "date:cessation_upper":"2015-04-28",
    "date:inception_lower":"2015-04-28",
    "date:inception_upper":"2015-04-28",
    "iso:country":"US",
    "sfomuseum:placetype":"tweet",
    "twitter:tweet":{
        "created":1430265339,
        "created_at":"Tue Apr 28 23:55:39 +0000 2015",
        "display_text_range":[
            "0",
            "70"
        ],
        "entities":{
            "hashtags":[
                {
                    "indices":[
                        "0",
                        "10"
                    ],
                    "text":"Wurlitzer"
                },
                {
                    "indices":[
                        "11",
                        "19"
                    ],
                    "text":"jukebox"
                },
                {
                    "indices":[
                        "20",
                        "26"
                    ],
                    "text":"1930s"
                },
                {
                    "indices":[
                        "27",
                        "35"
                    ],
                    "text":"ArtDeco"
                },
                {
                    "indices":[
                        "36",
                        "46"
                    ],
                    "text":"AgeOfDeco"
                }
            ],
            "urls":[
                {
                    "display_url":"instagram.com/p/2Ca4GURk-A/",
                    "expanded_url":"https://instagram.com/p/2Ca4GURk-A/",
                    "indices":[
                        "47",
                        "70"
                    ],
                    "url":"https://t.co/Z9l8tG5wqx"
                }
            ]
        },
        "favorite_count":"0",
        "favorited":false,
        "full_text":"#Wurlitzer #jukebox #1930s #ArtDeco #AgeOfDeco https://t.co/Z9l8tG5wqx",
        "id_str":"593201943004184576",
        "lang":"und",
        "possibly_sensitive":false,
        "retweet_count":"1",
        "retweeted":false,
        "source":"<a href=\"http://instagram.com\" rel=\"nofollow\">Instagram</a>",
        "truncated":false
    },
    "wof:name":"#Wurlitzer #jukebox #1930s #ArtDeco #AgeOfDeco https://t.co/Z9l8tG5wqx",
    "wof:placetype":"custom"
},
  "geometry": {"coordinates":[-122.386166,37.616356],"type":"Point"}
}