{
  "type": "Feature",
  "properties": {
    "date:cessation_lower": "2021-02-03",
    "date:cessation_upper": "2021-02-03",
    "date:inception_lower": "2021-02-03",
    "date:inception_upper": "2021-02-03",
    "sfomuseum:placetype": "tweet",
    "twitter:tweet": {
      "created": 1612313009,
      "created_at": "Wed Feb 03 00:43:29 +0000 2021",
      "display_text_range": [
        "0",
        "130"
      ],
      "edit_info": {
        "initial": {
          "editTweetIds": [
            "1356765214406889472"
          ],
          "editableUntil": "2021-02-03T01:43:29.250Z",
          "editsRemaining": "5",
          "isEditEligible": true
        }
      },
      "entities": {
      },
      "favorite_count": "7",
      "favorited": false,
      "full_text": "\"I know a man who lives in the Bay Area. He's 101 years old, still very sharp, and he was a flying boat captain for Pan American.\"",
      "id_str": "1356765214406889472",
      "lang": "en",
      "retweet_count": "0",
      "retweeted": false,
      "source": "\u003ca href=\"https://mobile.twitter.com\" rel=\"nofollow\"\u003eTwitter Web App\u003c/a\u003e",
      "truncated": false
    },
    "wof:name": "\"I know a man who lives in the Bay Area. He's 101 years old, still very sharp, and he was a flying boat captain for Pan American.\"",
    "wof:placetype": "custom",
    "wof:placetype_alt": [
      "tweet"
    ]
  },
  "geometry": {"coordinates":[-122.386166,37.616356],"type":"Point"}
}
