{
  "type": "Feature",
  "properties": {
    "sfomuseum:placetype": "tweet",
    "twitter:tweet": {
      "created": 1449279077,
      "created_at": "Sat Dec 05 01:31:17 +0000 2015",
      "display_text_range": [
        "0", 
        "118"
      ],
      "entities": {
        "hashtags": [
          {
            "indices": [
              "0", 
              "10"
            ],
            "text": "OnThisDay"
          }, 
          {
            "indices": [
              "80", 
              "85"
            ],
            "text": "PPIE"
          }, 
          {
            "indices": [
              "86", 
              "94"
            ],
            "text": "PPIE100"
          }
        ],
        "media": [
          {
            "display_url": "pic.twitter.com/PCEb2LBDoZ",
            "expanded_url": "https://twitter.com/SFOMuseum/status/672951341749297152/photo/1",
            "id_str": "672951341304537088",
            "indices": [
              "95", 
              "118"
            ],
            "media_url": "http://pbs.twimg.com/media/CVbNrfGUYAAVPBu.jpg",
            "media_url_https": "https://pbs.twimg.com/media/CVbNrfGUYAAVPBu.jpg",
            "sizes": {
              "large": {
                "h": "1450",
                "resize": "fit",
                "w": "1830"
              },
              "medium": {
                "h": "951",
                "resize": "fit",
                "w": "1200"
              },
              "small": {
                "h": "539",
                "resize": "fit",
                "w": "680"
              },
              "thumb": {
                "h": "150",
                "resize": "crop",
                "w": "150"
              }
            },
            "type": "photo",
            "url": "https://t.co/PCEb2LBDoZ"
          }
        ]
      },
      "extended_entities": {
        "media": [
          {
            "display_url": "pic.twitter.com/PCEb2LBDoZ",
            "expanded_url": "https://twitter.com/SFOMuseum/status/672951341749297152/photo/1",
            "id_str": "672951341304537088",
            "indices": [
              "95", 
              "118"
            ],
            "media_url": "http://pbs.twimg.com/media/CVbNrfGUYAAVPBu.jpg",
            "media_url_https": "https://pbs.twimg.com/media/CVbNrfGUYAAVPBu.jpg",
            "sizes": {
              "large": {
                "h": "1450",
                "resize": "fit",
                "w": "1830"
              },
              "medium": {
                "h": "951",
                "resize": "fit",
                "w": "1200"
              },
              "small": {
                "h": "539",
                "resize": "fit",
                "w": "680"
              },
              "thumb": {
                "h": "150",
                "resize": "crop",
                "w": "150"
              }
            },
            "type": "photo",
            "url": "https://t.co/PCEb2LBDoZ"
          }
        ]
      },
      "favorite_count": "1",
      "favorited": false,
      "full_text": "#OnThisDay in 1915 the Panama-Pacific International Exposition came to a close. #PPIE #PPIE100 https://t.co/PCEb2LBDoZ",
      "id_str": "672951341749297152",
      "lang": "en",
      "possibly_sensitive": false,
      "retweet_count": "0",
      "retweeted": false,
      "source": "\u003ca href=\"http://www.hootsuite.com\" rel=\"nofollow\"\u003eHootsuite\u003c/a\u003e",
      "truncated": false
    },
    "wof:name": "Twitter message #672951341749297152",
    "wof:placetype": "custom"
  },
  "geometry": {"coordinates":[-122.386166,37.616356],"type":"Point"}
}
