{
  "type": "Feature",
  "properties": {
    "date:cessation_lower": "2019-04-15",
    "date:cessation_upper": "2019-04-15",
    "date:inception_lower": "2019-04-15",
    "date:inception_upper": "2019-04-15",
    "iso:country": "US",
    "sfomuseum:placetype": "tweet",
    "twitter:tweet": {
      "created": 1555354549,
      "created_at": "Mon Apr 15 18:55:49 +0000 2019",
      "display_text_range": [
        "0",
        "140"
      ],
      "edit_info": {
        "initial": {
          "editTweetIds": [
            "1117864117253988354"
          ],
          "editableUntil": "2019-04-15T19:55:49.121Z",
          "editsRemaining": "5",
          "isEditEligible": true
        }
      },
      "entities": {
        "user_mentions": [
          {
            "id_str": "14848513",
            "indices": [
              "3",
              "15"
            ],
            "name": "National Air and Space Museum",
            "screen_name": "airandspace"
          }
        ]
      },
      "favorite_count": "0",
      "favorited": false,
      "full_text": "RT @airandspace: On this day in 1452, Leonardo da Vinci was born. \n\nDid you know that da Vinci was fascinated by the topic of human mechani…",
      "id_str": "1117864117253988354",
      "lang": "en",
      "retweet_count": "0",
      "retweeted": false,
      "source": "\u003ca href=\"http://twitter.com\" rel=\"nofollow\"\u003eTwitter Web Client\u003c/a\u003e",
      "truncated": false
    },
    "twitter:user_mentions": [
      "airandspace"
    ],
    "wof:name": "RT @airandspace: On this day in 1452, Leonardo da Vinci was born. \n\nDid you know that da Vinci was fascinated by the topic of human mechani…",
    "wof:placetype": "custom"
  },
  "geometry": {"coordinates":[-122.386166,37.616356],"type":"Point"}
}
