{
  "type": "Feature",
  "properties": {
    "date:cessation_lower":"2012-10-24",
    "date:cessation_upper":"2012-10-24",
    "date:inception_lower":"2012-10-24",
    "date:inception_upper":"2012-10-24",
    "iso:country":"US",
    "sfomuseum:placetype":"tweet",
    "twitter:tweet":{
        "created":1351111461,
        "created_at":"Wed Oct 24 20:44:21 +0000 2012",
        "display_text_range":[
            "0",
            "124"
        ],
        "entities":{
            "hashtags":[
                {
                    "indices":[
                        "57",
                        "66"
                    ],
                    "text":"SFGiants"
                },
                {
                    "indices":[
                        "101",
                        "109"
                    ],
                    "text":"Awesome"
                },
                {
                    "indices":[
                        "110",
                        "124"
                    ],
                    "text":"OrangeOctober"
                }
            ],
            "user_mentions":[
                {
                    "id_str":"16408759",
                    "indices":[
                        "92",
                        "99"
                    ],
                    "name":"San Francisco International Airport (SFO) \u2708\ufe0f",
                    "screen_name":"flySFO"
                }
            ]
        },
        "favorite_count":"0",
        "favorited":false,
        "full_text":"We're installing our newest exhibit in T2, &amp; SO many #SFGiants fans are cruising around @flySFO! #Awesome #OrangeOctober",
        "id_str":"261206518408560640",
        "lang":"en",
        "retweet_count":"1",
        "retweeted":false,
        "source":"<a href=\"http://www.hootsuite.com\" rel=\"nofollow\">Hootsuite</a>",
        "truncated":false
    },
    "wof:name":"We're installing our newest exhibit in T2, &amp; SO many #SFGiants fans are cruising around @flySFO! #Awesome #OrangeOctober",
    "wof:placetype":"custom"
},
  "geometry": {"coordinates":[-122.386166,37.616356],"type":"Point"}
}