{
  "type": "Feature",
  "properties": {
    "sfomuseum:placetype": "tweet",
    "twitter:tweet": {
      "created": 1351111461,
      "created_at": "Wed Oct 24 20:44:21 +0000 2012",
      "display_text_range": [
        "0", 
        "124"
      ],
      "entities": {
        "hashtags": [
          {
            "indices": [
              "57", 
              "66"
            ],
            "text": "SFGiants"
          }, 
          {
            "indices": [
              "101", 
              "109"
            ],
            "text": "Awesome"
          }, 
          {
            "indices": [
              "110", 
              "124"
            ],
            "text": "OrangeOctober"
          }
        ],
        "user_mentions": [
          {
            "id_str": "16408759",
            "indices": [
              "92", 
              "99"
            ],
            "name": "San Francisco International Airport (SFO) ✈️",
            "screen_name": "flySFO"
          }
        ]
      },
      "favorite_count": "0",
      "favorited": false,
      "full_text": "We're installing our newest exhibit in T2, \u0026amp; SO many #SFGiants fans are cruising around @flySFO! #Awesome #OrangeOctober",
      "id_str": "261206518408560640",
      "lang": "en",
      "retweet_count": "1",
      "retweeted": false,
      "source": "\u003ca href=\"http://www.hootsuite.com\" rel=\"nofollow\"\u003eHootsuite\u003c/a\u003e",
      "truncated": false
    },
    "wof:name": "Twitter message #261206518408560640",
    "wof:placetype": "custom"
  },
  "geometry": {"coordinates":[-122.386166,37.616356],"type":"Point"}
}
