{
  "type": "Feature",
  "properties": {
    "date:cessation_lower": "2015-03-10",
    "date:cessation_upper": "2015-03-10",
    "date:inception_lower": "2015-03-10",
    "date:inception_upper": "2015-03-10",
    "iso:country": "US",
    "sfomuseum:placetype": "tweet",
    "twitter:tweet": {
      "created": 1426017590,
      "created_at": "Tue Mar 10 19:59:50 +0000 2015",
      "display_text_range": [
        "0",
        "123"
      ],
      "edit_info": {
        "initial": {
          "editTweetIds": [
            "575385592873222145"
          ],
          "editableUntil": "2015-03-10T20:59:50.145Z",
          "editsRemaining": "5",
          "isEditEligible": true
        }
      },
      "entities": {
        "urls": [
          {
            "display_url": "instagram.com/p/0D08Eqxkxe/",
            "expanded_url": "https://instagram.com/p/0D08Eqxkxe/",
            "indices": [
              "100",
              "123"
            ],
            "url": "https://t.co/St1F01E1rw"
          }
        ]
      },
      "favorite_count": "0",
      "favorited": false,
      "full_text": "A scene of the Loughead brothers' Model G coming in to dock. The brothers (who later changed their… https://t.co/St1F01E1rw",
      "id_str": "575385592873222145",
      "lang": "en",
      "possibly_sensitive": false,
      "retweet_count": "0",
      "retweeted": false,
      "source": "\u003ca href=\"http://instagram.com\" rel=\"nofollow\"\u003eInstagram\u003c/a\u003e",
      "truncated": false
    },
    "wof:name": "A scene of the Loughead brothers' Model G coming in to dock. The brothers (who later changed their… https://t.co/St1F01E1rw",
    "wof:placetype": "custom"
  },
  "geometry": {"coordinates":[-122.386166,37.616356],"type":"Point"}
}
