{
  "type": "Feature",
  "properties": {
    "sfomuseum:placetype": "tweet",
    "twitter:tweet": {
      "created": 1324594985,
      "created_at": "Thu Dec 22 23:03:05 +0000 2011",
      "display_text_range": [
        "0", 
        "140"
      ],
      "entities": {
        "hashtags": [
          {
            "indices": [
              "101", 
              "112"
            ],
            "text": "UCBerkeley"
          }
        ],
        "user_mentions": [
          {
            "id_str": "63864806",
            "indices": [
              "3", 
              "16"
            ],
            "name": "Katherine Tam",
            "screen_name": "katherinetam"
          }
        ]
      },
      "favorite_count": "0",
      "favorited": false,
      "full_text": "RT @katherinetam: Airport-bound for the holidays? If u're at SFO, check out antique microscopes from #UCBerkeley collection on display:  ...",
      "id_str": "149988358125404160",
      "lang": "en",
      "retweet_count": "0",
      "retweeted": false,
      "source": "\u003ca href=\"http://www.hootsuite.com\" rel=\"nofollow\"\u003eHootsuite\u003c/a\u003e",
      "truncated": false
    },
    "wof:name": "Twitter message #149988358125404160",
    "wof:placetype": "custom"
  },
  "geometry": {"coordinates":[-122.386166,37.616356],"type":"Point"}
}
