{
  "type": "Feature",
  "properties": {
    "sfomuseum:placetype": "tweet",
    "twitter:tweet": {
      "created": 1455840928,
      "created_at": "Fri Feb 19 00:15:28 +0000 2016",
      "display_text_range": [
        "0", 
        "135"
      ],
      "entities": {
        "media": [
          {
            "display_url": "pic.twitter.com/TBZ2ZufjQ8",
            "expanded_url": "https://twitter.com/SFOMuseum/status/700473740291928064/photo/1",
            "id_str": "700473739507412992",
            "indices": [
              "112", 
              "135"
            ],
            "media_url": "http://pbs.twimg.com/media/CbiVJ6HUMAAyAMw.jpg",
            "media_url_https": "https://pbs.twimg.com/media/CbiVJ6HUMAAyAMw.jpg",
            "sizes": {
              "large": {
                "h": "996",
                "resize": "fit",
                "w": "755"
              },
              "medium": {
                "h": "996",
                "resize": "fit",
                "w": "755"
              },
              "small": {
                "h": "680",
                "resize": "fit",
                "w": "515"
              },
              "thumb": {
                "h": "150",
                "resize": "crop",
                "w": "150"
              }
            },
            "type": "photo",
            "url": "https://t.co/TBZ2ZufjQ8"
          }
        ]
      },
      "extended_entities": {
        "media": [
          {
            "display_url": "pic.twitter.com/TBZ2ZufjQ8",
            "expanded_url": "https://twitter.com/SFOMuseum/status/700473740291928064/photo/1",
            "id_str": "700473739507412992",
            "indices": [
              "112", 
              "135"
            ],
            "media_url": "http://pbs.twimg.com/media/CbiVJ6HUMAAyAMw.jpg",
            "media_url_https": "https://pbs.twimg.com/media/CbiVJ6HUMAAyAMw.jpg",
            "sizes": {
              "large": {
                "h": "996",
                "resize": "fit",
                "w": "755"
              },
              "medium": {
                "h": "996",
                "resize": "fit",
                "w": "755"
              },
              "small": {
                "h": "680",
                "resize": "fit",
                "w": "515"
              },
              "thumb": {
                "h": "150",
                "resize": "crop",
                "w": "150"
              }
            },
            "type": "photo",
            "url": "https://t.co/TBZ2ZufjQ8"
          }
        ]
      },
      "favorite_count": "1",
      "favorited": false,
      "full_text": "“Looking Back, Moving Ahead” by students from The Laurel School combines art, ancient Greece, and Claude Monet. https://t.co/TBZ2ZufjQ8",
      "id_str": "700473740291928064",
      "lang": "en",
      "possibly_sensitive": false,
      "retweet_count": "0",
      "retweeted": false,
      "source": "\u003ca href=\"http://www.hootsuite.com\" rel=\"nofollow\"\u003eHootsuite\u003c/a\u003e",
      "truncated": false
    },
    "wof:name": "Twitter message #700473740291928064",
    "wof:placetype": "custom"
  },
  "geometry": {"coordinates":[-122.386166,37.616356],"type":"Point"}
}
