{
  "type": "Feature",
  "properties": {
    "sfomuseum:placetype": "tweet",
    "twitter:tweet": {
      "created": 1332173311,
      "created_at": "Mon Mar 19 16:08:31 +0000 2012",
      "display_text_range": [
        "0", 
        "125"
      ],
      "entities": {
        "hashtags": [
          {
            "indices": [
              "44", 
              "48"
            ],
            "text": "SFO"
          }
        ],
        "user_mentions": [
          {
            "id_str": "36182094",
            "indices": [
              "32", 
              "39"
            ],
            "name": "Tahe Dooki",
            "screen_name": "TDooki"
          }
        ]
      },
      "favorite_count": "0",
      "favorited": false,
      "full_text": "Thanks! Glad you enjoyed it! RT @TDooki: At #SFO Airport, awesome motorcycle exhibition! All Italian 1950 - 1960 ..very nice!",
      "id_str": "181774158357733377",
      "lang": "en",
      "retweet_count": "0",
      "retweeted": false,
      "source": "\u003ca href=\"https://about.twitter.com/products/tweetdeck\" rel=\"nofollow\"\u003eTweetDeck\u003c/a\u003e",
      "truncated": false
    },
    "wof:name": "Twitter message #181774158357733377",
    "wof:placetype": "custom"
  },
  "geometry": {"coordinates":[-122.386166,37.616356],"type":"Point"}
}
