{
  "type": "Feature",
  "properties": {
    "iso:country":"US",
    "sfomuseum:placetype":"tweet",
    "twitter:tweet":{
        "created":1584686844,
        "created_at":"Fri Mar 20 06:47:24 +0000 2020",
        "display_text_range":[
            "0",
            "175"
        ],
        "entities":{
            "urls":[
                {
                    "display_url":"amnh.org/explore/origam\u2026",
                    "expanded_url":"https://www.amnh.org/explore/origami/how-to-videos",
                    "indices":[
                        "127",
                        "150"
                    ],
                    "url":"https://t.co/5Chm9WEtvr"
                },
                {
                    "display_url":"origami-resource-center.com/paper-airplane\u2026",
                    "expanded_url":"https://www.origami-resource-center.com/paper-airplane-instructions.html",
                    "indices":[
                        "152",
                        "175"
                    ],
                    "url":"https://t.co/vxXbT1M0NZ"
                }
            ]
        },
        "favorite_count":"3",
        "favorited":false,
        "full_text":"Things to do at home: if you would like to learn how to create any number of origami forms, check out these online resources:\n*https://t.co/5Chm9WEtvr\n*https://t.co/vxXbT1M0NZ",
        "id_str":"1240892680445415424",
        "in_reply_to_screen_name":"SFOMuseum",
        "in_reply_to_status_id":"1240778852458270721",
        "in_reply_to_status_id_str":"1240778852458270721",
        "in_reply_to_user_id":"116329337",
        "in_reply_to_user_id_str":"116329337",
        "lang":"en",
        "possibly_sensitive":false,
        "retweet_count":"1",
        "retweeted":false,
        "source":"<a href=\"https://mobile.twitter.com\" rel=\"nofollow\">Twitter Web App</a>",
        "truncated":false
    },
    "wof:name":"Things to do at home: if you would like to learn how to create any number of origami forms, check out these online resources:\n*https://t.co/5Chm9WEtvr\n*https://t.co/vxXbT1M0NZ",
    "wof:placetype":"custom"
},
  "geometry": {"coordinates":[-122.386166,37.616356],"type":"Point"}
}