{
  "type": "Feature",
  "properties": {
    "date:cessation_lower": "2012-09-18",
    "date:cessation_upper": "2012-09-18",
    "date:inception_lower": "2012-09-18",
    "date:inception_upper": "2012-09-18",
    "iso:country": "US",
    "sfomuseum:placetype": "tweet",
    "twitter:tweet": {
      "created": 1347988971,
      "created_at": "Tue Sep 18 17:22:51 +0000 2012",
      "display_text_range": [
        "0",
        "48"
      ],
      "edit_info": {
        "initial": {
          "editTweetIds": [
            "248109844882677760"
          ],
          "editableUntil": "2012-09-18T17:52:51.335Z",
          "editsRemaining": "5",
          "isEditEligible": true
        }
      },
      "entities": {
        "user_mentions": [
          {
            "id_str": "830232390",
            "indices": [
              "0",
              "16"
            ],
            "name": "Chicago to Palo Alto",
            "screen_name": "JakeandAnnaMove"
          }
        ]
      },
      "favorite_count": "0",
      "favorited": false,
      "full_text": "@JakeandAnnaMove PS- Welcome to the Bay Area! :)",
      "id_str": "248109844882677760",
      "in_reply_to_screen_name": "JakeandAnnaMove",
      "in_reply_to_user_id": "830232390",
      "in_reply_to_user_id_str": "830232390",
      "lang": "en",
      "retweet_count": "0",
      "retweeted": false,
      "source": "\u003ca href=\"https://about.twitter.com/products/tweetdeck\" rel=\"nofollow\"\u003eTweetDeck\u003c/a\u003e",
      "truncated": false
    },
    "wof:name": "@JakeandAnnaMove PS- Welcome to the Bay Area! :)",
    "wof:placetype": "custom"
  },
  "geometry": {"coordinates":[-122.386166,37.616356],"type":"Point"}
}
