{
  "type": "Feature",
  "properties": {
    "date:cessation_lower": "2024-01-03",
    "date:cessation_upper": "2024-01-03",
    "date:inception_lower": "2024-01-03",
    "date:inception_upper": "2024-01-03",
    "sfomuseum:placetype": "tweet",
    "twitter:tweet": {
      "created": 1704244113,
      "created_at": "Wed Jan 03 01:08:33 +0000 2024",
      "display_text_range": [
        "0",
        "110"
      ],
      "edit_info": {
        "initial": {
          "editTweetIds": [
            "1742352214696620125"
          ],
          "editableUntil": "2024-01-03T02:08:33.000Z",
          "editsRemaining": "5",
          "isEditEligible": false
        }
      },
      "entities": {
        "urls": [
          {
            "display_url": "collection.sfomuseum.org/objects/151193…",
            "expanded_url": "https://collection.sfomuseum.org/objects/1511934067/",
            "indices": [
              "87",
              "110"
            ],
            "url": "https://t.co/8iBzE0JW3X"
          }
        ]
      },
      "favorite_count": "0",
      "favorited": false,
      "full_text": "📸:\ntimetable: Ozark Air Lines; 1980\nGift of the William Hough Collection\n2008.108.576\n\nhttps://t.co/8iBzE0JW3X",
      "id_str": "1742352214696620125",
      "in_reply_to_screen_name": "SFOMuseum",
      "in_reply_to_status_id": "1741860081430577422",
      "in_reply_to_status_id_str": "1741860081430577422",
      "in_reply_to_user_id": "116329337",
      "in_reply_to_user_id_str": "116329337",
      "lang": "en",
      "possibly_sensitive": false,
      "retweet_count": "0",
      "retweeted": false,
      "source": "\u003ca href=\"https://mobile.twitter.com\" rel=\"nofollow\"\u003eTwitter Web App\u003c/a\u003e",
      "truncated": false
    },
    "wof:name": "📸:\ntimetable: Ozark Air Lines; 1980\nGift of the William Hough Collection\n2008.108.576\n\nhttps://t.co/8iBzE0JW3X",
    "wof:placetype": "custom",
    "wof:placetype_alt": [
      "tweet"
    ]
  },
  "geometry": {"coordinates":[-122.386166,37.616356],"type":"Point"}
}
