{
  "type": "Feature",
  "properties": {
    "sfomuseum:placetype": "tweet",
    "twitter:tweet": {
      "created": 1475292006,
      "created_at": "Sat Oct 01 03:20:06 +0000 2016",
      "display_text_range": [
        "0", 
        "160"
      ],
      "entities": {
        "hashtags": [
          {
            "indices": [
              "120", 
              "136"
            ],
            "text": "FashionInFlight"
          }
        ],
        "media": [
          {
            "display_url": "pic.twitter.com/sqLq3zspgF",
            "expanded_url": "https://twitter.com/SFOMuseum/status/782057474497142785/photo/1",
            "id_str": "782057470785126400",
            "indices": [
              "137", 
              "160"
            ],
            "media_url": "http://pbs.twimg.com/media/CtptIEwWgAAhgoA.jpg",
            "media_url_https": "https://pbs.twimg.com/media/CtptIEwWgAAhgoA.jpg",
            "sizes": {
              "large": {
                "h": "2000",
                "resize": "fit",
                "w": "1333"
              },
              "medium": {
                "h": "1200",
                "resize": "fit",
                "w": "800"
              },
              "small": {
                "h": "680",
                "resize": "fit",
                "w": "453"
              },
              "thumb": {
                "h": "150",
                "resize": "crop",
                "w": "150"
              }
            },
            "type": "photo",
            "url": "https://t.co/sqLq3zspgF"
          }
        ],
        "urls": [
          {
            "display_url": "bit.ly/fashioninflight",
            "expanded_url": "http://bit.ly/fashioninflight",
            "indices": [
              "96", 
              "119"
            ],
            "url": "https://t.co/UbL4YNFAUD"
          }
        ]
      },
      "extended_entities": {
        "media": [
          {
            "display_url": "pic.twitter.com/sqLq3zspgF",
            "expanded_url": "https://twitter.com/SFOMuseum/status/782057474497142785/photo/1",
            "id_str": "782057470785126400",
            "indices": [
              "137", 
              "160"
            ],
            "media_url": "http://pbs.twimg.com/media/CtptIEwWgAAhgoA.jpg",
            "media_url_https": "https://pbs.twimg.com/media/CtptIEwWgAAhgoA.jpg",
            "sizes": {
              "large": {
                "h": "2000",
                "resize": "fit",
                "w": "1333"
              },
              "medium": {
                "h": "1200",
                "resize": "fit",
                "w": "800"
              },
              "small": {
                "h": "680",
                "resize": "fit",
                "w": "453"
              },
              "thumb": {
                "h": "150",
                "resize": "crop",
                "w": "150"
              }
            },
            "type": "photo",
            "url": "https://t.co/sqLq3zspgF"
          }
        ]
      },
      "favorite_count": "2",
      "favorited": false,
      "full_text": "The 1974 TWA uniform featured pinstripe flared pants, a turtleneck \u0026amp; a safari-style jacket. https://t.co/UbL4YNFAUD #FashionInFlight https://t.co/sqLq3zspgF",
      "id_str": "782057474497142785",
      "lang": "en",
      "possibly_sensitive": false,
      "retweet_count": "0",
      "retweeted": false,
      "source": "\u003ca href=\"http://www.hootsuite.com\" rel=\"nofollow\"\u003eHootsuite\u003c/a\u003e",
      "truncated": false
    },
    "wof:name": "Twitter message #782057474497142785",
    "wof:placetype": "custom"
  },
  "geometry": {"coordinates":[-122.386166,37.616356],"type":"Point"}
}
