{
  "type": "Feature",
  "properties": {
    "date:cessation_lower": "2017-09-13",
    "date:cessation_upper": "2017-09-13",
    "date:inception_lower": "2017-09-13",
    "date:inception_upper": "2017-09-13",
    "iso:country": "US",
    "sfomuseum:placetype": "tweet",
    "twitter:tweet": {
      "created": 1505326843,
      "created_at": "Wed Sep 13 18:20:43 +0000 2017",
      "display_text_range": [
        "0",
        "149"
      ],
      "edit_info": {
        "initial": {
          "editTweetIds": [
            "908032710114869248"
          ],
          "editableUntil": "2017-09-13T19:20:43.180Z",
          "editsRemaining": "5",
          "isEditEligible": true
        }
      },
      "entities": {
        "hashtags": [
          {
            "indices": [
              "137",
              "149"
            ],
            "text": "askacurator"
          }
        ],
        "user_mentions": [
          {
            "id_str": "19646605",
            "indices": [
              "0",
              "9"
            ],
            "name": "Mar Dixon ☕️🎭🗿🏛❤️",
            "screen_name": "MarDixon"
          }
        ]
      },
      "favorite_count": "3",
      "favorited": false,
      "full_text": "@MarDixon Outside of SFO Museum, my favorite museum in the U.S. is the unusual and fascinating Museum of Jurassic Technology in LA - Kai #askacurator",
      "id_str": "908032710114869248",
      "in_reply_to_screen_name": "MarDixon",
      "in_reply_to_status_id": "907972043165065217",
      "in_reply_to_status_id_str": "907972043165065217",
      "in_reply_to_user_id": "19646605",
      "in_reply_to_user_id_str": "19646605",
      "lang": "en",
      "retweet_count": "1",
      "retweeted": false,
      "source": "\u003ca href=\"http://twitter.com\" rel=\"nofollow\"\u003eTwitter Web Client\u003c/a\u003e",
      "truncated": false
    },
    "wof:name": "@MarDixon Outside of SFO Museum, my favorite museum in the U.S. is the unusual and fascinating Museum of Jurassic Technology in LA - Kai #askacurator",
    "wof:placetype": "custom"
  },
  "geometry": {"coordinates":[-122.386166,37.616356],"type":"Point"}
}
