{
  "type": "Feature",
  "properties": {
    "date:cessation_lower": "2022-04-07",
    "date:cessation_upper": "2022-04-07",
    "date:inception_lower": "2022-04-07",
    "date:inception_upper": "2022-04-07",
    "sfomuseum:placetype": "tweet",
    "twitter:tweet": {
      "created": 1649371859,
      "created_at": "Thu Apr 07 22:50:59 +0000 2022",
      "display_text_range": [
        "0",
        "211"
      ],
      "edit_info": {
        "initial": {
          "editTweetIds": [
            "1512201300095643667"
          ],
          "editableUntil": "2022-04-07T23:20:59.941Z",
          "editsRemaining": "5",
          "isEditEligible": true
        }
      },
      "entities": {
      },
      "favorite_count": "4",
      "favorited": false,
      "full_text": "📸 4/4:\nroute map: CNAC (China National Aviation Corporation); 1948\nGift of Thomas G. Dragges\n2014.095.341\n\ntimetable: CNAC (China National Aviation Corporation); 10/06/1949\nGift of Thomas G. Dragges\n2015.167.292",
      "id_str": "1512201300095643667",
      "in_reply_to_screen_name": "SFOMuseum",
      "in_reply_to_status_id": "1512201298946707459",
      "in_reply_to_status_id_str": "1512201298946707459",
      "in_reply_to_user_id": "116329337",
      "in_reply_to_user_id_str": "116329337",
      "lang": "en",
      "retweet_count": "0",
      "retweeted": false,
      "source": "\u003ca href=\"https://mobile.twitter.com\" rel=\"nofollow\"\u003eTwitter Web App\u003c/a\u003e",
      "truncated": false
    },
    "wof:name": "📸 4/4:\nroute map: CNAC (China National Aviation Corporation); 1948\nGift of Thomas G. Dragges\n2014.095.341\n\ntimetable: CNAC (China National Aviation Corporation); 10/06/1949\nGift of Thomas G. Dragges\n2015.167.292",
    "wof:placetype": "custom"
  },
  "geometry": {"coordinates":[-122.386166,37.616356],"type":"Point"}
}
