{
  "type": "Feature",
  "properties": {
    "date:cessation_lower": "2018-10-25",
    "date:cessation_upper": "2018-10-25",
    "date:inception_lower": "2018-10-25",
    "date:inception_upper": "2018-10-25",
    "iso:country": "US",
    "sfomuseum:placetype": "tweet",
    "twitter:tweet": {
      "created": 1540429760,
      "created_at": "Thu Oct 25 01:09:20 +0000 2018",
      "display_text_range": [
        "0",
        "140"
      ],
      "edit_info": {
        "initial": {
          "editTweetIds": [
            "1055265018365775873"
          ],
          "editableUntil": "2018-10-25T02:09:20.911Z",
          "editsRemaining": "5",
          "isEditEligible": true
        }
      },
      "entities": {
        "user_mentions": [
          {
            "id_str": "14848513",
            "indices": [
              "3",
              "15"
            ],
            "name": "National Air and Space Museum",
            "screen_name": "airandspace"
          }
        ]
      },
      "favorite_count": "0",
      "favorited": false,
      "full_text": "RT @airandspace: How does a baseball team in the 1940s travel? Charter, of course! ⚾ Here's the New York Yankees in front of their airplane…",
      "id_str": "1055265018365775873",
      "lang": "en",
      "retweet_count": "0",
      "retweeted": false,
      "source": "\u003ca href=\"https://www.hootsuite.com\" rel=\"nofollow\"\u003eHootsuite Inc.\u003c/a\u003e",
      "truncated": false
    },
    "twitter:user_mentions": [
      "airandspace"
    ],
    "wof:name": "RT @airandspace: How does a baseball team in the 1940s travel? Charter, of course! ⚾ Here's the New York Yankees in front of their airplane…",
    "wof:placetype": "custom",
    "wof:placetype_alt": [
      "tweet"
    ]
  },
  "geometry": {"coordinates":[-122.386166,37.616356],"type":"Point"}
}
