{
  "type": "Feature",
  "properties": {
    "sfomuseum:placetype": "tweet",
    "twitter:tweet": {
      "created": 1333739563,
      "created_at": "Fri Apr 06 19:12:43 +0000 2012",
      "display_text_range": [
        "0", 
        "110"
      ],
      "entities": {
        "user_mentions": [
          {
            "id_str": "8813602",
            "indices": [
              "3", 
              "13"
            ],
            "name": "Stacey Burns",
            "screen_name": "WentRogue"
          }, 
          {
            "id_str": "116329337",
            "indices": [
              "15", 
              "25"
            ],
            "name": "SFO Museum",
            "screen_name": "SFOMuseum"
          }
        ]
      },
      "favorite_count": "0",
      "favorited": false,
      "full_text": "RT @WentRogue: @SFOMuseum Yeah, it was very cool--I loved it and it would be awesome if more airports did that",
      "id_str": "188343496745291777",
      "lang": "en",
      "retweet_count": "0",
      "retweeted": false,
      "source": "\u003ca href=\"http://twitter.com/download/iphone\" rel=\"nofollow\"\u003eTwitter for iPhone\u003c/a\u003e",
      "truncated": false
    },
    "wof:name": "Twitter message #188343496745291777",
    "wof:placetype": "custom"
  },
  "geometry": {"coordinates":[-122.386166,37.616356],"type":"Point"}
}
