{
  "type": "Feature",
  "properties": {
    "date:cessation_lower": "2016-08-09",
    "date:cessation_upper": "2016-08-09",
    "date:inception_lower": "2016-08-09",
    "date:inception_upper": "2016-08-09",
    "iso:country": "US",
    "sfomuseum:placetype": "tweet",
    "twitter:tweet": {
      "created": 1470788306,
      "created_at": "Wed Aug 10 00:18:26 +0000 2016",
      "display_text_range": [
        "0", 
        "114"
      ],
      "entities": {
        "user_mentions": [
          {
            "id_str": "113048196",
            "indices": [
              "0", 
              "12"
            ],
            "name": "Chris Manno",
            "screen_name": "Chris_Manno"
          }
        ]
      },
      "favorite_count": "2",
      "favorited": false,
      "full_text": "@Chris_Manno Ah! So close! Your first guess on the last question would have been correct! It is O'Hare in Chicago!",
      "id_str": "763167586087424000",
      "in_reply_to_screen_name": "Chris_Manno",
      "in_reply_to_status_id": "763163243460177921",
      "in_reply_to_status_id_str": "763163243460177921",
      "in_reply_to_user_id": "113048196",
      "in_reply_to_user_id_str": "113048196",
      "lang": "en",
      "retweet_count": "0",
      "retweeted": false,
      "source": "\u003ca href=\"http://twitter.com\" rel=\"nofollow\"\u003eTwitter Web Client\u003c/a\u003e",
      "truncated": false
    },
    "wof:name": "@Chris_Manno Ah! So close! Your first guess on the last question would have been correct! It is O'Hare in Chicago!",
    "wof:placetype": "custom"
  },
  "geometry": {"coordinates":[-122.386166,37.616356],"type":"Point"}
}
