{
  "type": "Feature",
  "properties": {
    "date:cessation_lower": "2016-04-23",
    "date:cessation_upper": "2016-04-23",
    "date:inception_lower": "2016-04-23",
    "date:inception_upper": "2016-04-23",
    "iso:country": "US",
    "sfomuseum:placetype": "tweet",
    "twitter:tweet": {
      "created": 1461434458,
      "created_at": "Sat Apr 23 18:00:58 +0000 2016",
      "display_text_range": [
        "0",
        "137"
      ],
      "entities": {
        "hashtags": [
          {
            "indices": [
              "6",
              "19"
            ],
            "text": "WorldBookDay"
          }
        ]
      },
      "favorite_count": "1",
      "favorited": false,
      "full_text": "Happy #WorldBookDay! Did you know our Aviation Museum and Library, located pre-security, in the IT is now open daily from 10am to 4:30pm?",
      "id_str": "723934706354544641",
      "lang": "en",
      "retweet_count": "0",
      "retweeted": false,
      "source": "\u003ca href=\"http://www.hootsuite.com\" rel=\"nofollow\"\u003eHootsuite\u003c/a\u003e",
      "truncated": false
    },
    "wof:name": "Happy #WorldBookDay! Did you know our Aviation Museum and Library, located pre-security, in the IT is now open daily from 10am to 4:30pm?",
    "wof:placetype": "custom"
  },
  "geometry": {"coordinates":[-122.386166,37.616356],"type":"Point"}
}
