{
  "type": "Feature",
  "properties": {
    "sfomuseum:placetype": "tweet",
    "twitter:tweet": {
      "created": 1450218459,
      "created_at": "Tue Dec 15 22:27:39 +0000 2015",
      "display_text_range": [
        "0", 
        "140"
      ],
      "entities": {
        "hashtags": [
          {
            "indices": [
              "42", 
              "59"
            ],
            "text": "aviationcultures"
          }
        ],
        "user_mentions": [
          {
            "id_str": "2525872574",
            "indices": [
              "3", 
              "19"
            ],
            "name": "Peter Hobbins",
            "screen_name": "history2wheeler"
          }
        ]
      },
      "favorite_count": "0",
      "favorited": false,
      "full_text": "RT @history2wheeler: Destination unknown? #aviationcultures closed with a panel of blue-sky possibilities and excitement about aviation htt…",
      "id_str": "676891396809220097",
      "lang": "en",
      "retweet_count": "0",
      "retweeted": false,
      "source": "\u003ca href=\"http://twitter.com\" rel=\"nofollow\"\u003eTwitter Web Client\u003c/a\u003e",
      "truncated": false
    },
    "wof:name": "Twitter message #676891396809220097",
    "wof:placetype": "custom"
  },
  "geometry": {"coordinates":[-122.386166,37.616356],"type":"Point"}
}
