{
  "type": "Feature",
  "properties": {
    "date:cessation_lower": "2023-02-08",
    "date:cessation_upper": "2023-02-08",
    "date:inception_lower": "2023-02-08",
    "date:inception_upper": "2023-02-08",
    "sfomuseum:placetype": "tweet",
    "twitter:tweet": {
      "created": 1675897112,
      "created_at": "Wed Feb 08 22:58:32 +0000 2023",
      "display_text_range": [
        "0",
        "129"
      ],
      "edit_info": {
        "initial": {
          "editTweetIds": [
            "1623456273357475840"
          ],
          "editableUntil": "2023-02-08T23:28:32.000Z",
          "editsRemaining": "5",
          "isEditEligible": false
        }
      },
      "entities": {
        "urls": [
          {
            "display_url": "bit.ly/3lilGLh",
            "expanded_url": "http://bit.ly/3lilGLh",
            "indices": [
              "37",
              "60"
            ],
            "url": "https://t.co/q1ky9fjE1W"
          },
          {
            "display_url": "bit.ly/3jEcEaO",
            "expanded_url": "http://bit.ly/3jEcEaO",
            "indices": [
              "106",
              "129"
            ],
            "url": "https://t.co/n1D7PWRCA1"
          }
        ]
      },
      "favorite_count": "1",
      "favorited": false,
      "full_text": "3520 Museum Preparator (Part-time):  https://t.co/q1ky9fjE1W\n\n3522 Senior Museum Preparator (Full-time):  https://t.co/n1D7PWRCA1",
      "id_str": "1623456273357475840",
      "in_reply_to_screen_name": "SFOMuseum",
      "in_reply_to_status_id": "1623456268500475905",
      "in_reply_to_status_id_str": "1623456268500475905",
      "in_reply_to_user_id": "116329337",
      "in_reply_to_user_id_str": "116329337",
      "lang": "en",
      "possibly_sensitive": false,
      "retweet_count": "1",
      "retweeted": false,
      "source": "\u003ca href=\"https://mobile.twitter.com\" rel=\"nofollow\"\u003eTwitter Web App\u003c/a\u003e",
      "truncated": false
    },
    "wof:name": "3520 Museum Preparator (Part-time):  https://t.co/q1ky9fjE1W\n\n3522 Senior Museum Preparator (Full-time):  https://t.co/n1D7PWRCA1",
    "wof:placetype": "custom"
  },
  "geometry": {"coordinates":[-122.386166,37.616356],"type":"Point"}
}
