{
  "type": "Feature",
  "properties": {
    "sfomuseum:placetype": "tweet",
    "twitter:tweet": {
      "created": 1433807675,
      "created_at": "Mon Jun 08 23:54:35 +0000 2015",
      "display_text_range": [
        "0", 
        "125"
      ],
      "entities": {
        "urls": [
          {
            "display_url": "instagram.com/p/3r_WGuxkzE/",
            "expanded_url": "https://instagram.com/p/3r_WGuxkzE/",
            "indices": [
              "102", 
              "125"
            ],
            "url": "https://t.co/MHICGR9p1I"
          }
        ]
      },
      "favorite_count": "1",
      "favorited": false,
      "full_text": "How warm is it outside today? Warm enough to make us think that we could be in this photo of Waikiki… https://t.co/MHICGR9p1I",
      "id_str": "608059579604303873",
      "lang": "en",
      "possibly_sensitive": false,
      "retweet_count": "0",
      "retweeted": false,
      "source": "\u003ca href=\"http://instagram.com\" rel=\"nofollow\"\u003eInstagram\u003c/a\u003e",
      "truncated": false
    },
    "wof:name": "Twitter message #608059579604303873",
    "wof:placetype": "custom"
  },
  "geometry": {"coordinates":[-122.386166,37.616356],"type":"Point"}
}
