{
  "type": "Feature",
  "properties": {
    "date:cessation_lower": "2022-04-28",
    "date:cessation_upper": "2022-04-28",
    "date:inception_lower": "2022-04-28",
    "date:inception_upper": "2022-04-28",
    "sfomuseum:placetype": "tweet",
    "twitter:tweet": {
      "created": 1651168959,
      "created_at": "Thu Apr 28 18:02:39 +0000 2022",
      "display_text_range": [
        "0",
        "259"
      ],
      "edit_info": {
        "initial": {
          "editTweetIds": [
            "1519738882928959488"
          ],
          "editableUntil": "2022-04-28T18:32:39.730Z",
          "editsRemaining": "5",
          "isEditEligible": true
        }
      },
      "entities": {
        "hashtags": [
          {
            "indices": [
              "212",
              "222"
            ],
            "text": "VideoArts"
          },
          {
            "indices": [
              "223",
              "236"
            ],
            "text": "VideoArtsSFO"
          },
          {
            "indices": [
              "237",
              "259"
            ],
            "text": "InternationalDanceDay"
          }
        ],
        "urls": [
          {
            "display_url": "bit.ly/3tX060o",
            "expanded_url": "https://bit.ly/3tX060o",
            "indices": [
              "187",
              "210"
            ],
            "url": "https://t.co/oS9q65CmTY"
          }
        ]
      },
      "favorite_count": "0",
      "favorited": false,
      "full_text": "See “Match” by Peter Walker \u0026amp; Emily Kikta in the Video Arts Gallery, located pre-security in the International Terminal with daily operating hours of 5:00am to 10:00pm, or online at: https://t.co/oS9q65CmTY\n\n#VideoArts #VideoArtsSFO #InternationalDanceDay",
      "id_str": "1519738882928959488",
      "in_reply_to_screen_name": "SFOMuseum",
      "in_reply_to_status_id": "1519738877300203520",
      "in_reply_to_status_id_str": "1519738877300203520",
      "in_reply_to_user_id": "116329337",
      "in_reply_to_user_id_str": "116329337",
      "lang": "en",
      "possibly_sensitive": false,
      "retweet_count": "0",
      "retweeted": false,
      "source": "\u003ca href=\"https://mobile.twitter.com\" rel=\"nofollow\"\u003eTwitter Web App\u003c/a\u003e",
      "truncated": false
    },
    "wof:name": "See “Match” by Peter Walker \u0026amp; Emily Kikta in the Video Arts Gallery, located pre-security in the International Terminal with daily operating hours of 5:00am to 10:00pm, or online at: https://t.co/oS9q65CmTY\n\n#VideoArts #VideoArtsSFO #InternationalDanceDay",
    "wof:placetype": "custom"
  },
  "geometry": {"coordinates":[-122.386166,37.616356],"type":"Point"}
}
