{
  "type": "Feature",
  "properties": {
    "sfomuseum:placetype": "tweet",
    "twitter:tweet": {
      "created": 1565712136,
      "created_at": "Tue Aug 13 16:02:16 +0000 2019",
      "display_text_range": [
        "0", 
        "301"
      ],
      "entities": {
        "hashtags": [
          {
            "indices": [
              "260", 
              "277"
            ],
            "text": "CaliforniaCrafts"
          }
        ],
        "media": [
          {
            "display_url": "pic.twitter.com/rvmNMNx2ko",
            "expanded_url": "https://twitter.com/SFOMuseum/status/1161306986027388929/photo/1",
            "id_str": "1161306984316133376",
            "indices": [
              "278", 
              "301"
            ],
            "media_url": "http://pbs.twimg.com/media/EB3KjKNX4AAdfZ3.jpg",
            "media_url_https": "https://pbs.twimg.com/media/EB3KjKNX4AAdfZ3.jpg",
            "sizes": {
              "large": {
                "h": "1473",
                "resize": "fit",
                "w": "2000"
              },
              "medium": {
                "h": "884",
                "resize": "fit",
                "w": "1200"
              },
              "small": {
                "h": "501",
                "resize": "fit",
                "w": "680"
              },
              "thumb": {
                "h": "150",
                "resize": "crop",
                "w": "150"
              }
            },
            "type": "photo",
            "url": "https://t.co/rvmNMNx2ko"
          }
        ]
      },
      "extended_entities": {
        "media": [
          {
            "display_url": "pic.twitter.com/rvmNMNx2ko",
            "expanded_url": "https://twitter.com/SFOMuseum/status/1161306986027388929/photo/1",
            "id_str": "1161306984316133376",
            "indices": [
              "278", 
              "301"
            ],
            "media_url": "http://pbs.twimg.com/media/EB3KjKNX4AAdfZ3.jpg",
            "media_url_https": "https://pbs.twimg.com/media/EB3KjKNX4AAdfZ3.jpg",
            "sizes": {
              "large": {
                "h": "1473",
                "resize": "fit",
                "w": "2000"
              },
              "medium": {
                "h": "884",
                "resize": "fit",
                "w": "1200"
              },
              "small": {
                "h": "501",
                "resize": "fit",
                "w": "680"
              },
              "thumb": {
                "h": "150",
                "resize": "crop",
                "w": "150"
              }
            },
            "type": "photo",
            "url": "https://t.co/rvmNMNx2ko"
          }
        ]
      },
      "favorite_count": "2",
      "favorited": false,
      "full_text": "Bob Stocksdale had a masterful talent for revealing dramatic patterns hidden below the surface of rare wood. A self-educated craftsman, Stocksdale honed his woodworking techniques through decades of experience, constantly fine-tuning simple-yet-elegant forms. #CaliforniaCrafts https://t.co/rvmNMNx2ko",
      "id_str": "1161306986027388929",
      "lang": "en",
      "possibly_sensitive": false,
      "retweet_count": "1",
      "retweeted": false,
      "source": "\u003ca href=\"https://www.hootsuite.com\" rel=\"nofollow\"\u003eHootsuite Inc.\u003c/a\u003e",
      "truncated": false
    },
    "wof:name": "Twitter message #1161306986027388929",
    "wof:placetype": "custom"
  },
  "geometry": {"coordinates":[-122.386166,37.616356],"type":"Point"}
}
