{
  "type": "Feature",
  "properties": {
    "sfomuseum:placetype": "tweet",
    "twitter:tweet": {
      "created": 1452048908,
      "created_at": "Wed Jan 06 02:55:08 +0000 2016",
      "display_text_range": [
        "0", 
        "137"
      ],
      "entities": {
        "hashtags": [
          {
            "indices": [
              "99", 
              "113"
            ],
            "text": "MingeiFolkArt"
          }
        ],
        "media": [
          {
            "display_url": "pic.twitter.com/ie8ZdEArM8",
            "expanded_url": "https://twitter.com/SFOMuseum/status/684568855696535552/photo/1",
            "id_str": "684568854996107265",
            "indices": [
              "114", 
              "137"
            ],
            "media_url": "http://pbs.twimg.com/media/CYATvyJWwAEwEMT.jpg",
            "media_url_https": "https://pbs.twimg.com/media/CYATvyJWwAEwEMT.jpg",
            "sizes": {
              "large": {
                "h": "1429",
                "resize": "fit",
                "w": "2048"
              },
              "medium": {
                "h": "838",
                "resize": "fit",
                "w": "1200"
              },
              "small": {
                "h": "475",
                "resize": "fit",
                "w": "680"
              },
              "thumb": {
                "h": "150",
                "resize": "crop",
                "w": "150"
              }
            },
            "type": "photo",
            "url": "https://t.co/ie8ZdEArM8"
          }
        ],
        "urls": [
          {
            "display_url": "ow.ly/WFG5a",
            "expanded_url": "http://ow.ly/WFG5a",
            "indices": [
              "75", 
              "98"
            ],
            "url": "https://t.co/iJRsyPLHre"
          }
        ]
      },
      "extended_entities": {
        "media": [
          {
            "display_url": "pic.twitter.com/ie8ZdEArM8",
            "expanded_url": "https://twitter.com/SFOMuseum/status/684568855696535552/photo/1",
            "id_str": "684568854996107265",
            "indices": [
              "114", 
              "137"
            ],
            "media_url": "http://pbs.twimg.com/media/CYATvyJWwAEwEMT.jpg",
            "media_url_https": "https://pbs.twimg.com/media/CYATvyJWwAEwEMT.jpg",
            "sizes": {
              "large": {
                "h": "1429",
                "resize": "fit",
                "w": "2048"
              },
              "medium": {
                "h": "838",
                "resize": "fit",
                "w": "1200"
              },
              "small": {
                "h": "475",
                "resize": "fit",
                "w": "680"
              },
              "thumb": {
                "h": "150",
                "resize": "crop",
                "w": "150"
              }
            },
            "type": "photo",
            "url": "https://t.co/ie8ZdEArM8"
          }
        ]
      },
      "favorite_count": "0",
      "favorited": false,
      "full_text": "Learn more about the Darumas dolls featured in our “Mingei” exhibition at: https://t.co/iJRsyPLHre #MingeiFolkArt https://t.co/ie8ZdEArM8",
      "id_str": "684568855696535552",
      "lang": "en",
      "possibly_sensitive": false,
      "retweet_count": "0",
      "retweeted": false,
      "source": "\u003ca href=\"http://www.hootsuite.com\" rel=\"nofollow\"\u003eHootsuite\u003c/a\u003e",
      "truncated": false
    },
    "wof:name": "Twitter message #684568855696535552",
    "wof:placetype": "custom"
  },
  "geometry": {"coordinates":[-122.386166,37.616356],"type":"Point"}
}
