{
  "type": "Feature",
  "properties": {
    "sfomuseum:placetype": "tweet",
    "twitter:tweet": {
      "created": 1453430110,
      "created_at": "Fri Jan 22 02:35:10 +0000 2016",
      "display_text_range": [
        "0", 
        "140"
      ],
      "entities": {
        "media": [
          {
            "display_url": "pic.twitter.com/Z2sTQ6MVoh",
            "expanded_url": "https://twitter.com/SFOMuseum/status/690362037717852161/photo/1",
            "id_str": "690362013013401601",
            "indices": [
              "117", 
              "140"
            ],
            "media_url": "http://pbs.twimg.com/media/CZSol9gWYAEfO8E.jpg",
            "media_url_https": "https://pbs.twimg.com/media/CZSol9gWYAEfO8E.jpg",
            "sizes": {
              "large": {
                "h": "886",
                "resize": "fit",
                "w": "1024"
              },
              "medium": {
                "h": "886",
                "resize": "fit",
                "w": "1024"
              },
              "small": {
                "h": "588",
                "resize": "fit",
                "w": "680"
              },
              "thumb": {
                "h": "150",
                "resize": "crop",
                "w": "150"
              }
            },
            "type": "photo",
            "url": "https://t.co/Z2sTQ6MVoh"
          }
        ]
      },
      "extended_entities": {
        "media": [
          {
            "display_url": "pic.twitter.com/Z2sTQ6MVoh",
            "expanded_url": "https://twitter.com/SFOMuseum/status/690362037717852161/photo/1",
            "id_str": "690362013013401601",
            "indices": [
              "117", 
              "140"
            ],
            "media_url": "http://pbs.twimg.com/media/CZSol9gWYAEfO8E.jpg",
            "media_url_https": "https://pbs.twimg.com/media/CZSol9gWYAEfO8E.jpg",
            "sizes": {
              "large": {
                "h": "886",
                "resize": "fit",
                "w": "1024"
              },
              "medium": {
                "h": "886",
                "resize": "fit",
                "w": "1024"
              },
              "small": {
                "h": "588",
                "resize": "fit",
                "w": "680"
              },
              "thumb": {
                "h": "150",
                "resize": "crop",
                "w": "150"
              }
            },
            "type": "photo",
            "url": "https://t.co/Z2sTQ6MVoh"
          }
        ]
      },
      "favorite_count": "0",
      "favorited": false,
      "full_text": "These are your last few weeks to see “Mingei: Traditional Japanese Arts”, pre-security in the International Terminal https://t.co/Z2sTQ6MVoh",
      "id_str": "690362037717852161",
      "lang": "en",
      "possibly_sensitive": false,
      "retweet_count": "1",
      "retweeted": false,
      "source": "\u003ca href=\"http://twitter.com/download/iphone\" rel=\"nofollow\"\u003eTwitter for iPhone\u003c/a\u003e",
      "truncated": false
    },
    "wof:name": "Twitter message #690362037717852161",
    "wof:placetype": "custom"
  },
  "geometry": {"coordinates":[-122.386166,37.616356],"type":"Point"}
}
