{
  "type": "Feature",
  "properties": {
    "date:cessation_lower": "2022-07-08",
    "date:cessation_upper": "2022-07-08",
    "date:inception_lower": "2022-07-08",
    "date:inception_upper": "2022-07-08",
    "sfomuseum:placetype": "tweet",
    "twitter:tweet": {
      "created": 1657241804,
      "created_at": "Fri Jul 08 00:56:44 +0000 2022",
      "display_text_range": [
        "0",
        "175"
      ],
      "edit_info": {
        "initial": {
          "editTweetIds": [
            "1545210239158366208"
          ],
          "editableUntil": "2022-07-08T01:26:44.000Z",
          "editsRemaining": "5",
          "isEditEligible": false
        }
      },
      "entities": {
      },
      "favorite_count": "0",
      "favorited": false,
      "full_text": "📸 1/3:\ntimetable: Ozark Air Lines; 11/01/1951\nGift of Thomas G. Dragges\n2015.167.532\n\ntimetable: Ozark Air Lines, pocket schedule; 1951\nGift of Thomas G. Dragges\n2014.084.1157",
      "id_str": "1545210239158366208",
      "in_reply_to_screen_name": "SFOMuseum",
      "in_reply_to_status_id": "1545210234766909440",
      "in_reply_to_status_id_str": "1545210234766909440",
      "in_reply_to_user_id": "116329337",
      "in_reply_to_user_id_str": "116329337",
      "lang": "en",
      "retweet_count": "0",
      "retweeted": false,
      "source": "\u003ca href=\"https://mobile.twitter.com\" rel=\"nofollow\"\u003eTwitter Web App\u003c/a\u003e",
      "truncated": false
    },
    "wof:name": "📸 1/3:\ntimetable: Ozark Air Lines; 11/01/1951\nGift of Thomas G. Dragges\n2015.167.532\n\ntimetable: Ozark Air Lines, pocket schedule; 1951\nGift of Thomas G. Dragges\n2014.084.1157",
    "wof:placetype": "custom"
  },
  "geometry": {"coordinates":[-122.386166,37.616356],"type":"Point"}
}
