{
  "type": "Feature",
  "properties": {
    "date:cessation_lower": "2021-06-29",
    "date:cessation_upper": "2021-06-29",
    "date:inception_lower": "2021-06-29",
    "date:inception_upper": "2021-06-29",
    "sfomuseum:placetype": "tweet",
    "twitter:tweet": {
      "created": 1625005353,
      "created_at": "Tue Jun 29 22:22:33 +0000 2021",
      "display_text_range": [
        "0",
        "139"
      ],
      "edit_info": {
        "initial": {
          "editTweetIds": [
            "1410000766157291523"
          ],
          "editableUntil": "2021-06-29T23:22:33.856Z",
          "editsRemaining": "5",
          "isEditEligible": true
        }
      },
      "entities": {
        "user_mentions": [
          {
            "id_str": "16408759",
            "indices": [
              "3",
              "10"
            ],
            "name": "San Francisco International Airport (SFO) ✈️",
            "screen_name": "flySFO"
          },
          {
            "id_str": "116329337",
            "indices": [
              "124",
              "134"
            ],
            "name": "SFO Museum",
            "screen_name": "SFOMuseum"
          }
        ]
      },
      "favorite_count": "0",
      "favorited": false,
      "full_text": "RT @flySFO: ✔️ A children’s area next to the new departure gates.\n✔️ A new museum gallery featuring rotating exhibitions by @SFOMuseum.\n✔️…",
      "id_str": "1410000766157291523",
      "lang": "en",
      "retweet_count": "0",
      "retweeted": false,
      "source": "\u003ca href=\"https://mobile.twitter.com\" rel=\"nofollow\"\u003eTwitter Web App\u003c/a\u003e",
      "truncated": false
    },
    "twitter:user_mentions": [
      "flySFO",
      "SFOMuseum"
    ],
    "wof:name": "RT @flySFO: ✔️ A children’s area next to the new departure gates.\n✔️ A new museum gallery featuring rotating exhibitions by @SFOMuseum.\n✔️…",
    "wof:placetype": "custom"
  },
  "geometry": {"coordinates":[-122.386166,37.616356],"type":"Point"}
}
