{
  "type": "Feature",
  "properties": {
    "sfomuseum:placetype": "tweet",
    "twitter:tweet": {
      "created": 1386193779,
      "created_at": "Wed Dec 04 21:49:39 +0000 2013",
      "display_text_range": [
        "0", 
        "111"
      ],
      "entities": {
        "hashtags": [
          {
            "indices": [
              "34", 
              "40"
            ],
            "text": "PanAm"
          }, 
          {
            "indices": [
              "104", 
              "111"
            ],
            "text": "avgeek"
          }
        ],
        "urls": [
          {
            "display_url": "ow.ly/28vEtJ",
            "expanded_url": "http://ow.ly/28vEtJ",
            "indices": [
              "81", 
              "103"
            ],
            "url": "http://t.co/MMtJK5D89z"
          }
        ]
      },
      "favorite_count": "0",
      "favorited": false,
      "full_text": "This day marks the end of an era: #PanAm's final flight was on this day in 1991. http://t.co/MMtJK5D89z #avgeek",
      "id_str": "408352425318555648",
      "lang": "en",
      "possibly_sensitive": false,
      "retweet_count": "3",
      "retweeted": false,
      "source": "\u003ca href=\"http://www.hootsuite.com\" rel=\"nofollow\"\u003eHootsuite\u003c/a\u003e",
      "truncated": false
    },
    "wof:name": "Twitter message #408352425318555648",
    "wof:placetype": "custom"
  },
  "geometry": {"coordinates":[-122.386166,37.616356],"type":"Point"}
}
