{
  "type": "Feature",
  "properties": {
    "sfomuseum:placetype": "tweet",
    "twitter:tweet": {
      "created": 1489026306,
      "created_at": "Thu Mar 09 02:25:06 +0000 2017",
      "display_text_range": [
        "0", 
        "108"
      ],
      "entities": {
        "media": [
          {
            "display_url": "pic.twitter.com/iyOYhQFxaA",
            "expanded_url": "https://twitter.com/SFOMuseum/status/839663304066928642/photo/1",
            "id_str": "839663300564541440",
            "indices": [
              "85", 
              "108"
            ],
            "media_url": "http://pbs.twimg.com/media/C6cVUrkU4AAGS74.jpg",
            "media_url_https": "https://pbs.twimg.com/media/C6cVUrkU4AAGS74.jpg",
            "sizes": {
              "large": {
                "h": "2000",
                "resize": "fit",
                "w": "1333"
              },
              "medium": {
                "h": "1200",
                "resize": "fit",
                "w": "800"
              },
              "small": {
                "h": "680",
                "resize": "fit",
                "w": "453"
              },
              "thumb": {
                "h": "150",
                "resize": "crop",
                "w": "150"
              }
            },
            "type": "photo",
            "url": "https://t.co/iyOYhQFxaA"
          }
        ],
        "urls": [
          {
            "display_url": "bit.ly/fashioninflight",
            "expanded_url": "http://bit.ly/fashioninflight",
            "indices": [
              "61", 
              "84"
            ],
            "url": "https://t.co/UbL4YNFAUD"
          }
        ]
      },
      "extended_entities": {
        "media": [
          {
            "display_url": "pic.twitter.com/iyOYhQFxaA",
            "expanded_url": "https://twitter.com/SFOMuseum/status/839663304066928642/photo/1",
            "id_str": "839663300564541440",
            "indices": [
              "85", 
              "108"
            ],
            "media_url": "http://pbs.twimg.com/media/C6cVUrkU4AAGS74.jpg",
            "media_url_https": "https://pbs.twimg.com/media/C6cVUrkU4AAGS74.jpg",
            "sizes": {
              "large": {
                "h": "2000",
                "resize": "fit",
                "w": "1333"
              },
              "medium": {
                "h": "1200",
                "resize": "fit",
                "w": "800"
              },
              "small": {
                "h": "680",
                "resize": "fit",
                "w": "453"
              },
              "thumb": {
                "h": "150",
                "resize": "crop",
                "w": "150"
              }
            },
            "type": "photo",
            "url": "https://t.co/iyOYhQFxaA"
          }
        ]
      },
      "favorite_count": "7",
      "favorited": false,
      "full_text": "Have you seen our new banners in the International Terminal? https://t.co/UbL4YNFAUD https://t.co/iyOYhQFxaA",
      "id_str": "839663304066928642",
      "lang": "en",
      "possibly_sensitive": false,
      "retweet_count": "0",
      "retweeted": false,
      "source": "\u003ca href=\"http://www.hootsuite.com\" rel=\"nofollow\"\u003eHootsuite\u003c/a\u003e",
      "truncated": false
    },
    "wof:name": "Twitter message #839663304066928642",
    "wof:placetype": "custom"
  },
  "geometry": {"coordinates":[-122.386166,37.616356],"type":"Point"}
}
