{
  "type": "Feature",
  "properties": {
    "date:cessation_lower": "2013-06-05",
    "date:cessation_upper": "2013-06-05",
    "date:inception_lower": "2013-06-05",
    "date:inception_upper": "2013-06-05",
    "iso:country": "US",
    "sfomuseum:placetype": "tweet",
    "twitter:tweet": {
      "created": 1370466304,
      "created_at": "Wed Jun 05 21:05:04 +0000 2013",
      "display_text_range": [
        "0", 
        "108"
      ],
      "entities": {
        "hashtags": [
          {
            "indices": [
              "45", 
              "54"
            ],
            "text": "souvenir"
          }
        ],
        "urls": [
          {
            "display_url": "instagram.com/p/aMQxRCxk_Q/",
            "expanded_url": "http://instagram.com/p/aMQxRCxk_Q/",
            "indices": [
              "86", 
              "108"
            ],
            "url": "http://t.co/3Dg4Oem4yZ"
          }
        ]
      },
      "favorite_count": "0",
      "favorited": false,
      "full_text": "On your next trip to Hawaii, be sure to mail #souvenir coconuts instead of postcards. http://t.co/3Dg4Oem4yZ",
      "id_str": "342386613256609792",
      "lang": "en",
      "possibly_sensitive": false,
      "retweet_count": "0",
      "retweeted": false,
      "source": "\u003ca href=\"http://instagram.com\" rel=\"nofollow\"\u003eInstagram\u003c/a\u003e",
      "truncated": false
    },
    "wof:name": "On your next trip to Hawaii, be sure to mail #souvenir coconuts instead of postcards. http://t.co/3Dg4Oem4yZ",
    "wof:placetype": "custom"
  },
  "geometry": {"coordinates":[-122.386166,37.616356],"type":"Point"}
}
