{
  "type": "Feature",
  "properties": {
    "date:cessation_lower": "2014-07-21",
    "date:cessation_upper": "2014-07-21",
    "date:inception_lower": "2014-07-21",
    "date:inception_upper": "2014-07-21",
    "iso:country": "US",
    "sfomuseum:placetype": "tweet",
    "twitter:tweet": {
      "created": 1405963182,
      "created_at": "Mon Jul 21 17:19:42 +0000 2014",
      "display_text_range": [
        "0", 
        "61"
      ],
      "entities": {
        "user_mentions": [
          {
            "id_str": "18344457",
            "indices": [
              "0", 
              "7"
            ],
            "name": "bogie",
            "screen_name": "cbogie"
          }
        ]
      },
      "favorite_count": "1",
      "favorited": false,
      "full_text": "@cbogie Ha! As long as no animals go stampeding through it...",
      "id_str": "491271309641666560",
      "in_reply_to_screen_name": "cbogie",
      "in_reply_to_status_id": "491268146511089666",
      "in_reply_to_status_id_str": "491268146511089666",
      "in_reply_to_user_id": "18344457",
      "in_reply_to_user_id_str": "18344457",
      "lang": "en",
      "retweet_count": "0",
      "retweeted": false,
      "source": "\u003ca href=\"http://www.hootsuite.com\" rel=\"nofollow\"\u003eHootsuite\u003c/a\u003e",
      "truncated": false
    },
    "wof:name": "@cbogie Ha! As long as no animals go stampeding through it...",
    "wof:placetype": "custom"
  },
  "geometry": {"coordinates":[-122.386166,37.616356],"type":"Point"}
}
