{
  "type": "Feature",
  "properties": {
    "date:cessation_lower": "2022-07-18",
    "date:cessation_upper": "2022-07-18",
    "date:inception_lower": "2022-07-18",
    "date:inception_upper": "2022-07-18",
    "sfomuseum:placetype": "tweet",
    "twitter:tweet": {
      "created": 1658183633,
      "created_at": "Mon Jul 18 22:33:53 +0000 2022",
      "display_text_range": [
        "0",
        "126"
      ],
      "edit_info": {
        "initial": {
          "editTweetIds": [
            "1549160555792834560"
          ],
          "editableUntil": "2022-07-18T23:03:53.000Z",
          "editsRemaining": "5",
          "isEditEligible": false
        }
      },
      "entities": {
        "urls": [
          {
            "display_url": "bit.ly/3yCZHlb",
            "expanded_url": "https://bit.ly/3yCZHlb",
            "indices": [
              "103",
              "126"
            ],
            "url": "https://t.co/LAit576DRy"
          }
        ]
      },
      "favorite_count": "0",
      "favorited": false,
      "full_text": "📸 2/2:\nflight attendant smock: Braniff International; 1968\nGift of Thomas G. Dragges\n2001.016.081 a b\n\nhttps://t.co/LAit576DRy",
      "id_str": "1549160555792834560",
      "in_reply_to_screen_name": "SFOMuseum",
      "in_reply_to_status_id": "1549160554370965504",
      "in_reply_to_status_id_str": "1549160554370965504",
      "in_reply_to_user_id": "116329337",
      "in_reply_to_user_id_str": "116329337",
      "lang": "en",
      "possibly_sensitive": false,
      "retweet_count": "0",
      "retweeted": false,
      "source": "\u003ca href=\"https://mobile.twitter.com\" rel=\"nofollow\"\u003eTwitter Web App\u003c/a\u003e",
      "truncated": false
    },
    "wof:name": "📸 2/2:\nflight attendant smock: Braniff International; 1968\nGift of Thomas G. Dragges\n2001.016.081 a b\n\nhttps://t.co/LAit576DRy",
    "wof:placetype": "custom"
  },
  "geometry": {"coordinates":[-122.386166,37.616356],"type":"Point"}
}
