{
  "type": "Feature",
  "properties": {
    "sfomuseum:placetype": "tweet",
    "twitter:tweet": {
      "created": 1547611207,
      "created_at": "Wed Jan 16 04:00:07 +0000 2019",
      "display_text_range": [
        "0", 
        "149"
      ],
      "entities": {
        "hashtags": [
          {
            "indices": [
              "111", 
              "125"
            ],
            "text": "1950sConsumer"
          }
        ],
        "media": [
          {
            "display_url": "pic.twitter.com/aIn5TyAA9Q",
            "expanded_url": "https://twitter.com/SFOMuseum/status/1085386190298189824/photo/1",
            "id_str": "1085386187534204929",
            "indices": [
              "126", 
              "149"
            ],
            "media_url": "http://pbs.twimg.com/media/DxAQ_KgXgAE85vS.jpg",
            "media_url_https": "https://pbs.twimg.com/media/DxAQ_KgXgAE85vS.jpg",
            "sizes": {
              "large": {
                "h": "1333",
                "resize": "fit",
                "w": "2000"
              },
              "medium": {
                "h": "800",
                "resize": "fit",
                "w": "1200"
              },
              "small": {
                "h": "453",
                "resize": "fit",
                "w": "680"
              },
              "thumb": {
                "h": "150",
                "resize": "crop",
                "w": "150"
              }
            },
            "type": "photo",
            "url": "https://t.co/aIn5TyAA9Q"
          }
        ],
        "urls": [
          {
            "display_url": "bit.ly/1950sConsumer",
            "expanded_url": "http://bit.ly/1950sConsumer",
            "indices": [
              "87", 
              "110"
            ],
            "url": "https://t.co/A9goh7obtY"
          }
        ]
      },
      "extended_entities": {
        "media": [
          {
            "display_url": "pic.twitter.com/aIn5TyAA9Q",
            "expanded_url": "https://twitter.com/SFOMuseum/status/1085386190298189824/photo/1",
            "id_str": "1085386187534204929",
            "indices": [
              "126", 
              "149"
            ],
            "media_url": "http://pbs.twimg.com/media/DxAQ_KgXgAE85vS.jpg",
            "media_url_https": "https://pbs.twimg.com/media/DxAQ_KgXgAE85vS.jpg",
            "sizes": {
              "large": {
                "h": "1333",
                "resize": "fit",
                "w": "2000"
              },
              "medium": {
                "h": "800",
                "resize": "fit",
                "w": "1200"
              },
              "small": {
                "h": "453",
                "resize": "fit",
                "w": "680"
              },
              "thumb": {
                "h": "150",
                "resize": "crop",
                "w": "150"
              }
            },
            "type": "photo",
            "url": "https://t.co/aIn5TyAA9Q"
          }
        ]
      },
      "favorite_count": "3",
      "favorited": false,
      "full_text": "\"The Modern Consumer: Products and Style\" is on display, post-security, in Terminal 3. https://t.co/A9goh7obtY #1950sConsumer https://t.co/aIn5TyAA9Q",
      "id_str": "1085386190298189824",
      "lang": "en",
      "possibly_sensitive": false,
      "retweet_count": "0",
      "retweeted": false,
      "source": "\u003ca href=\"https://www.hootsuite.com\" rel=\"nofollow\"\u003eHootsuite Inc.\u003c/a\u003e",
      "truncated": false
    },
    "wof:name": "Twitter message #1085386190298189824",
    "wof:placetype": "custom"
  },
  "geometry": {"coordinates":[-122.386166,37.616356],"type":"Point"}
}
