{
  "type": "Feature",
  "properties": {
    "sfomuseum:placetype": "tweet",
    "twitter:tweet": {
      "created": 1507949404,
      "created_at": "Sat Oct 14 02:50:04 +0000 2017",
      "display_text_range": [
        "0", 
        "161"
      ],
      "entities": {
        "media": [
          {
            "display_url": "pic.twitter.com/GaEUXlIgN9",
            "expanded_url": "https://twitter.com/SFOMuseum/status/919032530308878338/photo/1",
            "id_str": "919032526345293824",
            "indices": [
              "138", 
              "161"
            ],
            "media_url": "http://pbs.twimg.com/media/DMEPNqXXUAAj3A2.jpg",
            "media_url_https": "https://pbs.twimg.com/media/DMEPNqXXUAAj3A2.jpg",
            "sizes": {
              "large": {
                "h": "2000",
                "resize": "fit",
                "w": "1461"
              },
              "medium": {
                "h": "1200",
                "resize": "fit",
                "w": "877"
              },
              "small": {
                "h": "680",
                "resize": "fit",
                "w": "497"
              },
              "thumb": {
                "h": "150",
                "resize": "crop",
                "w": "150"
              }
            },
            "type": "photo",
            "url": "https://t.co/GaEUXlIgN9"
          }
        ],
        "urls": [
          {
            "display_url": "bit.ly/ShoesinCulture",
            "expanded_url": "http://bit.ly/ShoesinCulture",
            "indices": [
              "114", 
              "137"
            ],
            "url": "https://t.co/BRnTenNejX"
          }
        ]
      },
      "extended_entities": {
        "media": [
          {
            "display_url": "pic.twitter.com/GaEUXlIgN9",
            "expanded_url": "https://twitter.com/SFOMuseum/status/919032530308878338/photo/1",
            "id_str": "919032526345293824",
            "indices": [
              "138", 
              "161"
            ],
            "media_url": "http://pbs.twimg.com/media/DMEPNqXXUAAj3A2.jpg",
            "media_url_https": "https://pbs.twimg.com/media/DMEPNqXXUAAj3A2.jpg",
            "sizes": {
              "large": {
                "h": "2000",
                "resize": "fit",
                "w": "1461"
              },
              "medium": {
                "h": "1200",
                "resize": "fit",
                "w": "877"
              },
              "small": {
                "h": "680",
                "resize": "fit",
                "w": "497"
              },
              "thumb": {
                "h": "150",
                "resize": "crop",
                "w": "150"
              }
            },
            "type": "photo",
            "url": "https://t.co/GaEUXlIgN9"
          }
        ]
      },
      "favorite_count": "2",
      "favorited": false,
      "full_text": "See more shoes in \"Stepping Out: Shoes in World Culture\" on display, pre-security, in the International Terminal. https://t.co/BRnTenNejX https://t.co/GaEUXlIgN9",
      "id_str": "919032530308878338",
      "lang": "en",
      "possibly_sensitive": false,
      "retweet_count": "0",
      "retweeted": false,
      "source": "\u003ca href=\"http://www.hootsuite.com\" rel=\"nofollow\"\u003eHootsuite\u003c/a\u003e",
      "truncated": false
    },
    "wof:name": "Twitter message #919032530308878338",
    "wof:placetype": "custom"
  },
  "geometry": {"coordinates":[-122.386166,37.616356],"type":"Point"}
}
