{
  "type": "Feature",
  "properties": {
    "date:cessation_lower": "2016-07-15",
    "date:cessation_upper": "2016-07-15",
    "date:inception_lower": "2016-07-15",
    "date:inception_upper": "2016-07-15",
    "iso:country": "US",
    "sfomuseum:placetype": "tweet",
    "twitter:tweet": {
      "created": 1468609533,
      "created_at": "Fri Jul 15 19:05:33 +0000 2016",
      "display_text_range": [
        "0", 
        "126"
      ],
      "entities": {
        "hashtags": [
          {
            "indices": [
              "92", 
              "102"
            ],
            "text": "Boeing100"
          }
        ],
        "urls": [
          {
            "display_url": "projects.seattletimes.com/2016/boeing-ti…",
            "expanded_url": "http://projects.seattletimes.com/2016/boeing-timeline/",
            "indices": [
              "103", 
              "126"
            ],
            "url": "https://t.co/VnVPn0TC7P"
          }
        ],
        "user_mentions": [
          {
            "id_str": "14352556",
            "indices": [
              "44", 
              "57"
            ],
            "name": "The Seattle Times",
            "screen_name": "seattletimes"
          }
        ]
      },
      "favorite_count": "1",
      "favorited": false,
      "full_text": "Check out this interactive time line by the @seattletimes! Flying high: 100 years of Boeing #Boeing100 https://t.co/VnVPn0TC7P",
      "id_str": "754029150369873920",
      "lang": "en",
      "possibly_sensitive": false,
      "retweet_count": "0",
      "retweeted": false,
      "source": "\u003ca href=\"http://www.hootsuite.com\" rel=\"nofollow\"\u003eHootsuite\u003c/a\u003e",
      "truncated": false
    },
    "wof:name": "Check out this interactive time line by the @seattletimes! Flying high: 100 years of Boeing #Boeing100 https://t.co/VnVPn0TC7P",
    "wof:placetype": "custom"
  },
  "geometry": {"coordinates":[-122.386166,37.616356],"type":"Point"}
}
