{
  "type": "Feature",
  "properties": {
    "date:cessation_lower": "2021-04-07",
    "date:cessation_upper": "2021-04-07",
    "date:inception_lower": "2021-04-07",
    "date:inception_upper": "2021-04-07",
    "sfomuseum:placetype": "tweet",
    "twitter:tweet": {
      "created": 1617832470,
      "created_at": "Wed Apr 07 21:54:30 +0000 2021",
      "display_text_range": [
        "0",
        "279"
      ],
      "edit_info": {
        "initial": {
          "editTweetIds": [
            "1379915513107607553"
          ],
          "editableUntil": "2021-04-07T22:24:30.572Z",
          "editsRemaining": "5",
          "isEditEligible": true
        }
      },
      "entities": {
      },
      "favorite_count": "0",
      "favorited": false,
      "full_text": "📸2:\nAerovias Venezuela Europa, DC-4 cockpit; 1950s\nGift of Thomas G. Dragges\n2015.166.0108\n\nPan Am, Boeing 314a “Capetown Clipper” and Douglas DC-4; c. late 1940s\n1993.03.14\n\nPan Am, DC-4; late 1940s\n1993.03.22\n\nWestern Air Lines; Nov. 1949\nGift of Thomas G. Dragges\n2015.167.887",
      "id_str": "1379915513107607553",
      "in_reply_to_screen_name": "SFOMuseum",
      "in_reply_to_status_id": "1379915511228551169",
      "in_reply_to_status_id_str": "1379915511228551169",
      "in_reply_to_user_id": "116329337",
      "in_reply_to_user_id_str": "116329337",
      "lang": "en",
      "retweet_count": "0",
      "retweeted": false,
      "source": "\u003ca href=\"https://mobile.twitter.com\" rel=\"nofollow\"\u003eTwitter Web App\u003c/a\u003e",
      "truncated": false
    },
    "wof:name": "📸2:\nAerovias Venezuela Europa, DC-4 cockpit; 1950s\nGift of Thomas G. Dragges\n2015.166.0108\n\nPan Am, Boeing 314a “Capetown Clipper” and Douglas DC-4; c. late 1940s\n1993.03.14\n\nPan Am, DC-4; late 1940s\n1993.03.22\n\nWestern Air Lines; Nov. 1949\nGift of Thomas G. Dragges\n2015.167.887",
    "wof:placetype": "custom"
  },
  "geometry": {"coordinates":[-122.386166,37.616356],"type":"Point"}
}
