{
  "type": "Feature",
  "properties": {
    "date:cessation_lower": "2021-10-21",
    "date:cessation_upper": "2021-10-21",
    "date:inception_lower": "2021-10-21",
    "date:inception_upper": "2021-10-21",
    "sfomuseum:placetype": "tweet",
    "twitter:tweet": {
      "created": 1634860424,
      "created_at": "Thu Oct 21 23:53:44 +0000 2021",
      "display_text_range": [
        "0",
        "93"
      ],
      "edit_info": {
        "initial": {
          "editTweetIds": [
            "1451335928010534916"
          ],
          "editableUntil": "2021-10-22T00:23:44.412Z",
          "editsRemaining": "5",
          "isEditEligible": true
        }
      },
      "entities": {
      },
      "favorite_count": "0",
      "favorited": false,
      "full_text": "📸: negative: San Francisco International Airport (SFO), Concorde; 1974\nTransfer\n2011.032.2610",
      "id_str": "1451335928010534916",
      "in_reply_to_screen_name": "SFOMuseum",
      "in_reply_to_status_id": "1451335926525825029",
      "in_reply_to_status_id_str": "1451335926525825029",
      "in_reply_to_user_id": "116329337",
      "in_reply_to_user_id_str": "116329337",
      "lang": "fr",
      "retweet_count": "0",
      "retweeted": false,
      "source": "\u003ca href=\"http://twitter.com/download/iphone\" rel=\"nofollow\"\u003eTwitter for iPhone\u003c/a\u003e",
      "truncated": false
    },
    "wof:name": "📸: negative: San Francisco International Airport (SFO), Concorde; 1974\nTransfer\n2011.032.2610",
    "wof:placetype": "custom"
  },
  "geometry": {"coordinates":[-122.386166,37.616356],"type":"Point"}
}
