{
  "type": "Feature",
  "properties": {
    "date:cessation_lower": "2018-12-05",
    "date:cessation_upper": "2018-12-05",
    "date:inception_lower": "2018-12-05",
    "date:inception_upper": "2018-12-05",
    "iso:country": "US",
    "sfomuseum:placetype": "tweet",
    "twitter:tweet": {
      "created": 1544037339,
      "created_at": "Wed Dec 05 19:15:39 +0000 2018",
      "display_text_range": [
        "0",
        "122"
      ],
      "edit_info": {
        "initial": {
          "editTweetIds": [
            "1070396297822105601"
          ],
          "editableUntil": "2018-12-05T20:15:39.059Z",
          "editsRemaining": "5",
          "isEditEligible": true
        }
      },
      "entities": {
        "urls": [
          {
            "display_url": "airlinemaps.tumblr.com/post/180136163…",
            "expanded_url": "http://airlinemaps.tumblr.com/post/180136163922/avianca-60th-anniversary-map-1979-an-avianca-60th",
            "indices": [
              "75",
              "98"
            ],
            "url": "https://t.co/scy5HvcPuy"
          },
          {
            "display_url": "twitter.com/avianca/status…",
            "expanded_url": "https://twitter.com/avianca/status/1070301769643679744",
            "indices": [
              "99",
              "122"
            ],
            "url": "https://t.co/0FmtKnpXPn"
          }
        ],
        "user_mentions": [
          {
            "id_str": "3609709582",
            "indices": [
              "3",
              "15"
            ],
            "name": "Airline Maps",
            "screen_name": "airlinemaps"
          }
        ]
      },
      "favorite_count": "0",
      "favorited": false,
      "full_text": "RT @airlinemaps: Happy 99th birthday Avianca! 🎂\n\nA throwback to your 60th: https://t.co/scy5HvcPuy https://t.co/0FmtKnpXPn",
      "id_str": "1070396297822105601",
      "lang": "en",
      "possibly_sensitive": false,
      "retweet_count": "0",
      "retweeted": false,
      "source": "\u003ca href=\"http://twitter.com/#!/download/ipad\" rel=\"nofollow\"\u003eTwitter for iPad\u003c/a\u003e",
      "truncated": false
    },
    "twitter:user_mentions": [
      "airlinemaps"
    ],
    "wof:name": "RT @airlinemaps: Happy 99th birthday Avianca! 🎂\n\nA throwback to your 60th: https://t.co/scy5HvcPuy https://t.co/0FmtKnpXPn",
    "wof:placetype": "custom"
  },
  "geometry": {"coordinates":[-122.386166,37.616356],"type":"Point"}
}
