{
  "type": "Feature",
  "properties": {
    "date:cessation_lower":"2012-02-07",
    "date:cessation_upper":"2012-02-07",
    "date:inception_lower":"2012-02-07",
    "date:inception_upper":"2012-02-07",
    "iso:country":"US",
    "sfomuseum:placetype":"tweet",
    "twitter:tweet":{
        "created":1328641321,
        "created_at":"Tue Feb 07 19:02:01 +0000 2012",
        "display_text_range":[
            "0",
            "139"
        ],
        "entities":{
            "urls":[
                {
                    "display_url":"bit.ly/sGPNcT",
                    "expanded_url":"http://bit.ly/sGPNcT",
                    "indices":[
                        "119",
                        "139"
                    ],
                    "url":"http://t.co/YzSJ0uqV"
                }
            ]
        },
        "favorite_count":"0",
        "favorited":false,
        "full_text":"Moto Devil's 160cc Raid was good race performer but was unable to win the ultimate victory: a Grand Prix Championship. http://t.co/YzSJ0uqV",
        "id_str":"166959920204361728",
        "lang":"en",
        "possibly_sensitive":false,
        "retweet_count":"0",
        "retweeted":false,
        "source":"<a href=\"https://about.twitter.com/products/tweetdeck\" rel=\"nofollow\">TweetDeck</a>",
        "truncated":false
    },
    "wof:name":"Moto Devil's 160cc Raid was good race performer but was unable to win the ultimate victory: a Grand Prix Championship. http://t.co/YzSJ0uqV",
    "wof:placetype":"custom"
},
  "geometry": {"coordinates":[-122.386166,37.616356],"type":"Point"}
}