{
  "type": "Feature",
  "properties": {
    "date:cessation_lower": "2021-09-15",
    "date:cessation_upper": "2021-09-15",
    "date:inception_lower": "2021-09-15",
    "date:inception_upper": "2021-09-15",
    "sfomuseum:placetype": "tweet",
    "twitter:tweet": {
      "created": 1631664955,
      "created_at": "Wed Sep 15 00:15:55 +0000 2021",
      "display_text_range": [
        "0",
        "215"
      ],
      "edit_info": {
        "initial": {
          "editTweetIds": [
            "1437933161753636870"
          ],
          "editableUntil": "2021-09-15T01:15:55.925Z",
          "editsRemaining": "5",
          "isEditEligible": true
        }
      },
      "entities": {
      },
      "favorite_count": "0",
      "favorited": false,
      "full_text": "📸 1/2:\nnegative: San Francisco International Airport (SFO), aerial, South Terminal construction; 1963\nTransfer\n2011.032.0527\n.\nnegative: San Francisco International Airport (SFO), aerial; 1963\nTransfer\n2011.032.1100",
      "id_str": "1437933161753636870",
      "in_reply_to_screen_name": "SFOMuseum",
      "in_reply_to_status_id": "1437933158251462657",
      "in_reply_to_status_id_str": "1437933158251462657",
      "in_reply_to_user_id": "116329337",
      "in_reply_to_user_id_str": "116329337",
      "lang": "en",
      "retweet_count": "0",
      "retweeted": false,
      "source": "\u003ca href=\"https://mobile.twitter.com\" rel=\"nofollow\"\u003eTwitter Web App\u003c/a\u003e",
      "truncated": false
    },
    "wof:name": "📸 1/2:\nnegative: San Francisco International Airport (SFO), aerial, South Terminal construction; 1963\nTransfer\n2011.032.0527\n.\nnegative: San Francisco International Airport (SFO), aerial; 1963\nTransfer\n2011.032.1100",
    "wof:placetype": "custom"
  },
  "geometry": {"coordinates":[-122.386166,37.616356],"type":"Point"}
}
