{
  "type": "Feature",
  "properties": {
    "date:cessation_lower": "2021-04-07",
    "date:cessation_upper": "2021-04-07",
    "date:inception_lower": "2021-04-07",
    "date:inception_upper": "2021-04-07",
    "sfomuseum:placetype": "tweet",
    "twitter:tweet": {
      "created": 1617832470,
      "created_at": "Wed Apr 07 21:54:30 +0000 2021",
      "display_text_range": [
        "0",
        "278"
      ],
      "edit_info": {
        "initial": {
          "editTweetIds": [
            "1379915511228551169"
          ],
          "editableUntil": "2021-04-07T22:24:30.124Z",
          "editsRemaining": "5",
          "isEditEligible": true
        }
      },
      "entities": {
      },
      "favorite_count": "0",
      "favorited": false,
      "full_text": "📸:\nUnited DC-4E; c. 1939\nGift of Jane Luna Euler\n2013.106.026\n\nUnited DC-4E; 1939\nGift of Frank A. Norick\n2013.075.015\n\nColonial Airlines, DC-4 over New York City; c. 1946 \nGift of M.D. Klaas\n2018.112.0121\n\nMATS, Douglas C-54; c. 1945\nGift of the Pan Am Assoc.\n2000.058.0472.028",
      "id_str": "1379915511228551169",
      "in_reply_to_screen_name": "SFOMuseum",
      "in_reply_to_status_id": "1379915507319508995",
      "in_reply_to_status_id_str": "1379915507319508995",
      "in_reply_to_user_id": "116329337",
      "in_reply_to_user_id_str": "116329337",
      "lang": "en",
      "retweet_count": "0",
      "retweeted": false,
      "source": "\u003ca href=\"https://mobile.twitter.com\" rel=\"nofollow\"\u003eTwitter Web App\u003c/a\u003e",
      "truncated": false
    },
    "wof:name": "📸:\nUnited DC-4E; c. 1939\nGift of Jane Luna Euler\n2013.106.026\n\nUnited DC-4E; 1939\nGift of Frank A. Norick\n2013.075.015\n\nColonial Airlines, DC-4 over New York City; c. 1946 \nGift of M.D. Klaas\n2018.112.0121\n\nMATS, Douglas C-54; c. 1945\nGift of the Pan Am Assoc.\n2000.058.0472.028",
    "wof:placetype": "custom"
  },
  "geometry": {"coordinates":[-122.386166,37.616356],"type":"Point"}
}
