{
  "type": "Feature",
  "properties": {
    "date:cessation_lower":"2018-05-18",
    "date:cessation_upper":"2018-05-18",
    "date:inception_lower":"2018-05-18",
    "date:inception_upper":"2018-05-18",
    "iso:country":"US",
    "sfomuseum:placetype":"tweet",
    "twitter:tweet":{
        "created":1526666536,
        "created_at":"Fri May 18 18:02:16 +0000 2018",
        "display_text_range":[
            "0",
            "54"
        ],
        "entities":{
            "hashtags":[
                {
                    "indices":[
                        "11",
                        "30"
                    ],
                    "text":"historyinthemaking"
                }
            ],
            "urls":[
                {
                    "display_url":"twitter.com/kimblackproud/\u2026",
                    "expanded_url":"https://twitter.com/kimblackproud/status/996861581165285377",
                    "indices":[
                        "31",
                        "54"
                    ],
                    "url":"https://t.co/gSwJEsTpvM"
                }
            ]
        },
        "favorite_count":"1",
        "favorited":false,
        "full_text":"\ud83d\udc69\ud83c\udffe\u200d\u2708\ufe0f\ud83d\udc69\ud83c\udffe\u200d\u2708\ufe0f #historyinthemaking https://t.co/gSwJEsTpvM",
        "id_str":"997537870964445185",
        "lang":"und",
        "possibly_sensitive":false,
        "retweet_count":"0",
        "retweeted":false,
        "source":"<a href=\"http://twitter.com\" rel=\"nofollow\">Twitter Web Client</a>",
        "truncated":false
    },
    "wof:name":"\ud83d\udc69\ud83c\udffe\u200d\u2708\ufe0f\ud83d\udc69\ud83c\udffe\u200d\u2708\ufe0f #historyinthemaking https://t.co/gSwJEsTpvM",
    "wof:placetype":"custom"
},
  "geometry": {"coordinates":[-122.386166,37.616356],"type":"Point"}
}