{
  "type": "Feature",
  "properties": {
    "sfomuseum:placetype": "tweet",
    "twitter:tweet": {
      "created": 1322003242,
      "created_at": "Tue Nov 22 23:07:22 +0000 2011",
      "display_text_range": [
        "0", 
        "70"
      ],
      "entities": {
        "user_mentions": [
          {
            "id_str": "17659635",
            "indices": [
              "15", 
              "26"
            ],
            "name": "Fran",
            "screen_name": "FranBoogie"
          }, 
          {
            "id_str": "231887259",
            "indices": [
              "27", 
              "38"
            ],
            "name": "Thud Rumble",
            "screen_name": "ThudRumble"
          }, 
          {
            "id_str": "21543254",
            "indices": [
              "39", 
              "47"
            ],
            "name": "DJ Q*BERT",
            "screen_name": "DJQbert"
          }, 
          {
            "id_str": "116329337",
            "indices": [
              "48", 
              "58"
            ],
            "name": "SFO Museum",
            "screen_name": "SFOMuseum"
          }
        ]
      },
      "favorite_count": "0",
      "favorited": false,
      "full_text": "Absolutely! RT @FranBoogie @ThudRumble @DJQbert @SFOMuseum - all ages?",
      "id_str": "139117799728611328",
      "lang": "en",
      "retweet_count": "0",
      "retweeted": false,
      "source": "\u003ca href=\"https://about.twitter.com/products/tweetdeck\" rel=\"nofollow\"\u003eTweetDeck\u003c/a\u003e",
      "truncated": false
    },
    "wof:name": "Twitter message #139117799728611328",
    "wof:placetype": "custom"
  },
  "geometry": {"coordinates":[-122.386166,37.616356],"type":"Point"}
}
