{
  "type": "Feature",
  "properties": {
    "sfomuseum:placetype": "tweet",
    "twitter:tweet": {
      "created": 1334174675,
      "created_at": "Wed Apr 11 20:04:35 +0000 2012",
      "display_text_range": [
        "0", 
        "139"
      ],
      "entities": {
        "urls": [
          {
            "display_url": "bit.ly/Hy32on",
            "expanded_url": "http://bit.ly/Hy32on",
            "indices": [
              "119", 
              "139"
            ],
            "url": "http://t.co/hBFtLij1"
          }
        ]
      },
      "favorite_count": "0",
      "favorited": false,
      "full_text": "The zipper's advent was a breakthrough for open-cockpit flight suit design, allowing ventilation \u0026 faster suiting time http://t.co/hBFtLij1",
      "id_str": "190168487438729216",
      "lang": "en",
      "possibly_sensitive": false,
      "retweet_count": "0",
      "retweeted": false,
      "source": "\u003ca href=\"https://about.twitter.com/products/tweetdeck\" rel=\"nofollow\"\u003eTweetDeck\u003c/a\u003e",
      "truncated": false
    },
    "wof:name": "Twitter message #190168487438729216",
    "wof:placetype": "custom"
  },
  "geometry": {"coordinates":[-122.386166,37.616356],"type":"Point"}
}
