{
  "type": "Feature",
  "properties": {
    "sfomuseum:placetype": "tweet",
    "twitter:tweet": {
      "created": 1404256730,
      "created_at": "Tue Jul 01 23:18:50 +0000 2014",
      "display_text_range": [
        "0", 
        "123"
      ],
      "entities": {
        "urls": [
          {
            "display_url": "instagram.com/p/p7TZGpRk0w/",
            "expanded_url": "http://instagram.com/p/p7TZGpRk0w/",
            "indices": [
              "101", 
              "123"
            ],
            "url": "http://t.co/dVLXvLoEbm"
          }
        ]
      },
      "favorite_count": "1",
      "favorited": false,
      "full_text": "Moon jar perfection by Kim Yik-yung, who, inspired by Bernard Leach, shifted her original education… http://t.co/dVLXvLoEbm",
      "id_str": "484113931883921408",
      "lang": "en",
      "possibly_sensitive": false,
      "retweet_count": "1",
      "retweeted": false,
      "source": "\u003ca href=\"http://instagram.com\" rel=\"nofollow\"\u003eInstagram\u003c/a\u003e",
      "truncated": false
    },
    "wof:name": "Twitter message #484113931883921408",
    "wof:placetype": "custom"
  },
  "geometry": {"coordinates":[-122.386166,37.616356],"type":"Point"}
}
