{
  "type": "Feature",
  "properties": {
    "date:cessation_lower": "2018-03-08",
    "date:cessation_upper": "2018-03-08",
    "date:inception_lower": "2018-03-08",
    "date:inception_upper": "2018-03-08",
    "iso:country": "US",
    "sfomuseum:placetype": "tweet",
    "twitter:tweet": {
      "created": 1520531153,
      "created_at": "Thu Mar 08 17:45:53 +0000 2018",
      "display_text_range": [
        "0",
        "59"
      ],
      "edit_info": {
        "initial": {
          "editTweetIds": [
            "971804211603124224"
          ],
          "editableUntil": "2018-03-08T18:15:53.952Z",
          "editsRemaining": "5",
          "isEditEligible": true
        }
      },
      "entities": {
        "hashtags": [
          {
            "indices": [
              "12",
              "35"
            ],
            "text": "InternationalWomensDay"
          }
        ],
        "urls": [
          {
            "display_url": "twitter.com/emirates/statu…",
            "expanded_url": "https://twitter.com/emirates/status/970977811556073472",
            "indices": [
              "36",
              "59"
            ],
            "url": "https://t.co/BG1p2xOGnM"
          }
        ],
        "user_mentions": [
          {
            "id_str": "16408759",
            "indices": [
              "3",
              "10"
            ],
            "name": "San Francisco International Airport (SFO) ✈️",
            "screen_name": "flySFO"
          }
        ]
      },
      "favorite_count": "0",
      "favorited": false,
      "full_text": "RT @flySFO: #InternationalWomensDay https://t.co/BG1p2xOGnM",
      "id_str": "971804211603124224",
      "lang": "qme",
      "possibly_sensitive": false,
      "retweet_count": "0",
      "retweeted": false,
      "source": "\u003ca href=\"http://twitter.com\" rel=\"nofollow\"\u003eTwitter Web Client\u003c/a\u003e",
      "truncated": false
    },
    "wof:name": "RT @flySFO: #InternationalWomensDay https://t.co/BG1p2xOGnM",
    "wof:placetype": "custom"
  },
  "geometry": {"coordinates":[-122.386166,37.616356],"type":"Point"}
}
