{
  "type": "Feature",
  "properties": {
    "date:cessation_lower": "2012-08-03",
    "date:cessation_upper": "2012-08-03",
    "date:inception_lower": "2012-08-03",
    "date:inception_upper": "2012-08-03",
    "iso:country": "US",
    "sfomuseum:placetype": "tweet",
    "twitter:tweet": {
      "created": 1344020961,
      "created_at": "Fri Aug 03 19:09:21 +0000 2012",
      "display_text_range": [
        "0",
        "115"
      ],
      "edit_info": {
        "initial": {
          "editTweetIds": [
            "231466806320193538"
          ],
          "editableUntil": "2012-08-03T19:39:21.729Z",
          "editsRemaining": "5",
          "isEditEligible": true
        }
      },
      "entities": {
        "hashtags": [
          {
            "indices": [
              "100",
              "115"
            ],
            "text": "MuseumOlympics"
          }
        ],
        "urls": [
          {
            "display_url": "yfrog.com/mm243zej",
            "expanded_url": "http://yfrog.com/mm243zej",
            "indices": [
              "11",
              "31"
            ],
            "url": "http://t.co/k0RKkHMj"
          }
        ]
      },
      "favorite_count": "0",
      "favorited": false,
      "full_text": "New sport? http://t.co/k0RKkHMj Hmmm, maybe not. We've been running cheese all morning, it seems... #MuseumOlympics",
      "id_str": "231466806320193538",
      "lang": "en",
      "possibly_sensitive": false,
      "retweet_count": "0",
      "retweeted": false,
      "source": "\u003ca href=\"https://about.twitter.com/products/tweetdeck\" rel=\"nofollow\"\u003eTweetDeck\u003c/a\u003e",
      "truncated": false
    },
    "wof:name": "New sport? http://t.co/k0RKkHMj Hmmm, maybe not. We've been running cheese all morning, it seems... #MuseumOlympics",
    "wof:placetype": "custom"
  },
  "geometry": {"coordinates":[-122.386166,37.616356],"type":"Point"}
}
