{
  "type": "Feature",
  "properties": {
    "sfomuseum:placetype": "tweet",
    "twitter:tweet": {
      "created": 1503974706,
      "created_at": "Tue Aug 29 02:45:06 +0000 2017",
      "display_text_range": [
        "0", 
        "86"
      ],
      "entities": {
        "user_mentions": [
          {
            "id_str": "181608016",
            "indices": [
              "0", 
              "12"
            ],
            "name": "airlineguys",
            "screen_name": "airlineguys"
          }, 
          {
            "id_str": "16408759",
            "indices": [
              "79", 
              "86"
            ],
            "name": "San Francisco International Airport (SFO) ✈️",
            "screen_name": "flySFO"
          }
        ]
      },
      "favorite_count": "0",
      "favorited": false,
      "full_text": "@airlineguys Thanks for the heads up! It seems like our whole website is down. @flySFO",
      "id_str": "902361439716818944",
      "in_reply_to_screen_name": "airlineguys",
      "in_reply_to_status_id": "902349830651072512",
      "in_reply_to_status_id_str": "902349830651072512",
      "in_reply_to_user_id": "181608016",
      "in_reply_to_user_id_str": "181608016",
      "lang": "en",
      "retweet_count": "0",
      "retweeted": false,
      "source": "\u003ca href=\"http://twitter.com/download/iphone\" rel=\"nofollow\"\u003eTwitter for iPhone\u003c/a\u003e",
      "truncated": false
    },
    "wof:name": "Twitter message #902361439716818944",
    "wof:placetype": "custom"
  },
  "geometry": {"coordinates":[-122.386166,37.616356],"type":"Point"}
}
