{
  "type": "Feature",
  "properties": {
    "sfomuseum:placetype": "tweet",
    "twitter:tweet": {
      "created": 1420848971,
      "created_at": "Sat Jan 10 00:16:11 +0000 2015",
      "display_text_range": [
        "0", 
        "121"
      ],
      "entities": {
        "hashtags": [
          {
            "indices": [
              "80", 
              "88"
            ],
            "text": "Indulge"
          }, 
          {
            "indices": [
              "89", 
              "97"
            ],
            "text": "Tiffany"
          }
        ],
        "urls": [
          {
            "display_url": "instagram.com/p/xpylN4Rk3G/",
            "expanded_url": "http://instagram.com/p/xpylN4Rk3G/",
            "indices": [
              "99", 
              "121"
            ],
            "url": "http://t.co/r7nLYnOMjx"
          }
        ]
      },
      "favorite_count": "0",
      "favorited": false,
      "full_text": "Every now and then, the background noise in our gallery photos is just perfect. #Indulge #Tiffany… http://t.co/r7nLYnOMjx",
      "id_str": "553706836239855616",
      "lang": "en",
      "possibly_sensitive": false,
      "retweet_count": "0",
      "retweeted": false,
      "source": "\u003ca href=\"http://instagram.com\" rel=\"nofollow\"\u003eInstagram\u003c/a\u003e",
      "truncated": false
    },
    "wof:name": "Twitter message #553706836239855616",
    "wof:placetype": "custom"
  },
  "geometry": {"coordinates":[-122.386166,37.616356],"type":"Point"}
}
