{
  "type": "Feature",
  "properties": {
    "date:cessation_lower": "2023-10-06",
    "date:cessation_upper": "2023-10-06",
    "date:inception_lower": "2023-10-06",
    "date:inception_upper": "2023-10-06",
    "sfomuseum:placetype": "tweet",
    "twitter:tweet": {
      "created": 1696610968,
      "created_at": "Fri Oct 06 16:49:28 +0000 2023",
      "display_text_range": [
        "0",
        "140"
      ],
      "edit_info": {
        "initial": {
          "editTweetIds": [
            "1710336480965804236"
          ],
          "editableUntil": "2023-10-06T17:49:28.234Z",
          "editsRemaining": "5",
          "isEditEligible": false
        }
      },
      "entities": {
        "user_mentions": [
          {
            "id_str": "56377143",
            "indices": [
              "3",
              "7"
            ],
            "name": "KLM",
            "screen_name": "KLM"
          }
        ]
      },
      "favorite_count": "0",
      "favorited": false,
      "full_text": "RT @KLM: Just in! The reveal of our brand-new Delft Blue miniature house… ‘Station Valkenburg’! Did you know KLM launches a new house on it…",
      "id_str": "1710336480965804236",
      "lang": "en",
      "retweet_count": "0",
      "retweeted": false,
      "source": "\u003ca href=\"https://mobile.twitter.com\" rel=\"nofollow\"\u003eTwitter Web App\u003c/a\u003e",
      "truncated": false
    },
    "twitter:user_mentions": [
      "KLM"
    ],
    "wof:name": "RT @KLM: Just in! The reveal of our brand-new Delft Blue miniature house… ‘Station Valkenburg’! Did you know KLM launches a new house on it…",
    "wof:placetype": "custom",
    "wof:placetype_alt": [
      "tweet"
    ]
  },
  "geometry": {"coordinates":[-122.386166,37.616356],"type":"Point"}
}
