{
  "type": "Feature",
  "properties": {
    "sfomuseum:placetype": "tweet",
    "twitter:tweet": {
      "created": 1445994326,
      "created_at": "Wed Oct 28 01:05:26 +0000 2015",
      "display_text_range": [
        "0", 
        "123"
      ],
      "entities": {
        "hashtags": [
          {
            "indices": [
              "85", 
              "99"
            ],
            "text": "TravelTuesday"
          }
        ],
        "media": [
          {
            "display_url": "pic.twitter.com/Szqt02f29L",
            "expanded_url": "https://twitter.com/SFOMuseum/status/659174099160289280/photo/1",
            "id_str": "659174098929590272",
            "indices": [
              "100", 
              "123"
            ],
            "media_url": "http://pbs.twimg.com/media/CSXbWbvWIAAmWOL.jpg",
            "media_url_https": "https://pbs.twimg.com/media/CSXbWbvWIAAmWOL.jpg",
            "sizes": {
              "large": {
                "h": "480",
                "resize": "fit",
                "w": "321"
              },
              "medium": {
                "h": "480",
                "resize": "fit",
                "w": "321"
              },
              "small": {
                "h": "480",
                "resize": "fit",
                "w": "321"
              },
              "thumb": {
                "h": "150",
                "resize": "crop",
                "w": "150"
              }
            },
            "type": "photo",
            "url": "https://t.co/Szqt02f29L"
          }
        ]
      },
      "extended_entities": {
        "media": [
          {
            "display_url": "pic.twitter.com/Szqt02f29L",
            "expanded_url": "https://twitter.com/SFOMuseum/status/659174099160289280/photo/1",
            "id_str": "659174098929590272",
            "indices": [
              "100", 
              "123"
            ],
            "media_url": "http://pbs.twimg.com/media/CSXbWbvWIAAmWOL.jpg",
            "media_url_https": "https://pbs.twimg.com/media/CSXbWbvWIAAmWOL.jpg",
            "sizes": {
              "large": {
                "h": "480",
                "resize": "fit",
                "w": "321"
              },
              "medium": {
                "h": "480",
                "resize": "fit",
                "w": "321"
              },
              "small": {
                "h": "480",
                "resize": "fit",
                "w": "321"
              },
              "thumb": {
                "h": "150",
                "resize": "crop",
                "w": "150"
              }
            },
            "type": "photo",
            "url": "https://t.co/Szqt02f29L"
          }
        ]
      },
      "favorite_count": "1",
      "favorited": false,
      "full_text": "Our Senior Registrar, Kenn, would love to go to Machu Picchu for his dream vacation. #TravelTuesday https://t.co/Szqt02f29L",
      "id_str": "659174099160289280",
      "lang": "en",
      "possibly_sensitive": false,
      "retweet_count": "0",
      "retweeted": false,
      "source": "\u003ca href=\"http://www.hootsuite.com\" rel=\"nofollow\"\u003eHootsuite\u003c/a\u003e",
      "truncated": false
    },
    "wof:name": "Twitter message #659174099160289280",
    "wof:placetype": "custom"
  },
  "geometry": {"coordinates":[-122.386166,37.616356],"type":"Point"}
}
