{
  "type": "Feature",
  "properties": {
    "sfomuseum:placetype": "tweet",
    "twitter:tweet": {
      "created": 1508011238,
      "created_at": "Sat Oct 14 20:00:38 +0000 2017",
      "display_text_range": [
        "0", 
        "161"
      ],
      "entities": {
        "media": [
          {
            "display_url": "pic.twitter.com/W9mgxPAn8n",
            "expanded_url": "https://twitter.com/SFOMuseum/status/919291880545898496/photo/1",
            "id_str": "919291876594929666",
            "indices": [
              "138", 
              "161"
            ],
            "media_url": "http://pbs.twimg.com/media/DMH7F1VX0AIKvoO.jpg",
            "media_url_https": "https://pbs.twimg.com/media/DMH7F1VX0AIKvoO.jpg",
            "sizes": {
              "large": {
                "h": "1333",
                "resize": "fit",
                "w": "2000"
              },
              "medium": {
                "h": "800",
                "resize": "fit",
                "w": "1200"
              },
              "small": {
                "h": "453",
                "resize": "fit",
                "w": "680"
              },
              "thumb": {
                "h": "150",
                "resize": "crop",
                "w": "150"
              }
            },
            "type": "photo",
            "url": "https://t.co/W9mgxPAn8n"
          }
        ],
        "urls": [
          {
            "display_url": "bit.ly/2xSo8hp",
            "expanded_url": "http://bit.ly/2xSo8hp",
            "indices": [
              "114", 
              "137"
            ],
            "url": "https://t.co/9Guq7fEKDP"
          }
        ]
      },
      "extended_entities": {
        "media": [
          {
            "display_url": "pic.twitter.com/W9mgxPAn8n",
            "expanded_url": "https://twitter.com/SFOMuseum/status/919291880545898496/photo/1",
            "id_str": "919291876594929666",
            "indices": [
              "138", 
              "161"
            ],
            "media_url": "http://pbs.twimg.com/media/DMH7F1VX0AIKvoO.jpg",
            "media_url_https": "https://pbs.twimg.com/media/DMH7F1VX0AIKvoO.jpg",
            "sizes": {
              "large": {
                "h": "1333",
                "resize": "fit",
                "w": "2000"
              },
              "medium": {
                "h": "800",
                "resize": "fit",
                "w": "1200"
              },
              "small": {
                "h": "453",
                "resize": "fit",
                "w": "680"
              },
              "thumb": {
                "h": "150",
                "resize": "crop",
                "w": "150"
              }
            },
            "type": "photo",
            "url": "https://t.co/W9mgxPAn8n"
          }
        ]
      },
      "favorite_count": "2",
      "favorited": false,
      "full_text": "See \"The SFO Peephole Cinema\" with videos by Signe Baumane, Kota Ezawa, and Laurie O’Brien, post-security, in T1. https://t.co/9Guq7fEKDP https://t.co/W9mgxPAn8n",
      "id_str": "919291880545898496",
      "lang": "en",
      "possibly_sensitive": false,
      "retweet_count": "0",
      "retweeted": false,
      "source": "\u003ca href=\"http://www.hootsuite.com\" rel=\"nofollow\"\u003eHootsuite\u003c/a\u003e",
      "truncated": false
    },
    "wof:name": "Twitter message #919291880545898496",
    "wof:placetype": "custom"
  },
  "geometry": {"coordinates":[-122.386166,37.616356],"type":"Point"}
}
