{
  "type": "Feature",
  "properties": {
    "sfomuseum:placetype": "tweet",
    "twitter:tweet": {
      "created": 1456891565,
      "created_at": "Wed Mar 02 04:06:05 +0000 2016",
      "display_text_range": [
        "0", 
        "139"
      ],
      "entities": {
        "urls": [
          {
            "display_url": "flysfo.com/museum/exhibit…",
            "expanded_url": "http://www.flysfo.com/museum/exhibitions/allure-art-nouveau-1890",
            "indices": [
              "111", 
              "134"
            ],
            "url": "https://t.co/kOdLUUC8Uo"
          }
        ],
        "user_mentions": [
          {
            "id_str": "213144804",
            "indices": [
              "0", 
              "13"
            ],
            "name": "Anita Weaver",
            "screen_name": "anitaweaver1"
          }
        ]
      },
      "favorite_count": "1",
      "favorited": false,
      "full_text": "@anitaweaver1 You still have plenty of time! \"The Allure of Art Nouveau\" will be on display until August 2016! https://t.co/kOdLUUC8Uo–1914",
      "id_str": "704880429849931777",
      "in_reply_to_screen_name": "anitaweaver1",
      "in_reply_to_status_id": "704878350976708609",
      "in_reply_to_status_id_str": "704878350976708609",
      "in_reply_to_user_id": "213144804",
      "in_reply_to_user_id_str": "213144804",
      "lang": "en",
      "possibly_sensitive": false,
      "retweet_count": "0",
      "retweeted": false,
      "source": "\u003ca href=\"http://twitter.com/download/iphone\" rel=\"nofollow\"\u003eTwitter for iPhone\u003c/a\u003e",
      "truncated": false
    },
    "wof:name": "Twitter message #704880429849931777",
    "wof:placetype": "custom"
  },
  "geometry": {"coordinates":[-122.386166,37.616356],"type":"Point"}
}
