{
  "type": "Feature",
  "properties": {
    "sfomuseum:placetype": "tweet",
    "twitter:tweet": {
      "created": 1369934360,
      "created_at": "Thu May 30 17:19:20 +0000 2013",
      "display_text_range": [
        "0", 
        "143"
      ],
      "entities": {
        "urls": [
          {
            "display_url": "ow.ly/lydcr",
            "expanded_url": "http://ow.ly/lydcr",
            "indices": [
              "121", 
              "143"
            ],
            "url": "http://t.co/pW4Cdn9Xw2"
          }
        ]
      },
      "favorite_count": "0",
      "favorited": false,
      "full_text": "Tonight! Tom Culbert speaks on Pan Am's secret 1941 contract w/British \u0026amp; US govts to move WWII supplies thru Africa. http://t.co/pW4Cdn9Xw2",
      "id_str": "340155479865040896",
      "lang": "en",
      "possibly_sensitive": false,
      "retweet_count": "2",
      "retweeted": false,
      "source": "\u003ca href=\"http://www.hootsuite.com\" rel=\"nofollow\"\u003eHootsuite\u003c/a\u003e",
      "truncated": false
    },
    "wof:name": "Twitter message #340155479865040896",
    "wof:placetype": "custom"
  },
  "geometry": {"coordinates":[-122.386166,37.616356],"type":"Point"}
}
