{
  "type": "Feature",
  "properties": {
    "date:cessation_lower": "2013-05-30",
    "date:cessation_upper": "2013-05-30",
    "date:inception_lower": "2013-05-30",
    "date:inception_upper": "2013-05-30",
    "iso:country": "US",
    "sfomuseum:placetype": "tweet",
    "twitter:tweet": {
      "created": 1369934360,
      "created_at": "Thu May 30 17:19:20 +0000 2013",
      "display_text_range": [
        "0",
        "143"
      ],
      "edit_info": {
        "initial": {
          "editTweetIds": [
            "340155479865040896"
          ],
          "editableUntil": "2013-05-30T18:19:20.840Z",
          "editsRemaining": "5",
          "isEditEligible": true
        }
      },
      "entities": {
        "urls": [
          {
            "display_url": "ow.ly/lydcr",
            "expanded_url": "http://ow.ly/lydcr",
            "indices": [
              "121",
              "143"
            ],
            "url": "http://t.co/pW4Cdn9Xw2"
          }
        ]
      },
      "favorite_count": "0",
      "favorited": false,
      "full_text": "Tonight! Tom Culbert speaks on Pan Am's secret 1941 contract w/British \u0026amp; US govts to move WWII supplies thru Africa. http://t.co/pW4Cdn9Xw2",
      "id_str": "340155479865040896",
      "lang": "en",
      "possibly_sensitive": false,
      "retweet_count": "1",
      "retweeted": false,
      "source": "\u003ca href=\"http://www.hootsuite.com\" rel=\"nofollow\"\u003eHootsuite\u003c/a\u003e",
      "truncated": false
    },
    "wof:name": "Tonight! Tom Culbert speaks on Pan Am's secret 1941 contract w/British \u0026amp; US govts to move WWII supplies thru Africa. http://t.co/pW4Cdn9Xw2",
    "wof:placetype": "custom",
    "wof:placetype_alt": [
      "tweet"
    ]
  },
  "geometry": {"coordinates":[-122.386166,37.616356],"type":"Point"}
}
