{
  "type": "Feature",
  "properties": {
    "date:cessation_lower":"2013-01-10",
    "date:cessation_upper":"2013-01-10",
    "date:inception_lower":"2013-01-10",
    "date:inception_upper":"2013-01-10",
    "iso:country":"US",
    "sfomuseum:placetype":"tweet",
    "twitter:tweet":{
        "created":1357840338,
        "created_at":"Thu Jan 10 17:52:18 +0000 2013",
        "display_text_range":[
            "0",
            "129"
        ],
        "entities":{
            "user_mentions":[
                {
                    "id_str":"156059588",
                    "indices":[
                        "0",
                        "16"
                    ],
                    "name":"\ud83c\udf0aShereen Rayle\ud83c\udf0a",
                    "screen_name":"shereentrvlschp"
                }
            ]
        },
        "favorite_count":"0",
        "favorited":false,
        "full_text":"@shereentrvlschp We're glad to hear you like the painting! Alas, we don't have the ability to sell anything...no museum store : )",
        "id_str":"289429473806409728",
        "in_reply_to_screen_name":"shereentrvlschp",
        "in_reply_to_status_id":"289417850991562754",
        "in_reply_to_status_id_str":"289417850991562754",
        "in_reply_to_user_id":"156059588",
        "in_reply_to_user_id_str":"156059588",
        "lang":"en",
        "retweet_count":"0",
        "retweeted":false,
        "source":"<a href=\"http://twitter.com/download/iphone\" rel=\"nofollow\">Twitter for iPhone</a>",
        "truncated":false
    },
    "wof:name":"@shereentrvlschp We're glad to hear you like the painting! Alas, we don't have the ability to sell anything...no museum store : )",
    "wof:placetype":"custom"
},
  "geometry": {"coordinates":[-122.386166,37.616356],"type":"Point"}
}