{
  "type": "Feature",
  "properties": {
    "date:cessation_lower": "2012-02-03",
    "date:cessation_upper": "2012-02-03",
    "date:inception_lower": "2012-02-03",
    "date:inception_upper": "2012-02-03",
    "iso:country": "US",
    "sfomuseum:placetype": "tweet",
    "twitter:tweet": {
      "created": 1328228715,
      "created_at": "Fri Feb 03 00:25:15 +0000 2012",
      "display_text_range": [
        "0",
        "115"
      ],
      "edit_info": {
        "initial": {
          "editTweetIds": [
            "165229323387805700"
          ],
          "editableUntil": "2012-02-03T00:55:15.165Z",
          "editsRemaining": "5",
          "isEditEligible": true
        }
      },
      "entities": {
        "urls": [
          {
            "display_url": "4sq.com/yKqJt5",
            "expanded_url": "http://4sq.com/yKqJt5",
            "indices": [
              "95",
              "115"
            ],
            "url": "http://t.co/bTZ5NVSC"
          }
        ],
        "user_mentions": [
          {
            "id_str": "14548676",
            "indices": [
              "27",
              "37"
            ],
            "name": "Sen. Brant Feldman",
            "screen_name": "AGMSports"
          }
        ]
      },
      "favorite_count": "0",
      "favorited": false,
      "full_text": "*blush* Why, thank you! RT @AGMSports: Very pretty in here (@ SFO Aviation Library and Museum) http://t.co/bTZ5NVSC",
      "id_str": "165229323387805700",
      "lang": "en",
      "possibly_sensitive": false,
      "retweet_count": "0",
      "retweeted": false,
      "source": "\u003ca href=\"https://about.twitter.com/products/tweetdeck\" rel=\"nofollow\"\u003eTweetDeck\u003c/a\u003e",
      "truncated": false
    },
    "wof:name": "*blush* Why, thank you! RT @AGMSports: Very pretty in here (@ SFO Aviation Library and Museum) http://t.co/bTZ5NVSC",
    "wof:placetype": "custom"
  },
  "geometry": {"coordinates":[-122.386166,37.616356],"type":"Point"}
}
