{
  "type": "Feature",
  "properties": {
    "sfomuseum:placetype": "tweet",
    "twitter:tweet": {
      "created": 1482175189,
      "created_at": "Mon Dec 19 19:19:49 +0000 2016",
      "display_text_range": [
        "0", 
        "140"
      ],
      "entities": {
        "hashtags": [
          {
            "indices": [
              "70", 
              "90"
            ],
            "text": "johnpatrickmckenzie"
          }, 
          {
            "indices": [
              "111", 
              "126"
            ],
            "text": "HolidayArtShop"
          }
        ],
        "user_mentions": [
          {
            "id_str": "59629328",
            "indices": [
              "3", 
              "19"
            ],
            "name": "Creativity Explored",
            "screen_name": "creativityxplrd"
          }
        ]
      },
      "favorite_count": "0",
      "favorited": false,
      "full_text": "RT @creativityxplrd: December picnic time! Pick up this one-of-a-kind #johnpatrickmckenzie tablecloth from our #HolidayArtShop. https://t.c…",
      "id_str": "810927635400445952",
      "lang": "en",
      "retweet_count": "0",
      "retweeted": false,
      "source": "\u003ca href=\"http://twitter.com\" rel=\"nofollow\"\u003eTwitter Web Client\u003c/a\u003e",
      "truncated": false
    },
    "wof:name": "Twitter message #810927635400445952",
    "wof:placetype": "custom"
  },
  "geometry": {"coordinates":[-122.386166,37.616356],"type":"Point"}
}
