{
  "type": "Feature",
  "properties": {
    "sfomuseum:placetype": "tweet",
    "twitter:tweet": {
      "created": 1321463401,
      "created_at": "Wed Nov 16 17:10:01 +0000 2011",
      "display_text_range": [
        "0", 
        "67"
      ],
      "entities": {
        "user_mentions": [
          {
            "id_str": "6321372",
            "indices": [
              "0", 
              "9"
            ],
            "name": "Steve Patrizi",
            "screen_name": "spatrizi"
          }
        ]
      },
      "favorite_count": "0",
      "favorited": false,
      "full_text": "@spatrizi We're glad to hear that the exhibit resonated with you :)",
      "id_str": "136853539346587648",
      "in_reply_to_screen_name": "spatrizi",
      "in_reply_to_user_id": "6321372",
      "in_reply_to_user_id_str": "6321372",
      "lang": "en",
      "retweet_count": "0",
      "retweeted": false,
      "source": "\u003ca href=\"https://about.twitter.com/products/tweetdeck\" rel=\"nofollow\"\u003eTweetDeck\u003c/a\u003e",
      "truncated": false
    },
    "wof:name": "Twitter message #136853539346587648",
    "wof:placetype": "custom"
  },
  "geometry": {"coordinates":[-122.386166,37.616356],"type":"Point"}
}
