{
  "type": "Feature",
  "properties": {
    "sfomuseum:placetype": "tweet",
    "twitter:tweet": {
      "created": 1329248424,
      "created_at": "Tue Feb 14 19:40:24 +0000 2012",
      "display_text_range": [
        "0", 
        "118"
      ],
      "entities": {
        "hashtags": [
          {
            "indices": [
              "8", 
              "20"
            ],
            "text": "MuseumCrush"
          }, 
          {
            "indices": [
              "110", 
              "118"
            ],
            "text": "140love"
          }
        ]
      },
      "favorite_count": "0",
      "favorited": false,
      "full_text": "Darling #MuseumCrush, the Taj Mahal is dull \u0026 dreary in comparison to the monuments we would build for you... #140love",
      "id_str": "169506293072150528",
      "lang": "en",
      "retweet_count": "0",
      "retweeted": false,
      "source": "\u003ca href=\"https://about.twitter.com/products/tweetdeck\" rel=\"nofollow\"\u003eTweetDeck\u003c/a\u003e",
      "truncated": false
    },
    "wof:name": "Twitter message #169506293072150528",
    "wof:placetype": "custom"
  },
  "geometry": {"coordinates":[-122.386166,37.616356],"type":"Point"}
}
