{
  "type": "Feature",
  "properties": {
    "sfomuseum:placetype": "tweet",
    "twitter:tweet": {
      "created": 1466035598,
      "created_at": "Thu Jun 16 00:06:38 +0000 2016",
      "display_text_range": [
        "0", 
        "102"
      ],
      "entities": {
        "hashtags": [
          {
            "indices": [
              "53", 
              "61"
            ],
            "text": "Balmain"
          }, 
          {
            "indices": [
              "62", 
              "78"
            ],
            "text": "FashionInFlight"
          }
        ],
        "media": [
          {
            "display_url": "pic.twitter.com/UokyDTSeFK",
            "expanded_url": "https://twitter.com/SFOMuseum/status/743233284075839488/photo/1",
            "id_str": "743233272205840385",
            "indices": [
              "79", 
              "102"
            ],
            "media_url": "http://pbs.twimg.com/media/ClB-uScUkAEm41q.jpg",
            "media_url_https": "https://pbs.twimg.com/media/ClB-uScUkAEm41q.jpg",
            "sizes": {
              "large": {
                "h": "2048",
                "resize": "fit",
                "w": "1608"
              },
              "medium": {
                "h": "1200",
                "resize": "fit",
                "w": "942"
              },
              "small": {
                "h": "680",
                "resize": "fit",
                "w": "534"
              },
              "thumb": {
                "h": "150",
                "resize": "crop",
                "w": "150"
              }
            },
            "type": "photo",
            "url": "https://t.co/UokyDTSeFK"
          }
        ]
      },
      "extended_entities": {
        "media": [
          {
            "display_url": "pic.twitter.com/UokyDTSeFK",
            "expanded_url": "https://twitter.com/SFOMuseum/status/743233284075839488/photo/1",
            "id_str": "743233272205840385",
            "indices": [
              "79", 
              "102"
            ],
            "media_url": "http://pbs.twimg.com/media/ClB-uScUkAEm41q.jpg",
            "media_url_https": "https://pbs.twimg.com/media/ClB-uScUkAEm41q.jpg",
            "sizes": {
              "large": {
                "h": "2048",
                "resize": "fit",
                "w": "1608"
              },
              "medium": {
                "h": "1200",
                "resize": "fit",
                "w": "942"
              },
              "small": {
                "h": "680",
                "resize": "fit",
                "w": "534"
              },
              "thumb": {
                "h": "150",
                "resize": "crop",
                "w": "150"
              }
            },
            "type": "photo",
            "url": "https://t.co/UokyDTSeFK"
          }
        ]
      },
      "favorite_count": "15",
      "favorited": false,
      "full_text": "“Good fashion is evolution, not revolution.” –Pierre #Balmain #FashionInFlight https://t.co/UokyDTSeFK",
      "id_str": "743233284075839488",
      "lang": "en",
      "possibly_sensitive": false,
      "retweet_count": "12",
      "retweeted": false,
      "source": "\u003ca href=\"http://www.hootsuite.com\" rel=\"nofollow\"\u003eHootsuite\u003c/a\u003e",
      "truncated": false
    },
    "wof:name": "Twitter message #743233284075839488",
    "wof:placetype": "custom"
  },
  "geometry": {"coordinates":[-122.386166,37.616356],"type":"Point"}
}
