{
  "type": "Feature",
  "properties": {
    "sfomuseum:placetype": "tweet",
    "twitter:tweet": {
      "created": 1532744703,
      "created_at": "Sat Jul 28 02:25:03 +0000 2018",
      "display_text_range": [
        "0", 
        "197"
      ],
      "entities": {
        "hashtags": [
          {
            "indices": [
              "154", 
              "173"
            ],
            "text": "AviationEvolutions"
          }
        ],
        "media": [
          {
            "display_url": "pic.twitter.com/sL9faJK4vo",
            "expanded_url": "https://twitter.com/SFOMuseum/status/1023031553310552064/photo/1",
            "id_str": "1023031550668165121",
            "indices": [
              "174", 
              "197"
            ],
            "media_url": "http://pbs.twimg.com/media/DjKJxmuX0AEz9p6.jpg",
            "media_url_https": "https://pbs.twimg.com/media/DjKJxmuX0AEz9p6.jpg",
            "sizes": {
              "large": {
                "h": "1096",
                "resize": "fit",
                "w": "2000"
              },
              "medium": {
                "h": "658",
                "resize": "fit",
                "w": "1200"
              },
              "small": {
                "h": "373",
                "resize": "fit",
                "w": "680"
              },
              "thumb": {
                "h": "150",
                "resize": "crop",
                "w": "150"
              }
            },
            "type": "photo",
            "url": "https://t.co/sL9faJK4vo"
          }
        ]
      },
      "extended_entities": {
        "media": [
          {
            "display_url": "pic.twitter.com/sL9faJK4vo",
            "expanded_url": "https://twitter.com/SFOMuseum/status/1023031553310552064/photo/1",
            "id_str": "1023031550668165121",
            "indices": [
              "174", 
              "197"
            ],
            "media_url": "http://pbs.twimg.com/media/DjKJxmuX0AEz9p6.jpg",
            "media_url_https": "https://pbs.twimg.com/media/DjKJxmuX0AEz9p6.jpg",
            "sizes": {
              "large": {
                "h": "1096",
                "resize": "fit",
                "w": "2000"
              },
              "medium": {
                "h": "658",
                "resize": "fit",
                "w": "1200"
              },
              "small": {
                "h": "373",
                "resize": "fit",
                "w": "680"
              },
              "thumb": {
                "h": "150",
                "resize": "crop",
                "w": "150"
              }
            },
            "type": "photo",
            "url": "https://t.co/sL9faJK4vo"
          }
        ]
      },
      "favorite_count": "7",
      "favorited": false,
      "full_text": "Introduced in 1983, by Lufthansa and Swissair, the Airbus 310 proved reliable in service while providing a comfortable and spacious cabin for passengers. #AviationEvolutions https://t.co/sL9faJK4vo",
      "id_str": "1023031553310552064",
      "lang": "en",
      "possibly_sensitive": false,
      "retweet_count": "1",
      "retweeted": false,
      "source": "\u003ca href=\"https://www.hootsuite.com\" rel=\"nofollow\"\u003eHootsuite Inc.\u003c/a\u003e",
      "truncated": false
    },
    "wof:name": "Twitter message #1023031553310552064",
    "wof:placetype": "custom"
  },
  "geometry": {"coordinates":[-122.386166,37.616356],"type":"Point"}
}
