{
  "type": "Feature",
  "properties": {
    "sfomuseum:placetype": "tweet",
    "twitter:tweet": {
      "created": 1327598128,
      "created_at": "Thu Jan 26 17:15:28 +0000 2012",
      "display_text_range": [
        "0", 
        "86"
      ],
      "entities": {
        "user_mentions": [
          {
            "id_str": "19292047",
            "indices": [
              "0", 
              "12"
            ],
            "name": "Brian Audley",
            "screen_name": "BrianAudley"
          }
        ]
      },
      "favorite_count": "0",
      "favorited": false,
      "full_text": "@BrianAudley Thanks for checking out \"Revolutions per Minute\"! We hope you enjoyed it!",
      "id_str": "162584450495025152",
      "in_reply_to_screen_name": "BrianAudley",
      "in_reply_to_status_id": "162542082572038144",
      "in_reply_to_status_id_str": "162542082572038144",
      "in_reply_to_user_id": "19292047",
      "in_reply_to_user_id_str": "19292047",
      "lang": "en",
      "retweet_count": "0",
      "retweeted": false,
      "source": "\u003ca href=\"https://about.twitter.com/products/tweetdeck\" rel=\"nofollow\"\u003eTweetDeck\u003c/a\u003e",
      "truncated": false
    },
    "wof:name": "Twitter message #162584450495025152",
    "wof:placetype": "custom"
  },
  "geometry": {"coordinates":[-122.386166,37.616356],"type":"Point"}
}
