{
  "type": "Feature",
  "properties": {
    "sfomuseum:placetype": "tweet",
    "twitter:tweet": {
      "created": 1327010445,
      "created_at": "Thu Jan 19 22:00:45 +0000 2012",
      "display_text_range": [
        "0", 
        "119"
      ],
      "entities": {
        "urls": [
          {
            "display_url": "ow.ly/8zrvT",
            "expanded_url": "http://ow.ly/8zrvT",
            "indices": [
              "99", 
              "119"
            ],
            "url": "http://t.co/XPH8n0Cr"
          }
        ]
      },
      "favorite_count": "0",
      "favorited": false,
      "full_text": "\"Man...is only fully a human being when he plays.\" Playfulness on display in our automata exhibit! http://t.co/XPH8n0Cr",
      "id_str": "160119531401003008",
      "lang": "en",
      "possibly_sensitive": false,
      "retweet_count": "0",
      "retweeted": false,
      "source": "\u003ca href=\"http://www.hootsuite.com\" rel=\"nofollow\"\u003eHootsuite\u003c/a\u003e",
      "truncated": false
    },
    "wof:name": "Twitter message #160119531401003008",
    "wof:placetype": "custom"
  },
  "geometry": {"coordinates":[-122.386166,37.616356],"type":"Point"}
}
