{
  "type": "Feature",
  "properties": {
    "date:cessation_lower":"2014-11-03",
    "date:cessation_upper":"2014-11-03",
    "date:inception_lower":"2014-11-03",
    "date:inception_upper":"2014-11-03",
    "iso:country":"US",
    "sfomuseum:placetype":"tweet",
    "twitter:tweet":{
        "created":1415064670,
        "created_at":"Tue Nov 04 01:31:10 +0000 2014",
        "display_text_range":[
            "0",
            "96"
        ],
        "entities":{
            "hashtags":[
                {
                    "indices":[
                        "90",
                        "96"
                    ],
                    "text":"PanAm"
                }
            ],
            "urls":[
                {
                    "display_url":"ow.ly/DLT3q",
                    "expanded_url":"http://ow.ly/DLT3q",
                    "indices":[
                        "67",
                        "89"
                    ],
                    "url":"http://t.co/sCVhV416Pu"
                }
            ]
        },
        "favorite_count":"0",
        "favorited":false,
        "full_text":"$955 would get you from Honolulu to Manila both today and in 1940: http://t.co/sCVhV416Pu #PanAm",
        "id_str":"529445718013276160",
        "lang":"en",
        "possibly_sensitive":false,
        "retweet_count":"0",
        "retweeted":false,
        "source":"<a href=\"http://www.hootsuite.com\" rel=\"nofollow\">Hootsuite</a>",
        "truncated":false
    },
    "wof:name":"$955 would get you from Honolulu to Manila both today and in 1940: http://t.co/sCVhV416Pu #PanAm",
    "wof:placetype":"custom"
},
  "geometry": {"coordinates":[-122.386166,37.616356],"type":"Point"}
}