{
  "type": "Feature",
  "properties": {
    "date:cessation_lower":"2016-08-17",
    "date:cessation_upper":"2016-08-17",
    "date:inception_lower":"2016-08-17",
    "date:inception_upper":"2016-08-17",
    "iso:country":"US",
    "sfomuseum:placetype":"tweet",
    "twitter:tweet":{
        "created":1471468248,
        "created_at":"Wed Aug 17 21:10:48 +0000 2016",
        "display_text_range":[
            "0",
            "140"
        ],
        "entities":{
            "hashtags":[
                {
                    "indices":[
                        "26",
                        "50"
                    ],
                    "text":"BlackCatAppreciationDay"
                },
                {
                    "indices":[
                        "67",
                        "76"
                    ],
                    "text":"purrfect"
                },
                {
                    "indices":[
                        "116",
                        "135"
                    ],
                    "text":"CreativityExplored"
                }
            ],
            "user_mentions":[
                {
                    "id_str":"59629328",
                    "indices":[
                        "3",
                        "19"
                    ],
                    "name":"Creativity Explored",
                    "screen_name":"creativityxplrd"
                }
            ]
        },
        "favorite_count":"0",
        "favorited":false,
        "full_text":"RT @creativityxplrd: It's #BlackCatAppreciationDay and here is the #purrfect black cat by late artist Badia Forbes. #CreativityExplored htt\u2026",
        "id_str":"766019471861395457",
        "lang":"en",
        "retweet_count":"0",
        "retweeted":false,
        "source":"<a href=\"http://twitter.com\" rel=\"nofollow\">Twitter Web Client</a>",
        "truncated":false
    },
    "wof:name":"RT @creativityxplrd: It's #BlackCatAppreciationDay and here is the #purrfect black cat by late artist Badia Forbes. #CreativityExplored htt\u2026",
    "wof:placetype":"custom"
},
  "geometry": {"coordinates":[-122.386166,37.616356],"type":"Point"}
}