{
  "type": "Feature",
  "properties": {
    "date:cessation_lower": "2016-03-30",
    "date:cessation_upper": "2016-03-30",
    "date:inception_lower": "2016-03-30",
    "date:inception_upper": "2016-03-30",
    "iso:country": "US",
    "sfomuseum:placetype": "tweet",
    "twitter:hashtags": [
      "ToyStory20"
    ],
    "twitter:tweet": {
      "created": 1459308611,
      "created_at": "Wed Mar 30 03:30:11 +0000 2016",
      "display_text_range": [
        "0",
        "130"
      ],
      "edit_info": {
        "initial": {
          "editTweetIds": [
            "715018257330282496"
          ],
          "editableUntil": "2016-03-30T04:30:11.601Z",
          "editsRemaining": "5",
          "isEditEligible": true
        }
      },
      "entities": {
        "hashtags": [
          {
            "indices": [
              "119",
              "130"
            ],
            "text": "ToyStory20"
          }
        ],
        "urls": [
          {
            "display_url": "flysfo.com/museum/exhibit…",
            "expanded_url": "http://www.flysfo.com/museum/exhibitions/toy-story-twenty",
            "indices": [
              "95",
              "118"
            ],
            "url": "https://t.co/353FbYlrcp"
          }
        ]
      },
      "favorite_count": "0",
      "favorited": false,
      "full_text": "“Toy Story at Twenty” is on display, everyday, 24 hours of day, in the International Terminal. https://t.co/353FbYlrcp #ToyStory20",
      "id_str": "715018257330282496",
      "lang": "en",
      "possibly_sensitive": false,
      "retweet_count": "0",
      "retweeted": false,
      "source": "\u003ca href=\"http://www.hootsuite.com\" rel=\"nofollow\"\u003eHootsuite\u003c/a\u003e",
      "truncated": false
    },
    "wof:name": "“Toy Story at Twenty” is on display, everyday, 24 hours of day, in the International Terminal. https://t.co/353FbYlrcp #ToyStory20",
    "wof:placetype": "custom",
    "wof:placetype_alt": [
      "tweet"
    ]
  },
  "geometry": {"coordinates":[-122.386166,37.616356],"type":"Point"}
}
