{
  "type": "Feature",
  "properties": {
    "sfomuseum:placetype": "tweet",
    "twitter:tweet": {
      "created": 1459308611,
      "created_at": "Wed Mar 30 03:30:11 +0000 2016",
      "display_text_range": [
        "0", 
        "130"
      ],
      "entities": {
        "hashtags": [
          {
            "indices": [
              "119", 
              "130"
            ],
            "text": "ToyStory20"
          }
        ],
        "urls": [
          {
            "display_url": "flysfo.com/museum/exhibit…",
            "expanded_url": "http://www.flysfo.com/museum/exhibitions/toy-story-twenty",
            "indices": [
              "95", 
              "118"
            ],
            "url": "https://t.co/353FbYlrcp"
          }
        ]
      },
      "favorite_count": "0",
      "favorited": false,
      "full_text": "“Toy Story at Twenty” is on display, everyday, 24 hours of day, in the International Terminal. https://t.co/353FbYlrcp #ToyStory20",
      "id_str": "715018257330282496",
      "lang": "en",
      "possibly_sensitive": false,
      "retweet_count": "0",
      "retweeted": false,
      "source": "\u003ca href=\"http://www.hootsuite.com\" rel=\"nofollow\"\u003eHootsuite\u003c/a\u003e",
      "truncated": false
    },
    "wof:name": "Twitter message #715018257330282496",
    "wof:placetype": "custom"
  },
  "geometry": {"coordinates":[-122.386166,37.616356],"type":"Point"}
}
