{
  "type": "Feature",
  "properties": {
    "sfomuseum:placetype": "tweet",
    "twitter:tweet": {
      "created": 1486694406,
      "created_at": "Fri Feb 10 02:40:06 +0000 2017",
      "display_text_range": [
        "0", 
        "168"
      ],
      "entities": {
        "hashtags": [
          {
            "indices": [
              "121", 
              "125"
            ],
            "text": "TBT"
          }, 
          {
            "indices": [
              "126", 
              "144"
            ],
            "text": "ThrowbackThursday"
          }
        ],
        "media": [
          {
            "display_url": "pic.twitter.com/alBMOJ0xmC",
            "expanded_url": "https://twitter.com/SFOMuseum/status/829882607148101632/photo/1",
            "id_str": "829882604140765184",
            "indices": [
              "145", 
              "168"
            ],
            "media_url": "http://pbs.twimg.com/media/C4RV1OEWIAA6L6P.jpg",
            "media_url_https": "https://pbs.twimg.com/media/C4RV1OEWIAA6L6P.jpg",
            "sizes": {
              "large": {
                "h": "2048",
                "resize": "fit",
                "w": "2048"
              },
              "medium": {
                "h": "1200",
                "resize": "fit",
                "w": "1200"
              },
              "small": {
                "h": "680",
                "resize": "fit",
                "w": "680"
              },
              "thumb": {
                "h": "150",
                "resize": "crop",
                "w": "150"
              }
            },
            "type": "photo",
            "url": "https://t.co/alBMOJ0xmC"
          }
        ]
      },
      "extended_entities": {
        "media": [
          {
            "display_url": "pic.twitter.com/alBMOJ0xmC",
            "expanded_url": "https://twitter.com/SFOMuseum/status/829882607148101632/photo/1",
            "id_str": "829882604140765184",
            "indices": [
              "145", 
              "168"
            ],
            "media_url": "http://pbs.twimg.com/media/C4RV1OEWIAA6L6P.jpg",
            "media_url_https": "https://pbs.twimg.com/media/C4RV1OEWIAA6L6P.jpg",
            "sizes": {
              "large": {
                "h": "2048",
                "resize": "fit",
                "w": "2048"
              },
              "medium": {
                "h": "1200",
                "resize": "fit",
                "w": "1200"
              },
              "small": {
                "h": "680",
                "resize": "fit",
                "w": "680"
              },
              "thumb": {
                "h": "150",
                "resize": "crop",
                "w": "150"
              }
            },
            "type": "photo",
            "url": "https://t.co/alBMOJ0xmC"
          }
        ]
      },
      "favorite_count": "0",
      "favorited": false,
      "full_text": "On the eve of our 90th anniversary, SFO is served by 58 scheduled airlines \u0026amp; serves over 50 mil passengers annually! #TBT #ThrowbackThursday https://t.co/alBMOJ0xmC",
      "id_str": "829882607148101632",
      "lang": "en",
      "possibly_sensitive": false,
      "retweet_count": "1",
      "retweeted": false,
      "source": "\u003ca href=\"http://www.hootsuite.com\" rel=\"nofollow\"\u003eHootsuite\u003c/a\u003e",
      "truncated": false
    },
    "wof:name": "Twitter message #829882607148101632",
    "wof:placetype": "custom"
  },
  "geometry": {"coordinates":[-122.386166,37.616356],"type":"Point"}
}
