{
  "type": "Feature",
  "properties": {
    "date:cessation_lower": "2012-06-13",
    "date:cessation_upper": "2012-06-13",
    "date:inception_lower": "2012-06-13",
    "date:inception_upper": "2012-06-13",
    "iso:country": "US",
    "sfomuseum:placetype": "tweet",
    "twitter:tweet": {
      "created": 1339619096,
      "created_at": "Wed Jun 13 20:24:56 +0000 2012",
      "display_text_range": [
        "0",
        "63"
      ],
      "edit_info": {
        "initial": {
          "editTweetIds": [
            "213004043851800576"
          ],
          "editableUntil": "2012-06-13T20:54:56.135Z",
          "editsRemaining": "5",
          "isEditEligible": true
        }
      },
      "entities": {
        "hashtags": [
          {
            "indices": [
              "29",
              "40"
            ],
            "text": "MuseumLove"
          }
        ],
        "user_mentions": [
          {
            "id_str": "18090088",
            "indices": [
              "13",
              "27"
            ],
            "name": "de Young Museum",
            "screen_name": "deyoungmuseum"
          }
        ]
      },
      "favorite_count": "0",
      "favorited": false,
      "full_text": "Awww, thanks @deyoungmuseum! #MuseumLove right back at you!  :)",
      "id_str": "213004043851800576",
      "in_reply_to_screen_name": "deyoungmuseum",
      "in_reply_to_status_id": "213001449859317761",
      "in_reply_to_status_id_str": "213001449859317761",
      "in_reply_to_user_id": "18090088",
      "in_reply_to_user_id_str": "18090088",
      "lang": "en",
      "retweet_count": "0",
      "retweeted": false,
      "source": "\u003ca href=\"http://www.hootsuite.com\" rel=\"nofollow\"\u003eHootsuite\u003c/a\u003e",
      "truncated": false
    },
    "wof:name": "Awww, thanks @deyoungmuseum! #MuseumLove right back at you!  :)",
    "wof:placetype": "custom"
  },
  "geometry": {"coordinates":[-122.386166,37.616356],"type":"Point"}
}
