{
  "type": "Feature",
  "properties": {
    "sfomuseum:placetype": "tweet",
    "twitter:tweet": {
      "created": 1553705797,
      "created_at": "Wed Mar 27 16:56:37 +0000 2019",
      "display_text_range": [
        "0", 
        "191"
      ],
      "entities": {
        "user_mentions": [
          {
            "id_str": "51203",
            "indices": [
              "0", 
              "12"
            ],
            "name": "anna",
            "screen_name": "annapickard"
          }
        ]
      },
      "favorite_count": "4",
      "favorited": false,
      "full_text": "@annapickard Hi! Thanks so much for stopping by! If you would like more catalogs or brochures, please email us at curator@flysfo.com and we can send you (or your friends) some free of charge!",
      "id_str": "1110948752699748352",
      "in_reply_to_screen_name": "annapickard",
      "in_reply_to_status_id": "1110931272811974657",
      "in_reply_to_status_id_str": "1110931272811974657",
      "in_reply_to_user_id": "51203",
      "in_reply_to_user_id_str": "51203",
      "lang": "en",
      "retweet_count": "0",
      "retweeted": false,
      "source": "\u003ca href=\"http://twitter.com\" rel=\"nofollow\"\u003eTwitter Web Client\u003c/a\u003e",
      "truncated": false
    },
    "wof:name": "Twitter message #1110948752699748352",
    "wof:placetype": "custom"
  },
  "geometry": {"coordinates":[-122.386166,37.616356],"type":"Point"}
}
