{
  "type": "Feature",
  "properties": {
    "date:cessation_lower": "2023-03-17",
    "date:cessation_upper": "2023-03-17",
    "date:inception_lower": "2023-03-17",
    "date:inception_upper": "2023-03-17",
    "sfomuseum:placetype": "tweet",
    "twitter:tweet": {
      "created": 1679076066,
      "created_at": "Fri Mar 17 18:01:06 +0000 2023",
      "display_text_range": [
        "0",
        "115"
      ],
      "edit_info": {
        "initial": {
          "editTweetIds": [
            "1636789773343027201"
          ],
          "editableUntil": "2023-03-17T18:31:06.000Z",
          "editsRemaining": "5",
          "isEditEligible": false
        }
      },
      "entities": {
        "urls": [
          {
            "display_url": "bit.ly/3mxujlA",
            "expanded_url": "http://bit.ly/3mxujlA",
            "indices": [
              "92",
              "115"
            ],
            "url": "https://t.co/llcpviaIRa"
          }
        ]
      },
      "favorite_count": "2",
      "favorited": false,
      "full_text": "📸:\npostcard: Aer Lingus, Douglas DC-3; 1940s-1950s\nGift of Thomas G. Dragges\n2015.166.0077\n\nhttps://t.co/llcpviaIRa",
      "id_str": "1636789773343027201",
      "in_reply_to_screen_name": "SFOMuseum",
      "in_reply_to_status_id": "1636789771120041985",
      "in_reply_to_status_id_str": "1636789771120041985",
      "in_reply_to_user_id": "116329337",
      "in_reply_to_user_id_str": "116329337",
      "lang": "en",
      "possibly_sensitive": false,
      "retweet_count": "1",
      "retweeted": false,
      "source": "\u003ca href=\"https://mobile.twitter.com\" rel=\"nofollow\"\u003eTwitter Web App\u003c/a\u003e",
      "truncated": false
    },
    "wof:name": "📸:\npostcard: Aer Lingus, Douglas DC-3; 1940s-1950s\nGift of Thomas G. Dragges\n2015.166.0077\n\nhttps://t.co/llcpviaIRa",
    "wof:placetype": "custom"
  },
  "geometry": {"coordinates":[-122.386166,37.616356],"type":"Point"}
}
