{
  "type": "Feature",
  "properties": {
    "date:cessation_lower": "2016-08-22",
    "date:cessation_upper": "2016-08-22",
    "date:inception_lower": "2016-08-22",
    "date:inception_upper": "2016-08-22",
    "iso:country": "US",
    "sfomuseum:placetype": "tweet",
    "twitter:tweet": {
      "created": 1471901032,
      "created_at": "Mon Aug 22 21:23:52 +0000 2016",
      "display_text_range": [
        "0",
        "127"
      ],
      "entities": {
        "hashtags": [
          {
            "indices": [
              "86",
              "102"
            ],
            "text": "FashionInFlight"
          }
        ],
        "urls": [
          {
            "display_url": "twitter.com/airandspace/st…",
            "expanded_url": "https://twitter.com/airandspace/status/767776166279274500",
            "indices": [
              "104",
              "127"
            ],
            "url": "https://t.co/eQhPa8YQrE"
          }
        ]
      },
      "favorite_count": "1",
      "favorited": false,
      "full_text": "A replica of the 1930 Boeing Air Transport uniform Ellen Church wore is on display in #FashionInFlight. https://t.co/eQhPa8YQrE",
      "id_str": "767834696948473857",
      "lang": "en",
      "possibly_sensitive": false,
      "retweet_count": "1",
      "retweeted": false,
      "source": "\u003ca href=\"http://twitter.com\" rel=\"nofollow\"\u003eTwitter Web Client\u003c/a\u003e",
      "truncated": false
    },
    "wof:name": "A replica of the 1930 Boeing Air Transport uniform Ellen Church wore is on display in #FashionInFlight. https://t.co/eQhPa8YQrE",
    "wof:placetype": "custom"
  },
  "geometry": {"coordinates":[-122.386166,37.616356],"type":"Point"}
}
