{
  "type": "Feature",
  "properties": {
    "date:cessation_lower":"2014-01-13",
    "date:cessation_upper":"2014-01-13",
    "date:inception_lower":"2014-01-13",
    "date:inception_upper":"2014-01-13",
    "iso:country":"US",
    "sfomuseum:placetype":"tweet",
    "twitter:tweet":{
        "created":1389640699,
        "created_at":"Mon Jan 13 19:18:19 +0000 2014",
        "display_text_range":[
            "0",
            "64"
        ],
        "entities":{
            "user_mentions":[
                {
                    "id_str":"570553905",
                    "indices":[
                        "0",
                        "11"
                    ],
                    "name":"Georgia Freedman",
                    "screen_name":"g_freedman"
                }
            ]
        },
        "favorite_count":"0",
        "favorited":false,
        "full_text":"@g_freedman Thank you!  We hope you can view our exhibits again!",
        "id_str":"422809856899547136",
        "in_reply_to_screen_name":"g_freedman",
        "in_reply_to_status_id":"422128329379303424",
        "in_reply_to_status_id_str":"422128329379303424",
        "in_reply_to_user_id":"570553905",
        "in_reply_to_user_id_str":"570553905",
        "lang":"en",
        "retweet_count":"0",
        "retweeted":false,
        "source":"<a href=\"http://www.hootsuite.com\" rel=\"nofollow\">Hootsuite</a>",
        "truncated":false
    },
    "wof:name":"@g_freedman Thank you!  We hope you can view our exhibits again!",
    "wof:placetype":"custom"
},
  "geometry": {"coordinates":[-122.386166,37.616356],"type":"Point"}
}