{
  "type": "Feature",
  "properties": {
    "date:cessation_lower": "2011-11-09",
    "date:cessation_upper": "2011-11-09",
    "date:inception_lower": "2011-11-09",
    "date:inception_upper": "2011-11-09",
    "iso:country": "US",
    "sfomuseum:placetype": "tweet",
    "twitter:tweet": {
      "created": 1320870011,
      "created_at": "Wed Nov 09 20:20:11 +0000 2011",
      "display_text_range": [
        "0",
        "133"
      ],
      "edit_info": {
        "initial": {
          "editTweetIds": [
            "134364684567592961"
          ],
          "editableUntil": "2011-11-09T20:50:11.833Z",
          "editsRemaining": "5",
          "isEditEligible": true
        }
      },
      "entities": {
        "urls": [
          {
            "display_url": "ow.ly/1A5khL",
            "expanded_url": "http://ow.ly/1A5khL",
            "indices": [
              "113",
              "133"
            ],
            "url": "http://t.co/fxwz7yfU"
          }
        ]
      },
      "favorite_count": "0",
      "favorited": false,
      "full_text": "To brighten your day, we offer the celebrated master of folk ceramics, Candelario Medrano, on display in the IT: http://t.co/fxwz7yfU",
      "id_str": "134364684567592961",
      "lang": "en",
      "possibly_sensitive": false,
      "retweet_count": "0",
      "retweeted": false,
      "source": "\u003ca href=\"http://www.hootsuite.com\" rel=\"nofollow\"\u003eHootsuite\u003c/a\u003e",
      "truncated": false
    },
    "wof:name": "To brighten your day, we offer the celebrated master of folk ceramics, Candelario Medrano, on display in the IT: http://t.co/fxwz7yfU",
    "wof:placetype": "custom"
  },
  "geometry": {"coordinates":[-122.386166,37.616356],"type":"Point"}
}
