{
  "type": "Feature",
  "properties": {
    "sfomuseum:placetype": "tweet",
    "twitter:tweet": {
      "created": 1404260604,
      "created_at": "Wed Jul 02 00:23:24 +0000 2014",
      "display_text_range": [
        "0", 
        "106"
      ],
      "entities": {
        "hashtags": [
          {
            "indices": [
              "99", 
              "106"
            ],
            "text": "avgeek"
          }
        ],
        "urls": [
          {
            "display_url": "ow.ly/yG32u",
            "expanded_url": "http://ow.ly/yG32u",
            "indices": [
              "76", 
              "98"
            ],
            "url": "http://t.co/WLU7q6Oag9"
          }
        ]
      },
      "favorite_count": "0",
      "favorited": false,
      "full_text": "Delta's handy family tree features the evolution of airlines of years past: http://t.co/WLU7q6Oag9 #avgeek",
      "id_str": "484130182673223683",
      "lang": "en",
      "possibly_sensitive": false,
      "retweet_count": "0",
      "retweeted": false,
      "source": "\u003ca href=\"http://www.hootsuite.com\" rel=\"nofollow\"\u003eHootsuite\u003c/a\u003e",
      "truncated": false
    },
    "wof:name": "Twitter message #484130182673223683",
    "wof:placetype": "custom"
  },
  "geometry": {"coordinates":[-122.386166,37.616356],"type":"Point"}
}
