{
  "type": "Feature",
  "properties": {
    "date:cessation_lower": "2023-03-21",
    "date:cessation_upper": "2023-03-21",
    "date:inception_lower": "2023-03-21",
    "date:inception_upper": "2023-03-21",
    "sfomuseum:placetype": "tweet",
    "twitter:tweet": {
      "created": 1679358337,
      "created_at": "Tue Mar 21 00:25:37 +0000 2023",
      "display_text_range": [
        "0",
        "278"
      ],
      "edit_info": {
        "initial": {
          "editTweetIds": [
            "1637973700963360768"
          ],
          "editableUntil": "2023-03-21T00:55:37.000Z",
          "editsRemaining": "5",
          "isEditEligible": false
        }
      },
      "entities": {
        "hashtags": [
          {
            "indices": [
              "262",
              "278"
            ],
            "text": "WomenInAviation"
          }
        ],
        "user_mentions": [
          {
            "id_str": "475278265",
            "indices": [
              "56",
              "71"
            ],
            "name": "The Ninety-Nines, Inc.®",
            "screen_name": "TheNinetyNines"
          },
          {
            "id_str": "123634795",
            "indices": [
              "141",
              "146"
            ],
            "name": "NAHF",
            "screen_name": "NAHF"
          }
        ]
      },
      "favorite_count": "3",
      "favorited": false,
      "full_text": "Zoe Dell helped to organize the Monterey Bay Chapter of @TheNinetyNines in 1965. She and her husband are credited as founding members of the @NAHF in Dayton, OH. She served as their first female president and was inducted in 2008 as a Living Legend of Aviation. #WomenInAviation",
      "id_str": "1637973700963360768",
      "in_reply_to_screen_name": "SFOMuseum",
      "in_reply_to_status_id": "1637973699604406272",
      "in_reply_to_status_id_str": "1637973699604406272",
      "in_reply_to_user_id": "116329337",
      "in_reply_to_user_id_str": "116329337",
      "lang": "en",
      "retweet_count": "0",
      "retweeted": false,
      "source": "\u003ca href=\"https://mobile.twitter.com\" rel=\"nofollow\"\u003eTwitter Web App\u003c/a\u003e",
      "truncated": false
    },
    "wof:name": "Zoe Dell helped to organize the Monterey Bay Chapter of @TheNinetyNines in 1965. She and her husband are credited as founding members of the @NAHF in Dayton, OH. She served as their first female president and was inducted in 2008 as a Living Legend of Aviation. #WomenInAviation",
    "wof:placetype": "custom"
  },
  "geometry": {"coordinates":[-122.386166,37.616356],"type":"Point"}
}
