{
  "type": "Feature",
  "properties": {
    "date:cessation_lower": "2015-07-09",
    "date:cessation_upper": "2015-07-09",
    "date:inception_lower": "2015-07-09",
    "date:inception_upper": "2015-07-09",
    "iso:country": "US",
    "sfomuseum:placetype": "tweet",
    "twitter:hashtags": [
      "ILoveYouCA"
    ],
    "twitter:tweet": {
      "created": 1436482462,
      "created_at": "Thu Jul 09 22:54:22 +0000 2015",
      "display_text_range": [
        "0",
        "119"
      ],
      "edit_info": {
        "initial": {
          "editTweetIds": [
            "619278446791888897"
          ],
          "editableUntil": "2015-07-09T23:54:22.009Z",
          "editsRemaining": "5",
          "isEditEligible": true
        }
      },
      "entities": {
        "hashtags": [
          {
            "indices": [
              "59",
              "70"
            ],
            "text": "ILoveYouCA"
          }
        ],
        "urls": [
          {
            "display_url": "instagram.com/p/47tGFuRk26/",
            "expanded_url": "https://instagram.com/p/47tGFuRk26/",
            "indices": [
              "96",
              "119"
            ],
            "url": "https://t.co/igKswVbVfn"
          }
        ]
      },
      "favorite_count": "0",
      "favorited": false,
      "full_text": "Installation is underway in the International Terminal for #ILoveYouCA, the natural history of… https://t.co/igKswVbVfn",
      "id_str": "619278446791888897",
      "lang": "en",
      "possibly_sensitive": false,
      "retweet_count": "1",
      "retweeted": false,
      "source": "\u003ca href=\"http://instagram.com\" rel=\"nofollow\"\u003eInstagram\u003c/a\u003e",
      "truncated": false
    },
    "wof:name": "Installation is underway in the International Terminal for #ILoveYouCA, the natural history of… https://t.co/igKswVbVfn",
    "wof:placetype": "custom"
  },
  "geometry": {"coordinates":[-122.386166,37.616356],"type":"Point"}
}
