{
  "type": "Feature",
  "properties": {
    "sfomuseum:placetype": "tweet",
    "twitter:tweet": {
      "created": 1514148004,
      "created_at": "Sun Dec 24 20:40:04 +0000 2017",
      "display_text_range": [
        "0", 
        "191"
      ],
      "entities": {
        "hashtags": [
          {
            "indices": [
              "66", 
              "81"
            ],
            "text": "WilliamGarnett"
          }
        ],
        "media": [
          {
            "display_url": "pic.twitter.com/FhZaFuX1Kw",
            "expanded_url": "https://twitter.com/SFOMuseum/status/945031341699207168/photo/1",
            "id_str": "945031338205351940",
            "indices": [
              "168", 
              "191"
            ],
            "media_url": "http://pbs.twimg.com/media/DR1s_r9XkAQcb79.jpg",
            "media_url_https": "https://pbs.twimg.com/media/DR1s_r9XkAQcb79.jpg",
            "sizes": {
              "large": {
                "h": "2000",
                "resize": "fit",
                "w": "1425"
              },
              "medium": {
                "h": "1200",
                "resize": "fit",
                "w": "855"
              },
              "small": {
                "h": "680",
                "resize": "fit",
                "w": "485"
              },
              "thumb": {
                "h": "150",
                "resize": "crop",
                "w": "150"
              }
            },
            "type": "photo",
            "url": "https://t.co/FhZaFuX1Kw"
          }
        ]
      },
      "extended_entities": {
        "media": [
          {
            "display_url": "pic.twitter.com/FhZaFuX1Kw",
            "expanded_url": "https://twitter.com/SFOMuseum/status/945031341699207168/photo/1",
            "id_str": "945031338205351940",
            "indices": [
              "168", 
              "191"
            ],
            "media_url": "http://pbs.twimg.com/media/DR1s_r9XkAQcb79.jpg",
            "media_url_https": "https://pbs.twimg.com/media/DR1s_r9XkAQcb79.jpg",
            "sizes": {
              "large": {
                "h": "2000",
                "resize": "fit",
                "w": "1425"
              },
              "medium": {
                "h": "1200",
                "resize": "fit",
                "w": "855"
              },
              "small": {
                "h": "680",
                "resize": "fit",
                "w": "485"
              },
              "thumb": {
                "h": "150",
                "resize": "crop",
                "w": "150"
              }
            },
            "type": "photo",
            "url": "https://t.co/FhZaFuX1Kw"
          }
        ]
      },
      "favorite_count": "4",
      "favorited": false,
      "full_text": "In an era when most aerial photography was produced mechanically, #WilliamGarnett worked with an artist’s eye, pioneering the use of aerial photography as an art form. https://t.co/FhZaFuX1Kw",
      "id_str": "945031341699207168",
      "lang": "en",
      "possibly_sensitive": false,
      "retweet_count": "0",
      "retweeted": false,
      "source": "\u003ca href=\"http://www.hootsuite.com\" rel=\"nofollow\"\u003eHootsuite\u003c/a\u003e",
      "truncated": false
    },
    "wof:name": "Twitter message #945031341699207168",
    "wof:placetype": "custom"
  },
  "geometry": {"coordinates":[-122.386166,37.616356],"type":"Point"}
}
