{
  "type": "Feature",
  "properties": {
    "sfomuseum:placetype": "tweet",
    "twitter:tweet": {
      "created": 1323111960,
      "created_at": "Mon Dec 05 19:06:00 +0000 2011",
      "display_text_range": [
        "0", 
        "83"
      ],
      "entities": {
        "urls": [
          {
            "display_url": "instagr.am/p/XKS74/",
            "expanded_url": "http://instagr.am/p/XKS74/",
            "indices": [
              "63", 
              "83"
            ],
            "url": "http://t.co/9iVXgWTC"
          }
        ],
        "user_mentions": [
          {
            "id_str": "22503207",
            "indices": [
              "3", 
              "11"
            ],
            "name": "𝒶𝓀𝑒𝓂𝒾",
            "screen_name": "ImekaSF"
          }
        ]
      },
      "favorite_count": "0",
      "favorited": false,
      "full_text": "RT @ImekaSF: Super cool record exhibition at SFO Terminal 2... http://t.co/9iVXgWTC",
      "id_str": "143768100259639296",
      "lang": "en",
      "possibly_sensitive": false,
      "retweet_count": "1",
      "retweeted": false,
      "source": "\u003ca href=\"https://about.twitter.com/products/tweetdeck\" rel=\"nofollow\"\u003eTweetDeck\u003c/a\u003e",
      "truncated": false
    },
    "wof:name": "Twitter message #143768100259639296",
    "wof:placetype": "custom"
  },
  "geometry": {"coordinates":[-122.386166,37.616356],"type":"Point"}
}
