{
  "type": "Feature",
  "properties": {
    "date:cessation_lower": "2012-06-27",
    "date:cessation_upper": "2012-06-27",
    "date:inception_lower": "2012-06-27",
    "date:inception_upper": "2012-06-27",
    "iso:country": "US",
    "sfomuseum:placetype": "tweet",
    "twitter:tweet": {
      "created": 1340823284,
      "created_at": "Wed Jun 27 18:54:44 +0000 2012",
      "display_text_range": [
        "0",
        "133"
      ],
      "edit_info": {
        "initial": {
          "editTweetIds": [
            "218054774476648448"
          ],
          "editableUntil": "2012-06-27T19:24:44.154Z",
          "editsRemaining": "5",
          "isEditEligible": true
        }
      },
      "entities": {
        "hashtags": [
          {
            "indices": [
              "0",
              "9"
            ],
            "text": "Aviation"
          }
        ],
        "urls": [
          {
            "display_url": "yfrog.com/mne74fdj",
            "expanded_url": "http://yfrog.com/mne74fdj",
            "indices": [
              "113",
              "133"
            ],
            "url": "http://t.co/w1raBoLv"
          }
        ]
      },
      "favorite_count": "0",
      "favorited": false,
      "full_text": "#Aviation irreverence: 1965 Sun Aire Lines air sickness bag invites users to join the Quyat Erp Barfing Society: http://t.co/w1raBoLv",
      "id_str": "218054774476648448",
      "lang": "en",
      "possibly_sensitive": false,
      "retweet_count": "0",
      "retweeted": false,
      "source": "\u003ca href=\"https://about.twitter.com/products/tweetdeck\" rel=\"nofollow\"\u003eTweetDeck\u003c/a\u003e",
      "truncated": false
    },
    "wof:name": "#Aviation irreverence: 1965 Sun Aire Lines air sickness bag invites users to join the Quyat Erp Barfing Society: http://t.co/w1raBoLv",
    "wof:placetype": "custom"
  },
  "geometry": {"coordinates":[-122.386166,37.616356],"type":"Point"}
}
