{
  "type": "Feature",
  "properties": {
    "date:cessation_lower": "2013-11-01",
    "date:cessation_upper": "2013-11-01",
    "date:inception_lower": "2013-11-01",
    "date:inception_upper": "2013-11-01",
    "iso:country": "US",
    "sfomuseum:placetype": "tweet",
    "twitter:tweet": {
      "created": 1383332276,
      "created_at": "Fri Nov 01 18:57:56 +0000 2013",
      "display_text_range": [
        "0",
        "58"
      ],
      "edit_info": {
        "initial": {
          "editTweetIds": [
            "396350410258415616"
          ],
          "editableUntil": "2013-11-01T19:27:56.297Z",
          "editsRemaining": "5",
          "isEditEligible": true
        }
      },
      "entities": {
        "hashtags": [
          {
            "indices": [
              "22",
              "35"
            ],
            "text": "JapaneseToys"
          }
        ],
        "urls": [
          {
            "display_url": "instagram.com/p/gLs1Ltxk9H/",
            "expanded_url": "http://instagram.com/p/gLs1Ltxk9H/",
            "indices": [
              "36",
              "58"
            ],
            "url": "http://t.co/IaFX9U5xN4"
          }
        ]
      },
      "favorite_count": "0",
      "favorited": false,
      "full_text": "Settling Red King in. #JapaneseToys http://t.co/IaFX9U5xN4",
      "id_str": "396350410258415616",
      "lang": "en",
      "possibly_sensitive": false,
      "retweet_count": "1",
      "retweeted": false,
      "source": "\u003ca href=\"http://instagram.com\" rel=\"nofollow\"\u003eInstagram\u003c/a\u003e",
      "truncated": false
    },
    "wof:name": "Settling Red King in. #JapaneseToys http://t.co/IaFX9U5xN4",
    "wof:placetype": "custom"
  },
  "geometry": {"coordinates":[-122.386166,37.616356],"type":"Point"}
}
