{
  "type": "Feature",
  "properties": {
    "sfomuseum:placetype": "tweet",
    "twitter:tweet": {
      "created": 1383332276,
      "created_at": "Fri Nov 01 18:57:56 +0000 2013",
      "display_text_range": [
        "0", 
        "58"
      ],
      "entities": {
        "hashtags": [
          {
            "indices": [
              "22", 
              "35"
            ],
            "text": "JapaneseToys"
          }
        ],
        "urls": [
          {
            "display_url": "instagram.com/p/gLs1Ltxk9H/",
            "expanded_url": "http://instagram.com/p/gLs1Ltxk9H/",
            "indices": [
              "36", 
              "58"
            ],
            "url": "http://t.co/IaFX9U5xN4"
          }
        ]
      },
      "favorite_count": "0",
      "favorited": false,
      "full_text": "Settling Red King in. #JapaneseToys http://t.co/IaFX9U5xN4",
      "id_str": "396350410258415616",
      "lang": "en",
      "possibly_sensitive": false,
      "retweet_count": "1",
      "retweeted": false,
      "source": "\u003ca href=\"http://instagram.com\" rel=\"nofollow\"\u003eInstagram\u003c/a\u003e",
      "truncated": false
    },
    "wof:name": "Twitter message #396350410258415616",
    "wof:placetype": "custom"
  },
  "geometry": {"coordinates":[-122.386166,37.616356],"type":"Point"}
}
