{
  "type": "Feature",
  "properties": {
    "sfomuseum:placetype": "tweet",
    "twitter:tweet": {
      "created": 1317920710,
      "created_at": "Thu Oct 06 17:05:10 +0000 2011",
      "display_text_range": [
        "0", 
        "65"
      ],
      "entities": {
        "user_mentions": [
          {
            "id_str": "14060372",
            "indices": [
              "0", 
              "11"
            ],
            "name": "Mike Gualtieri",
            "screen_name": "mgualtieri"
          }, 
          {
            "id_str": "15288527",
            "indices": [
              "12", 
              "26"
            ],
            "name": "Glenn O'Donnell",
            "screen_name": "glennodonnell"
          }
        ]
      },
      "favorite_count": "0",
      "favorited": false,
      "full_text": "@mgualtieri @glennodonnell We're so glad you enjoyed the exhibit!",
      "id_str": "121994419963572224",
      "in_reply_to_screen_name": "mgualtieri",
      "in_reply_to_status_id": "121983691164631040",
      "in_reply_to_status_id_str": "121983691164631040",
      "in_reply_to_user_id": "14060372",
      "in_reply_to_user_id_str": "14060372",
      "lang": "en",
      "retweet_count": "0",
      "retweeted": false,
      "source": "\u003ca href=\"http://www.hootsuite.com\" rel=\"nofollow\"\u003eHootsuite\u003c/a\u003e",
      "truncated": false
    },
    "wof:name": "Twitter message #121994419963572224",
    "wof:placetype": "custom"
  },
  "geometry": {"coordinates":[-122.386166,37.616356],"type":"Point"}
}
