{
  "type": "Feature",
  "properties": {
    "date:cessation_lower": "2022-03-11",
    "date:cessation_upper": "2022-03-11",
    "date:inception_lower": "2022-03-11",
    "date:inception_upper": "2022-03-11",
    "sfomuseum:placetype": "tweet",
    "twitter:tweet": {
      "created": 1646964149,
      "created_at": "Fri Mar 11 02:02:29 +0000 2022",
      "display_text_range": [
        "0",
        "190"
      ],
      "edit_info": {
        "initial": {
          "editTweetIds": [
            "1502102631983976449"
          ],
          "editableUntil": "2022-03-11T03:02:29.839Z",
          "editsRemaining": "5",
          "isEditEligible": true
        }
      },
      "entities": {
      },
      "favorite_count": "1",
      "favorited": false,
      "full_text": "📸 2/2:\nluggage label: Capital Airlines; 1950s\nGift of Thomas G. Dragges\n2015.168.111\n\npostcard: Capital Airlines, Washington, Douglas DC-4; \nc. 1948\nGift of Captain Jon Simmonds\n2015.057.347",
      "id_str": "1502102631983976449",
      "in_reply_to_screen_name": "SFOMuseum",
      "in_reply_to_status_id": "1502102629840605190",
      "in_reply_to_status_id_str": "1502102629840605190",
      "in_reply_to_user_id": "116329337",
      "in_reply_to_user_id_str": "116329337",
      "lang": "en",
      "retweet_count": "0",
      "retweeted": false,
      "source": "\u003ca href=\"https://mobile.twitter.com\" rel=\"nofollow\"\u003eTwitter Web App\u003c/a\u003e",
      "truncated": false
    },
    "wof:name": "📸 2/2:\nluggage label: Capital Airlines; 1950s\nGift of Thomas G. Dragges\n2015.168.111\n\npostcard: Capital Airlines, Washington, Douglas DC-4; \nc. 1948\nGift of Captain Jon Simmonds\n2015.057.347",
    "wof:placetype": "custom"
  },
  "geometry": {"coordinates":[-122.386166,37.616356],"type":"Point"}
}
