{
  "type": "Feature",
  "properties": {
    "date:cessation_lower": "2022-05-13",
    "date:cessation_upper": "2022-05-13",
    "date:inception_lower": "2022-05-13",
    "date:inception_upper": "2022-05-13",
    "sfomuseum:placetype": "tweet",
    "twitter:tweet": {
      "created": 1652402855,
      "created_at": "Fri May 13 00:47:35 +0000 2022",
      "display_text_range": [
        "0",
        "220"
      ],
      "edit_info": {
        "initial": {
          "editTweetIds": [
            "1524914215957430274"
          ],
          "editableUntil": "2022-05-13T01:17:35.000Z",
          "editsRemaining": "5",
          "isEditEligible": true
        }
      },
      "entities": {
      },
      "favorite_count": "1",
      "favorited": false,
      "full_text": "📸 2/2:\nbrochure: Flying Tiger (Cargo); c. 1975\nGift of the Ralph F. Mitchell, Jr. Family\n2013.146.031\n\npromotional print: Flying Tiger Line, Boeing 707-349C; c. 1975\nGift of the Ralph F. Mitchell, Jr. Family\n2013.146.184",
      "id_str": "1524914215957430274",
      "in_reply_to_screen_name": "SFOMuseum",
      "in_reply_to_status_id": "1524914213608599552",
      "in_reply_to_status_id_str": "1524914213608599552",
      "in_reply_to_user_id": "116329337",
      "in_reply_to_user_id_str": "116329337",
      "lang": "en",
      "retweet_count": "0",
      "retweeted": false,
      "source": "\u003ca href=\"https://mobile.twitter.com\" rel=\"nofollow\"\u003eTwitter Web App\u003c/a\u003e",
      "truncated": false
    },
    "wof:name": "📸 2/2:\nbrochure: Flying Tiger (Cargo); c. 1975\nGift of the Ralph F. Mitchell, Jr. Family\n2013.146.031\n\npromotional print: Flying Tiger Line, Boeing 707-349C; c. 1975\nGift of the Ralph F. Mitchell, Jr. Family\n2013.146.184",
    "wof:placetype": "custom"
  },
  "geometry": {"coordinates":[-122.386166,37.616356],"type":"Point"}
}
