{
  "type": "Feature",
  "properties": {
    "date:cessation_lower": "2011-11-07",
    "date:cessation_upper": "2011-11-07",
    "date:inception_lower": "2011-11-07",
    "date:inception_upper": "2011-11-07",
    "iso:country": "US",
    "sfomuseum:placetype": "tweet",
    "twitter:tweet": {
      "created": 1320709393,
      "created_at": "Mon Nov 07 23:43:13 +0000 2011",
      "display_text_range": [
        "0", 
        "71"
      ],
      "entities": {
        "user_mentions": [
          {
            "id_str": "7081402",
            "indices": [
              "0", 
              "11"
            ],
            "name": "Bonnie Burton",
            "screen_name": "bonniegrrl"
          }
        ]
      },
      "favorite_count": "0",
      "favorited": false,
      "full_text": "@bonniegrrl Thanks for checking out our exhibit! Live long and prosper!",
      "id_str": "133691000752312322",
      "in_reply_to_screen_name": "bonniegrrl",
      "in_reply_to_user_id": "7081402",
      "in_reply_to_user_id_str": "7081402",
      "lang": "en",
      "retweet_count": "0",
      "retweeted": false,
      "source": "\u003ca href=\"https://about.twitter.com/products/tweetdeck\" rel=\"nofollow\"\u003eTweetDeck\u003c/a\u003e",
      "truncated": false
    },
    "wof:name": "@bonniegrrl Thanks for checking out our exhibit! Live long and prosper!",
    "wof:placetype": "custom"
  },
  "geometry": {"coordinates":[-122.386166,37.616356],"type":"Point"}
}
