{
  "type": "Feature",
  "properties": {
    "date:cessation_lower": "2021-11-20",
    "date:cessation_upper": "2021-11-20",
    "date:inception_lower": "2021-11-20",
    "date:inception_upper": "2021-11-20",
    "sfomuseum:placetype": "tweet",
    "twitter:tweet": {
      "created": 1637368157,
      "created_at": "Sat Nov 20 00:29:17 +0000 2021",
      "display_text_range": [
        "0",
        "203"
      ],
      "edit_info": {
        "initial": {
          "editTweetIds": [
            "1461854122060115970"
          ],
          "editableUntil": "2021-11-20T01:29:17.292Z",
          "editsRemaining": "5",
          "isEditEligible": true
        }
      },
      "entities": {
      },
      "favorite_count": "0",
      "favorited": false,
      "full_text": "📸1/2:\nStorage jar  c. 1840–50\nThomas Chandler (1810-54)\nEdgefield District, South Carolina\nalkaline-glazed stoneware with brush-applied iron slip decoration\nCollection of Kenneth Fechtner \nL2020.1401.006",
      "id_str": "1461854122060115970",
      "in_reply_to_screen_name": "SFOMuseum",
      "in_reply_to_status_id": "1461854119430213634",
      "in_reply_to_status_id_str": "1461854119430213634",
      "in_reply_to_user_id": "116329337",
      "in_reply_to_user_id_str": "116329337",
      "lang": "en",
      "retweet_count": "0",
      "retweeted": false,
      "source": "\u003ca href=\"https://mobile.twitter.com\" rel=\"nofollow\"\u003eTwitter Web App\u003c/a\u003e",
      "truncated": false
    },
    "wof:name": "📸1/2:\nStorage jar  c. 1840–50\nThomas Chandler (1810-54)\nEdgefield District, South Carolina\nalkaline-glazed stoneware with brush-applied iron slip decoration\nCollection of Kenneth Fechtner \nL2020.1401.006",
    "wof:placetype": "custom"
  },
  "geometry": {"coordinates":[-122.386166,37.616356],"type":"Point"}
}
