{
  "type": "Feature",
  "properties": {
    "sfomuseum:placetype": "tweet",
    "twitter:tweet": {
      "created": 1442282708,
      "created_at": "Tue Sep 15 02:05:08 +0000 2015",
      "display_text_range": [
        "0", 
        "88"
      ],
      "entities": {
        "hashtags": [
          {
            "indices": [
              "49", 
              "65"
            ],
            "text": "behindthescenes"
          }
        ],
        "media": [
          {
            "display_url": "pic.twitter.com/uM231hDnEW",
            "expanded_url": "https://twitter.com/SFOMuseum/status/643606441912365056/photo/1",
            "id_str": "643606441279029249",
            "indices": [
              "66", 
              "88"
            ],
            "media_url": "http://pbs.twimg.com/media/CO6MpfuXAAEaYm2.jpg",
            "media_url_https": "https://pbs.twimg.com/media/CO6MpfuXAAEaYm2.jpg",
            "sizes": {
              "large": {
                "h": "1536",
                "resize": "fit",
                "w": "2048"
              },
              "medium": {
                "h": "900",
                "resize": "fit",
                "w": "1200"
              },
              "small": {
                "h": "510",
                "resize": "fit",
                "w": "680"
              },
              "thumb": {
                "h": "150",
                "resize": "crop",
                "w": "150"
              }
            },
            "type": "photo",
            "url": "http://t.co/uM231hDnEW"
          }
        ]
      },
      "extended_entities": {
        "media": [
          {
            "display_url": "pic.twitter.com/uM231hDnEW",
            "expanded_url": "https://twitter.com/SFOMuseum/status/643606441912365056/photo/1",
            "id_str": "643606441279029249",
            "indices": [
              "66", 
              "88"
            ],
            "media_url": "http://pbs.twimg.com/media/CO6MpfuXAAEaYm2.jpg",
            "media_url_https": "https://pbs.twimg.com/media/CO6MpfuXAAEaYm2.jpg",
            "sizes": {
              "large": {
                "h": "1536",
                "resize": "fit",
                "w": "2048"
              },
              "medium": {
                "h": "900",
                "resize": "fit",
                "w": "1200"
              },
              "small": {
                "h": "510",
                "resize": "fit",
                "w": "680"
              },
              "thumb": {
                "h": "150",
                "resize": "crop",
                "w": "150"
              }
            },
            "type": "photo",
            "url": "http://t.co/uM231hDnEW"
          }
        ]
      },
      "favorite_count": "0",
      "favorited": false,
      "full_text": "These fragile objects are packed very carefully. #behindthescenes http://t.co/uM231hDnEW",
      "id_str": "643606441912365056",
      "lang": "en",
      "possibly_sensitive": false,
      "retweet_count": "0",
      "retweeted": false,
      "source": "\u003ca href=\"http://www.hootsuite.com\" rel=\"nofollow\"\u003eHootsuite\u003c/a\u003e",
      "truncated": false
    },
    "wof:name": "Twitter message #643606441912365056",
    "wof:placetype": "custom"
  },
  "geometry": {"coordinates":[-122.386166,37.616356],"type":"Point"}
}
