{
  "type": "Feature",
  "properties": {
    "sfomuseum:placetype": "tweet",
    "twitter:tweet": {
      "created": 1482889811,
      "created_at": "Wed Dec 28 01:50:11 +0000 2016",
      "display_text_range": [
        "0", 
        "161"
      ],
      "entities": {
        "hashtags": [
          {
            "indices": [
              "121", 
              "137"
            ],
            "text": "AModernApproach"
          }
        ],
        "media": [
          {
            "display_url": "pic.twitter.com/GasNsW7rxP",
            "expanded_url": "https://twitter.com/SFOMuseum/status/813924976839495681/photo/1",
            "id_str": "813924973299568640",
            "indices": [
              "138", 
              "161"
            ],
            "media_url": "http://pbs.twimg.com/media/C0ukc2tXEAA1Cwg.jpg",
            "media_url_https": "https://pbs.twimg.com/media/C0ukc2tXEAA1Cwg.jpg",
            "sizes": {
              "large": {
                "h": "1473",
                "resize": "fit",
                "w": "2000"
              },
              "medium": {
                "h": "884",
                "resize": "fit",
                "w": "1200"
              },
              "small": {
                "h": "501",
                "resize": "fit",
                "w": "680"
              },
              "thumb": {
                "h": "150",
                "resize": "crop",
                "w": "150"
              }
            },
            "type": "photo",
            "url": "https://t.co/GasNsW7rxP"
          }
        ]
      },
      "extended_entities": {
        "media": [
          {
            "display_url": "pic.twitter.com/GasNsW7rxP",
            "expanded_url": "https://twitter.com/SFOMuseum/status/813924976839495681/photo/1",
            "id_str": "813924973299568640",
            "indices": [
              "138", 
              "161"
            ],
            "media_url": "http://pbs.twimg.com/media/C0ukc2tXEAA1Cwg.jpg",
            "media_url_https": "https://pbs.twimg.com/media/C0ukc2tXEAA1Cwg.jpg",
            "sizes": {
              "large": {
                "h": "1473",
                "resize": "fit",
                "w": "2000"
              },
              "medium": {
                "h": "884",
                "resize": "fit",
                "w": "1200"
              },
              "small": {
                "h": "501",
                "resize": "fit",
                "w": "680"
              },
              "thumb": {
                "h": "150",
                "resize": "crop",
                "w": "150"
              }
            },
            "type": "photo",
            "url": "https://t.co/GasNsW7rxP"
          }
        ]
      },
      "favorite_count": "0",
      "favorited": false,
      "full_text": "Adaline Kent worked primarily in fine arts sculpture and crossed into the decorative arts with this sculpted candelabra. #AModernApproach https://t.co/GasNsW7rxP",
      "id_str": "813924976839495681",
      "lang": "en",
      "possibly_sensitive": false,
      "retweet_count": "1",
      "retweeted": false,
      "source": "\u003ca href=\"http://www.hootsuite.com\" rel=\"nofollow\"\u003eHootsuite\u003c/a\u003e",
      "truncated": false
    },
    "wof:name": "Twitter message #813924976839495681",
    "wof:placetype": "custom"
  },
  "geometry": {"coordinates":[-122.386166,37.616356],"type":"Point"}
}
