{
  "type": "Feature",
  "properties": {
    "date:cessation_lower": "2021-09-09",
    "date:cessation_upper": "2021-09-09",
    "date:inception_lower": "2021-09-09",
    "date:inception_upper": "2021-09-09",
    "sfomuseum:placetype": "tweet",
    "twitter:tweet": {
      "created": 1631156183,
      "created_at": "Thu Sep 09 02:56:23 +0000 2021",
      "display_text_range": [
        "0",
        "267"
      ],
      "edit_info": {
        "initial": {
          "editTweetIds": [
            "1435799214592651264"
          ],
          "editableUntil": "2021-09-09T03:56:23.275Z",
          "editsRemaining": "5",
          "isEditEligible": true
        }
      },
      "entities": {
      },
      "favorite_count": "0",
      "favorited": false,
      "full_text": "📸:\npostcard: Tupolev Tu-144 prototype; c. 1972\nGift of Thomas G. Dragges\n2015.166.0093\n\nslide: Tupolev Tu-144 prototype; c. 1972\nGift of John Warren Minor, Jr.\n2017.097.072\n\npostcard: Tupolev Tu-144 prototype; c. 1972\nGift of the William Hough Collection\n2008.055.064",
      "id_str": "1435799214592651264",
      "in_reply_to_screen_name": "SFOMuseum",
      "in_reply_to_status_id": "1435799212612984835",
      "in_reply_to_status_id_str": "1435799212612984835",
      "in_reply_to_user_id": "116329337",
      "in_reply_to_user_id_str": "116329337",
      "lang": "en",
      "retweet_count": "0",
      "retweeted": false,
      "source": "\u003ca href=\"https://mobile.twitter.com\" rel=\"nofollow\"\u003eTwitter Web App\u003c/a\u003e",
      "truncated": false
    },
    "wof:name": "📸:\npostcard: Tupolev Tu-144 prototype; c. 1972\nGift of Thomas G. Dragges\n2015.166.0093\n\nslide: Tupolev Tu-144 prototype; c. 1972\nGift of John Warren Minor, Jr.\n2017.097.072\n\npostcard: Tupolev Tu-144 prototype; c. 1972\nGift of the William Hough Collection\n2008.055.064",
    "wof:placetype": "custom",
    "wof:placetype_alt": [
      "tweet"
    ]
  },
  "geometry": {"coordinates":[-122.386166,37.616356],"type":"Point"}
}
