{
  "type": "Feature",
  "properties": {
    "date:cessation_lower": "2014-07-18",
    "date:cessation_upper": "2014-07-18",
    "date:inception_lower": "2014-07-18",
    "date:inception_upper": "2014-07-18",
    "iso:country": "US",
    "sfomuseum:placetype": "tweet",
    "twitter:tweet": {
      "created": 1405727756,
      "created_at": "Fri Jul 18 23:55:56 +0000 2014",
      "display_text_range": [
        "0",
        "143"
      ],
      "entities": {
        "urls": [
          {
            "display_url": "ow.ly/zkMne",
            "expanded_url": "http://ow.ly/zkMne",
            "indices": [
              "121",
              "143"
            ],
            "url": "http://t.co/vJCZCih79B"
          }
        ]
      },
      "favorite_count": "1",
      "favorited": false,
      "full_text": "Western Air Express' 1920s SF-LA brochure includes an intriguing short story \u0026amp; lovely fine print about the $50 fare: http://t.co/vJCZCih79B",
      "id_str": "490283862585798656",
      "lang": "en",
      "possibly_sensitive": false,
      "retweet_count": "0",
      "retweeted": false,
      "source": "\u003ca href=\"http://www.hootsuite.com\" rel=\"nofollow\"\u003eHootsuite\u003c/a\u003e",
      "truncated": false
    },
    "wof:name": "Western Air Express' 1920s SF-LA brochure includes an intriguing short story \u0026amp; lovely fine print about the $50 fare: http://t.co/vJCZCih79B",
    "wof:placetype": "custom"
  },
  "geometry": {"coordinates":[-122.386166,37.616356],"type":"Point"}
}
