{
  "type": "Feature",
  "properties": {
    "date:cessation_lower": "2023-12-27",
    "date:cessation_upper": "2023-12-27",
    "date:inception_lower": "2023-12-27",
    "date:inception_upper": "2023-12-27",
    "sfomuseum:placetype": "tweet",
    "twitter:tweet": {
      "created": 1703637560,
      "created_at": "Wed Dec 27 00:39:20 +0000 2023",
      "display_text_range": [
        "0",
        "154"
      ],
      "edit_info": {
        "initial": {
          "editTweetIds": [
            "1739808146250690885"
          ],
          "editableUntil": "2023-12-27T01:39:20.000Z",
          "editsRemaining": "5",
          "isEditEligible": false
        }
      },
      "entities": {
      },
      "favorite_count": "1",
      "favorited": false,
      "full_text": "📸:\nphotograph: San Francisco Airport, Administration Building lobby interior; 01/12/1940\nTransfer from San Francisco International Airport\n1997.52.078.001",
      "id_str": "1739808146250690885",
      "in_reply_to_screen_name": "SFOMuseum",
      "in_reply_to_status_id": "1739808141569933449",
      "in_reply_to_status_id_str": "1739808141569933449",
      "in_reply_to_user_id": "116329337",
      "in_reply_to_user_id_str": "116329337",
      "lang": "en",
      "retweet_count": "0",
      "retweeted": false,
      "source": "\u003ca href=\"https://mobile.twitter.com\" rel=\"nofollow\"\u003eTwitter Web App\u003c/a\u003e",
      "truncated": false
    },
    "wof:name": "📸:\nphotograph: San Francisco Airport, Administration Building lobby interior; 01/12/1940\nTransfer from San Francisco International Airport\n1997.52.078.001",
    "wof:placetype": "custom"
  },
  "geometry": {"coordinates":[-122.386166,37.616356],"type":"Point"}
}
