{
  "type": "Feature",
  "properties": {
    "date:cessation_lower": "2023-03-21",
    "date:cessation_upper": "2023-03-21",
    "date:inception_lower": "2023-03-21",
    "date:inception_upper": "2023-03-21",
    "sfomuseum:placetype": "tweet",
    "twitter:hashtags": [
      "WomenInAviation",
      "WomensHistoryMonth"
    ],
    "twitter:tweet": {
      "created": 1679358336,
      "created_at": "Tue Mar 21 00:25:36 +0000 2023",
      "display_text_range": [
        "0",
        "237"
      ],
      "edit_info": {
        "initial": {
          "editTweetIds": [
            "1637973698409033729"
          ],
          "editableUntil": "2023-03-21T00:55:36.000Z",
          "editsRemaining": "5",
          "isEditEligible": false
        }
      },
      "entities": {
        "hashtags": [
          {
            "indices": [
              "201",
              "217"
            ],
            "text": "WomenInAviation"
          },
          {
            "indices": [
              "218",
              "237"
            ],
            "text": "WomensHistoryMonth"
          }
        ]
      },
      "favorite_count": "0",
      "favorited": false,
      "full_text": "She married her husband, Ervin Nutter in 1965; he owned Elano Corporation, an aerospace engineering firm and supplier. Zoe Dell became president of Elano’s small aircraft division and a company pilot. #WomenInAviation #WomensHistoryMonth",
      "id_str": "1637973698409033729",
      "in_reply_to_screen_name": "SFOMuseum",
      "in_reply_to_status_id": "1637973696878116865",
      "in_reply_to_status_id_str": "1637973696878116865",
      "in_reply_to_user_id": "116329337",
      "in_reply_to_user_id_str": "116329337",
      "lang": "en",
      "retweet_count": "0",
      "retweeted": false,
      "source": "\u003ca href=\"https://mobile.twitter.com\" rel=\"nofollow\"\u003eTwitter Web App\u003c/a\u003e",
      "truncated": false
    },
    "wof:name": "She married her husband, Ervin Nutter in 1965; he owned Elano Corporation, an aerospace engineering firm and supplier. Zoe Dell became president of Elano’s small aircraft division and a company pilot. #WomenInAviation #WomensHistoryMonth",
    "wof:placetype": "custom"
  },
  "geometry": {"coordinates":[-122.386166,37.616356],"type":"Point"}
}
