{
  "type": "Feature",
  "properties": {
    "date:cessation_lower":"2011-10-20",
    "date:cessation_upper":"2011-10-20",
    "date:inception_lower":"2011-10-20",
    "date:inception_upper":"2011-10-20",
    "iso:country":"US",
    "sfomuseum:placetype":"tweet",
    "twitter:tweet":{
        "created":1319147196,
        "created_at":"Thu Oct 20 21:46:36 +0000 2011",
        "display_text_range":[
            "0",
            "60"
        ],
        "entities":{
            "hashtags":[
                {
                    "indices":[
                        "28",
                        "39"
                    ],
                    "text":"earthquake"
                }
            ]
        },
        "favorite_count":"0",
        "favorited":false,
        "full_text":"Good thing we practiced our #earthquake drills this morning.",
        "id_str":"127138674981879808",
        "lang":"en",
        "retweet_count":"0",
        "retweeted":false,
        "source":"<a href=\"https://about.twitter.com/products/tweetdeck\" rel=\"nofollow\">TweetDeck</a>",
        "truncated":false
    },
    "wof:name":"Good thing we practiced our #earthquake drills this morning.",
    "wof:placetype":"custom"
},
  "geometry": {"coordinates":[-122.386166,37.616356],"type":"Point"}
}