{
  "type": "Feature",
  "properties": {
    "sfomuseum:placetype": "tweet",
    "twitter:tweet": {
      "created": 1319147196,
      "created_at": "Thu Oct 20 21:46:36 +0000 2011",
      "display_text_range": [
        "0", 
        "60"
      ],
      "entities": {
        "hashtags": [
          {
            "indices": [
              "28", 
              "39"
            ],
            "text": "earthquake"
          }
        ]
      },
      "favorite_count": "0",
      "favorited": false,
      "full_text": "Good thing we practiced our #earthquake drills this morning.",
      "id_str": "127138674981879808",
      "lang": "en",
      "retweet_count": "0",
      "retweeted": false,
      "source": "\u003ca href=\"https://about.twitter.com/products/tweetdeck\" rel=\"nofollow\"\u003eTweetDeck\u003c/a\u003e",
      "truncated": false
    },
    "wof:name": "Twitter message #127138674981879808",
    "wof:placetype": "custom"
  },
  "geometry": {"coordinates":[-122.386166,37.616356],"type":"Point"}
}
