{
  "type": "Feature",
  "properties": {
    "date:cessation_lower": "2019-05-23",
    "date:cessation_upper": "2019-05-23",
    "date:inception_lower": "2019-05-23",
    "date:inception_upper": "2019-05-23",
    "iso:country": "US",
    "sfomuseum:placetype": "tweet",
    "twitter:tweet": {
      "created": 1558572425,
      "created_at": "Thu May 23 00:47:05 +0000 2019",
      "display_text_range": [
        "0",
        "140"
      ],
      "edit_info": {
        "initial": {
          "editTweetIds": [
            "1131360870913626112"
          ],
          "editableUntil": "2019-05-23T01:17:05.951Z",
          "editsRemaining": "5",
          "isEditEligible": true
        }
      },
      "entities": {
        "hashtags": [
          {
            "indices": [
              "51",
              "65"
            ],
            "text": "HarveyMilkDay"
          }
        ],
        "user_mentions": [
          {
            "id_str": "38349184",
            "indices": [
              "3",
              "14"
            ],
            "name": "Office of the Governor of California",
            "screen_name": "CAgovernor"
          },
          {
            "id_str": "11347122",
            "indices": [
              "17",
              "29"
            ],
            "name": "Gavin Newsom",
            "screen_name": "GavinNewsom"
          }
        ]
      },
      "favorite_count": "0",
      "favorited": false,
      "full_text": "RT @CAgovernor: .@GavinNewsom has proclaimed today #HarveyMilkDay! 🏳️‍🌈\n \nWe honor a hero who fought for freedom and equality. The LGBTQ co…",
      "id_str": "1131360870913626112",
      "lang": "en",
      "retweet_count": "0",
      "retweeted": false,
      "source": "\u003ca href=\"http://twitter.com\" rel=\"nofollow\"\u003eTwitter Web Client\u003c/a\u003e",
      "truncated": false
    },
    "wof:name": "RT @CAgovernor: .@GavinNewsom has proclaimed today #HarveyMilkDay! 🏳️‍🌈\n \nWe honor a hero who fought for freedom and equality. The LGBTQ co…",
    "wof:placetype": "custom"
  },
  "geometry": {"coordinates":[-122.386166,37.616356],"type":"Point"}
}
