{
  "type": "Feature",
  "properties": {
    "sfomuseum:placetype": "tweet",
    "twitter:tweet": {
      "created": 1354131793,
      "created_at": "Wed Nov 28 19:43:13 +0000 2012",
      "display_text_range": [
        "0", 
        "58"
      ],
      "entities": {
        "user_mentions": [
          {
            "id_str": "65772273",
            "indices": [
              "0", 
              "13"
            ],
            "name": "Brad Barton",
            "screen_name": "realitythief"
          }
        ]
      },
      "favorite_count": "0",
      "favorited": false,
      "full_text": "@realitythief  Welcome home! Glad you enjoyed the exhibit.",
      "id_str": "273874708867448832",
      "in_reply_to_screen_name": "realitythief",
      "in_reply_to_user_id": "65772273",
      "in_reply_to_user_id_str": "65772273",
      "lang": "en",
      "retweet_count": "0",
      "retweeted": false,
      "source": "\u003ca href=\"https://about.twitter.com/products/tweetdeck\" rel=\"nofollow\"\u003eTweetDeck\u003c/a\u003e",
      "truncated": false
    },
    "wof:name": "Twitter message #273874708867448832",
    "wof:placetype": "custom"
  },
  "geometry": {"coordinates":[-122.386166,37.616356],"type":"Point"}
}
