{
  "type": "Feature",
  "properties": {
    "sfomuseum:placetype": "tweet",
    "twitter:tweet": {
      "created": 1553120837,
      "created_at": "Wed Mar 20 22:27:17 +0000 2019",
      "display_text_range": [
        "0", 
        "140"
      ],
      "entities": {
        "user_mentions": [
          {
            "id_str": "14848513",
            "indices": [
              "3", 
              "15"
            ],
            "name": "National Air and Space Museum",
            "screen_name": "airandspace"
          }
        ]
      },
      "favorite_count": "0",
      "favorited": false,
      "full_text": "RT @airandspace: Growing up, Mary Riddle was inspired to fly, but some said women pilots couldn't be successful. She wanted to prove them w…",
      "id_str": "1108495252770443266",
      "lang": "en",
      "retweet_count": "0",
      "retweeted": false,
      "source": "\u003ca href=\"https://www.hootsuite.com\" rel=\"nofollow\"\u003eHootsuite Inc.\u003c/a\u003e",
      "truncated": false
    },
    "wof:name": "Twitter message #1108495252770443266",
    "wof:placetype": "custom"
  },
  "geometry": {"coordinates":[-122.386166,37.616356],"type":"Point"}
}
