{
  "type": "Feature",
  "properties": {
    "sfomuseum:placetype": "tweet",
    "twitter:tweet": {
      "created": 1471624594,
      "created_at": "Fri Aug 19 16:36:34 +0000 2016",
      "display_text_range": [
        "0", 
        "140"
      ],
      "entities": {
        "hashtags": [
          {
            "indices": [
              "21", 
              "41"
            ],
            "text": "NationalAviationDay"
          }
        ],
        "user_mentions": [
          {
            "id_str": "13192972",
            "indices": [
              "3", 
              "13"
            ],
            "name": "Alaska Airlines",
            "screen_name": "AlaskaAir"
          }
        ]
      },
      "favorite_count": "0",
      "favorited": false,
      "full_text": "RT @AlaskaAir: Happy #NationalAviationDay. We started flying in 1932 with a three-seat Stinson. Today we’re flying 153 Boeing 737s. https:/…",
      "id_str": "766675234262876160",
      "lang": "en",
      "retweet_count": "0",
      "retweeted": false,
      "source": "\u003ca href=\"http://twitter.com\" rel=\"nofollow\"\u003eTwitter Web Client\u003c/a\u003e",
      "truncated": false
    },
    "wof:name": "Twitter message #766675234262876160",
    "wof:placetype": "custom"
  },
  "geometry": {"coordinates":[-122.386166,37.616356],"type":"Point"}
}
