{
  "type": "Feature",
  "properties": {
    "sfomuseum:placetype": "tweet",
    "twitter:tweet": {
      "created": 1470100807,
      "created_at": "Tue Aug 02 01:20:07 +0000 2016",
      "display_text_range": [
        "0", 
        "140"
      ],
      "entities": {
        "media": [
          {
            "display_url": "pic.twitter.com/R9qD17K7RE",
            "expanded_url": "https://twitter.com/SFOMuseum/status/760284007506608129/photo/1",
            "id_str": "760284003165466624",
            "indices": [
              "117", 
              "140"
            ],
            "media_url": "http://pbs.twimg.com/media/Co0SRdEW8AAyjVz.jpg",
            "media_url_https": "https://pbs.twimg.com/media/Co0SRdEW8AAyjVz.jpg",
            "sizes": {
              "large": {
                "h": "1991",
                "resize": "fit",
                "w": "2000"
              },
              "medium": {
                "h": "1195",
                "resize": "fit",
                "w": "1200"
              },
              "small": {
                "h": "677",
                "resize": "fit",
                "w": "680"
              },
              "thumb": {
                "h": "150",
                "resize": "crop",
                "w": "150"
              }
            },
            "type": "photo",
            "url": "https://t.co/R9qD17K7RE"
          }
        ]
      },
      "extended_entities": {
        "media": [
          {
            "display_url": "pic.twitter.com/R9qD17K7RE",
            "expanded_url": "https://twitter.com/SFOMuseum/status/760284007506608129/photo/1",
            "id_str": "760284003165466624",
            "indices": [
              "117", 
              "140"
            ],
            "media_url": "http://pbs.twimg.com/media/Co0SRdEW8AAyjVz.jpg",
            "media_url_https": "https://pbs.twimg.com/media/Co0SRdEW8AAyjVz.jpg",
            "sizes": {
              "large": {
                "h": "1991",
                "resize": "fit",
                "w": "2000"
              },
              "medium": {
                "h": "1195",
                "resize": "fit",
                "w": "1200"
              },
              "small": {
                "h": "677",
                "resize": "fit",
                "w": "680"
              },
              "thumb": {
                "h": "150",
                "resize": "crop",
                "w": "150"
              }
            },
            "type": "photo",
            "url": "https://t.co/R9qD17K7RE"
          }
        ]
      },
      "favorite_count": "6",
      "favorited": false,
      "full_text": "In this photo from circa 1927 an air mail pilot checks weather conditions before taking off for his next destination https://t.co/R9qD17K7RE",
      "id_str": "760284007506608129",
      "lang": "en",
      "possibly_sensitive": false,
      "retweet_count": "1",
      "retweeted": false,
      "source": "\u003ca href=\"http://www.hootsuite.com\" rel=\"nofollow\"\u003eHootsuite\u003c/a\u003e",
      "truncated": false
    },
    "wof:name": "Twitter message #760284007506608129",
    "wof:placetype": "custom"
  },
  "geometry": {"coordinates":[-122.386166,37.616356],"type":"Point"}
}
