{
  "type": "Feature",
  "properties": {
    "date:cessation_lower": "2013-07-05",
    "date:cessation_upper": "2013-07-05",
    "date:inception_lower": "2013-07-05",
    "date:inception_upper": "2013-07-05",
    "iso:country": "US",
    "sfomuseum:placetype": "tweet",
    "twitter:hashtags": [
      "SFO",
      "Hummer",
      "andrewjunge",
      "artsyfartsy",
      "art"
    ],
    "twitter:tweet": {
      "created": 1373040702,
      "created_at": "Fri Jul 05 16:11:42 +0000 2013",
      "display_text_range": [
        "0",
        "126"
      ],
      "edit_info": {
        "initial": {
          "editTweetIds": [
            "353184421630844929"
          ],
          "editableUntil": "2013-07-05T17:11:42.623Z",
          "editsRemaining": "5",
          "isEditEligible": true
        }
      },
      "entities": {
        "hashtags": [
          {
            "indices": [
              "23",
              "27"
            ],
            "text": "art"
          },
          {
            "indices": [
              "31",
              "35"
            ],
            "text": "SFO"
          },
          {
            "indices": [
              "37",
              "44"
            ],
            "text": "Hummer"
          },
          {
            "indices": [
              "76",
              "88"
            ],
            "text": "andrewjunge"
          },
          {
            "indices": [
              "90",
              "102"
            ],
            "text": "artsyfartsy"
          }
        ],
        "urls": [
          {
            "display_url": "instagram.com/p/bXkRMpDbTP/",
            "expanded_url": "http://instagram.com/p/bXkRMpDbTP/",
            "indices": [
              "104",
              "126"
            ],
            "url": "http://t.co/29YwL5TaiM"
          }
        ],
        "user_mentions": [
          {
            "id_str": "81275405",
            "indices": [
              "3",
              "12"
            ],
            "name": "RJ de Vera",
            "screen_name": "rjdevera"
          }
        ]
      },
      "favorite_count": "0",
      "favorited": false,
      "full_text": "RT @rjdevera: Recycled #art at #SFO. #Hummer done in collected styrofoam by #andrewjunge. #artsyfartsy… http://t.co/29YwL5TaiM",
      "id_str": "353184421630844929",
      "lang": "en",
      "possibly_sensitive": false,
      "retweet_count": "0",
      "retweeted": false,
      "source": "\u003ca href=\"http://www.hootsuite.com\" rel=\"nofollow\"\u003eHootsuite\u003c/a\u003e",
      "truncated": false
    },
    "twitter:user_mentions": [
      "rjdevera"
    ],
    "wof:name": "RT @rjdevera: Recycled #art at #SFO. #Hummer done in collected styrofoam by #andrewjunge. #artsyfartsy… http://t.co/29YwL5TaiM",
    "wof:placetype": "custom",
    "wof:placetype_alt": [
      "tweet"
    ]
  },
  "geometry": {"coordinates":[-122.386166,37.616356],"type":"Point"}
}
