{
  "type": "Feature",
  "properties": {
    "sfomuseum:placetype": "tweet",
    "twitter:tweet": {
      "created": 1538330705,
      "created_at": "Sun Sep 30 18:05:05 +0000 2018",
      "display_text_range": [
        "0", 
        "178"
      ],
      "entities": {
        "hashtags": [
          {
            "indices": [
              "0", 
              "10"
            ],
            "text": "OnThisDay"
          }, 
          {
            "indices": [
              "147", 
              "154"
            ],
            "text": "avgeek"
          }
        ],
        "media": [
          {
            "display_url": "pic.twitter.com/G0zMQTKBjJ",
            "expanded_url": "https://twitter.com/SFOMuseum/status/1046460941464948737/photo/1",
            "id_str": "1046460938315075585",
            "indices": [
              "155", 
              "178"
            ],
            "media_url": "http://pbs.twimg.com/media/DoXGrdOXkAEHzo-.jpg",
            "media_url_https": "https://pbs.twimg.com/media/DoXGrdOXkAEHzo-.jpg",
            "sizes": {
              "large": {
                "h": "1595",
                "resize": "fit",
                "w": "2000"
              },
              "medium": {
                "h": "957",
                "resize": "fit",
                "w": "1200"
              },
              "small": {
                "h": "542",
                "resize": "fit",
                "w": "680"
              },
              "thumb": {
                "h": "150",
                "resize": "crop",
                "w": "150"
              }
            },
            "type": "photo",
            "url": "https://t.co/G0zMQTKBjJ"
          }
        ]
      },
      "extended_entities": {
        "media": [
          {
            "display_url": "pic.twitter.com/G0zMQTKBjJ",
            "expanded_url": "https://twitter.com/SFOMuseum/status/1046460941464948737/photo/1",
            "id_str": "1046460938315075585",
            "indices": [
              "155", 
              "178"
            ],
            "media_url": "http://pbs.twimg.com/media/DoXGrdOXkAEHzo-.jpg",
            "media_url_https": "https://pbs.twimg.com/media/DoXGrdOXkAEHzo-.jpg",
            "sizes": {
              "large": {
                "h": "1595",
                "resize": "fit",
                "w": "2000"
              },
              "medium": {
                "h": "957",
                "resize": "fit",
                "w": "1200"
              },
              "small": {
                "h": "542",
                "resize": "fit",
                "w": "680"
              },
              "thumb": {
                "h": "150",
                "resize": "crop",
                "w": "150"
              }
            },
            "type": "photo",
            "url": "https://t.co/G0zMQTKBjJ"
          }
        ]
      },
      "favorite_count": "41",
      "favorited": false,
      "full_text": "#OnThisDay in 1968, the first 747 rolled out of Boeing's Everett plant. Have you ever been to the Boeing assembly building in Everett, Washington? #avgeek https://t.co/G0zMQTKBjJ",
      "id_str": "1046460941464948737",
      "lang": "en",
      "possibly_sensitive": false,
      "retweet_count": "10",
      "retweeted": false,
      "source": "\u003ca href=\"https://www.hootsuite.com\" rel=\"nofollow\"\u003eHootsuite Inc.\u003c/a\u003e",
      "truncated": false
    },
    "wof:name": "Twitter message #1046460941464948737",
    "wof:placetype": "custom"
  },
  "geometry": {"coordinates":[-122.386166,37.616356],"type":"Point"}
}
