{
  "type": "Feature",
  "properties": {
    "date:cessation_lower": "2017-06-02",
    "date:cessation_upper": "2017-06-02",
    "date:inception_lower": "2017-06-02",
    "date:inception_upper": "2017-06-02",
    "iso:country": "US",
    "sfomuseum:placetype": "tweet",
    "twitter:hashtags": [
      "TheTypewriter"
    ],
    "twitter:tweet": {
      "created": 1496420255,
      "created_at": "Fri Jun 02 16:17:35 +0000 2017",
      "display_text_range": [
        "0",
        "114"
      ],
      "edit_info": {
        "initial": {
          "editTweetIds": [
            "870675773174108160"
          ],
          "editableUntil": "2017-06-02T17:17:35.355Z",
          "editsRemaining": "5",
          "isEditEligible": true
        }
      },
      "entities": {
        "hashtags": [
          {
            "indices": [
              "64",
              "78"
            ],
            "text": "TheTypewriter"
          }
        ],
        "urls": [
          {
            "display_url": "bit.ly/Thetypewriter",
            "expanded_url": "http://bit.ly/Thetypewriter",
            "indices": [
              "91",
              "114"
            ],
            "url": "https://t.co/Nph1wFWx99"
          }
        ],
        "user_mentions": [
          {
            "id_str": "41060630",
            "indices": [
              "0",
              "11"
            ],
            "name": "Tia Carrere",
            "screen_name": "TiaCarrere"
          }
        ]
      },
      "favorite_count": "0",
      "favorited": false,
      "full_text": "@TiaCarrere Thanks so much for stopping by! We hope you enjoyed #TheTypewriter exhibition! https://t.co/Nph1wFWx99",
      "id_str": "870675773174108160",
      "in_reply_to_screen_name": "TiaCarrere",
      "in_reply_to_status_id": "870671826325651458",
      "in_reply_to_status_id_str": "870671826325651458",
      "in_reply_to_user_id": "41060630",
      "in_reply_to_user_id_str": "41060630",
      "lang": "en",
      "possibly_sensitive": false,
      "retweet_count": "0",
      "retweeted": false,
      "source": "\u003ca href=\"http://twitter.com\" rel=\"nofollow\"\u003eTwitter Web Client\u003c/a\u003e",
      "truncated": false
    },
    "twitter:user_mentions": [
      "TiaCarrere"
    ],
    "wof:name": "@TiaCarrere Thanks so much for stopping by! We hope you enjoyed #TheTypewriter exhibition! https://t.co/Nph1wFWx99",
    "wof:placetype": "custom",
    "wof:placetype_alt": [
      "tweet"
    ]
  },
  "geometry": {"coordinates":[-122.386166,37.616356],"type":"Point"}
}
