{
  "type": "Feature",
  "properties": {
    "sfomuseum:placetype": "tweet",
    "twitter:tweet": {
      "created": 1460569073,
      "created_at": "Wed Apr 13 17:37:53 +0000 2016",
      "display_text_range": [
        "0", 
        "140"
      ],
      "entities": {
        "hashtags": [
          {
            "indices": [
              "28", 
              "35"
            ],
            "text": "avgeek"
          }
        ],
        "urls": [
          {
            "display_url": "usat.ly/1oY6XSg",
            "expanded_url": "http://usat.ly/1oY6XSg",
            "indices": [
              "106", 
              "129"
            ],
            "url": "https://t.co/agcYytVktM"
          }
        ],
        "user_mentions": [
          {
            "id_str": "24016767",
            "indices": [
              "3", 
              "18"
            ],
            "name": "USA TODAY Travel",
            "screen_name": "usatodaytravel"
          }
        ]
      },
      "favorite_count": "0",
      "favorited": false,
      "full_text": "RT @usatodaytravel: April's #avgeek gallery: 30 cool aviation photos (incl. this traffic jam at Heathrow) https://t.co/agcYytVktM https://t…",
      "id_str": "720305018352439296",
      "lang": "en",
      "possibly_sensitive": false,
      "retweet_count": "0",
      "retweeted": false,
      "source": "\u003ca href=\"http://twitter.com\" rel=\"nofollow\"\u003eTwitter Web Client\u003c/a\u003e",
      "truncated": false
    },
    "wof:name": "Twitter message #720305018352439296",
    "wof:placetype": "custom"
  },
  "geometry": {"coordinates":[-122.386166,37.616356],"type":"Point"}
}
