{
  "type": "Feature",
  "properties": {
    "sfomuseum:placetype": "tweet",
    "twitter:tweet": {
      "created": 1360604481,
      "created_at": "Mon Feb 11 17:41:21 +0000 2013",
      "display_text_range": [
        "0", 
        "140"
      ],
      "entities": {
        "user_mentions": [
          {
            "id_str": "165511377",
            "indices": [
              "3", 
              "15"
            ],
            "name": "Andy Richter",
            "screen_name": "AndyRichter"
          }
        ]
      },
      "favorite_count": "0",
      "favorited": false,
      "full_text": "RT @AndyRichter: At Virgin terminal at SFO, they have a board game exhibit. This is \"Eddie Cantor's Tell It to the Judge.\" Yipes! http:/ ...",
      "id_str": "301023128627343360",
      "lang": "en",
      "retweet_count": "0",
      "retweeted": false,
      "source": "\u003ca href=\"http://twitter.com\" rel=\"nofollow\"\u003eTwitter Web Client\u003c/a\u003e",
      "truncated": false
    },
    "wof:name": "Twitter message #301023128627343360",
    "wof:placetype": "custom"
  },
  "geometry": {"coordinates":[-122.386166,37.616356],"type":"Point"}
}
