{
  "type": "Feature",
  "properties": {
    "date:cessation_lower": "2017-02-22",
    "date:cessation_upper": "2017-02-22",
    "date:inception_lower": "2017-02-22",
    "date:inception_upper": "2017-02-22",
    "iso:country": "US",
    "sfomuseum:placetype": "tweet",
    "twitter:tweet": {
      "created": 1487782990,
      "created_at": "Wed Feb 22 17:03:10 +0000 2017",
      "display_text_range": [
        "0",
        "140"
      ],
      "edit_info": {
        "initial": {
          "editTweetIds": [
            "834448457012178944"
          ],
          "editableUntil": "2017-02-22T17:33:10.111Z",
          "editsRemaining": "5",
          "isEditEligible": true
        }
      },
      "entities": {
        "hashtags": [
          {
            "indices": [
              "52",
              "63"
            ],
            "text": "JeffDivine"
          }
        ],
        "urls": [
          {
            "display_url": "bit.ly/2m5lPlg",
            "expanded_url": "http://bit.ly/2m5lPlg",
            "indices": [
              "95",
              "118"
            ],
            "url": "https://t.co/hq7FhDmwPs"
          }
        ],
        "user_mentions": [
          {
            "id_str": "20607927",
            "indices": [
              "3",
              "14"
            ],
            "name": "Chris McGinnis",
            "screen_name": "cjmcginnis"
          },
          {
            "id_str": "260907612",
            "indices": [
              "84",
              "91"
            ],
            "name": "United Airlines",
            "screen_name": "united"
          },
          {
            "id_str": "116329337",
            "indices": [
              "119",
              "129"
            ],
            "name": "SFO Museum",
            "screen_name": "SFOMuseum"
          }
        ]
      },
      "favorite_count": "0",
      "favorited": false,
      "full_text": "RT @cjmcginnis: Dude! Don't miss SFO's newest exhib #JeffDivine Surf Photography in @United T3 https://t.co/hq7FhDmwPs @SFOMuseum https://t…",
      "id_str": "834448457012178944",
      "lang": "en",
      "possibly_sensitive": false,
      "retweet_count": "0",
      "retweeted": false,
      "source": "\u003ca href=\"http://twitter.com\" rel=\"nofollow\"\u003eTwitter Web Client\u003c/a\u003e",
      "truncated": false
    },
    "wof:name": "RT @cjmcginnis: Dude! Don't miss SFO's newest exhib #JeffDivine Surf Photography in @United T3 https://t.co/hq7FhDmwPs @SFOMuseum https://t…",
    "wof:placetype": "custom"
  },
  "geometry": {"coordinates":[-122.386166,37.616356],"type":"Point"}
}
