{
  "type": "Feature",
  "properties": {
    "sfomuseum:placetype": "tweet",
    "twitter:tweet": {
      "created": 1520796610,
      "created_at": "Sun Mar 11 19:30:10 +0000 2018",
      "display_text_range": [
        "0", 
        "248"
      ],
      "entities": {
        "hashtags": [
          {
            "indices": [
              "41", 
              "50"
            ],
            "text": "Concorde"
          }, 
          {
            "indices": [
              "205", 
              "224"
            ],
            "text": "AviationEvolutions"
          }
        ],
        "media": [
          {
            "display_url": "pic.twitter.com/r6KIydoUkv",
            "expanded_url": "https://twitter.com/SFOMuseum/status/972917615957020673/photo/1",
            "id_str": "972917613150928896",
            "indices": [
              "225", 
              "248"
            ],
            "media_url": "http://pbs.twimg.com/media/DYB_aheVAAAewBX.jpg",
            "media_url_https": "https://pbs.twimg.com/media/DYB_aheVAAAewBX.jpg",
            "sizes": {
              "large": {
                "h": "1591",
                "resize": "fit",
                "w": "2000"
              },
              "medium": {
                "h": "955",
                "resize": "fit",
                "w": "1200"
              },
              "small": {
                "h": "541",
                "resize": "fit",
                "w": "680"
              },
              "thumb": {
                "h": "150",
                "resize": "crop",
                "w": "150"
              }
            },
            "type": "photo",
            "url": "https://t.co/r6KIydoUkv"
          }
        ]
      },
      "extended_entities": {
        "media": [
          {
            "display_url": "pic.twitter.com/r6KIydoUkv",
            "expanded_url": "https://twitter.com/SFOMuseum/status/972917615957020673/photo/1",
            "id_str": "972917613150928896",
            "indices": [
              "225", 
              "248"
            ],
            "media_url": "http://pbs.twimg.com/media/DYB_aheVAAAewBX.jpg",
            "media_url_https": "https://pbs.twimg.com/media/DYB_aheVAAAewBX.jpg",
            "sizes": {
              "large": {
                "h": "1591",
                "resize": "fit",
                "w": "2000"
              },
              "medium": {
                "h": "955",
                "resize": "fit",
                "w": "1200"
              },
              "small": {
                "h": "541",
                "resize": "fit",
                "w": "680"
              },
              "thumb": {
                "h": "150",
                "resize": "crop",
                "w": "150"
              }
            },
            "type": "photo",
            "url": "https://t.co/r6KIydoUkv"
          }
        ]
      },
      "favorite_count": "59",
      "favorited": false,
      "full_text": "A supersonic transatlantic flight on the #Concorde between Paris and Washington D.C. lasted on average just three and one-half hours at 1,350 miles per hour, faster than the speed of the Earth's rotation. #AviationEvolutions https://t.co/r6KIydoUkv",
      "id_str": "972917615957020673",
      "lang": "en",
      "possibly_sensitive": false,
      "retweet_count": "15",
      "retweeted": false,
      "source": "\u003ca href=\"http://www.hootsuite.com\" rel=\"nofollow\"\u003eHootsuite\u003c/a\u003e",
      "truncated": false
    },
    "wof:name": "Twitter message #972917615957020673",
    "wof:placetype": "custom"
  },
  "geometry": {"coordinates":[-122.386166,37.616356],"type":"Point"}
}
