{
  "type": "Feature",
  "properties": {
    "date:cessation_lower": "2023-04-13",
    "date:cessation_upper": "2023-04-13",
    "date:inception_lower": "2023-04-13",
    "date:inception_upper": "2023-04-13",
    "sfomuseum:placetype": "tweet",
    "twitter:hashtags": [
      "ChloëFitzmaurice",
      "EarthMonth",
      "VideoArts",
      "VideoArtsSFO",
      "ForTheBees"
    ],
    "twitter:tweet": {
      "created": 1681408194,
      "created_at": "Thu Apr 13 17:49:54 +0000 2023",
      "display_text_range": [
        "0",
        "279"
      ],
      "edit_info": {
        "initial": {
          "editTweetIds": [
            "1646571428035330048"
          ],
          "editableUntil": "2023-04-13T18:19:54.000Z",
          "editsRemaining": "5",
          "isEditEligible": false
        }
      },
      "entities": {
        "hashtags": [
          {
            "indices": [
              "213",
              "223"
            ],
            "text": "VideoArts"
          },
          {
            "indices": [
              "224",
              "237"
            ],
            "text": "VideoArtsSFO"
          },
          {
            "indices": [
              "238",
              "249"
            ],
            "text": "ForTheBees"
          },
          {
            "indices": [
              "250",
              "267"
            ],
            "text": "ChloëFitzmaurice"
          },
          {
            "indices": [
              "268",
              "279"
            ],
            "text": "EarthMonth"
          }
        ],
        "urls": [
          {
            "display_url": "bit.ly/VideoArts",
            "expanded_url": "http://bit.ly/VideoArts",
            "indices": [
              "188",
              "211"
            ],
            "url": "https://t.co/s0oA7gcWli"
          }
        ]
      },
      "favorite_count": "2",
      "favorited": false,
      "full_text": "See “For the Bees” by Chloë Fitzmaurice in the Video Arts Gallery, located pre-security in the International Terminal, open daily from 7am to 10pm. Learn more about this month’s films at: https://t.co/s0oA7gcWli\n\n#VideoArts #VideoArtsSFO #ForTheBees #ChloëFitzmaurice #EarthMonth",
      "id_str": "1646571428035330048",
      "in_reply_to_screen_name": "SFOMuseum",
      "in_reply_to_status_id": "1646571424663080960",
      "in_reply_to_status_id_str": "1646571424663080960",
      "in_reply_to_user_id": "116329337",
      "in_reply_to_user_id_str": "116329337",
      "lang": "en",
      "possibly_sensitive": false,
      "retweet_count": "1",
      "retweeted": false,
      "source": "\u003ca href=\"https://mobile.twitter.com\" rel=\"nofollow\"\u003eTwitter Web App\u003c/a\u003e",
      "truncated": false
    },
    "wof:name": "See “For the Bees” by Chloë Fitzmaurice in the Video Arts Gallery, located pre-security in the International Terminal, open daily from 7am to 10pm. Learn more about this month’s films at: https://t.co/s0oA7gcWli\n\n#VideoArts #VideoArtsSFO #ForTheBees #ChloëFitzmaurice #EarthMonth",
    "wof:placetype": "custom"
  },
  "geometry": {"coordinates":[-122.386166,37.616356],"type":"Point"}
}
