{
  "type": "Feature",
  "properties": {
    "sfomuseum:placetype": "tweet",
    "twitter:tweet": {
      "created": 1358533258,
      "created_at": "Fri Jan 18 18:20:58 +0000 2013",
      "display_text_range": [
        "0", 
        "138"
      ],
      "entities": {
        "urls": [
          {
            "display_url": "4sq.com/YddtWU",
            "expanded_url": "http://4sq.com/YddtWU",
            "indices": [
              "118", 
              "138"
            ],
            "url": "http://t.co/j49yp8FY"
          }
        ],
        "user_mentions": [
          {
            "id_str": "20706514",
            "indices": [
              "28", 
              "40"
            ],
            "name": "Jon Paul Buchmeyer",
            "screen_name": "jpbuchmeyer"
          }
        ]
      },
      "favorite_count": "0",
      "favorited": false,
      "full_text": "We're glad you didn't :) MT @jpbuchmeyer: Vintage nancy drew board game on display at sfo. Almost had to break glass! http://t.co/j49yp8FY",
      "id_str": "292335792498565122",
      "lang": "en",
      "possibly_sensitive": false,
      "retweet_count": "0",
      "retweeted": false,
      "source": "\u003ca href=\"https://about.twitter.com/products/tweetdeck\" rel=\"nofollow\"\u003eTweetDeck\u003c/a\u003e",
      "truncated": false
    },
    "wof:name": "Twitter message #292335792498565122",
    "wof:placetype": "custom"
  },
  "geometry": {"coordinates":[-122.386166,37.616356],"type":"Point"}
}
