{
  "type": "Feature",
  "properties": {
    "sfomuseum:placetype": "tweet",
    "twitter:tweet": {
      "created": 1351707654,
      "created_at": "Wed Oct 31 18:20:54 +0000 2012",
      "display_text_range": [
        "0", 
        "38"
      ],
      "entities": {
        "hashtags": [
          {
            "indices": [
              "6", 
              "16"
            ],
            "text": "Halloween"
          }
        ],
        "urls": [
          {
            "display_url": "instagr.am/p/RdN5gTRk9V/",
            "expanded_url": "http://instagr.am/p/RdN5gTRk9V/",
            "indices": [
              "18", 
              "38"
            ],
            "url": "http://t.co/B9rltqs6"
          }
        ]
      },
      "favorite_count": "0",
      "favorited": false,
      "full_text": "Happy #Halloween! http://t.co/B9rltqs6",
      "id_str": "263707134468976640",
      "lang": "en",
      "possibly_sensitive": false,
      "retweet_count": "0",
      "retweeted": false,
      "source": "\u003ca href=\"http://instagram.com\" rel=\"nofollow\"\u003eInstagram\u003c/a\u003e",
      "truncated": false
    },
    "wof:name": "Twitter message #263707134468976640",
    "wof:placetype": "custom"
  },
  "geometry": {"coordinates":[-122.386166,37.616356],"type":"Point"}
}
