{
  "type": "Feature",
  "properties": {
    "date:cessation_lower": "2012-12-13",
    "date:cessation_upper": "2012-12-13",
    "date:inception_lower": "2012-12-13",
    "date:inception_upper": "2012-12-13",
    "iso:country": "US",
    "sfomuseum:placetype": "tweet",
    "twitter:tweet": {
      "created": 1355426736,
      "created_at": "Thu Dec 13 19:25:36 +0000 2012",
      "display_text_range": [
        "0",
        "138"
      ],
      "edit_info": {
        "initial": {
          "editTweetIds": [
            "279306094889795584"
          ],
          "editableUntil": "2012-12-13T20:25:36.935Z",
          "editsRemaining": "5",
          "isEditEligible": true
        }
      },
      "entities": {
        "urls": [
          {
            "display_url": "pic.twitter.com/wcq2LJNR",
            "expanded_url": "https://twitter.com/sharonw/status/279103415987077120/photo/1",
            "indices": [
              "118",
              "138"
            ],
            "url": "http://t.co/wcq2LJNR"
          }
        ],
        "user_mentions": [
          {
            "id_str": "512562844",
            "indices": [
              "29",
              "37"
            ],
            "name": "Sharon Wong",
            "screen_name": "sharonw"
          },
          {
            "id_str": "681813",
            "indices": [
              "92",
              "102"
            ],
            "name": "Jane IMAGINABLE McGonigal ❤️",
            "screen_name": "avantgame"
          },
          {
            "id_str": "1754957417731792897",
            "indices": [
              "103",
              "117"
            ],
            "name": "Jennifer Keener",
            "screen_name": "JenniferMarie"
          }
        ]
      },
      "favorite_count": "2",
      "favorited": false,
      "full_text": "We love that you love it! MT @sharonw: I love that SFO has an exhibit about game history :) @avantgame @jennifermarie http://t.co/wcq2LJNR",
      "id_str": "279306094889795584",
      "lang": "en",
      "possibly_sensitive": false,
      "retweet_count": "3",
      "retweeted": false,
      "source": "\u003ca href=\"https://about.twitter.com/products/tweetdeck\" rel=\"nofollow\"\u003eTweetDeck\u003c/a\u003e",
      "truncated": false
    },
    "twitter:user_mentions": [
      "sharonw",
      "avantgame",
      "jennifermarie"
    ],
    "wof:name": "We love that you love it! MT @sharonw: I love that SFO has an exhibit about game history :) @avantgame @jennifermarie http://t.co/wcq2LJNR",
    "wof:placetype": "custom"
  },
  "geometry": {"coordinates":[-122.386166,37.616356],"type":"Point"}
}
