{
  "type": "Feature",
  "properties": {
    "date:cessation_lower": "2014-03-31",
    "date:cessation_upper": "2014-03-31",
    "date:inception_lower": "2014-03-31",
    "date:inception_upper": "2014-03-31",
    "iso:country": "US",
    "sfomuseum:placetype": "tweet",
    "twitter:hashtags": [
      "SFO"
    ],
    "twitter:tweet": {
      "created": 1396283588,
      "created_at": "Mon Mar 31 16:33:08 +0000 2014",
      "display_text_range": [
        "0",
        "140"
      ],
      "edit_info": {
        "initial": {
          "editTweetIds": [
            "450672151432273920"
          ],
          "editableUntil": "2014-03-31T17:33:08.642Z",
          "editsRemaining": "5",
          "isEditEligible": true
        }
      },
      "entities": {
        "hashtags": [
          {
            "indices": [
              "55",
              "59"
            ],
            "text": "SFO"
          }
        ],
        "user_mentions": [
          {
            "id_str": "112811342",
            "indices": [
              "3",
              "15"
            ],
            "name": "Christine Aiko Beck",
            "screen_name": "AikoDesigns"
          }
        ]
      },
      "favorite_count": "0",
      "favorited": false,
      "full_text": "RT @AikoDesigns: Japanese toys | from kokeshi to kaiju #SFO has great exhibits. Love this one, it's very natsukashi @… http://t.co/4IcQtljj…",
      "id_str": "450672151432273920",
      "lang": "en",
      "retweet_count": "0",
      "retweeted": false,
      "source": "\u003ca href=\"http://www.hootsuite.com\" rel=\"nofollow\"\u003eHootsuite\u003c/a\u003e",
      "truncated": false
    },
    "twitter:user_mentions": [
      "AikoDesigns"
    ],
    "wof:name": "RT @AikoDesigns: Japanese toys | from kokeshi to kaiju #SFO has great exhibits. Love this one, it's very natsukashi @… http://t.co/4IcQtljj…",
    "wof:placetype": "custom"
  },
  "geometry": {"coordinates":[-122.386166,37.616356],"type":"Point"}
}
