{
  "type": "Feature",
  "properties": {
    "sfomuseum:placetype": "tweet",
    "twitter:tweet": {
      "created": 1466565905,
      "created_at": "Wed Jun 22 03:25:05 +0000 2016",
      "display_text_range": [
        "0", 
        "130"
      ],
      "entities": {
        "hashtags": [
          {
            "indices": [
              "92", 
              "106"
            ],
            "text": "TravelTuesday"
          }
        ],
        "media": [
          {
            "display_url": "pic.twitter.com/9EqtDAhaFX",
            "expanded_url": "https://twitter.com/SFOMuseum/status/745457554592006144/photo/1",
            "id_str": "745457550460596229",
            "indices": [
              "107", 
              "130"
            ],
            "media_url": "http://pbs.twimg.com/media/ClhlsUpWMAUQlb6.jpg",
            "media_url_https": "https://pbs.twimg.com/media/ClhlsUpWMAUQlb6.jpg",
            "sizes": {
              "large": {
                "h": "1021",
                "resize": "fit",
                "w": "2000"
              },
              "medium": {
                "h": "613",
                "resize": "fit",
                "w": "1200"
              },
              "small": {
                "h": "347",
                "resize": "fit",
                "w": "680"
              },
              "thumb": {
                "h": "150",
                "resize": "crop",
                "w": "150"
              }
            },
            "type": "photo",
            "url": "https://t.co/9EqtDAhaFX"
          }
        ]
      },
      "extended_entities": {
        "media": [
          {
            "display_url": "pic.twitter.com/9EqtDAhaFX",
            "expanded_url": "https://twitter.com/SFOMuseum/status/745457554592006144/photo/1",
            "id_str": "745457550460596229",
            "indices": [
              "107", 
              "130"
            ],
            "media_url": "http://pbs.twimg.com/media/ClhlsUpWMAUQlb6.jpg",
            "media_url_https": "https://pbs.twimg.com/media/ClhlsUpWMAUQlb6.jpg",
            "sizes": {
              "large": {
                "h": "1021",
                "resize": "fit",
                "w": "2000"
              },
              "medium": {
                "h": "613",
                "resize": "fit",
                "w": "1200"
              },
              "small": {
                "h": "347",
                "resize": "fit",
                "w": "680"
              },
              "thumb": {
                "h": "150",
                "resize": "crop",
                "w": "150"
              }
            },
            "type": "photo",
            "url": "https://t.co/9EqtDAhaFX"
          }
        ]
      },
      "favorite_count": "0",
      "favorited": false,
      "full_text": "Last week, the inaugural Nadi to SF flight landed at SFO. Photo: Fiji Airways ticket, 1969. #TravelTuesday https://t.co/9EqtDAhaFX",
      "id_str": "745457554592006144",
      "lang": "en",
      "possibly_sensitive": false,
      "retweet_count": "0",
      "retweeted": false,
      "source": "\u003ca href=\"http://www.hootsuite.com\" rel=\"nofollow\"\u003eHootsuite\u003c/a\u003e",
      "truncated": false
    },
    "wof:name": "Twitter message #745457554592006144",
    "wof:placetype": "custom"
  },
  "geometry": {"coordinates":[-122.386166,37.616356],"type":"Point"}
}
