{
  "type": "Feature",
  "properties": {
    "date:cessation_lower": "2017-01-19",
    "date:cessation_upper": "2017-01-19",
    "date:inception_lower": "2017-01-19",
    "date:inception_upper": "2017-01-19",
    "iso:country": "US",
    "sfomuseum:placetype": "tweet",
    "twitter:tweet": {
      "created": 1484864970,
      "created_at": "Thu Jan 19 22:29:30 +0000 2017",
      "display_text_range": [
        "0",
        "134"
      ],
      "edit_info": {
        "initial": {
          "editTweetIds": [
            "822209396369276928"
          ],
          "editableUntil": "2017-01-19T22:59:30.663Z",
          "editsRemaining": "5",
          "isEditEligible": true
        }
      },
      "entities": {
        "urls": [
          {
            "display_url": "bit.ly/OuijaAndBeyond",
            "expanded_url": "http://bit.ly/OuijaAndBeyond",
            "indices": [
              "111",
              "134"
            ],
            "url": "https://t.co/8nA11vPhZt"
          }
        ],
        "user_mentions": [
          {
            "id_str": "459023724",
            "indices": [
              "0",
              "10"
            ],
            "name": "Art by Rupy",
            "screen_name": "ArtByRupy"
          }
        ]
      },
      "favorite_count": "1",
      "favorited": false,
      "full_text": "@ArtByRupy Thanks so much for stopping by! We hope you enjoyed our exhibition! Did you have a favorite object? https://t.co/8nA11vPhZt",
      "id_str": "822209396369276928",
      "in_reply_to_screen_name": "ArtByRupy",
      "in_reply_to_status_id": "822207114944737280",
      "in_reply_to_status_id_str": "822207114944737280",
      "in_reply_to_user_id": "459023724",
      "in_reply_to_user_id_str": "459023724",
      "lang": "en",
      "possibly_sensitive": false,
      "retweet_count": "0",
      "retweeted": false,
      "source": "\u003ca href=\"http://twitter.com\" rel=\"nofollow\"\u003eTwitter Web Client\u003c/a\u003e",
      "truncated": false
    },
    "wof:name": "@ArtByRupy Thanks so much for stopping by! We hope you enjoyed our exhibition! Did you have a favorite object? https://t.co/8nA11vPhZt",
    "wof:placetype": "custom"
  },
  "geometry": {"coordinates":[-122.386166,37.616356],"type":"Point"}
}
