{
  "type": "Feature",
  "properties": {
    "sfomuseum:placetype": "tweet",
    "twitter:tweet": {
      "created": 1472492802,
      "created_at": "Mon Aug 29 17:46:42 +0000 2016",
      "display_text_range": [
        "0", 
        "140"
      ],
      "entities": {
        "hashtags": [
          {
            "indices": [
              "106", 
              "122"
            ],
            "text": "aviaitonhistory"
          }
        ],
        "user_mentions": [
          {
            "id_str": "181608016",
            "indices": [
              "3", 
              "15"
            ],
            "name": "airlineguys",
            "screen_name": "airlineguys"
          }
        ]
      },
      "favorite_count": "0",
      "favorited": false,
      "full_text": "RT @airlineguys: On this date: August 29, 1970 McDonnell Douglas DC-10 takes to the skies for first time. #aviaitonhistory https://t.co/26U…",
      "id_str": "770316763783372800",
      "lang": "en",
      "retweet_count": "0",
      "retweeted": false,
      "source": "\u003ca href=\"http://www.hootsuite.com\" rel=\"nofollow\"\u003eHootsuite\u003c/a\u003e",
      "truncated": false
    },
    "wof:name": "Twitter message #770316763783372800",
    "wof:placetype": "custom"
  },
  "geometry": {"coordinates":[-122.386166,37.616356],"type":"Point"}
}
