{
  "type": "Feature",
  "properties": {
    "sfomuseum:placetype": "tweet",
    "twitter:tweet": {
      "created": 1320101580,
      "created_at": "Mon Oct 31 22:53:00 +0000 2011",
      "display_text_range": [
        "0", 
        "79"
      ],
      "entities": {
        "hashtags": [
          {
            "indices": [
              "53", 
              "57"
            ],
            "text": "SFO"
          }
        ],
        "urls": [
          {
            "display_url": "twitpic.com/78a7xh",
            "expanded_url": "http://twitpic.com/78a7xh",
            "indices": [
              "59", 
              "79"
            ],
            "url": "http://t.co/Gp9BxoZo"
          }
        ],
        "user_mentions": [
          {
            "id_str": "24452514",
            "indices": [
              "17", 
              "23"
            ],
            "name": "Yuh Wen Ling",
            "screen_name": "YDubL"
          }
        ]
      },
      "favorite_count": "0",
      "favorited": false,
      "full_text": "Sweet Thanks! RT @YDubL: Super dig the TV exhibit at #SFO. http://t.co/Gp9BxoZo",
      "id_str": "131141649848991744",
      "lang": "en",
      "possibly_sensitive": false,
      "retweet_count": "1",
      "retweeted": false,
      "source": "\u003ca href=\"https://about.twitter.com/products/tweetdeck\" rel=\"nofollow\"\u003eTweetDeck\u003c/a\u003e",
      "truncated": false
    },
    "wof:name": "Twitter message #131141649848991744",
    "wof:placetype": "custom"
  },
  "geometry": {"coordinates":[-122.386166,37.616356],"type":"Point"}
}
