{
  "type": "Feature",
  "properties": {
    "date:cessation_lower": "2011-10-31",
    "date:cessation_upper": "2011-10-31",
    "date:inception_lower": "2011-10-31",
    "date:inception_upper": "2011-10-31",
    "iso:country": "US",
    "sfomuseum:placetype": "tweet",
    "twitter:hashtags": [
      "SFO"
    ],
    "twitter:tweet": {
      "created": 1320101580,
      "created_at": "Mon Oct 31 22:53:00 +0000 2011",
      "display_text_range": [
        "0",
        "79"
      ],
      "edit_info": {
        "initial": {
          "editTweetIds": [
            "131141649848991744"
          ],
          "editableUntil": "2011-10-31T23:53:00.475Z",
          "editsRemaining": "5",
          "isEditEligible": true
        }
      },
      "entities": {
        "hashtags": [
          {
            "indices": [
              "53",
              "57"
            ],
            "text": "SFO"
          }
        ],
        "urls": [
          {
            "display_url": "twitpic.com/78a7xh",
            "expanded_url": "http://twitpic.com/78a7xh",
            "indices": [
              "59",
              "79"
            ],
            "url": "http://t.co/Gp9BxoZo"
          }
        ],
        "user_mentions": [
          {
            "id_str": "1753535230995206144",
            "indices": [
              "17",
              "23"
            ],
            "name": "Yun Dublin",
            "screen_name": "YDubl"
          }
        ]
      },
      "favorite_count": "0",
      "favorited": false,
      "full_text": "Sweet Thanks! RT @YDubL: Super dig the TV exhibit at #SFO. http://t.co/Gp9BxoZo",
      "id_str": "131141649848991744",
      "lang": "en",
      "possibly_sensitive": false,
      "retweet_count": "1",
      "retweeted": false,
      "source": "\u003ca href=\"https://about.twitter.com/products/tweetdeck\" rel=\"nofollow\"\u003eTweetDeck\u003c/a\u003e",
      "truncated": false
    },
    "twitter:user_mentions": [
      "YDubl"
    ],
    "wof:name": "Sweet Thanks! RT @YDubL: Super dig the TV exhibit at #SFO. http://t.co/Gp9BxoZo",
    "wof:placetype": "custom",
    "wof:placetype_alt": [
      "tweet"
    ]
  },
  "geometry": {"coordinates":[-122.386166,37.616356],"type":"Point"}
}
