{
  "type": "Feature",
  "properties": {
    "sfomuseum:placetype": "tweet",
    "twitter:tweet": {
      "created": 1382399660,
      "created_at": "Mon Oct 21 23:54:20 +0000 2013",
      "display_text_range": [
        "0", 
        "100"
      ],
      "entities": {
        "hashtags": [
          {
            "indices": [
              "20", 
              "31"
            ],
            "text": "soinspired"
          }, 
          {
            "indices": [
              "59", 
              "63"
            ],
            "text": "SFO"
          }, 
          {
            "indices": [
              "73", 
              "77"
            ],
            "text": "art"
          }
        ],
        "urls": [
          {
            "display_url": "instagram.com/p/fvyQlYyXHA/",
            "expanded_url": "http://instagram.com/p/fvyQlYyXHA/",
            "indices": [
              "78", 
              "100"
            ],
            "url": "http://t.co/6iYJpwfm3e"
          }
        ],
        "user_mentions": [
          {
            "id_str": "546153359",
            "indices": [
              "3", 
              "18"
            ],
            "name": "Stephanie O.",
            "screen_name": "StephanieOdsgn"
          }
        ]
      },
      "favorite_count": "0",
      "favorited": false,
      "full_text": "RT @StephanieOdsgn: #soinspired rope wrapped whale tail at #SFO airport  #art http://t.co/6iYJpwfm3e",
      "id_str": "392438733964050432",
      "lang": "en",
      "possibly_sensitive": false,
      "retweet_count": "0",
      "retweeted": false,
      "source": "\u003ca href=\"http://www.hootsuite.com\" rel=\"nofollow\"\u003eHootsuite\u003c/a\u003e",
      "truncated": false
    },
    "wof:name": "Twitter message #392438733964050432",
    "wof:placetype": "custom"
  },
  "geometry": {"coordinates":[-122.386166,37.616356],"type":"Point"}
}
