{
  "type": "Feature",
  "properties": {
    "date:cessation_lower": "2012-10-05",
    "date:cessation_upper": "2012-10-05",
    "date:inception_lower": "2012-10-05",
    "date:inception_upper": "2012-10-05",
    "iso:country": "US",
    "sfomuseum:placetype": "tweet",
    "twitter:tweet": {
      "created": 1349476441,
      "created_at": "Fri Oct 05 22:34:01 +0000 2012",
      "display_text_range": [
        "0",
        "119"
      ],
      "edit_info": {
        "initial": {
          "editTweetIds": [
            "254348744957501440"
          ],
          "editableUntil": "2012-10-05T23:04:01.026Z",
          "editsRemaining": "5",
          "isEditEligible": true
        }
      },
      "entities": {
        "user_mentions": [
          {
            "id_str": "408686208",
            "indices": [
              "0",
              "13"
            ],
            "name": "Stefan Edward Jones 🇺🇦",
            "screen_name": "StefanEJones"
          }
        ]
      },
      "favorite_count": "0",
      "favorited": false,
      "full_text": "@StefanEJones Ooooh, we have upcoming exhibits on board games (Oct 2012) \u0026amp; Japanese toys (Oct 2013) you might like!",
      "id_str": "254348744957501440",
      "in_reply_to_screen_name": "StefanEJones",
      "in_reply_to_status_id": "254346656684843008",
      "in_reply_to_status_id_str": "254346656684843008",
      "in_reply_to_user_id": "408686208",
      "in_reply_to_user_id_str": "408686208",
      "lang": "en",
      "retweet_count": "1",
      "retweeted": false,
      "source": "\u003ca href=\"https://about.twitter.com/products/tweetdeck\" rel=\"nofollow\"\u003eTweetDeck\u003c/a\u003e",
      "truncated": false
    },
    "wof:name": "@StefanEJones Ooooh, we have upcoming exhibits on board games (Oct 2012) \u0026amp; Japanese toys (Oct 2013) you might like!",
    "wof:placetype": "custom"
  },
  "geometry": {"coordinates":[-122.386166,37.616356],"type":"Point"}
}
