{
  "type": "Feature",
  "properties": {
    "sfomuseum:placetype": "tweet",
    "twitter:tweet": {
      "created": 1366240171,
      "created_at": "Wed Apr 17 23:09:31 +0000 2013",
      "display_text_range": [
        "0", 
        "118"
      ],
      "entities": {
        "urls": [
          {
            "display_url": "instagram.com/p/YOT2mMRk3o/",
            "expanded_url": "http://instagram.com/p/YOT2mMRk3o/",
            "indices": [
              "96", 
              "118"
            ],
            "url": "http://t.co/zVZEKUdBif"
          }
        ]
      },
      "favorite_count": "0",
      "favorited": false,
      "full_text": "Made from discarded metal siding, Gaza Bowen's 'Cryptotomes' was a continuation of her earlier… http://t.co/zVZEKUdBif",
      "id_str": "324660927259635712",
      "lang": "en",
      "possibly_sensitive": false,
      "retweet_count": "0",
      "retweeted": false,
      "source": "\u003ca href=\"http://instagram.com\" rel=\"nofollow\"\u003eInstagram\u003c/a\u003e",
      "truncated": false
    },
    "wof:name": "Twitter message #324660927259635712",
    "wof:placetype": "custom"
  },
  "geometry": {"coordinates":[-122.386166,37.616356],"type":"Point"}
}
