{
  "type": "Feature",
  "properties": {
    "sfomuseum:placetype": "tweet",
    "twitter:tweet": {
      "created": 1317312911,
      "created_at": "Thu Sep 29 16:15:11 +0000 2011",
      "display_text_range": [
        "0", 
        "140"
      ],
      "entities": {
        "hashtags": [
          {
            "indices": [
              "126", 
              "140"
            ],
            "text": "TheAntennaAge"
          }
        ]
      },
      "favorite_count": "0",
      "favorited": false,
      "full_text": "Reality TV is older than it seems: Candid Camera began on the radio (as Candid Microphone) in 1957 \u0026 moved to TV a year later #TheAntennaAge",
      "id_str": "119445125322645504",
      "lang": "en",
      "retweet_count": "1",
      "retweeted": false,
      "source": "\u003ca href=\"http://www.hootsuite.com\" rel=\"nofollow\"\u003eHootsuite\u003c/a\u003e",
      "truncated": false
    },
    "wof:name": "Twitter message #119445125322645504",
    "wof:placetype": "custom"
  },
  "geometry": {"coordinates":[-122.386166,37.616356],"type":"Point"}
}
