{
  "type": "Feature",
  "properties": {
    "sfomuseum:placetype": "tweet",
    "twitter:tweet": {
      "created": 1344544898,
      "created_at": "Thu Aug 09 20:41:38 +0000 2012",
      "display_text_range": [
        "0", 
        "108"
      ],
      "entities": {
        "urls": [
          {
            "display_url": "instagr.am/p/OFhpu5yJiJ/",
            "expanded_url": "http://instagr.am/p/OFhpu5yJiJ/",
            "indices": [
              "88", 
              "108"
            ],
            "url": "http://t.co/Zp2ihToi"
          }
        ],
        "user_mentions": [
          {
            "id_str": "19748712",
            "indices": [
              "3", 
              "16"
            ],
            "name": "Isaac",
            "screen_name": "OlDirtyBiker"
          }, 
          {
            "id_str": "58563307",
            "indices": [
              "29", 
              "41"
            ],
            "name": "Salsa Cycles",
            "screen_name": "salsacycles"
          }
        ]
      },
      "favorite_count": "0",
      "favorited": false,
      "full_text": "RT @OlDirtyBiker: Old School @salsacycles on display at SFO's Repack to Rwanda exhibit: http://t.co/Zp2ihToi",
      "id_str": "233664357291159552",
      "lang": "en",
      "possibly_sensitive": false,
      "retweet_count": "0",
      "retweeted": false,
      "source": "\u003ca href=\"http://www.hootsuite.com\" rel=\"nofollow\"\u003eHootsuite\u003c/a\u003e",
      "truncated": false
    },
    "wof:name": "Twitter message #233664357291159552",
    "wof:placetype": "custom"
  },
  "geometry": {"coordinates":[-122.386166,37.616356],"type":"Point"}
}
