{
  "type": "Feature",
  "properties": {
    "date:cessation_lower":"2011-10-03",
    "date:cessation_upper":"2011-10-03",
    "date:inception_lower":"2011-10-03",
    "date:inception_upper":"2011-10-03",
    "iso:country":"US",
    "sfomuseum:placetype":"tweet",
    "twitter:tweet":{
        "created":1317666302,
        "created_at":"Mon Oct 03 18:25:02 +0000 2011",
        "display_text_range":[
            "0",
            "120"
        ],
        "entities":{
            "hashtags":[
                {
                    "indices":[
                        "85",
                        "99"
                    ],
                    "text":"TheAntennaAge"
                }
            ],
            "urls":[
                {
                    "display_url":"ow.ly/i/isJG",
                    "expanded_url":"http://ow.ly/i/isJG",
                    "indices":[
                        "100",
                        "120"
                    ],
                    "url":"http://t.co/j9asSOHA"
                }
            ]
        },
        "favorite_count":"0",
        "favorited":false,
        "full_text":"The Dick Van Dyke Show, one of tv's classic sit-coms, premiered on this day in 1961! #TheAntennaAge http://t.co/j9asSOHA",
        "id_str":"120927351713435648",
        "lang":"en",
        "possibly_sensitive":false,
        "retweet_count":"0",
        "retweeted":false,
        "source":"<a href=\"http://www.hootsuite.com\" rel=\"nofollow\">Hootsuite</a>",
        "truncated":false
    },
    "wof:name":"The Dick Van Dyke Show, one of tv's classic sit-coms, premiered on this day in 1961! #TheAntennaAge http://t.co/j9asSOHA",
    "wof:placetype":"custom"
},
  "geometry": {"coordinates":[-122.386166,37.616356],"type":"Point"}
}