{
  "type": "Feature",
  "properties": {
    "date:cessation_lower":"2011-12-16",
    "date:cessation_upper":"2011-12-16",
    "date:inception_lower":"2011-12-16",
    "date:inception_upper":"2011-12-16",
    "iso:country":"US",
    "sfomuseum:placetype":"tweet",
    "twitter:tweet":{
        "created":1324075980,
        "created_at":"Fri Dec 16 22:53:00 +0000 2011",
        "display_text_range":[
            "0",
            "139"
        ],
        "entities":{
            "urls":[
                {
                    "display_url":"4sq.com/vHTmRb",
                    "expanded_url":"http://4sq.com/vHTmRb",
                    "indices":[
                        "119",
                        "139"
                    ],
                    "url":"http://t.co/a9MExvFL"
                }
            ],
            "user_mentions":[
                {
                    "id_str":"20491034",
                    "indices":[
                        "35",
                        "45"
                    ],
                    "name":"Ari Levine",
                    "screen_name":"arilevine"
                }
            ]
        },
        "favorite_count":"0",
        "favorited":false,
        "full_text":"Thanks! Do you have a favorite? RT @arilevine: very cool vinyl cover art display (@ SFO Terminal 2 w/ 5 others) [pic]: http://t.co/a9MExvFL",
        "id_str":"147811493071683584",
        "lang":"en",
        "possibly_sensitive":false,
        "retweet_count":"0",
        "retweeted":false,
        "source":"<a href=\"https://about.twitter.com/products/tweetdeck\" rel=\"nofollow\">TweetDeck</a>",
        "truncated":false
    },
    "wof:name":"Thanks! Do you have a favorite? RT @arilevine: very cool vinyl cover art display (@ SFO Terminal 2 w/ 5 others) [pic]: http://t.co/a9MExvFL",
    "wof:placetype":"custom"
},
  "geometry": {"coordinates":[-122.386166,37.616356],"type":"Point"}
}