{
  "type": "Feature",
  "properties": {
    "date:cessation_lower": "2023-07-26",
    "date:cessation_upper": "2023-07-26",
    "date:inception_lower": "2023-07-26",
    "date:inception_upper": "2023-07-26",
    "sfomuseum:placetype": "tweet",
    "twitter:tweet": {
      "created": 1690396176,
      "created_at": "Wed Jul 26 18:29:36 +0000 2023",
      "display_text_range": [
        "0",
        "159"
      ],
      "edit_info": {
        "initial": {
          "editTweetIds": [
            "1684269753823809536"
          ],
          "editableUntil": "2023-07-26T19:29:36.000Z",
          "editsRemaining": "5",
          "isEditEligible": false
        }
      },
      "entities": {
        "hashtags": [
          {
            "indices": [
              "116",
              "126"
            ],
            "text": "PublicArt"
          },
          {
            "indices": [
              "127",
              "148"
            ],
            "text": "UrsulavonRydingsvard"
          },
          {
            "indices": [
              "149",
              "159"
            ],
            "text": "sculpture"
          }
        ],
        "urls": [
          {
            "display_url": "bit.ly/2Tnja4z",
            "expanded_url": "https://bit.ly/2Tnja4z",
            "indices": [
              "91",
              "114"
            ],
            "url": "https://t.co/zRelSnlNeQ"
          }
        ]
      },
      "favorite_count": "0",
      "favorited": false,
      "full_text": "See “Ocean Voices II” by Ursula von  Rydingsvard on display, post-security, in Terminal 3. https://t.co/zRelSnlNeQ\n\n#PublicArt #UrsulavonRydingsvard #sculpture",
      "id_str": "1684269753823809536",
      "in_reply_to_screen_name": "SFOMuseum",
      "in_reply_to_status_id": "1684269750392864768",
      "in_reply_to_status_id_str": "1684269750392864768",
      "in_reply_to_user_id": "116329337",
      "in_reply_to_user_id_str": "116329337",
      "lang": "ro",
      "possibly_sensitive": false,
      "retweet_count": "0",
      "retweeted": false,
      "source": "\u003ca href=\"https://mobile.twitter.com\" rel=\"nofollow\"\u003eTwitter Web App\u003c/a\u003e",
      "truncated": false
    },
    "wof:name": "See “Ocean Voices II” by Ursula von  Rydingsvard on display, post-security, in Terminal 3. https://t.co/zRelSnlNeQ\n\n#PublicArt #UrsulavonRydingsvard #sculpture",
    "wof:placetype": "custom",
    "wof:placetype_alt": [
      "tweet"
    ]
  },
  "geometry": {"coordinates":[-122.386166,37.616356],"type":"Point"}
}
