{
  "type": "Feature",
  "properties": {
    "sfomuseum:placetype": "tweet",
    "twitter:tweet": {
      "created": 1355947383,
      "created_at": "Wed Dec 19 20:03:03 +0000 2012",
      "display_text_range": [
        "0", 
        "142"
      ],
      "entities": {
        "urls": [
          {
            "display_url": "bit.ly/VRP5mR",
            "expanded_url": "http://bit.ly/VRP5mR",
            "indices": [
              "122", 
              "142"
            ],
            "url": "http://t.co/e3zy6cCL"
          }
        ]
      },
      "favorite_count": "0",
      "favorited": false,
      "full_text": "Artist \u0026amp; medical hypnotherapist Marilynne Morshead believes in rejuvenating power of art. See her work pre-TSA in T2: http://t.co/e3zy6cCL",
      "id_str": "281489844570558466",
      "lang": "en",
      "possibly_sensitive": false,
      "retweet_count": "0",
      "retweeted": false,
      "source": "\u003ca href=\"https://about.twitter.com/products/tweetdeck\" rel=\"nofollow\"\u003eTweetDeck\u003c/a\u003e",
      "truncated": false
    },
    "wof:name": "Twitter message #281489844570558466",
    "wof:placetype": "custom"
  },
  "geometry": {"coordinates":[-122.386166,37.616356],"type":"Point"}
}
