{
  "type": "Feature",
  "properties": {
    "sfomuseum:placetype": "tweet",
    "twitter:tweet": {
      "created": 1493770387,
      "created_at": "Wed May 03 00:13:07 +0000 2017",
      "display_text_range": [
        "0", 
        "140"
      ],
      "entities": {
        "hashtags": [
          {
            "indices": [
              "21", 
              "31"
            ],
            "text": "CopaMatch"
          }
        ],
        "urls": [
          {
            "display_url": "flysfo.com/copamatch",
            "expanded_url": "http://www.flysfo.com/copamatch",
            "indices": [
              "103", 
              "126"
            ],
            "url": "https://t.co/u3mXKB2ieP"
          }
        ],
        "user_mentions": [
          {
            "id_str": "16408759",
            "indices": [
              "3", 
              "10"
            ],
            "name": "San Francisco International Airport (SFO) ✈️",
            "screen_name": "flySFO"
          }
        ]
      },
      "favorite_count": "0",
      "favorited": false,
      "full_text": "RT @flySFO: Play the #CopaMatch game by 5/8 for a chance to win 2 tickets to Panama City or Rio! Go to https://t.co/u3mXKB2ieP to enter! ht…",
      "id_str": "859561422946041856",
      "lang": "en",
      "possibly_sensitive": false,
      "retweet_count": "0",
      "retweeted": false,
      "source": "\u003ca href=\"http://twitter.com\" rel=\"nofollow\"\u003eTwitter Web Client\u003c/a\u003e",
      "truncated": false
    },
    "wof:name": "Twitter message #859561422946041856",
    "wof:placetype": "custom"
  },
  "geometry": {"coordinates":[-122.386166,37.616356],"type":"Point"}
}
