{
  "type": "Feature",
  "properties": {
    "sfomuseum:placetype": "tweet",
    "twitter:tweet": {
      "created": 1318363013,
      "created_at": "Tue Oct 11 19:56:53 +0000 2011",
      "display_text_range": [
        "0", 
        "132"
      ],
      "entities": {
        "hashtags": [
          {
            "indices": [
              "118", 
              "132"
            ],
            "text": "TheAntennaAge"
          }
        ]
      },
      "favorite_count": "0",
      "favorited": false,
      "full_text": "Uttered for the first time on this day in 1975 were, \"Live, from New York! It's Saturday night!\" Happy birthday, SNL! #TheAntennaAge",
      "id_str": "123849573188902913",
      "lang": "en",
      "retweet_count": "1",
      "retweeted": false,
      "source": "\u003ca href=\"http://www.hootsuite.com\" rel=\"nofollow\"\u003eHootsuite\u003c/a\u003e",
      "truncated": false
    },
    "wof:name": "Twitter message #123849573188902913",
    "wof:placetype": "custom"
  },
  "geometry": {"coordinates":[-122.386166,37.616356],"type":"Point"}
}
