{
  "type": "Feature",
  "properties": {
    "date:cessation_lower": "2018-09-17",
    "date:cessation_upper": "2018-09-17",
    "date:inception_lower": "2018-09-17",
    "date:inception_upper": "2018-09-17",
    "iso:country": "US",
    "sfomuseum:placetype": "tweet",
    "twitter:tweet": {
      "created": 1537204428,
      "created_at": "Mon Sep 17 17:13:48 +0000 2018",
      "display_text_range": [
        "0",
        "140"
      ],
      "edit_info": {
        "initial": {
          "editTweetIds": [
            "1041736994278191104"
          ],
          "editableUntil": "2018-09-17T18:13:48.630Z",
          "editsRemaining": "5",
          "isEditEligible": true
        }
      },
      "entities": {
        "user_mentions": [
          {
            "id_str": "1027902861483552770",
            "indices": [
              "3",
              "15"
            ],
            "name": "Arhoolie Foundation",
            "screen_name": "ArhoolieFdn"
          },
          {
            "id_str": "9677372",
            "indices": [
              "34",
              "39"
            ],
            "name": "KQED",
            "screen_name": "KQED"
          },
          {
            "id_str": "276567401",
            "indices": [
              "44",
              "57"
            ],
            "name": "Rachael (Authenticated in My Mind) Myrow",
            "screen_name": "rachaelmyrow"
          },
          {
            "id_str": "116329337",
            "indices": [
              "97",
              "107"
            ],
            "name": "SFO Museum",
            "screen_name": "SFOMuseum"
          }
        ]
      },
      "favorite_count": "0",
      "favorited": false,
      "full_text": "RT @ArhoolieFdn: Great story from @KQED and @rachaelmyrow on the new Arhoolie Records exhibit at @SFOMuseum Give a listen: https://t.co/8GM…",
      "id_str": "1041736994278191104",
      "lang": "en",
      "retweet_count": "0",
      "retweeted": false,
      "source": "\u003ca href=\"http://twitter.com\" rel=\"nofollow\"\u003eTwitter Web Client\u003c/a\u003e",
      "truncated": false
    },
    "wof:name": "RT @ArhoolieFdn: Great story from @KQED and @rachaelmyrow on the new Arhoolie Records exhibit at @SFOMuseum Give a listen: https://t.co/8GM…",
    "wof:placetype": "custom"
  },
  "geometry": {"coordinates":[-122.386166,37.616356],"type":"Point"}
}
