{
  "type": "Feature",
  "properties": {
    "sfomuseum:placetype": "tweet",
    "twitter:tweet": {
      "created": 1563916429,
      "created_at": "Tue Jul 23 21:13:49 +0000 2019",
      "display_text_range": [
        "0", 
        "143"
      ],
      "entities": {
        "urls": [
          {
            "display_url": "bit.ly/HarveyMilkExhi…",
            "expanded_url": "http://bit.ly/HarveyMilkExhibition",
            "indices": [
              "120", 
              "143"
            ],
            "url": "https://t.co/eGYmHGjUIn"
          }
        ],
        "user_mentions": [
          {
            "id_str": "14526877",
            "indices": [
              "0", 
              "7"
            ],
            "name": "Gabe Ortíz",
            "screen_name": "TUSK81"
          }, 
          {
            "id_str": "16408759",
            "indices": [
              "8", 
              "15"
            ],
            "name": "San Francisco International Airport (SFO) ✈️",
            "screen_name": "flySFO"
          }
        ]
      },
      "favorite_count": "1",
      "favorited": false,
      "full_text": "@TUSK81 @flySFO Thank you so much for stopping by! We hope you enjoyed our exhibition \"Harvey Milk: Messenger of Hope!\" https://t.co/eGYmHGjUIn",
      "id_str": "1153775245318221824",
      "in_reply_to_screen_name": "TUSK81",
      "in_reply_to_status_id": "1152778952483725313",
      "in_reply_to_status_id_str": "1152778952483725313",
      "in_reply_to_user_id": "14526877",
      "in_reply_to_user_id_str": "14526877",
      "lang": "en",
      "possibly_sensitive": false,
      "retweet_count": "0",
      "retweeted": false,
      "source": "\u003ca href=\"http://twitter.com\" rel=\"nofollow\"\u003eTwitter Web Client\u003c/a\u003e",
      "truncated": false
    },
    "wof:name": "Twitter message #1153775245318221824",
    "wof:placetype": "custom"
  },
  "geometry": {"coordinates":[-122.386166,37.616356],"type":"Point"}
}
