{
  "type": "Feature",
  "properties": {
    "date:cessation_lower":"2019-07-23",
    "date:cessation_upper":"2019-07-23",
    "date:inception_lower":"2019-07-23",
    "date:inception_upper":"2019-07-23",
    "iso:country":"US",
    "sfomuseum:placetype":"tweet",
    "twitter:tweet":{
        "created":1563916429,
        "created_at":"Tue Jul 23 21:13:49 +0000 2019",
        "display_text_range":[
            "0",
            "143"
        ],
        "entities":{
            "urls":[
                {
                    "display_url":"bit.ly/HarveyMilkExhi\u2026",
                    "expanded_url":"http://bit.ly/HarveyMilkExhibition",
                    "indices":[
                        "120",
                        "143"
                    ],
                    "url":"https://t.co/eGYmHGjUIn"
                }
            ],
            "user_mentions":[
                {
                    "id_str":"14526877",
                    "indices":[
                        "0",
                        "7"
                    ],
                    "name":"Gabe Ort\u00edz",
                    "screen_name":"TUSK81"
                },
                {
                    "id_str":"16408759",
                    "indices":[
                        "8",
                        "15"
                    ],
                    "name":"San Francisco International Airport (SFO) \u2708\ufe0f",
                    "screen_name":"flySFO"
                }
            ]
        },
        "favorite_count":"1",
        "favorited":false,
        "full_text":"@TUSK81 @flySFO Thank you so much for stopping by! We hope you enjoyed our exhibition \"Harvey Milk: Messenger of Hope!\" https://t.co/eGYmHGjUIn",
        "id_str":"1153775245318221824",
        "in_reply_to_screen_name":"TUSK81",
        "in_reply_to_status_id":"1152778952483725313",
        "in_reply_to_status_id_str":"1152778952483725313",
        "in_reply_to_user_id":"14526877",
        "in_reply_to_user_id_str":"14526877",
        "lang":"en",
        "possibly_sensitive":false,
        "retweet_count":"0",
        "retweeted":false,
        "source":"<a href=\"http://twitter.com\" rel=\"nofollow\">Twitter Web Client</a>",
        "truncated":false
    },
    "wof:name":"@TUSK81 @flySFO Thank you so much for stopping by! We hope you enjoyed our exhibition \"Harvey Milk: Messenger of Hope!\" https://t.co/eGYmHGjUIn",
    "wof:placetype":"custom"
},
  "geometry": {"coordinates":[-122.386166,37.616356],"type":"Point"}
}