{
  "type": "Feature",
  "properties": {
    "date:cessation_lower":"2015-01-05",
    "date:cessation_upper":"2015-01-05",
    "date:inception_lower":"2015-01-05",
    "date:inception_upper":"2015-01-05",
    "iso:country":"US",
    "sfomuseum:placetype":"tweet",
    "twitter:tweet":{
        "created":1420488856,
        "created_at":"Mon Jan 05 20:14:16 +0000 2015",
        "display_text_range":[
            "0",
            "140"
        ],
        "entities":{
            "user_mentions":[
                {
                    "id_str":"17843620",
                    "indices":[
                        "3",
                        "14"
                    ],
                    "name":"mlukanuski",
                    "screen_name":"mlukanuski"
                },
                {
                    "id_str":"116329337",
                    "indices":[
                        "90",
                        "100"
                    ],
                    "name":"SFO Museum",
                    "screen_name":"SFOMuseum"
                }
            ]
        },
        "favorite_count":"0",
        "favorited":false,
        "full_text":"RT @mlukanuski: Beyond craft: provoking exhibit of Bay Area  art glass terminal 2. Thanks @SFOMuseum bright spot during flight delay http:/\u2026",
        "id_str":"552196401669894144",
        "lang":"en",
        "retweet_count":"0",
        "retweeted":false,
        "source":"<a href=\"http://www.hootsuite.com\" rel=\"nofollow\">Hootsuite</a>",
        "truncated":false
    },
    "wof:name":"RT @mlukanuski: Beyond craft: provoking exhibit of Bay Area  art glass terminal 2. Thanks @SFOMuseum bright spot during flight delay http:/\u2026",
    "wof:placetype":"custom"
},
  "geometry": {"coordinates":[-122.386166,37.616356],"type":"Point"}
}