{
  "type": "Feature",
  "properties": {
    "date:cessation_lower":"2012-05-03",
    "date:cessation_upper":"2012-05-03",
    "date:inception_lower":"2012-05-03",
    "date:inception_upper":"2012-05-03",
    "iso:country":"US",
    "sfomuseum:placetype":"tweet",
    "twitter:tweet":{
        "created":1336074970,
        "created_at":"Thu May 03 19:56:10 +0000 2012",
        "display_text_range":[
            "0",
            "127"
        ],
        "entities":{
            "urls":[
                {
                    "display_url":"yfrog.com/khjrxyqj",
                    "expanded_url":"http://yfrog.com/khjrxyqj",
                    "indices":[
                        "80",
                        "100"
                    ],
                    "url":"http://t.co/jhHnhcmq"
                }
            ]
        },
        "favorite_count":"0",
        "favorited":false,
        "full_text":"Link between microscopes &amp; automata: early versions of both (such as these: http://t.co/jhHnhcmq) were made by clockmakers!",
        "id_str":"198138905256656896",
        "lang":"en",
        "possibly_sensitive":false,
        "retweet_count":"1",
        "retweeted":false,
        "source":"<a href=\"https://about.twitter.com/products/tweetdeck\" rel=\"nofollow\">TweetDeck</a>",
        "truncated":false
    },
    "wof:name":"Link between microscopes &amp; automata: early versions of both (such as these: http://t.co/jhHnhcmq) were made by clockmakers!",
    "wof:placetype":"custom"
},
  "geometry": {"coordinates":[-122.386166,37.616356],"type":"Point"}
}