{
  "type": "Feature",
  "properties": {
    "sfomuseum:placetype": "tweet",
    "twitter:tweet": {
      "created": 1370017426,
      "created_at": "Fri May 31 16:23:46 +0000 2013",
      "display_text_range": [
        "0", 
        "137"
      ],
      "entities": {
        "hashtags": [
          {
            "indices": [
              "45", 
              "55"
            ],
            "text": "PanAfrica"
          }, 
          {
            "indices": [
              "130", 
              "137"
            ],
            "text": "avgeek"
          }
        ],
        "urls": [
          {
            "display_url": "ow.ly/lApwN",
            "expanded_url": "http://ow.ly/lApwN",
            "indices": [
              "107", 
              "129"
            ],
            "url": "http://t.co/6JnId8xbvJ"
          }
        ],
        "user_mentions": [
          {
            "id_str": "41842642",
            "indices": [
              "90", 
              "105"
            ],
            "name": "James Mowdy | BSPOKE",
            "screen_name": "JamesJetsOften"
          }
        ]
      },
      "favorite_count": "0",
      "favorited": false,
      "full_text": "Thanks to the folks who came to last night's #PanAfrica talk by Tom Culbert! Great pic by @JamesJetsOften- http://t.co/6JnId8xbvJ #avgeek",
      "id_str": "340503883329703936",
      "lang": "en",
      "possibly_sensitive": false,
      "retweet_count": "0",
      "retweeted": false,
      "source": "\u003ca href=\"http://www.hootsuite.com\" rel=\"nofollow\"\u003eHootsuite\u003c/a\u003e",
      "truncated": false
    },
    "wof:name": "Twitter message #340503883329703936",
    "wof:placetype": "custom"
  },
  "geometry": {"coordinates":[-122.386166,37.616356],"type":"Point"}
}
