{
  "type": "Feature",
  "properties": {
    "sfomuseum:placetype": "tweet",
    "twitter:tweet": {
      "created": 1449021322,
      "created_at": "Wed Dec 02 01:55:22 +0000 2015",
      "display_text_range": [
        "0", 
        "138"
      ],
      "entities": {
        "urls": [
          {
            "display_url": "archive.org/details/1809_H…",
            "expanded_url": "https://archive.org/details/1809_HM_Summers_Collection_San_Francisco_California_1941_07_00_20_00",
            "indices": [
              "115", 
              "138"
            ],
            "url": "https://t.co/PJvDimBTiz"
          }
        ]
      },
      "favorite_count": "3",
      "favorited": false,
      "full_text": "Have you ever seen a Pan Am flying boat take off? See some great archival footage of the iconic aircraft at 21:10. https://t.co/PJvDimBTiz",
      "id_str": "671870241408962561",
      "lang": "en",
      "possibly_sensitive": false,
      "retweet_count": "0",
      "retweeted": false,
      "source": "\u003ca href=\"http://www.hootsuite.com\" rel=\"nofollow\"\u003eHootsuite\u003c/a\u003e",
      "truncated": false
    },
    "wof:name": "Twitter message #671870241408962561",
    "wof:placetype": "custom"
  },
  "geometry": {"coordinates":[-122.386166,37.616356],"type":"Point"}
}
