{
  "type": "Feature",
  "properties": {
    "sfomuseum:placetype": "tweet",
    "twitter:tweet": {
      "created": 1348245431,
      "created_at": "Fri Sep 21 16:37:11 +0000 2012",
      "display_text_range": [
        "0", 
        "134"
      ],
      "entities": {
        "urls": [
          {
            "display_url": "sfist.com/2012/09/21/mea…",
            "expanded_url": "http://sfist.com/2012/09/21/meanwhile_in_southern_california_en.php",
            "indices": [
              "114", 
              "134"
            ],
            "url": "http://t.co/JEEzjSsB"
          }
        ],
        "user_mentions": [
          {
            "id_str": "14093707",
            "indices": [
              "31", 
              "37"
            ],
            "name": "SFist",
            "screen_name": "SFist"
          }
        ]
      },
      "favorite_count": "0",
      "favorited": false,
      "full_text": "We hope to catch a glimpse! RT @SFist: Can’t make it outside? Watch Shuttle Endeavour fly over the Bay Area live: http://t.co/JEEzjSsB",
      "id_str": "249185518099775488",
      "lang": "en",
      "possibly_sensitive": false,
      "retweet_count": "0",
      "retweeted": false,
      "source": "\u003ca href=\"http://www.hootsuite.com\" rel=\"nofollow\"\u003eHootsuite\u003c/a\u003e",
      "truncated": false
    },
    "wof:name": "Twitter message #249185518099775488",
    "wof:placetype": "custom"
  },
  "geometry": {"coordinates":[-122.386166,37.616356],"type":"Point"}
}
