{
  "type": "Feature",
  "properties": {
    "sfomuseum:placetype": "tweet",
    "twitter:tweet": {
      "created": 1365008494,
      "created_at": "Wed Apr 03 17:01:34 +0000 2013",
      "display_text_range": [
        "0", 
        "124"
      ],
      "entities": {
        "urls": [
          {
            "display_url": "instagram.com/p/XpnUfYRk_S/",
            "expanded_url": "http://instagram.com/p/XpnUfYRk_S/",
            "indices": [
              "102", 
              "124"
            ],
            "url": "http://t.co/fSvZLY5AJO"
          }
        ]
      },
      "favorite_count": "0",
      "favorited": false,
      "full_text": "On view pre-TSA in T1, Jet Set Carry-On: the Design, Branding, \u0026amp; Appeal of the Airline Flight Bag http://t.co/fSvZLY5AJO",
      "id_str": "319494899244339200",
      "lang": "en",
      "possibly_sensitive": false,
      "retweet_count": "1",
      "retweeted": false,
      "source": "\u003ca href=\"http://instagram.com\" rel=\"nofollow\"\u003eInstagram\u003c/a\u003e",
      "truncated": false
    },
    "wof:name": "Twitter message #319494899244339200",
    "wof:placetype": "custom"
  },
  "geometry": {"coordinates":[-122.386166,37.616356],"type":"Point"}
}
