{
  "type": "Feature",
  "properties": {
    "date:cessation_lower": "2022-11-08",
    "date:cessation_upper": "2022-11-08",
    "date:inception_lower": "2022-11-08",
    "date:inception_upper": "2022-11-08",
    "sfomuseum:placetype": "tweet",
    "twitter:tweet": {
      "created": 1667865780,
      "created_at": "Tue Nov 08 00:03:00 +0000 2022",
      "display_text_range": [
        "0",
        "288"
      ],
      "edit_info": {
        "initial": {
          "editTweetIds": [
            "1589770424753455104"
          ],
          "editableUntil": "2022-11-08T00:33:00.000Z",
          "editsRemaining": "5",
          "isEditEligible": false
        }
      },
      "entities": {
        "hashtags": [
          {
            "indices": [
              "276",
              "288"
            ],
            "text": "askacurator"
          }
        ],
        "user_mentions": [
          {
            "id_str": "24819749",
            "indices": [
              "0",
              "8"
            ],
            "name": "Brent",
            "screen_name": "sfbrent"
          }
        ]
      },
      "favorite_count": "1",
      "favorited": false,
      "full_text": "@sfbrent We do not have originals in our collection of the uniforms in Fashion in Flight that were shown in reproduction. The decision to display reproductions lay in the unavailability of originals of these uniforms for either acquisition or loan. Thanks so much for asking! #askacurator",
      "id_str": "1589770424753455104",
      "in_reply_to_screen_name": "sfbrent",
      "in_reply_to_status_id": "1588598209647357953",
      "in_reply_to_status_id_str": "1588598209647357953",
      "in_reply_to_user_id": "24819749",
      "in_reply_to_user_id_str": "24819749",
      "lang": "en",
      "retweet_count": "0",
      "retweeted": false,
      "source": "\u003ca href=\"https://mobile.twitter.com\" rel=\"nofollow\"\u003eTwitter Web App\u003c/a\u003e",
      "truncated": false
    },
    "wof:name": "@sfbrent We do not have originals in our collection of the uniforms in Fashion in Flight that were shown in reproduction. The decision to display reproductions lay in the unavailability of originals of these uniforms for either acquisition or loan. Thanks so much for asking! #askacurator",
    "wof:placetype": "custom"
  },
  "geometry": {"coordinates":[-122.386166,37.616356],"type":"Point"}
}
