{
  "type": "Feature",
  "properties": {
    "sfomuseum:placetype": "tweet",
    "twitter:tweet": {
      "created": 1349290382,
      "created_at": "Wed Oct 03 18:53:02 +0000 2012",
      "display_text_range": [
        "0", 
        "143"
      ],
      "entities": {
        "user_mentions": [
          {
            "id_str": "3042711",
            "indices": [
              "17", 
              "28"
            ],
            "name": "Mark Graham",
            "screen_name": "MarkGraham"
          }
        ]
      },
      "favorite_count": "0",
      "favorited": false,
      "full_text": "Woot! Thanks! RT @MarkGraham: Today is SFO-\u0026gt;JFK. The \"Deities in Stone\",Hindu Temple Architecture exhibit, at the United terminal is amazing",
      "id_str": "253568360359546881",
      "lang": "en",
      "retweet_count": "0",
      "retweeted": false,
      "source": "\u003ca href=\"https://about.twitter.com/products/tweetdeck\" rel=\"nofollow\"\u003eTweetDeck\u003c/a\u003e",
      "truncated": false
    },
    "wof:name": "Twitter message #253568360359546881",
    "wof:placetype": "custom"
  },
  "geometry": {"coordinates":[-122.386166,37.616356],"type":"Point"}
}
