{
  "type": "Feature",
  "properties": {
    "date:cessation_lower": "2015-08-18",
    "date:cessation_upper": "2015-08-18",
    "date:inception_lower": "2015-08-18",
    "date:inception_upper": "2015-08-18",
    "iso:country": "US",
    "sfomuseum:placetype": "tweet",
    "twitter:hashtags": [
      "SpreadYourWings",
      "NationalAviationDay"
    ],
    "twitter:tweet": {
      "created": 1439923666,
      "created_at": "Tue Aug 18 18:47:46 +0000 2015",
      "display_text_range": [
        "0",
        "140"
      ],
      "edit_info": {
        "initial": {
          "editTweetIds": [
            "633711904310038528"
          ],
          "editableUntil": "2015-08-18T19:47:46.442Z",
          "editsRemaining": "5",
          "isEditEligible": true
        }
      },
      "entities": {
        "hashtags": [
          {
            "indices": [
              "31",
              "47"
            ],
            "text": "SpreadYourWings"
          },
          {
            "indices": [
              "61",
              "81"
            ],
            "text": "NationalAviationDay"
          }
        ],
        "urls": [
          {
            "display_url": "go.nasa.gov/1J4QiQ3",
            "expanded_url": "http://go.nasa.gov/1J4QiQ3",
            "indices": [
              "107",
              "129"
            ],
            "url": "http://t.co/DId1OzAwmy"
          }
        ],
        "user_mentions": [
          {
            "id_str": "2734381938",
            "indices": [
              "3",
              "12"
            ],
            "name": "NASA Aeronautics",
            "screen_name": "NASAaero"
          }
        ]
      },
      "favorite_count": "0",
      "favorited": false,
      "full_text": "RT @NASAAero: Decided where to #SpreadYourWings tomorrow for #NationalAviationDay? Take a pic and post it! http://t.co/DId1OzAwmy http://t.…",
      "id_str": "633711904310038528",
      "lang": "en",
      "possibly_sensitive": false,
      "retweet_count": "0",
      "retweeted": false,
      "source": "\u003ca href=\"http://twitter.com/download/iphone\" rel=\"nofollow\"\u003eTwitter for iPhone\u003c/a\u003e",
      "truncated": false
    },
    "twitter:user_mentions": [
      "NASAaero"
    ],
    "wof:name": "RT @NASAAero: Decided where to #SpreadYourWings tomorrow for #NationalAviationDay? Take a pic and post it! http://t.co/DId1OzAwmy http://t.…",
    "wof:placetype": "custom",
    "wof:placetype_alt": [
      "tweet"
    ]
  },
  "geometry": {"coordinates":[-122.386166,37.616356],"type":"Point"}
}
