{
  "type": "Feature",
  "properties": {
    "date:cessation_lower": "2013-03-18",
    "date:cessation_upper": "2013-03-18",
    "date:inception_lower": "2013-03-18",
    "date:inception_upper": "2013-03-18",
    "iso:country": "US",
    "sfomuseum:placetype": "tweet",
    "twitter:tweet": {
      "created": 1363645347,
      "created_at": "Mon Mar 18 22:22:27 +0000 2013",
      "display_text_range": [
        "0",
        "80"
      ],
      "edit_info": {
        "initial": {
          "editTweetIds": [
            "313777446480646144"
          ],
          "editableUntil": "2013-03-18T22:52:27.601Z",
          "editsRemaining": "5",
          "isEditEligible": true
        }
      },
      "entities": {
        "hashtags": [
          {
            "indices": [
              "45",
              "57"
            ],
            "text": "FerrisPlock"
          }
        ],
        "urls": [
          {
            "display_url": "instagr.am/p/XA_EhJxk-g/",
            "expanded_url": "http://instagr.am/p/XA_EhJxk-g/",
            "indices": [
              "58",
              "80"
            ],
            "url": "http://t.co/u7BKhoQ2HK"
          }
        ]
      },
      "favorite_count": "0",
      "favorited": false,
      "full_text": "Recology comes in with another great artist! #FerrisPlock http://t.co/u7BKhoQ2HK",
      "id_str": "313777446480646144",
      "lang": "en",
      "possibly_sensitive": false,
      "retweet_count": "1",
      "retweeted": false,
      "source": "\u003ca href=\"http://instagram.com\" rel=\"nofollow\"\u003eInstagram\u003c/a\u003e",
      "truncated": false
    },
    "wof:name": "Recology comes in with another great artist! #FerrisPlock http://t.co/u7BKhoQ2HK",
    "wof:placetype": "custom"
  },
  "geometry": {"coordinates":[-122.386166,37.616356],"type":"Point"}
}
