{
  "type": "Feature",
  "properties": {
    "sfomuseum:placetype": "tweet",
    "twitter:tweet": {
      "created": 1394152611,
      "created_at": "Fri Mar 07 00:36:51 +0000 2014",
      "display_text_range": [
        "0", 
        "130"
      ],
      "entities": {
        "hashtags": [
          {
            "indices": [
              "2", 
              "20"
            ],
            "text": "throwbackthursday"
          }, 
          {
            "indices": [
              "126", 
              "130"
            ],
            "text": "tbt"
          }
        ],
        "urls": [
          {
            "display_url": "ow.ly/ukjtb",
            "expanded_url": "http://ow.ly/ukjtb",
            "indices": [
              "103", 
              "125"
            ],
            "url": "http://t.co/BUZkeERZk6"
          }
        ]
      },
      "favorite_count": "1",
      "favorited": false,
      "full_text": "A #throwbackthursday for what could have been- a 1932 proposal for the Golden Gate Union Air Terminal: http://t.co/BUZkeERZk6 #tbt",
      "id_str": "441734183476412416",
      "lang": "en",
      "possibly_sensitive": false,
      "retweet_count": "1",
      "retweeted": false,
      "source": "\u003ca href=\"http://www.hootsuite.com\" rel=\"nofollow\"\u003eHootsuite\u003c/a\u003e",
      "truncated": false
    },
    "wof:name": "Twitter message #441734183476412416",
    "wof:placetype": "custom"
  },
  "geometry": {"coordinates":[-122.386166,37.616356],"type":"Point"}
}
