{
  "type": "Feature",
  "properties": {
    "sfomuseum:placetype": "tweet",
    "twitter:tweet": {
      "created": 1517079620,
      "created_at": "Sat Jan 27 19:00:20 +0000 2018",
      "display_text_range": [
        "0", 
        "221"
      ],
      "entities": {
        "hashtags": [
          {
            "indices": [
              "0", 
              "10"
            ],
            "text": "OnThisDay"
          }
        ],
        "media": [
          {
            "display_url": "pic.twitter.com/2rZSsA6lGs",
            "expanded_url": "https://twitter.com/SFOMuseum/status/957327433006542848/photo/1",
            "id_str": "957327429835677698",
            "indices": [
              "198", 
              "221"
            ],
            "media_url": "http://pbs.twimg.com/media/DUkcOa0X4AIS1I8.jpg",
            "media_url_https": "https://pbs.twimg.com/media/DUkcOa0X4AIS1I8.jpg",
            "sizes": {
              "large": {
                "h": "1429",
                "resize": "fit",
                "w": "2000"
              },
              "medium": {
                "h": "857",
                "resize": "fit",
                "w": "1200"
              },
              "small": {
                "h": "486",
                "resize": "fit",
                "w": "680"
              },
              "thumb": {
                "h": "150",
                "resize": "crop",
                "w": "150"
              }
            },
            "type": "photo",
            "url": "https://t.co/2rZSsA6lGs"
          }
        ]
      },
      "extended_entities": {
        "media": [
          {
            "display_url": "pic.twitter.com/2rZSsA6lGs",
            "expanded_url": "https://twitter.com/SFOMuseum/status/957327433006542848/photo/1",
            "id_str": "957327429835677698",
            "indices": [
              "198", 
              "221"
            ],
            "media_url": "http://pbs.twimg.com/media/DUkcOa0X4AIS1I8.jpg",
            "media_url_https": "https://pbs.twimg.com/media/DUkcOa0X4AIS1I8.jpg",
            "sizes": {
              "large": {
                "h": "1429",
                "resize": "fit",
                "w": "2000"
              },
              "medium": {
                "h": "857",
                "resize": "fit",
                "w": "1200"
              },
              "small": {
                "h": "486",
                "resize": "fit",
                "w": "680"
              },
              "thumb": {
                "h": "150",
                "resize": "crop",
                "w": "150"
              }
            },
            "type": "photo",
            "url": "https://t.co/2rZSsA6lGs"
          }
        ]
      },
      "favorite_count": "67",
      "favorited": false,
      "full_text": "#OnThisDay in 1939, Pan American Airways received their first two Boeing 314 flying boats. The B 314 was introduced to Pan American's Pacific Division and used to open its Atlantic service in 1939. https://t.co/2rZSsA6lGs",
      "id_str": "957327433006542848",
      "lang": "en",
      "possibly_sensitive": false,
      "retweet_count": "19",
      "retweeted": false,
      "source": "\u003ca href=\"http://www.hootsuite.com\" rel=\"nofollow\"\u003eHootsuite\u003c/a\u003e",
      "truncated": false
    },
    "wof:name": "Twitter message #957327433006542848",
    "wof:placetype": "custom"
  },
  "geometry": {"coordinates":[-122.386166,37.616356],"type":"Point"}
}
