{
  "type": "Feature",
  "properties": {
    "sfomuseum:placetype": "tweet",
    "twitter:tweet": {
      "created": 1419298008,
      "created_at": "Tue Dec 23 01:26:48 +0000 2014",
      "display_text_range": [
        "0", 
        "138"
      ],
      "entities": {
        "hashtags": [
          {
            "indices": [
              "131", 
              "138"
            ],
            "text": "avgeek"
          }
        ],
        "urls": [
          {
            "display_url": "ow.ly/GjNi1",
            "expanded_url": "http://ow.ly/GjNi1",
            "indices": [
              "108", 
              "130"
            ],
            "url": "http://t.co/SjitL8Jksu"
          }
        ]
      },
      "favorite_count": "2",
      "favorited": false,
      "full_text": "The first transatlantic jetliner service wasn't via Boeing or Douglas, but the de Havilland DH-106 Comet 4: http://t.co/SjitL8Jksu #avgeek",
      "id_str": "547201623349796864",
      "lang": "en",
      "possibly_sensitive": false,
      "retweet_count": "3",
      "retweeted": false,
      "source": "\u003ca href=\"http://www.hootsuite.com\" rel=\"nofollow\"\u003eHootsuite\u003c/a\u003e",
      "truncated": false
    },
    "wof:name": "Twitter message #547201623349796864",
    "wof:placetype": "custom"
  },
  "geometry": {"coordinates":[-122.386166,37.616356],"type":"Point"}
}
