{
  "type": "Feature",
  "properties": {
    "date:cessation_lower": "2014-12-23",
    "date:cessation_upper": "2014-12-23",
    "date:inception_lower": "2014-12-23",
    "date:inception_upper": "2014-12-23",
    "iso:country": "US",
    "sfomuseum:placetype": "tweet",
    "twitter:hashtags": [
      "avgeek"
    ],
    "twitter:tweet": {
      "created": 1419298008,
      "created_at": "Tue Dec 23 01:26:48 +0000 2014",
      "display_text_range": [
        "0",
        "138"
      ],
      "edit_info": {
        "initial": {
          "editTweetIds": [
            "547201623349796864"
          ],
          "editableUntil": "2014-12-23T02:26:48.178Z",
          "editsRemaining": "5",
          "isEditEligible": true
        }
      },
      "entities": {
        "hashtags": [
          {
            "indices": [
              "131",
              "138"
            ],
            "text": "avgeek"
          }
        ],
        "urls": [
          {
            "display_url": "ow.ly/GjNi1",
            "expanded_url": "http://ow.ly/GjNi1",
            "indices": [
              "108",
              "130"
            ],
            "url": "http://t.co/SjitL8Jksu"
          }
        ]
      },
      "favorite_count": "2",
      "favorited": false,
      "full_text": "The first transatlantic jetliner service wasn't via Boeing or Douglas, but the de Havilland DH-106 Comet 4: http://t.co/SjitL8Jksu #avgeek",
      "id_str": "547201623349796864",
      "lang": "en",
      "possibly_sensitive": false,
      "retweet_count": "3",
      "retweeted": false,
      "source": "\u003ca href=\"http://www.hootsuite.com\" rel=\"nofollow\"\u003eHootsuite\u003c/a\u003e",
      "truncated": false
    },
    "wof:name": "The first transatlantic jetliner service wasn't via Boeing or Douglas, but the de Havilland DH-106 Comet 4: http://t.co/SjitL8Jksu #avgeek",
    "wof:placetype": "custom",
    "wof:placetype_alt": [
      "tweet"
    ]
  },
  "geometry": {"coordinates":[-122.386166,37.616356],"type":"Point"}
}
