{
  "type": "Feature",
  "properties": {
    "date:cessation_lower":"2017-05-17",
    "date:cessation_upper":"2017-05-17",
    "date:inception_lower":"2017-05-17",
    "date:inception_upper":"2017-05-17",
    "iso:country":"US",
    "sfomuseum:placetype":"tweet",
    "twitter:tweet":{
        "created":1495050220,
        "created_at":"Wed May 17 19:43:40 +0000 2017",
        "display_text_range":[
            "0",
            "152"
        ],
        "entities":{
            "hashtags":[
                {
                    "indices":[
                        "14",
                        "28"
                    ],
                    "text":"TheTypewriter"
                }
            ],
            "urls":[
                {
                    "display_url":"bit.ly/Thetypewriter",
                    "expanded_url":"http://bit.ly/Thetypewriter",
                    "indices":[
                        "129",
                        "152"
                    ],
                    "url":"https://t.co/Nph1wFWx99"
                }
            ],
            "user_mentions":[
                {
                    "id_str":"348881683",
                    "indices":[
                        "0",
                        "12"
                    ],
                    "name":"Rebecca Kohn",
                    "screen_name":"Bookcharmer"
                }
            ]
        },
        "favorite_count":"0",
        "favorited":false,
        "full_text":"@Bookcharmer \"#TheTypewriter: An Innovation in Writing\" will be up until late January 2018 so there is plenty of time to see it! https://t.co/Nph1wFWx99",
        "id_str":"864929428756807680",
        "in_reply_to_screen_name":"Bookcharmer",
        "in_reply_to_status_id":"864917886761967616",
        "in_reply_to_status_id_str":"864917886761967616",
        "in_reply_to_user_id":"348881683",
        "in_reply_to_user_id_str":"348881683",
        "lang":"en",
        "possibly_sensitive":false,
        "retweet_count":"0",
        "retweeted":false,
        "source":"<a href=\"http://twitter.com\" rel=\"nofollow\">Twitter Web Client</a>",
        "truncated":false
    },
    "wof:name":"@Bookcharmer \"#TheTypewriter: An Innovation in Writing\" will be up until late January 2018 so there is plenty of time to see it! https://t.co/Nph1wFWx99",
    "wof:placetype":"custom"
},
  "geometry": {"coordinates":[-122.386166,37.616356],"type":"Point"}
}