{
  "type": "Feature",
  "properties": {
    "sfomuseum:placetype": "tweet",
    "twitter:tweet": {
      "created": 1407281250,
      "created_at": "Tue Aug 05 23:27:30 +0000 2014",
      "display_text_range": [
        "0", 
        "56"
      ],
      "entities": {
        "user_mentions": [
          {
            "id_str": "231234588",
            "indices": [
              "0", 
              "15"
            ],
            "name": "Nancy Ewart",
            "screen_name": "namastenancysf"
          }
        ]
      },
      "favorite_count": "0",
      "favorited": false,
      "full_text": "@namastenancysf Thank you!! That's really great to hear!",
      "id_str": "496799689296322560",
      "in_reply_to_screen_name": "namastenancysf",
      "in_reply_to_status_id": "496798827408797698",
      "in_reply_to_status_id_str": "496798827408797698",
      "in_reply_to_user_id": "231234588",
      "in_reply_to_user_id_str": "231234588",
      "lang": "en",
      "retweet_count": "0",
      "retweeted": false,
      "source": "\u003ca href=\"http://www.hootsuite.com\" rel=\"nofollow\"\u003eHootsuite\u003c/a\u003e",
      "truncated": false
    },
    "wof:name": "Twitter message #496799689296322560",
    "wof:placetype": "custom"
  },
  "geometry": {"coordinates":[-122.386166,37.616356],"type":"Point"}
}
