{
  "type": "Feature",
  "properties": {
    "date:cessation_lower": "2013-10-21",
    "date:cessation_upper": "2013-10-21",
    "date:inception_lower": "2013-10-21",
    "date:inception_upper": "2013-10-21",
    "iso:country": "US",
    "sfomuseum:placetype": "tweet",
    "twitter:tweet": {
      "created": 1382373979,
      "created_at": "Mon Oct 21 16:46:19 +0000 2013",
      "display_text_range": [
        "0",
        "139"
      ],
      "entities": {
        "urls": [
          {
            "display_url": "ow.ly/q1Eg1",
            "expanded_url": "http://ow.ly/q1Eg1",
            "indices": [
              "117",
              "139"
            ],
            "url": "http://t.co/rxw1KTBQEb"
          }
        ],
        "user_mentions": [
          {
            "id_str": "16408759",
            "indices": [
              "94",
              "101"
            ],
            "name": "San Francisco International Airport (SFO) ✈️",
            "screen_name": "flySFO"
          }
        ]
      },
      "favorite_count": "0",
      "favorited": false,
      "full_text": "USA Today wants to know what US airport has the best art program. Help us win- vote daily for @flySFO until Nov. 11: http://t.co/rxw1KTBQEb",
      "id_str": "392331024233152512",
      "lang": "en",
      "possibly_sensitive": false,
      "retweet_count": "1",
      "retweeted": false,
      "source": "\u003ca href=\"http://www.hootsuite.com\" rel=\"nofollow\"\u003eHootsuite\u003c/a\u003e",
      "truncated": false
    },
    "wof:name": "USA Today wants to know what US airport has the best art program. Help us win- vote daily for @flySFO until Nov. 11: http://t.co/rxw1KTBQEb",
    "wof:placetype": "custom"
  },
  "geometry": {"coordinates":[-122.386166,37.616356],"type":"Point"}
}
