{
  "type": "Feature",
  "properties": {
    "sfomuseum:placetype": "tweet",
    "twitter:tweet": {
      "created": 1495848904,
      "created_at": "Sat May 27 01:35:04 +0000 2017",
      "display_text_range": [
        "0", 
        "147"
      ],
      "entities": {
        "hashtags": [
          {
            "indices": [
              "28", 
              "42"
            ],
            "text": "ArtsandCrafts"
          }
        ],
        "media": [
          {
            "display_url": "pic.twitter.com/CTMMPMGsiW",
            "expanded_url": "https://twitter.com/SFOMuseum/status/868279354161336320/photo/1",
            "id_str": "868279350734589953",
            "indices": [
              "124", 
              "147"
            ],
            "media_url": "http://pbs.twimg.com/media/DAy_eBpXkAEJPxt.jpg",
            "media_url_https": "https://pbs.twimg.com/media/DAy_eBpXkAEJPxt.jpg",
            "sizes": {
              "large": {
                "h": "2000",
                "resize": "fit",
                "w": "1600"
              },
              "medium": {
                "h": "1200",
                "resize": "fit",
                "w": "960"
              },
              "small": {
                "h": "680",
                "resize": "fit",
                "w": "544"
              },
              "thumb": {
                "h": "150",
                "resize": "crop",
                "w": "150"
              }
            },
            "type": "photo",
            "url": "https://t.co/CTMMPMGsiW"
          }
        ],
        "urls": [
          {
            "display_url": "bit.ly/SFOArtsandCraf…",
            "expanded_url": "http://bit.ly/SFOArtsandCrafts",
            "indices": [
              "100", 
              "123"
            ],
            "url": "https://t.co/beGCVuzpTr"
          }
        ]
      },
      "extended_entities": {
        "media": [
          {
            "display_url": "pic.twitter.com/CTMMPMGsiW",
            "expanded_url": "https://twitter.com/SFOMuseum/status/868279354161336320/photo/1",
            "id_str": "868279350734589953",
            "indices": [
              "124", 
              "147"
            ],
            "media_url": "http://pbs.twimg.com/media/DAy_eBpXkAEJPxt.jpg",
            "media_url_https": "https://pbs.twimg.com/media/DAy_eBpXkAEJPxt.jpg",
            "sizes": {
              "large": {
                "h": "2000",
                "resize": "fit",
                "w": "1600"
              },
              "medium": {
                "h": "1200",
                "resize": "fit",
                "w": "960"
              },
              "small": {
                "h": "680",
                "resize": "fit",
                "w": "544"
              },
              "thumb": {
                "h": "150",
                "resize": "crop",
                "w": "150"
              }
            },
            "type": "photo",
            "url": "https://t.co/CTMMPMGsiW"
          }
        ]
      },
      "favorite_count": "2",
      "favorited": false,
      "full_text": "Learn more in \"At Home with #ArtsandCrafts\" on display pre-security, in the International Terminal. https://t.co/beGCVuzpTr https://t.co/CTMMPMGsiW",
      "id_str": "868279354161336320",
      "lang": "en",
      "possibly_sensitive": false,
      "retweet_count": "0",
      "retweeted": false,
      "source": "\u003ca href=\"http://www.hootsuite.com\" rel=\"nofollow\"\u003eHootsuite\u003c/a\u003e",
      "truncated": false
    },
    "wof:name": "Twitter message #868279354161336320",
    "wof:placetype": "custom"
  },
  "geometry": {"coordinates":[-122.386166,37.616356],"type":"Point"}
}
