{
  "type": "Feature",
  "properties": {
    "date:cessation_lower": "2021-09-17",
    "date:cessation_upper": "2021-09-17",
    "date:inception_lower": "2021-09-17",
    "date:inception_upper": "2021-09-17",
    "sfomuseum:placetype": "tweet",
    "twitter:tweet": {
      "created": 1631840006,
      "created_at": "Fri Sep 17 00:53:26 +0000 2021",
      "display_text_range": [
        "0",
        "191"
      ],
      "edit_info": {
        "initial": {
          "editTweetIds": [
            "1438667375411220481"
          ],
          "editableUntil": "2021-09-17T01:23:26.102Z",
          "editsRemaining": "5",
          "isEditEligible": true
        }
      },
      "entities": {
      },
      "favorite_count": "0",
      "favorited": false,
      "full_text": "📸 1/2:\nHalf-gallon jug c. 1850\nCollin Rhodes Factory\nEdgefield District, South Carolina\nalkaline-glazed stoneware with kaolin slip-cup decoration\nCollection of Kenneth Fechtner\nL2020.1401.008",
      "id_str": "1438667375411220481",
      "in_reply_to_screen_name": "SFOMuseum",
      "in_reply_to_status_id": "1438667372907270144",
      "in_reply_to_status_id_str": "1438667372907270144",
      "in_reply_to_user_id": "116329337",
      "in_reply_to_user_id_str": "116329337",
      "lang": "en",
      "retweet_count": "0",
      "retweeted": false,
      "source": "\u003ca href=\"https://mobile.twitter.com\" rel=\"nofollow\"\u003eTwitter Web App\u003c/a\u003e",
      "truncated": false
    },
    "wof:name": "📸 1/2:\nHalf-gallon jug c. 1850\nCollin Rhodes Factory\nEdgefield District, South Carolina\nalkaline-glazed stoneware with kaolin slip-cup decoration\nCollection of Kenneth Fechtner\nL2020.1401.008",
    "wof:placetype": "custom"
  },
  "geometry": {"coordinates":[-122.386166,37.616356],"type":"Point"}
}
