{
  "type": "Feature",
  "properties": {
    "sfomuseum:placetype": "tweet",
    "twitter:tweet": {
      "created": 1460763623,
      "created_at": "Fri Apr 15 23:40:23 +0000 2016",
      "display_text_range": [
        "0", 
        "137"
      ],
      "entities": {
        "media": [
          {
            "display_url": "pic.twitter.com/DeSn2SqS3W",
            "expanded_url": "https://twitter.com/SFOMuseum/status/721121018425843712/photo/1",
            "id_str": "721121017142358017",
            "indices": [
              "114", 
              "137"
            ],
            "media_url": "http://pbs.twimg.com/media/CgHvvpLWsAEF2wN.jpg",
            "media_url_https": "https://pbs.twimg.com/media/CgHvvpLWsAEF2wN.jpg",
            "sizes": {
              "large": {
                "h": "2048",
                "resize": "fit",
                "w": "1508"
              },
              "medium": {
                "h": "1200",
                "resize": "fit",
                "w": "884"
              },
              "small": {
                "h": "680",
                "resize": "fit",
                "w": "501"
              },
              "thumb": {
                "h": "150",
                "resize": "crop",
                "w": "150"
              }
            },
            "type": "photo",
            "url": "https://t.co/DeSn2SqS3W"
          }
        ]
      },
      "extended_entities": {
        "media": [
          {
            "display_url": "pic.twitter.com/DeSn2SqS3W",
            "expanded_url": "https://twitter.com/SFOMuseum/status/721121018425843712/photo/1",
            "id_str": "721121017142358017",
            "indices": [
              "114", 
              "137"
            ],
            "media_url": "http://pbs.twimg.com/media/CgHvvpLWsAEF2wN.jpg",
            "media_url_https": "https://pbs.twimg.com/media/CgHvvpLWsAEF2wN.jpg",
            "sizes": {
              "large": {
                "h": "2048",
                "resize": "fit",
                "w": "1508"
              },
              "medium": {
                "h": "1200",
                "resize": "fit",
                "w": "884"
              },
              "small": {
                "h": "680",
                "resize": "fit",
                "w": "501"
              },
              "thumb": {
                "h": "150",
                "resize": "crop",
                "w": "150"
              }
            },
            "type": "photo",
            "url": "https://t.co/DeSn2SqS3W"
          }
        ]
      },
      "favorite_count": "11",
      "favorited": false,
      "full_text": "We are very pleased to announce that the Aviation Museum and Library will be open on Saturdays starting tomorrow. https://t.co/DeSn2SqS3W",
      "id_str": "721121018425843712",
      "lang": "en",
      "possibly_sensitive": false,
      "retweet_count": "4",
      "retweeted": false,
      "source": "\u003ca href=\"http://www.hootsuite.com\" rel=\"nofollow\"\u003eHootsuite\u003c/a\u003e",
      "truncated": false
    },
    "wof:name": "Twitter message #721121018425843712",
    "wof:placetype": "custom"
  },
  "geometry": {"coordinates":[-122.386166,37.616356],"type":"Point"}
}
