{
  "type": "Feature",
  "properties": {
    "sfomuseum:placetype": "tweet",
    "twitter:tweet": {
      "created": 1329428686,
      "created_at": "Thu Feb 16 21:44:46 +0000 2012",
      "display_text_range": [
        "0", 
        "135"
      ],
      "entities": {
        "hashtags": [
          {
            "indices": [
              "40", 
              "48"
            ],
            "text": "CAM2012"
          }
        ],
        "urls": [
          {
            "display_url": "ow.ly/97pYs",
            "expanded_url": "http://ow.ly/97pYs",
            "indices": [
              "115", 
              "135"
            ],
            "url": "http://t.co/BEqoRzSx"
          }
        ]
      },
      "favorite_count": "0",
      "favorited": false,
      "full_text": "We're excited about the next session at #CAM2012 on libraries \u0026 archives! Have you been to ours in the Int'l Term? http://t.co/BEqoRzSx",
      "id_str": "170262368176181248",
      "lang": "en",
      "possibly_sensitive": false,
      "retweet_count": "1",
      "retweeted": false,
      "source": "\u003ca href=\"http://www.hootsuite.com\" rel=\"nofollow\"\u003eHootsuite\u003c/a\u003e",
      "truncated": false
    },
    "wof:name": "Twitter message #170262368176181248",
    "wof:placetype": "custom"
  },
  "geometry": {"coordinates":[-122.386166,37.616356],"type":"Point"}
}
