{
  "type": "Feature",
  "properties": {
    "date:cessation_lower": "2012-02-16",
    "date:cessation_upper": "2012-02-16",
    "date:inception_lower": "2012-02-16",
    "date:inception_upper": "2012-02-16",
    "iso:country": "US",
    "sfomuseum:placetype": "tweet",
    "twitter:hashtags": [
      "CAM2012"
    ],
    "twitter:tweet": {
      "created": 1329428686,
      "created_at": "Thu Feb 16 21:44:46 +0000 2012",
      "display_text_range": [
        "0",
        "135"
      ],
      "edit_info": {
        "initial": {
          "editTweetIds": [
            "170262368176181248"
          ],
          "editableUntil": "2012-02-16T22:44:46.552Z",
          "editsRemaining": "5",
          "isEditEligible": true
        }
      },
      "entities": {
        "hashtags": [
          {
            "indices": [
              "40",
              "48"
            ],
            "text": "CAM2012"
          }
        ],
        "urls": [
          {
            "display_url": "ow.ly/97pYs",
            "expanded_url": "http://ow.ly/97pYs",
            "indices": [
              "115",
              "135"
            ],
            "url": "http://t.co/BEqoRzSx"
          }
        ]
      },
      "favorite_count": "0",
      "favorited": false,
      "full_text": "We're excited about the next session at #CAM2012 on libraries \u0026 archives! Have you been to ours in the Int'l Term? http://t.co/BEqoRzSx",
      "id_str": "170262368176181248",
      "lang": "en",
      "possibly_sensitive": false,
      "retweet_count": "1",
      "retweeted": false,
      "source": "\u003ca href=\"http://www.hootsuite.com\" rel=\"nofollow\"\u003eHootsuite\u003c/a\u003e",
      "truncated": false
    },
    "wof:name": "We're excited about the next session at #CAM2012 on libraries \u0026 archives! Have you been to ours in the Int'l Term? http://t.co/BEqoRzSx",
    "wof:placetype": "custom"
  },
  "geometry": {"coordinates":[-122.386166,37.616356],"type":"Point"}
}
