{
  "type": "Feature",
  "properties": {
    "date:cessation_lower":"2012-08-10",
    "date:cessation_upper":"2012-08-10",
    "date:inception_lower":"2012-08-10",
    "date:inception_upper":"2012-08-10",
    "iso:country":"US",
    "sfomuseum:placetype":"tweet",
    "twitter:tweet":{
        "created":1344622785,
        "created_at":"Fri Aug 10 18:19:45 +0000 2012",
        "display_text_range":[
            "0",
            "132"
        ],
        "entities":{
            "hashtags":[
                {
                    "indices":[
                        "117",
                        "132"
                    ],
                    "text":"MuseumOlympics"
                }
            ],
            "urls":[
                {
                    "display_url":"bit.ly/RGbDJL",
                    "expanded_url":"http://bit.ly/RGbDJL",
                    "indices":[
                        "96",
                        "116"
                    ],
                    "url":"http://t.co/q7d0yuw2"
                }
            ]
        },
        "favorite_count":"0",
        "favorited":false,
        "full_text":"Ohhh, a slight wobble in his landing subtracts a point from the Decorator Crab's overall score: http://t.co/q7d0yuw2 #MuseumOlympics",
        "id_str":"233991038329577472",
        "lang":"en",
        "possibly_sensitive":false,
        "retweet_count":"0",
        "retweeted":false,
        "source":"<a href=\"https://about.twitter.com/products/tweetdeck\" rel=\"nofollow\">TweetDeck</a>",
        "truncated":false
    },
    "wof:name":"Ohhh, a slight wobble in his landing subtracts a point from the Decorator Crab's overall score: http://t.co/q7d0yuw2 #MuseumOlympics",
    "wof:placetype":"custom"
},
  "geometry": {"coordinates":[-122.386166,37.616356],"type":"Point"}
}