{
  "type": "Feature",
  "properties": {
    "sfomuseum:placetype": "tweet",
    "twitter:tweet": {
      "created": 1412986510,
      "created_at": "Sat Oct 11 00:15:10 +0000 2014",
      "display_text_range": [
        "0", 
        "82"
      ],
      "entities": {
        "hashtags": [
          {
            "indices": [
              "5", 
              "10"
            ],
            "text": "TGIF"
          }, 
          {
            "indices": [
              "12", 
              "26"
            ],
            "text": "OrangeOctober"
          }, 
          {
            "indices": [
              "31", 
              "39"
            ],
            "text": "avgeeks"
          }, 
          {
            "indices": [
              "72", 
              "81"
            ],
            "text": "GoGiants"
          }
        ],
        "urls": [
          {
            "display_url": "ow.ly/CAOm4",
            "expanded_url": "http://ow.ly/CAOm4",
            "indices": [
              "49", 
              "71"
            ],
            "url": "http://t.co/6NrFn9Y5lv"
          }
        ]
      },
      "favorite_count": "1",
      "favorited": false,
      "full_text": "When #TGIF, #OrangeOctober and #avgeeks combine: http://t.co/6NrFn9Y5lv #GoGiants!",
      "id_str": "520729281522319360",
      "lang": "en",
      "possibly_sensitive": false,
      "retweet_count": "0",
      "retweeted": false,
      "source": "\u003ca href=\"http://www.hootsuite.com\" rel=\"nofollow\"\u003eHootsuite\u003c/a\u003e",
      "truncated": false
    },
    "wof:name": "Twitter message #520729281522319360",
    "wof:placetype": "custom"
  },
  "geometry": {"coordinates":[-122.386166,37.616356],"type":"Point"}
}
