{
  "type": "Feature",
  "properties": {
    "date:cessation_lower": "2022-08-18",
    "date:cessation_upper": "2022-08-18",
    "date:inception_lower": "2022-08-18",
    "date:inception_upper": "2022-08-18",
    "sfomuseum:placetype": "tweet",
    "twitter:tweet": {
      "created": 1660865466,
      "created_at": "Thu Aug 18 23:31:06 +0000 2022",
      "display_text_range": [
        "0",
        "143"
      ],
      "edit_info": {
        "initial": {
          "editTweetIds": [
            "1560408982040129536"
          ],
          "editableUntil": "2022-08-19T00:01:06.000Z",
          "editsRemaining": "5",
          "isEditEligible": false
        }
      },
      "entities": {
      },
      "favorite_count": "1",
      "favorited": false,
      "full_text": "📸 1/3:\nbrochure: Pan American World Airways, Boeing 707; 1958\nGift of David A. Abercrombie in memory of Stanley A. Abercrombie\n2001.039.235 a d",
      "id_str": "1560408982040129536",
      "in_reply_to_screen_name": "SFOMuseum",
      "in_reply_to_status_id": "1560408979531935745",
      "in_reply_to_status_id_str": "1560408979531935745",
      "in_reply_to_user_id": "116329337",
      "in_reply_to_user_id_str": "116329337",
      "lang": "en",
      "retweet_count": "0",
      "retweeted": false,
      "source": "\u003ca href=\"https://mobile.twitter.com\" rel=\"nofollow\"\u003eTwitter Web App\u003c/a\u003e",
      "truncated": false
    },
    "wof:name": "📸 1/3:\nbrochure: Pan American World Airways, Boeing 707; 1958\nGift of David A. Abercrombie in memory of Stanley A. Abercrombie\n2001.039.235 a d",
    "wof:placetype": "custom",
    "wof:placetype_alt": [
      "tweet"
    ]
  },
  "geometry": {"coordinates":[-122.386166,37.616356],"type":"Point"}
}
