{
  "type": "Feature",
  "properties": {
    "date:cessation_lower": "2012-03-02",
    "date:cessation_upper": "2012-03-02",
    "date:inception_lower": "2012-03-02",
    "date:inception_upper": "2012-03-02",
    "iso:country": "US",
    "sfomuseum:placetype": "tweet",
    "twitter:tweet": {
      "created": 1330721881,
      "created_at": "Fri Mar 02 20:58:01 +0000 2012",
      "display_text_range": [
        "0",
        "28"
      ],
      "edit_info": {
        "initial": {
          "editTweetIds": [
            "175686421464625152"
          ],
          "editableUntil": "2012-03-02T21:28:01.630Z",
          "editsRemaining": "5",
          "isEditEligible": true
        }
      },
      "entities": {
        "user_mentions": [
          {
            "id_str": "111394227",
            "indices": [
              "0",
              "13"
            ],
            "name": "Marin History Museum",
            "screen_name": "MarinHistory"
          }
        ]
      },
      "favorite_count": "0",
      "favorited": false,
      "full_text": "@MarinHistory Ha! Good one!!",
      "id_str": "175686421464625152",
      "in_reply_to_screen_name": "MarinHistory",
      "in_reply_to_status_id": "175683794458775554",
      "in_reply_to_status_id_str": "175683794458775554",
      "in_reply_to_user_id": "111394227",
      "in_reply_to_user_id_str": "111394227",
      "lang": "en",
      "retweet_count": "0",
      "retweeted": false,
      "source": "\u003ca href=\"http://twitter.com/download/iphone\" rel=\"nofollow\"\u003eTwitter for iPhone\u003c/a\u003e",
      "truncated": false
    },
    "wof:name": "@MarinHistory Ha! Good one!!",
    "wof:placetype": "custom"
  },
  "geometry": {"coordinates":[-122.386166,37.616356],"type":"Point"}
}
