{
  "type": "Feature",
  "properties": {
    "sfomuseum:placetype": "tweet",
    "twitter:tweet": {
      "created": 1504836013,
      "created_at": "Fri Sep 08 02:00:13 +0000 2017",
      "display_text_range": [
        "0", 
        "155"
      ],
      "entities": {
        "media": [
          {
            "display_url": "pic.twitter.com/NCX4B4vpJP",
            "expanded_url": "https://twitter.com/SFOMuseum/status/905974019781996544/photo/1",
            "id_str": "905974015457681408",
            "indices": [
              "132", 
              "155"
            ],
            "media_url": "http://pbs.twimg.com/media/DJKqkScW4AAyYhU.jpg",
            "media_url_https": "https://pbs.twimg.com/media/DJKqkScW4AAyYhU.jpg",
            "sizes": {
              "large": {
                "h": "2000",
                "resize": "fit",
                "w": "1426"
              },
              "medium": {
                "h": "1200",
                "resize": "fit",
                "w": "856"
              },
              "small": {
                "h": "680",
                "resize": "fit",
                "w": "485"
              },
              "thumb": {
                "h": "150",
                "resize": "crop",
                "w": "150"
              }
            },
            "type": "photo",
            "url": "https://t.co/NCX4B4vpJP"
          }
        ]
      },
      "extended_entities": {
        "media": [
          {
            "display_url": "pic.twitter.com/NCX4B4vpJP",
            "expanded_url": "https://twitter.com/SFOMuseum/status/905974019781996544/photo/1",
            "id_str": "905974015457681408",
            "indices": [
              "132", 
              "155"
            ],
            "media_url": "http://pbs.twimg.com/media/DJKqkScW4AAyYhU.jpg",
            "media_url_https": "https://pbs.twimg.com/media/DJKqkScW4AAyYhU.jpg",
            "sizes": {
              "large": {
                "h": "2000",
                "resize": "fit",
                "w": "1426"
              },
              "medium": {
                "h": "1200",
                "resize": "fit",
                "w": "856"
              },
              "small": {
                "h": "680",
                "resize": "fit",
                "w": "485"
              },
              "thumb": {
                "h": "150",
                "resize": "crop",
                "w": "150"
              }
            },
            "type": "photo",
            "url": "https://t.co/NCX4B4vpJP"
          }
        ]
      },
      "favorite_count": "1",
      "favorited": false,
      "full_text": "Barker composes images that seek to visually overwhelm, while educating the public about the detrimental effects of marine plastic. https://t.co/NCX4B4vpJP",
      "id_str": "905974019781996544",
      "lang": "en",
      "possibly_sensitive": false,
      "retweet_count": "1",
      "retweeted": false,
      "source": "\u003ca href=\"http://www.hootsuite.com\" rel=\"nofollow\"\u003eHootsuite\u003c/a\u003e",
      "truncated": false
    },
    "wof:name": "Twitter message #905974019781996544",
    "wof:placetype": "custom"
  },
  "geometry": {"coordinates":[-122.386166,37.616356],"type":"Point"}
}
