{
  "type": "Feature",
  "properties": {
    "date:cessation_lower": "2014-02-24",
    "date:cessation_upper": "2014-02-24",
    "date:inception_lower": "2014-02-24",
    "date:inception_upper": "2014-02-24",
    "iso:country": "US",
    "sfomuseum:placetype": "tweet",
    "twitter:tweet": {
      "created": 1393261540,
      "created_at": "Mon Feb 24 17:05:40 +0000 2014",
      "display_text_range": [
        "0",
        "140"
      ],
      "edit_info": {
        "initial": {
          "editTweetIds": [
            "437996764109754368"
          ],
          "editableUntil": "2014-02-24T18:05:40.807Z",
          "editsRemaining": "5",
          "isEditEligible": true
        }
      },
      "entities": {
        "user_mentions": [
          {
            "id_str": "20218070",
            "indices": [
              "3",
              "17"
            ],
            "name": "Richard Adler",
            "screen_name": "reallyrichard"
          }
        ]
      },
      "favorite_count": "0",
      "favorited": false,
      "full_text": "RT @reallyrichard: Arrived at SFO to find a wonderful exhibit of Japanese toys, from robots and Ultramen and Godzillas to Hello Kitties htt…",
      "id_str": "437996764109754368",
      "lang": "en",
      "retweet_count": "0",
      "retweeted": false,
      "source": "\u003ca href=\"http://www.hootsuite.com\" rel=\"nofollow\"\u003eHootsuite\u003c/a\u003e",
      "truncated": false
    },
    "twitter:user_mentions": [
      "reallyrichard"
    ],
    "wof:name": "RT @reallyrichard: Arrived at SFO to find a wonderful exhibit of Japanese toys, from robots and Ultramen and Godzillas to Hello Kitties htt…",
    "wof:placetype": "custom",
    "wof:placetype_alt": [
      "tweet"
    ]
  },
  "geometry": {"coordinates":[-122.386166,37.616356],"type":"Point"}
}
