{
  "type": "Feature",
  "properties": {
    "sfomuseum:placetype": "tweet",
    "twitter:tweet": {
      "created": 1462417810,
      "created_at": "Thu May 05 03:10:10 +0000 2016",
      "display_text_range": [
        "0", 
        "140"
      ],
      "entities": {
        "hashtags": [
          {
            "indices": [
              "0", 
              "10"
            ],
            "text": "SneakPeek"
          }, 
          {
            "indices": [
              "100", 
              "116"
            ],
            "text": "FashionInFlight"
          }
        ],
        "media": [
          {
            "display_url": "pic.twitter.com/ZUqNulFClm",
            "expanded_url": "https://twitter.com/SFOMuseum/status/728059181077549056/photo/1",
            "id_str": "728059179898961920",
            "indices": [
              "117", 
              "140"
            ],
            "media_url": "http://pbs.twimg.com/media/ChqV93lXAAAJV2B.jpg",
            "media_url_https": "https://pbs.twimg.com/media/ChqV93lXAAAJV2B.jpg",
            "sizes": {
              "large": {
                "h": "2048",
                "resize": "fit",
                "w": "1536"
              },
              "medium": {
                "h": "1200",
                "resize": "fit",
                "w": "900"
              },
              "small": {
                "h": "680",
                "resize": "fit",
                "w": "510"
              },
              "thumb": {
                "h": "150",
                "resize": "crop",
                "w": "150"
              }
            },
            "type": "photo",
            "url": "https://t.co/ZUqNulFClm"
          }
        ]
      },
      "extended_entities": {
        "media": [
          {
            "display_url": "pic.twitter.com/ZUqNulFClm",
            "expanded_url": "https://twitter.com/SFOMuseum/status/728059181077549056/photo/1",
            "id_str": "728059179898961920",
            "indices": [
              "117", 
              "140"
            ],
            "media_url": "http://pbs.twimg.com/media/ChqV93lXAAAJV2B.jpg",
            "media_url_https": "https://pbs.twimg.com/media/ChqV93lXAAAJV2B.jpg",
            "sizes": {
              "large": {
                "h": "2048",
                "resize": "fit",
                "w": "1536"
              },
              "medium": {
                "h": "1200",
                "resize": "fit",
                "w": "900"
              },
              "small": {
                "h": "680",
                "resize": "fit",
                "w": "510"
              },
              "thumb": {
                "h": "150",
                "resize": "crop",
                "w": "150"
              }
            },
            "type": "photo",
            "url": "https://t.co/ZUqNulFClm"
          }
        ]
      },
      "favorite_count": "5",
      "favorited": false,
      "full_text": "#SneakPeek! What's going on in the Design Lab? Some uniforms being prepped for an upcoming exhibit! #FashionInFlight https://t.co/ZUqNulFClm",
      "id_str": "728059181077549056",
      "lang": "en",
      "possibly_sensitive": false,
      "retweet_count": "1",
      "retweeted": false,
      "source": "\u003ca href=\"http://www.hootsuite.com\" rel=\"nofollow\"\u003eHootsuite\u003c/a\u003e",
      "truncated": false
    },
    "wof:name": "Twitter message #728059181077549056",
    "wof:placetype": "custom"
  },
  "geometry": {"coordinates":[-122.386166,37.616356],"type":"Point"}
}
