{
  "type": "Feature",
  "properties": {
    "date:cessation_lower": "2014-09-19",
    "date:cessation_upper": "2014-09-19",
    "date:inception_lower": "2014-09-19",
    "date:inception_upper": "2014-09-19",
    "iso:country": "US",
    "sfomuseum:placetype": "tweet",
    "twitter:hashtags": [
      "AdIcons",
      "octopus",
      "tgif"
    ],
    "twitter:tweet": {
      "created": 1411164094,
      "created_at": "Fri Sep 19 22:01:34 +0000 2014",
      "display_text_range": [
        "0",
        "128"
      ],
      "edit_info": {
        "initial": {
          "editTweetIds": [
            "513085518125756416"
          ],
          "editableUntil": "2014-09-19T23:01:34.846Z",
          "editsRemaining": "5",
          "isEditEligible": true
        }
      },
      "entities": {
        "hashtags": [
          {
            "indices": [
              "82",
              "90"
            ],
            "text": "AdIcons"
          },
          {
            "indices": [
              "91",
              "99"
            ],
            "text": "octopus"
          },
          {
            "indices": [
              "100",
              "105"
            ],
            "text": "tgif"
          }
        ],
        "urls": [
          {
            "display_url": "instagram.com/p/tJKJQsxkxM/",
            "expanded_url": "http://instagram.com/p/tJKJQsxkxM/",
            "indices": [
              "106",
              "128"
            ],
            "url": "http://t.co/6lZbcgw1d3"
          }
        ]
      },
      "favorite_count": "0",
      "favorited": false,
      "full_text": "And some days, it would be nice to have as many arms as Octopus Car Wash's Ozzie. #AdIcons #octopus #tgif http://t.co/6lZbcgw1d3",
      "id_str": "513085518125756416",
      "lang": "en",
      "possibly_sensitive": false,
      "retweet_count": "0",
      "retweeted": false,
      "source": "\u003ca href=\"http://instagram.com\" rel=\"nofollow\"\u003eInstagram\u003c/a\u003e",
      "truncated": false
    },
    "wof:name": "And some days, it would be nice to have as many arms as Octopus Car Wash's Ozzie. #AdIcons #octopus #tgif http://t.co/6lZbcgw1d3",
    "wof:placetype": "custom",
    "wof:placetype_alt": [
      "tweet"
    ]
  },
  "geometry": {"coordinates":[-122.386166,37.616356],"type":"Point"}
}
