{
  "type": "Feature",
  "properties": {
    "date:cessation_lower": "2022-04-14",
    "date:cessation_upper": "2022-04-14",
    "date:inception_lower": "2022-04-14",
    "date:inception_upper": "2022-04-14",
    "sfomuseum:placetype": "tweet",
    "twitter:tweet": {
      "created": 1649976189,
      "created_at": "Thu Apr 14 22:43:09 +0000 2022",
      "display_text_range": [
        "0",
        "240"
      ],
      "edit_info": {
        "initial": {
          "editTweetIds": [
            "1514736042900815898"
          ],
          "editableUntil": "2022-04-14T23:13:09.719Z",
          "editsRemaining": "5",
          "isEditEligible": true
        }
      },
      "entities": {
        "hashtags": [
          {
            "indices": [
              "216",
              "226"
            ],
            "text": "VideoArts"
          },
          {
            "indices": [
              "227",
              "240"
            ],
            "text": "VideoArtsSFO"
          }
        ],
        "urls": [
          {
            "display_url": "bit.ly/3wTo6U4",
            "expanded_url": "https://bit.ly/3wTo6U4",
            "indices": [
              "192",
              "215"
            ],
            "url": "https://t.co/s4Vm0Hmoua"
          }
        ]
      },
      "favorite_count": "1",
      "favorited": false,
      "full_text": "See “Righteous Energy” by Maria Constanza Ferreira in the Video Arts Gallery, located pre-security in the International Terminal with daily operating hours of 5:00am to 10:00pm, or online at: https://t.co/s4Vm0Hmoua #VideoArts #VideoArtsSFO",
      "id_str": "1514736042900815898",
      "in_reply_to_screen_name": "SFOMuseum",
      "in_reply_to_status_id": "1514736038807175182",
      "in_reply_to_status_id_str": "1514736038807175182",
      "in_reply_to_user_id": "116329337",
      "in_reply_to_user_id_str": "116329337",
      "lang": "en",
      "possibly_sensitive": false,
      "retweet_count": "0",
      "retweeted": false,
      "source": "\u003ca href=\"https://mobile.twitter.com\" rel=\"nofollow\"\u003eTwitter Web App\u003c/a\u003e",
      "truncated": false
    },
    "wof:name": "See “Righteous Energy” by Maria Constanza Ferreira in the Video Arts Gallery, located pre-security in the International Terminal with daily operating hours of 5:00am to 10:00pm, or online at: https://t.co/s4Vm0Hmoua #VideoArts #VideoArtsSFO",
    "wof:placetype": "custom"
  },
  "geometry": {"coordinates":[-122.386166,37.616356],"type":"Point"}
}
