{
  "type": "Feature",
  "properties": {
    "date:cessation_lower":"2013-03-11",
    "date:cessation_upper":"2013-03-11",
    "date:inception_lower":"2013-03-11",
    "date:inception_upper":"2013-03-11",
    "iso:country":"US",
    "sfomuseum:placetype":"tweet",
    "twitter:tweet":{
        "created":1363019753,
        "created_at":"Mon Mar 11 16:35:53 +0000 2013",
        "display_text_range":[
            "0",
            "139"
        ],
        "entities":{
            "urls":[
                {
                    "display_url":"bit.ly/pxjjvO",
                    "expanded_url":"http://bit.ly/pxjjvO",
                    "indices":[
                        "117",
                        "139"
                    ],
                    "url":"http://t.co/tixRpjcPKl"
                }
            ]
        },
        "favorite_count":"1",
        "favorited":false,
        "full_text":"We have 2 new photo shows! T3 pssngrs can see Robert B. Taylor: Rural California 1975-2013. Not flying? It's online: http://t.co/tixRpjcPKl",
        "id_str":"311153516100063232",
        "lang":"en",
        "possibly_sensitive":false,
        "retweet_count":"3",
        "retweeted":false,
        "source":"<a href=\"https://about.twitter.com/products/tweetdeck\" rel=\"nofollow\">TweetDeck</a>",
        "truncated":false
    },
    "wof:name":"We have 2 new photo shows! T3 pssngrs can see Robert B. Taylor: Rural California 1975-2013. Not flying? It's online: http://t.co/tixRpjcPKl",
    "wof:placetype":"custom"
},
  "geometry": {"coordinates":[-122.386166,37.616356],"type":"Point"}
}