{
  "type": "Feature",
  "properties": {
    "sfomuseum:placetype": "tweet",
    "twitter:tweet": {
      "created": 1507324512,
      "created_at": "Fri Oct 06 21:15:12 +0000 2017",
      "display_text_range": [
        "0", 
        "158"
      ],
      "entities": {
        "media": [
          {
            "display_url": "pic.twitter.com/yaFKV4ZC98",
            "expanded_url": "https://twitter.com/SFOMuseum/status/916411542073171968/photo/1",
            "id_str": "916411538935861249",
            "indices": [
              "135", 
              "158"
            ],
            "media_url": "http://pbs.twimg.com/media/DLe_cHZXUAERdUZ.jpg",
            "media_url_https": "https://pbs.twimg.com/media/DLe_cHZXUAERdUZ.jpg",
            "sizes": {
              "large": {
                "h": "1951",
                "resize": "fit",
                "w": "2000"
              },
              "medium": {
                "h": "1171",
                "resize": "fit",
                "w": "1200"
              },
              "small": {
                "h": "663",
                "resize": "fit",
                "w": "680"
              },
              "thumb": {
                "h": "150",
                "resize": "crop",
                "w": "150"
              }
            },
            "type": "photo",
            "url": "https://t.co/yaFKV4ZC98"
          }
        ]
      },
      "extended_entities": {
        "media": [
          {
            "display_url": "pic.twitter.com/yaFKV4ZC98",
            "expanded_url": "https://twitter.com/SFOMuseum/status/916411542073171968/photo/1",
            "id_str": "916411538935861249",
            "indices": [
              "135", 
              "158"
            ],
            "media_url": "http://pbs.twimg.com/media/DLe_cHZXUAERdUZ.jpg",
            "media_url_https": "https://pbs.twimg.com/media/DLe_cHZXUAERdUZ.jpg",
            "sizes": {
              "large": {
                "h": "1951",
                "resize": "fit",
                "w": "2000"
              },
              "medium": {
                "h": "1171",
                "resize": "fit",
                "w": "1200"
              },
              "small": {
                "h": "663",
                "resize": "fit",
                "w": "680"
              },
              "thumb": {
                "h": "150",
                "resize": "crop",
                "w": "150"
              }
            },
            "type": "photo",
            "url": "https://t.co/yaFKV4ZC98"
          }
        ]
      },
      "favorite_count": "5",
      "favorited": false,
      "full_text": "“I used to go ‘round to Aunt Mimi’s house and John would be at the typewriter, which was fairly unusual in Liverpool.\" —Paul McCartney https://t.co/yaFKV4ZC98",
      "id_str": "916411542073171968",
      "lang": "en",
      "possibly_sensitive": false,
      "retweet_count": "0",
      "retweeted": false,
      "source": "\u003ca href=\"http://www.hootsuite.com\" rel=\"nofollow\"\u003eHootsuite\u003c/a\u003e",
      "truncated": false
    },
    "wof:name": "Twitter message #916411542073171968",
    "wof:placetype": "custom"
  },
  "geometry": {"coordinates":[-122.386166,37.616356],"type":"Point"}
}
