{
  "type": "Feature",
  "properties": {
    "date:cessation_lower": "2020-02-05",
    "date:cessation_upper": "2020-02-05",
    "date:inception_lower": "2020-02-05",
    "date:inception_upper": "2020-02-05",
    "iso:country": "US",
    "sfomuseum:placetype": "tweet",
    "twitter:tweet": {
      "created": 1580947091,
      "created_at": "Wed Feb 05 23:58:11 +0000 2020",
      "display_text_range": [
        "0",
        "106"
      ],
      "entities": {
        "user_mentions": [
          {
            "id_str": "19062784",
            "indices": [
              "0",
              "6"
            ],
            "name": "Max Beverton-Palmer",
            "screen_name": "Maxjb"
          }
        ]
      },
      "favorite_count": "1",
      "favorited": false,
      "full_text": "@Maxjb Thanks so much for stopping by! We hope you enjoyed your visit! Did you have a favorite exhibition?",
      "id_str": "1225207022053810176",
      "in_reply_to_screen_name": "Maxjb",
      "in_reply_to_status_id": "1225201738648576003",
      "in_reply_to_status_id_str": "1225201738648576003",
      "in_reply_to_user_id": "19062784",
      "in_reply_to_user_id_str": "19062784",
      "lang": "en",
      "retweet_count": "0",
      "retweeted": false,
      "source": "\u003ca href=\"https://mobile.twitter.com\" rel=\"nofollow\"\u003eTwitter Web App\u003c/a\u003e",
      "truncated": false
    },
    "wof:name": "@Maxjb Thanks so much for stopping by! We hope you enjoyed your visit! Did you have a favorite exhibition?",
    "wof:placetype": "custom"
  },
  "geometry": {"coordinates":[-122.386166,37.616356],"type":"Point"}
}
