{
  "type": "Feature",
  "properties": {
    "sfomuseum:placetype": "tweet",
    "twitter:tweet": {
      "created": 1402332978,
      "created_at": "Mon Jun 09 16:56:18 +0000 2014",
      "display_text_range": [
        "0", 
        "48"
      ],
      "entities": {
        "user_mentions": [
          {
            "id_str": "513699167",
            "indices": [
              "0", 
              "12"
            ],
            "name": "Alli Burness",
            "screen_name": "alli_burnie"
          }
        ]
      },
      "favorite_count": "0",
      "favorited": false,
      "full_text": "@Alli_Burnie Thanks for visiting \u0026amp; tweeting!",
      "id_str": "476045133142839297",
      "in_reply_to_screen_name": "alli_burnie",
      "in_reply_to_status_id": "475359309355040768",
      "in_reply_to_status_id_str": "475359309355040768",
      "in_reply_to_user_id": "513699167",
      "in_reply_to_user_id_str": "513699167",
      "lang": "en",
      "retweet_count": "0",
      "retweeted": false,
      "source": "\u003ca href=\"http://www.hootsuite.com\" rel=\"nofollow\"\u003eHootsuite\u003c/a\u003e",
      "truncated": false
    },
    "wof:name": "Twitter message #476045133142839297",
    "wof:placetype": "custom"
  },
  "geometry": {"coordinates":[-122.386166,37.616356],"type":"Point"}
}
