{
  "type": "Feature",
  "properties": {
    "sfomuseum:placetype": "tweet",
    "twitter:tweet": {
      "created": 1445642719,
      "created_at": "Fri Oct 23 23:25:19 +0000 2015",
      "display_text_range": [
        "0", 
        "134"
      ],
      "entities": {
        "hashtags": [
          {
            "indices": [
              "94", 
              "110"
            ],
            "text": "FlashbackFriday"
          }
        ],
        "media": [
          {
            "display_url": "pic.twitter.com/2SlaXoj8Su",
            "expanded_url": "https://twitter.com/SFOMuseum/status/657699352127918080/photo/1",
            "id_str": "657699351783845888",
            "indices": [
              "111", 
              "134"
            ],
            "media_url": "http://pbs.twimg.com/media/CSCeE2gUsAAYrde.jpg",
            "media_url_https": "https://pbs.twimg.com/media/CSCeE2gUsAAYrde.jpg",
            "sizes": {
              "large": {
                "h": "402",
                "resize": "fit",
                "w": "618"
              },
              "medium": {
                "h": "402",
                "resize": "fit",
                "w": "618"
              },
              "small": {
                "h": "402",
                "resize": "fit",
                "w": "618"
              },
              "thumb": {
                "h": "150",
                "resize": "crop",
                "w": "150"
              }
            },
            "type": "photo",
            "url": "https://t.co/2SlaXoj8Su"
          }
        ]
      },
      "extended_entities": {
        "media": [
          {
            "display_url": "pic.twitter.com/2SlaXoj8Su",
            "expanded_url": "https://twitter.com/SFOMuseum/status/657699352127918080/photo/1",
            "id_str": "657699351783845888",
            "indices": [
              "111", 
              "134"
            ],
            "media_url": "http://pbs.twimg.com/media/CSCeE2gUsAAYrde.jpg",
            "media_url_https": "https://pbs.twimg.com/media/CSCeE2gUsAAYrde.jpg",
            "sizes": {
              "large": {
                "h": "402",
                "resize": "fit",
                "w": "618"
              },
              "medium": {
                "h": "402",
                "resize": "fit",
                "w": "618"
              },
              "small": {
                "h": "402",
                "resize": "fit",
                "w": "618"
              },
              "thumb": {
                "h": "150",
                "resize": "crop",
                "w": "150"
              }
            },
            "type": "photo",
            "url": "https://t.co/2SlaXoj8Su"
          }
        ]
      },
      "favorite_count": "0",
      "favorited": false,
      "full_text": "United and TWA were among the airlines that used DC-3s at San Francisco Airport in the 1930s. #FlashbackFriday https://t.co/2SlaXoj8Su",
      "id_str": "657699352127918080",
      "lang": "en",
      "possibly_sensitive": false,
      "retweet_count": "0",
      "retweeted": false,
      "source": "\u003ca href=\"http://www.hootsuite.com\" rel=\"nofollow\"\u003eHootsuite\u003c/a\u003e",
      "truncated": false
    },
    "wof:name": "Twitter message #657699352127918080",
    "wof:placetype": "custom"
  },
  "geometry": {"coordinates":[-122.386166,37.616356],"type":"Point"}
}
