{
  "type": "Feature",
  "properties": {
    "date:cessation_lower": "2013-05-24",
    "date:cessation_upper": "2013-05-24",
    "date:inception_lower": "2013-05-24",
    "date:inception_upper": "2013-05-24",
    "iso:country": "US",
    "sfomuseum:placetype": "tweet",
    "twitter:hashtags": [
      "PanAm"
    ],
    "twitter:tweet": {
      "created": 1369426604,
      "created_at": "Fri May 24 20:16:44 +0000 2013",
      "display_text_range": [
        "0",
        "146"
      ],
      "edit_info": {
        "initial": {
          "editTweetIds": [
            "338025796214087681"
          ],
          "editableUntil": "2013-05-24T21:16:44.690Z",
          "editsRemaining": "5",
          "isEditEligible": true
        }
      },
      "entities": {
        "hashtags": [
          {
            "indices": [
              "58",
              "64"
            ],
            "text": "PanAm"
          }
        ],
        "urls": [
          {
            "display_url": "ow.ly/lnuzL",
            "expanded_url": "http://ow.ly/lnuzL",
            "indices": [
              "124",
              "146"
            ],
            "url": "http://t.co/NsR0HpOG3V"
          }
        ]
      },
      "favorite_count": "0",
      "favorited": false,
      "full_text": "Helicopter service was a perk for 1st \u0026amp; Clipper class #PanAm pssngrs at the iconic \u0026amp; now-closed Worldport Terminal. http://t.co/NsR0HpOG3V",
      "id_str": "338025796214087681",
      "lang": "en",
      "possibly_sensitive": false,
      "retweet_count": "0",
      "retweeted": false,
      "source": "\u003ca href=\"http://www.hootsuite.com\" rel=\"nofollow\"\u003eHootsuite\u003c/a\u003e",
      "truncated": false
    },
    "wof:name": "Helicopter service was a perk for 1st \u0026amp; Clipper class #PanAm pssngrs at the iconic \u0026amp; now-closed Worldport Terminal. http://t.co/NsR0HpOG3V",
    "wof:placetype": "custom"
  },
  "geometry": {"coordinates":[-122.386166,37.616356],"type":"Point"}
}
