{
  "type": "Feature",
  "properties": {
    "sfomuseum:placetype": "tweet",
    "twitter:tweet": {
      "created": 1339457140,
      "created_at": "Mon Jun 11 23:25:40 +0000 2012",
      "display_text_range": [
        "0", 
        "106"
      ],
      "entities": {
        "urls": [
          {
            "display_url": "fb.me/ReiHklc8",
            "expanded_url": "http://fb.me/ReiHklc8",
            "indices": [
              "86", 
              "106"
            ],
            "url": "http://t.co/M1vJrSke"
          }
        ],
        "user_mentions": [
          {
            "id_str": "557415629",
            "indices": [
              "16", 
              "28"
            ],
            "name": "Maria Leung",
            "screen_name": "Maria_Leung"
          }
        ]
      },
      "favorite_count": "0",
      "favorited": false,
      "full_text": "Awesome sketch, @Maria_Leung! Spot on drawing of Nance O'Banion's \"Billboard Series\"! http://t.co/M1vJrSke",
      "id_str": "212324752465993729",
      "in_reply_to_screen_name": "Maria_Leung",
      "in_reply_to_status_id": "212041826272690176",
      "in_reply_to_status_id_str": "212041826272690176",
      "in_reply_to_user_id": "557415629",
      "in_reply_to_user_id_str": "557415629",
      "lang": "en",
      "possibly_sensitive": false,
      "retweet_count": "0",
      "retweeted": false,
      "source": "\u003ca href=\"http://www.hootsuite.com\" rel=\"nofollow\"\u003eHootsuite\u003c/a\u003e",
      "truncated": false
    },
    "wof:name": "Twitter message #212324752465993729",
    "wof:placetype": "custom"
  },
  "geometry": {"coordinates":[-122.386166,37.616356],"type":"Point"}
}
