{
  "type": "Feature",
  "properties": {
    "sfomuseum:placetype": "tweet",
    "twitter:tweet": {
      "created": 1417825399,
      "created_at": "Sat Dec 06 00:23:19 +0000 2014",
      "display_text_range": [
        "0", 
        "79"
      ],
      "entities": {
        "hashtags": [
          {
            "indices": [
              "62", 
              "67"
            ],
            "text": "TGIF"
          }, 
          {
            "indices": [
              "68", 
              "79"
            ],
            "text": "RockPoster"
          }
        ],
        "urls": [
          {
            "display_url": "ow.ly/Fscyt",
            "expanded_url": "http://ow.ly/Fscyt",
            "indices": [
              "39", 
              "61"
            ],
            "url": "http://t.co/Neenj7WAtY"
          }
        ]
      },
      "favorite_count": "0",
      "favorited": false,
      "full_text": "Rock out and stay groovy this weekend! http://t.co/Neenj7WAtY #TGIF #RockPoster",
      "id_str": "541025055724298240",
      "lang": "en",
      "possibly_sensitive": false,
      "retweet_count": "0",
      "retweeted": false,
      "source": "\u003ca href=\"http://www.hootsuite.com\" rel=\"nofollow\"\u003eHootsuite\u003c/a\u003e",
      "truncated": false
    },
    "wof:name": "Twitter message #541025055724298240",
    "wof:placetype": "custom"
  },
  "geometry": {"coordinates":[-122.386166,37.616356],"type":"Point"}
}
