{
  "type": "Feature",
  "properties": {
    "date:cessation_lower": "2024-03-30",
    "date:cessation_upper": "2024-03-30",
    "date:inception_lower": "2024-03-30",
    "date:inception_upper": "2024-03-30",
    "sfomuseum:placetype": "tweet",
    "twitter:tweet": {
      "created": 1711758995,
      "created_at": "Sat Mar 30 00:36:35 +0000 2024",
      "display_text_range": [
        "0",
        "123"
      ],
      "edit_info": {
        "initial": {
          "editTweetIds": [
            "1773871912806158738"
          ],
          "editableUntil": "2024-03-30T01:36:35.000Z",
          "editsRemaining": "5",
          "isEditEligible": false
        }
      },
      "entities": {
        "urls": [
          {
            "display_url": "ow.ly/MBcG50R5f35",
            "expanded_url": "https://ow.ly/MBcG50R5f35",
            "indices": [
              "89",
              "112"
            ],
            "url": "https://t.co/XUzORAw309"
          }
        ]
      },
      "favorite_count": "0",
      "favorited": false,
      "full_text": "poster: La Conquete de l'Air, Le Petit Journal; 1909 \nSFO Museum Collection \n1997.61.01 \nhttps://t.co/XUzORAw309\n\n52Posters",
      "id_str": "1773871912806158738",
      "in_reply_to_screen_name": "SFOMuseum",
      "in_reply_to_status_id": "1773871909467550199",
      "in_reply_to_status_id_str": "1773871909467550199",
      "in_reply_to_user_id": "116329337",
      "in_reply_to_user_id_str": "116329337",
      "lang": "fr",
      "possibly_sensitive": false,
      "retweet_count": "0",
      "retweeted": false,
      "source": "\u003ca href=\"https://mobile.twitter.com\" rel=\"nofollow\"\u003eTwitter Web App\u003c/a\u003e",
      "truncated": false
    },
    "wof:name": "poster: La Conquete de l'Air, Le Petit Journal; 1909 \nSFO Museum Collection \n1997.61.01 \nhttps://t.co/XUzORAw309\n\n52Posters",
    "wof:placetype": "custom",
    "wof:placetype_alt": [
      "tweet"
    ]
  },
  "geometry": {"coordinates":[-122.386166,37.616356],"type":"Point"}
}
