{
  "type": "Feature",
  "properties": {
    "sfomuseum:placetype": "tweet",
    "twitter:tweet": {
      "created": 1499390705,
      "created_at": "Fri Jul 07 01:25:05 +0000 2017",
      "display_text_range": [
        "0", 
        "163"
      ],
      "entities": {
        "hashtags": [
          {
            "indices": [
              "122", 
              "139"
            ],
            "text": "sfoartsandcrafts"
          }
        ],
        "media": [
          {
            "display_url": "pic.twitter.com/1riA1njEke",
            "expanded_url": "https://twitter.com/SFOMuseum/status/883134743986016256/photo/1",
            "id_str": "883134740878024704",
            "indices": [
              "140", 
              "163"
            ],
            "media_url": "http://pbs.twimg.com/media/DEGGXibXYAA2fA3.jpg",
            "media_url_https": "https://pbs.twimg.com/media/DEGGXibXYAA2fA3.jpg",
            "sizes": {
              "large": {
                "h": "1473",
                "resize": "fit",
                "w": "2000"
              },
              "medium": {
                "h": "884",
                "resize": "fit",
                "w": "1200"
              },
              "small": {
                "h": "501",
                "resize": "fit",
                "w": "680"
              },
              "thumb": {
                "h": "150",
                "resize": "crop",
                "w": "150"
              }
            },
            "type": "photo",
            "url": "https://t.co/1riA1njEke"
          }
        ]
      },
      "extended_entities": {
        "media": [
          {
            "display_url": "pic.twitter.com/1riA1njEke",
            "expanded_url": "https://twitter.com/SFOMuseum/status/883134743986016256/photo/1",
            "id_str": "883134740878024704",
            "indices": [
              "140", 
              "163"
            ],
            "media_url": "http://pbs.twimg.com/media/DEGGXibXYAA2fA3.jpg",
            "media_url_https": "https://pbs.twimg.com/media/DEGGXibXYAA2fA3.jpg",
            "sizes": {
              "large": {
                "h": "1473",
                "resize": "fit",
                "w": "2000"
              },
              "medium": {
                "h": "884",
                "resize": "fit",
                "w": "1200"
              },
              "small": {
                "h": "501",
                "resize": "fit",
                "w": "680"
              },
              "thumb": {
                "h": "150",
                "resize": "crop",
                "w": "150"
              }
            },
            "type": "photo",
            "url": "https://t.co/1riA1njEke"
          }
        ]
      },
      "favorite_count": "2",
      "favorited": false,
      "full_text": "Repoussé is the centuries-old technique of creating motifs in metalwork by fine hammering on the surface’s opposite side. #sfoartsandcrafts https://t.co/1riA1njEke",
      "id_str": "883134743986016256",
      "lang": "en",
      "possibly_sensitive": false,
      "retweet_count": "1",
      "retweeted": false,
      "source": "\u003ca href=\"http://www.hootsuite.com\" rel=\"nofollow\"\u003eHootsuite\u003c/a\u003e",
      "truncated": false
    },
    "wof:name": "Twitter message #883134743986016256",
    "wof:placetype": "custom"
  },
  "geometry": {"coordinates":[-122.386166,37.616356],"type":"Point"}
}
