{
  "type": "Feature",
  "properties": {
    "sfomuseum:placetype": "tweet",
    "twitter:tweet": {
      "created": 1547258411,
      "created_at": "Sat Jan 12 02:00:11 +0000 2019",
      "display_text_range": [
        "0", 
        "286"
      ],
      "entities": {
        "hashtags": [
          {
            "indices": [
              "224", 
              "237"
            ],
            "text": "HamishDobbie"
          }, 
          {
            "indices": [
              "248", 
              "262"
            ],
            "text": "BritishSilver"
          }
        ],
        "media": [
          {
            "display_url": "pic.twitter.com/0GxHRKZ1KK",
            "expanded_url": "https://twitter.com/SFOMuseum/status/1083906456192135168/photo/1",
            "id_str": "1083906453700780032",
            "indices": [
              "263", 
              "286"
            ],
            "media_url": "http://pbs.twimg.com/media/DwrPLUaWoAAVSOX.jpg",
            "media_url_https": "https://pbs.twimg.com/media/DwrPLUaWoAAVSOX.jpg",
            "sizes": {
              "large": {
                "h": "1611",
                "resize": "fit",
                "w": "2000"
              },
              "medium": {
                "h": "967",
                "resize": "fit",
                "w": "1200"
              },
              "small": {
                "h": "548",
                "resize": "fit",
                "w": "680"
              },
              "thumb": {
                "h": "150",
                "resize": "crop",
                "w": "150"
              }
            },
            "type": "photo",
            "url": "https://t.co/0GxHRKZ1KK"
          }
        ]
      },
      "extended_entities": {
        "media": [
          {
            "display_url": "pic.twitter.com/0GxHRKZ1KK",
            "expanded_url": "https://twitter.com/SFOMuseum/status/1083906456192135168/photo/1",
            "id_str": "1083906453700780032",
            "indices": [
              "263", 
              "286"
            ],
            "media_url": "http://pbs.twimg.com/media/DwrPLUaWoAAVSOX.jpg",
            "media_url_https": "https://pbs.twimg.com/media/DwrPLUaWoAAVSOX.jpg",
            "sizes": {
              "large": {
                "h": "1611",
                "resize": "fit",
                "w": "2000"
              },
              "medium": {
                "h": "967",
                "resize": "fit",
                "w": "1200"
              },
              "small": {
                "h": "548",
                "resize": "fit",
                "w": "680"
              },
              "thumb": {
                "h": "150",
                "resize": "crop",
                "w": "150"
              }
            },
            "type": "photo",
            "url": "https://t.co/0GxHRKZ1KK"
          }
        ]
      },
      "favorite_count": "6",
      "favorited": false,
      "full_text": "\"In recent months, I have been moving closer to traditional silversmithing, but I'm still keen to combine this with advanced technology…to bridge the gap between the two different approaches so that they become integrated.\" #HamishDobbie (b. 1991) #BritishSilver https://t.co/0GxHRKZ1KK",
      "id_str": "1083906456192135168",
      "lang": "en",
      "possibly_sensitive": false,
      "retweet_count": "0",
      "retweeted": false,
      "source": "\u003ca href=\"https://www.hootsuite.com\" rel=\"nofollow\"\u003eHootsuite Inc.\u003c/a\u003e",
      "truncated": false
    },
    "wof:name": "Twitter message #1083906456192135168",
    "wof:placetype": "custom"
  },
  "geometry": {"coordinates":[-122.386166,37.616356],"type":"Point"}
}
