{
  "type": "Feature",
  "properties": {
    "sfomuseum:placetype": "tweet",
    "twitter:tweet": {
      "created": 1333575090,
      "created_at": "Wed Apr 04 21:31:30 +0000 2012",
      "display_text_range": [
        "0", 
        "135"
      ],
      "entities": {
        "urls": [
          {
            "display_url": "bit.ly/HlOaIb",
            "expanded_url": "http://bit.ly/HlOaIb",
            "indices": [
              "115", 
              "135"
            ],
            "url": "http://t.co/DFoqqXwI"
          }
        ]
      },
      "favorite_count": "0",
      "favorited": false,
      "full_text": "Axel Salto, on his art: \"These naturalistic models...were made to inhabit, almost covertly, the ceramic material.\" http://t.co/DFoqqXwI",
      "id_str": "187653644882161664",
      "lang": "en",
      "possibly_sensitive": false,
      "retweet_count": "0",
      "retweeted": false,
      "source": "\u003ca href=\"https://about.twitter.com/products/tweetdeck\" rel=\"nofollow\"\u003eTweetDeck\u003c/a\u003e",
      "truncated": false
    },
    "wof:name": "Twitter message #187653644882161664",
    "wof:placetype": "custom"
  },
  "geometry": {"coordinates":[-122.386166,37.616356],"type":"Point"}
}
