{
  "type": "Feature",
  "properties": {
    "sfomuseum:placetype": "tweet",
    "twitter:tweet": {
      "created": 1390585363,
      "created_at": "Fri Jan 24 17:42:43 +0000 2014",
      "display_text_range": [
        "0", 
        "139"
      ],
      "entities": {
        "urls": [
          {
            "display_url": "ow.ly/sV9s9",
            "expanded_url": "http://ow.ly/sV9s9",
            "indices": [
              "94", 
              "116"
            ],
            "url": "http://t.co/mKAzkxdmKb"
          }
        ],
        "user_mentions": [
          {
            "id_str": "86239754",
            "indices": [
              "0", 
              "9"
            ],
            "name": "Marcin Wichary",
            "screen_name": "mwichary"
          }, 
          {
            "id_str": "13248592",
            "indices": [
              "122", 
              "138"
            ],
            "name": "David Rumsey",
            "screen_name": "DavidRumseyMaps"
          }
        ]
      },
      "favorite_count": "0",
      "favorited": false,
      "full_text": "@mwichary Glad you enjoyed the exhibit! Select maps are on our website; high res via David's: http://t.co/mKAzkxdmKb (cc: @DavidRumseyMaps)",
      "id_str": "426772061714120704",
      "in_reply_to_screen_name": "mwichary",
      "in_reply_to_status_id": "426722963228868608",
      "in_reply_to_status_id_str": "426722963228868608",
      "in_reply_to_user_id": "86239754",
      "in_reply_to_user_id_str": "86239754",
      "lang": "en",
      "possibly_sensitive": false,
      "retweet_count": "0",
      "retweeted": false,
      "source": "\u003ca href=\"http://www.hootsuite.com\" rel=\"nofollow\"\u003eHootsuite\u003c/a\u003e",
      "truncated": false
    },
    "wof:name": "Twitter message #426772061714120704",
    "wof:placetype": "custom"
  },
  "geometry": {"coordinates":[-122.386166,37.616356],"type":"Point"}
}
