{
  "type": "Feature",
  "properties": {
    "sfomuseum:placetype": "tweet",
    "twitter:tweet": {
      "created": 1505358015,
      "created_at": "Thu Sep 14 03:00:15 +0000 2017",
      "display_text_range": [
        "0", 
        "131"
      ],
      "entities": {
        "hashtags": [
          {
            "indices": [
              "121", 
              "131"
            ],
            "text": "sneakpeek"
          }
        ],
        "urls": [
          {
            "display_url": "youtube.com/watch?v=vuwxSK…",
            "expanded_url": "https://www.youtube.com/watch?v=vuwxSKlZ24c",
            "indices": [
              "97", 
              "120"
            ],
            "url": "https://t.co/ZG253K2Kma"
          }
        ]
      },
      "favorite_count": "0",
      "favorited": false,
      "full_text": "Our newest program, the Video Arts room, will open next week. Check out our teaser trailer here: https://t.co/ZG253K2Kma #sneakpeek",
      "id_str": "908163454422470657",
      "lang": "en",
      "possibly_sensitive": false,
      "retweet_count": "1",
      "retweeted": false,
      "source": "\u003ca href=\"http://www.hootsuite.com\" rel=\"nofollow\"\u003eHootsuite\u003c/a\u003e",
      "truncated": false
    },
    "wof:name": "Twitter message #908163454422470657",
    "wof:placetype": "custom"
  },
  "geometry": {"coordinates":[-122.386166,37.616356],"type":"Point"}
}
