{
  "type": "Feature",
  "properties": {
    "sfomuseum:placetype": "tweet",
    "twitter:tweet": {
      "created": 1334867383,
      "created_at": "Thu Apr 19 20:29:43 +0000 2012",
      "display_text_range": [
        "0", 
        "137"
      ],
      "entities": {
        "hashtags": [
          {
            "indices": [
              "5", 
              "27"
            ],
            "text": "NationalVolunteerWeek"
          }
        ]
      },
      "favorite_count": "0",
      "favorited": false,
      "full_text": "It's #NationalVolunteerWeek! We're grateful to have a wonderful group of 59 volunteers helping us out - THANK YOU for your time \u0026 energy!",
      "id_str": "193073915243925505",
      "lang": "en",
      "retweet_count": "0",
      "retweeted": false,
      "source": "\u003ca href=\"https://about.twitter.com/products/tweetdeck\" rel=\"nofollow\"\u003eTweetDeck\u003c/a\u003e",
      "truncated": false
    },
    "wof:name": "Twitter message #193073915243925505",
    "wof:placetype": "custom"
  },
  "geometry": {"coordinates":[-122.386166,37.616356],"type":"Point"}
}
