{
  "type": "Feature",
  "properties": {
    "sfomuseum:placetype": "tweet",
    "twitter:tweet": {
      "created": 1320103891,
      "created_at": "Mon Oct 31 23:31:31 +0000 2011",
      "display_text_range": [
        "0", 
        "106"
      ],
      "entities": {
        "urls": [
          {
            "display_url": "yfrog.com/hwd0lubj",
            "expanded_url": "http://yfrog.com/hwd0lubj",
            "indices": [
              "86", 
              "106"
            ],
            "url": "http://t.co/DBcghipq"
          }
        ]
      },
      "favorite_count": "0",
      "favorited": false,
      "full_text": "Have a great Halloween! Say hi to the Adam's Family if your flying out of terminal 3. http://t.co/DBcghipq",
      "id_str": "131151341220409344",
      "lang": "en",
      "possibly_sensitive": false,
      "retweet_count": "0",
      "retweeted": false,
      "source": "\u003ca href=\"https://about.twitter.com/products/tweetdeck\" rel=\"nofollow\"\u003eTweetDeck\u003c/a\u003e",
      "truncated": false
    },
    "wof:name": "Twitter message #131151341220409344",
    "wof:placetype": "custom"
  },
  "geometry": {"coordinates":[-122.386166,37.616356],"type":"Point"}
}
