{
  "type": "Feature",
  "properties": {
    "date:cessation_lower":"2018-09-12",
    "date:cessation_upper":"2018-09-12",
    "date:inception_lower":"2018-09-12",
    "date:inception_upper":"2018-09-12",
    "iso:country":"US",
    "sfomuseum:placetype":"tweet",
    "twitter:tweet":{
        "created":1536772868,
        "created_at":"Wed Sep 12 17:21:08 +0000 2018",
        "display_text_range":[
            "0",
            "221"
        ],
        "entities":{
            "user_mentions":[
                {
                    "id_str":"14245868",
                    "indices":[
                        "0",
                        "12"
                    ],
                    "name":"pvmurthy",
                    "screen_name":"gremlinAnon"
                }
            ]
        },
        "favorite_count":"0",
        "favorited":false,
        "full_text":"@gremlinAnon Hi! The second floor of the Aviation Museum and Library contains our library books which are available for research by appointment and a continuation of our photo show from the first floor. Thanks for asking!",
        "id_str":"1039926899697307648",
        "in_reply_to_screen_name":"gremlinAnon",
        "in_reply_to_status_id":"1039922008861995009",
        "in_reply_to_status_id_str":"1039922008861995009",
        "in_reply_to_user_id":"14245868",
        "in_reply_to_user_id_str":"14245868",
        "lang":"en",
        "retweet_count":"0",
        "retweeted":false,
        "source":"<a href=\"http://twitter.com\" rel=\"nofollow\">Twitter Web Client</a>",
        "truncated":false
    },
    "wof:name":"@gremlinAnon Hi! The second floor of the Aviation Museum and Library contains our library books which are available for research by appointment and a continuation of our photo show from the first floor. Thanks for asking!",
    "wof:placetype":"custom"
},
  "geometry": {"coordinates":[-122.386166,37.616356],"type":"Point"}
}