{
  "type": "Feature",
  "properties": {
    "date:cessation_lower": "2023-03-02",
    "date:cessation_upper": "2023-03-02",
    "date:inception_lower": "2023-03-02",
    "date:inception_upper": "2023-03-02",
    "sfomuseum:placetype": "tweet",
    "twitter:hashtags": [
      "InternationalWomensHistoryMonth",
      "VideoArts",
      "VideoArtsSFO",
      "Akoon",
      "ZeinaAref"
    ],
    "twitter:tweet": {
      "created": 1677787524,
      "created_at": "Thu Mar 02 20:05:24 +0000 2023",
      "display_text_range": [
        "0",
        "280"
      ],
      "edit_info": {
        "initial": {
          "editTweetIds": [
            "1631385235362566145"
          ],
          "editableUntil": "2023-03-02T20:35:24.000Z",
          "editsRemaining": "5",
          "isEditEligible": false
        }
      },
      "entities": {
        "hashtags": [
          {
            "indices": [
              "205",
              "215"
            ],
            "text": "VideoArts"
          },
          {
            "indices": [
              "216",
              "229"
            ],
            "text": "VideoArtsSFO"
          },
          {
            "indices": [
              "230",
              "236"
            ],
            "text": "Akoon"
          },
          {
            "indices": [
              "237",
              "247"
            ],
            "text": "ZeinaAref"
          },
          {
            "indices": [
              "248",
              "280"
            ],
            "text": "InternationalWomensHistoryMonth"
          }
        ],
        "urls": [
          {
            "display_url": "bit.ly/VideoArts",
            "expanded_url": "http://bit.ly/VideoArts",
            "indices": [
              "180",
              "203"
            ],
            "url": "https://t.co/s0oA7gcWli"
          }
        ]
      },
      "favorite_count": "1",
      "favorited": false,
      "full_text": "See “Akoon” by Zeina Aref in the Video Arts Gallery, located pre-security in the International Terminal, open daily from 7:00am to 10:00pm. Learn more about this month’s films at: https://t.co/s0oA7gcWli\n\n#VideoArts #VideoArtsSFO #Akoon #ZeinaAref #InternationalWomensHistoryMonth",
      "id_str": "1631385235362566145",
      "in_reply_to_screen_name": "SFOMuseum",
      "in_reply_to_status_id": "1631385233743568896",
      "in_reply_to_status_id_str": "1631385233743568896",
      "in_reply_to_user_id": "116329337",
      "in_reply_to_user_id_str": "116329337",
      "lang": "en",
      "possibly_sensitive": false,
      "retweet_count": "1",
      "retweeted": false,
      "source": "\u003ca href=\"https://mobile.twitter.com\" rel=\"nofollow\"\u003eTwitter Web App\u003c/a\u003e",
      "truncated": false
    },
    "wof:name": "See “Akoon” by Zeina Aref in the Video Arts Gallery, located pre-security in the International Terminal, open daily from 7:00am to 10:00pm. Learn more about this month’s films at: https://t.co/s0oA7gcWli\n\n#VideoArts #VideoArtsSFO #Akoon #ZeinaAref #InternationalWomensHistoryMonth",
    "wof:placetype": "custom",
    "wof:placetype_alt": [
      "tweet"
    ]
  },
  "geometry": {"coordinates":[-122.386166,37.616356],"type":"Point"}
}
