{
  "type": "Feature",
  "properties": {
    "date:cessation_lower":"2012-04-11",
    "date:cessation_upper":"2012-04-11",
    "date:inception_lower":"2012-04-11",
    "date:inception_upper":"2012-04-11",
    "iso:country":"US",
    "sfomuseum:placetype":"tweet",
    "twitter:tweet":{
        "created":1334163330,
        "created_at":"Wed Apr 11 16:55:30 +0000 2012",
        "display_text_range":[
            "0",
            "121"
        ],
        "entities":{
            "urls":[
                {
                    "display_url":"tinyurl.com/7a28rme",
                    "expanded_url":"http://tinyurl.com/7a28rme",
                    "indices":[
                        "80",
                        "100"
                    ],
                    "url":"http://t.co/CS6P7jQV"
                }
            ],
            "user_mentions":[
                {
                    "id_str":"24747746",
                    "indices":[
                        "3",
                        "17"
                    ],
                    "name":"Stephanie Orma",
                    "screen_name":"StephanieOrma"
                },
                {
                    "id_str":"16408759",
                    "indices":[
                        "39",
                        "46"
                    ],
                    "name":"San Francisco International Airport (SFO) \u2708\ufe0f",
                    "screen_name":"flySFO"
                },
                {
                    "id_str":"19294924",
                    "indices":[
                        "105",
                        "121"
                    ],
                    "name":"CA Home + Design",
                    "screen_name":"CAHomeandDesign"
                }
            ]
        },
        "favorite_count":"0",
        "favorited":false,
        "full_text":"RT @StephanieOrma: Sew cool! Check out @flySFO's new history of sewing exhibit: http://t.co/CS6P7jQV via @CAHomeandDesign",
        "id_str":"190120905396068352",
        "lang":"en",
        "possibly_sensitive":false,
        "retweet_count":"0",
        "retweeted":false,
        "source":"<a href=\"http://www.hootsuite.com\" rel=\"nofollow\">Hootsuite</a>",
        "truncated":false
    },
    "wof:name":"RT @StephanieOrma: Sew cool! Check out @flySFO's new history of sewing exhibit: http://t.co/CS6P7jQV via @CAHomeandDesign",
    "wof:placetype":"custom"
},
  "geometry": {"coordinates":[-122.386166,37.616356],"type":"Point"}
}