{
  "type": "Feature",
  "properties": {
    "sfomuseum:placetype": "tweet",
    "twitter:tweet": {
      "created": 1456892407,
      "created_at": "Wed Mar 02 04:20:07 +0000 2016",
      "display_text_range": [
        "0", 
        "137"
      ],
      "entities": {
        "hashtags": [
          {
            "indices": [
              "19", 
              "25"
            ],
            "text": "PanAm"
          }, 
          {
            "indices": [
              "99", 
              "113"
            ],
            "text": "TravelTuesday"
          }
        ],
        "media": [
          {
            "display_url": "pic.twitter.com/OAlslnBtUc",
            "expanded_url": "https://twitter.com/SFOMuseum/status/704883961714098181/photo/1",
            "id_str": "704883961101729792",
            "indices": [
              "114", 
              "137"
            ],
            "media_url": "http://pbs.twimg.com/media/CchAOl1WwAA9n0d.jpg",
            "media_url_https": "https://pbs.twimg.com/media/CchAOl1WwAA9n0d.jpg",
            "sizes": {
              "large": {
                "h": "2048",
                "resize": "fit",
                "w": "1323"
              },
              "medium": {
                "h": "1200",
                "resize": "fit",
                "w": "775"
              },
              "small": {
                "h": "680",
                "resize": "fit",
                "w": "439"
              },
              "thumb": {
                "h": "150",
                "resize": "crop",
                "w": "150"
              }
            },
            "type": "photo",
            "url": "https://t.co/OAlslnBtUc"
          }
        ]
      },
      "extended_entities": {
        "media": [
          {
            "display_url": "pic.twitter.com/OAlslnBtUc",
            "expanded_url": "https://twitter.com/SFOMuseum/status/704883961714098181/photo/1",
            "id_str": "704883961101729792",
            "indices": [
              "114", 
              "137"
            ],
            "media_url": "http://pbs.twimg.com/media/CchAOl1WwAA9n0d.jpg",
            "media_url_https": "https://pbs.twimg.com/media/CchAOl1WwAA9n0d.jpg",
            "sizes": {
              "large": {
                "h": "2048",
                "resize": "fit",
                "w": "1323"
              },
              "medium": {
                "h": "1200",
                "resize": "fit",
                "w": "775"
              },
              "small": {
                "h": "680",
                "resize": "fit",
                "w": "439"
              },
              "thumb": {
                "h": "150",
                "resize": "crop",
                "w": "150"
              }
            },
            "type": "photo",
            "url": "https://t.co/OAlslnBtUc"
          }
        ]
      },
      "favorite_count": "3",
      "favorited": false,
      "full_text": "This classic 1950s #PanAm travel poster features a Boeing 377 flying above Amsterdam, Netherlands. #TravelTuesday https://t.co/OAlslnBtUc",
      "id_str": "704883961714098181",
      "lang": "en",
      "possibly_sensitive": false,
      "retweet_count": "3",
      "retweeted": false,
      "source": "\u003ca href=\"http://www.hootsuite.com\" rel=\"nofollow\"\u003eHootsuite\u003c/a\u003e",
      "truncated": false
    },
    "wof:name": "Twitter message #704883961714098181",
    "wof:placetype": "custom"
  },
  "geometry": {"coordinates":[-122.386166,37.616356],"type":"Point"}
}
