{
  "type": "Feature",
  "properties": {
    "sfomuseum:placetype": "tweet",
    "twitter:tweet": {
      "created": 1328313918,
      "created_at": "Sat Feb 04 00:05:18 +0000 2012",
      "display_text_range": [
        "0", 
        "54"
      ],
      "entities": {
        "user_mentions": [
          {
            "id_str": "86903209",
            "indices": [
              "0", 
              "14"
            ],
            "name": "Penfold Merton",
            "screen_name": "penfoldmerton"
          }
        ]
      },
      "favorite_count": "0",
      "favorited": false,
      "full_text": "@penfoldmerton Thank you for checking out the exhibit!",
      "id_str": "165586694031163392",
      "in_reply_to_screen_name": "penfoldmerton",
      "in_reply_to_status_id": "165585401124364288",
      "in_reply_to_status_id_str": "165585401124364288",
      "in_reply_to_user_id": "86903209",
      "in_reply_to_user_id_str": "86903209",
      "lang": "en",
      "retweet_count": "0",
      "retweeted": false,
      "source": "\u003ca href=\"https://about.twitter.com/products/tweetdeck\" rel=\"nofollow\"\u003eTweetDeck\u003c/a\u003e",
      "truncated": false
    },
    "wof:name": "Twitter message #165586694031163392",
    "wof:placetype": "custom"
  },
  "geometry": {"coordinates":[-122.386166,37.616356],"type":"Point"}
}
