{
  "type": "Feature",
  "properties": {
    "sfomuseum:placetype": "tweet",
    "twitter:tweet": {
      "created": 1498694855,
      "created_at": "Thu Jun 29 00:07:35 +0000 2017",
      "display_text_range": [
        "0", 
        "161"
      ],
      "entities": {
        "hashtags": [
          {
            "indices": [
              "28", 
              "38"
            ],
            "text": "Valentino"
          }, 
          {
            "indices": [
              "81", 
              "85"
            ],
            "text": "TWA"
          }, 
          {
            "indices": [
              "121", 
              "137"
            ],
            "text": "FashionInFlight"
          }
        ],
        "media": [
          {
            "display_url": "pic.twitter.com/fFOskAxhcY",
            "expanded_url": "https://twitter.com/SFOMuseum/status/880216136826138625/photo/1",
            "id_str": "880216133827272704",
            "indices": [
              "138", 
              "161"
            ],
            "media_url": "http://pbs.twimg.com/media/DDcn6P5XoAAzTAx.jpg",
            "media_url_https": "https://pbs.twimg.com/media/DDcn6P5XoAAzTAx.jpg",
            "sizes": {
              "large": {
                "h": "2000",
                "resize": "fit",
                "w": "1333"
              },
              "medium": {
                "h": "1200",
                "resize": "fit",
                "w": "800"
              },
              "small": {
                "h": "680",
                "resize": "fit",
                "w": "453"
              },
              "thumb": {
                "h": "150",
                "resize": "crop",
                "w": "150"
              }
            },
            "type": "photo",
            "url": "https://t.co/fFOskAxhcY"
          }
        ]
      },
      "extended_entities": {
        "media": [
          {
            "display_url": "pic.twitter.com/fFOskAxhcY",
            "expanded_url": "https://twitter.com/SFOMuseum/status/880216136826138625/photo/1",
            "id_str": "880216133827272704",
            "indices": [
              "138", 
              "161"
            ],
            "media_url": "http://pbs.twimg.com/media/DDcn6P5XoAAzTAx.jpg",
            "media_url_https": "https://pbs.twimg.com/media/DDcn6P5XoAAzTAx.jpg",
            "sizes": {
              "large": {
                "h": "2000",
                "resize": "fit",
                "w": "1333"
              },
              "medium": {
                "h": "1200",
                "resize": "fit",
                "w": "800"
              },
              "small": {
                "h": "680",
                "resize": "fit",
                "w": "453"
              },
              "thumb": {
                "h": "150",
                "resize": "crop",
                "w": "150"
              }
            },
            "type": "photo",
            "url": "https://t.co/fFOskAxhcY"
          }
        ]
      },
      "favorite_count": "2",
      "favorited": false,
      "full_text": "Rome-based fashion designer #Valentino Garavani brought his passion for color to #TWA in 1971 with a uniform collection. #FashionInFlight https://t.co/fFOskAxhcY",
      "id_str": "880216136826138625",
      "lang": "en",
      "possibly_sensitive": false,
      "retweet_count": "1",
      "retweeted": false,
      "source": "\u003ca href=\"http://www.hootsuite.com\" rel=\"nofollow\"\u003eHootsuite\u003c/a\u003e",
      "truncated": false
    },
    "wof:name": "Twitter message #880216136826138625",
    "wof:placetype": "custom"
  },
  "geometry": {"coordinates":[-122.386166,37.616356],"type":"Point"}
}
