{
  "type": "Feature",
  "properties": {
    "date:cessation_lower": "2012-08-03",
    "date:cessation_upper": "2012-08-03",
    "date:inception_lower": "2012-08-03",
    "date:inception_upper": "2012-08-03",
    "iso:country": "US",
    "sfomuseum:placetype": "tweet",
    "twitter:tweet": {
      "created": 1344014159,
      "created_at": "Fri Aug 03 17:15:59 +0000 2012",
      "display_text_range": [
        "0",
        "94"
      ],
      "edit_info": {
        "initial": {
          "editTweetIds": [
            "231438276257525760"
          ],
          "editableUntil": "2012-08-03T17:45:59.632Z",
          "editsRemaining": "5",
          "isEditEligible": true
        }
      },
      "entities": {
        "hashtags": [
          {
            "indices": [
              "69",
              "84"
            ],
            "text": "MuseumOlympics"
          },
          {
            "indices": [
              "85",
              "94"
            ],
            "text": "Aviation"
          }
        ],
        "urls": [
          {
            "display_url": "yfrog.com/mn1bhvbj",
            "expanded_url": "http://yfrog.com/mn1bhvbj",
            "indices": [
              "48",
              "68"
            ],
            "url": "http://t.co/g1lfPbK3"
          }
        ]
      },
      "favorite_count": "0",
      "favorited": false,
      "full_text": "Synchronized Fabulousness routine starts...NOW! http://t.co/g1lfPbK3 #MuseumOlympics #Aviation",
      "id_str": "231438276257525760",
      "lang": "en",
      "possibly_sensitive": false,
      "retweet_count": "2",
      "retweeted": false,
      "source": "\u003ca href=\"https://about.twitter.com/products/tweetdeck\" rel=\"nofollow\"\u003eTweetDeck\u003c/a\u003e",
      "truncated": false
    },
    "wof:name": "Synchronized Fabulousness routine starts...NOW! http://t.co/g1lfPbK3 #MuseumOlympics #Aviation",
    "wof:placetype": "custom"
  },
  "geometry": {"coordinates":[-122.386166,37.616356],"type":"Point"}
}
