{
  "type": "Feature",
  "properties": {
    "date:cessation_lower": "2012-01-30",
    "date:cessation_upper": "2012-01-30",
    "date:inception_lower": "2012-01-30",
    "date:inception_upper": "2012-01-30",
    "iso:country": "US",
    "sfomuseum:placetype": "tweet",
    "twitter:tweet": {
      "created": 1327958279,
      "created_at": "Mon Jan 30 21:17:59 +0000 2012",
      "display_text_range": [
        "0",
        "126"
      ],
      "edit_info": {
        "initial": {
          "editTweetIds": [
            "164095032817754112"
          ],
          "editableUntil": "2012-01-30T21:47:59.219Z",
          "editsRemaining": "5",
          "isEditEligible": true
        }
      },
      "entities": {
        "urls": [
          {
            "display_url": "yfrog.com/obmn0yij",
            "expanded_url": "http://yfrog.com/obmn0yij",
            "indices": [
              "106",
              "126"
            ],
            "url": "http://t.co/JY22dmFd"
          }
        ]
      },
      "favorite_count": "0",
      "favorited": false,
      "full_text": "The Lone Ranger galloped onto the scene on this day in 1933, first in a radio show, moving to tv in 1948. http://t.co/JY22dmFd",
      "id_str": "164095032817754112",
      "lang": "en",
      "possibly_sensitive": false,
      "retweet_count": "0",
      "retweeted": false,
      "source": "\u003ca href=\"https://about.twitter.com/products/tweetdeck\" rel=\"nofollow\"\u003eTweetDeck\u003c/a\u003e",
      "truncated": false
    },
    "wof:name": "The Lone Ranger galloped onto the scene on this day in 1933, first in a radio show, moving to tv in 1948. http://t.co/JY22dmFd",
    "wof:placetype": "custom"
  },
  "geometry": {"coordinates":[-122.386166,37.616356],"type":"Point"}
}
